Workbook
Name IQ_CH: 110000
Name IQ_CQ: 5000
Name IQ_CY: 10000
Name IQ_DAILY: 500000
Name IQ_FH: 100000
Name IQ_FQ: 500
Name IQ_FY: 1000
Name IQ_LTM: 2000
Name IQ_MONTH: 15000
Name IQ_NTM: 6000
Name IQ_WEEK: 50000
Name IQ_YTD: 3000

Sheet Main
A1: Applied Digital Corporation | Public company
A2: NASDAQ: apld (MI KEY: 4992232; SPCIQ KEY: 3563673)
A4: General Information | F4: USD MN
A5: Company name | F5: Applied Digital Corp.
A6: Ticker | F6: APLD
A7: Stock exchange | F7: NASDAQ
A8: Fiscal year ending | F8: 45808
A9: Moody's corporate rating | F9: NR
A10: S&P corporate rating | F10: B+
A11: Fitch corporate rating | F11: BB-
A12: Predicted beta | F12: =_xll.ciqfunctions.udf.CIQ(F6, "IQ_CUSTOM_BETA", "11/30/2024", "11/30/2025", "D", "^SPX", , "H") -> 2.24798
A13: Marginal tax rate | F13: 0.21
A15: Selected Market Data | F15: USD MN
A16: Current Price | F16: 27.1
A17: % of 52-week High | F17: =F16/F18 -> 0.67412935
A18: 52-week High Price | F18: 40.2
A19: 52-week Low Price | F19: 3.31
A20: Dividend per Share (MRQ) | F20: 0
A22: Fully Diluted Shares Outstanding | F22: =F38 -> 3.3397066e+08
A23: Equity Value | F23: =F22*F16 -> 9.0506048e+09
A25: Plus: Total Debt | F25: 876020000
A26: Plus: Preferred Stock | F26: =6932000+56796000 -> 63728000
A27: Plus: Noncontrolling Interest | F27: -
A28: Less: Cash and Cash Equivalents | F28: -73911000
A29: Enterprise Value | F29: =SUM(F23:F28) -> 9.9164418e+09
A31: Calculation of Fully Diluted Shares outstanding | F31: USD MN
A32: Basic Shares Outstanding | F32: 255892902
A33: Plus: Shares from In-the-Money Options | F33: =D48 -> 25491329
A34: Less: Shares repurchased | F34: =-E48/F16 -> -8156488.8
A35: Net New Shares from Options | F35: =SUM(F32:F34) -> 2.7322774e+08
A36: Plus Shares from Convertible Securities | F36: =E63 -> 46100000
A37: Plus : Shares from RSU's, PSU's and Restricted stock | F37: =C55 -> 14642914
A38: Total | F38: =SUM(F35:F37) -> 3.3397066e+08
A40: Options /Warrants
A41: Tranche | B41: Number of shares | C41: Exercise Price | D41: In-the-Money Shares | E41: Proceeds
A42: AI Warrant 1 | B42: 1500000 | C42: 10 | D42: =IF($C42 < $F$16, $B42, 0) -> 1500000 | E42: =IF(D42>0, D42*C42, 0) -> 15000000
A43: AI Warrant 2 | B43: 1500000 | C43: 7.5 | D43: =IF($C43 < $F$16, $B43, 0) -> 1500000 | E43: =IF(D43>0, D43*C43, 0) -> 11250000
A44: Macquaire Warrant | B44: 1035197 | C44: 9.66 | D44: =IF($C44 < $F$16, $B44, 0) -> 1035197 | E44: =IF(D44>0, D44*C44, 0) -> 10000003
A45: STB Warrant | B45: 1000000 | C45: 7.83 | D45: =IF($C45 < $F$16, $B45, 0) -> 1000000 | E45: =IF(D45>0, D45*C45, 0) -> 7830000
A46: CoreWeave Warrant | B46: 12062521 | C46: 7.19 | D46: =IF($C46 < $F$16, $B46, 0) -> 12062521 | E46: =IF(D46>0, D46*C46, 0) -> 86729526
A47: Building 4 Warrant | B47: 8393611 | C47: 10.75 | D47: =IF($C47 < $F$16, $B47, 0) -> 8393611 | E47: =IF(D47>0, D47*C47, 0) -> 90231318
A48: Total | B48: =SUM(B42:B47) -> 25491329 | C48: - | D48: =SUM(D42:D47) -> 25491329 | E48: =SUM(E42:E47) -> 2.2104085e+08
A50: RSU's PSU's and Restricted Stock
A51: Units | B51: Number of shares | C51: Dilutive Shares | D51: Comments
A52: RSUs | B52: 7163970 | C52: =B52 -> 7163970 | D52: 1:1 Conversion
A53: PSUs | B53: 7207500 | C53: =B53 -> 7207500 | D53: Assumed probable vesting
A54: Restricted | B54: 271444 | C54: =B54 -> 271444 | D54: Always dilutive
A55: Total | B55: =SUM(B52:B54) -> 14642914 | C55: =B55 -> 14642914
A57: Convertible Notes
A58: Convertible Securities | B58: Units | C58: Conversion Price | D58: Shares If Converted | E58: Dilutive Shares | F58: Comments
A59: Senior Unsecured Notes | B59: - | C59: - | D59: 46100000 | E59: 46100000 | F59: Fully dilutive; 10-Q shows 46.1M if converted
A60: Series G Preferred Stock | B60: - | C60: Variable | D60: - | E60: - | F60: Fully Converted; ignored
A61: Series E Preferred | B61: 301673 | C61: - | D61: - | E61: - | F61: Not Convertible
A62: Series E-1 Preferred | B62: 62260 | C62: - | D62: - | E62: - | F62: Not Convertible
A63: Total | B63: =SUM(B61:B62) -> 363933 | D63: =SUM(D59:D62) -> 46100000 | E63: =SUM(E59:E62) -> 46100000
A65: Balance sheet Data
E66: August 31, 2025 | F66: May 31, 2025
A67: ASSETS
A68: Current assets:
A69: Cash and cash equivalents | E69: 73911000 | F69: 41552000
A70: Restricted cash:
A71: Funds for construction | E71: 2851000 | F71: 41026000
A72: Letters of credit | E72: 37342000 | F72: 31342000
A73: Accounts receivable | E73: 29134000 | F73: 3043000
A74: Prepaid expenses and other current assets | E74: 188491000 | F74: 9430000
A75: Current assets held for sale | E75: 310006000 | F75: 304200000
A76: Total current assets | E76: 641735000 | F76: 430593000
A77: Property and equipment, net | E77: 1461775000 | F77: 1206341000
A78: Operating lease right of use assets, net | E78: 810000 | F78: 960000
A79: Finance lease right of use assets, net | E79: 16893000 | F79: 17820000
A80: Other assets | E80: 277782000 | F80: 214376000
A81: TOTAL ASSETS | E81: 2398995000 | F81: 1870090000
A83: LIABILITIES, TEMPORARY EQUITY AND STOCKHOLDERS' EQUITY
A84: Current liabilities:
A85: Accounts payable | E85: 172823000 | F85: 247528000
A86: Accrued liabilities | E86: 182948000 | F86: 29549000
A87: Current portion of operating lease liability | E87: 688000 | F87: 692000
A88: Current portion of finance lease liability | E88: 11951000 | F88: 13633000
A89: Current portion of debt | E89: 382056000 | F89: 10331000
A91: Customer deposits | E91: 16752000 | F91: 16125000
A93: Deferred revenue | E93: 626000 | F93: 0
A95: Due to customer | E95: 3054000 | F95: 4807000
A96: Current liabilities held-for-sale | E96: 188215000 | F96: 216047000
A97: Other current liabilities | E97: 26380000 | F97: 19432000
A98: Total current liabilities | E98: 985493000 | F98: 558144000
A99: Long-term portion of operating lease liability | E99: 220000 | F99: 381000
... A103: Total liabilities | E103: 1291007000 | F103: 1236365000
A104: Commitments and contingencies (Note 14)
A105: Temporary equity
A106: Series E preferred stock, $0.001 par value, 2,000,000 shares authorized, 301,673 shares issued and outstanding at August 31, 2025, and 301,673 shares issued and outstanding at May 31, 2025 | E106: 6932000 | F106: 6932000
A107: Series E-1 preferred stock, $0.001 par value, 62,500 shares authorized, 62,500 shares issued and 62,260 shares outstanding at August 31, 2025, and 62,500 shares issued and 62,485 shares outstanding at May 31, 2025 | E107: 56796000 | F107: 57011000
A108: Series G preferred stock, $0.001 par value, 156,000 shares authorized, no shares issued and outstanding at August 31, 2025, and 78,000 shares issued and outstanding at May 31, 2025 | E108: 0 | F108: 72094000
A109: Stockholders' equity:
A110: Common stock, $0.001 par value, 400,000,000 shares authorized, 278,584,101 shares issued and 269,292,902 shares outstanding at August 31, 2025, and 234,200,868 shares issued and 224,909,669 shares outstanding at May 31, 2025 | E110: 274000 | F110: 230000
A111: Treasury stock, 9,291,199 shares at August 31, 2025 and 9,291,199 shares at May 31, 2025, at cost | E111: -31400000 | F111: -31400000
A112: Additional paid in capital | E112: 1573367000 | F112: 1009913000
A113: Accumulated deficit | E113: -497981000 | F113: -481055000
A114: Total stockholders’ equity attributable to Applied Digital Corporation | E114: 1044260000 | F114: 497688000
A116: TOTAL LIABILITIES, TEMPORARY EQUITY AND STOCKHOLDERS' EQUITY | E116: 2398995000 | F116: 1870090000
A118: 1000
...

Sheet Investment ratios
B2: LTM Return on Investment Ratios | I2: Trading Multiples
B3: Return on Invested Capital | F3: =_xll.ciqfunctions.udf.CIQ(Main!F6, "IQ_RETURN_INVESTED_CAPITAL", "LTM12026")% -> -0.197087 | M3: LTM | N3: NFY | O3: NFY+1 | P3: NFY+2 | Q3: NFY+3
B4: Return on Equity | F4: =_xll.ciqfunctions.udf.CIQ(Main!F6, "IQ_RETURN_EQUITY_FS", "LTM12026")% -> -0.287557 | M4: 2025 | N4: 2026E | O4: 2027E | P4: 2028E | Q4: 2029E
B5: Return on Assets | F5: =Main!G135/AVERAGE(Main!F81,Main!E81) -> -5.2777586e-05 | I5: EV/Sales | M5: =9916.4/173.56 -> 57.135285 | N5: =_xll.ciqfunctions.udf.CIQ(Main!F6, "IQ_TEV_TOTAL_REV_FWD", "FY2026") -> 31.1243 | O5: =_xll.ciqfunctions.udf.CIQ(Main!F6, "IQ_TEV_TOTAL_REV_FWD", "FY2027") -> 20.14424 | P5: =_xll.ciqfunctions.udf.CIQ(Main!F6, "IQ_TEV_TOTAL_REV_FWD", "FY2028") -> 10.24775 | Q5: -419949
B6: Implied Annual Dividend Per Share | F6: ='EBITDA Adjustment'!F28+'EBITDA Adjustment'!F29 -> 23.109377 | I6: %change | M6: - | N6: =N5/M5-1 -> -0.45525256 | O6: =O5/N5-1 -> -0.35278095 | P6: =P5/O5-1 -> -0.49128138 | Q6: =P6*P5 -> -5.0345287
I7: EV/EBITDA | M7: 92.55 | N7: 156.18 | O7: 32.35 | P7: 14.8 | Q7: =-MEDIAN(N8:P8)*P7 -> 8.0290572
B8: LTM Credit Statistics | I8: %change | M8: - | N8: =N7/M7-1 -> 0.68752026 | O8: =O7/N7-1 -> -0.7928672 | P8: =P7/O7-1 -> -0.54250386 | Q8: =Q7/P7-1 -> -0.45749614
B9: Debt/Total Capitalisation | F9: =(10.3+677.8)/(10.3+677.8+1870) -> 0.2689887 | I9: EV/EBIT | M9: NM | N9: NM | O9: 56.64 | P9: 19.43 | Q9: =-P10*P9 -> 12.764659
B10: Total Debt/EBITDA | F10: =(677.8+10.3)/-171.5 -> -4.0122449 | I10: % change | M10: - | N10: - | O10: - | P10: =P9/O9-1 -> -0.65695621 | Q10: =Q9/P9-1 -> -0.34304379
B11: Net Debt/EBITDA | F11: =(677.8+10.3-148.4)/-171.5 -> -3.1469388 | I11: Market Cap/ Revenue | M11: 26.74 | N11: 29.55 | O11: 15.89 | P11: 9.06 | Q11: =-P12*P11 -> 3.8942605
B12: Total Debt/Adjusted EBITDA | F12: =(677.8+10.3)/13.9 -> 49.503597 | I12: % change | M12: - | N12: =N11/M11-1 -> 0.10508601 | O12: =O11/N11-1 -> -0.46226734 | P12: =P11/O11-1 -> -0.42983008 | Q12: =Q11/P11-1 -> -0.57016992
B13: Net Debt/Adjusted EBITDA | F13: =(677.8+10.3-148.4)/13.9 -> 38.827338 | I13: PE | M13: NM | N13: NM | O13: NM | P13: 35.98 | Q13: 35.98
B14: EBITDA/Interest Expense | F14: =-171.5/(17.2-0.1) -> -10.02924 | I14: % change | M14: - | N14: - | O14: - | P14: - | Q14: -
B15: (EBITDA-capex)/Interest Expense | F15: =(-171.5-876.2)/(17.2-0.1) -> -61.269006
B16: EBIT/Interest Expense | F16: =(-129)/(17.2-0.1) -> -7.5438596

Sheet EBITDA Adjustment
A3: EBITDA ADJUSTMENTS
D4: Fiscal Year Ending 31 May | G4: Q1 | H4: Q1 | I4: LTM
D5: 2023A | E5: 2024A | F5: 2025A | G5: 31/08/2025 | H5: 31/08/2026 | I5: 31/08/2025
A6: Net Income (Loss) | D6: -43528 | E6: -79979 | F6: -160950 | G6: 15868 | H6: 27823 | I6: =F6+G6-H6 -> -172905
A7: Add Interest exp. | D7: =_xll.ciqfunctions.udf.CIQ(Main!F6, "IQ_INTEREST_EXP", "FY2023") -> -2.006 | E7: =_xll.ciqfunctions.udf.CIQ(Main!F6, "IQ_INTEREST_EXP", "FY2024") -> -17.708 | F7: =_xll.ciqfunctions.udf.CIQ(Main!F6, "IQ_INTEREST_EXP", "FY2025") -> -14.739 | G7: =_xll.ciqfunctions.udf.CIQ(Main!F6, "IQ_INTEREST_EXP", "FQ12025") -> -3.003 | H7: =_xll.ciqfunctions.udf.CIQ(Main!F6, "IQ_INTEREST_EXP", "FQ12026") -> -5.522 | I7: =_xll.ciqfunctions.udf.CIQ(Main!F6, "IQ_INTEREST_EXP", "LTM12026") -> -17.258
A8: Add Income Tax Expense | D8: =_xll.ciqfunctions.udf.CIQ(Main!F6, "IQ_INC_TAX", "FY2023") -> -0.523 | E8: =_xll.ciqfunctions.udf.CIQ(Main!F6, "IQ_INC_TAX", "FY2024") -> 0.096 | F8: =_xll.ciqfunctions.udf.CIQ(Main!F6, "IQ_INC_TAX", "FY2025") -> 0.102 | G8: =_xll.ciqfunctions.udf.CIQ(Main!F6, "IQ_INC_TAX", "FQ12025") -> 0 | H8: =_xll.ciqfunctions.udf.CIQ(Main!F6, "IQ_INC_TAX", "FQ12026") -> 0.008 | I8: =_xll.ciqfunctions.udf.CIQ(Main!F6, "IQ_INC_TAX", "LTM12026") -> 0.11
A9: Add D&A | D9: =_xll.ciqfunctions.udf.CIQ(Main!F6, "IQ_DA_CF", "FY2023") -> 7.614 | E9: =_xll.ciqfunctions.udf.CIQ(Main!F6, "IQ_DA_CF", "FY2024") -> 79.36 | F9: =_xll.ciqfunctions.udf.CIQ(Main!F6, "IQ_DA_CF", "FY2025") -> 97.945 | G9: =_xll.ciqfunctions.udf.CIQ(Main!F6, "IQ_DA_CF", "FQ12025") -> 34.271 | H9: =_xll.ciqfunctions.udf.CIQ(Main!F6, "IQ_DA_CF", "FQ12026") -> 4.152 | I9: =_xll.ciqfunctions.udf.CIQ(Main!F6, "IQ_DA_CF", "LTM12026") -> 67.826
A10: EBITDA (GAAP) | D10: =SUM(D6:D9) -> -43522.915 | E10: =SUM(E6:E9) -> -79917.252 | F10: =SUM(F6:F9) -> -160866.69 | G10: =SUM(G6:G9) -> 15899.268 | H10: =SUM(H6:H9) -> 27821.638 | I10: =SUM(I6:I9) -> -172854.32
A11: Add Stock Based Comp | D11: =_xll.ciqfunctions.udf.CIQ(Main!F6, "IQ_STOCK_BASED_TOTAL", "FY2023") -> 32.072 | E11: =_xll.ciqfunctions.udf.CIQ(Main!F6, "IQ_STOCK_BASED_TOTAL", "FY2024") -> 17.362 | F11: =_xll.ciqfunctions.udf.CIQ(Main!F6, "IQ_STOCK_BASED_TOTAL", "FY2025") -> 22.704 | G11: =_xll.ciqfunctions.udf.CIQ(Main!F6, "IQ_STOCK_BASED_TOTAL", "FQ12025") -> -2.919 | H11: =_xll.ciqfunctions.udf.CIQ(Main!F6, "IQ_STOCK_BASED_TOTAL", "FQ12026") -> 15.465 | I11: =_xll.ciqfunctions.udf.CIQ(Main!F6, "IQ_STOCK_BASED_TOTAL", "LTM12026") -> 41.088
A12: Add Non recurring repairs | D12: - | E12: 1.224 | F12: 1.73 | G12: 0.32 | H12: 1.73 | I12: =F12+H106-G12 -> 1.41
A13: Add Acquisition /disposition/integration exp | D13: 2164 | E13: 5545 | F13: 17269 | G13: 2876 | H13: 1196 | I13: =F13-G13+H13 -> 15589
A14: Litigation exp | D14: - | E14: 1.589 | F14: 1.389 | G14: 407 | H14: 190 | I14: =F14+H14-G14 -> -215.611
A15: Loss on abandonment of assets | D15: - | E15: - | F15: 1138 | G15: 628 | H15: 1751 | I15: =F15-G15+H15 -> 2261
A16: (Gain) loss on classification held for sale | D16: - | E16: 15417 | F16: -24616 | G16: -24808 | H16: - | I16: =F16+G16 -> -49424
A17: Loss on change in Fair value of debt | D17: - | E17: 7401 | F17: 85439 | G17: 6422 | H17: - | I17: =F17-1 -> 85438
A18: Preferred dividends | D18: - | F18: 2615 | G18: - | H18: 44 | I18: 431
A19: Other non-recurring expenses | D19: 1777 | F19: 627 | H19: 74 | I19: 490
A21: Reported EBITDA | D21: =SUM(D10:D19) -> -39549.843 | E21: -34698 | F21: -128820 | G21: =SUM(G10:G17) -> 1421.669 | H21: =SUM(H10:H19) -> 31093.833 | I21: =SUM(E21:H21) -> -131002.5
A24: Share adjustements
A26: Stock Class | D26: LTM Dividend Paid | E26: Shares Outstanding | F26: LTM Dividend Per Share
A27: Common Stock | D27: 0 | E27: 279685875
A28: Series E Pref | D28: 214000 | E28: 301673 | F28: =D28/E28 -> 0.70937737
A29: Series E-1 Pref | D29: 1400000 | E29: 62500 | F29: =D29/E29 -> 22.4

Sheet _CIQHiddenCacheSheet
A1: 50 | B1: BAABTAVMT0NBTAFI/////wFQ3gAAACRDSVEuQVBMRC5JUV9URVZfVE9UQUxfUkVWX0ZXRC5GWTIwMjgBAAAAmWA2AAIAAAAQMTAuMjQ3NzQ3NDYyOTQ0MgENAAAABQAAAAE5AQAAAAcyNjQyNTE1AgAAAAoxMDA1NDI1NjY5AwAAAAYxMDAzMDcEAAAAATIGAAAAATAHAAAAAzE2MAgAAAABMAkAAAABMQoAAAABMAsAAAALMTQ2Mjg4MTU4NDMMAAAAATENAAAACDIvMy8yMDI2N9/5V2ti3gjJv0dYa2LeCCRDSVEuQVBMRC5JUV9URVZfVE9UQUxfUkVWX0ZXRC5GWTIwMjYBAAAAmWA2AAIAAAAQMzEuMTI0Mjk5NTY5NzMyNAENAAAABQAAAAE5AQAAAAcyNjQyNTE1AgAAAAoxMDA1NDA1MzIzAwAAAAYxMDAzMDcEAAAAATIGAAAAATAHAAAAAzE2MAgAAAABMAkAAAABMQoAAAABMAsAAAALMTQ2Mzg4NjM5OTQMAAAAATENAAAACDIvMy8yMDI2N9/5V2ti3gjJv0dYa2LeCCRDSVEuQVBMRC5JUV9URVZfVE9UQUxfUkVWX0ZXRC5GWTIwMjcBAAAAmWA2AAIAAAAPMjAuMTQ0MjQ0OTc1MzkyAQ0AAAAFAAAAATkBAAAABzI2NDI1MTUCAAAACjEwMDU0MjU2NjgDAAAABjEwMDMwNwQAAAABMgYAAAABMAcAAAADMTYwCAAAAAEwCQAAAAExCgAAAAEwCwAAAAsxNDYzMzI2MjYwNwwAAAABMQ0AAAAIMi8zLzIwMjY33/lXa2LeCI6SUVhrYt4IE0NJUS5WTk8uSVFfQkVUQV8yWVIBAAAASMUEAAIAAAAQMS4yNjM3NDkwNzE4NzYx | C1: NAA33/lXa2LeCMm/R1hrYt4IE0NJUS5ETFIuSVFfQkVUQV8yWVIBAAAARHyoAAIAAAARMC43NjIwMDI3Mzg2NTMzNzMAN9/5V2ti3gjJv0dYa2LeCBRDSVEuV1VMRi5JUV9CRVRBXzJZUgEAAAASRKhjAgAAABAzLjIwODE5ODcwMDc0NzE3ADff+VdrYt4IuvZJWGti3ggUQ0lRLk1BUkEuSVFfQkVUQV8yWVIBAAAA2MxwCQIAAAAQMi4zOTQxMDgzMjk5NTgxMQA33/lXa2LeCLr2SVhrYt4IFENJUS5SSU9ULklRX0JFVEFfMllSAQAAAEZkFwACAAAAEDIuNjA3ODM0MTUzNjcxNDYAN9/5V2ti3gjxgUtYa2LeCBNDSVEuSFVULklRX0JFVEFfMllSAQAAAILoOmQCAAAADjIuNjQ0Njk1NjQ1ODA0ADff+VdrYt4IX3pMWGti3ggUQ0lRLkhJVkUuSVFfQkVUQV8yWVIBAAAA2XQwAAIAAAAQMi45MjI0MzY4MTk0Njk0OAA33/lXa2LeCMm/R1hrYt4IN0NJUS5BUExELklRX0NVU1RPTV9CRVRBLjExLzMwLzIwMjQuMTEvMzAvMjAyNS5ELl5TUFguLkgBAAAAmWA2AAIAAAAQMi4yNDc5NzY4ODQyNDk5NgA33/lXa2LeCF96TFhrYt4IFENJUS5DUldWLklRX0JFVEFfMllSAQAAAMypHiQDAAAAAAA33/lXa2LeCE4OT1hrYt4IFENJUS5DTFNLLklRX0JFVEFfMllSAQAAAA7iCQMCAAAAEDIuNDA1MzYwMDA2ODE4ODQAN9/5V2ti3ghODk9Ya2LeCBRDSVEuQ09SWi5JUV9CRVRBXzJZUgEAAAA7lFIiAgAAABAyLjk0MTQ4NTQx | D1: MDE2NDM4ADff+VdrYt4ITg5PWGti3ggUQ0lRLkJJVEYuSVFfQkVUQV8yWVIBAAAAFd2VIAIAAAAQMi44NzM3Njc0NTI1MTc0NQA33/lXa2LeCN6XUFhrYt4IFENJUS5CVEJULklRX0JFVEFfMllSAQAAAFfCQiACAAAAEDIuMzQ5MDkzNzM3MTg3NDcAN9/5V2ti3giOklFYa2LeCBRDSVEuRVFJWC5JUV9CRVRBXzJZUgEAAAAqbgAAAgAAABAwLjY1NjM3NTI0ODYwODU3ADff+VdrYt4ITnFHWGti3ggUQ0lRLklSRU4uSVFfQkVUQV8yWVIBAAAAF5gYKgIAAAAQMi44Mzg0ODYzOTQyNjM3NgA33/lXa2LeCMYMTlhrYt4IFENJUS5BUExELklRX0JFVEFfMllSAQAAAJlgNgACAAAAEDMuMTI0ODA0NTAwMjMwMjgAN9/5V2ti3giOklFYa2LeCBxDSVEuRVFJWC5JUV9UT1RBTF9SRVYuRlkyMDI0AQAAACpuAAACAAAABDg3MzcBCAAAAAUAAAABMQEAAAALLTE5NjAxMzk0MDYDAAAAAzE2MAIAAAACMjgEAAAAATAHAAAACDIvMi8yMDI2CAAAAAoxMi8zMS8yMDI0CQAAAAEwN9/5V2ti3gjJv0dYa2LeCBdDSVEuRVFJWC5JUV9OSS5MVE0zMjAyNQEAAAAqbgAAAgAAAAQxMDcxAQgAAAAFAAAAATEBAAAACy0xOTE5ODE0OTY1AwAAAAMxNjACAAAAAjE1BAAAAAEwBwAAAAgyLzIvMjAyNggAAAAJOS8zMC8yMDI1CQAAAAEwN9/5V2ti3gjJv0dYa2LeCCFDSVEuQ0xTSy5JUV9CQVNJQ19FUFNfSU5DTC5GWTIwMjQBAAAADuIJ | E1: AwIAAAAJLTAuNjg3OTk0AQgAAAAFAAAAATEBAAAACy0xOTE0MzUxMjc1AwAAAAMxNjACAAAAATkEAAAAATAHAAAACDIvMi8yMDI2CAAAAAk5LzMwLzIwMjQJAAAAATA33/lXa2LeCMm/R1hrYt4IIUNJUS5JUkVOLklRX0JBU0lDX0VQU19JTkNMLkZZMjAyNAEAAAAXmBgqAgAAAAktMC4yOTAyNDIBCAAAAAUAAAABMQEAAAALLTE5MjcyMTQ0NjEDAAAAAzE2MAIAAAABOQQAAAABMAcAAAAIMi8yLzIwMjYIAAAACTYvMzAvMjAyNAkAAAABMDff+VdrYt4Iyb9HWGti3ggeQ0lRLldVTEYuSVFfVE9UQUxfUkVWLkxUTTMyMDI1AQAAABJEqGMCAAAABzE2Ny42MDQBCAAAAAUAAAABMQEAAAALLTE5MTc1MzIzODIDAAAAAzE2MAIAAAACMjgEAAAAATAHAAAACDIvMi8yMDI2CAAAAAk5LzMwLzIwMjUJAAAAATA33/lXa2LeCLr2SVhrYt4IFUNJUS5IVVQuSVFfUkVWLkZZMjAyMwEAAACC6DpkAgAAAAY2OS45NTgBCAAAAAUAAAABMQEAAAALLTE5NTczNTIxMzMDAAAAAzE2MAIAAAADMTEyBAAAAAEwBwAAAAgyLzIvMjAyNggAAAAKMTIvMzEvMjAyMwkAAAABMDff+VdrYt4IuvZJWGti3ggVQ0lRLkhJVkUuSVFfTkkuRlkyMDI0AQAAANl0MAACAAAABDI2LjUBCAAAAAUAAAABMQEAAAALLTE5MzcyMjQ4NTgDAAAAAzE2MAIAAAACMTUEAAAAATAHAAAACDIvMi8yMDI2CAAAAAkzLzMxLzIwMjQJAAAAATA33/lXa2LeCLr2 | F1: SVhrYt4IGUNJUS5ISVZFLklRX0VCSVREQS5GWTIwMjQBAAAA2XQwAAIAAAAGOTYuNzIzAQgAAAAFAAAAATEBAAAACy0xOTM3MjI0ODU4AwAAAAMxNjACAAAABDQwNTEEAAAAATAHAAAACDIvMi8yMDI2CAAAAAkzLzMxLzIwMjQJAAAAATA33/lXa2LeCLr2SVhrYt4IFUNJUS5CSVRGLklRX05JLkZZMjAyNAEAAAAV3ZUgAgAAAActNTQuMDYzAQgAAAAFAAAAATEBAAAACy0xOTU0MTc2OTU1AwAAAAMxNjACAAAAAjE1BAAAAAEwBwAAAAgyLzIvMjAyNggAAAAKMTIvMzEvMjAyNAkAAAABMDff+VdrYt4IuvZJWGti3ggZQ0lRLkJJVEYuSVFfRUJJVERBLkZZMjAyNAEAAAAV3ZUgAgAAAAYzNC4yMzIBCAAAAAUAAAABMQEAAAALLTE5NTQxNzY5NTUDAAAAAzE2MAIAAAAENDA1MQQAAAABMAcAAAAIMi8yLzIwMjYIAAAACjEyLzMxLzIwMjQJAAAAATA33/lXa2LeCLr2SVhrYt4IF0NJUS5CVEJULklRX05JLkxUTTMyMDI1AQAAAFfCQiACAAAACjEzNy4wMTg4MDkBCAAAAAUAAAABMQEAAAALLTE5MTY2Njk2MjkDAAAAAzE2MAIAAAACMTUEAAAAATAHAAAACDIvMi8yMDI2CAAAAAk5LzMwLzIwMjUJAAAAATA33/lXa2LeCLr2SVhrYt4IGUNJUS5DT1JaLklRX0VCSVQuTFRNMzIwMjUBAAAAO5RSIgIAAAAILTE1Ni4wODQBCAAAAAUAAAABMQEAAAALLTE5MjA2OTk3NjIDAAAAAzE2MAIAAAADNDAwBAAAAAEwBwAAAAgy | G1: LzIvMjAyNggAAAAJOS8zMC8yMDI1CQAAAAEwN9/5V2ti3gi69klYa2LeCBdDSVEuQ09SWi5JUV9HUC5MVE0zMjAyNQEAAAA7lFIiAgAAAAYzNC4xMzUBCAAAAAUAAAABMQEAAAALLTE5MjA2OTk3NjIDAAAAAzE2MAIAAAACMTAEAAAAATAHAAAACDIvMi8yMDI2CAAAAAk5LzMwLzIwMjUJAAAAATA33/lXa2LeCLr2SVhrYt4IJENJUS5BUExELklRX1NUT0NLX0JBU0VEX1RPVEFMLkZZMjAyMwEAAACZYDYAAgAAAAYzMi4wNzIBCAAAAAUAAAABMQEAAAALLTE5MzQyNDM2NzMDAAAAAzE2MAIAAAAFMjQwMzQEAAAAATAHAAAACDIvMi8yMDI2CAAAAAk1LzMxLzIwMjMJAAAAATA33/lXa2LeCLr2SVhrYt4IG0NJUS5BUExELklRX0lOQ19UQVguRlExMjAyNgEAAACZYDYAAgAAAAUwLjAwOAEIAAAABQAAAAExAQAAAAstMTkyMjAwMjM4MgMAAAADMTYwAgAAAAI3NQQAAAABMAcAAAAIMi8yLzIwMjYIAAAACTgvMzEvMjAyNQkAAAABMDff+VdrYt4IjpJRWGti3ggfQ0lRLkFQTEQuSVFfSU5URVJFU1RfRVhQLkZZMjAyNQEAAACZYDYAAgAAAActMTQuNzM5AQgAAAAFAAAAATEBAAAACy0xOTM0MjQzNjY3AwAAAAMxNjACAAAAAjgyBAAAAAEwBwAAAAgyLzIvMjAyNggAAAAJNS8zMS8yMDI1CQAAAAEwN9/5V2ti3gi69klYa2LeCChDSVEuQVBMRC5JUV9DSEFOR0VfREVGX1RBWF9UT1RBTC5GUTEyMDI1AQAAAJlgNgAD | H1: AAAAAAA33/lXa2LeCLr2SVhrYt4IJENJUS5BUExELklRX05FVF9JTlRFUkVTVF9FWFAuRlExMjAyNQEAAACZYDYAAgAAAAYtMy4wMDMBCAAAAAUAAAABMQEAAAALLTE5MjIwMDIzOTEDAAAAAzE2MAIAAAADMzY4BAAAAAEwBwAAAAgyLzIvMjAyNggAAAAJOC8zMS8yMDI0CQAAAAEwN9/5V2ti3gi69klYa2LeCCNDSVEuQVBMRC5JUV9ORVRfSU5URVJFU1RfRVhQLkZZMjAyNAEAAACZYDYAAgAAAActMTcuNzA4AQgAAAAFAAAAATEBAAAACy0xOTM0MjQzNjM0AwAAAAMxNjACAAAAAzM2OAQAAAABMAcAAAAIMi8yLzIwMjYIAAAACTUvMzEvMjAyNAkAAAABMDff+VdrYt4IuvZJWGti3ggcQ0lRLkFQTEQuSVFfU0dBX1NVUFBMLkZZMjAyNAEAAACZYDYAAgAAAAU0NS4wMgEIAAAABQAAAAExAQAAAAstMTkzNDI0MzYzNAMAAAADMTYwAgAAAAMxMDIEAAAAATAHAAAACDIvMi8yMDI2CAAAAAk1LzMxLzIwMjQJAAAAATA33/lXa2LeCLr2SVhrYt4IGUNJUS5BUExELklRX0NPR1MuTFRNMTIwMjYBAAAAmWA2AAIAAAAHMTM0LjMxNAEIAAAABQAAAAExAQAAAAstMTkyMjAwMTYzNgMAAAADMTYwAgAAAAIzNAQAAAABMAcAAAAIMi8yLzIwMjYIAAAACTgvMzEvMjAyNQkAAAABMDff+VdrYt4IuvZJWGti3ggbQ0lRLlZOTy5JUV9UT1RBTF9SRVYuRlkyMDI0AQAAAEjFBAACAAAABzE5MDAuMTUBCAAAAAUAAAABMQEAAAAL | I1: LTE5NjA0NTU1MDUDAAAAAzE2MAIAAAACMjgEAAAAATAHAAAACDIvMi8yMDI2CAAAAAoxMi8zMS8yMDI0CQAAAAEwN9/5V2ti3gjel1BYa2LeCBhDSVEuRExSLklRX0VCSVREQS5GWTIwMjQBAAAARHyoAAIAAAAIMjQxMy44MDkBCAAAAAUAAAABMQEAAAALLTE5NTgzNTE3MDkDAAAAAzE2MAIAAAAENDA1MQQAAAABMAcAAAAIMi8yLzIwMjYIAAAACjEyLzMxLzIwMjQJAAAAATA33/lXa2LeCPGBS1hrYt4IG0NJUS5ETFIuSVFfVE9UQUxfUkVWLkZZMjAyNAEAAABEfKgAAgAAAAc1NDM0LjgzAQgAAAAFAAAAATEBAAAACy0xOTU4MzUxNzA5AwAAAAMxNjACAAAAAjI4BAAAAAEwBwAAAAgyLzIvMjAyNggAAAAKMTIvMzEvMjAyNAkAAAABMDff+VdrYt4I8YFLWGti3ggeQ0lRLkNSV1YuSVFfVE9UQUxfUkVWLkxUTTMyMDI1AQAAAMypHiQCAAAACDQzMDYuNTI2AQgAAAAFAAAAATEBAAAACy0xOTE2NzQ1NTYyAwAAAAMxNjACAAAAAjI4BAAAAAEwBwAAAAgyLzIvMjAyNggAAAAJOS8zMC8yMDI1CQAAAAEwN9/5V2ti3gjxgUtYa2LeCB5DSVEuQ0xTSy5JUV9UT1RBTF9SRVYuTFRNMzIwMjUBAAAADuIJAwIAAAAHNjMxLjkzNwEIAAAABQAAAAExAQAAAAstMTkzMjY5MjczMQMAAAADMTYwAgAAAAIyOAQAAAABMAcAAAAIMi8yLzIwMjYIAAAACTYvMzAvMjAyNQkAAAABMDff+VdrYt4I8YFLWGti3ggbQ0lRLklSRU4u | J1: SVFfRUJJVERBLkxUTTMyMDI1AQAAABeYGCoCAAAABzEzNy4xNTEBCAAAAAUAAAABMQEAAAALLTE5MTc2NTg0MzcDAAAAAzE2MAIAAAAENDA1MQQAAAABMAcAAAAIMi8yLzIwMjYIAAAACTMvMzEvMjAyNQkAAAABMDff+VdrYt4I8YFLWGti3ggeQ0lRLklSRU4uSVFfVE9UQUxfUkVWLkxUTTMyMDI1AQAAABeYGCoCAAAABzM3NC42MjkBCAAAAAUAAAABMQEAAAALLTE5MTc2NTg0MzcDAAAAAzE2MAIAAAACMjgEAAAAATAHAAAACDIvMi8yMDI2CAAAAAkzLzMxLzIwMjUJAAAAATA33/lXa2LeCPGBS1hrYt4IF0NJUS5XVUxGLklRX0dQLkxUTTMyMDI1AQAAABJEqGMCAAAABjg0LjIxMgEIAAAABQAAAAExAQAAAAstMTkxNzUzMjM4MgMAAAADMTYwAgAAAAIxMAQAAAABMAcAAAAIMi8yLzIwMjYIAAAACTkvMzAvMjAyNQkAAAABMDff+VdrYt4I8YFLWGti3ggeQ0lRLlJJT1QuSVFfVE9UQUxfUkVWLkxUTTMyMDI1AQAAAEZkFwACAAAABzYzNy4xNjIBCAAAAAUAAAABMQEAAAALLTE5MTk0MzQxNTYDAAAAAzE2MAIAAAACMjgEAAAAATAHAAAACDIvMi8yMDI2CAAAAAk5LzMwLzIwMjUJAAAAATA33/lXa2LeCPGBS1hrYt4IF0NJUS5NQVJBLklRX0dQLkxUTTMyMDI1AQAAANjMcAkCAAAABjQxMi40MwEIAAAABQAAAAExAQAAAAstMTkxODQ2NzI5NwMAAAADMTYwAgAAAAIxMAQAAAABMAcAAAAIMi8yLzIwMjYIAAAA | K1: CTkvMzAvMjAyNQkAAAABMDff+VdrYt4I8YFLWGti3ggcQ0lRLkhJVkUuSVFfVE9UQUxfUkVWLkZZMjAyMwEAAADZdDAAAgAAAAcxMDYuMzE4AQgAAAAFAAAAATEBAAAACy0xOTg4OTYxOTg3AwAAAAMxNjACAAAAAjI4BAAAAAEwBwAAAAgyLzIvMjAyNggAAAAJMy8zMS8yMDIzCQAAAAEwN9/5V2ti3ghfekxYa2LeCBdDSVEuSElWRS5JUV9FQklULkZZMjAyNAEAAADZdDAAAgAAAAYzNS4zMDUBCAAAAAUAAAABMQEAAAALLTE5MzcyMjQ4NTgDAAAAAzE2MAIAAAADNDAwBAAAAAEwBwAAAAgyLzIvMjAyNggAAAAJMy8zMS8yMDI0CQAAAAEwN9/5V2ti3ghfekxYa2LeCBxDSVEuQklURi5JUV9UT1RBTF9SRVYuRlkyMDIzAQAAABXdlSACAAAABzE0Ni4zNjYBCAAAAAUAAAABMQEAAAALLTE5NTQxNzY5NTcDAAAAAzE2MAIAAAACMjgEAAAAATAHAAAACDIvMi8yMDI2CAAAAAoxMi8zMS8yMDIzCQAAAAEwN9/5V2ti3ghfekxYa2LeCBtDSVEuQlRCVC5JUV9FQklUREEuTFRNMzIwMjQBAAAAV8JCIAIAAAAJMjMuODgwMzMzAQgAAAAFAAAAATEBAAAACy0xOTE2NjY5NjcxAwAAAAMxNjACAAAABDQwNTEEAAAAATAHAAAACDIvMi8yMDI2CAAAAAk5LzMwLzIwMjQJAAAAATA33/lXa2LeCF96TFhrYt4IHkNJUS5CVEJULklRX1RPVEFMX1JFVi5MVE0zMjAyNAEAAABXwkIgAgAAAAk5OC4wMDAyMDgBCAAAAAUAAAABMQEA | L1: AAALLTE5MTY2Njk2NzEDAAAAAzE2MAIAAAACMjgEAAAAATAHAAAACDIvMi8yMDI2CAAAAAk5LzMwLzIwMjQJAAAAATA33/lXa2LeCF96TFhrYt4IF0NJUS5DT1JaLklRX05JLkxUTTMyMDI1AQAAADuUUiICAAAACC03NjguMzA3AQgAAAAFAAAAATEBAAAACy0xOTIwNjk5NzYyAwAAAAMxNjACAAAAAjE1BAAAAAEwBwAAAAgyLzIvMjAyNggAAAAJOS8zMC8yMDI1CQAAAAEwN9/5V2ti3ghfekxYa2LeCCJDSVEuQ09SWi5JUV9FQklUREFfRVFfSU5DLkxUTTMyMDI1AQAAADuUUiICAAAABy01NC4wNTUBCAAAAAUAAAABMQEAAAALLTE5MjA2OTk3NjIDAAAAAzE2MAIAAAAFMjE2NzcEAAAAATAHAAAACDIvMi8yMDI2CAAAAAk5LzMwLzIwMjUJAAAAATA33/lXa2LeCF96TFhrYt4IJENJUS5BUExELklRX1NUT0NLX0JBU0VEX1RPVEFMLkZZMjAyNAEAAACZYDYAAgAAAAYxNy4zNjIBCAAAAAUAAAABMQEAAAALLTE5MzQyNDM2MzQDAAAAAzE2MAIAAAAFMjQwMzQEAAAAATAHAAAACDIvMi8yMDI2CAAAAAk1LzMxLzIwMjQJAAAAATA33/lXa2LeCF96TFhrYt4IHENJUS5BUExELklRX0lOQ19UQVguTFRNMTIwMjYBAAAAmWA2AAIAAAAEMC4xMQEIAAAABQAAAAExAQAAAAstMTkyMjAwMTYzNgMAAAADMTYwAgAAAAI3NQQAAAABMAcAAAAIMi8yLzIwMjYIAAAACTgvMzEvMjAyNQkAAAABMDff+VdrYt4IjpJRWGti3ggg | M1: Q0lRLkFQTEQuSVFfSU5URVJFU1RfRVhQLkZRMTIwMjUBAAAAmWA2AAIAAAAGLTMuMDAzAQgAAAAFAAAAATEBAAAACy0xOTIyMDAyMzkxAwAAAAMxNjACAAAAAjgyBAAAAAEwBwAAAAgyLzIvMjAyNggAAAAJOC8zMS8yMDI0CQAAAAEwN9/5V2ti3ghfekxYa2LeCChDSVEuQVBMRC5JUV9DSEFOR0VfREVGX1RBWF9UT1RBTC5GUTEyMDI2AQAAAJlgNgADAAAAAAA33/lXa2LeCF96TFhrYt4IJENJUS5BUExELklRX05FVF9JTlRFUkVTVF9FWFAuRlExMjAyNgEAAACZYDYAAgAAAAYtNS41MjIBCAAAAAUAAAABMQEAAAALLTE5MjIwMDIzODIDAAAAAzE2MAIAAAADMzY4BAAAAAEwBwAAAAgyLzIvMjAyNggAAAAJOC8zMS8yMDI1CQAAAAEwN9/5V2ti3ghfekxYa2LeCCNDSVEuQVBMRC5JUV9ORVRfSU5URVJFU1RfRVhQLkZZMjAyNQEAAACZYDYAAgAAAActMTQuNzM5AQgAAAAFAAAAATEBAAAACy0xOTM0MjQzNjY3AwAAAAMxNjACAAAAAzM2OAQAAAABMAcAAAAIMi8yLzIwMjYIAAAACTUvMzEvMjAyNQkAAAABMDff+VdrYt4IX3pMWGti3ggcQ0lRLkFQTEQuSVFfU0dBX1NVUFBMLkZZMjAyNQEAAACZYDYAAgAAAAY4My4wNjUBCAAAAAUAAAABMQEAAAALLTE5MzQyNDM2NjcDAAAAAzE2MAIAAAADMTAyBAAAAAEwBwAAAAgyLzIvMjAyNggAAAAJNS8zMS8yMDI1CQAAAAEwN9/5V2ti3ghfekxYa2LeCB5DSVEuQVBM | N1: RC5JUV9TR0FfU1VQUEwuTFRNMTIwMjYBAAAAmWA2AAIAAAAHMTAxLjIyNAEIAAAABQAAAAExAQAAAAstMTkyMjAwMTYzNgMAAAADMTYwAgAAAAMxMDIEAAAAATAHAAAACDIvMi8yMDI2CAAAAAk4LzMxLzIwMjUJAAAAATA33/lXa2LeCMYMTlhrYt4IGENJUS5WTk8uSVFfRUJJVERBLkZZMjAyNAEAAABIxQQAAgAAAAc4MjAuNzk5AQgAAAAFAAAAATEBAAAACy0xOTYwNDU1NTA1AwAAAAMxNjACAAAABDQwNTEEAAAAATAHAAAACDIvMi8yMDI2CAAAAAoxMi8zMS8yMDI0CQAAAAEwN9/5V2ti3gjel1BYa2LeCCFDSVEuRVFJWC5JUV9CQVNJQ19FUFNfSU5DTC5GWTIwMjQBAAAAKm4AAAIAAAAIOC41Mzc4NzUBCAAAAAUAAAABMQEAAAALLTE5NjAxMzk0MDYDAAAAAzE2MAIAAAABOQQAAAABMAcAAAAIMi8yLzIwMjYIAAAACjEyLzMxLzIwMjQJAAAAATA33/lXa2LeCF96TFhrYt4IGUNJUS5FUUlYLklRX0VCSVREQS5GWTIwMjQBAAAAKm4AAAIAAAAEMzYyNQEIAAAABQAAAAExAQAAAAstMTk2MDEzOTQwNgMAAAADMTYwAgAAAAQ0MDUxBAAAAAEwBwAAAAgyLzIvMjAyNggAAAAKMTIvMzEvMjAyNAkAAAABMDff+VdrYt4IX3pMWGti3ggXQ0lRLkNSV1YuSVFfR1AuTFRNMzIwMjUBAAAAzKkeJAIAAAAIMzE4MC40ODMBCAAAAAUAAAABMQEAAAALLTE5MTY3NDU1NjIDAAAAAzE2MAIAAAACMTAEAAAAATAHAAAACDIv | O1: Mi8yMDI2CAAAAAk5LzMwLzIwMjUJAAAAATA33/lXa2LeCF96TFhrYt4IGUNJUS5DTFNLLklRX0VCSVQuTFRNMzIwMjUBAAAADuIJAwIAAAAHMjYxLjQ2NgEIAAAABQAAAAExAQAAAAstMTkzMjY5MjczMQMAAAADMTYwAgAAAAM0MDAEAAAAATAHAAAACDIvMi8yMDI2CAAAAAk2LzMwLzIwMjUJAAAAATA33/lXa2LeCF96TFhrYt4IF0NJUS5DTFNLLklRX0dQLkxUTTMyMDI1AQAAAA7iCQMCAAAABzMyOC45NTMBCAAAAAUAAAABMQEAAAALLTE5MzI2OTI3MzEDAAAAAzE2MAIAAAACMTAEAAAAATAHAAAACDIvMi8yMDI2CAAAAAk2LzMwLzIwMjUJAAAAATA33/lXa2LeCF96TFhrYt4IGUNJUS5JUkVOLklRX0VCSVQuTFRNMzIwMjUBAAAAF5gYKgIAAAAGLTYuOTcxAQgAAAAFAAAAATEBAAAACy0xOTE3NjU4NDM3AwAAAAMxNjACAAAAAzQwMAQAAAABMAcAAAAIMi8yLzIwMjYIAAAACTMvMzEvMjAyNQkAAAABMDff+VdrYt4IX3pMWGti3ggXQ0lRLklSRU4uSVFfR1AuTFRNMzIwMjUBAAAAF5gYKgIAAAAHMjU0LjA5OAEIAAAABQAAAAExAQAAAAstMTkxNzY1ODQzNwMAAAADMTYwAgAAAAIxMAQAAAABMAcAAAAIMi8yLzIwMjYIAAAACTMvMzEvMjAyNQkAAAABMDff+VdrYt4Iyb9HWGti3ggbQ0lRLldVTEYuSVFfRUJJVERBLkxUTTMyMDI1AQAAABJEqGMCAAAABy0zNS4yNDkBCAAAAAUAAAABMQEAAAALLTE5MTc1 | P1: MzIzODIDAAAAAzE2MAIAAAAENDA1MQQAAAABMAcAAAAIMi8yLzIwMjYIAAAACTkvMzAvMjAyNQkAAAABMDff+VdrYt4IuvZJWGti3ggZQ0lRLlJJT1QuSVFfRUJJVC5MVE0zMjAyNQEAAABGZBcAAgAAAAcxODIuMTcxAQgAAAAFAAAAATEBAAAACy0xOTE5NDM0MTU2AwAAAAMxNjACAAAAAzQwMAQAAAABMAcAAAAIMi8yLzIwMjYIAAAACTkvMzAvMjAyNQkAAAABMDff+VdrYt4IX3pMWGti3ggXQ0lRLlJJT1QuSVFfR1AuTFRNMzIwMjUBAAAARmQXAAIAAAAHMjUxLjk4NwEIAAAABQAAAAExAQAAAAstMTkxOTQzNDE1NgMAAAADMTYwAgAAAAIxMAQAAAABMAcAAAAIMi8yLzIwMjYIAAAACTkvMzAvMjAyNQkAAAABMDff+VdrYt4Iyb9HWGti3ggqQ0lRLk1BUkEuSVFfRUJJVERBX0xFQVNFX0FESlVTVEVELkxUTTMyMDI1AQAAANjMcAkCAAAACDEyMzcuODE4AQgAAAAFAAAAATEBAAAACy0xOTE4NDY3Mjk3AwAAAAMxNjACAAAABTQ4OTkzBAAAAAEwBwAAAAgyLzIvMjAyNggAAAAJOS8zMC8yMDI1CQAAAAEwN9/5V2ti3gjJv0dYa2LeCB5DSVEuTUFSQS5JUV9UT1RBTF9SRVYuTFRNMzIwMjUBAAAA2MxwCQIAAAAHOTE5LjE3MwEIAAAABQAAAAExAQAAAAstMTkxODQ2NzI5NwMAAAADMTYwAgAAAAIyOAQAAAABMAcAAAAIMi8yLzIwMjYIAAAACTkvMzAvMjAyNQkAAAABMDff+VdrYt4I8YFLWGti3ggeQ0lRLkNP | Q1: UlouSVFfVE9UQUxfUkVWLkxUTTMyMDI0AQAAADuUUiICAAAABzU1Ny42NzYBCAAAAAUAAAABMQEAAAALLTE5MjA2OTk3NjQDAAAAAzE2MAIAAAACMjgEAAAAATAHAAAACDIvMi8yMDI2CAAAAAk5LzMwLzIwMjQJAAAAATA33/lXa2LeCF96TFhrYt4IJENJUS5BUExELklRX1NUT0NLX0JBU0VEX1RPVEFMLkZZMjAyNQEAAACZYDYAAgAAAAYyMi43MDQBCAAAAAUAAAABMQEAAAALLTE5MzQyNDM2NjcDAAAAAzE2MAIAAAAFMjQwMzQEAAAAATAHAAAACDIvMi8yMDI2CAAAAAk1LzMxLzIwMjUJAAAAATA33/lXa2LeCMm/R1hrYt4IGENJUS5BUExELklRX0RBX0NGLkZZMjAyMwEAAACZYDYAAgAAAAU3LjYxNAEIAAAABQAAAAExAQAAAAstMTkzNDI0MzY3MwMAAAADMTYwAgAAAAQyMTYwBAAAAAEwBwAAAAgyLzIvMjAyNggAAAAJNS8zMS8yMDIzCQAAAAEwN9/5V2ti3ghODk9Ya2LeCCBDSVEuQVBMRC5JUV9JTlRFUkVTVF9FWFAuRlExMjAyNgEAAACZYDYAAgAAAAYtNS41MjIBCAAAAAUAAAABMQEAAAALLTE5MjIwMDIzODIDAAAAAzE2MAIAAAACODIEAAAAATAHAAAACDIvMi8yMDI2CAAAAAk4LzMxLzIwMjUJAAAAATA33/lXa2LeCPGBS1hrYt4IHUNJUS5BUExELklRX1NHQV9TVVBQTC5GUTEyMDI1AQAAAJlgNgACAAAABjEwLjk5MwEIAAAABQAAAAExAQAAAAstMTkyMjAwMjM5MQMAAAADMTYwAgAAAAMxMDIE | R1: AAAAATAHAAAACDIvMi8yMDI2CAAAAAk4LzMxLzIwMjQJAAAAATA33/lXa2LeCPGBS1hrYt4IIENJUS5WTk8uSVFfQkFTSUNfRVBTX0lOQ0wuRlkyMDI0AQAAAEjFBAACAAAACDAuMDQzNDI5AQgAAAAFAAAAATEBAAAACy0xOTYwNDU1NTA1AwAAAAMxNjACAAAAATkEAAAAATAHAAAACDIvMi8yMDI2CAAAAAoxMi8zMS8yMDI0CQAAAAEwN9/5V2ti3gjGDE5Ya2LeCCBDSVEuRExSLklRX0JBU0lDX0VQU19JTkNMLkZZMjAyNAEAAABEfKgAAgAAAAgxLjczNzQwNgEIAAAABQAAAAExAQAAAAstMTk1ODM1MTcwOQMAAAADMTYwAgAAAAE5BAAAAAEwBwAAAAgyLzIvMjAyNggAAAAKMTIvMzEvMjAyNAkAAAABMDff+VdrYt4IxgxOWGti3ggXQ0lRLkNSV1YuSVFfTkkuTFRNMzIwMjUBAAAAzKkeJAIAAAAILTc2Ni42NDYBCAAAAAUAAAABMQEAAAALLTE5MTY3NDU1NjIDAAAAAzE2MAIAAAACMTUEAAAAATAHAAAACDIvMi8yMDI2CAAAAAk5LzMwLzIwMjUJAAAAATA33/lXa2LeCMYMTlhrYt4IG0NJUS5DUldWLklRX0VCSVREQS5MVE0zMjAyNQEAAADMqR4kAgAAAAgyMTg0LjEzOQEIAAAABQAAAAExAQAAAAstMTkxNjc0NTU2MgMAAAADMTYwAgAAAAQ0MDUxBAAAAAEwBwAAAAgyLzIvMjAyNggAAAAJOS8zMC8yMDI1CQAAAAEwN9/5V2ti3gjGDE5Ya2LeCBdDSVEuQ0xTSy5JUV9OSS5MVE0zMjAyNQEAAAAO4gkDAgAA | S1: AAYzMDMuMjEBCAAAAAUAAAABMQEAAAALLTE5MzI2OTI3MzEDAAAAAzE2MAIAAAACMTUEAAAAATAHAAAACDIvMi8yMDI2CAAAAAk2LzMwLzIwMjUJAAAAATA33/lXa2LeCMYMTlhrYt4IG0NJUS5DTFNLLklRX0VCSVREQS5MVE0zMjAyNQEAAAAO4gkDAgAAAAc1NTMuMzI0AQgAAAAFAAAAATEBAAAACy0xOTMyNjkyNzMxAwAAAAMxNjACAAAABDQwNTEEAAAAATAHAAAACDIvMi8yMDI2CAAAAAk2LzMwLzIwMjUJAAAAATA33/lXa2LeCMYMTlhrYt4IF0NJUS5JUkVOLklRX05JLkxUTTMyMDI1AQAAABeYGCoCAAAABy0zNS42MzIBCAAAAAUAAAABMQEAAAALLTE5MTc2NTg0MzcDAAAAAzE2MAIAAAACMTUEAAAAATAHAAAACDIvMi8yMDI2CAAAAAkzLzMxLzIwMjUJAAAAATA33/lXa2LeCMYMTlhrYt4IHENJUS5XVUxGLklRX1RPVEFMX1JFVi5GWTIwMjQBAAAAEkSoYwIAAAAHMTQwLjA1MQEIAAAABQAAAAExAQAAAAstMTk1NzE0MjkyNwMAAAADMTYwAgAAAAIyOAQAAAABMAcAAAAIMi8yLzIwMjYIAAAACjEyLzMxLzIwMjQJAAAAATA33/lXa2LeCMYMTlhrYt4IGUNJUS5XVUxGLklRX0VCSVQuTFRNMzIwMjUBAAAAEkSoYwIAAAAILTEwOC4zNTUBCAAAAAUAAAABMQEAAAALLTE5MTc1MzIzODIDAAAAAzE2MAIAAAADNDAwBAAAAAEwBwAAAAgyLzIvMjAyNggAAAAJOS8zMC8yMDI1CQAAAAEwN9/5V2ti3gjGDE5Y | T1: a2LeCBdDSVEuUklPVC5JUV9OSS5MVE0zMjAyNQEAAABGZBcAAgAAAAcxNjQuMDAyAQgAAAAFAAAAATEBAAAACy0xOTE5NDM0MTU2AwAAAAMxNjACAAAAAjE1BAAAAAEwBwAAAAgyLzIvMjAyNggAAAAJOS8zMC8yMDI1CQAAAAEwN9/5V2ti3gjGDE5Ya2LeCCpDSVEuUklPVC5JUV9FQklUREFfTEVBU0VfQURKVVNURUQuTFRNMzIwMjUBAAAARmQXAAIAAAAHNTE1LjAzNQEIAAAABQAAAAExAQAAAAstMTkxOTQzNDE1NgMAAAADMTYwAgAAAAU0ODk5MwQAAAABMAcAAAAIMi8yLzIwMjYIAAAACTkvMzAvMjAyNQkAAAABMDff+VdrYt4IxgxOWGti3ggZQ0lRLk1BUkEuSVFfRUJJVC5MVE0zMjAyNQEAAADYzHAJAgAAAAc1MDUuMDU2AQgAAAAFAAAAATEBAAAACy0xOTE4NDY3Mjk3AwAAAAMxNjACAAAAAzQwMAQAAAABMAcAAAAIMi8yLzIwMjYIAAAACTkvMzAvMjAyNQkAAAABMDff+VdrYt4IxgxOWGti3gghQ0lRLkhJVkUuSVFfQkFTSUNfRVBTX0lOQ0wuRlkyMDI0AQAAANl0MAACAAAACDAuMjk0NDI3AQgAAAAFAAAAATEBAAAACy0xOTM3MjI0ODU4AwAAAAMxNjACAAAAATkEAAAAATAHAAAACDIvMi8yMDI2CAAAAAkzLzMxLzIwMjQJAAAAATA33/lXa2LeCMYMTlhrYt4IGUNJUS5ISVZFLklRX0VCSVREQS5GWTIwMjMBAAAA2XQwAAIAAAAHLTQ1Ljk5MgEIAAAABQAAAAExAQAAAAstMTk4ODk2MTk4NwMAAAAD | U1: MTYwAgAAAAQ0MDUxBAAAAAEwBwAAAAgyLzIvMjAyNggAAAAJMy8zMS8yMDIzCQAAAAEwN9/5V2ti3gjGDE5Ya2LeCCFDSVEuQklURi5JUV9CQVNJQ19FUFNfSU5DTC5GWTIwMjQBAAAAFd2VIAIAAAAJLTAuMTMwMzc1AQgAAAAFAAAAATEBAAAACy0xOTU0MTc2OTU1AwAAAAMxNjACAAAAATkEAAAAATAHAAAACDIvMi8yMDI2CAAAAAoxMi8zMS8yMDI0CQAAAAEwN9/5V2ti3gjGDE5Ya2LeCBlDSVEuQklURi5JUV9FQklUREEuRlkyMDIzAQAAABXdlSACAAAABjIwLjc3MwEIAAAABQAAAAExAQAAAAstMTk1NDE3Njk1NwMAAAADMTYwAgAAAAQ0MDUxBAAAAAEwBwAAAAgyLzIvMjAyNggAAAAKMTIvMzEvMjAyMwkAAAABMDff+VdrYt4ITg5PWGti3gglQ0lRLkFQTEQuSVFfU1RPQ0tfQkFTRURfVE9UQUwuRlExMjAyNQEAAACZYDYAAgAAAAYtMi45MTkBCAAAAAUAAAABMQEAAAALLTE5MjIwMDIzOTEDAAAAAzE2MAIAAAAFMjQwMzQEAAAAATAHAAAACDIvMi8yMDI2CAAAAAk4LzMxLzIwMjQJAAAAATA33/lXa2LeCE4OT1hrYt4IGENJUS5BUExELklRX0RBX0NGLkZZMjAyNAEAAACZYDYAAgAAAAU3OS4zNgEIAAAABQAAAAExAQAAAAstMTkzNDI0MzYzNAMAAAADMTYwAgAAAAQyMTYwBAAAAAEwBwAAAAgyLzIvMjAyNggAAAAJNS8zMS8yMDI0CQAAAAEwN9/5V2ti3gjel1BYa2LeCCFDSVEuQVBMRC5JUV9JTlRF | V1: UkVTVF9FWFAuTFRNMTIwMjYBAAAAmWA2AAIAAAAHLTE3LjI1OAEIAAAABQAAAAExAQAAAAstMTkyMjAwMTYzNgMAAAADMTYwAgAAAAI4MgQAAAABMAcAAAAIMi8yLzIwMjYIAAAACTgvMzEvMjAyNQkAAAABMDff+VdrYt4ITg5PWGti3ggsQ0lRLkFQTEQuSVFfUkVUVVJOX0lOVkVTVEVEX0NBUElUQUwuTFRNMTIwMjYBAAAAmWA2AAIAAAAILTE5LjcwODcAN9/5V2ti3ghODk9Ya2LeCBpDSVEuQVBMRC5JUV9JTkNfVEFYLkZZMjAyNQEAAACZYDYAAgAAAAUwLjEwMgEIAAAABQAAAAExAQAAAAstMTkzNDI0MzY2NwMAAAADMTYwAgAAAAI3NQQAAAABMAcAAAAIMi8yLzIwMjYIAAAACTUvMzEvMjAyNQkAAAABMDff+VdrYt4IjpJRWGti3ggaQ0lRLkFQTEQuSVFfSU5DX1RBWC5GWTIwMjMBAAAAmWA2AAIAAAAGLTAuNTIzAQgAAAAFAAAAATEBAAAACy0xOTM0MjQzNjczAwAAAAMxNjACAAAAAjc1BAAAAAEwBwAAAAgyLzIvMjAyNggAAAAJNS8zMS8yMDIzCQAAAAEwN9/5V2ti3gjel1BYa2LeCB1DSVEuQVBMRC5JUV9TR0FfU1VQUEwuRlExMjAyNgEAAACZYDYAAgAAAAYyOS4xNTIBCAAAAAUAAAABMQEAAAALLTE5MjIwMDIzODIDAAAAAzE2MAIAAAADMTAyBAAAAAEwBwAAAAgyLzIvMjAyNggAAAAJOC8zMS8yMDI1CQAAAAEwN9/5V2ti3ghODk9Ya2LeCB1DSVEuQVBMRC5JUV9UT1RBTF9SRVYuRlExMjAyNgEA | W1: AACZYDYAAgAAAAY2NC4yMTYBCAAAAAUAAAABMQEAAAALLTE5MjIwMDIzODIDAAAAAzE2MAIAAAACMjgEAAAAATAHAAAACDIvMi8yMDI2CAAAAAk4LzMxLzIwMjUJAAAAATA33/lXa2LeCE4OT1hrYt4IFUNJUS5CSVRGLklRX0dQLkZZMjAyNAEAAAAV3ZUgAgAAAActMzIuMzU5AQgAAAAFAAAAATEBAAAACy0xOTU0MTc2OTU1AwAAAAMxNjACAAAAAjEwBAAAAAEwBwAAAAgyLzIvMjAyNggAAAAKMTIvMzEvMjAyNAkAAAABMDff+VdrYt4Iyb9HWGti3ggZQ0lRLkJUQlQuSVFfRUJJVC5MVE0zMjAyNQEAAABXwkIgAgAAAAoxMjguMzYyMTA0AQgAAAAFAAAAATEBAAAACy0xOTE2NjY5NjI5AwAAAAMxNjACAAAAAzQwMAQAAAABMAcAAAAIMi8yLzIwMjYIAAAACTkvMzAvMjAyNQkAAAABMDff+VdrYt4Iyb9HWGti3ggbQ0lRLkFQTEQuSVFfSU5DX1RBWC5GUTEyMDI1AQAAAJlgNgADAAAAAAA33/lXa2LeCN6XUFhrYt4IJ0NJUS5BUExELklRX0NIQU5HRV9ERUZfVEFYX1RPVEFMLkZZMjAyNAEAAACZYDYAAwAAAAAAN9/5V2ti3gjJv0dYa2LeCBxDSVEuQVBMRC5JUV9TR0FfU1VQUEwuRlkyMDIzAQAAAJlgNgACAAAABjUzLjkxNQEIAAAABQAAAAExAQAAAAstMTkzNDI0MzY3MwMAAAADMTYwAgAAAAMxMDIEAAAAATAHAAAACDIvMi8yMDI2CAAAAAk1LzMxLzIwMjMJAAAAATA33/lXa2LeCMm/R1hrYt4IJUNJUS5B | X1: UExELklRX05FVF9JTlRFUkVTVF9FWFAuTFRNMTIwMjYBAAAAmWA2AAIAAAAHLTE3LjI1OAEIAAAABQAAAAExAQAAAAstMTkyMjAwMTYzNgMAAAADMTYwAgAAAAMzNjgEAAAAATAHAAAACDIvMi8yMDI2CAAAAAk4LzMxLzIwMjUJAAAAATA33/lXa2LeCMm/R1hrYt4IHkNJUS5FUUlYLklRX1RPVEFMX1JFVi5MVE0zMjAyNQEAAAAqbgAAAgAAAAQ5MDc2AQgAAAAFAAAAATEBAAAACy0xOTE5ODE0OTY1AwAAAAMxNjACAAAAAjI4BAAAAAEwBwAAAAgyLzIvMjAyNggAAAAJOS8zMC8yMDI1CQAAAAEwN9/5V2ti3ghODk9Ya2LeCBlDSVEuQ1JXVi5JUV9FQklULkxUTTMyMDI1AQAAAMypHiQCAAAABzE4NS4yNjMBCAAAAAUAAAABMQEAAAALLTE5MTY3NDU1NjIDAAAAAzE2MAIAAAADNDAwBAAAAAEwBwAAAAgyLzIvMjAyNggAAAAJOS8zMC8yMDI1CQAAAAEwN9/5V2ti3ghODk9Ya2LeCBlDSVEuSVJFTi5JUV9FQklUREEuRlkyMDI0AQAAABeYGCoCAAAABjMxLjIxMgEIAAAABQAAAAExAQAAAAstMTkyNzIxNDQ2MQMAAAADMTYwAgAAAAQ0MDUxBAAAAAEwBwAAAAgyLzIvMjAyNggAAAAJNi8zMC8yMDI0CQAAAAEwN9/5V2ti3ghODk9Ya2LeCBxDSVEuSVJFTi5JUV9UT1RBTF9SRVYuRlkyMDI0AQAAABeYGCoCAAAABzE4Ny4xOTIBCAAAAAUAAAABMQEAAAALLTE5MjcyMTQ0NjEDAAAAAzE2MAIAAAACMjgEAAAAATAH | Y1: AAAACDIvMi8yMDI2CAAAAAk2LzMwLzIwMjQJAAAAATA33/lXa2LeCE4OT1hrYt4IF0NJUS5XVUxGLklRX05JLkxUTTMyMDI1AQAAABJEqGMCAAAACC01NjQuMDM0AQgAAAAFAAAAATEBAAAACy0xOTE3NTMyMzgyAwAAAAMxNjACAAAAAjE1BAAAAAEwBwAAAAgyLzIvMjAyNggAAAAJOS8zMC8yMDI1CQAAAAEwN9/5V2ti3ghODk9Ya2LeCBxDSVEuUklPVC5JUV9UT1RBTF9SRVYuRlkyMDI0AQAAAEZkFwACAAAABzM3Ni42NTgBCAAAAAUAAAABMQEAAAALLTE5NTczNzU0NzUDAAAAAzE2MAIAAAACMjgEAAAAATAHAAAACDIvMi8yMDI2CAAAAAoxMi8zMS8yMDI0CQAAAAEwN9/5V2ti3ghODk9Ya2LeCBdDSVEuTUFSQS5JUV9OSS5MVE0zMjAyNQEAAADYzHAJAgAAAAc5MjYuNjkyAQgAAAAFAAAAATEBAAAACy0xOTE4NDY3Mjk3AwAAAAMxNjACAAAAAjE1BAAAAAEwBwAAAAgyLzIvMjAyNggAAAAJOS8zMC8yMDI1CQAAAAEwN9/5V2ti3ghODk9Ya2LeCCFDSVEuSElWRS5JUV9CQVNJQ19FUFNfSU5DTC5GWTIwMjMBAAAA2XQwAAIAAAAJLTIuODUyODk0AQgAAAAFAAAAATEBAAAACy0xOTg4OTYxOTg3AwAAAAMxNjACAAAAATkEAAAAATAHAAAACDIvMi8yMDI2CAAAAAkzLzMxLzIwMjMJAAAAATA33/lXa2LeCE4OT1hrYt4IIUNJUS5CSVRGLklRX0JBU0lDX0VQU19JTkNMLkZZMjAyMwEAAAAV3ZUgAgAAAAktMC40 | Z1: MTUzNTYBCAAAAAUAAAABMQEAAAALLTE5NTQxNzY5NTcDAAAAAzE2MAIAAAABOQQAAAABMAcAAAAIMi8yLzIwMjYIAAAACjEyLzMxLzIwMjMJAAAAATA33/lXa2LeCE4OT1hrYt4II0NJUS5CVEJULklRX0JBU0lDX0VQU19JTkNMLkxUTTMyMDI0AQAAAFfCQiACAAAACS0wLjAyMjA0MwEIAAAABQAAAAExAQAAAAstMTkxNjY2OTY3MQMAAAADMTYwAgAAAAE5BAAAAAEwBwAAAAgyLzIvMjAyNggAAAAJOS8zMC8yMDI0CQAAAAEwN9/5V2ti3ghODk9Ya2LeCBtDSVEuQ09SWi5JUV9FQklUREEuTFRNMzIwMjQBAAAAO5RSIgIAAAAHMTUxLjE0OAEIAAAABQAAAAExAQAAAAstMTkyMDY5OTc2NAMAAAADMTYwAgAAAAQ0MDUxBAAAAAEwBwAAAAgyLzIvMjAyNggAAAAJOS8zMC8yMDI0CQAAAAEwN9/5V2ti3gjel1BYa2LeCCVDSVEuQVBMRC5JUV9TVE9DS19CQVNFRF9UT1RBTC5GUTEyMDI2AQAAAJlgNgACAAAABjE1LjQ2NQEIAAAABQAAAAExAQAAAAstMTkyMjAwMjM4MgMAAAADMTYwAgAAAAUyNDAzNAQAAAABMAcAAAAIMi8yLzIwMjYIAAAACTgvMzEvMjAyNQkAAAABMDff+VdrYt4I3pdQWGti3ggYQ0lRLkFQTEQuSVFfREFfQ0YuRlkyMDI1AQAAAJlgNgACAAAABjk3Ljk0NQEIAAAABQAAAAExAQAAAAstMTkzNDI0MzY2NwMAAAADMTYwAgAAAAQyMTYwBAAAAAEwBwAAAAgyLzIvMjAyNggAAAAJNS8zMS8yMDI1 | AA1: CQAAAAEwN9/5V2ti3gjel1BYa2LeCCVDSVEuQVBMRC5JUV9SRVRVUk5fRVFVSVRZX0ZTLkxUTTEyMDI2AQAAAJlgNgACAAAACC0yOC43NTU3AQgAAAAFAAAAATEBAAAACy0xOTIyMDAxNjM2AwAAAAMxNjACAAAABDQxMjgEAAAAATAHAAAACDIvMi8yMDI2CAAAAAk4LzMxLzIwMjUJAAAAATA33/lXa2LeCN6XUFhrYt4IGkNJUS5BUExELklRX0lOQ19UQVguRlkyMDI0AQAAAJlgNgACAAAABTAuMDk2AQgAAAAFAAAAATEBAAAACy0xOTM0MjQzNjM0AwAAAAMxNjACAAAAAjc1BAAAAAEwBwAAAAgyLzIvMjAyNggAAAAJNS8zMS8yMDI0CQAAAAEwN9/5V2ti3gjel1BYa2LeCBdDSVEuQVBMRC5JUV9DT0dTLkZZMjAyNAEAAACZYDYAAgAAAAcxMDYuNjUzAQgAAAAFAAAAATEBAAAACy0xOTM0MjQzNjM0AwAAAAMxNjACAAAAAjM0BAAAAAEwBwAAAAgyLzIvMjAyNggAAAAJNS8zMS8yMDI0CQAAAAEwN9/5V2ti3gjel1BYa2LeCB5DSVEuQVBMRC5JUV9UT1RBTF9SRVYuTFRNMTIwMjYBAAAAmWA2AAIAAAAGMTczLjU2AQgAAAAFAAAAATEBAAAACy0xOTIyMDAxNjM2AwAAAAMxNjACAAAAAjI4BAAAAAEwBwAAAAgyLzIvMjAyNggAAAAJOC8zMS8yMDI1CQAAAAEwN9/5V2ti3gjel1BYa2LeCBRDSVEuVk5PLklRX05JLkZZMjAyNAEAAABIxQQAAgAAAAY3MC4zODcBCAAAAAUAAAABMQEAAAALLTE5NjA0NTU1MDUDAAAA | AB1: AzE2MAIAAAACMTUEAAAAATAHAAAACDIvMi8yMDI2CAAAAAoxMi8zMS8yMDI0CQAAAAEwN9/5V2ti3ghOcUdYa2LeCCFDSVEuQ0xTSy5JUV9CQVNJQ19FUFNfSU5DTC5GWTIwMjUBAAAADuIJAwIAAAAHMS4yNTIxMQEIAAAABQAAAAExAQAAAAstMTkxNDM1MTI3MwMAAAADMTYwAgAAAAE5BAAAAAEwBwAAAAgyLzIvMjAyNggAAAAJOS8zMC8yMDI1CQAAAAEwN9/5V2ti3gjJv0dYa2LeCBdDSVEuRVFJWC5JUV9HUC5MVE0zMjAyNQEAAAAqbgAAAgAAAAQ0NTcwAQgAAAAFAAAAATEBAAAACy0xOTE5ODE0OTY1AwAAAAMxNjACAAAAAjEwBAAAAAEwBwAAAAgyLzIvMjAyNggAAAAJOS8zMC8yMDI1CQAAAAEwN9/5V2ti3gjel1BYa2LeCB1DSVEuRExSLklRX1RPVEFMX1JFVi5MVE0zMjAyNQEAAABEfKgAAgAAAAg1ODQxLjAzNgEIAAAABQAAAAExAQAAAAstMTkxOTEzNjkxNgMAAAADMTYwAgAAAAIyOAQAAAABMAcAAAAIMi8yLzIwMjYIAAAACTkvMzAvMjAyNQkAAAABMDff+VdrYt4I3pdQWGti3ggZQ0lRLkNMU0suSVFfRUJJVERBLkZZMjAyNAEAAAAO4gkDAgAAAAY5NS4zNjYBCAAAAAUAAAABMQEAAAALLTE5MTQzNTEyNzUDAAAAAzE2MAIAAAAENDA1MQQAAAABMAcAAAAIMi8yLzIwMjYIAAAACTkvMzAvMjAyNAkAAAABMDff+VdrYt4I3pdQWGti3ggcQ0lRLkNMU0suSVFfVE9UQUxfUkVWLkZZMjAyNAEAAAAO | AC1: 4gkDAgAAAAczNzguOTY4AQgAAAAFAAAAATEBAAAACy0xOTE0MzUxMjc1AwAAAAMxNjACAAAAAjI4BAAAAAEwBwAAAAgyLzIvMjAyNggAAAAJOS8zMC8yMDI0CQAAAAEwN9/5V2ti3ghODk9Ya2LeCBlDSVEuV1VMRi5JUV9FQklUREEuRlkyMDI0AQAAABJEqGMCAAAABTYuNTE2AQgAAAAFAAAAATEBAAAACy0xOTU3MTQyOTI3AwAAAAMxNjACAAAABDQwNTEEAAAAATAHAAAACDIvMi8yMDI2CAAAAAoxMi8zMS8yMDI0CQAAAAEwN9/5V2ti3ghODk9Ya2LeCBlDSVEuTUFSQS5JUV9FQklUREEuRlkyMDI0AQAAANjMcAkCAAAABjc3Mi44NAEIAAAABQAAAAExAQAAAAstMTk1NzE3NzIxMAMAAAADMTYwAgAAAAQ0MDUxBAAAAAEwBwAAAAgyLzIvMjAyNggAAAAKMTIvMzEvMjAyNAkAAAABMDff+VdrYt4I3pdQWGti3ggcQ0lRLk1BUkEuSVFfVE9UQUxfUkVWLkZZMjAyNAEAAADYzHAJAgAAAAc2NTYuMzc4AQgAAAAFAAAAATEBAAAACy0xOTU3MTc3MjEwAwAAAAMxNjACAAAAAjI4BAAAAAEwBwAAAAgyLzIvMjAyNggAAAAKMTIvMzEvMjAyNAkAAAABMDff+VdrYt4I3pdQWGti3ggbQ0lRLkFQTEQuSVFfRUJJVERBLkxUTTEyMDI2AQAAAJlgNgACAAAABTUuODQ4AQgAAAAFAAAAATEBAAAACy0xOTIyMDAxNjM2AwAAAAMxNjACAAAABDQwNTEEAAAAATAHAAAACDIvMi8yMDI2CAAAAAk4LzMxLzIwMjUJAAAAATA33/lX | AD1: a2LeCE4OT1hrYt4IJkNJUS5BUExELklRX1NUT0NLX0JBU0VEX1RPVEFMLkxUTTEyMDI2AQAAAJlgNgACAAAABjQxLjA4OAEIAAAABQAAAAExAQAAAAstMTkyMjAwMTYzNgMAAAADMTYwAgAAAAUyNDAzNAQAAAABMAcAAAAIMi8yLzIwMjYIAAAACTgvMzEvMjAyNQkAAAABMDff+VdrYt4IjpJRWGti3ggZQ0lRLkFQTEQuSVFfREFfQ0YuRlExMjAyNQEAAACZYDYAAgAAAAYzNC4yNzEBCAAAAAUAAAABMQEAAAALLTE5MjIwMDIzOTEDAAAAAzE2MAIAAAAEMjE2MAQAAAABMAcAAAAIMi8yLzIwMjYIAAAACTgvMzEvMjAyNAkAAAABMDff+VdrYt4IjpJRWGti3ggZQ0lRLkFQTEQuSVFfREFfQ0YuRlExMjAyNgEAAACZYDYAAgAAAAU0LjE1MgEIAAAABQAAAAExAQAAAAstMTkyMjAwMjM4MgMAAAADMTYwAgAAAAQyMTYwBAAAAAEwBwAAAAgyLzIvMjAyNggAAAAJOC8zMS8yMDI1CQAAAAEwN9/5V2ti3giOklFYa2LeCBdDSVEuQVBMRC5JUV9DT0dTLkZZMjAyNQEAAACZYDYAAgAAAAcxMDEuNDUxAQgAAAAFAAAAATEBAAAACy0xOTM0MjQzNjY3AwAAAAMxNjACAAAAAjM0BAAAAAEwBwAAAAgyLzIvMjAyNggAAAAJNS8zMS8yMDI1CQAAAAEwN9/5V2ti3gjJv0dYa2LeCBdDSVEuQVBMRC5JUV9DT0dTLkZZMjAyMwEAAACZYDYAAgAAAAY0NC4zODgBCAAAAAUAAAABMQEAAAALLTE5MzQyNDM2NzMDAAAAAzE2MAIAAAAC | AE1: MzQEAAAAATAHAAAACDIvMi8yMDI2CAAAAAk1LzMxLzIwMjMJAAAAATA33/lXa2LeCI6SUVhrYt4IGkNJUS5ETFIuSVFfRUJJVERBLkxUTTMyMDI1AQAAAER8qAACAAAACDI2NjIuOTYxAQgAAAAFAAAAATEBAAAACy0xOTE5MTM2OTE2AwAAAAMxNjACAAAABDQwNTEEAAAAATAHAAAACDIvMi8yMDI2CAAAAAk5LzMwLzIwMjUJAAAAATA33/lXa2LeCMm/R1hrYt4IIUNJUS5XVUxGLklRX0JBU0lDX0VQU19JTkNMLkZZMjAyNAEAAAASRKhjAgAAAAktMC4yMDYxMzMBCAAAAAUAAAABMQEAAAALLTE5NTcxNDI5MjcDAAAAAzE2MAIAAAABOQQAAAABMAcAAAAIMi8yLzIwMjYIAAAACjEyLzMxLzIwMjQJAAAAATA33/lXa2LeCMm/R1hrYt4IIUNJUS5NQVJBLklRX0JBU0lDX0VQU19JTkNMLkZZMjAyNAEAAADYzHAJAgAAAAgxLjg2NjYzNAEIAAAABQAAAAExAQAAAAstMTk1NzE3NzIxMAMAAAADMTYwAgAAAAE5BAAAAAEwBwAAAAgyLzIvMjAyNggAAAAKMTIvMzEvMjAyNAkAAAABMDff+VdrYt4Iyb9HWGti3ggXQ0lRLkJJVEYuSVFfRUJJVC5GWTIwMjQBAAAAFd2VIAIAAAAILTEwMy41OTkBCAAAAAUAAAABMQEAAAALLTE5NTQxNzY5NTUDAAAAAzE2MAIAAAADNDAwBAAAAAEwBwAAAAgyLzIvMjAyNggAAAAKMTIvMzEvMjAyNAkAAAABMDff+VdrYt4Iyb9HWGti3ggXQ0lRLkJUQlQuSVFfR1AuTFRNMzIwMjUBAAAA | AF1: V8JCIAIAAAAJNTIuMDM0ODk1AQgAAAAFAAAAATEBAAAACy0xOTE2NjY5NjI5AwAAAAMxNjACAAAAAjEwBAAAAAEwBwAAAAgyLzIvMjAyNggAAAAJOS8zMC8yMDI1CQAAAAEwN9/5V2ti3gjJv0dYa2LeCB5DSVEuQ09SWi5JUV9UT1RBTF9SRVYuTFRNMzIwMjUBAAAAO5RSIgIAAAAHMzM0LjE4MQEIAAAABQAAAAExAQAAAAstMTkyMDY5OTc2MgMAAAADMTYwAgAAAAIyOAQAAAABMAcAAAAIMi8yLzIwMjYIAAAACTkvMzAvMjAyNQkAAAABMDff+VdrYt4Iyb9HWGti3ggfQ0lRLkFQTEQuSVFfSU5URVJFU1RfRVhQLkZZMjAyNAEAAACZYDYAAgAAAActMTcuNzA4AQgAAAAFAAAAATEBAAAACy0xOTM0MjQzNjM0AwAAAAMxNjACAAAAAjgyBAAAAAEwBwAAAAgyLzIvMjAyNggAAAAJNS8zMS8yMDI0CQAAAAEwN9/5V2ti3gjJv0dYa2LeCCNDSVEuQVBMRC5JUV9ORVRfSU5URVJFU1RfRVhQLkZZMjAyMwEAAACZYDYAAgAAAAYtMi4wMDYBCAAAAAUAAAABMQEAAAALLTE5MzQyNDM2NzMDAAAAAzE2MAIAAAADMzY4BAAAAAEwBwAAAAgyLzIvMjAyNggAAAAJNS8zMS8yMDIzCQAAAAEwN9/5V2ti3gjJv0dYa2LeCClDSVEuQVBMRC5JUV9DSEFOR0VfREVGX1RBWF9UT1RBTC5MVE0xMjAyNgEAAACZYDYAAwAAAAAAN9/5V2ti3gjGDE5Ya2LeCBZDSVEuVk5PLklRX0VCSVQuRlkyMDI0AQAAAEjFBAACAAAABzM3Ni4zMzQB | AG1: CAAAAAUAAAABMQEAAAALLTE5NjA0NTU1MDUDAAAAAzE2MAIAAAADNDAwBAAAAAEwBwAAAAgyLzIvMjAyNggAAAAKMTIvMzEvMjAyNAkAAAABMDff+VdrYt4I8YFLWGti3ggUQ0lRLlZOTy5JUV9HUC5GWTIwMjQBAAAASMUEAAIAAAAHOTcyLjM1NAEIAAAABQAAAAExAQAAAAstMTk2MDQ1NTUwNQMAAAADMTYwAgAAAAIxMAQAAAABMAcAAAAIMi8yLzIwMjYIAAAACjEyLzMxLzIwMjQJAAAAATA33/lXa2LeCE4OT1hrYt4IG0NJUS5FUUlYLklRX0VCSVREQS5MVE0zMjAyNQEAAAAqbgAAAgAAAAQzOTAwAQgAAAAFAAAAATEBAAAACy0xOTE5ODE0OTY1AwAAAAMxNjACAAAABDQwNTEEAAAAATAHAAAACDIvMi8yMDI2CAAAAAk5LzMwLzIwMjUJAAAAATA33/lXa2LeCI6SUVhrYt4IGENJUS5ETFIuSVFfRUJJVC5MVE0zMjAyNQEAAABEfKgAAgAAAAc4MDEuMDI4AQgAAAAFAAAAATEBAAAACy0xOTE5MTM2OTE2AwAAAAMxNjACAAAAAzQwMAQAAAABMAcAAAAIMi8yLzIwMjYIAAAACTkvMzAvMjAyNQkAAAABMDff+VdrYt4Iyb9HWGti3ggWQ0lRLkRMUi5JUV9HUC5MVE0zMjAyNQEAAABEfKgAAgAAAAgzMjAxLjI0NQEIAAAABQAAAAExAQAAAAstMTkxOTEzNjkxNgMAAAADMTYwAgAAAAIxMAQAAAABMAcAAAAIMi8yLzIwMjYIAAAACTkvMzAvMjAyNQkAAAABMDff+VdrYt4IxgxOWGti3gghQ0lRLlJJT1QuSVFfQkFT | AH1: SUNfRVBTX0lOQ0wuRlkyMDI0AQAAAEZkFwACAAAACDAuMzk2NDA5AQgAAAAFAAAAATEBAAAACy0xOTU3Mzc1NDc1AwAAAAMxNjACAAAAATkEAAAAATAHAAAACDIvMi8yMDI2CAAAAAoxMi8zMS8yMDI0CQAAAAEwN9/5V2ti3ghODk9Ya2LeCBlDSVEuUklPVC5JUV9FQklUREEuRlkyMDI0AQAAAEZkFwACAAAABzMwNC4zOTcBCAAAAAUAAAABMQEAAAALLTE5NTczNzU0NzUDAAAAAzE2MAIAAAAENDA1MQQAAAABMAcAAAAIMi8yLzIwMjYIAAAACjEyLzMxLzIwMjQJAAAAATA33/lXa2LeCMYMTlhrYt4IHUNJUS5IVVQuSVFfVE9UQUxfUkVWLkxUTTMyMDI1AQAAAILoOmQCAAAABzE3OC4zMTgBCAAAAAUAAAABMQEAAAALLTE5MTg1NzYyOTADAAAAAzE2MAIAAAACMjgEAAAAATAHAAAACDIvMi8yMDI2CAAAAAk5LzMwLzIwMjUJAAAAATA33/lXa2LeCI6SUVhrYt4IHENJUS5ISVZFLklRX1RPVEFMX1JFVi5GWTIwMjQBAAAA2XQwAAIAAAAHMTE0LjQ2NQEIAAAABQAAAAExAQAAAAstMTkzNzIyNDg1OAMAAAADMTYwAgAAAAIyOAQAAAABMAcAAAAIMi8yLzIwMjYIAAAACTMvMzEvMjAyNAkAAAABMDff+VdrYt4IjpJRWGti3ggcQ0lRLkJJVEYuSVFfVE9UQUxfUkVWLkZZMjAyNAEAAAAV3ZUgAgAAAAcxOTIuODgxAQgAAAAFAAAAATEBAAAACy0xOTU0MTc2OTU1AwAAAAMxNjACAAAAAjI4BAAAAAEwBwAAAAgyLzIv | AI1: MjAyNggAAAAKMTIvMzEvMjAyNAkAAAABMDff+VdrYt4IjpJRWGti3ggbQ0lRLkJUQlQuSVFfRUJJVERBLkxUTTMyMDI1AQAAAFfCQiACAAAACjE2Mi4xOTkwODkBCAAAAAUAAAABMQEAAAALLTE5MTY2Njk2MjkDAAAAAzE2MAIAAAAENDA1MQQAAAABMAcAAAAIMi8yLzIwMjYIAAAACTkvMzAvMjAyNQkAAAABMDff+VdrYt4IjpJRWGti3ggeQ0lRLkJUQlQuSVFfVE9UQUxfUkVWLkxUTTMyMDI1AQAAAFfCQiACAAAACjEwNS43MDMxNDMBCAAAAAUAAAABMQEAAAALLTE5MTY2Njk2MjkDAAAAAzE2MAIAAAACMjgEAAAAATAHAAAACDIvMi8yMDI2CAAAAAk5LzMwLzIwMjUJAAAAATA33/lXa2LeCI6SUVhrYt4IH0NJUS5BUExELklRX0lOVEVSRVNUX0VYUC5GWTIwMjMBAAAAmWA2AAIAAAAGLTIuMDA2AQgAAAAFAAAAATEBAAAACy0xOTM0MjQzNjczAwAAAAMxNjACAAAAAjgyBAAAAAEwBwAAAAgyLzIvMjAyNggAAAAJNS8zMS8yMDIzCQAAAAEwN9/5V2ti3giOklFYa2LeCBpDSVEuQVBMRC5JUV9EQV9DRi5MVE0xMjAyNgEAAACZYDYAAgAAAAY2Ny44MjYBCAAAAAUAAAABMQEAAAALLTE5MjIwMDE2MzYDAAAAAzE2MAIAAAAEMjE2MAQAAAABMAcAAAAIMi8yLzIwMjYIAAAACTgvMzEvMjAyNQkAAAABMDff+VdrYt4IjpJRWGti3ggYQ0lRLkFQTEQuSVFfQ09HUy5GUTEyMDI1AQAAAJlgNgACAAAABjIyLjc0MwEI | AJ1: AAAABQAAAAExAQAAAAstMTkyMjAwMjM5MQMAAAADMTYwAgAAAAIzNAQAAAABMAcAAAAIMi8yLzIwMjYIAAAACTgvMzEvMjAyNAkAAAABMDff+VdrYt4IjpJRWGti3ggZQ0lRLkVRSVguSVFfRUJJVC5MVE0zMjAyNQEAAAAqbgAAAgAAAAQxODc5AQgAAAAFAAAAATEBAAAACy0xOTE5ODE0OTY1AwAAAAMxNjACAAAAAzQwMAQAAAABMAcAAAAIMi8yLzIwMjYIAAAACTkvMzAvMjAyNQkAAAABMDff+VdrYt4ITnFHWGti3ggWQ0lRLkRMUi5JUV9OSS5MVE0zMjAyNQEAAABEfKgAAgAAAAgxMzk5LjUxMQEIAAAABQAAAAExAQAAAAstMTkxOTEzNjkxNgMAAAADMTYwAgAAAAIxNQQAAAABMAcAAAAIMi8yLzIwMjYIAAAACTkvMzAvMjAyNQkAAAABMDff+VdrYt4Iyb9HWGti3gghQ0lRLklSRU4uSVFfQkFTSUNfRVBTX0lOQ0wuRlkyMDI1AQAAABeYGCoCAAAACDAuNDA1MTU1AQgAAAAFAAAAATEBAAAACy0xOTI3MjE0NDI0AwAAAAMxNjACAAAAATkEAAAAATAHAAAACDIvMi8yMDI2CAAAAAk2LzMwLzIwMjUJAAAAATA33/lXa2LeCMm/R1hrYt4IFkNJUS5IVVQuSVFfR1AuTFRNMzIwMjUBAAAAgug6ZAIAAAAFODUuMjQBCAAAAAUAAAABMQEAAAALLTE5MTg1NzYyOTADAAAAAzE2MAIAAAACMTAEAAAAATAHAAAACDIvMi8yMDI2CAAAAAk5LzMwLzIwMjUJAAAAATA33/lXa2LeCMm/R1hrYt4IFUNJUS5ISVZFLklRX0dQ | AK1: LkZZMjAyNAEAAADZdDAAAgAAAAYzNy41MjIBCAAAAAUAAAABMQEAAAALLTE5MzcyMjQ4NTgDAAAAAzE2MAIAAAACMTAEAAAAATAHAAAACDIvMi8yMDI2CAAAAAkzLzMxLzIwMjQJAAAAATA33/lXa2LeCMm/R1hrYt4IJ0NJUS5BUExELklRX0NIQU5HRV9ERUZfVEFYX1RPVEFMLkZZMjAyMwEAAACZYDYAAgAAAAUtMC41NAEIAAAABQAAAAExAQAAAAstMTkzNDI0MzY3MwMAAAADMTYwAgAAAAUzMDkyNAQAAAABMAcAAAAIMi8yLzIwMjYIAAAACTUvMzEvMjAyMwkAAAABMDff+VdrYt4Iyb9HWGti3ggYQ0lRLkFQTEQuSVFfQ09HUy5GUTEyMDI2AQAAAJlgNgACAAAABjU1LjYwNgEIAAAABQAAAAExAQAAAAstMTkyMjAwMjM4MgMAAAADMTYwAgAAAAIzNAQAAAABMAcAAAAIMi8yLzIwMjYIAAAACTgvMzEvMjAyNQkAAAABMDff+VdrYt4Iyb9HWGti3ggdQ0lRLkFQTEQuSVFfVE9UQUxfUkVWLkZRMTIwMjUBAAAAmWA2AAIAAAAGMzQuODQ5AQgAAAAFAAAAATEBAAAACy0xOTIyMDAyMzkxAwAAAAMxNjACAAAAAjI4BAAAAAEwBwAAAAgyLzIvMjAyNggAAAAJOC8zMS8yMDI0CQAAAAEwN9/5V2ti3gjJv0dYa2LeCBlDSVEuVk5PLklRX0VQU19FU1QuRlkyMDI3AQAAAEjFBAACAAAABS0wLjA1AQ4AAAAFAAAAATMBAAAABzI2NjMwMDICAAAACjEwMDI1Mjg4NzYDAAAABjEwMDI3OAQAAAABMgYAAAABMAcAAAADMTYw | AL1: CAAAAAEwCQAAAAExCgAAAAEwCwAAAAsxNDYzOTA2NDA2NwwAAAABMQ0AAAAIMi8zLzIwMjYQAAAACDIvMi8yMDI2N9/5V2ti3ggNG0dYa2LeCB1DSVEuVk5PLklRX1JFVkVOVUVfRVNULkZZMjAyNgEAAABIxQQAAgAAAAoxODEzLjY0MTc1AQ4AAAAFAAAAATMBAAAAATACAAAACjEwMDI1Mjg4NzUDAAAABjEwMDE4MAQAAAABMgYAAAABMAcAAAADMTYwCAAAAAEwCQAAAAExCgAAAAEwCwAAAAsxNDYzNzI3NjU1NwwAAAABMQ0AAAAIMi8zLzIwMjYQAAAACDIvMi8yMDI2N9/5V2ti3gjJv0dYa2LeCBpDSVEuQ0xTSy5JUV9FUFNfRVNULkZZMjAyNwEAAAAO4gkDAgAAAAUwLjkzNQEOAAAABQAAAAEzAQAAAAg2MTUzMTM4OQIAAAAKMTAwNDQ4NjA3OAMAAAAGMTAwMjc4BAAAAAEyBgAAAAEwBwAAAAMxNjAIAAAAATAJAAAAATEKAAAAATALAAAACzE0NjM2NzU5MTA1DAAAAAExDQAAAAgyLzMvMjAyNhAAAAAIMi8yLzIwMjY33/lXa2LeCMm/R1hrYt4IGkNJUS5JUkVOLklRX0VQU19FU1QuRlkyMDI3AQAAABeYGCoCAAAABzEuMDU5NjkBDgAAAAUAAAABMwEAAAAKMTY4NjI2NDA5NgIAAAAKMTAwNTU3NTI4NAMAAAAGMTAwMjc4BAAAAAEyBgAAAAEwBwAAAAMxNjAIAAAAATAJAAAAATEKAAAAATALAAAACzE0NjMzNjgxODM1DAAAAAExDQAAAAgyLzMvMjAyNhAAAAAIMi8yLzIwMjY33/lXa2LeCMm/R1hrYt4IGkNJ | AM1: US5SSU9ULklRX0VQU19FU1QuRlkyMDI3AQAAAEZkFwACAAAACC0wLjU4MjE3AQ4AAAAFAAAAATMBAAAABzQyNzY3NzcCAAAACjEwMDA0NjY2MDgDAAAABjEwMDI3OAQAAAABMgYAAAABMAcAAAADMTYwCAAAAAEwCQAAAAExCgAAAAEwCwAAAAsxNDYzMzcyNjU3NwwAAAABMQ0AAAAIMi8zLzIwMjYQAAAACDIvMi8yMDI2N9/5V2ti3gi69klYa2LeCBhDSVEuTUFSQS5JUV9FUFNfRVNULjYwMDABAAAA2MxwCQIAAAAHLTAuNTgxNgEOAAAABQAAAAIxMQEAAAAJMTYyNzUxMjQ2AgAAAAc0OTk4Njk0AwAAAAYxMDAyNzgEAAAAATIGAAAAATAHAAAAAzE2MAgAAAABMAkAAAABMQoAAAABMAsAAAALMTQ2MTczOTg1MTMMAAAAAjEyDQAAAAgyLzMvMjAyNhAAAAAIMi8yLzIwMjY33/lXa2LeCLr2SVhrYt4IHkNJUS5FUUlYLklRX1JFVkVOVUVfRVNULkZZMjAyNgEAAAAqbgAAAgAAAAsxMDA3NC4yOTk0MQEOAAAABQAAAAEzAQAAAAEwAgAAAAoxMDAyMjkzNTg1AwAAAAYxMDAxODAEAAAAATIGAAAAATAHAAAAAzE2MAgAAAABMAkAAAABMQoAAAABMAsAAAALMTQ2MzY3NTEzNzkMAAAAATENAAAACDIvMy8yMDI2EAAAAAgyLzIvMjAyNjff+VdrYt4IxgxOWGti3ggaQ0lRLkNMU0suSVFfRVBTX0VTVC5GWTIwMjYBAAAADuIJAwIAAAAHMC43MjY2NwEOAAAABQAAAAEzAQAAAAg2MTUzMTM4OQIAAAAKMTAwNDQ4NjA3MwMA | AN1: AAAGMTAwMjc4BAAAAAEyBgAAAAEwBwAAAAMxNjAIAAAAATAJAAAAATEKAAAAATALAAAACzE0NjM2NzU5NDI5DAAAAAExDQAAAAgyLzMvMjAyNhAAAAAIMi8yLzIwMjY33/lXa2LeCPGBS1hrYt4IHENJUS5WTk8uSVFfRUJJVERBX0VTVC5GWTIwMjYBAAAASMUEAAIAAAAJNjk4Ljc2Mzc4AQ4AAAAFAAAAATMBAAAAATACAAAACjEwMDI1Mjg4NzUDAAAABjEwMDE4NwQAAAABMgYAAAABMAcAAAADMTYwCAAAAAEwCQAAAAExCgAAAAEwCwAAAAsxNDYzNzI3NjQ5NwwAAAABMQ0AAAAIMi8zLzIwMjYQAAAACDIvMi8yMDI2N9/5V2ti3gjGDE5Ya2LeCB1DSVEuRExSLklRX1JFVkVOVUVfRVNULkZZMjAyNgEAAABEfKgAAgAAAAo2NzMyLjM1MTM1AQ4AAAAFAAAAATMBAAAAATACAAAACjEwMDIzMTcwNjADAAAABjEwMDE4MAQAAAABMgYAAAABMAcAAAADMTYwCAAAAAEwCQAAAAExCgAAAAEwCwAAAAsxNDYzOTM4ODg2NgwAAAABMQ0AAAAIMi8zLzIwMjYQAAAACDIvMi8yMDI2N9/5V2ti3ghfekxYa2LeCB5DSVEuSElWRS5JUV9SRVZFTlVFX0VTVC5GWTIwMjUBAAAA2XQwAAIAAAAJMTE1Ljk3ODYyAQ4AAAAFAAAAATMBAAAAATACAAAACjEwMDM5NzY3NDcDAAAABjEwMDE4MAQAAAABMwYAAAABMAcAAAADMTYwCAAAAAEwCQAAAAExCgAAAAEwCwAAAAsxNDM1MjQ1NjgxMQwAAAABMQ0AAAAIMi8zLzIwMjYQAAAACTMv | AO1: MzEvMjAyNTff+VdrYt4IX3pMWGti3ggdQ0lRLkJJVEYuSVFfRUJJVERBX0VTVC5GWTIwMjUBAAAAFd2VIAIAAAAINjQuNDcxNzUBDgAAAAUAAAABMwEAAAABMAIAAAAKMTAwNDk3MzYzMwMAAAAGMTAwMTg3BAAAAAEzBgAAAAEwBwAAAAMxNjAIAAAAATAJAAAAATEKAAAAATALAAAACzE0NjM2OTAyNTYxDAAAAAExDQAAAAgyLzMvMjAyNhAAAAAKMTIvMzEvMjAyNTff+VdrYt4IX3pMWGti3ggeQ0lRLkJJVEYuSVFfUkVWRU5VRV9FU1QuRlkyMDI1AQAAABXdlSACAAAABzI3Ni41NTUBDgAAAAUAAAABMwEAAAABMAIAAAAKMTAwNDk3MzYzMwMAAAAGMTAwMTgwBAAAAAEzBgAAAAEwBwAAAAMxNjAIAAAAATAJAAAAATEKAAAAATALAAAACzE0NjM2OTAyNTg1DAAAAAExDQAAAAgyLzMvMjAyNhAAAAAKMTIvMzEvMjAyNTff+VdrYt4Iyb9HWGti3ggdQ0lRLkJUQlQuSVFfRUJJVERBX0VTVC5GWTIwMjYBAAAAV8JCIAIAAAAIODYuMDE2ODcBDgAAAAUAAAABMwEAAAABMAIAAAAKMTAwNTI4Mjg2MgMAAAAGMTAwMTg3BAAAAAEyBgAAAAEwBwAAAAMxNjAIAAAAATAJAAAAATEKAAAAATALAAAACzE0NjEyMjk1MDgwDAAAAAExDQAAAAgyLzMvMjAyNhAAAAAIMi8yLzIwMjY33/lXa2LeCPGBS1hrYt4IHkNJUS5CVEJULklRX1JFVkVOVUVfRVNULkZZMjAyNgEAAABXwkIgAgAAAAkyMTMuMDc2NzUBDgAAAAUAAAABMwEA | AP1: AAABMAIAAAAKMTAwNTI4Mjg2MgMAAAAGMTAwMTgwBAAAAAEyBgAAAAEwBwAAAAMxNjAIAAAAATAJAAAAATEKAAAAATALAAAACzE0NjEyMjk0ODgwDAAAAAExDQAAAAgyLzMvMjAyNhAAAAAIMi8yLzIwMjY33/lXa2LeCMm/R1hrYt4IGkNJUS5FUUlYLklRX0VQU19FU1QuRlkyMDI2AQAAACpuAAACAAAACDE1LjEyMjI2AQ4AAAAFAAAAATMBAAAACTI4MzQ1NDMwNAIAAAAKMTAwMjI5MzU4NQMAAAAGMTAwMjc4BAAAAAEyBgAAAAEwBwAAAAMxNjAIAAAAATAJAAAAATEKAAAAATALAAAACzE0NjM2NzUxNjU1DAAAAAExDQAAAAgyLzMvMjAyNhAAAAAIMi8yLzIwMjY33/lXa2LeCMYMTlhrYt4IGkNJUS5CVEJULklRX0VQU19FU1QuRlkyMDI0AQAAAFfCQiACAAAABy0wLjA2NzUBDgAAAAUAAAABMwEAAAAJNTU1NzQ0MjQyAgAAAAoxMDA1MjgyODYwAwAAAAYxMDAyNzgEAAAAATIGAAAAATAHAAAAAzE2MAgAAAABMAkAAAABMQoAAAABMAsAAAALMTQwOTUxNTA2MTgMAAAAATENAAAACDIvMy8yMDI2EAAAAAoxMi8zMS8yMDI0N9/5V2ti3ghODk9Ya2LeCB1DSVEuQ09SWi5JUV9FQklUREFfRVNULkZZMjAyNgEAAAA7lFIiAgAAAAkzMjkuMDIwNzEBDgAAAAUAAAABMwEAAAABMAIAAAAKMTAwNTUyMTM3NwMAAAAGMTAwMTg3BAAAAAEyBgAAAAEwBwAAAAMxNjAIAAAAATAJAAAAATEKAAAAATALAAAACzE0NjM0MDgy | AQ1: Nzk2DAAAAAExDQAAAAgyLzMvMjAyNhAAAAAIMi8yLzIwMjY33/lXa2LeCE4OT1hrYt4IHkNJUS5DT1JaLklRX1JFVkVOVUVfRVNULkZZMjAyNgEAAAA7lFIiAgAAAAk3NzAuNjI4NTMBDgAAAAUAAAABMwEAAAABMAIAAAAKMTAwNTUyMTM3NwMAAAAGMTAwMTgwBAAAAAEyBgAAAAEwBwAAAAMxNjAIAAAAATAJAAAAATEKAAAAATALAAAACzE0NjM0MDgzMDE4DAAAAAExDQAAAAgyLzMvMjAyNhAAAAAIMi8yLzIwMjY33/lXa2LeCE4OT1hrYt4IGkNJUS5JUkVOLklRX0VQU19FU1QuRlkyMDI2AQAAABeYGCoCAAAABzEuMDU2MzUBDgAAAAUAAAABMwEAAAAKMTY4NjI2NDA5NgIAAAAKMTAwNTU3NTI4MwMAAAAGMTAwMjc4BAAAAAEyBgAAAAEwBwAAAAMxNjAIAAAAATAJAAAAATEKAAAAATALAAAACzE0NjMzNjgxODY2DAAAAAExDQAAAAgyLzMvMjAyNhAAAAAIMi8yLzIwMjY33/lXa2LeCMm/R1hrYt4IGkNJUS5SSU9ULklRX0VQU19FU1QuRlkyMDI2AQAAAEZkFwACAAAACC0wLjQ3NTUzAQ4AAAAFAAAAATMBAAAABzQyNzY3NzcCAAAACjEwMDA0NjY2MDcDAAAABjEwMDI3OAQAAAABMgYAAAABMAcAAAADMTYwCAAAAAEwCQAAAAExCgAAAAEwCwAAAAsxNDYzMzcyNjIwMwwAAAABMQ0AAAAIMi8zLzIwMjYQAAAACDIvMi8yMDI2N9/5V2ti3gjJv0dYa2LeCBlDSVEuVk5PLklRX0VQU19FU1QuRlkyMDI2AQAAAEjF | AR1: BAACAAAABi0wLjE4NQEOAAAABQAAAAEzAQAAAAcyNjYzMDAyAgAAAAoxMDAyNTI4ODc1AwAAAAYxMDAyNzgEAAAAATIGAAAAATAHAAAAAzE2MAgAAAABMAkAAAABMQoAAAABMAsAAAALMTQ2MzcyNzY3MjUMAAAAATENAAAACDIvMy8yMDI2EAAAAAgyLzIvMjAyNjff+VdrYt4ITg5PWGti3ggaQ0lRLkVRSVguSVFfRVBTX0VTVC5GWTIwMjcBAAAAKm4AAAIAAAAIMTYuNDY1MjQBDgAAAAUAAAABMwEAAAAJMjgzNDU0MzA0AgAAAAoxMDAyMjkzNTg2AwAAAAYxMDAyNzgEAAAAATIGAAAAATAHAAAAAzE2MAgAAAABMAkAAAABMQoAAAABMAsAAAALMTQ2MzY3NTE1ODMMAAAAATENAAAACDIvMy8yMDI2EAAAAAgyLzIvMjAyNjff+VdrYt4ITg5PWGti3ggZQ0lRLkRMUi5JUV9FUFNfRVNULkZZMjAyNgEAAABEfKgAAgAAAAcxLjU5ODMzAQ4AAAAFAAAAATMBAAAACDEyNDE2OTY0AgAAAAoxMDAyMzE3MDYwAwAAAAYxMDAyNzgEAAAAATIGAAAAATAHAAAAAzE2MAgAAAABMAkAAAABMQoAAAABMAsAAAALMTQ2Mzk4NTE2MDIMAAAAATENAAAACDIvMy8yMDI2EAAAAAgyLzIvMjAyNjff+VdrYt4ITg5PWGti3ggeQ0lRLldVTEYuSVFfUkVWRU5VRV9FU1QuRlkyMDI2AQAAABJEqGMCAAAACTQwMC41OTUxOAEOAAAABQAAAAEzAQAAAAEwAgAAAAoxMDA2MDMwNzMyAwAAAAYxMDAxODAEAAAAATIGAAAAATAHAAAAAzE2MAgA | AS1: AAABMAkAAAABMQoAAAABMAsAAAALMTQ2MzMzODU5NzgMAAAAATENAAAACDIvMy8yMDI2EAAAAAgyLzIvMjAyNjff+VdrYt4IjpJRWGti3ggcQ0lRLk1BUkEuSVFfUkVWRU5VRV9FU1QuNjAwMAEAAADYzHAJAgAAAAkxMDU1LjA3NDUBDgAAAAUAAAACMTEBAAAAATACAAAABzQ5OTg2OTQDAAAABjEwMDE4MAQAAAABMgYAAAABMAcAAAADMTYwCAAAAAEwCQAAAAExCgAAAAEwCwAAAAsxNDYxNzM5ODQ4OQwAAAACMTINAAAACDIvMy8yMDI2EAAAAAgyLzIvMjAyNjff+VdrYt4ITg5PWGti3ggdQ0lRLkhJVkUuSVFfRUJJVERBX0VTVC5GWTIwMjUBAAAA2XQwAAIAAAAINDEuMTM4MjkBDgAAAAUAAAABMwEAAAABMAIAAAAKMTAwMzk3Njc0NwMAAAAGMTAwMTg3BAAAAAEzBgAAAAEwBwAAAAMxNjAIAAAAATAJAAAAATEKAAAAATALAAAACzE0MzUyNDc5MzI3DAAAAAExDQAAAAgyLzMvMjAyNhAAAAAJMy8zMS8yMDI1N9/5V2ti3ghODk9Ya2LeCBpDSVEuQlRCVC5JUV9FUFNfRVNULkZZMjAyNgEAAABXwkIgAgAAAAYwLjAxMjUBDgAAAAUAAAABMwEAAAAJNTU1NzQ0MjQyAgAAAAoxMDA1MjgyODYyAwAAAAYxMDAyNzgEAAAAATIGAAAAATAHAAAAAzE2MAgAAAABMAkAAAABMQoAAAABMAsAAAALMTQ2MTIyOTQ5MjgMAAAAATENAAAACDIvMy8yMDI2EAAAAAgyLzIvMjAyNjff+VdrYt4ITg5PWGti3ggZQ0lRLkRMUi5J | AT1: UV9FUFNfRVNULkZZMjAyNwEAAABEfKgAAgAAAAcyLjEzMDUyAQ4AAAAFAAAAATMBAAAACDEyNDE2OTY0AgAAAAoxMDAyMzE3MDYxAwAAAAYxMDAyNzgEAAAAATIGAAAAATAHAAAAAzE2MAgAAAABMAkAAAABMQoAAAABMAsAAAALMTQ2MzY2OTIxOTkMAAAAATENAAAACDIvMy8yMDI2EAAAAAgyLzIvMjAyNjff+VdrYt4ITg5PWGti3ggdQ0lRLklSRU4uSVFfRUJJVERBX0VTVC5GWTIwMjYBAAAAF5gYKgIAAAAJNjgwLjg1NDE1AQ4AAAAFAAAAATMBAAAAATACAAAACjEwMDU1NzUyODMDAAAABjEwMDE4NwQAAAABMgYAAAABMAcAAAADMTYwCAAAAAEwCQAAAAExCgAAAAEwCwAAAAsxNDYzMzY3MzY0OQwAAAABMQ0AAAAIMi8zLzIwMjYQAAAACDIvMi8yMDI2N9/5V2ti3gjel1BYa2LeCB5DSVEuSVJFTi5JUV9SRVZFTlVFX0VTVC5GWTIwMjYBAAAAF5gYKgIAAAAKMTE0OC4wNzUyMwEOAAAABQAAAAEzAQAAAAEwAgAAAAoxMDA1NTc1MjgzAwAAAAYxMDAxODAEAAAAATIGAAAAATAHAAAAAzE2MAgAAAABMAkAAAABMQoAAAABMAsAAAALMTQ2MzM2NzM4NTkMAAAAATENAAAACDIvMy8yMDI2EAAAAAgyLzIvMjAyNjff+VdrYt4I3pdQWGti3ggdQ0lRLlJJT1QuSVFfRUJJVERBX0VTVC5GWTIwMjYBAAAARmQXAAIAAAAJMzA1LjUxNDEyAQ4AAAAFAAAAATMBAAAAATACAAAACjEwMDA0NjY2MDcDAAAABjEwMDE4NwQA | AU1: AAABMgYAAAABMAcAAAADMTYwCAAAAAEwCQAAAAExCgAAAAEwCwAAAAsxNDYzMzM5NTAwMQwAAAABMQ0AAAAIMi8zLzIwMjYQAAAACDIvMi8yMDI2N9/5V2ti3gjel1BYa2LeCB5DSVEuUklPVC5JUV9SRVZFTlVFX0VTVC5GWTIwMjYBAAAARmQXAAIAAAAJNzQ4LjQzMjgxAQ4AAAAFAAAAATMBAAAAATACAAAACjEwMDA0NjY2MDcDAAAABjEwMDE4MAQAAAABMgYAAAABMAcAAAADMTYwCAAAAAEwCQAAAAExCgAAAAEwCwAAAAsxNDYzMzM5NTAyMQwAAAABMQ0AAAAIMi8zLzIwMjYQAAAACDIvMi8yMDI2N9/5V2ti3gjel1BYa2LeCBpDSVEuSElWRS5JUV9FUFNfRVNULkZZMjAyNQEAAADZdDAAAgAAAAYtMC4yMjEBDgAAAAUAAAABMwEAAAAHMjYzOTE2OQIAAAAKMTAwMzk3Njc0NwMAAAAGMTAwMjc4BAAAAAEzBgAAAAEwBwAAAAIyNwgAAAABMAkAAAABMQoAAAABMAsAAAALMTQzNTI0NzkzOTMMAAAAATENAAAACDIvMy8yMDI2EAAAAAkzLzMxLzIwMjU33/lXa2LeCE4OT1hrYt4IGkNJUS5CSVRGLklRX0VQU19FU1QuRlkyMDI1AQAAABXdlSACAAAABi0wLjI1NQEOAAAABQAAAAEzAQAAAAk2MjgyNzQ3MzMCAAAACjEwMDQ5NzM2MzMDAAAABjEwMDI3OAQAAAABMwYAAAABMAcAAAADMTYwCAAAAAEwCQAAAAExCgAAAAEwCwAAAAsxNDYzNjkwMzEzMQwAAAABMQ0AAAAIMi8zLzIwMjYQAAAACjEyLzMxLzIwMjU3 | AV1: 3/lXa2LeCI6SUVhrYt4IGkNJUS5CVEJULklRX0VQU19FU1QuRlkyMDI1AQAAAFfCQiACAAAABjAuMzQyNQEOAAAABQAAAAEzAQAAAAk1NTU3NDQyNDICAAAACjEwMDUyODI4NjEDAAAABjEwMDI3OAQAAAABMgYAAAABMAcAAAADMTYwCAAAAAEwCQAAAAExCgAAAAEwCwAAAAsxNDYxMjI5NDkxNgwAAAABMQ0AAAAIMi8zLzIwMjYQAAAACjEyLzMxLzIwMjU33/lXa2LeCE4OT1hrYt4IGkNJUS5DT1JaLklRX0VQU19FU1QuRlkyMDI0AQAAADuUUiICAAAACC0zLjk5OTI0AQ4AAAAFAAAAATMBAAAACjE4NjM0ODc0MzMCAAAACjEwMDUzMDM1NDkDAAAABjEwMDI3OAQAAAABMgYAAAABMAcAAAADMTYwCAAAAAEwCQAAAAExCgAAAAEwCwAAAAsxNDE1NzgxOTg5MQwAAAABMQ0AAAAIMi8zLzIwMjYQAAAACjEyLzMxLzIwMjQ33/lXa2LeCI6SUVhrYt4IHUNJUS5DTFNLLklRX0VCSVREQV9FU1QuRlkyMDI2AQAAAA7iCQMCAAAABjMyNy40NQEOAAAABQAAAAEzAQAAAAEwAgAAAAoxMDA0NDg2MDczAwAAAAYxMDAxODcEAAAAATIGAAAAATAHAAAAAzE2MAgAAAABMAkAAAABMQoAAAABMAsAAAALMTQ2MzMzMTQ4MzMMAAAAATENAAAACDIvMy8yMDI2EAAAAAgyLzIvMjAyNjff+VdrYt4I8YFLWGti3ggeQ0lRLkNMU0suSVFfUkVWRU5VRV9FU1QuRlkyMDI2AQAAAA7iCQMCAAAACTgwNS43OTE0MgEOAAAABQAAAAEzAQAA | AW1: AAEwAgAAAAoxMDA0NDg2MDczAwAAAAYxMDAxODAEAAAAATIGAAAAATAHAAAAAzE2MAgAAAABMAkAAAABMQoAAAABMAsAAAALMTQ2MzMzMTQ4NTcMAAAAATENAAAACDIvMy8yMDI2EAAAAAgyLzIvMjAyNjff+VdrYt4IjpJRWGti3ggaQ0lRLldVTEYuSVFfRVBTX0VTVC5GWTIwMjYBAAAAEkSoYwIAAAAHLTAuNTI3NQEOAAAABQAAAAEzAQAAAAoxNzU4ODk4MjI3AgAAAAoxMDA2MDMwNzMyAwAAAAYxMDAyNzgEAAAAATIGAAAAATAHAAAAAzE2MAgAAAABMAkAAAABMQoAAAABMAsAAAALMTQ2MDI5Nzc5NDIMAAAAATENAAAACDIvMy8yMDI2EAAAAAgyLzIvMjAyNjff+VdrYt4Iyb9HWGti3ggbQ0lRLk1BUkEuSVFfRUJJVERBX0VTVC42MDAwAQAAANjMcAkCAAAACDQzNi44OTcyAQ4AAAAFAAAAAjExAQAAAAEwAgAAAAc0OTk4Njk0AwAAAAYxMDAxODcEAAAAATIGAAAAATAHAAAAAzE2MAgAAAABMAkAAAABMQoAAAABMAsAAAALMTQ2MTczOTg0OTMMAAAAAjEyDQAAAAgyLzMvMjAyNhAAAAAIMi8yLzIwMjY33/lXa2LeCI6SUVhrYt4IGkNJUS5ISVZFLklRX0VQU19FU1QuRlkyMDI2AQAAANl0MAACAAAACC0wLjA4NzQzAQ4AAAAFAAAAATMBAAAABzI2MzkxNjkCAAAACjEwMDM5NzY3NTQDAAAABjEwMDI3OAQAAAABMwYAAAABMAcAAAACMjcIAAAAATAJAAAAATEKAAAAATALAAAACzE0NjM2NDc1NzEzDAAAAAEx | AX1: DQAAAAgyLzMvMjAyNhAAAAAIMi8yLzIwMjY33/lXa2LeCI6SUVhrYt4IGkNJUS5CSVRGLklRX0VQU19FU1QuRlkyMDI2AQAAABXdlSACAAAABi0wLjE1NgEOAAAABQAAAAEzAQAAAAk2MjgyNzQ3MzMCAAAACjEwMDQ5NzM2MzQDAAAABjEwMDI3OAQAAAABMwYAAAABMAcAAAADMTYwCAAAAAEwCQAAAAExCgAAAAEwCwAAAAsxNDYzNjkwMzA4MwwAAAABMQ0AAAAIMi8zLzIwMjYQAAAACDIvMi8yMDI2N9/5V2ti3giOklFYa2LeCBpDSVEuV1VMRi5JUV9FUFNfRVNULkZZMjAyNwEAAAASRKhjAgAAAAMwLjIBDgAAAAUAAAABMwEAAAAKMTc1ODg5ODIyNwIAAAAKMTAwNjE0OTIzMQMAAAAGMTAwMjc4BAAAAAEyBgAAAAEwBwAAAAMxNjAIAAAAATAJAAAAATEKAAAAATALAAAACzE0NTk4NDIyMjI1DAAAAAExDQAAAAgyLzMvMjAyNhAAAAAIMi8yLzIwMjY33/lXa2LeCMm/R1hrYt4IGkNJUS5NQVJBLklRX0VQU19FU1QuRlkyMDI3AQAAANjMcAkCAAAABzAuNzcwODUBDgAAAAUAAAABMwEAAAAJMTYyNzUxMjQ2AgAAAAoxMDA1MTM2ODE1AwAAAAYxMDAyNzgEAAAAATIGAAAAATAHAAAAAzE2MAgAAAABMAkAAAABMQoAAAABMAsAAAALMTQ2MTczOTgyNzQMAAAAATENAAAACDIvMy8yMDI2EAAAAAgyLzIvMjAyNjff+VdrYt4Iyb9HWGti3gg=

Sheet Comps
F1: 1000000
F2: Market Valuation | I2: LTM Financial Statistics | O2: LTM Profitability Margins | T2: Growth Rates | AD2: General | AF2: Return On Investment | AK2: LTM Leverage Ratios | AO2: LTM Coverage Ratios | AS2: Credit Ratings
T3: Sales | V3: EBITDA | X3: EPS
B4: Company | E4: Ticker | F4: Equity Value | G4: Enterprise Value | I4: Sales | J4: Gross Profit | K4: EBITDA (adj.) | L4: EBIT | M4: Net Income | O4: Gross Profit (%) | P4: EBITDA (%) | Q4: EBIT(%) | R4: Net Income (%) | T4: Hist. 1 year | U4: Est 1-year | V4: Hist 1. Year | W4: Est 1-year | X4: Current | Y4: Hist 1-year. | Z4: Est. 1-year | AA4: Est. LT | AD4: Predicted Beta | AF4: ROIC | AG4: ROE | AH4: ROA | AI4: Implied Div. Yield | AK4: Debt/Total Cap. | AL4: Debt/EBITDA | AM4: Net Debt / EBITDA | AO4: EBITDA/Int. Exp. | AP4: EBITDA -Cpx/Int. | AQ4: EBIT/Int Exp. | AS4: Moody's | AT4: S&P | AU4: Fitch
B5: Applied Digital Corporation | E5: APLD | F5: =((Main!F23)/1000000) -> 9050.6048 | G5: =((Main!F29))/1000000 -> 9916.4418 | I5: =(Main!G123*1000)/1000000 -> 173.56 | J5: =Main!G127/1000 -> 39.246 | K5: =_xll.ciqfunctions.udf.CIQ($E$5, "IQ_EBITDA", "LTM12026") -> 5.848 | L5: =Main!G131/1000 -> -129.804 | M5: =Main!G135/1000 -> -112.656 | O5: =Main!G128 -> 0.22612353 | P5: =K5/I5 -> 0.0336944 | Q5: =L5/I5 -> -0.74789122 | R5: =M5/I5 -> -0.64908965 | T5: =Main!G124 -> 0.76725654 | U5: 0.7129 | V5: =Main!G141 -> -0.67746134 | W5: =60.66/K5-1 -> 9.372777 | Y5: =(Main!G138+1.17)/-1.17 -> -0.57748923 | Z5: =(Z7/Main!G138)-1 -> -0.089690935 | AA5: NA | AD5: =_xll.ciqfunctions.udf.CIQ($E$5, "IQ_BETA_2YR") -> 3.1248 | AF5: ='Investment ratios'!F3 -> -0.197087 | AG5: ='Investment ratios'!F4 -> -0.287557 | AH5: ='Investment ratios'!F5 -> -5.2777586e-05 | AI5: ='Investment ratios'!F6 -> 23.109377 | AK5: ='Investment ratios'!F9 -> 0.2689887 | AL5: ='Investment ratios'!F10 -> -4.0122449 | AM5: ='Investment ratios'!F11 -> -3.1469388 | AO5: ='Investment ratios'!F14 -> -10.02924 | AP5: ='Investment ratios'!F15 -> -61.269006 | AQ5: ='Investment ratios'!F16 -> -7.5438596
B6: Values | X6: -0.0087 | Y6: -1.17857 | Z6: -0.45 | AA6: -0.26833
Y7: -1.17857 | Z7: -0.45 | AA7: -0.26833
B8: Tier 1: Direct operating competitors | AD8: Tier 1: Direct operating competitors
B10: Core Scientific | E10: CORZ | F10: 5563.19 | G10: 6103.5 | I10: =_xll.ciqfunctions.udf.CIQ(E10, "IQ_TOTAL_REV", "LTM32025") -> 334.181 | J10: =_xll.ciqfunctions.udf.CIQ(E10, "IQ_GP", "LTM32025") -> 34.135 | K10: =_xll.ciqfunctions.udf.CIQ(E10, "IQ_EBITDA_EQ_INC", "LTM32025") -> -54.055 | L10: =_xll.ciqfunctions.udf.CIQ(E10, "IQ_EBIT", "LTM32025") -> -156.084 | M10: =_xll.ciqfunctions.udf.CIQ(E10, "IQ_NI", "LTM32025") -> -768.307 | O10: =J10/I10 -> 0.10214524 | P10: =K10/I10 -> -0.16175366 | Q10: =L10/I10 -> -0.46706426 | R10: =M10/I10 -> -2.2990745 | T10: =(I10/T11)-1 -> -0.40076137 | U10: =(U11/I10)-1 -> 1.3060214 | V10: =(K10/V11)-1 -> -1.3576296 | W10: =-(W11/K10)-1 -> 5.0867766 | Y10: -0.6056 | Z10: 0.9565 | AA10: 0.3334 | AD10: =_xll.ciqfunctions.udf.CIQ($E$10, "IQ_BETA_2YR") -> 2.94149
B11: Values | T11: =_xll.ciqfunctions.udf.CIQ(E10, "IQ_TOTAL_REV", "LTM32024") -> 557.676 | U11: =_xll.ciqfunctions.udf.CIQ(E10, "IQ_REVENUE_EST", "FY2026") -> 770.62853 | V11: =_xll.ciqfunctions.udf.CIQ(E10, "IQ_EBITDA", "LTM32024") -> 151.148 | W11: =_xll.ciqfunctions.udf.CIQ(E10, "IQ_EBITDA_EST", "FY2026") -> 329.02071 | X11: =_xll.ciqfunctions.udf.CIQ($E$10, "IQ_EPS_EST", "FY2024") -> -3.99924 | Y11: -2.69978 | Z11: 0.09 | AA11: 0.12
B12: Bit Digital | E12: BTBT | F12: 669.7 | G12: 739 | I12: =_xll.ciqfunctions.udf.CIQ(E12, "IQ_TOTAL_REV", "LTM32025") -> 105.70314 | J12: =_xll.ciqfunctions.udf.CIQ(E12, "IQ_GP", "LTM32025") -> 52.0349 | K12: =_xll.ciqfunctions.udf.CIQ(E12, "IQ_EBITDA", "LTM32025") -> 162.19909 | L12: =_xll.ciqfunctions.udf.CIQ(E12, "IQ_EBIT", "LTM32025") -> 128.3621 | M12: =_xll.ciqfunctions.udf.CIQ(E12, "IQ_NI", "LTM32025") -> 137.01881 | O12: =J12/I12 -> 0.49227393 | P12: =K12/I12 -> 1.5344775 | Q12: =L12/I12 -> 1.2143641 | R12: =M12/I12 -> 1.2962605 | T12: =($I$12/T13)-1 -> 0.078601158 | U12: =(U13/I12)-1 -> 1.0158034 | V12: =(K12/V13)-1 -> 5.7921628 | W12: =(W13/K12)-1 -> -0.4696834 | Y12: =(X13/Y13)-1 -> 2.0626134 | Z12: =(Z13/X13)-1 -> -6.0740741 | AA12: =(AA13/X13)-1 -> -1.1851852 | AD12: =_xll.ciqfunctions.udf.CIQ($E$12, "IQ_BETA_2YR") -> 2.34909
B13: Values | T13: =_xll.ciqfunctions.udf.CIQ(E12, "IQ_TOTAL_REV", "LTM32024") -> 98.00021 | U13: =_xll.ciqfunctions.udf.CIQ(E12, "IQ_REVENUE_EST", "FY2026") -> 213.07675 | V13: =_xll.ciqfunctions.udf.CIQ(E12, "IQ_EBITDA", "LTM32024") -> 23.88033 | W13: =_xll.ciqfunctions.udf.CIQ(E12, "IQ_EBITDA_EST", "FY2026") -> 86.01687 | X13: =_xll.ciqfunctions.udf.CIQ($E$12, "IQ_EPS_EST", "FY2024") -> -0.0675 | Y13: =_xll.ciqfunctions.udf.CIQ(E12, "IQ_BASIC_EPS_INCL", "LTM32024") -> -0.02204 | Z13: =_xll.ciqfunctions.udf.CIQ(E12, "IQ_EPS_EST", "FY2025") -> 0.3425 | AA13: =_xll.ciqfunctions.udf.CIQ(E12, "IQ_EPS_EST", "FY2026") -> 0.0125
B14: Bitfarms | E14: BITF | F14: 1514.6 | G14: 1501.2 | I14: =_xll.ciqfunctions.udf.CIQ($E$14, "IQ_TOTAL_REV", "FY2024") -> 192.881 | J14: =_xll.ciqfunctions.udf.CIQ($E$14, "IQ_GP", "FY2024") -> -32.359 | K14: =_xll.ciqfunctions.udf.CIQ($E$14, "IQ_EBITDA", "FY2024") -> 34.232 | L14: =_xll.ciqfunctions.udf.CIQ($E$14, "IQ_EBIT", "FY2024") -> -103.599 | M14: =_xll.ciqfunctions.udf.CIQ($E$14, "IQ_NI", "FY2024") -> -54.063 | O14: =J14/I14 -> -0.16776665 | P14: =K14/I14 -> 0.1774773 | Q14: =L14/I14 -> -0.53711356 | R14: =M14/I14 -> -0.28029199 | T14: =(I14/T15)-1 -> 0.31779922 | U14: =(U15/I14)-1 -> 0.43381152 | V14: =(K14/V15)-1 -> 0.64790834 | W14: =(W15/K14)-1 -> 0.88337667 | Y14: =(X15/Y15)-1 -> -0.68610362 | Z14: =(Z15/X15)-1 -> 0.95582145 | AA14: =(AA15/X15)-1 -> 0.19650253 | AD14: =_xll.ciqfunctions.udf.CIQ($E$14, "IQ_BETA_2YR") -> 2.87377
B15: Values | T15: =_xll.ciqfunctions.udf.CIQ($E$14, "IQ_TOTAL_REV", "FY2023") -> 146.366 | U15: =_xll.ciqfunctions.udf.CIQ($E$14, "IQ_REVENUE_EST", "FY2025") -> 276.555 | V15: =_xll.ciqfunctions.udf.CIQ($E$14, "IQ_EBITDA", "FY2023") -> 20.773 | W15: =_xll.ciqfunctions.udf.CIQ($E$14, "IQ_EBITDA_EST", "FY2025") -> 64.47175 | X15: =_xll.ciqfunctions.udf.CIQ($E$14, "IQ_BASIC_EPS_INCL", "FY2024") -> -0.13038 | Y15: =_xll.ciqfunctions.udf.CIQ($E$14, "IQ_BASIC_EPS_INCL", "FY2023") -> -0.41536 | Z15: =_xll.ciqfunctions.udf.CIQ($E$14, "IQ_EPS_EST", "FY2025") -> -0.255 | AA15: =_xll.ciqfunctions.udf.CIQ($E$14, "IQ_EPS_EST", "FY2026") -> -0.156
B16: HIVE Digital | E16: HIVE | F16: 684 | G16: 658.5 | I16: =_xll.ciqfunctions.udf.CIQ($E$16, "IQ_TOTAL_REV", "FY2024") -> 114.465 | J16: =_xll.ciqfunctions.udf.CIQ($E$16, "IQ_GP", "FY2024") -> 37.522 | K16: =_xll.ciqfunctions.udf.CIQ($E$16, "IQ_EBITDA", "FY2024") -> 96.723 | L16: =_xll.ciqfunctions.udf.CIQ($E$16, "IQ_EBIT", "FY2024") -> 35.305 | M16: =_xll.ciqfunctions.udf.CIQ($E$16, "IQ_NI", "FY2024") -> 26.5 | O16: =J16/I16 -> 0.32780326 | P16: =K16/I16 -> 0.84500066 | Q16: =L16/I16 -> 0.30843489 | R16: =M16/I16 -> 0.23151182 | T16: =(I16/T17)-1 -> 0.076628605 | U16: =(U17/I16)-1 -> 0.013223431 | V16: =(K16/V17)-1 -> -3.1030397 | W16: =(W17/K16)-1 -> -0.57467934 | Y16: =(X17/Y17)-1 -> -1.1032041 | Z16: =(X17/Z17)-1 -> -2.3322624 | AA16: =(AA17/X17)-1 -> -1.2969466 | AD16: =_xll.ciqfunctions.udf.CIQ($E$16, "IQ_BETA_2YR") -> 2.92244
B17: Values | T17: =_xll.ciqfunctions.udf.CIQ($E$16, "IQ_TOTAL_REV", "FY2023") -> 106.318 | U17: =_xll.ciqfunctions.udf.CIQ($E$16, "IQ_REVENUE_EST", "FY2025") -> 115.97862 | V17: =_xll.ciqfunctions.udf.CIQ($E$16, "IQ_EBITDA", "FY2023") -> -45.992 | W17: =_xll.ciqfunctions.udf.CIQ($E$16, "IQ_EBITDA_EST", "FY2025") -> 41.13829 | X17: =_xll.ciqfunctions.udf.CIQ($E$16, "IQ_BASIC_EPS_INCL", "FY2024") -> 0.29443 | Y17: =_xll.ciqfunctions.udf.CIQ($E$16, "IQ_BASIC_EPS_INCL", "FY2023") -> -2.85289 | Z17: =_xll.ciqfunctions.udf.CIQ($E$16, "IQ_EPS_EST", "FY2025") -> -0.221 | AA17: =_xll.ciqfunctions.udf.CIQ($E$16, "IQ_EPS_EST", "FY2026") -> -0.08743
B18: Hut 8 | E18: HUT | F18: 5444 | G18: 6012.7 | I18: =_xll.ciqfunctions.udf.CIQ(E18, "IQ_TOTAL_REV", "LTM32025") -> 178.318 | J18: =_xll.ciqfunctions.udf.CIQ(E18, "IQ_GP", "LTM32025") -> 85.24 | K18: =(65969-50858+41270)/1000 -> 56.381 | L18: =(65969+3325+(41279+2679)-(50858+2411))/1000 -> 59.983 | M18: =(6775-1215-6456)/1000 -> -0.896 | O18: =J18/I18 -> 0.47802241 | P18: =K18/I18 -> 0.31618233 | Q18: =L18/I18 -> 0.33638219 | R18: =M18/I18 -> -0.0050247311 | T18: =(I18/T19)-1 -> 1.5489294 | U18: =(U19/L18)-1 -> 5.518912 | V18: =(K18/V19)-1 -> -0.88753468 | W18: =(W19/K18)-1 -> 2.2161047 | X18: - | Y18: - | Z18: - | AA18: - | AD18: =_xll.ciqfunctions.udf.CIQ($E$18, "IQ_BETA_2YR") -> 2.6447
B19: Values | T19: =_xll.ciqfunctions.udf.CIQ(E18, "IQ_REV", "FY2023") -> 69.958 | U19: 391.0239 | V19: 501.319 | W19: 181.3272
B20: Mara Holdings | E20: MARA | F20: 4201.6 | G20: 7034.4 | I20: =_xll.ciqfunctions.udf.CIQ(E20, "IQ_TOTAL_REV", "LTM32025") -> 919.173 | J20: =_xll.ciqfunctions.udf.CIQ(E20, "IQ_GP", "LTM32025") -> 412.43 | K20: =_xll.ciqfunctions.udf.CIQ(E20, "IQ_EBITDA_LEASE_ADJUSTED", "LTM32025") -> 1237.818 | L20: =_xll.ciqfunctions.udf.CIQ(E20, "IQ_EBIT", "LTM32025") -> 505.056 | M20: =_xll.ciqfunctions.udf.CIQ(E20, "IQ_NI", "LTM32025") -> 926.692 | O20: =J20/I20 -> 0.44869682 | P20: =K20/I20 -> 1.3466649 | Q20: =L20/I20 -> 0.54946784 | R20: =M20/I20 -> 1.0081802 | T20: =(I20/T21)-1 -> 0.40037143 | U20: =(U21/I20)-1 -> 0.14785193 | V20: =(K20/V21)-1 -> 0.60164847 | W20: =(W21/K20)-1 -> -0.64704246 | Y20: =(X21/Y21)-1 -> -0.71606585 | Z20: =(Z21/X21)-1 -> -2.0973585 | AA20: =(AA21/Z21)-1 -> -2.3253955 | AD20: =_xll.ciqfunctions.udf.CIQ($E$20, "IQ_BETA_2YR") -> 2.39411
B21: Values | T21: =_xll.ciqfunctions.udf.CIQ($E$20, "IQ_TOTAL_REV", "FY2024") -> 656.378 | U21: =_xll.ciqfunctions.udf.CIQ($E$20, "IQ_REVENUE_EST", IQ_NTM) -> 1055.0745 | V21: =_xll.ciqfunctions.udf.CIQ($E$20, "IQ_EBITDA", "FY2024") -> 772.84 | W21: =_xll.ciqfunctions.udf.CIQ($E$20, "IQ_EBITDA_EST", IQ_NTM) -> 436.8972 | X21: 0.53 | Y21: =_xll.ciqfunctions.udf.CIQ($E$20, "IQ_BASIC_EPS_INCL", "FY2024") -> 1.86663 | Z21: =_xll.ciqfunctions.udf.CIQ($E$20, "IQ_EPS_EST", IQ_NTM) -> -0.5816 | AA21: =_xll.ciqfunctions.udf.CIQ($E$20, "IQ_EPS_EST", "FY2027") -> 0.77085
B22: Riot Platforms | E22: RIOT | F22: 6436 | G22: 6977.1 | I22: =_xll.ciqfunctions.udf.CIQ($E$22, "IQ_TOTAL_REV", "LTM32025") -> 637.162 | J22: =_xll.ciqfunctions.udf.CIQ($E$22, "IQ_GP", "LTM32025") -> 251.987 | K22: =_xll.ciqfunctions.udf.CIQ($E$22, "IQ_EBITDA_LEASE_ADJUSTED", "LTM32025") -> 515.035 | L22: =_xll.ciqfunctions.udf.CIQ($E$22, "IQ_EBIT", "LTM32025") -> 182.171 | M22: =_xll.ciqfunctions.udf.CIQ($E$22, "IQ_NI", "LTM32025") -> 164.002 | O22: =J22/I22 -> 0.39548341 | P22: =K22/I22 -> 0.80832661 | Q22: =L22/I22 -> 0.28591002 | R22: =M22/I22 -> 0.25739451 | T22: =(I22/T23)-1 -> 0.69161945 | U22: =(U23/I22)-1 -> 0.17463504 | V22: =(K22/V23)-1 -> 0.69198448 | W22: =(W23/K22)-1 -> -0.40680901 | Y22: =(X23/Y23)-1 -> -1.2270377 | Z22: =-(Z23/X23)-1 -> -6.2836667 | AA22: =-(AA23/X23)-1 -> -7.4685556 | AD22: =_xll.ciqfunctions.udf.CIQ($E$22, "IQ_BETA_2YR") -> 2.60783
B23: Values | T23: =_xll.ciqfunctions.udf.CIQ($E$22, "IQ_TOTAL_REV", "FY2024") -> 376.658 | U23: =_xll.ciqfunctions.udf.CIQ($E$22, "IQ_REVENUE_EST", "FY2026") -> 748.43281 | V23: =_xll.ciqfunctions.udf.CIQ($E$22, "IQ_EBITDA", "FY2024") -> 304.397 | W23: =_xll.ciqfunctions.udf.CIQ($E$22, "IQ_EBITDA_EST", "FY2026") -> 305.51412 | X23: -0.09 | Y23: =_xll.ciqfunctions.udf.CIQ($E$22, "IQ_BASIC_EPS_INCL", "FY2024") -> 0.39641 | Z23: =_xll.ciqfunctions.udf.CIQ($E$22, "IQ_EPS_EST", "FY2026") -> -0.47553 | AA23: =_xll.ciqfunctions.udf.CIQ($E$22, "IQ_EPS_EST", "FY2027") -> -0.58217
B24: TeraWulf | E24: WULF | F24: 5949.5 | G24: 6332.7 | I24: =_xll.ciqfunctions.udf.CIQ($E$24, "IQ_TOTAL_REV", "LTM32025") -> 167.604 | J24: =_xll.ciqfunctions.udf.CIQ($E$24, "IQ_GP", "LTM32025") -> 84.212 | K24: =_xll.ciqfunctions.udf.CIQ($E$24, "IQ_EBITDA", "LTM32025") -> -35.249 | L24: =_xll.ciqfunctions.udf.CIQ($E$24, "IQ_EBIT", "LTM32025") -> -108.355 | M24: =_xll.ciqfunctions.udf.CIQ($E$24, "IQ_NI", "LTM32025") -> -564.034 | O24: =J24/I24 -> 0.50244624 | P24: =K24/I24 -> -0.21031121 | Q24: =L24/I24 -> -0.64649412 | R24: =M24/I24 -> -3.3652777 | T24: =(I24/T25)-1 -> 0.19673547 | U24: =(U25/I24)-1 -> 1.390129 | V24: =(K24/V25)-1 -> -6.4096071 | W24: =(W25/K24)-1 -> -12.364725 | Y24: =(X25/Y25)-1 -> 6.0343958 | Z24: =(Z25/X25)-1 -> -0.6362069 | AA24: =(AA25/X25)-1 -> -1.137931 | AD24: =_xll.ciqfunctions.udf.CIQ($E$24, "IQ_BETA_2YR") -> 3.2082
B25: Values | T25: =_xll.ciqfunctions.udf.CIQ($E$24, "IQ_TOTAL_REV", "FY2024") -> 140.051 | U25: =_xll.ciqfunctions.udf.CIQ($E$24, "IQ_REVENUE_EST", "FY2026") -> 400.59518 | V25: =_xll.ciqfunctions.udf.CIQ($E$24, "IQ_EBITDA", "FY2024") -> 6.516 | W25: =_xll.ciqfunctions.udf.CIQ($E$24, "IQ_REVENUE_EST", "FY2026") -> 400.59518 | X25: -1.45 | Y25: =_xll.ciqfunctions.udf.CIQ($E$24, "IQ_BASIC_EPS_INCL", "FY2024") -> -0.20613 | Z25: =_xll.ciqfunctions.udf.CIQ($E$24, "IQ_EPS_EST", "FY2026") -> -0.5275 | AA25: =_xll.ciqfunctions.udf.CIQ($E$24, "IQ_EPS_EST", "FY2027") -> 0.2
B26: IREN Limited | E26: IREN | F26: 15260 | G26: 17296.1 | I26: =_xll.ciqfunctions.udf.CIQ($E$26, "IQ_TOTAL_REV", "LTM32025") -> 374.629 | J26: =_xll.ciqfunctions.udf.CIQ($E$26, "IQ_GP", "LTM32025") -> 254.098 | K26: =_xll.ciqfunctions.udf.CIQ($E$26, "IQ_EBITDA", "LTM32025") -> 137.151 | L26: =_xll.ciqfunctions.udf.CIQ($E$26, "IQ_EBIT", "LTM32025") -> -6.971 | M26: =_xll.ciqfunctions.udf.CIQ($E$26, "IQ_NI", "LTM32025") -> -35.632 | O26: =J26/I26 -> 0.6782657 | P26: =K26/I26 -> 0.36609819 | Q26: =L26/I26 -> -0.018607743 | R26: =M26/I26 -> -0.095112765 | T26: =(I26/T27)-1 -> 1.0013088 | U26: =(U27/I26)-1 -> 2.0645658 | V26: =(K26/V27)-1 -> 3.3941753 | W26: =(W27/K26)-1 -> 3.9642668 | AD26: =_xll.ciqfunctions.udf.CIQ($E$26, "IQ_BETA_2YR") -> 2.83849
B27: Values | T27: =_xll.ciqfunctions.udf.CIQ($E$26, "IQ_TOTAL_REV", "FY2024") -> 187.192 | U27: =_xll.ciqfunctions.udf.CIQ($E$26, "IQ_REVENUE_EST", "FY2026") -> 1148.0752 | V27: =_xll.ciqfunctions.udf.CIQ($E$26, "IQ_EBITDA", "FY2024") -> 31.212 | W27: =_xll.ciqfunctions.udf.CIQ($E$26, "IQ_EBITDA_EST", "FY2026") -> 680.85415 | X27: =_xll.ciqfunctions.udf.CIQ($E$26, "IQ_BASIC_EPS_INCL", "FY2025") -> 0.40516 | Y27: =_xll.ciqfunctions.udf.CIQ($E$26, "IQ_BASIC_EPS_INCL", "FY2024") -> -0.29024 | Z27: =_xll.ciqfunctions.udf.CIQ($E$26, "IQ_EPS_EST", "FY2026") -> 1.05635 | AA27: =_xll.ciqfunctions.udf.CIQ($E$26, "IQ_EPS_EST", "FY2027") -> 1.05969
B28: CleanSpark | E28: CLSK | F28: 3409.5 | G28: 4192.3 | I28: =_xll.ciqfunctions.udf.CIQ($E$28, "IQ_TOTAL_REV", "LTM32025") -> 631.937 | J28: =_xll.ciqfunctions.udf.CIQ($E$28, "IQ_GP", "LTM32025") -> 328.953 | K28: =_xll.ciqfunctions.udf.CIQ($E$28, "IQ_EBITDA", "LTM32025") -> 553.324 | L28: =_xll.ciqfunctions.udf.CIQ($E$28, "IQ_EBIT", "LTM32025") -> 261.466 | M28: =_xll.ciqfunctions.udf.CIQ($E$28, "IQ_NI", "LTM32025") -> 303.21 | O28: =J28/$I$28 -> 0.52054714 | P28: =K28/$I$28 -> 0.87559994 | Q28: =L28/$I$28 -> 0.41375327 | R28: =M28/$I$28 -> 0.47981049 | AD28: =_xll.ciqfunctions.udf.CIQ($E$28, "IQ_BETA_2YR") -> 2.40536
B29: Values | T29: =_xll.ciqfunctions.udf.CIQ($E$28, "IQ_TOTAL_REV", "FY2024") -> 378.968 | U29: =_xll.ciqfunctions.udf.CIQ($E$28, "IQ_REVENUE_EST", "FY2026") -> 805.79142 | V29: =_xll.ciqfunctions.udf.CIQ($E$28, "IQ_EBITDA", "FY2024") -> 95.366 | W29: =_xll.ciqfunctions.udf.CIQ($E$28, "IQ_EBITDA_EST", "FY2026") -> 327.45 | X29: =_xll.ciqfunctions.udf.CIQ($E$28, "IQ_BASIC_EPS_INCL", "FY2025") -> 1.25211 | Y29: =_xll.ciqfunctions.udf.CIQ($E$28, "IQ_BASIC_EPS_INCL", "FY2024") -> -0.68799 | Z29: =_xll.ciqfunctions.udf.CIQ($E$28, "IQ_EPS_EST", "FY2026") -> 0.72667 | AA29: =_xll.ciqfunctions.udf.CIQ($E$28, "IQ_EPS_EST", "FY2027") -> 0.935
B31: Mean | AD31: Mean
B32: Median | AD32: Median
B34: Tier 2: Infrastructure Platforms/ AI Data Center Operators | AD34: Tier 2: Infrastructure Platforms/ AI Data Center Operators
B36: CoreWeave | E36: CRWV | F36: 44748.9 | G36: 61616.7 | I36: =_xll.ciqfunctions.udf.CIQ($E$36, "IQ_TOTAL_REV", "LTM32025") -> 4306.526 | J36: =_xll.ciqfunctions.udf.CIQ($E$36, "IQ_GP", "LTM32025") -> 3180.483 | K36: =_xll.ciqfunctions.udf.CIQ($E$36, "IQ_EBITDA", "LTM32025") -> 2184.139 | L36: =_xll.ciqfunctions.udf.CIQ($E$36, "IQ_EBIT", "LTM32025") -> 185.263 | M36: =_xll.ciqfunctions.udf.CIQ($E$36, "IQ_NI", "LTM32025") -> -766.646 | O36: =J36/$I$36 -> 0.73852637 | P36: =K36/$I$36 -> 0.50716958 | Q36: =L36/$I$36 -> 0.04301913 | R36: =M36/$I$36 -> -0.17801959 | AD36: =_xll.ciqfunctions.udf.CIQ($E$36, "IQ_BETA_2YR") -> 0
B37: Values
B38: Lambda | E38: - | F38: - | G38: - | I38: - | J38: - | K38: - | L38: - | M38: - | O38: - | P38: - | Q38: - | R38: - | T38: - | U38: - | V38: - | W38: - | X38: - | Y38: - | Z38: - | AA38: -
B39: Values | E39: - | F39: - | G39: - | I39: - | J39: - | K39: - | L39: - | M39: - | O39: - | P39: - | Q39: - | R39: - | T39: - | U39: - | V39: - | W39: - | X39: - | Y39: - | Z39: - | AA39: -
B40: Crusoe Energy | E40: - | F40: - | G40: - | I40: - | J40: - | K40: - | L40: - | M40: - | O40: - | P40: - | Q40: - | R40: - | T40: - | U40: - | V40: - | W40: - | X40: - | Y40: - | Z40: - | AA40: -
B41: Values | E41: - | F41: - | G41: - | I41: - | J41: - | K41: - | L41: - | M41: - | O41: - | P41: - | Q41: - | R41: - | T41: - | U41: - | V41: - | W41: - | X41: - | Y41: - | Z41: - | AA41: -
B42: NTT Global Data Centers | E42: - | F42: - | G42: - | I42: - | J42: - | K42: - | L42: - | M42: - | O42: - | P42: - | Q42: - | R42: - | T42: - | U42: - | V42: - | W42: - | X42: - | Y42: - | Z42: - | AA42: -
B43: Values | E43: - | F43: - | G43: - | I43: - | J43: - | K43: - | L43: - | M43: - | O43: - | P43: - | Q43: - | R43: - | T43: - | U43: - | V43: - | W43: - | X43: - | Y43: - | Z43: - | AA43: -
B45: Mean | AD45: Mean
B46: Median | AD46: Median
B48: Tier 3: Data Center REITs | AD48: Tier 3: Data Center REITs
B50: Digital Realty Trust | E50: DLR | F50: 54706.1 | G50: 55693.9 | I50: =_xll.ciqfunctions.udf.CIQ(E50, "IQ_TOTAL_REV", "LTM32025") -> 5841.036 | J50: =_xll.ciqfunctions.udf.CIQ(E50, "IQ_GP", "LTM32025") -> 3201.245 | K50: =_xll.ciqfunctions.udf.CIQ(E50, "IQ_EBITDA", "LTM32025") -> 2662.961 | L50: =_xll.ciqfunctions.udf.CIQ(E50, "IQ_EBIT", "LTM32025") -> 801.028 | M50: =_xll.ciqfunctions.udf.CIQ(E50, "IQ_NI", "LTM32025") -> 1399.511 | O50: =J50/$I$50 -> 0.54806117 | P50: =K50/$I$50 -> 0.4559056 | Q50: =L50/$I$50 -> 0.137138 | R50: =M50/$I$50 -> 0.23959979 | AD50: =_xll.ciqfunctions.udf.CIQ($E$50, "IQ_BETA_2YR") -> 0.762
B51: Values | T51: =_xll.ciqfunctions.udf.CIQ($E$50, "IQ_TOTAL_REV", "FY2024") -> 5434.83 | U51: =_xll.ciqfunctions.udf.CIQ($E$50, "IQ_REVENUE_EST", "FY2026") -> 6732.3513 | V51: =_xll.ciqfunctions.udf.CIQ($E$50, "IQ_EBITDA", "FY2024") -> 2413.809 | W51: =_xll.ciqfunctions.udf.CIQ($E$50, "IQ_REVENUE_EST", "FY2026") -> 6732.3513 | X51: 3 | Y51: =_xll.ciqfunctions.udf.CIQ($E$50, "IQ_BASIC_EPS_INCL", "FY2024") -> 1.73741 | Z51: =_xll.ciqfunctions.udf.CIQ($E$50, "IQ_EPS_EST", "FY2026") -> 1.59833 | AA51: =_xll.ciqfunctions.udf.CIQ($E$50, "IQ_EPS_EST", "FY2027") -> 2.13052
B52: Equinix | E52: EQIX | F52: 78452.6 | G52: 97380.6 | I52: =_xll.ciqfunctions.udf.CIQ($E$52, "IQ_TOTAL_REV", "LTM32025") -> 9076 | J52: =_xll.ciqfunctions.udf.CIQ($E$52, "IQ_GP", "LTM32025") -> 4570 | K52: =_xll.ciqfunctions.udf.CIQ($E$52, "IQ_EBITDA", "LTM32025") -> 3900 | L52: =_xll.ciqfunctions.udf.CIQ($E$52, "IQ_EBIT", "LTM32025") -> 1879 | M52: =_xll.ciqfunctions.udf.CIQ($E$52, "IQ_NI", "LTM32025") -> 1071 | O52: =J52/$I$52 -> 0.50352578 | P52: =K52/$I$52 -> 0.42970472 | Q52: =L52/$I$52 -> 0.20702953 | R52: =M52/$I$52 -> 0.11800353 | AD52: =_xll.ciqfunctions.udf.CIQ($E$52, "IQ_BETA_2YR") -> 0.65638
B53: Values | T53: =_xll.ciqfunctions.udf.CIQ($E$52, "IQ_TOTAL_REV", "FY2024") -> 8737 | U53: =_xll.ciqfunctions.udf.CIQ($E$52, "IQ_REVENUE_EST", "FY2026") -> 10074.299 | V53: =_xll.ciqfunctions.udf.CIQ($E$52, "IQ_EBITDA", "FY2024") -> 3625 | W53: =_xll.ciqfunctions.udf.CIQ($E$52, "IQ_REVENUE_EST", "FY2026") -> 10074.299 | X53: 15.09 | Y53: =_xll.ciqfunctions.udf.CIQ($E$52, "IQ_BASIC_EPS_INCL", "FY2024") -> 8.53788 | Z53: =_xll.ciqfunctions.udf.CIQ($E$52, "IQ_EPS_EST", "FY2026") -> 15.12226 | AA53: =_xll.ciqfunctions.udf.CIQ($E$52, "IQ_EPS_EST", "FY2027") -> 16.46524
B54: Vornado Realty Trust | E54: VNO | F54: 6451.1 | G54: 7011.9 | I54: =_xll.ciqfunctions.udf.CIQ($E$54, "IQ_TOTAL_REV", "FY2024") -> 1900.15 | J54: =_xll.ciqfunctions.udf.CIQ($E$54, "IQ_GP", "FY2024") -> 972.354 | K54: =_xll.ciqfunctions.udf.CIQ($E$54, "IQ_EBITDA", "FY2024") -> 820.799 | L54: =_xll.ciqfunctions.udf.CIQ($E$54, "IQ_EBIT", "FY2024") -> 376.334 | M54: =_xll.ciqfunctions.udf.CIQ($E$54, "IQ_NI", "FY2024") -> 70.387 | O54: =J54/$I$54 -> 0.51172486 | P54: =K54/$I$54 -> 0.43196537 | Q54: =L54/$I$54 -> 0.19805489 | R54: =M54/$I$54 -> 0.037042865 | AD54: =_xll.ciqfunctions.udf.CIQ($E$54, "IQ_BETA_2YR") -> 1.26375
B55: Values | T55: =_xll.ciqfunctions.udf.CIQ($E$54, "IQ_TOTAL_REV", "FY2024") -> 1900.15 | U55: =_xll.ciqfunctions.udf.CIQ($E$54, "IQ_REVENUE_EST", "FY2026") -> 1813.6418 | V55: =_xll.ciqfunctions.udf.CIQ($E$54, "IQ_EBITDA", "FY2024") -> 820.799 | W55: =_xll.ciqfunctions.udf.CIQ($E$54, "IQ_EBITDA_EST", "FY2026") -> 698.76378 | X55: - | Y55: =_xll.ciqfunctions.udf.CIQ($E$54, "IQ_BASIC_EPS_INCL", "FY2024") -> 0.04343 | Z55: =_xll.ciqfunctions.udf.CIQ($E$54, "IQ_EPS_EST", "FY2026") -> -0.185 | AA55: =_xll.ciqfunctions.udf.CIQ($E$54, "IQ_EPS_EST", "FY2027") -> -0.05
B57: Mean | AD57: Mean
B58: Median | AD58: Median
