Workbook

Sheet Trading Multiples
A1: Company Comp Set
A2: Company Name | B2: EV/Total Revenue | C2: EV/EBITDA | D2: TEV/EBIT LTM - Latest | E2: P/E | F2: P/TangBV LTM - Latest | G2: NTM TEV/Forward Total Revenue (Capital IQ) | H2: NTM TEV/Forward EBITDA (Capital IQ) | I2: NTM Forward P/E (Capital IQ)
A3: The TJX Companies, Inc. (NYSE:TJX) | B3: 2.5 | C3: 13 | D3: 22.6 | E3: 28.1 | F3: 16.4 | G3: 2.41 | H3: 18.15 | I3: 26.6
A4: Kohl's Corporation (NYSE:KSS) | B4: 0.5 | C4: 5.3 | D4: 16.2 | E4: 9.3 | F4: 0.3 | G4: 0.55 | H4: 7.31 | I4: 23.07
A5: The Gap, Inc. (NYSE:GAP) | B5: 0.7 | C5: 3.8 | D5: 9.8 | E5: 9.8 | F5: 2.7 | G5: 0.72 | H5: 6.32 | I5: 8.97
A6: Nordstrom, Inc. (NYSE:JWN) | B6: 0.5 | C6: 4.8 | D6: 13.4 | E6: 14 | F6: 4.5 | G6: 0.48 | H6: 6.27 | I6: 11.11
A7: Dillard's, Inc. (NYSE:DDS) | B7: 0.8 | C7: 5.7 | D7: 7.2 | E7: 10 | F7: 3.3 | G7: 0.83 | H7: 7.08 | I7: 12.85
A8: Macy's, Inc. (NYSE:M) | B8: =75700/'Implied Valuation'!B3 -> 3.1718763 | C8: =75700/'Implied Valuation'!C3 -> 59.936659 | D8: 9.4 | E8: =11/0.16 -> 68.75 | F8: =11/(4035/278) -> 0.75786865 | G8: 0.4 | H8: 4.69 | I8: 6.42
A10: Summary Statistics | B10: TEV/Total Revenues LTM - Latest | C10: TEV/EBITDA LTM - Latest | D10: TEV/EBIT LTM - Latest | E10: P/Diluted EPS Before Extra LTM - Latest | F10: P/TangBV LTM - Latest | G10: NTM TEV/Forward Total Revenue (Capital IQ) | H10: NTM TEV/Forward EBITDA (Capital IQ) | I10: NTM Forward P/E (Capital IQ)
A11: High | B11: =MAX(B3:B7) -> 2.5 | C11: =MAX(C3:C7) -> 13 | D11: =MAX(D3:D7) -> 22.6 | E11: =MAX(E3:E7) -> 28.1 | F11: =MAX(F3:F7) -> 16.4 | G11: =MAX(G3:G7) -> 2.41 | H11: =MAX(H3:H7) -> 18.15 | I11: =MAX(I3:I7) -> 26.6
A12: Low | B12: =MIN(B3:B7) -> 0.5 | C12: =MIN(C3:C7) -> 3.8 | D12: =MIN(D3:D7) -> 7.2 | E12: =MIN(E3:E7) -> 9.3 | F12: =MIN(F3:F7) -> 0.3 | G12: =MIN(G3:G7) -> 0.48 | H12: =MIN(H3:H7) -> 6.27 | I12: =MIN(I3:I7) -> 8.97
A13: Mean | B13: =AVERAGE(B3:B7) -> 1 | C13: =AVERAGE(C3:C7) -> 6.52 | D13: =AVERAGE(D3:D7) -> 13.84 | E13: =AVERAGE(E3:E7) -> 14.24 | F13: =AVERAGE(F3:F7) -> 5.44 | G13: =AVEDEV(G3:G7) -> 0.5648 | H13: =AVEDEV(H3:H7) -> 3.6496 | I13: =AVEDEV(I3:I7) -> 6.652
A14: Median | B14: =MEDIAN(B3:B7) -> 0.7 | C14: =MEDIAN(C3:C7) -> 5.3 | D14: =MEDIAN(D3:D7) -> 13.4 | E14: =MEDIAN(E3:E7) -> 10 | F14: =MEDIAN(F3:F7) -> 3.3 | G14: =MEDIAN(G3:G7) -> 0.72 | H14: =MEDIAN(H3:H7) -> 7.08 | I14: =MEDIAN(I3:I7) -> 12.85

Sheet Implied Valuation
A1: Company Comp Set
A2: Company Name | B2: LTM Total Revenue | C2: LTM EBITDA | D2: LTM EBIT | E2: NTM Revenue (Capital IQ) | F2: NTM EBITDA (Capital IQ) | G2: LTM Basic EPS | H2: NTM EPS (Capital IQ) | I2: LTM Tangible Book Value/Share
A3: Macy's, Inc. (NYSE:M) | B3: 23866 | C3: 1263 | D3: 913 | E3: 21372 | F3: -1490.7 | G3: =0.16 -> 0.16 | H3: 0.1 | I3: 8.99
E5: Total Enterprise Value Multiples | H5: Pricing Multiples
B6: LTM TEV/Total Revenues | C6: LTM TEV/EBITDA | D6: LTM TEV/EBIT | E6: NTM TEV/Forward Total Revenue | F6: NTM TEV/Forward EBITDA | G6: LTM P/Diluted EPS Before Extra | H6: NTM Forward P/E | I6: LTM P/TangBV
A7: High | B7: ='[1]Trading Multiples'!B11 -> 2.5 | C7: ='[1]Trading Multiples'!C11 -> 13 | D7: ='[1]Trading Multiples'!D11 -> 22.6 | E7: ='[1]Trading Multiples'!G11 -> 2.41 | F7: ='[1]Trading Multiples'!H11 -> 18.15 | G7: ='[1]Trading Multiples'!E11 -> 28.1 | H7: ='[1]Trading Multiples'!I11 -> 26.6 | I7: ='[1]Trading Multiples'!F11 -> 16.4
A8: Low | B8: ='[1]Trading Multiples'!B12 -> 0.5 | C8: ='[1]Trading Multiples'!C12 -> 3.8 | D8: 7.2 | E8: ='[1]Trading Multiples'!G12 -> 0.48 | F8: ='[1]Trading Multiples'!H12 -> 6.27 | G8: ='[1]Trading Multiples'!E12 -> 9.3 | H8: ='[1]Trading Multiples'!I12 -> 8.97 | I8: ='[1]Trading Multiples'!F12 -> 0.3
A9: Mean | B9: ='[1]Trading Multiples'!B13 -> 1 | C9: ='[1]Trading Multiples'!C13 -> 6.52 | D9: 4.448 | E9: ='[1]Trading Multiples'!G13 -> 0.5648 | F9: ='[1]Trading Multiples'!H13 -> 3.6496 | G9: ='[1]Trading Multiples'!E13 -> 14.24 | H9: ='[1]Trading Multiples'!I13 -> 6.652 | I9: ='[1]Trading Multiples'!F13 -> 5.44
A10: Median | B10: ='[1]Trading Multiples'!B14 -> 0.7 | C10: ='[1]Trading Multiples'!C14 -> 5.3 | D10: 13.4 | E10: ='[1]Trading Multiples'!G14 -> 0.72 | F10: ='[1]Trading Multiples'!H14 -> 7.08 | G10: ='[1]Trading Multiples'!E14 -> 10 | H10: ='[1]Trading Multiples'!I14 -> 12.85 | I10: ='[1]Trading Multiples'!F14 -> 3.3
A12: Implied Enterprise Value
A13: High | B13: =B$3*B7 -> 59665 | C13: =C$3*C7 -> 16419 | D13: =D$3*D7 -> 20633.8 | E13: =E$3*E7 -> 51506.52 | F13: =F$3*F7 -> -27056.205
A14: Low | B14: =B$3*B8 -> 11933 | C14: =C$3*C8 -> 4799.4 | D14: =D$3*D8 -> 6573.6 | E14: =E$3*E8 -> 10258.56 | F14: =F$3*F8 -> -9346.689
A15: Mean | B15: =B$3*B9 -> 23866 | C15: =C$3*C9 -> 8234.76 | D15: =D$3*D9 -> 4061.024 | E15: =E$3*E9 -> 12070.906 | F15: =F$3*F9 -> -5440.4587
A16: Median | B16: =B$3*B10 -> 16706.2 | C16: =C$3*C10 -> 6693.9 | D16: =D$3*D10 -> 12234.2 | E16: =E$3*E10 -> 15387.84 | F16: =F$3*F10 -> -10554.156
A18: + Total Cash & ST Investments | B18: 1306 | C18: 1306 | D18: 1306 | E18: 1306 | F18: 1306
A19: - Total Debt | B19: 6073 | C19: 6073 | D19: 6073 | E19: 6073 | F19: 6073
A20: - Total Pref. Equity | B20: - | C20: - | D20: - | E20: - | F20: -
A21: - Minority Interest | B21: - | C21: - | D21: - | E21: - | F21: -
A23: = Implied Equity Value
A24: High | B24: =B13+B$18-B$19 -> 54898 | C24: =C13+C$18-C$19 -> 11652 | D24: =D13+D$18-D$19 -> 15866.8 | E24: =E13+E$18-E$19 -> 46739.52 | F24: =F13+F$18-F$19 -> -31823.205 | G24: =G$3*G7*G$29 -> 1249.888 | H24: =H$3*H7*H$29 -> 739.48 | I24: =I$3*I7*I$29 -> 40987.208
A25: Low | B25: =B14+B$18-B$19 -> 7166 | C25: =C14+C$18-C$19 -> 32.4 | D25: =D14+D$18-D$19 -> 1806.6 | E25: =E14+E$18-E$19 -> 5491.56 | F25: =F14+F$18-F$19 -> -14113.689 | G25: =G$3*G8*G$29 -> 413.664 | H25: =H$3*H8*H$29 -> 249.366 | I25: =I$3*I8*I$29 -> 749.766
A26: Mean | B26: =B15+B$18-B$19 -> 19099 | C26: =C15+C$18-C$19 -> 3467.76 | D26: =D15+D$18-D$19 -> -705.976 | E26: =E15+E$18-E$19 -> 7303.9056 | F26: =F15+F$18-F$19 -> -10207.459 | G26: =G$3*G9*G$29 -> 633.3952 | H26: =H$3*H9*H$29 -> 184.9256 | I26: =I$3*I9*I$29 -> 13595.757
A27: Median | B27: =B16+B$18-B$19 -> 11939.2 | C27: =C16+C$18-C$19 -> 1926.9 | D27: =D16+D$18-D$19 -> 7467.2 | E27: =E16+E$18-E$19 -> 10620.84 | F27: =F16+F$18-F$19 -> -15321.156 | G27: =G$3*G10*G$29 -> 444.8 | H27: =H$3*H10*H$29 -> 357.23 | I27: =I$3*I10*I$29 -> 8247.426
A29: / Shares Outstanding | B29: 278 | C29: 278 | D29: 278 | E29: 278 | F29: 278 | G29: 278 | H29: 278 | I29: 278
A31: = Implied Price per Share
A32: High | B32: =B24/B$29 -> 197.47482 | C32: =C24/C$29 -> 41.913669 | D32: =D24/D$29 -> 57.07482 | E32: =E24/E$29 -> 168.12777 | F32: =F24/F$29 -> -114.47196 | G32: =G24/G$29 -> 4.496 | H32: =H24/H$29 -> 2.66 | I32: =I24/I$29 -> 147.436
A33: Low | B33: =B25/B$29 -> 25.776978 | C33: =C25/C$29 -> 0.11654676 | D33: =D25/D$29 -> 6.4985612 | E33: =E25/E$29 -> 19.753813 | F33: =F25/F$29 -> -50.768665 | G33: =G25/G$29 -> 1.488 | H33: =H25/H$29 -> 0.897 | I33: =I25/I$29 -> 2.697
A34: Mean | B34: =B26/B$29 -> 68.701439 | C34: =C26/C$29 -> 12.473957 | D34: =D26/D$29 -> -2.539482 | E34: =E26/E$29 -> 26.273042 | F34: =F26/F$29 -> -36.717477 | G34: =G26/G$29 -> 2.2784 | H34: =H26/H$29 -> 0.6652 | I34: =I26/I$29 -> 48.9056
A35: Median | B35: =B27/B$29 -> 42.946763 | C35: =C27/C$29 -> 6.931295 | D35: =D27/D$29 -> 26.860432 | E35: =E27/E$29 -> 38.20446 | F35: =F27/F$29 -> -55.112072 | G35: =G27/G$29 -> 1.6 | H35: =H27/H$29 -> 1.285 | I35: =I27/I$29 -> 29.667
A37: Mean Equity Value Across Multiples | B37: Equity Value | C37: Price Per Share
A38: High | B38: =AVERAGE(B24:I24) -> 17538.711 | C38: =B38/C$29 -> 63.08889
A39: Low | B39: =AVERAGE(B25:I25) -> 224.45837 | C39: =B39/C$29 -> 0.80740423
A40: Mean | B40: =AVERAGE(B26:I26) -> 4171.4136 | C40: =B40/C$29 -> 15.005085
A41: Median | B41: =AVERAGE(B27:I27) -> 3210.305 | C41: =B41/C$29 -> 11.54786

Sheet Cover
A1: Macy's, Inc. (NYSE:"M")
A2: Financial Statements (Exported from S&P Cap IQ)
A4: Template: | B4: Standard | D4: Restatement: | E4: Latest Filings
A5: Period Type: | B5: Annual | D5: Order: | E5: Latest on Right
A6: Currency: | B6: US Dollar | D6: Conversion: | E6: Historical
A7: Units: | B7: Millions (mm) | D7: Decimals: | E7: Capital IQ (Default)
A8: Source: | B8: Capital IQ & Proprietary Data

Sheet Key Stats
A5: Macy's, Inc. (NYSE:M) > Financials > Key Stats
A7: In Millions of USD, except per share items. | B7: Currency: | C7: US Dollar | E7: Conversion: | F7: Historical
B8: Order: | C8: Latest on Right | E8: Units: | F8: Millions (mm)
B9: Decimals: | C9: Capital IQ (Default) | E9: Dilution: | F9: Basic
A12: Key Financials¹ | B12: 2019A | C12: 2020A | D12: 2021A | E12: 2022A | F12: 2023A | G12: 2024A | H12: 2025A | I12: 2025E
A13: For the Fiscal Period Ending | B13: 12 months Feb-02-2019A | C13: 12 months Feb-01-2020A | D13: 12 months Jan-30-2021A | E13: 12 months Jan-29-2022A | F13: 12 months Jan-28-2023A | G13: 12 months Feb-03-2024A | H13: 12 months Feb-01-2025A | I13: 12 months† Jan-31-2026E
A14: Currency | B14: USD | C14: USD | D14: USD | E14: USD | F14: USD | G14: USD | H14: USD | I14: USD
A16: Total Revenue | B16: 25739 | C16: 25331 | D16: 18097 | E16: 25399 | F16: 25449 | G16: 23866 | H16: 23006 | I16: 21240.837
A17: Growth Over Prior Year | B17: 0.003822 | C17: -0.015852 | D17: -0.285579 | E17: 0.403492 | F17: 0.001968 | G17: -0.062203 | H17: -0.036035 | I17: -
A19: Gross Profit | B19: 10524 | C19: 10160 | D19: 5811 | E19: 10443 | F19: 10102 | G19: 9642 | H19: 9266 | I19: -
A20: Margin % | B20: 0.408873 | C20: 0.401089 | D20: 0.321102 | E20: 0.411157 | F20: 0.39695 | G20: 0.404005 | H20: 0.402764 | I20: 0.3905
A22: EBITDA | B22: 2198 | C22: 1855 | D22: -211 | E22: 2970 | F22: 2262 | G22: 1891 | H22: 1484 | I22: 1820.5283
A23: Margin % | B23: 0.085395 | C23: 0.07323 | D23: -0.011659 | E23: 0.116933 | F23: 0.088883 | G23: 0.079234 | H23: 0.064504 | I23: 0.085708875
A25: EBIT | B25: 1532 | C25: 1159 | D25: -902 | E25: 2334 | F25: 1640 | G25: 1263 | H25: 913 | I25: 895.74194
A26: Margin % | B26: 0.05952 | C26: 0.045754 | D26: -0.049842 | E26: 0.091893 | F26: 0.064442 | G26: 0.05292 | H26: 0.039685 | I26: 0.042170746
A28: Earnings from Cont. Ops. | B28: 1098 | C28: 564 | D28: -3944 | E28: 1430 | F28: 1146 | G28: 45 | H28: 582 | I28: -
A29: Margin % | B29: 0.042658 | C29: 0.022265 | D29: -0.217936 | E29: 0.056301 | F29: 0.045031 | G29: 0.001885 | H29: 0.025297 | I29: -
A31: Net Income | B31: 1108 | C31: 564 | D31: -3944 | E31: 1430 | F31: 1146 | G31: 45 | H31: 582 | I31: 594.09608
A32: Margin % | B32: 0.043047 | C32: 0.022265 | D32: -0.217936 | E32: 0.056301 | F32: 0.045031 | G32: 0.001885 | H32: 0.025297 | I32: 0.027969523
A34: Diluted EPS Excl. Extra Items³ | B34: 3.56 | C34: 1.81 | D34: -12.68 | E34: 4.55 | F34: 4.08 | G34: 0.16 | H34: 2.07 | I34: 2.11394
A35: Growth Over Prior Year | B35: -0.301961 | C35: -0.491574 | D35: NM | E35: NM | F35: -0.103297 | G35: -0.960785 | H35: 11.9375 | I35: -
A37: Same Store Sales Growth % | B37: 0.017 | C37: -0.008 | D37: -0.279 | E37: 0.43 | F37: 0.003 | G37: -0.069 | H37: -0.02 | I37: -
A39: Currency | B39: USD | C39: USD | D39: USD | E39: USD | F39: USD | G39: USD | H39: USD | I39: USD
A40: Exchange Rate | B40: 1 | C40: 1 | D40: 1 | E40: 1 | F40: 1 | G40: 1 | H40: 1 | I40: 1
A41: Conversion Method | B41: H | C41: H | D41: H | E41: H | F41: H | G41: H | H41: H | I41: S
A43: ¹All results are taken from the most recently filed statement for each period. When there has been more than one, earlier filings can be viewed on the individual statement pages.
A44: ³All forward period figures are consensus mean estimates provided by the brokers and may not be on a comparable basis as financials.
A45: †Growth rates for forward periods are calculated against prior period estimates or actual pro forma results as disclosed on the Estimates Consensus page.
A46: Growth Rates are calculated in originally reported currency only and will not reflect any currency conversion selected above.
A48: Current Capitalization (Millions of USD)
A49: Currency | B49: USD
A50: Share Price | B50: 13.24
A51: Shares Out. | B51: 277.71764
A53: Market Capitalization | B53: 3676.9815 | C53: =B53*10^6 -> 3676981513
A54: - Cash & Short Term Investments | B54: 1306 | C54: =C53/10^9 -> 3.6769815
A55: + Total Debt | B55: 6073
A56: + Pref. Equity | B56: -
A57: + Total Minority Interest | B57: -
A58: - Long Term Marketable Securities | B58: -
A59: = Total Enterprise Value (TEV) | B59: 8443.9815
A61: Book Value of Common Equity | B61: 4552
A62: + Pref. Equity | B62: -
A63: + Total Minority Interest | B63: -
A64: + Total Debt | B64: 6073
A65: = Total Capital | B65: 10625
A67: **For companies that have multiple share classes that publicly trade, we are incorporating the different prices to calculate our company level market capitalization. Please click on the value to see the detailed calculation. Prices shown on this page are the close price of the company’s primary stock class. Shares shown on this page are total company as-reported share values.
A71: Total Liability includes Total Debt, Minority Interest and Pref. Equity.
A72: Net Liability includes Total Liability, net of Cash and Short Term Investments.
A73: TEV includes Market Cap and Net Liability.
A74: Total Capital includes Common Equity and Total Liability.
A76: Valuation Multiples based on Current Capitalization | B76: 2024A | C76: 2025A | D76: 2026E | E76: 2027E | F76: 2028E
A77: For the Fiscal Period Ending | B77: 12 months Feb-03-2024A | C77: 12 months Feb-01-2025A | D77: 12 months Jan-31-2026E | E77: 12 months Jan-31-2027E | F77: 12 months Jan-31-2028E
A78: TEV/Total Revenue | B78: 0.353807 | C78: 0.367033 | D78: 0.39753525 | E78: 0.41996972 | F78: 0.48267613
A80: TEV/EBITDA | B80: 3.706752 | C80: 4.498658 | D80: 4.638204 | E80: 4.8038013 | F80: 4.9691959
A82: TEV/EBIT | B82: 6.685654 | C82: 9.24861 | D82: 9.4268016 | E82: 9.8714636 | F82: 9.8431054
A84: P/Diluted EPS Before Extra | B84: 82.75 | C84: 6.396135 | D84: 6.2631863 | E84: 6.3148958 | F84: 5.9092634
A86: P/BV | B86: 0.899817 | C86: 0.807692 | D86: 0.7466651 | E86: 0.77752461 | F86: 0.79369314
A88: Price/Tang BV | B88: 1.797408 | C88: 1.472413 | D88: - | E88: - | F88: -

Sheet FA
A1: FA - Financial Analysis
A2: don't have to necessary analyse every formula below: | L2: FYs
A3: 1) Profitability (IS) | J3: 1) Profitability | L3: 2019 | M3: 2020 | N3: 2021 | O3: 2022 | P3: 2023 | Q3: 2024
J4: Gross Margin | L4: 0.40887369 | M4: 0.40108957 | N4: 0.32110295 | O4: 0.40866677 | P4: 0.39856183 | Q4: 0.40739965
A5: Gross Margin = (Revenue - COGS) / Revenue | J5: Gross Margin (%) | L5: =L4 -> 0.40887369 | M5: =M4 -> 0.40108957 | N5: =N4 -> 0.32110295 | O5: =O4 -> 0.40866677 | P5: =P4 -> 0.39856183 | Q5: =Q4 -> 0.40739965
A6: Operating Margin = Operating Income / Revenue
A7: Net Profit Margin = Net Income / Revenue | J7: EBITDA Margin | L7: 0.067523991 | M7: 0.038293001 | N7: -0.24727855 | O7: 0.092914756 | P7: 0.067979095 | Q7: 0.016006034
A8: Return on Assets (ROA) = Net Income / Average Total Assets | J8: EBITDA Margin (%) | L8: =L7 -> 0.067523991 | M8: =M7 -> 0.038293001 | N8: =N7 -> -0.24727855 | O8: =O7 -> 0.092914756 | P8: =P7 -> 0.067979095 | Q8: =Q7 -> 0.016006034
A9: Return on Equity (ROE) = Net Income / Average Shareholders’ Equity
A10: Return on Invested Capital (ROIC) = NOPAT / Average Invested Capital | J10: Net Profit Margin | L10: 0.043047515 | M10: 0.022265209 | N10: -0.21793667 | O10: 0.056539617 | P10: 0.046249361 | Q10: 0.0043995642
J11: Net Profit Margin (%) | L11: =L10 -> 0.043047515 | M11: =M10 -> 0.022265209 | N11: =N10 -> -0.21793667 | O11: =O10 -> 0.056539617 | P11: =P10 -> 0.046249361 | Q11: =Q10 -> 0.0043995642
A13: 2) Liquidity (BS) | J13: ROA | L13: 0.057726373 | M13: 0.026638957 | N13: -0.22274935 | O13: 0.081296191 | P13: 0.069785367 | Q13: 0.0064631294
J14: ROE | L14: 0.17215662 | M14: 0.088442841 | N14: -1.5448492 | O14: 0.39491853 | P14: 0.28833905 | Q14: 0.025380711
A15: Current Ratio = Current Assets / Current Liabilities
A16: Quick Ratio = (Current Assets - Inventory) / Current Liabilities
L17: FYs
J18: 2) Liquidity | L18: 2019 | M18: 2020 | N18: 2021 | O18: 2022 | P18: 2023 | Q18: 2024
A19: 3) Leverage & Solvency (BS) | J19: Current Ratio | L19: 1.422974 | M19: 1.1843478 | N19: 1.1543775 | O19: 1.2477843 | P19: 1.2040732 | Q19: 1.3744921
A21: Debt-to-Equity = Total Debt / Shareholders’ Equity | J21: Quick Ratio | L21: 0.41704893 | M21: 0.28208696 | N21: 0.44987866 | O21: 0.43851551 | P21: 0.32627031 | Q21: 0.39006772
A22: Debt-to-Assets = Total Debt / Total Assets
A23: Interest Coverage Ratio = EBIT / Interest Expense
A24: Debt Service Coverage Ratio (DSCR) = EBITDA / Total Debt Service | L24: FYs
J25: 3) Leverage & Solvency | L25: 2019 | M25: 2020 | N25: 2021 | O25: 2022 | P25: 2023 | Q25: 2024
J26: Debt-to-Equity
A27: 4) Efficiency (BS & IS) | J27: Debt-to-Assets
J28: Interest Coverage Ratio
A29: Asset Turnover = Revenue / Average Total Assets | J29: DSCR
A30: Inventory Turnover = COGS / Average Inventory
A31: Receivables Turnover = Revenue / Average Accounts Receivable
A32: Days Sales Outstanding (DSO) = (Accounts Receivable / Revenue) × 365 | L32: FYs
A33: Days Inventory Outstanding (DIO) = (Average Inventory / COGS) × 365 | J33: 4) Efficiecny | L33: 2019 | M33: 2020 | N33: 2021 | O33: 2022 | P33: 2023 | Q33: 2024
A34: Cash Conversion Cycle (CCC) = DIO + DSO - Days Payables Outstanding (DPO) | J34: Asset Turnover
J35: Inventory Turnover
J36: Receivabls Turnover
A38: 5) Cash Flow Analysis (CFS) | J38: Days Sales Outs. (days)
J39: Days Sales Outs. (Months) | L39: =L38/12 -> 0 | M39: =M38/12 -> 0 | N39: =N38/12 -> 0 | O39: =O38/12 -> 0 | P39: =P38/12 -> 0 | Q39: =Q38/12 -> 0
A40: Operating Cash Flow (OCF) = Cash Flow from Operations
A41: Free Cash Flow (FCF) = OCF - Capital Expenditures | J41: Days Inventory Outs (days)
A42: FCF Yield = FCF / Market Capitalization | J42: Days Inventory Outs (Months) | L42: =L41/12 -> 0 | M42: =M41/12 -> 0 | N42: =N41/12 -> 0 | O42: =O41/12 -> 0 | P42: =P41/12 -> 0 | Q42: =Q41/12 -> 0
A43: Cash Flow to Debt Ratio = OCF / Total Debt
J44: Days Payables Outs. (days)
J45: Days Payables Outs. (Months)
J47: Cash Conversion Cycle (CCC) | L47: =L38+L41-L44 -> 0 | M47: =M38+M41-M44 -> 0 | N47: =N38+N41-N44 -> 0 | O47: =O38+O41-O44 -> 0 | P47: =P38+P41-P44 -> 0 | Q47: =Q38+Q41-Q44 -> 0
L50: FYs
J51: 5) Cash Flow Analysis | L51: 2019 | M51: 2020 | N51: 2021 | O51: 2022 | P51: 2023 | Q51: 2024
J52: Operating Cash Flow
J53: Investing Cash Flow
J54: Financing Cash Flow
J56: Free Cash Flow
J57: FCF Yield

Sheet Financial Analysis
A6: Macy's, Inc. (NYSE:M) > Financial Analysis
A8: In Millions of USD, except per share items.
A10: Don’t have to calculate everything
A11: FA content
A12: Revenue breakdown analysis
A13: Profitability analysis
A14: Balance sheet
A15: Cash flow
A16: 1) Profitability | G16: 2019 | L16: 2020 | Q16: 2021 | V16: 2022 | AA16: 2023 | AF16: 2024
A17: For the Fiscal Period Ending | C17: 1Q 2019 | D17: 2Q 2019 | E17: 3Q 2019 | F17: 4Q 2019 | G17: 2019A | H17: 1Q 2020 | I17: 2Q 2020 | J17: 3Q 2020 | K17: 4Q 2020 | L17: 2020A | M17: 1Q 2021 | N17: 2Q 2021 | O17: 3Q 2021 | P17: 4Q 2021 | Q17: 2021A | R17: 1Q 2022 | S17: 2Q 2022 | T17: 3Q 2022 | U17: 4Q 2022 | V17: 2022A | W17: 1Q 2023 | X17: 2Q 2023 | Y17: 3Q 2023 | Z17: 4Q2023 | AA17: 2023A | AB17: 1Q 2024 | AC17: 2Q 2024 | AD17: 3Q 2024 | AE17: 4Q2024 | AF17: 2024A
A18: Currency: USD
A20: Revenue | C20: ='3FS'!C21 -> 5698 | D20: ='3FS'!D21 -> 5758 | E20: ='3FS'!E21 -> 5589 | F20: ='3FS'!F21 -> 8695 | G20: ='3FS'!G21 -> 25739 | H20: ='3FS'!H21 -> 5676 | I20: ='3FS'!I21 -> 5722 | J20: ='3FS'!J21 -> 5356 | ... AF20: ='3FS'!AF21 -> 23866
A21: EBITDA | C21: ='3FS'!C34 -> 244 | D21: ='3FS'!D34 -> 285 | E21: ='3FS'!E34 -> 117 | F21: ='3FS'!F34 -> 885 | G21: ='3FS'!G34 -> 1532 | H21: ='3FS'!H34 -> 167 | I21: ='3FS'!I34 -> 157 | J21: ='3FS'!J34 -> 48 | ... AF21: ='3FS'!AF34 -> 1263
A23: Gross Margin = (Revenue - COGS) / Revenue | C23: ='3FS'!C25/'3FS'!C21 -> 0.40645841 | D23: ='3FS'!D25/'3FS'!D21 -> 0.42341091 | E23: ='3FS'!E25/'3FS'!E21 -> 0.42279478 | F23: ='3FS'!F25/'3FS'!F21 -> 0.39183439 | G23: ='3FS'!G25/'3FS'!G21 -> 0.40887369 | H23: ='3FS'!H25/'3FS'!H21 -> 0.40045807 | I23: ='3FS'!I25/'3FS'!I21 -> 0.40667599 | J23: ='3FS'!J25/'3FS'!J21 -> 0.42008962 | ... AF23: ='3FS'!AF25/'3FS'!AF21 -> 0.4040057
A24: Gross Margin (%) | C24: =C23 -> 0.40645841 | D24: =D23 -> 0.42341091 | E24: =E23 -> 0.42279478 | F24: =F23 -> 0.39183439 | G24: =G23 -> 0.40887369 | H24: =H23 -> 0.40045807 | I24: =I23 -> 0.40667599 | J24: =J23 -> 0.42008962 | ... AF24: =AF23 -> 0.4040057
A25: Operating Margin = Operating Income / Revenue | C25: ='3FS'!C34/'3FS'!C21 -> 0.042822043 | D25: ='3FS'!D34/'3FS'!D21 -> 0.049496353 | E25: ='3FS'!E34/'3FS'!E21 -> 0.020933977 | F25: ='3FS'!F34/'3FS'!F21 -> 0.10178263 | G25: ='3FS'!G34/'3FS'!G21 -> 0.059520572 | H25: ='3FS'!H34/'3FS'!H21 -> 0.029422128 | I25: ='3FS'!I34/'3FS'!I21 -> 0.027437959 | J25: ='3FS'!J34/'3FS'!J21 -> 0.0089619119 | ... AF25: ='3FS'!AF34/'3FS'!AF21 -> 0.052920473
A26: EBITDA Margin (%) | C26: =C25 -> 0.042822043 | D26: =D25 -> 0.049496353 | E26: =E25 -> 0.020933977 | F26: =F25 -> 0.10178263 | G26: =G25 -> 0.059520572 | H26: =H25 -> 0.029422128 | I26: =I25 -> 0.027437959 | J26: =J25 -> 0.0089619119 | ... AF26: =AF25 -> 0.052920473
A27: Net Profit Margin = Net Income / Revenue | C27: ='3FS'!C59/'3FS'!C21 -> 0.024394524 | D27: ='3FS'!D59/'3FS'!D21 -> 0.028829455 | E27: ='3FS'!E59/'3FS'!E21 -> 0.011093219 | F27: ='3FS'!F59/'3FS'!F21 -> 0.085106383 | G27: ='3FS'!G59/'3FS'!G21 -> 0.043047515 | H27: ='3FS'!H59/'3FS'!H21 -> 0.023960536 | I27: ='3FS'!I59/'3FS'!I21 -> 0.01502971 | J27: ='3FS'!J59/'3FS'!J21 -> 0.00037341299 | ... AF27: ='3FS'!AF59/'3FS'!AF21 -> 0.0018855275
A28: Net Profit Margin (%) | C28: =C27 -> 0.024394524 | D28: =D27 -> 0.028829455 | E28: =E27 -> 0.011093219 | F28: =F27 -> 0.085106383 | G28: =G27 -> 0.043047515 | H28: =H27 -> 0.023960536 | I28: =I27 -> 0.01502971 | J28: =J27 -> 0.00037341299 | ... AF28: =AF27 -> 0.0018855275
A30: Return on Assets (ROA) = Net Income / Average Total Assets | C30: ='3FS'!C59/'3FS'!C95 -> 0.0071034342 | D30: ='3FS'!D59/'3FS'!D95 -> 0.008892222 | E30: ='3FS'!E59/'3FS'!E95 -> 0.0030450371 | F30: ='3FS'!F59/'3FS'!F95 -> 0.038553715 | G30: ='3FS'!G59/'3FS'!G95 -> 0.057726373 | H30: ='3FS'!H59/'3FS'!H95 -> 0.0063861758 | I30: ='3FS'!I59/'3FS'!I95 -> 0.0041463767 | J30: ='3FS'!J59/'3FS'!J95 -> 8.8703597e-05 | ... AF30: ='3FS'!AF59/'3FS'!AF95 -> 0.0027699126
A31: Return on Equity (ROE) = Net Income / Average Shareholders’ Equity | C31: ='3FS'!C59/'3FS'!C126 -> 0.023961386 | D31: ='3FS'!D59/'3FS'!D126 -> 0.028164235 | E31: ='3FS'!E59/'3FS'!E126 -> 0.010983171 | F31: ='3FS'!F59/'3FS'!F126 -> 0.11497825 | G31: ='3FS'!G59/'3FS'!G126 -> 0.17215662 | H31: ='3FS'!H59/'3FS'!H126 -> 0.018712163 | I31: ='3FS'!I59/'3FS'!I126 -> 0.011853894 | J31: ='3FS'!J59/'3FS'!J126 -> 0.00028433324 | ... AF31: ='3FS'!AF59/'3FS'!AF126 -> 0.011152416
A33: 2) Liquidity | G33: 2019 | L33: 2020 | Q33: 2021 | V33: 2022 | AA33: 2023 | AF33: 2024
A34: For the Fiscal Period Ending | C34: 1Q 2019 | D34: 2Q 2019 | E34: 3Q 2019 | F34: 4Q 2019 | G34: 2019A | H34: 1Q 2020 | I34: 2Q 2020 | J34: 3Q 2020 | K34: 4Q 2020 | L34: 2020A | M34: 1Q 2021 | N34: 2Q 2021 | O34: 3Q 2021 | P34: 4Q 2021 | Q34: 2021A | R34: 1Q 2022 | S34: 2Q 2022 | T34: 3Q 2022 | U34: 4Q 2022 | V34: 2022A | W34: 1Q 2023 | X34: 2Q 2023 | Y34: 3Q 2023 | Z34: 4Q2023 | AA34: 2023A | AB34: 1Q 2024 | AC34: 2Q 2024 | AD34: 3Q 2024 | AE34: 4Q2024 | AF34: 2024A
A35: Currency: USD
A37: Current Ratio = Current Assets / Current Liabilities | C37: ='3FS'!C84/'3FS'!C106 -> 1.5186134 | D37: ='3FS'!D84/'3FS'!D106 -> 1.5320241 | E37: ='3FS'!E84/'3FS'!E106 -> 1.3449721 | F37: ='3FS'!F84/'3FS'!F106 -> 1.422974 | G37: ='3FS'!G84/'3FS'!G106 -> 1.422974 | H37: ='3FS'!H84/'3FS'!H106 -> 1.4156206 | I37: ='3FS'!I84/'3FS'!I106 -> 1.4746565 | J37: ='3FS'!J84/'3FS'!J106 -> 1.2812162 | ... AF37: ='3FS'!AF84/'3FS'!AF106 -> 1.3435569
A38: Quick Ratio = (Current Assets - Inventory) / Current Liabilities | C38: =('3FS'!C84-'3FS'!C80)/'3FS'!C106 -> 0.47646248 | D38: =('3FS'!D84-'3FS'!D80)/'3FS'!D106 -> 0.42602098 | E38: =('3FS'!E84-'3FS'!E80)/'3FS'!E106 -> 0.23587834 | F38: =('3FS'!F84-'3FS'!F80)/'3FS'!F106 -> 0.41704893 | G38: =('3FS'!G84-'3FS'!G80)/'3FS'!G106 -> 0.41704893 | H38: =('3FS'!H84-'3FS'!H80)/'3FS'!H106 -> 0.3201833 | I38: =('3FS'!I84-'3FS'!I80)/'3FS'!I106 -> 0.34174364 | J38: =('3FS'!J84-'3FS'!J80)/'3FS'!J106 -> 0.16129032 | ... AF38: =('3FS'!AF84-'3FS'!AF80)/'3FS'!AF106 -> 0.38128861
A40: 3) Leverage, Solvency | G40: 2019 | L40: 2020 | Q40: 2021 | V40: 2022 | AA40: 2023 | AF40: 2024
A41: For the Fiscal Period Ending | C41: 1Q 2019 | D41: 2Q 2019 | E41: 3Q 2019 | F41: 4Q 2019 | G41: 2019A | H41: 1Q 2020 | I41: 2Q 2020 | J41: 3Q 2020 | K41: 4Q 2020 | L41: 2020A | M41: 1Q 2021 | N41: 2Q 2021 | O41: 3Q 2021 | P41: 4Q 2021 | Q41: 2021A | R41: 1Q 2022 | S41: 2Q 2022 | T41: 3Q 2022 | U41: 4Q 2022 | V41: 2022A | W41: 1Q 2023 | X41: 2Q 2023 | Y41: 3Q 2023 | Z41: 4Q2023 | AA41: 2023A | AB41: 1Q 2024 | AC41: 2Q 2024 | AD41: 3Q 2024 | AE41: 4Q2024 | AF41: 2024A
A42: Currency: USD
A44: Debt-to-Equity = Total Debt / Shareholders’ Equity | C44: ='3FS'!C115/'3FS'!C126 -> 2.3732115 | D44: ='3FS'!D115/'3FS'!D126 -> 2.1672888 | E44: ='3FS'!E115/'3FS'!E126 -> 2.6069088 | F44: ='3FS'!F115/'3FS'!F126 -> 1.9822871 | G44: ='3FS'!G115/'3FS'!G126 -> 1.9822871 | H44: ='3FS'!H115/'3FS'!H126 -> 2.0601266 | I44: ='3FS'!I115/'3FS'!I126 -> 1.9884218 | J44: ='3FS'!J115/'3FS'!J126 -> 2.3443276 | ... AF44: ='3FS'!AF115/'3FS'!AF126 -> 3.0262701
A45: Debt-to-Assets = Total Debt / Total Assets | C45: ='3FS'!C115/'3FS'!C95 -> 0.70354661 | D45: ='3FS'!D115/'3FS'!D95 -> 0.68427255 | E45: ='3FS'!E115/'3FS'!E95 -> 0.72275429 | F45: ='3FS'!F115/'3FS'!F95 -> 0.66468688 | G45: ='3FS'!G115/'3FS'!G95 -> 0.66468688 | H45: ='3FS'!H115/'3FS'!H95 -> 0.70308978 | I45: ='3FS'!I115/'3FS'!I95 -> 0.69553059 | J45: ='3FS'!J115/'3FS'!J95 -> 0.73136116 | ... AF45: ='3FS'!AF115/'3FS'!AF95 -> 0.75163117
A46: Interest Coverage Ratio = EBITDA / Interest Expense | C46: ='3FS'!C34/'3FS'!C39 -> -3.6969697 | D46: ='3FS'!D34/'3FS'!D39 -> -4.5967742 | E46: ='3FS'!E34/'3FS'!E39 -> -1.9830508 | F46: ='3FS'!F34/'3FS'!F39 -> -18.061224 | G46: ='3FS'!G34/'3FS'!G39 -> -6.4915254 | H46: ='3FS'!H34/'3FS'!H39 -> -3.5531915 | I46: ='3FS'!I34/'3FS'!I39 -> -3.3404255 | J46: ='3FS'!J34/'3FS'!J39 -> -1 | ... AF46: ='3FS'!AF34/'3FS'!AF39 -> -9.3555556
A47: Debt Service Coverage Ratio (DSCR) = EBITDA / Total Debt Service Debt service = (Interest + Debt Repayments) | C47: ='3FS'!C34/('3FS'!C39+'3FS'!C164) -> -3.0886076 | D47: ='3FS'!D34/('3FS'!D39+'3FS'!D164) -> -0.57459677 | E47: ='3FS'!E34/('3FS'!E39+'3FS'!E164) -> 4.3333333 | F47: ='3FS'!F34/('3FS'!F39+'3FS'!F164) -> -1.0573477 | G47: ='3FS'!G34/('3FS'!G39+'3FS'!G164) -> -1.1061372 | H47: ='3FS'!H34/('3FS'!H39+'3FS'!H164) -> -1.7578947 | I47: ='3FS'!I34/('3FS'!I39+'3FS'!I164) -> -0.94578313 | J47: ='3FS'!J34/('3FS'!J39+'3FS'!J164) -> 0.62337662 | ... AF47: ='3FS'!AF34/('3FS'!AF39+'3FS'!AF164) -> -1.1502732
A49: 4) Efficiency | G49: 2019 | L49: 2020 | Q49: 2021 | V49: 2022 | AA49: 2023 | AF49: 2024
A50: For the Fiscal Period Ending | C50: 1Q 2019 | D50: 2Q 2019 | E50: 3Q 2019 | F50: 4Q 2019 | G50: 2019A | H50: 1Q 2020 | I50: 2Q 2020 | J50: 3Q 2020 | K50: 4Q 2020 | L50: 2020A | M50: 1Q 2021 | N50: 2Q 2021 | O50: 3Q 2021 | P50: 4Q 2021 | Q50: 2021A | R50: 1Q 2022 | S50: 2Q 2022 | T50: 3Q 2022 | U50: 4Q 2022 | V50: 2022A | W50: 1Q 2023 | X50: 2Q 2023 | Y50: 3Q 2023 | Z50: 4Q 2023 | AA50: 2023A | AB50: 1Q 2024 | AC50: 2Q 2024 | AD50: 3Q 2024 | AE50: 4Q 2024 | AF50: 2024A
A51: Currency: USD
A53: Asset Turnover = Revenue / Average Total Assets | C53: =C54/C55 -> 0.2911897 | D53: =D54/D55 -> 0.30844225 | E53: =E54/E55 -> 0.27449536 | F53: =F54/F55 -> 0.45300615 | G53: =G54/G55 -> 1.340992 | H53: =H54/AVERAGE(C55,H55) -> 0.26938136 | I53: =I54/AVERAGE(D55,I55) -> 0.29039052 | J53: =J54/AVERAGE(E55,J55) -> 0.24965041 | K53: =K54/AVERAGE(F55,K55) -> 0.4249616 | L53: =L54/AVERAGE(G55,L55) -> 1.2465441 | M53: =M54/AVERAGE(H55,M55) -> 0.1578855 | N53: =N54/AVERAGE(I55,N55) -> 0.19434233 | O53: =O54/AVERAGE(J55,O55) -> 0.20042624 | ... AF53: =AF54/AVERAGE(AA55,AF55) -> 1.4415318
A54: Total Revenue | C54: 5698 | D54: 5758 | E54: 5589 | F54: 8695 | G54: 25739 | H54: 5504 | I54: 5722 | J54: 5356 | K54: 8577 | L54: 25159 | M54: 3148 | N54: 3727 | O54: 4185 | P54: 7037 | Q54: 18097 | R54: 4865 | S54: 5844 | T54: 5653 | U54: 8930 | V54: 25399 | W54: 5565 | X54: 5834 | Y54: 5467 | Z54: 8583 | AA54: 25449 | AB54: 5173 | AC54: 5280 | AD54: 5038 | AE54: 8375 | AF54: 23866
A55: Total Assets | C55: 19568 | D55: 18668 | E55: 20361 | F55: 19194 | G55: 19194 | H55: 21296 | I55: 20741 | J55: 22547 | K55: 21172 | L55: 21172 | M55: 18581 | N55: 17614 | O55: 19214 | P55: 17706 | Q55: 17706 | R55: 18082 | S55: 18417 | T55: 18279 | U55: 17590 | V55: 17590 | W55: 16972 | X55: 16342 | Y55: 18230 | Z55: 16866 | AA55: 16866 | AB55: 16868 | AC55: 16304 | AD55: 18111 | AE55: 16246 | AF55: 16246
A57: Inventory Turnover = COGS / Average Inventory | C57: =C58/C59 -> 0.63919864 | D57: =D58/D59 -> 0.66989508 | E57: =E58/E59 -> 0.4513782 | F57: =F58/F59 -> 1.0047501 | G57: =G58/G59 -> 2.8911267 | H57: =H58/AVERAGE(C59,H59) -> 0.63082769 | I57: =I58/AVERAGE(D59,I59) -> 0.68002003 | J57: =J58/AVERAGE(E59,J59) -> 0.43129903 | K57: =K58/AVERAGE(F59,K59) -> 1.0077505 | L57: =L58/AVERAGE(G59,L59) -> 2.9030715 | M57: =M58/AVERAGE(H59,M59) -> 0.42241627 | N57: =N58/AVERAGE(I59,N59) -> 0.63128556 | O57: =O58/AVERAGE(J59,O59) -> 0.41435484 | ... AF57: =AF58/AVERAGE(AA59,AF59) -> 3.2969402
A58: Cost Of Goods Sold | C58: 3382 | D58: 3320 | E58: 3226 | F58: 5288 | G58: 15216 | H58: 3403 | I58: 3395 | J58: 3106 | K58: 5266 | L58: 15170 | M58: 2201 | N58: 2718 | O58: 2569 | P58: 4798 | Q58: 12286 | R58: 2889 | S58: 3353 | T58: 3207 | U58: 5507 | V58: 14956 | W58: 3231 | X58: 3422 | Y58: 3204 | Z58: 5450 | AA58: 15307 | AB58: 2988 | AC58: 3176 | AD58: 2905 | AE58: 5154 | AF58: 14223
A59: Inventory | C59: 5291 | D59: 4956 | E59: 7147 | F59: 5263 | G59: 5263 | H59: 5498 | I59: 5029 | J59: 7256 | K59: 5188 | L59: 5188 | M59: 4923 | N59: 3582 | O59: 5144 | P59: 3774 | Q59: 3774 | R59: 4230 | S59: 4298 | T59: 6141 | U59: 4383 | V59: 4383 | W59: 4956 | X59: 4610 | Y59: 6403 | Z59: 4267 | AA59: 4267 | AB59: 4607 | AC59: 4129 | AD59: 6025 | AE59: 4361 | AF59: 4361
A61: Receivables Turnover = Revenue / Average Accounts Receivable | C61: =C62/C63 -> 22.792 | D61: =D62/D63 -> 22.061303 | E61: =E62/E63 -> 31.05 | F61: =F62/F63 -> 21.7375 | G61: =G62/G63 -> 64.3475 | H61: =H62/AVERAGE(C63,H63) -> 22.603696 | I61: =I62/AVERAGE(D63,I63) -> 22.842315 | J61: =J62/AVERAGE(E63,J63) -> 30.174648 | K61: =K62/AVERAGE(F63,K63) -> 21.203956 | L61: =L62/AVERAGE(G63,L63) -> 62.197775 | M61: =M62/AVERAGE(H63,M63) -> 15.469287 | N61: =N62/AVERAGE(I63,N63) -> 17.580189 | O61: =O62/AVERAGE(J63,O63) -> 23.25 | ... AF61: =AF62/AVERAGE(AA63,AF63) -> 80.492411
A62: Total Revenue | C62: 5698 | D62: 5758 | E62: 5589 | F62: 8695 | G62: 25739 | H62: 5504 | I62: 5722 | J62: 5356 | K62: 8577 | L62: 25159 | M62: 3148 | N62: 3727 | O62: 4185 | P62: 7037 | Q62: 18097 | R62: 4865 | S62: 5844 | T62: 5653 | U62: 8930 | V62: 25399 | W62: 5565 | X62: 5834 | Y62: 5467 | Z62: 8583 | AA62: 25449 | AB62: 5173 | AC62: 5280 | AD62: 5038 | AE62: 8375 | AF62: 23866
A63: Accounts Receivables | C63: 250 | D63: 261 | E63: 180 | F63: 400 | G63: 400 | H63: 237 | I63: 240 | J63: 175 | K63: 409 | L63: 409 | M63: 170 | N63: 184 | O63: 185 | P63: 276 | Q63: 276 | R63: 205 | S63: 221 | T63: 212 | U63: 297 | V63: 297 | W63: 233 | X63: 219 | Y63: 204 | Z63: 300 | AA63: 300 | AB63: 255 | AC63: 223 | AD63: 218 | AE63: 293 | AF63: 293
A65: Payables Turnover = COGS / Average Accounts Payable | C65: =C66/C67 -> 0.91036339 | D65: =D66/D67 -> 0.94911378 | E65: =E66/E67 -> 0.5970757 | F65: =F66/F67 -> 2.0045489 | G65: =G66/G67 -> 5.7680061 | H65: =H66/AVERAGE(C67,H67) -> 0.95082425 | I65: =I66/AVERAGE(D67,I67) -> 1.0166193 | J65: =J66/AVERAGE(E67,J67) -> 0.58537505 | K65: =K66/AVERAGE(F67,K67) -> 1.9882953 | L65: =L66/AVERAGE(G67,L67) -> 5.7277704 | M65: =M66/AVERAGE(H67,M67) -> 0.59390178 | N65: =N66/AVERAGE(I67,N67) -> 0.8156039 | O65: =O66/AVERAGE(J67,O67) -> 0.48942656 | ... AF65: =AF66/AVERAGE(AA67,AF67) -> 5.1402241
A66: Cost Of Goods Sold | C66: 3382 | D66: 3320 | E66: 3226 | F66: 5288 | G66: 15216 | H66: 3403 | I66: 3395 | J66: 3106 | K66: 5266 | L66: 15170 | M66: 2201 | N66: 2718 | O66: 2569 | P66: 4798 | Q66: 12286 | R66: 2889 | S66: 3353 | T66: 3207 | U66: 5507 | V66: 14956 | W66: 3231 | X66: 3422 | Y66: 3204 | Z66: 5450 | AA66: 15307 | AB66: 2988 | AC66: 3176 | AD66: 2905 | AE66: 5154 | AF66: 14223
A67: Accounts Payable | C67: 3715 | D67: 3498 | E67: 5403 | F67: 2638 | G67: 2638 | H67: 3443 | I67: 3181 | J67: 5209 | K67: 2659 | L67: 2659 | M67: 3969 | N67: 3484 | O67: 5289 | P67: 2856 | Q67: 2856 | R67: 4353 | S67: 4391 | T67: 5787 | U67: 3280 | V67: 3280 | W67: 4648 | X67: 4113 | Y67: 5951 | Z67: 2874 | AA67: 2874 | AB67: 4074 | AC67: 3696 | AD67: 5328 | AE67: 2660 | AF67: 2660
A69: Days Sales Outstanding (DSO) = (Average Accounts Receivable / Revenue) × 365 | C69: =(1/C61)*365 -> 16.014391 | D69: =(1/D61)*365 -> 16.544807 | E69: =(1/E61)*365 -> 11.755233 | F69: =(1/F61)*365 -> 16.791259 | G69: =(1/G61)*365 -> 5.672326 | H69: =(1/H61)*365 -> 16.147802 | I69: =(1/I61)*365 -> 15.979116 | J69: =(1/J61)*365 -> 12.096247 | ... AF69: =(1/AF61)*365 -> 4.534589
A70: Days Inventory Outstanding (DIO) = (Average Inventory / COGS) × 365 | C70: =(1/C57)*365 -> 571.0275 | D70: =(1/D57)*365 -> 544.86145 | E70: =(1/E57)*365 -> 808.63453 | F70: =(1/F57)*365 -> 363.27439 | G70: =(1/G57)*365 -> 126.24836 | H70: =(1/H57)*365 -> 578.60491 | I70: =(1/I57)*365 -> 536.7489 | J70: =(1/J57)*365 -> 846.28059 | ... AF70: =(1/AF57)*365 -> 110.70871
A71: Days Payables Outstanding (DPO) = (Average Accounts Payable / COGS) x 365 | C71: =(1/C65)*365 -> 400.93879 | D71: =(1/D65)*365 -> 384.56928 | E71: =(1/E65)*365 -> 611.31277 | F71: =(1/F65)*365 -> 182.08585 | G71: =(1/G65)*365 -> 63.2801 | H71: =(1/H65)*365 -> 383.87746 | I71: =(1/I65)*365 -> 359.03314 | J71: =(1/J65)*365 -> 623.53187 | ... AF71: =(1/AF65)*365 -> 71.008578
A73: Cash Conversion Cycle (CCC) = DIO + DSO - Days Payables Outstanding (DPO) | C73: =C69+C70-C71 -> 186.1031 | D73: =D69+D70-D71 -> 176.83698 | E73: =E69+E70-E71 -> 209.07699 | F73: =F69+F70-F71 -> 197.9798 | G73: =G69+G70-G71 -> 68.640583 | H73: =H69+H70-H71 -> 210.87525 | I73: =I69+I70-I71 -> 193.69487 | J73: =J69+J70-J71 -> 234.84496 | ... AF73: =AF69+AF70-AF71 -> 44.234723
A75: 5) Cash Flow Analysis | G75: 2019 | L75: 2020 | Q75: 2021 | V75: 2022 | AA75: 2023 | AF75: 2024
A76: For the Fiscal Period Ending | C76: 1Q 2019 | D76: 2Q 2019 | E76: 3Q 2019 | F76: 4Q 2019 | G76: 2019A | H76: 1Q 2020 | I76: 2Q 2020 | J76: 3Q 2020 | K76: 4Q 2020 | L76: 2020A | M76: 1Q 2021 | N76: 2Q 2021 | O76: 3Q 2021 | P76: 4Q 2021 | Q76: 2021A | R76: 1Q 2022 | S76: 2Q 2022 | T76: 3Q 2022 | U76: 4Q 2022 | V76: 2022A | W76: 1Q 2023 | X76: 2Q 2023 | Y76: 3Q 2023 | Z76: 4Q2023 | AA76: 2023A | AB76: 1Q 2024 | AC76: 2Q 2024 | AD76: 3Q 2024 | AE76: 4Q2024 | AF76: 2024A
A77: Currency: USD
A79: Operating CF | C79: ='3FS'!C151 -> 322 | D79: ='3FS'!D151 -> 222 | E79: ='3FS'!E151 -> -115 | F79: ='3FS'!F151 -> 1306 | G79: ='3FS'!G151 -> 1735 | H79: ='3FS'!H151 -> -38 | I79: ='3FS'!I151 -> 388 | J79: ='3FS'!J151 -> -178 | ... AF79: ='3FS'!AF151 -> 1305
A80: Investing CF | C80: ='3FS'!C161 -> -156 | D80: ='3FS'!D161 -> -156 | E80: ='3FS'!E161 -> -237 | F80: ='3FS'!F161 -> 93 | G80: ='3FS'!G161 -> -456 | H80: ='3FS'!H161 -> -237 | I80: ='3FS'!I161 -> -217 | J80: ='3FS'!J161 -> -275 | ... AF80: ='3FS'!AF161 -> -913
A81: Financing CF | C81: ='3FS'!C174 -> -99 | D81: ='3FS'!D174 -> -537 | E81: ='3FS'!E174 -> 20 | F81: ='3FS'!F174 -> -928 | G81: ='3FS'!G174 -> -1544 | H81: ='3FS'!H174 -> -158 | I81: ='3FS'!I174 -> -239 | J81: ='3FS'!J174 -> 57 | ... AF81: ='3FS'!AF174 -> -220
A83: Free Cash Flow (FCF) = OCF - Capital Expenditures | C83: ='3FS'!C151-ABS('3FS'!C153) -> 190 | D83: ='3FS'!D151-ABS('3FS'!D153) -> 79 | E83: ='3FS'!E151-ABS('3FS'!E153) -> -308 | F83: ='3FS'!F151-ABS('3FS'!F153) -> 1117 | G83: ='3FS'!G151-ABS('3FS'!G153) -> 1078 | H83: ='3FS'!H151-ABS('3FS'!H153) -> -242 | I83: ='3FS'!I151-ABS('3FS'!I153) -> 214 | J83: ='3FS'!J151-ABS('3FS'!J153) -> -423 | ... AF83: ='3FS'!AF151-ABS('3FS'!AF153) -> 674
A85: FCF Yield = FCF / Market Capitalization | C85: =C83/'Key Stats'!$B$53 -> 0.051672819 | D85: =D83/'Key Stats'!$B$53 -> 0.021485014 | E85: =E83/'Key Stats'!$B$53 -> -0.083764359 | F85: =F83/'Key Stats'!$B$53 -> 0.30378178 | G85: =G83/'Key Stats'!$B$53 -> 0.29317526 | H85: =H83/'Key Stats'!$B$53 -> -0.065814854 | I85: =I83/'Key Stats'!$B$53 -> 0.058199912 | J85: =J83/'Key Stats'!$B$53 -> -0.11504001 | ... AF85: =AF83/'Key Stats'!$B$53 -> 0.18330253
A86: Cash Flow to Debt Ratio = OCF / Total Debt | C86: ='3FS'!C151/'3FS'!C115 -> 0.023389264 | D86: ='3FS'!D151/'3FS'!D115 -> 0.017379051 | E86: ='3FS'!E151/'3FS'!E115 -> -0.0078146235 | F86: ='3FS'!F151/'3FS'!F115 -> 0.10236714 | G86: ='3FS'!G151/'3FS'!G115 -> 0.1359931 | H86: ='3FS'!H151/'3FS'!H115 -> -0.0025379016 | I86: ='3FS'!I151/'3FS'!I115 -> 0.026895882 | J86: ='3FS'!J151/'3FS'!J115 -> -0.010794421 | ... AF86: ='3FS'!AF151/'3FS'!AF115 -> 0.10687085

Sheet FA Graphs
A6: Macy's, Inc. (NYSE:M) > Financial Analysis
A8: In Millions of USD, except per share items.
A16: 1) Profitability | C16: 2019 | D16: 2020 | E16: 2021 | F16: 2022 | G16: 2023 | H16: 2024
A17: For the Fiscal Period Ending | C17: 2019 | D17: 2020 | E17: 2021 | F17: 2022 | G17: 2023 | H17: 2024
A18: Currency: USD
A20: Revenue (US$m) | C20: 25739 | D20: 25331 | E20: 18097 | F20: 25399 | G20: 25449 | H20: 23866
A21: Operating Income (US$m) | C21: 1532 | D21: 1159 | E21: -902 | F21: 2334 | G21: 1640 | H21: 1263
A23: Gross Margin = (Revenue - COGS) / Revenue | C23: 0.40887369 | D23: 0.40108957 | E23: 0.32110295 | F23: 0.41115792 | G23: 0.39695076 | H23: 0.4040057
A24: Gross Margin (%) | C24: 0.40887369 | D24: 0.40108957 | E24: 0.32110295 | F24: 0.41115792 | G24: 0.39695076 | H24: 0.4040057
A25: Operating Margin = Operating Income / Revenue | C25: 0.059520572 | D25: 0.045754214 | E25: -0.049842515 | F25: 0.091893382 | G25: 0.064442611 | H25: 0.052920473
A26: Operating Margin (%) | C26: 0.059520572 | D26: 0.045754214 | E26: -0.049842515 | F26: 0.091893382 | G26: 0.064442611 | H26: 0.052920473
A27: Net Profit Margin = Net Income / Revenue | C27: 0.043047515 | D27: 0.022265209 | E27: -0.21793667 | F27: 0.056301429 | G27: 0.045031239 | H27: 0.0018855275
A28: Net Profit Margin (%) | C28: 0.043047515 | D28: 0.022265209 | E28: -0.21793667 | F28: 0.056301429 | G28: 0.045031239 | H28: 0.0018855275
A30: Return on Assets (ROA) = Net Income / Average Total Assets | C30: 0.057726373 | D30: 0.026638957 | E30: -0.22274935 | F30: 0.081296191 | G30: 0.06794735 | H30: 0.0027699126
A31: Return on Equity (ROE) = Net Income / Average Shareholders’ Equity | C31: 0.17215662 | D31: 0.088442841 | E31: -1.5448492 | F31: 0.39491853 | G31: 0.28074473 | H31: 0.011152416
A33: 2) Liquidity | C33: 2019 | D33: 2020 | E33: 2021 | F33: 2022 | G33: 2023 | H33: 2024
A34: For the Fiscal Period Ending | C34: 2019 | D34: 2020 | E34: 2021 | F34: 2022 | G34: 2023 | H34: 2024
A35: Currency: USD
A37: Current Ratio | C37: 1.422974 | D37: 1.1843478 | E37: 1.1543775 | F37: 1.2477843 | G37: 1.2040732 | H37: 1.3435569
A38: Quick Ratio | C38: 0.41704893 | D38: 0.28208696 | E38: 0.44987866 | F38: 0.43851551 | G38: 0.32627031 | H38: 0.38128861
A40: 3) Leverage, Solvency | C40: 2019 | D40: 2020 | E40: 2021 | F40: 2022 | G40: 2023 | H40: 2024
A41: For the Fiscal Period Ending | C41: 2019 | D41: 2020 | E41: 2021 | F41: 2022 | G41: 2023 | H41: 2024
A42: Currency: USD
A44: Debt-to-Equity Ratio | C44: 1.9822871 | D44: 2.3200565 | E44: 5.9353702 | F44: 3.8577741 | G44: 3.1317981 | H44: 3.0262701
A46: Assets | C46: 19194 | D46: 21172 | E46: 17706 | F46: 17590 | G46: 16866 | H46: 16246
A47: Liabilities | C47: 12758 | D47: 14795 | E47: 15153 | F47: 13969 | G47: 12784 | H47: 12211
A49: Debt-to-Assets (%) | C49: 0.66468688 | D49: 0.6988003 | E49: 0.85581159 | F49: 0.7941444 | G49: 0.75797462 | H49: 0.75163117
A50: Interest Coverage Ratio | C50: -6.4915254 | D50: -6.2648649 | E50: 3.2214286 | F50: -9.1529412 | G50: -10.123457 | H50: -9.3555556
A51: Debt Service Coverage Ratio | C51: -1.1061372 | D51: -1.3732227 | E51: 0.38845823 | F51: -0.78401075 | G51: -0.47632878 | H51: -1.1502732
A53: 4) Efficiency | C53: 2019 | D53: 2020 | E53: 2021 | F53: 2022 | G53: 2023 | H53: 2024
A54: For the Fiscal Period Ending | C54: 2019 | D54: 2020 | E54: 2021 | F54: 2022 | G54: 2023 | H54: 2024
A55: Currency: USD
A57: Asset Turnover | C57: 1.340992 | D57: 1.2465441 | E57: 0.93096353 | F57: 1.4391999 | G57: 1.4771883 | H57: 1.4415318
A58: Inventory Turnover | C58: 2.8911267 | D58: 2.9030715 | E58: 2.7417987 | F58: 3.6670344 | G58: 3.5391908 | H58: 3.2969402
A59: Receivables Turnover | C59: 64.3475 | D59: 62.197775 | E59: 52.837956 | F59: 88.652705 | G59: 85.256281 | H59: 80.492411
A60: Payables Turnover | C60: 5.7680061 | D60: 5.7277704 | E60: 4.455485 | F60: 4.874837 | G60: 4.9746506 | H60: 5.1402241
A63: Days Sales Outstanding (DSO) | C63: 5.672326 | D63: 5.8683771 | E63: 6.9079129 | F63: 4.1171897 | G63: 4.2812095 | H63: 4.534589
A64: Days Inventory Outstanding (DIO) | C64: 126.24836 | D64: 125.72891 | E64: 133.12429 | F64: 99.535471 | G64: 103.13092 | H64: 110.70871
A65: Days Payables Outstanding (DPO) | C65: 63.2801 | D65: 63.724621 | E65: 81.921496 | F65: 74.874298 | G65: 73.371987 | H65: 71.008578
A67: Cash Conversion Cycle (CCC) | C67: 68.640583 | D67: 67.872662 | E67: 58.110705 | F67: 28.778362 | G67: 34.040143 | H67: 44.234723
A69: 5) Cash Flow Analysis | C69: 2019 | D69: 2020 | E69: 2021 | F69: 2022 | G69: 2023 | H69: 2024
A70: For the Fiscal Period Ending | C70: 2019 | D70: 2020 | E70: 2021 | F70: 2022 | G70: 2023 | H70: 2024
A71: Currency: USD
A73: Operating | C73: 1735 | D73: 1608 | E73: 649 | F73: 2712 | G73: 1615 | H73: 1305
A74: Investing | C74: -456 | D74: -1002 | E74: -325 | F74: -370 | G74: -1169 | H74: -913
A75: Financing | C75: -1544 | D75: -1123 | E75: 699 | F75: -2381 | G75: -1296 | H75: -220
A77: Free Cash Flow (FCF) | C77: 1078 | D77: 706 | E77: 311 | F77: 2358 | G77: 727 | H77: 674
A79: FCF Yield = FCF / Market Capitalization | C79: 0.29317526 | D79: 0.19200532 | E79: 0.084580246 | F79: 0.64128688 | G79: 0.19771652 | H79: 0.18330253
A80: Cash Flow to Debt Ratio = OCF / Total Debt | C80: 0.1359931 | D80: 0.10868537 | E80: 0.042829803 | F80: 0.19414418 | G80: 0.12632979 | H80: 0.10687085
A82: 6) Revenue Breakdown | C82: 2019 | D82: 2020 | E82: 2021 | F82: 2022 | G82: 2023 | H82: 2024
A83: For the Fiscal Period Ending | C83: 2019 | D83: 2020 | E83: 2021 | F83: 2022 | G83: 2023 | H83: 2024
A84: Currency: USD
A85: a) Revenue Segments Breakdown
A86: Product/ Broad Segment
A87: Women’s Accessories, Intimate Apparel, Shoes and Cosmetics | C87: 9457 | D87: 9454 | E87: 7206 | F87: 10119 | G87: 9597 | H87: 9520
A88: Men’s and Kids | C88: 5699 | D88: 5628 | E88: 3486 | F88: 5252 | G88: 5297 | H88: 4918
A89: Women’s Apparel | C89: 5642 | D89: 5411 | E89: 2909 | F89: 4433 | G89: 5349 | H89: 4861
A90: Home/Other | C90: 4173 | D90: 4067 | E90: 3745 | F90: 4656 | G90: 4199 | H90: 3793
A91: Credit Card | C91: 768 | D91: 771 | E91: 751 | F91: 832 | G91: 863 | H91: 619
A92: Macy's Media Network | C92: - | D92: - | E92: - | F92: - | G92: 144 | H92: 155
A94: Total Revenue | C94: =SUM(C87:C92) -> 25739 | D94: =SUM(D87:D92) -> 25331 | E94: =SUM(E87:E92) -> 18097 | F94: =SUM(F87:F92) -> 25292 | G94: =SUM(G87:G92) -> 25449 | H94: =SUM(H87:H92) -> 23866
A96: b) Revenue Channels Proportion
A97: Women’s Accessories, Intimate Apparel, Shoes and Cosmetics | C97: =C87/$C$94 -> 0.36741909 | D97: =D87/$D$94 -> 0.37321859 | E97: =E87/$E$94 -> 0.39818754 | F97: =F87/$F$94 -> 0.40008698 | G97: =G87/$G$94 -> 0.37710716 | H97: =H87/$H$94 -> 0.39889382
A98: Men’s and Kids | C98: =C88/$C$94 -> 0.22141497 | D98: =D88/$D$94 -> 0.22217836 | E98: =E88/$E$94 -> 0.19262861 | F98: =F88/$F$94 -> 0.20765459 | G98: =G88/$G$94 -> 0.20814177 | H98: =H88/$H$94 -> 0.20606721
A99: Women’s Apparel | C99: =C89/$C$94 -> 0.21920044 | D99: =D89/$D$94 -> 0.21361178 | E99: =E89/$E$94 -> 0.16074487 | F99: =F89/$F$94 -> 0.17527281 | G99: =G89/$G$94 -> 0.21018508 | H99: =H89/$H$94 -> 0.20367887
A100: Home/Other | C100: =C90/$C$94 -> 0.16212751 | D100: =D90/$D$94 -> 0.16055426 | E100: =E90/$E$94 -> 0.20694038 | F100: =F90/$F$94 -> 0.18408983 | G100: =G90/$G$94 -> 0.16499666 | H100: =H90/$H$94 -> 0.15892902
A101: Credit Card | C101: =C91/$C$94 -> 0.029837989 | D101: =D91/$D$94 -> 0.030437014 | E101: =E91/$E$94 -> 0.041498591 | F101: =F91/$F$94 -> 0.032895777 | G101: =G91/$G$94 -> 0.033910959 | H101: =H91/$H$94 -> 0.025936479
A102: Macy's Media Network | C102: =C92/$C$94 -> #VALUE! | D102: =D92/$D$94 -> #VALUE! | E102: =E92/$E$94 -> #VALUE! | F102: =F92/$F$94 -> #VALUE! | G102: =G92/$G$94 -> 0.0056583756 | H102: =H92/$H$94 -> 0.0064945948

Sheet 3FS
A5: Macy's, Inc. (NYSE:M) > Financials > 3 Financial Statements
A7: In Millions of USD, except per share items.
A14: Income Statement | G14: 2019 | L14: 2020 | Q14: 2021 | V14: 2022 | AA14: 2023 | AF14: 2024 | AG14: 2025
A15: For the Fiscal Period Ending | C15: 1Q 2019 | D15: 2Q 2019 | E15: 3Q 2019 | F15: 4Q 2019 | G15: 2019A | H15: 1Q 2020 | I15: 2Q 2020 | J15: 3Q 2020 | K15: 4Q 2020 | L15: 2020A | M15: 1Q 2021 | N15: 2Q 2021 | O15: 3Q 2021 | P15: 4Q 2021 | Q15: 2021A | R15: 1Q 2022 | S15: 2Q 2022 | T15: 3Q 2022 | U15: 4Q 2022 | V15: 2022A | W15: 1Q 2023 | X15: 2Q 2023 | Y15: 3Q 2023 | Z15: 4Q2023 | AA15: 2023A | AB15: 1Q 2024 | AC15: 2Q 2024 | AD15: 3Q 2024 | AE15: 4Q2024 | AF15: 2024A
A16: Currency: USD
A18: Revenue | C18: 5541 | D18: 5572 | E18: 5404 | F18: 8455 | G18: =SUM(C18:F18) -> 24972 | H18: 5504 | I18: 5546 | J18: 5173 | K18: 8337 | L18: =SUM(H18:K18) -> 24560 | M18: 3017 | N18: 3559 | O18: 3990 | P18: 6780 | Q18: =SUM(M18:P18) -> 17346 | R18: 4706 | S18: 5647 | T18: 5440 | U18: 8666 | V18: =SUM(R18:U18) -> 24459 | W18: 5348 | X18: 5600 | Y18: 5230 | Z18: 8264 | AA18: =SUM(W18:Z18) -> 24442 | AB18: 4982 | AC18: 5130 | AD18: 4860 | AE18: 8120 | AF18: =SUM(AB18:AE18) -> 23092
A19: Other Revenue | C19: 157 | D19: 186 | E19: 185 | F19: 240 | G19: =SUM(C19:F19) -> 768 | H19: 172 | I19: 176 | J19: 183 | K19: 240 | L19: =SUM(H19:K19) -> 771 | M19: 131 | N19: 168 | O19: 195 | P19: 257 | Q19: =SUM(M19:P19) -> 751 | R19: 159 | S19: 197 | T19: 213 | U19: 264 | V19: =SUM(R19:U19) -> 833 | W19: 217 | X19: 234 | Y19: 237 | Z19: 319 | AA19: =SUM(W19:Z19) -> 1007 | AB19: 191 | AC19: 150 | AD19: 178 | AE19: 255 | AF19: =SUM(AB19:AE19) -> 774
A20: Year end adjustments | C20: - | D20: - | E20: - | F20: - | G20: -1 | H20: - | I20: - | J20: - | K20: - | L20: 0 | M20: - | N20: - | O20: - | P20: - | Q20: 0 | R20: - | S20: - | T20: - | U20: - | V20: 107 | W20: - | X20: - | Y20: - | Z20: - | AA20: 0 | AB20: - | AC20: - | AD20: - | AE20: - | AF20: 0
A21: Total Revenue | C21: =SUM(C18:C19) -> 5698 | D21: =SUM(D18:D19) -> 5758 | E21: =SUM(E18:E19) -> 5589 | F21: =SUM(F18:F19) -> 8695 | G21: =SUM(G18:G20) -> 25739 | H21: =SUM(H18:H19) -> 5676 | I21: =SUM(I18:I19) -> 5722 | J21: =SUM(J18:J19) -> 5356 | K21: =SUM(K18:K19) -> 8577 | L21: =SUM(L18:L20) -> 25331 | M21: =SUM(M18:M19) -> 3148 | N21: =SUM(N18:N19) -> 3727 | O21: =SUM(O18:O19) -> 4185 | P21: =SUM(P18:P19) -> 7037 | Q21: =SUM(Q18:Q20) -> 18097 | R21: =SUM(R18:R19) -> 4865 | S21: =SUM(S18:S19) -> 5844 | T21: =SUM(T18:T19) -> 5653 | U21: =SUM(U18:U19) -> 8930 | V21: =SUM(V18:V20) -> 25399 | W21: =SUM(W18:W19) -> 5565 | X21: =SUM(X18:X19) -> 5834 | Y21: =SUM(Y18:Y19) -> 5467 | Z21: =SUM(Z18:Z19) -> 8583 | AA21: =SUM(AA18:AA20) -> 25449 | AB21: =SUM(AB18:AB19) -> 5173 | AC21: =SUM(AC18:AC19) -> 5280 | AD21: =SUM(AD18:AD19) -> 5038 | AE21: =SUM(AE18:AE19) -> 8375 | AF21: =SUM(AF18:AF20) -> 23866
A23: Cost Of Goods Sold | C23: 3382 | D23: 3320 | E23: 3226 | F23: 5288 | G23: =SUM(C23:F23) -> 15216 | H23: 3403 | I23: 3395 | J23: 3106 | K23: 5266 | L23: =SUM(H23:K23) -> 15170 | M23: 2201 | N23: 2718 | O23: 2569 | P23: 4798 | Q23: =SUM(M23:P23) -> 12286 | R23: 2889 | S23: 3353 | T23: 3207 | U23: 5507 | V23: =SUM(R23:U23) -> 14956 | W23: 3231 | X23: 3422 | Y23: 3204 | Z23: 5450 | AA23: =SUM(W23:Z23) -> 15307 | AB23: 2988 | AC23: 3176 | AD23: 2905 | AE23: 5154 | AF23: =SUM(AB23:AE23) -> 14223
A24: Year end adjustments | C24: - | D24: - | E24: - | F24: - | G24: 1 | H24: - | I24: - | J24: - | K24: - | L24: -1 | M24: - | N24: - | O24: - | P24: - | Q24: 0 | R24: - | S24: - | T24: - | U24: - | V24: 0 | W24: - | X24: - | Y24: - | Z24: - | AA24: -40 | AB24: - | AC24: - | AD24: - | AE24: - | AF24: -1
A25: Gross Profit | C25: =C21-C23 -> 2316 | D25: =D21-D23 -> 2438 | E25: =E21-E23 -> 2363 | F25: =F21-F23 -> 3407 | G25: =G21-G23+G24 -> 10524 | H25: =H21-H23 -> 2273 | I25: =I21-I23 -> 2327 | J25: =J21-J23 -> 2250 | K25: =K21-K23 -> 3311 | L25: =L21-L23+L24 -> 10160 | M25: =M21-M23 -> 947 | N25: =N21-N23 -> 1009 | O25: =O21-O23 -> 1616 | P25: =P21-P23 -> 2239 | Q25: =Q21-Q23+Q24 -> 5811 | R25: =R21-R23 -> 1976 | S25: =S21-S23 -> 2491 | T25: =T21-T23 -> 2446 | U25: =U21-U23 -> 3423 | V25: =V21-V23+V24 -> 10443 | W25: =W21-W23 -> 2334 | X25: =X21-X23 -> 2412 | Y25: =Y21-Y23 -> 2263 | Z25: =Z21-Z23 -> 3133 | AA25: =AA21-AA23+AA24 -> 10102 | AB25: =AB21-AB23 -> 2185 | AC25: =AC21-AC23 -> 2104 | AD25: =AD21-AD23 -> 2133 | AE25: =AE21-AE23 -> 3221 | AF25: =AF21-AF23+AF24 -> 9642
A27: Selling General & Admin Exp. | C27: 2072 | D27: 2153 | E27: 2246 | F27: 2530 | G27: =SUM(C27:F27) -> 9001 | H27: 2105 | I27: 2169 | J27: 2194 | K27: 2501 | L27: =SUM(H27:K27) -> 8969 | M27: 1589 | N27: 1386 | O27: 1710 | P27: 2027 | Q27: 6713 | R27: 1733 | S27: 1881 | T27: 1956 | U27: 2412 | V27: =SUM(R27:U27) -> 7982 | W27: 1898 | X27: 2004 | Y27: 2081 | Z27: 2457 | AA27: =SUM(W27:Z27) -> 8440 | AB27: 1946 | AC27: 1976 | AD27: 2038 | AE27: 2404 | AF27: =SUM(AB27:AE27) -> 8364
A28: R & D Exp. | C28: - | D28: - | E28: - | F28: - | G28: =SUM(C28:F28) -> 0 | H28: - | I28: - | J28: - | K28: - | L28: =SUM(H28:K28) -> 0 | M28: - | N28: - | O28: - | P28: - | Q28: - | R28: - | S28: - | T28: - | U28: - | V28: =SUM(R28:U28) -> 0 | W28: - | X28: - | Y28: - | Z28: - | AA28: =SUM(W28:Z28) -> 0 | AB28: - | AC28: - | AD28: - | AE28: - | AF28: -
A29: Depreciation & Amort. | C29: - | D29: - | E29: - | F29: - | G29: =SUM(C29:F29) -> 0 | H29: - | I29: - | J29: - | K29: - | L29: =SUM(H29:K29) -> 0 | M29: - | N29: - | O29: - | P29: - | Q29: - | R29: - | S29: - | T29: - | U29: - | V29: =SUM(R29:U29) -> 0 | W29: - | X29: - | Y29: - | Z29: - | AA29: =SUM(W29:Z29) -> 0 | AB29: - | AC29: - | AD29: - | AE29: - | AF29: -
A30: Other Operating Expense/(Income) | C30: - | D30: - | E30: - | F30: -8 | G30: =SUM(C30:F30) -> -8 | H30: 1 | I30: 1 | J30: 8 | K30: -10 | L30: =SUM(H30:K30) -> 0 | M30: 9 | N30: 58 | O30: 12 | P30: -79 | Q30: - | R30: - | S30: - | T30: - | U30: 21 | V30: =SUM(R30:U30) -> 21 | W30: - | X30: - | Y30: - | Z30: 21 | AA30: =SUM(W30:Z30) -> 21 | AB30: - | AC30: - | AD30: - | AE30: 15 | AF30: 15
A31: Year-end Adjustments | C31: - | D31: - | E31: - | F31: - | G31: -1 | H31: - | I31: - | J31: - | K31: - | L31: 32 | M31: - | N31: - | O31: - | P31: - | Q31: 0 | R31: - | S31: - | T31: - | U31: - | V31: 106 | W31: - | X31: - | Y31: - | Z31: - | AA31: 1 | AB31: - | AC31: - | AD31: - | AE31: - | AF31: 0
A32: Other Operating Exp., Total | C32: =SUM(C27:C30) -> 2072 | D32: =SUM(D27:D30) -> 2153 | E32: =SUM(E27:E30) -> 2246 | F32: =SUM(F27:F30) -> 2522 | G32: =SUM(G27:G31) -> 8992 | H32: =SUM(H27:H30) -> 2106 | I32: =SUM(I27:I30) -> 2170 | J32: =SUM(J27:J30) -> 2202 | K32: =SUM(K27:K30) -> 2491 | L32: =SUM(L27:L31) -> 9001 | M32: =SUM(M27:M30) -> 1598 | N32: =SUM(N27:N30) -> 1444 | O32: =SUM(O27:O30) -> 1722 | P32: =SUM(P27:P30) -> 1948 | Q32: =SUM(Q27:Q31) -> 6713 | R32: =SUM(R27:R30) -> 1733 | S32: =SUM(S27:S30) -> 1881 | T32: =SUM(T27:T30) -> 1956 | U32: =SUM(U27:U30) -> 2433 | V32: =SUM(V27:V31) -> 8109 | W32: =SUM(W27:W30) -> 1898 | X32: =SUM(X27:X30) -> 2004 | Y32: =SUM(Y27:Y30) -> 2081 | Z32: =SUM(Z27:Z30) -> 2478 | AA32: =SUM(AA27:AA31) -> 8462 | AB32: =SUM(AB27:AB30) -> 1946 | AC32: =SUM(AC27:AC30) -> 1976 | AD32: =SUM(AD27:AD30) -> 2038 | AE32: =SUM(AE27:AE30) -> 2419 | AF32: =SUM(AF27:AF31) -> 8379
A34: Operating Income (EBITDA) | C34: =C25-C32 -> 244 | D34: =D25-D32 -> 285 | E34: =E25-E32 -> 117 | F34: =F25-F32 -> 885 | G34: =G25-G32 -> 1532 | H34: =H25-H32 -> 167 | I34: =I25-I32 -> 157 | J34: =J25-J32 -> 48 | ... AF34: =AF25-AF32 -> 1263
A36: Interest Expense | C36: -71 | D36: -69 | E36: -64 | F36: -57 | G36: =SUM(C36:F36) -> -261 | H36: -54 | I36: -52 | J36: -52 | K36: -46 | L36: =SUM(H36:K36) -> -204 | M36: -49 | N36: -70 | O36: -80 | P36: -85 | Q36: =SUM(M36:P36) -> -284 | R36: -79 | S36: -80 | T36: -53 | U36: -44 | V36: =SUM(R36:U36) -> -256 | W36: -47 | X36: -42 | Y36: -42 | Z36: -31 | AA36: =SUM(W36:Z36) -> -162 | AB36: -37 | AC36: -36 | AD36: -35 | AE36: -27 | AF36: =SUM(AB36:AE36) -> -135
A37: Interest and Invest. Income | C37: 5 | D37: 7 | E37: 5 | F37: 8 | G37: =SUM(C37:F37) -> 25 | H37: 7 | I37: 5 | J37: 4 | K37: 4 | L37: =SUM(H37:K37) -> 20 | M37: 2 | N37: 1 | O37: - | P37: 1 | Q37: =SUM(M37:P37) -> 4 | R37: - | S37: - | T37: - | U37: 0 | V37: =SUM(R37:U37) -> 0 | W37: - | X37: - | Y37: - | Z37: - | AA37: =SUM(W37:Z37) -> 0 | AB37: - | AC37: - | AD37: - | AE37: - | AF37: =SUM(AB37:AE37) -> 0
A38: Year-end adjustments | C38: - | D38: - | E38: - | F38: - | G38: 0 | H38: - | I38: - | J38: - | K38: - | L38: -1 | M38: - | N38: - | O38: - | P38: - | Q38: 0 | R38: - | S38: - | T38: - | U38: - | V38: 1 | W38: - | X38: - | Y38: - | Z38: - | AA38: 0 | AB38: - | AC38: - | AD38: - | AE38: - | AF38: 0
A39: Net Interest Exp. | C39: =SUM(C36:C37) -> -66 | D39: =SUM(D36:D37) -> -62 | E39: =SUM(E36:E37) -> -59 | F39: =SUM(F36:F37) -> -49 | G39: =SUM(G36:G38) -> -236 | H39: =SUM(H36:H37) -> -47 | I39: =SUM(I36:I37) -> -47 | J39: =SUM(J36:J37) -> -48 | K39: =SUM(K36:K37) -> -42 | L39: =SUM(L36:L38) -> -185 | M39: =SUM(M36:M37) -> -47 | N39: =SUM(N36:N37) -> -69 | O39: =SUM(O36:O37) -> -80 | P39: =SUM(P36:P37) -> -84 | Q39: =SUM(Q36:Q38) -> -280 | R39: =SUM(R36:R37) -> -79 | S39: =SUM(S36:S37) -> -80 | T39: =SUM(T36:T37) -> -53 | U39: =SUM(U36:U37) -> -44 | V39: =SUM(V36:V38) -> -255 | W39: =SUM(W36:W37) -> -47 | X39: =SUM(X36:X37) -> -42 | Y39: =SUM(Y36:Y37) -> -42 | Z39: =SUM(Z36:Z37) -> -31 | AA39: =SUM(AA36:AA38) -> -162 | AB39: =SUM(AB36:AB37) -> -37 | AC39: =SUM(AC36:AC37) -> -36 | AD39: =SUM(AD36:AD37) -> -35 | AE39: =SUM(AE36:AE37) -> -27 | AF39: =SUM(AF36:AF38) -> -135
A41: Other Non-Operating Inc. (Exp.) | C41: 0 | D41: 0 | E41: 0 | F41: 0 | G41: 0 | H41: 0 | I41: 0 | J41: 0 | K41: 0 | L41: 0 | M41: 0 | N41: -3 | O41: 0 | P41: -1 | Q41: =SUM(M41:P41) -> -4 | R41: 0 | S41: 0 | T41: 0 | U41: 0 | V41: 0 | W41: 0 | X41: 0 | Y41: 0 | Z41: 0 | AA41: 0 | AB41: 0 | AC41: 0 | AD41: 0 | AE41: 0 | AF41: 0
A42: Year-end Adjustments | C42: 0 | D42: 0 | E42: 0 | F42: 0 | G42: -1 | H42: 0 | I42: 0 | J42: 0 | K42: 0 | L42: 1 | M42: 0 | N42: 0 | O42: 0 | P42: 0 | Q42: -1 | R42: 0 | S42: 0 | T42: 0 | U42: 0 | V42: 0 | W42: 0 | X42: 0 | Y42: 0 | Z42: 0 | AA42: 0 | AB42: 0 | AC42: 0 | AD42: 0 | AE42: 0 | AF42: 1
A43: EBT Excl. Unusual Items | C43: =C34+C39+C41+C42 -> 178 | D43: =D34+D39+D41+D42 -> 223 | E43: =E34+E39+E41+E42 -> 58 | F43: =F34+F39+F41+F42 -> 836 | G43: =G34+G39+G41+G42 -> 1295 | H43: =H34+H39+H41+H42 -> 120 | I43: =I34+I39+I41+I42 -> 110 | J43: =J34+J39+J41+J42 -> 0 | ... AF43: =AF34+AF39+AF41+AF42 -> 1129
A45: Restructuring Charges | C45: -19 | D45: -17 | E45: -3 | F45: -41 | G45: =SUM(C45:F45) -> -80 | H45: - | I45: - | J45: -5 | K45: -313 | L45: =SUM(H45:K45) -> -318 | M45: -25 | N45: -169 | O45: -2 | P45: -28 | Q45: =SUM(M45:P45) -> -224 | R45: - | S45: - | T45: - | U45: -3 | V45: =SUM(R45:U45) -> -3 | W45: - | X45: - | Y45: - | Z45: -5 | AA45: =SUM(W45:Z45) -> -5 | AB45: - | AC45: - | AD45: - | AE45: -55 | AF45: =SUM(AB45:AE45) -> -55
A46: Impairment of Goodwill | C46: - | D46: - | E46: - | F46: - | G46: =SUM(C46:F46) -> 0 | H46: - | I46: - | J46: - | K46: - | L46: =SUM(H46:K46) -> 0 | M46: -3070 | N46: - | O46: - | P46: 0 | Q46: =SUM(M46:P46) -> -3070 | R46: - | S46: - | T46: - | U46: - | V46: =SUM(R46:U46) -> 0 | W46: - | X46: - | Y46: - | Z46: - | AA46: =SUM(W46:Z46) -> 0 | AB46: - | AC46: - | AD46: - | AE46: - | AF46: =SUM(AB46:AE46) -> 0
A47: Gain (Loss) On Sale Of Assets | C47: 24 | D47: 46 | E47: 42 | F47: 278 | G47: =SUM(C47:F47) -> 390 | H47: 43 | I47: 7 | J47: 17 | K47: 95 | L47: =SUM(H47:K47) -> 162 | M47: 16 | N47: - | O47: 3 | P47: 40 | Q47: =SUM(M47:P47) -> 59 | R47: 6 | S47: 6 | T47: 50 | U47: 30 | V47: =SUM(R47:U47) -> 92 | W47: 42 | X47: - | Y47: 32 | Z47: 15 | AA47: =SUM(W47:Z47) -> 89 | AB47: 11 | AC47: 4 | AD47: 5 | AE47: 41 | AF47: =SUM(AB47:AE47) -> 61
A48: Asset Writedown | C48: - | D48: - | E48: - | F48: -64 | G48: =SUM(C48:F48) -> -64 | H48: - | I48: -1 | J48: - | K48: -35 | L48: =SUM(H48:K48) -> -36 | M48: -380 | N48: -15 | O48: -6 | P48: 190 | Q48: =SUM(M48:P48) -> -211 | R48: -19 | S48: -2 | T48: - | U48: 15 | V48: =SUM(R48:U48) -> -6 | W48: -8 | X48: -2 | Y48: -15 | Z48: 10 | AA48: =SUM(W48:Z48) -> -15 | AB48: -2 | AC48: -4 | AD48: -15 | AE48: -936 | AF48: =SUM(AB48:AE48) -> -957
A49: Gain (Loss) on Early Retirement of Debt | C49: - | D49: -5 | E49: - | F49: - | G49: =SUM(C49:F49) -> -5 | H49: - | I49: - | J49: - | K49: - | L49: =SUM(H49:K49) -> 0 | M49: - | N49: - | O49: - | P49: - | Q49: =SUM(M49:P49) -> 0 | R49: -11 | S49: -3 | T49: -185 | U49: - | V49: =SUM(R49:U49) -> -199 | W49: -31 | X49: - | Y49: - | Z49: - | AA49: =SUM(W49:Z49) -> -31 | AB49: - | AC49: - | AD49: - | AE49: - | AF49: =SUM(AB49:AE49) -> 0
A50: Settlement Charges | C50: - | D50: -50 | E50: -23 | F50: -43 | G50: =SUM(C50:F50) -> -116 | H50: - | I50: - | J50: -12 | K50: -76 | L50: =SUM(H50:K50) -> -88 | M50: - | N50: -38 | O50: -26 | P50: -94 | Q50: =SUM(M50:P50) -> -158 | R50: - | S50: -81 | T50: -8 | U50: -6 | V50: =SUM(R50:U50) -> -95 | W50: - | X50: - | Y50: -32 | Z50: -7 | AA50: =SUM(W50:Z50) -> -39 | AB50: - | AC50: -122 | AD50: -7 | AE50: -5 | AF50: =SUM(AB50:AE50) -> -134
A51: Year-end Adjustments | C51: - | D51: - | E51: - | F51: - | G51: 0 | H51: - | I51: - | J51: - | K51: - | L51: 33 | M51: - | N51: - | O51: - | P51: - | Q51: 1 | R51: - | S51: 0 | T51: - | U51: - | V51: -2 | W51: - | X51: - | Y51: - | Z51: - | AA51: 0 | AB51: - | AC51: - | AD51: - | AE51: - | AF51: -1
A52: EBT Incl. Unusual Items | C52: =C43+SUM(C45:C51) -> 183 | D52: =D43+SUM(D45:D51) -> 197 | E52: =E43+SUM(E45:E51) -> 74 | F52: =F43+SUM(F45:F51) -> 966 | G52: =G43+SUM(G45:G51) -> 1420 | H52: =H43+SUM(H45:H51) -> 163 | I52: =I43+SUM(I45:I51) -> 116 | J52: =J43+SUM(J45:J51) -> 0 | ... AF52: =AF43+SUM(AF45:AF51) -> 43
A55: Income Tax Expense | C55: 52 | D55: 33 | E55: 12 | F55: 226 | G55: 322 | H55: 27 | I55: 30 | J55: -2 | K55: 109 | L55: =SUM(H55:K55) -> 164 | M55: -576 | N55: -298 | O55: -126 | P55: 154 | Q55: =SUM(M55:P55) -> -846 | R55: 37 | S55: 105 | T55: 55 | U55: 239 | V55: =SUM(R55:U55) -> 436 | W55: 106 | X55: 89 | Y55: 17 | Z55: 128 | AA55: 331 | AB55: 56 | AC55: -8 | AD55: 2 | AE55: -52 | AF55: =SUM(AB55:AE55) -> -2
A56: Net Income to Company | C56: =C52-C55 -> 131 | D56: =D52-D55 -> 164 | E56: =E52-E55 -> 62 | F56: =F52-F55 -> 740 | G56: =G52-G55 -> 1098 | H56: =H52-H55 -> 136 | I56: =I52-I55 -> 86 | J56: =J52-J55 -> 2 | ... AF56: =AF52-AF55 -> 45
A58: Minority Int. in Earnings | C58: 8 | D58: 2 | E58: 0 | F58: 0 | G58: =SUM(C58:F58) -> 10 | H58: 0 | I58: 0 | J58: 0 | K58: 0 | L58: 0 | M58: 0 | N58: 0 | O58: 0 | P58: 0 | Q58: 0 | R58: 0 | S58: 0 | T58: 0 | U58: 0 | V58: 0 | W58: 0 | X58: 0 | Y58: 0 | Z58: 0 | AA58: 0 | AB58: 0 | AC58: 0 | AD58: 0 | AE58: 0 | AF58: 0
A59: Net Income | C59: =C56+C58 -> 139 | D59: =D56+D58 -> 166 | E59: =E56+E58 -> 62 | F59: =F56+F58 -> 740 | G59: =G56+G58 -> 1108 | H59: =H56+H58 -> 136 | I59: =I56+I58 -> 86 | J59: =J56+J58 -> 2 | ... AF59: =AF56+AF58 -> 45
A62: Basic EPS | C62: 0.45 | D62: 0.54 | E62: 0.2 | F62: 2.4 | G62: 3.6 | H62: 0.44 | I62: 0.28 | J62: 0.01 | K62: 1.1 | L62: 1.82 | M62: -11.53 | N62: -1.38 | O62: -0.29 | P62: 0.51 | Q62: -12.68 | R62: 0.33 | S62: 1.1 | T62: 0.78 | U62: 2.51 | V62: 4.66 | W62: 1.01 | X62: 1.01 | Y62: 0.4 | Z62: 1.87 | AA62: 4.17 | AB62: 0.57 | AC62: -0.08 | AD62: 0.15 | AE62: -0.47 | AF62: 0.16
A63: Weighted Avg. Basic Shares Out. | C63: 306.6 | D63: 307.7 | E63: 308.1 | F63: 308.4 | G63: 307.7 | H63: 309.1 | I63: 309.8 | J63: 309.9 | K63: 309.9 | L63: 309.7 | M63: 310.6 | N63: 311.2 | O63: 311.2 | P63: 311.4 | Q63: 311.1 | R63: 311.6 | S63: 312.4 | T63: 306.9 | U63: 296.5 | V63: 306.8 | W63: 283.6 | X63: 271.1 | Y63: 272 | Z63: 272.2 | AA63: 274.7 | AB63: 273.1 | AC63: 273.8 | AD63: 274.7 | AE63: 275 | AF63: 274.2
A65: Diluted EPS | C65: 0.45 | D65: 0.53 | E65: 0.2 | F65: 2.38 | G65: 3.56 | H65: 0.44 | I65: 0.28 | J65: 0.01 | K65: 1.09 | L65: 1.81 | M65: -11.53 | N65: -1.39 | O65: -0.29 | P65: 0.51 | Q65: -12.68 | R65: 0.32 | S65: 1.08 | T65: 0.76 | U65: 2.43 | V65: 4.55 | W65: 0.98 | X65: 0.99 | Y65: 0.39 | Z65: 1.83 | AA65: 4.08 | AB65: 0.56 | AC65: -0.08 | AD65: 0.15 | AE65: -0.47 | AF65: 0.16
A66: Weighted Avg. Diluted Shares Out. | C66: 309.4 | D66: 312 | E66: 312.2 | F66: 311.9 | G66: 311.4 | H66: 311.4 | I66: 311.6 | J66: 311 | K66: 311.5 | L66: 311.4 | M66: 310.6 | N66: 311.2 | O66: 311.2 | P66: 316.6 | Q66: 311.1 | R66: 318.6 | S66: 318.6 | T66: 313.8 | U66: 304.8 | V66: 314 | W66: 290.9 | X66: 277.4 | Y66: 277.7 | Z66: 278.5 | AA66: 281.1 | AB66: 277.8 | AC66: 273.8 | AD66: 277.6 | AE66: 275 | AF66: 278.2
A69: Balance Sheet | F69: 2019 | K69: 2020 | P69: 2021 | U69: 2022 | Z69: 2023 | AE69: 2024
A70: For the Fiscal Period Ending | C70: 1Q 2019 | D70: 2Q 2019 | E70: 3Q 2019 | F70: 4Q 2019 | G70: 2019A | H70: 1Q 2020 | I70: 2Q 2020 | J70: 3Q 2020 | K70: 4Q 2020 | L70: 2020A | M70: 1Q 2021 | N70: 2Q 2021 | O70: 3Q 2021 | P70: 4Q 2021 | Q70: 2021A | R70: 1Q 2022 | S70: 2Q 2022 | T70: 3Q 2022 | U70: 4Q 2022 | V70: 2022A | W70: 1Q 2023 | X70: 2Q 2023 | Y70: 3Q 2023 | Z70: 4Q 2023 | AA70: 2023A | AB70: 1Q 2024 | AC70: 2Q 2024 | AD70: 3Q 2024 | AE70: 4Q2024 | AF70: 2024A
A71: Currency: USD
A72: ASSETS
A73: Cash And Equivalents | C73: 1531 | D73: 1068 | E73: 736 | F73: 1162 | G73: =F73 -> 1162 | H73: 737 | I73: 674 | J73: 301 | K73: 685 | L73: =K73 -> 685 | M73: 1523 | N73: 1395 | O73: 1551 | P73: 1679 | Q73: =P73 -> 1679 | R73: 1798 | S73: 2137 | T73: 316 | U73: 1712 | V73: =U73 -> 1712 | W73: 672 | X73: 300 | Y73: 326 | Z73: 862 | AA73: =Z73 -> 862 | AB73: 603 | AC73: 438 | AD73: 364 | AE73: 1034 | AF73: =AE73 -> 1034
A74: Total Cash & ST Investments | C74: 1531 | D74: 1068 | E74: 736 | F74: 1162 | G74: =F74 -> 1162 | H74: 737 | I74: 674 | J74: 301 | K74: 685 | L74: =K74 -> 685 | M74: 1523 | N74: 1395 | O74: 1551 | P74: 1679 | Q74: =P74 -> 1679 | R74: 1798 | S74: 2137 | T74: 316 | U74: 1712 | V74: =U74 -> 1712 | W74: 672 | X74: 300 | Y74: 326 | Z74: 862 | AA74: =Z74 -> 862 | AB74: =AB73 -> 603 | AC74: =AC73 -> 438 | AD74: =AD73 -> 364 | AE74: =AE73 -> 1034 | AF74: =AE74 -> 1034
A76: Accounts Receivable | C76: 250 | D76: 261 | E76: 180 | F76: 400 | G76: 400 | H76: 237 | I76: 240 | J76: 175 | K76: 409 | L76: 409 | M76: 170 | N76: 184 | O76: 185 | P76: 276 | Q76: 276 | R76: 205 | S76: 221 | T76: 212 | U76: 297 | V76: 297 | W76: 233 | X76: 219 | Y76: 204 | Z76: 300 | AA76: 300 | AB76: 255 | AC76: 223 | AD76: 218 | AE76: 293 | AF76: 293
A77: Other Receivables | C77: 0 | D77: 0 | E77: 10 | F77: - | G77: - | H77: 0 | I77: 0 | J77: 1 | K77: - | L77: - | M77: 0 | N77: 0 | O77: 0 | P77: 0 | Q77: - | R77: 520 | S77: 520 | T77: 590 | U77: 0 | V77: - | W77: - | X77: - | Y77: - | Z77: - | AA77: - | AB77: - | AC77: 70 | AD77: 73 | AE77: - | AF77: -
A78: Total Receivables | C78: =SUM(C76:C77) -> 250 | D78: =SUM(D76:D77) -> 261 | E78: =SUM(E76:E77) -> 190 | F78: =SUM(F76:F77) -> 400 | G78: 400 | H78: =SUM(H76:H77) -> 237 | I78: =SUM(I76:I77) -> 240 | J78: =SUM(J76:J77) -> 176 | K78: =SUM(K76:K77) -> 409 | L78: 409 | M78: =SUM(M76:M77) -> 170 | N78: =SUM(N76:N77) -> 184 | O78: =SUM(O76:O77) -> 185 | P78: =SUM(P76:P77) -> 276 | Q78: 276 | R78: =SUM(R76:R77) -> 725 | S78: =SUM(S76:S77) -> 741 | T78: =SUM(T76:T77) -> 802 | U78: =SUM(U76:U77) -> 297 | V78: 297 | W78: =SUM(W76:W77) -> 233 | X78: =SUM(X76:X77) -> 219 | Y78: =SUM(Y76:Y77) -> 204 | Z78: =SUM(Z76:Z77) -> 300 | AA78: 300 | AB78: =SUM(AB76:AB77) -> 255 | AC78: =SUM(AC76:AC77) -> 293 | AD78: =SUM(AD76:AD77) -> 291 | AE78: =SUM(AE76:AE77) -> 293 | AF78: 293
A80: Inventory | C80: 5291 | D80: 4956 | E80: 7147 | F80: 5263 | G80: 5263 | H80: 5498 | I80: 5029 | J80: 7256 | K80: 5188 | L80: 5188 | M80: 4923 | N80: 3582 | O80: 5144 | P80: 3774 | Q80: 3774 | R80: 4230 | S80: 4298 | T80: 6141 | U80: 4383 | V80: 4383 | W80: 4956 | X80: 4610 | Y80: 6403 | Z80: 4267 | AA80: 4267 | AB80: 4607 | AC80: 4129 | AD80: 6025 | AE80: 4361 | AF80: 4361
A81: Prepaid Exp. | C81: 434 | D81: 415 | E81: 414 | F81: 368 | G81: 368 | H81: 433 | I81: 449 | J81: 404 | K81: 310 | L81: 310 | M81: 389 | N81: 356 | O81: 361 | P81: 316 | Q81: 316 | R81: 351 | S81: 320 | T81: 190 | U81: 207 | V81: 207 | W81: 228 | X81: 275 | Y81: 273 | Z81: 237 | AA81: 237 | AB81: 263 | AC81: 317 | AD81: 276 | AE81: 276 | AF81: 276
A82: Restricted Cash | C82: - | D82: - | E82: - | F82: 37 | G82: 37 | H82: - | I82: - | J82: - | K82: 37 | L82: 37 | M82: - | N82: - | O82: - | P82: - | Q82: - | R82: - | S82: - | T82: - | U82: - | V82: - | W82: - | X82: - | Y82: - | Z82: - | AA82: - | AB82: - | AC82: - | AD82: - | AE82: - | AF82: -
A83: Other Current Assets | C83: 204 | D83: 165 | E83: 180 | F83: 215 | G83: 215 | H83: 200 | I83: 154 | J83: 164 | K83: 181 | L83: 181 | M83: 130 | N83: 114 | O83: 116 | P83: 139 | Q83: 139 | R83: 136 | S83: 115 | T83: 142 | U83: 159 | V83: 159 | W83: 144 | X83: 112 | Y83: 142 | Z83: 187 | AA83: 187 | AB83: 127 | AC83: 94 | AD83: 114 | AE83: 125 | AF83: 125
A84: Total Current Assets | C84: =SUM(C80:C83)+C78+C74 -> 7710 | D84: =SUM(D80:D83)+D78+D74 -> 6865 | E84: =SUM(E80:E83)+E78+E74 -> 8667 | F84: =SUM(F80:F83)+F78+F74 -> 7445 | G84: 7445 | H84: =SUM(H80:H83)+H78+H74 -> 7105 | I84: =SUM(I80:I83)+I78+I74 -> 6546 | J84: =SUM(J80:J83)+J78+J74 -> 8301 | K84: =SUM(K80:K83)+K78+K74 -> 6810 | L84: 6810 | M84: =SUM(M80:M83)+M78+M74 -> 7135 | N84: =SUM(N80:N83)+N78+N74 -> 5631 | O84: =SUM(O80:O83)+O78+O74 -> 7357 | P84: =SUM(P80:P83)+P78+P74 -> 6184 | Q84: =SUM(Q80:Q83)+Q78+Q74 -> 6184 | R84: =SUM(R80:R83)+R78+R74 -> 7240 | S84: =SUM(S80:S83)+S78+S74 -> 7611 | T84: =SUM(T80:T83)+T78+T74 -> 7591 | ... AF84: =SUM(AF80:AF83)+AF78+AF74 -> 6089
A86: Gross Property, Plant & Equipment | C86: 11340 | D86: 11461 | E86: 11656 | F86: 11132 | G86: 11132 | H86: 13763 | I86: 13879 | J86: 14092 | K86: 13705 | L86: 13705 | M86: 13657 | N86: 13956 | O86: 13966 | P86: 13231 | Q86: 13231 | R86: 13201 | S86: 13221 | T86: 13234 | U86: 13034 | V86: 13034 | W86: 13008 | X86: 13191 | Y86: 13487 | Z86: 13242 | AA86: 13242 | AB86: 13342 | AC86: 13473 | AD86: 13663 | AE86: 11902 | AF86: 11902
A87: Accumulated Depreciation | C87: -4765 | D87: -4914 | E87: -5084 | F87: -4495 | G87: -4495 | H87: -4633 | I87: -4760 | J87: -4938 | K87: -4404 | L87: -4404 | M87: -4560 | N87: -4642 | O87: -4816 | P87: -4413 | Q87: -4413 | R87: -4550 | S87: -4689 | T87: -4826 | U87: -4561 | V87: -4561 | W87: -4671 | X87: -4820 | Y87: -4957 | Z87: -4646 | AA87: -4646 | AB87: -4763 | AC87: -4905 | AD87: -5066 | AE87: -4289 | AF87: -4289
A88: Net Property, Plant & Equipment | C88: =SUM(C86:C87) -> 6575 | D88: =SUM(D86:D87) -> 6547 | E88: =SUM(E86:E87) -> 6572 | F88: =SUM(F86:F87) -> 6637 | G88: 6637 | H88: =SUM(H86:H87) -> 9130 | I88: =SUM(I86:I87) -> 9119 | J88: =SUM(J86:J87) -> 9154 | K88: =SUM(K86:K87) -> 9301 | L88: =SUM(L86:L87) -> 9301 | M88: =SUM(M86:M87) -> 9097 | N88: =SUM(N86:N87) -> 9314 | O88: =SUM(O86:O87) -> 9150 | ... AF88: =SUM(AF86:AF87) -> 7613
A90: Goodwill | C90: 3908 | D90: 3908 | E90: 3908 | F90: 3908 | G90: 3908 | H90: 3908 | I90: 3908 | J90: 3908 | K90: 3908 | L90: 3908 | M90: 838 | N90: 828 | O90: 828 | P90: 828 | Q90: 828 | R90: 828 | S90: 828 | T90: 828 | U90: 828 | V90: 828 | W90: 828 | X90: 828 | Y90: 828 | Z90: 828 | AA90: 828 | AB90: 828 | AC90: 828 | AD90: 828 | AE90: 828 | AF90: 828
A91: Other Intangibles | C91: 486 | D91: 483 | E91: 481 | F91: 1148 | G91: 1148 | H91: 441 | I91: 440 | J91: 440 | K91: 1081 | L91: 1081 | M91: 439 | N91: 438 | O91: 437 | P91: 928 | Q91: 928 | R91: 436 | S91: 436 | T91: 435 | U91: 946 | V91: 946 | W91: 434 | X91: 433 | Y91: 433 | Z91: 1098 | AA91: 1098 | AB91: 432 | AC91: 431 | AD91: 431 | AE91: 1187 | AF91: 1187
A92: Other Long-Term Assets | C92: 889 | D92: 865 | E92: 733 | F92: 56 | G92: 56 | H92: 712 | I92: 728 | J92: 744 | K92: 72 | L92: 72 | M92: 1072 | N92: 1403 | O92: 1442 | P92: 948 | Q92: 948 | R92: 927 | S92: 1010 | T92: 1017 | U92: 585 | V92: 585 | W92: 1140 | X92: 1194 | Y92: 1091 | Z92: 491 | AA92: 491 | AB92: 1174 | AC92: 1206 | AD92: 1185 | AE92: 529 | AF92: 529
A93: Total Non-Current Assets | C93: =C88+SUM(C90:C92) -> 11858 | D93: =D88+SUM(D90:D92) -> 11803 | E93: =E88+SUM(E90:E92) -> 11694 | F93: =F88+SUM(F90:F92) -> 11749 | G93: =G88+SUM(G90:G92) -> 11749 | H93: =H88+SUM(H90:H92) -> 14191 | I93: =I88+SUM(I90:I92) -> 14195 | J93: =J88+SUM(J90:J92) -> 14246 | ... AF93: =AF88+SUM(AF90:AF92) -> 10157
A95: Total Assets | C95: =C84+C93 -> 19568 | D95: =D84+D93 -> 18668 | E95: =E84+E93 -> 20361 | F95: =F84+F93 -> 19194 | G95: =G84+G93 -> 19194 | H95: =H84+H93 -> 21296 | I95: =I84+I93 -> 20741 | J95: =J84+J93 -> 22547 | ... AF95: =AF84+AF93 -> 16246
A97: LIABILITIES
A98: Accounts Payable | C98: 3715 | D98: 3498 | E98: 5403 | F98: 2638 | G98: =F98 -> 2638 | H98: 3443 | I98: 3181 | J98: 5209 | K98: 2659 | L98: =K98 -> 2659 | M98: 3969 | N98: 3484 | O98: 5289 | P98: 2856 | Q98: =P98 -> 2856 | R98: 4353 | S98: 4391 | T98: 5787 | U98: 3280 | V98: =U98 -> 3280 | W98: 4648 | X98: 4113 | Y98: 5951 | Z98: 2874 | AA98: =Z98 -> 2874 | AB98: 4074 | AC98: 3696 | AD98: 5328 | AE98: 2660 | AF98: =AE98 -> 2660
A99: Accrued Exp. | C99: - | D99: - | E99: - | F99: 939 | G99: =F99 -> 939 | H99: - | I99: - | J99: - | K99: 731 | L99: =K99 -> 731 | M99: - | N99: - | O99: - | P99: 844 | Q99: =P99 -> 844 | R99: - | S99: - | T99: - | U99: 818 | V99: =U99 -> 818 | W99: - | X99: - | Y99: - | Z99: 719 | AA99: =Z99 -> 719 | AB99: - | AC99: - | AD99: - | AE99: 680 | AF99: =AE99 -> 680
A100: Short-term Borrowings | C100: - | D100: - | E100: - | F100: - | G100: =F100 -> - | H100: - | I100: - | J100: - | K100: - | L100: =K100 -> - | M100: - | N100: - | O100: - | P100: - | Q100: =P100 -> - | R100: - | S100: - | T100: - | U100: - | V100: =U100 -> - | W100: - | X100: - | Y100: - | Z100: - | AA100: =Z100 -> - | AB100: - | AC100: - | AD100: - | AE100: - | AF100: =AE100 -> -
A101: Curr. Port. of LT Debt | C101: 25 | D101: 63 | E101: 65 | F101: 36 | G101: =F101 -> 36 | H101: 41 | I101: 6 | J101: 6 | K101: 539 | L101: =K101 -> 539 | M101: 739 | N101: 539 | O101: 536 | P101: 452 | Q101: =P101 -> 452 | R101: 294 | S101: 1546 | T101: 140 | U101: - | V101: =U101 -> - | W101: - | X101: - | Y101: 183 | Z101: - | AA101: =Z101 -> - | AB101: - | AC101: - | AD101: 160 | AE101: - | AF101: =AE101 -> -
A102: Curr. Port. of Leases | C102: - | D102: - | E102: - | F102: 7 | G102: =F102 -> 7 | H102: 363 | I102: 351 | J102: 314 | K102: 333 | L102: =K102 -> 333 | M102: - | N102: - | O102: - | P102: 200 | Q102: =P102 -> 200 | R102: - | S102: - | T102: - | U102: 330 | V102: =U102 -> 330 | W102: - | X102: - | Y102: - | Z102: 335 | AA102: =Z102 -> 335 | AB102: - | AC102: - | AD102: - | AE102: 358 | AF102: =AE102 -> 358
A103: Curr. Income Taxes Payable | C103: 312 | D103: 15 | E103: - | F103: 168 | G103: =F103 -> 168 | H103: 182 | I103: 20 | J103: - | K103: 81 | L103: =K103 -> 81 | M103: 80 | N103: - | O103: - | P103: - | Q103: =P103 -> - | R103: 63 | S103: 18 | T103: - | U103: 108 | V103: =U103 -> 108 | W103: 222 | X103: 23 | Y103: 21 | Z103: 58 | AA103: =Z103 -> 58 | AB103: 134 | AC103: - | AD103: - | AE103: 48 | AF103: =AE103 -> 48
A104: Unearned Revenue, Current | C104: 727 | D104: 662 | E104: 711 | F104: 879 | G104: =F104 -> 879 | H104: 696 | I104: 654 | J104: 705 | K104: 839 | L104: =K104 -> 839 | M104: 732 | N104: 675 | O104: 639 | P104: 616 | Q104: =P104 -> 616 | R104: 580 | S104: 547 | T104: 500 | U104: 481 | V104: =U104 -> 481 | W104: 428 | X104: 386 | Y104: 355 | Z104: 399 | AA104: =Z104 -> 399 | AB104: 360 | AC104: 340 | AD104: 336 | AE104: 384 | AF104: =AE104 -> 384
A105: Other Current Liabilities | C105: 298 | D105: 243 | E105: 265 | F105: 565 | G105: =F105 -> 565 | H105: 294 | I105: 227 | J105: 245 | K105: 568 | L105: =K105 -> 568 | M105: 252 | N105: 156 | O105: 187 | P105: 389 | Q105: =P105 -> 389 | R105: 228 | S105: 198 | T105: 244 | U105: 399 | V105: =U105 -> 399 | W105: 245 | X105: 186 | Y105: 233 | Z105: 476 | AA105: =Z105 -> 476 | AB105: 214 | AC105: 148 | AD105: 190 | AE105: 402 | AF105: =AE105 -> 402
A106: Total Current Liabilities | C106: =SUM(C98:C105) -> 5077 | D106: =SUM(D98:D105) -> 4481 | E106: =SUM(E98:E105) -> 6444 | F106: =SUM(F98:F105) -> 5232 | G106: =F106 -> 5232 | H106: =SUM(H98:H105) -> 5019 | I106: =SUM(I98:I105) -> 4439 | J106: =SUM(J98:J105) -> 6479 | K106: =SUM(K98:K105) -> 5750 | L106: =K106 -> 5750 | M106: =SUM(M98:M105) -> 5772 | N106: =SUM(N98:N105) -> 4854 | O106: =SUM(O98:O105) -> 6651 | P106: =SUM(P98:P105) -> 5357 | Q106: =P106 -> 5357 | R106: =SUM(R98:R105) -> 5518 | S106: =SUM(S98:S105) -> 6700 | T106: =SUM(T98:T105) -> 6671 | U106: =SUM(U98:U105) -> 5416 | V106: =U106 -> 5416 | W106: =SUM(W98:W105) -> 5543 | X106: =SUM(X98:X105) -> 4708 | Y106: =SUM(Y98:Y105) -> 6743 | Z106: =SUM(Z98:Z105) -> 4861 | AA106: =Z106 -> 4861 | AB106: =SUM(AB98:AB105) -> 4782 | AC106: =SUM(AC98:AC105) -> 4184 | AD106: =SUM(AD98:AD105) -> 6014 | AE106: =SUM(AE98:AE105) -> 4532 | AF106: =AE106 -> 4532
A108: Long-Term Debt | C108: 5857 | D108: 5473 | E108: 5469 | F108: 4683 | G108: =F108 -> 4683 | H108: 4680 | I108: 4680 | J108: 4677 | K108: 3621 | L108: =K108 -> 3621 | M108: 4918 | N108: 4851 | O108: 4852 | P108: 4407 | Q108: =P108 -> 4407 | R108: 4558 | S108: 3295 | T108: 3295 | U108: 3295 | V108: =U108 -> 3295 | W108: 2994 | X108: 2995 | Y108: 2996 | Z108: 2996 | AA108: =Z108 -> 2996 | AB108: 2996 | AC108: 2997 | AD108: 2997 | AE108: 2998 | AF108: =AE108 -> 2998
A109: Long-Term Leases | C109: - | D109: - | E109: - | F109: 25 | G109: =F109 -> 25 | H109: 2823 | I109: 2836 | J109: 2819 | K109: 2918 | L109: =K109 -> 2918 | M109: 2923 | N109: 3269 | O109: 3266 | P109: 3185 | Q109: =P109 -> 3185 | R109: 3166 | S109: 3096 | T109: 3090 | U109: 3098 | V109: =U109 -> 3098 | W109: 3030 | X109: 3008 | Y109: 2988 | Z109: 2963 | AA109: =Z109 -> 2963 | AB109: 2996 | AC109: 2975 | AD109: 3034 | AE109: 2986 | AF109: =AE109 -> 2986
A110: Pension & Other Post-Retirement Benefits | C110: - | D110: - | E110: - | F110: 698 | G110: =F110 -> 698 | H110: - | I110: - | J110: - | K110: 745 | L110: =K110 -> 745 | M110: - | N110: - | O110: - | P110: 660 | Q110: =P110 -> 660 | R110: - | S110: - | T110: - | U110: 598 | V110: =U110 -> 598 | W110: - | X110: - | Y110: - | Z110: 495 | AA110: =Z110 -> 495 | AB110: - | AC110: - | AD110: - | AE110: 456 | AF110: =AE110 -> 456
A111: Def. Tax Liability, Non-Curr. | C111: 1169 | D111: 1194 | E111: 1185 | F111: 1238 | G111: =F111 -> 1238 | H111: 1193 | I111: 1206 | J111: 1200 | K111: 1169 | L111: =K111 -> 1169 | M111: 944 | N111: 921 | O111: 917 | P111: 908 | Q111: =P111 -> 908 | R111: 868 | S111: 913 | T111: 970 | U111: 983 | V111: =U111 -> 983 | W111: 968 | X111: 948 | Y111: 884 | Z111: 947 | AA111: =Z111 -> 947 | AB111: 916 | AC111: 933 | AD111: 925 | AE111: 745 | AF111: =AE111 -> 745
A112: Other Non-Current Liabilities | C112: 1664 | D112: 1626 | E112: 1618 | F112: 882 | G112: =F112 -> 882 | H112: 1258 | I112: 1265 | J112: 1315 | K112: 592 | L112: =K112 -> 592 | M112: 1327 | N112: 1395 | O112: 1285 | P112: 636 | Q112: =P112 -> 636 | R112: 1297 | S112: 1267 | T112: 1245 | U112: 579 | V112: =U112 -> 579 | W112: 1159 | X112: 1152 | Y112: 1144 | Z112: 522 | AA112: =Z112 -> 522 | AB112: 1008 | AC112: 1005 | AD112: 997 | AE112: 494 | AF112: =AE112 -> 494
A113: Total Non-Current Liabilities | C113: =SUM(C108:C112) -> 8690 | D113: =SUM(D108:D112) -> 8293 | E113: =SUM(E108:E112) -> 8272 | F113: =SUM(F108:F112) -> 7526 | G113: =F113 -> 7526 | H113: =SUM(H108:H112) -> 9954 | I113: =SUM(I108:I112) -> 9987 | J113: =SUM(J108:J112) -> 10011 | K113: =SUM(K108:K112) -> 9045 | L113: =K113 -> 9045 | M113: =SUM(M108:M112) -> 10112 | N113: =SUM(N108:N112) -> 10436 | O113: =SUM(O108:O112) -> 10320 | P113: =SUM(P108:P112) -> 9796 | Q113: =P113 -> 9796 | R113: =SUM(R108:R112) -> 9889 | S113: =SUM(S108:S112) -> 8571 | T113: =SUM(T108:T112) -> 8600 | U113: =SUM(U108:U112) -> 8553 | V113: =U113 -> 8553 | W113: =SUM(W108:W112) -> 8151 | X113: =SUM(X108:X112) -> 8103 | Y113: =SUM(Y108:Y112) -> 8012 | Z113: =SUM(Z108:Z112) -> 7923 | AA113: =Z113 -> 7923 | AB113: =SUM(AB108:AB112) -> 7916 | AC113: =SUM(AC108:AC112) -> 7910 | AD113: =SUM(AD108:AD112) -> 7953 | AE113: =SUM(AE108:AE112) -> 7679 | AF113: =AE113 -> 7679
A115: Total Liabilities | C115: =C106+C113 -> 13767 | D115: =D106+D113 -> 12774 | E115: =E106+E113 -> 14716 | F115: =F106+F113 -> 12758 | G115: =G106+G113 -> 12758 | H115: =H106+H113 -> 14973 | I115: =I106+I113 -> 14426 | J115: =J106+J113 -> 16490 | ... AF115: =AF106+AF113 -> 12211
A117: Common Stock | C117: 5821 | D117: 5916 | E117: 5667 | F117: 3 | G117: =F117 -> 3 | H117: 3 | I117: 3 | J117: 3 | K117: 3 | L117: =K117 -> 3 | M117: 3 | N117: 3 | O117: 3 | P117: 3 | Q117: =P117 -> 3 | R117: 3 | S117: 3 | T117: 3 | U117: 3 | V117: =U117 -> 3 | W117: 3 | X117: 3 | Y117: 3 | Z117: 3 | AA117: =Z117 -> 3 | AB117: 3 | AC117: 3 | AD117: 3 | AE117: 3 | AF117: =AE117 -> 3
A118: Additional Paid In Capital | C118: - | D118: - | E118: - | F118: 652 | G118: =F118 -> 652 | H118: 606 | I118: 617 | J118: 626 | K118: 621 | L118: =K118 -> 621 | M118: 565 | N118: 568 | O118: 575 | P118: 571 | Q118: =P118 -> 571 | R118: 558 | S118: 498 | T118: 507 | U118: 517 | V118: =U118 -> 517 | W118: 476 | X118: 450 | Y118: 463 | Z118: 467 | AA118: =Z118 -> 467 | AB118: 373 | AC118: 352 | AD118: 367 | AE118: 352 | AF118: =AE118 -> 352
A119: Retained Earnings | C119: - | D119: - | E119: - | F119: 8050 | G119: =F119 -> 8050 | H119: 7911 | I119: 7883 | J119: 7649 | K119: 7989 | L119: =K119 -> 7989 | M119: 4291 | N119: 3860 | O119: 3769 | P119: 3928 | Q119: =P119 -> 3928 | R119: 4031 | S119: 4376 | T119: 4523 | U119: 5268 | V119: =U119 -> 5268 | W119: 5509 | X119: 5742 | Y119: 5764 | Z119: 6268 | AA119: =Z119 -> 6268 | AB119: 6378 | AC119: 6310 | AD119: 6261 | AE119: 6088 | AF119: =AE119 -> 6088
A120: Treasury Stock | C120: - | D120: - | E120: - | F120: -1318 | G120: =F120 -> -1318 | H120: -1252 | I120: -1248 | J120: -1244 | K120: -1241 | L120: =K120 -> -1241 | M120: -1180 | N120: -1176 | O120: -1175 | P120: -1161 | Q120: =P120 -> -1161 | R120: -1137 | S120: -1066 | T120: -1364 | U120: -1545 | V120: =U120 -> -1545 | W120: -2092 | X120: -2049 | Y120: -2048 | Z120: -2038 | AA120: =Z120 -> -2038 | AB120: -1967 | AC120: -1929 | AD120: -1928 | AE120: -1912 | AF120: =AE120 -> -1912
A121: Comprehensive Inc. and Other | C121: - | D121: - | E121: - | F121: -951 | G121: =F121 -> -951 | H121: - | I121: - | J121: - | K121: -995 | L121: =K121 -> -995 | M121: - | N121: - | O121: - | P121: -788 | Q121: =P121 -> -788 | R121: - | S121: - | T121: - | U121: -622 | V121: =U121 -> -622 | W121: - | X121: - | Y121: - | Z121: -618 | AA121: =Z121 -> -618 | AB121: - | AC121: - | AD121: - | AE121: -496 | AF121: =AE121 -> -496
A122: Total Common Equity | C122: =SUM(C117:C121) -> 5821 | D122: =SUM(D117:D121) -> 5916 | E122: =SUM(E117:E121) -> 5667 | F122: =SUM(F117:F121) -> 6436 | G122: =F122 -> 6436 | H122: =SUM(H117:H121) -> 7268 | I122: =SUM(I117:I121) -> 7255 | J122: =SUM(J117:J121) -> 7034 | K122: =SUM(K117:K121) -> 6377 | L122: =K122 -> 6377 | M122: =SUM(M117:M121) -> 3679 | N122: =SUM(N117:N121) -> 3255 | O122: =SUM(O117:O121) -> 3172 | P122: =SUM(P117:P121) -> 2553 | Q122: =P122 -> 2553 | R122: =SUM(R117:R121) -> 3455 | S122: =SUM(S117:S121) -> 3811 | T122: =SUM(T117:T121) -> 3669 | U122: =SUM(U117:U121) -> 3621 | V122: =U122 -> 3621 | W122: =SUM(W117:W121) -> 3896 | X122: =SUM(X117:X121) -> 4146 | Y122: =SUM(Y117:Y121) -> 4182 | Z122: =SUM(Z117:Z121) -> 4082 | AA122: =Z122 -> 4082 | AB122: =SUM(AB117:AB121) -> 4787 | AC122: =SUM(AC117:AC121) -> 4736 | AD122: =SUM(AD117:AD121) -> 4703 | AE122: =SUM(AE117:AE121) -> 4035 | AF122: =AE122 -> 4035
A124: Minority Interest | C124: -20 | D124: -22 | E124: -22 | F124: 0 | G124: =F124 -> 0 | H124: 0 | I124: 0 | J124: 0 | K124: 0 | L124: 0 | M124: 0 | N124: 0 | O124: 0 | P124: 0 | Q124: 0 | R124: 0 | S124: 0 | T124: 0 | U124: 0 | V124: 0 | W124: 0 | X124: 0 | Y124: 0 | Z124: 0 | AA124: 0 | AB124: 0 | AC124: 0 | AD124: 0 | AE124: 0 | AF124: 0
A126: Total Equity | C126: =C122+C124 -> 5801 | D126: =D122+D124 -> 5894 | E126: =E122+E124 -> 5645 | F126: =F122+F124 -> 6436 | G126: =G122+G124 -> 6436 | H126: =H122+H124 -> 7268 | I126: =I122+I124 -> 7255 | J126: =J122+J124 -> 7034 | ... AF126: =AF122+AF124 -> 4035
A128: Total Liabilities And Equity | C128: =C115+C126 -> 19568 | D128: =D115+D126 -> 18668 | E128: =E115+E126 -> 20361 | F128: =F115+F126 -> 19194 | G128: =G115+G126 -> 19194 | H128: =H115+H126 -> 22241 | I128: =I115+I126 -> 21681 | J128: =J115+J126 -> 23524 | ... AF128: =AF115+AF126 -> 16246
A131: Check: A = L + E? | C131: =IF(C95=C128, "True", C95-C128) -> True | D131: =IF(D95=D128, "True", D95-D128) -> True | E131: =IF(E95=E128, "True", E95-E128) -> True | F131: =IF(F95=F128, "True", F95-F128) -> True | G131: =IF(G95=G128, "True", G95-G128) -> True | H131: =IF(H95=H128, "True", H95-H128) -> -945 | I131: =IF(I95=I128, "True", I95-I128) -> -940 | J131: =IF(J95=J128, "True", J95-J128) -> -977 | ... AF131: =IF(AF95=AF128, "True", AF95-AF128) -> True
A133: Cash Flow Statement | G133: 2019 | L133: 2020 | Q133: 2021 | V133: 2022 | AA133: 2023 | AF133: 2024
A134: For the Fiscal Period Ending | C134: 1Q 2019 | D134: 2Q 2019 | E134: 3Q 2019 | F134: 4Q 2019 | G134: 2019A | H134: 1Q 2020 | I134: 2Q 2020 | J134: 3Q 2020 | K134: 4Q 2020 | L134: 2020A | M134: 1Q 2021 | N134: 2Q 2021 | O134: 3Q 2021 | P134: 4Q 2021 | Q134: 2021A | R134: 1Q 2022 | S134: 2Q 2022 | T134: 3Q 2022 | U134: 4Q 2022 | V134: 2022A | W134: 1Q 2023 | X134: 2Q 2023 | Y134: 3Q 2023 | Z134: 4Q 2023 | AA134: 2023A | AB134: 1Q 2024 | AC134: 2Q 2024 | AD134: 3Q 2024 | AE134: 4Q2024 | AF134: 2024A
A135: Currency: USD
A137: Net Income | C137: 139 | D137: 167 | E137: 62 | F137: 740 | G137: =SUM(C137:F137) -> 1108 | H137: 136 | I137: 87 | J137: 1 | K137: 340 | L137: =SUM(H137:K137) -> 564 | M137: -3581 | N137: -431 | O137: -92 | P137: 160 | Q137: =SUM(M137:P137) -> -3944 | R137: 103 | S137: 345 | T137: 239 | U137: 743 | V137: =SUM(R137:U137) -> 1430 | W137: 286 | X137: 275 | Y137: 107 | Z137: 509 | AA137: =SUM(W137:Z137) -> 1177 | AB137: 155 | AC137: -22 | AD137: 40 | AE137: -128 | AF137: =SUM(AB137:AE137) -> 45
A138: Depreciation & Amort. | C138: 235 | D138: 235 | E138: 248 | F138: -52 | G138: =SUM(C138:F138) -> 666 | H138: 236 | I138: 236 | J138: 253 | K138: -29 | L138: =SUM(H138:K138) -> 696 | M138: 237 | N138: 235 | O138: 250 | P138: -31 | Q138: =SUM(M138:P138) -> 691 | R138: 224 | S138: 220 | T138: 224 | U138: -32 | V138: =SUM(R138:U138) -> 636 | W138: 206 | X138: 207 | Y138: 225 | Z138: -16 | AA138: =SUM(W138:Z138) -> 622 | AB138: 218 | AC138: 215 | AD138: 232 | AE138: -37 | AF138: =SUM(AB138:AE138) -> 628
A139: Depreciation & Amort., Total | C139: =C138 -> 235 | D139: =D138 -> 235 | E139: =E138 -> 248 | F139: =F138 -> -52 | G139: =G138 -> 666 | H139: =H138 -> 236 | I139: =I138 -> 236 | J139: =J138 -> 253 | ... AF139: =AF138 -> 628
A141: Other Amortization | C141: - | D141: -5 | E141: 0 | F141: 286 | G141: =SUM(C141:F141) -> 281 | H141: - | I141: 1 | J141: 0 | K141: 288 | L141: =SUM(H141:K141) -> 289 | M141: - | N141: 4 | O141: 7 | P141: 275 | Q141: =SUM(M141:P141) -> 286 | R141: 8 | S141: 6 | T141: 52 | U141: 242 | V141: =SUM(R141:U141) -> 308 | W141: 2 | X141: 3 | Y141: 3 | Z141: 238 | AA141: =SUM(W141:Z141) -> 246 | AB141: 3 | AC141: 2 | AD141: 3 | AE141: 271 | AF141: =SUM(AB141:AE141) -> 279
A142: (Gain) Loss From Sale Of Assets | C142: -24 | D142: -46 | E142: -41 | F142: -278 | G142: =SUM(C142:F142) -> -389 | H142: -43 | I142: -6 | J142: -18 | K142: -95 | L142: =SUM(H142:K142) -> -162 | M142: -16 | N142: 0 | O142: -4 | P142: -40 | Q142: =SUM(M142:P142) -> -60 | R142: -6 | S142: -6 | T142: -49 | U142: -30 | V142: =SUM(R142:U142) -> -91 | W142: -42 | X142: 0 | Y142: -32 | Z142: -15 | AA142: =SUM(W142:Z142) -> -89 | AB142: -11 | AC142: -4 | AD142: -5 | AE142: -41 | AF142: =SUM(AB142:AE142) -> -61
A143: Asset Writedown & Restructuring Costs | C143: 19 | D143: 17 | E143: 3 | F143: 105 | G143: =SUM(C143:F143) -> 144 | H143: - | I143: 1 | J143: 5 | K143: 348 | L143: =SUM(H143:K143) -> 354 | M143: 3175 | N143: 183 | O143: 8 | P143: 138 | Q143: =SUM(M143:P143) -> 3504 | R143: 19 | S143: 2 | T143: 0 | U143: -12 | V143: =SUM(R143:U143) -> 9 | W143: 8 | X143: 2 | Y143: 15 | Z143: -5 | AA143: =SUM(W143:Z143) -> 20 | AB143: 2 | AC143: 4 | AD143: 15 | AE143: 991 | AF143: =SUM(AB143:AE143) -> 1012
...

Sheet D&A
F8: HISTORICAL | AJ8: FORECASTED
A10: Average useful life | B10: 15 | F10: 19Q1 | G10: 19Q2 | H10: 19Q3 | I10: 19Q4 | J10: 2019A | K10: 20Q1 | L10: 20Q2 | M10: 20Q3 | N10: 20Q4 | O10: 2020A | P10: 21Q1 | Q10: 21Q2 | R10: 21Q3 | S10: 21Q4 | T10: 2021A | U10: 22Q1 | V10: 22Q2 | W10: 22Q3 | X10: 22Q4 | Y10: 2022A | Z10: 23Q1 | AA10: 23Q2 | AB10: 23Q3 | AC10: 23Q4 | AD10: 2023A | AE10: 24Q1 | AF10: 24Q2 | AG10: 24Q3 | AH10: 24Q4 | AI10: 2024A | AJ10: 25Q1 | AK10: 25Q2 | AL10: 25Q3 | AM10: 25Q4 | AN10: 2025E | AO10: 26Q1 | AP10: 26Q2 | AQ10: 26Q3 | AR10: 26Q4 | AS10: 2026E | AT10: 2027Q1 | AU10: 2027Q2 | AV10: 2027Q3 | AW10: 2027Q4 | AX10: 2027E | AY10: 2028Q1 | AZ10: 2028Q2 | BA10: 2028Q3 | BB10: 2028Q4 | BC10: 2028E | BD10: 2029Q1 | BE10: 2029Q2 | BF10: 2029Q3 | BG10: 2029Q4 | BH10: 2029E
A12: CAPEX | E12: USD'm | F12: =-CFS!$C$34 -> 132 | G12: =-CFS!$D$34 -> 143 | H12: =-CFS!$E$34 -> 193 | I12: =-CFS!$F$34 -> 189 | J12: =-CFS!$AA$34 -> 657 | K12: =-CFS!G34 -> 204 | L12: =-CFS!H34 -> 174 | M12: =-CFS!I34 -> 245 | N12: =-CFS!J34 -> 279 | O12: =-CFS!AB34 -> 902 | P12: =-CFS!K34 -> 122 | Q12: =-CFS!L34 -> 106 | R12: =-CFS!M34 -> 62 | S12: =-CFS!N34 -> 48 | T12: =-CFS!AC34 -> 338 | U12: =-CFS!O34 -> 61 | V12: =-CFS!P34 -> 81 | W12: =-CFS!Q34 -> 88 | X12: =-CFS!R34 -> 124 | Y12: =-CFS!AD34 -> 354 | Z12: =-CFS!S34 -> 171 | AA12: =-CFS!T34 -> 207 | AB12: =-CFS!U34 -> 277 | AC12: =-CFS!V34 -> 233 | AD12: =-CFS!AE34 -> 888 | AE12: =-CFS!W34 -> 215 | AF12: =-CFS!X34 -> 175 | AG12: =-CFS!Y34 -> 95 | AH12: =-CFS!Z34 -> 146 | AI12: =-CFS!AF34 -> 631 | AJ12: 175 | AK12: 175 | AL12: 175 | AM12: 175 | AN12: =SUM(AJ12:AM12) -> 700 | AO12: 200 | AP12: 200 | AQ12: 200 | AR12: 200 | AS12: =SUM(AO12:AR12) -> 800 | AT12: 200 | AU12: 200 | AV12: 200 | AW12: 200 | AX12: 800 | AY12: 200 | AZ12: 200 | BA12: 200 | BB12: 200 | BC12: 800 | BD12: 200 | BE12: 200 | BF12: 200 | BG12: 200 | BH12: 800
A13: % change in CAPEX | E13: % | G13: =(G12-F12)/F12 -> 0.083333333 | H13: =(H12-G12)/G12 -> 0.34965035 | I13: =(I12-H12)/H12 -> -0.020725389 | J13: =AVERAGE(G13:I13) -> 0.13741943 | K13: =(K12-I12)/I12 -> 0.079365079 | L13: =(L12-K12)/K12 -> -0.14705882 | M13: =(M12-L12)/L12 -> 0.40804598 | N13: =(N12-M12)/M12 -> 0.13877551 | O13: =AVERAGE(K13:N13) -> 0.11978194 | P13: =(P12-N12)/N12 -> -0.56272401 | Q13: =(Q12-P12)/P12 -> -0.13114754 | R13: =(R12-Q12)/Q12 -> -0.41509434 | S13: =(S12-R12)/R12 -> -0.22580645 | T13: =AVERAGE(P13:S13) -> -0.33369309 | U13: =(U12-S12)/S12 -> 0.27083333 | V13: =(V12-U12)/U12 -> 0.32786885 | W13: =(W12-V12)/V12 -> 0.086419753 | X13: =(X12-W12)/W12 -> 0.40909091 | Y13: =AVERAGE(U13:X13) -> 0.27355321 | Z13: =(Z12-X12)/X12 -> 0.37903226 | AA13: =(AA12-Z12)/Z12 -> 0.21052632 | AB13: =(AB12-AA12)/AA12 -> 0.33816425 | AC13: =(AC12-AB12)/AB12 -> -0.15884477 | AD13: =AVERAGE(Z13:AC13) -> 0.19221951 | AE13: =(AE12-AC12)/AC12 -> -0.077253219 | AF13: =(AF12-AE12)/AE12 -> -0.18604651 | AG13: =(AG12-AF12)/AF12 -> -0.45714286 | AH13: =(AH12-AG12)/AG12 -> 0.53684211 | AI13: =AVERAGE(AE13:AH13) -> -0.045900121 | AJ13: =(AJ12-AH12)/AH12 -> 0.19863014 | AK13: =(AK12-AJ12)/AJ12 -> 0 | AL13: =(AL12-AK12)/AK12 -> 0 | AM13: =(AM12-AL12)/AL12 -> 0 | AN13: =(AN12-AI12)/AI12 -> 0.10935024 | AO13: =(AO12-AM12)/AM12 -> 0.14285714 | AP13: =(AP12-AO12)/AO12 -> 0 | AQ13: =(AQ12-AP12)/AP12 -> 0 | AR13: =(AR12-AQ12)/AQ12 -> 0 | AS13: =AVERAGE(AO13:AR13) -> 0.035714286 | AT13: =(AT12-AR12)/AR12 -> 0 | AU13: =(AU12-AT12)/AT12 -> 0 | AV13: =(AV12-AU12)/AU12 -> 0 | AW13: =(AW12-AV12)/AV12 -> 0 | AX13: =(AX12-AS12)/AS12 -> 0 | AY13: =(AY12-AW12)/AW12 -> 0 | AZ13: =(AZ12-AY12)/AY12 -> 0 | BA13: =(BA12-AZ12)/AZ12 -> 0 | BB13: =(BB12-BA12)/BA12 -> 0 | BC13: =(BC12-AX12)/AX12 -> 0 | BD13: =(BD12-BB12)/BB12 -> 0 | BE13: =(BE12-BD12)/BD12 -> 0 | BF13: =(BF12-BE12)/BE12 -> 0 | BG13: =(BG12-BF12)/BF12 -> 0 | BH13: =(BH12-BC12)/BC12 -> 0
A15: PPE
A17: Beginning PPE | AN17: =AI33 -> 7613 | AS17: =AN33 -> 7758.8 | AX17: =AS33 -> 7941.5467 | BC17: =AX33 -> 8058.7769 | BH17: =BC33 -> 8114.8584
A18: Additions: CAPEX | AN18: =AN12 -> 700 | AS18: =AS12 -> 800 | AX18: =AX12 -> 800 | BC18: =BC12 -> 800 | BH18: =BH12 -> 800
A19: Additions / (subtractions) in other CAPEX | AN19: 0
A21: Depreciation of existing PPE | AN21: =-AN17/B10 -> -507.53333 | AS21: =-AS17/$B10 -> -517.25333 | AX21: =-AX17/$B10 -> -529.43644 | BC21: =-BC17/$B10 -> -537.25179 | BH21: =-BH17/$B10 -> -540.99056
A22: Depreciation of new CAPEX:
A23: 2025E | AN23: =-$AN$12/$B$10 -> -46.666667 | AS23: =-$AN$12/$B$10 -> -46.666667 | AX23: =-$AN$12/$B$10 -> -46.666667 | BC23: =-$AN$12/$B$10 -> -46.666667 | BH23: =-$AN$12/$B$10 -> -46.666667
A24: 2026E | B24: =AN12 -> 700 | AS24: =-$AS$18/$B$10 -> -53.333333 | AX24: =-$AS$18/$B$10 -> -53.333333 | BC24: =-$AS$18/$B$10 -> -53.333333 | BH24: =-$AS$18/$B$10 -> -53.333333
A25: 2027E | B25: =AS12 -> 800 | AX25: =-$AX$18/$B$10 -> -53.333333 | BC25: =-$AX$18/$B$10 -> -53.333333 | BH25: =-$AX$18/$B$10 -> -53.333333
A26: 2028E | B26: =AX12 -> 800 | BC26: =-BC18/$B10 -> -53.333333 | BH26: =-BH18/$B10 -> -53.333333
A27: 2029E | B27: =BC12 -> 800 | BH27: =-BH18/$B10 -> -53.333333
B28: =BH12 -> 800
A29: Total depreciation of new CAPEX | E29: USD'm | AN29: =SUM(AN23:AN28) -> -46.666667 | AS29: =SUM(AS23:AS28) -> -100 | AX29: =SUM(AX23:AX28) -> -153.33333 | BC29: =SUM(BC23:BC28) -> -206.66667 | BH29: =SUM(BH23:BH27) -> -260
A31: Total depreciation | E31: USD'm | AN31: =SUM(AN21,AN29) -> -554.2 | AS31: =SUM(AS21,AS29) -> -617.25333 | AX31: =SUM(AX21,AX29) -> -682.76978 | BC31: =SUM(BC21,BC29) -> -743.91846 | BH31: =SUM(BH21,BH29) -> -800.99056
A33: Closing PPE | E33: USD'm | F33: =BS!C33 -> 6575 | G33: =BS!D33 -> 6547 | H33: =BS!E33 -> 6572 | I33: =BS!F33 -> 6637 | J33: =BS!G33 -> 6637 | K33: =BS!H33 -> 9130 | L33: =BS!I33 -> 9119 | M33: =BS!J33 -> 9154 | ... AI33: =BS!AF33 -> 7613 | AN33: =SUM(AN17,AN18,AN19,AN31) -> 7758.8 | AS33: =SUM(AS17,AS18,AS19,AS31) -> 7941.5467 | AX33: =SUM(AX17,AX18,AX19,AX31) -> 8058.7769 | BC33: =SUM(BC17,BC18,BC19,BC31) -> 8114.8584 | BH33: =SUM(BH17,BH18,BH19,BH31) -> 8113.8679

Sheet Stores
B2: Count | D2: Locations
D3: 2024 | E3: 2023 | F3: 2022 | G3: 2021 | H3: 2020 | J3: 2025 | K3: 2026
B5: Macy's Department Stores | D5: 390 | E5: 435 | F5: 441 | G5: =51+395 -> 446 | H5: =58+395 -> 453
B6: Macy's Furniture | D6: 34 | E6: 45 | F6: 46 | G6: 47 | H6: 47
B7: Macy's Furniture Clearance | D7: 1 | E7: 1 | F7: 1 | G7: 2 | H7: 2
B8: Freestanding Backstage* | D8: 5 | E8: 9 | F8: 9 | G8: 8 | H8: 6
B9: Macy's Small Format | D9: 20 | E9: 12 | F9: 8 | G9: 5 | H9: 2
B10: Stores converted to Fulfillment Centers | F10: 2 | G10: 2 | H10: 2
B11: Total Macy's | D11: 450 | E11: 502 | F11: 507 | G11: 510 | H11: 512 | J11: =D11-50 -> 400 | K11: =J11-50 -> 350
B14: Bloomingdale's Department Stores | D14: 31 | E14: 32 | F14: 32 | G14: 33 | H14: 33
B15: Bloomie's | D15: 4 | E15: 3 | F15: 2 | G15: 1 | H15: 0
B16: Bloomingdale's Furniture/Other | D16: 1 | E16: 1 | F16: 1 | G16: 1 | H16: 1
B17: Bloomingdale's The Outlet | D17: 23 | E17: 21 | F17: 20 | G17: 20 | H17: 19
B18: Total Bloomingdale's | D18: 59 | E18: 57 | F18: 55 | G18: 55 | H18: 53 | J18: =ROUND(D18*SQRT(1.2),0)+2 -> 67 | K18: =ROUND(J18*SQRT(1.2),0)+1 -> 74 | M18: =K18-D18 -> 15 | N18: =K18/D18 -> 1.2542373
B20: Bluemercury | D20: 171 | E20: 159 | F20: 160 | G20: 160 | H20: 162 | J20: =ROUND(D20*SQRT(1.2),0) -> 187 | K20: =ROUND(J20*SQRT(1.2),0) -> 205 | M20: =K20-D20 -> 34 | N20: =K20/D20 -> 1.1988304
B22: Total Macy's, Inc. | D22: 680 | E22: 718 | F22: 722 | G22: 725 | H22: 727 | J22: =SUM(J11,J18,J20) -> 654 | K22: =SUM(K11,K18,K20) -> 629

Sheet Schedule's
A1: Cost Schedule | BJ1: Assumptions
E2: Units | F2: 19Q1 | G2: 19Q2 | H2: 19Q3 | I2: 19Q4 | J2: 2019A | K2: 20Q1 | L2: 20Q2 | M2: 20Q3 | N2: 20Q4 | O2: 2020A | P2: 21Q1 | Q2: 21Q2 | R2: 21Q3 | S2: 21Q4 | T2: 2021A | U2: 22Q1 | V2: 22Q2 | W2: 22Q3 | X2: 22Q4 | Y2: 2022A | Z2: 23Q1 | AA2: 23Q2 | AB2: 23Q3 | AC2: 23Q4 | AD2: 2023A | AE2: 24Q1 | AF2: 24Q2 | AG2: 24Q3 | AH2: 24Q4 | AI2: 2024A | AJ2: 25Q1 | AK2: 25Q2 | AL2: 25Q3 | AM2: 25Q4 | AN2: 2025E | AO2: 26Q1 | AP2: 26Q2 | AQ2: 26Q3 | AR2: 26Q4 | AS2: 2026E | AT2: 27Q1 | AU2: 27Q2 | AV2: 27Q3 | AW2: 27Q4 | AX2: 2027E | AY2: 2028E | AZ2: Please add all the assumption here (ex- projected sg&a as a % of sales | BJ2: Cost of sales : Base case 61.6% , Bull : 61.3% , Bear : 61.8% (the extra % is cos of π)
A3: Total Revenue | E3: USD | F3: 5698 | G3: 5758 | H3: 5589 | I3: 8695 | J3: 25739 | K3: 5676 | L3: 5722 | M3: 5356 | N3: 8577 | O3: 25331 | P3: 3148 | Q3: 3727 | R3: 4185 | S3: 7037 | T3: 18097 | U3: 4865 | V3: 5844 | W3: 5653 | X3: 8930 | Y3: 25399 | Z3: 5565 | AA3: 5834 | AB3: 5467 | AC3: 8583 | AD3: 25449 | AE3: 5173 | AF3: 5280 | AG3: 5038 | AH3: 8375 | AI3: 23866 | AJ3: =AJ16 -> 5966.4834 | AK3: =AK16 -> 5966.4834 | AL3: =AL16 -> 5966.4834 | AM3: =AM16 -> 5966.4834 | AN3: =AN16 -> 23865.934 | AO3: =AO16 -> 6309.5163 | AP3: =AP16 -> 6309.5163 | AQ3: =AQ16 -> 6309.5163 | ... AY3: =AY16 -> 25238.31
A4: YoY Growth % | K4: =(K3-F3)/F3 -> -0.0038610039 | L4: =(L3-G3)/G3 -> -0.0062521709 | M4: =(M3-H3)/H3 -> -0.041689032 | N4: =(N3-I3)/I3 -> -0.013571018 | O4: =(O3-J3)/J3 -> -0.015851432 | P4: =(P3-K3)/K3 -> -0.44538407 | Q4: =(Q3-L3)/L3 -> -0.34865432 | R4: =(R3-M3)/M3 -> -0.21863331 | ... AX4: =(AX3-AS3)/AS3 -> 3.959206e-06 | AY4: =(AY3-AX3)/AX3 -> 5.7357009e-06
A5: Cost of sales | F5: 3382 | G5: 3320 | H5: 3226 | I5: 5288 | J5: =SUM(F5:I5) -> 15216 | K5: 3403 | L5: 3395 | M5: 3106 | N5: 5266 | O5: =SUM(K5:N5) -> 15170 | P5: 2201 | Q5: 2718 | R5: 2569 | S5: 4798 | T5: =SUM(P5:S5) -> 12286 | U5: 2889 | V5: 3353 | W5: 3207 | X5: 5507 | Y5: =SUM(U5:X5) -> 14956 | Z5: 3231 | AA5: 3422 | AB5: 3204 | AC5: 5450 | AD5: =SUM(Z5:AC5) -> 15307 | AE5: 2988 | AF5: 3176 | AG5: 2905 | AH5: 5154 | AI5: =SUM(AE5:AH5) -> 14223 | AN5: =AI$5*AN6 -> 8761.368 | AS5: =AN$5*AS6 -> 5397.0027 | AX5: =AS$5*AX6 -> 3324.5537 | AY5: =AX$5*AY6 -> 2047.9251
A6: COGS Margin | E6: % | F6: =F5/F3 -> 0.59354159 | G6: =G5/G3 -> 0.57658909 | H6: =H5/H3 -> 0.57720522 | I6: =I5/I3 -> 0.60816561 | J6: =J5/J3 -> 0.59116516 | K6: =K5/K3 -> 0.59954193 | L6: =L5/L3 -> 0.59332401 | M6: =M5/M3 -> 0.57991038 | ... AI6: =AI5/AI3 -> 0.5959524 | AN6: 0.616 | AS6: 0.616 | AX6: 0.616 | AY6: 0.616
A7: Gross Margin | E7: % | F7: =1-F6 -> 0.40645841 | G7: =1-G6 -> 0.42341091 | H7: =1-H6 -> 0.42279478 | I7: =1-I6 -> 0.39183439 | J7: =1-J6 -> 0.40883484 | K7: =1-K6 -> 0.40045807 | L7: =1-L6 -> 0.40667599 | M7: =1-M6 -> 0.42008962 | ... AI7: =1-AI6 -> 0.4040476 | AN7: 0.4 | AS7: 0.4 | AX7: 0.4 | AY7: 0.4
A9: Operating Expense
A10: SG&A | F10: 2072 | G10: 2153 | H10: 2246 | I10: 2530 | J10: =SUM(F10:I10) -> 9001 | K10: 2105 | L10: 2169 | M10: 2194 | N10: 2501 | O10: =SUM(K10:N10) -> 8969 | P10: 1589 | Q10: 1386 | R10: 1710 | S10: 2027 | T10: 6713 | U10: 1733 | V10: 1881 | W10: 1956 | X10: 2412 | Y10: =SUM(U10:X10) -> 7982 | Z10: 1898 | AA10: 2004 | AB10: 2081 | AC10: 2457 | AD10: =SUM(Z10:AC10) -> 8440 | AE10: 1946 | AF10: 1976 | AG10: 2038 | AH10: 2404 | AI10: =SUM(AE10:AH10) -> 8364
A11: Impairment, Restructing and other costs | F11: - | G11: - | H11: - | I11: -8 | J11: =SUM(F11:I11) -> -8 | K11: 1 | L11: 1 | M11: 8 | N11: -10 | O11: =SUM(K11:N11) -> 0 | P11: 9 | Q11: 58 | R11: 12 | S11: -79 | T11: - | U11: - | V11: - | W11: - | X11: 21 | Y11: =SUM(U11:X11) -> 21 | Z11: - | AA11: - | AB11: - | AC11: 21 | AD11: =SUM(Z11:AC11) -> 21 | AE11: - | AF11: - | AG11: - | AH11: 15 | AI11: 15
A12: Marketing Expense | J12: 1142 | O12: 818 | T12: 1177 | Y12: 1163 | AD12: 1107 | AI12: 1102
J13: =SUM(J10:J12) -> 10135 | O13: =SUM(O10:O12) -> 9787 | T13: =SUM(T10:T12) -> 7890 | Y13: =SUM(Y10:Y12) -> 9166 | AD13: =SUM(AD10:AD12) -> 9568 | AI13: =SUM(AI10:AI12) -> 9481
A14: Revenue Schedule | B14: Base Case (Old) | AM14: Projected Revenue Schedule | BB14: MACY'S MARKET SHARE | BC14: 0.13
BA15: Industry | BB15: YoY Growth rate | BC15: EXPECTED SEGMENT GROWTH FROM MACY NEWS AND REPORTS | BR15: 2019 | BS15: 2020 | BT15: 2021 | BU15: 2022 | BV15: 2023 | BW15: 2024 | BX15: 2025 | BY15: 2026 | BZ15: 2027 | CA15: 2028 | CB15: 2029
A16: Total Revenue (USD) | F16: 5698 | G16: 5758 | H16: 5589 | I16: 8695 | J16: 25739 | K16: 5676 | L16: 5722 | M16: 5356 | N16: 8577 | O16: 25331 | P16: 3148 | Q16: 3727 | R16: 4185 | S16: 7037 | T16: 18097 | U16: 4865 | V16: 5844 | W16: 5653 | X16: 8930 | Y16: 25399 | Z16: 5565 | AA16: 5834 | AB16: 5467 | AC16: 8583 | AD16: 25449 | AE16: 5173 | AF16: 5280 | AG16: 5038 | AH16: 8375 | AI16: 23866 | AJ16: =AJ23+AJ24 -> 5966.4834 | AK16: =AK23+AK24 -> 5966.4834 | AL16: =AL23+AL24 -> 5966.4834 | AM16: =AM23+AM24 -> 5966.4834 | AN16: =AN23+AN24 -> 23865.934 | AO16: =AO23+AO24 -> 6309.5163 | AP16: =AP23+AP24 -> 6309.5163 | AQ16: =AQ23+AQ24 -> 6309.5163 | ... AY16: =AY23+AY24 -> 25238.31 | BA16: Accesesories | BB16: 0.029 | BC16: 2-3% | BQ16: no of stores | BR16: 839 | BS16: 789 | BT16: 787 | BU16: 783 | BV16: 718 | BW16: 680 | BX16: =BW16-66 -> 614 | BY16: =BX16-84 -> 530 | BZ16: =BY16-16 -> 514 | CA16: 516 | CB16: 516
A17: YoY Revenue Growth % | K17: =K4 -> -0.0038610039 | L17: =L4 -> -0.0062521709 | M17: =M4 -> -0.041689032 | N17: =N4 -> -0.013571018 | O17: =O4 -> -0.015851432 | P17: =P4 -> -0.44538407 | Q17: =Q4 -> -0.34865432 | R17: =R4 -> -0.21863331 | ... AI17: =AI4 -> -0.062202837 | BA17: wOMEN apparel | BB17: 0.0188 | BC17: 1-2% | BQ17: G rate in stores | BS17: =(BS16-BR16)/BR16 -> -0.059594756 | BT17: =(BT16-BS16)/BS16 -> -0.0025348542 | BU17: =(BU16-BT16)/BT16 -> -0.0050825921 | BV17: =(BV16-BU16)/BU16 -> -0.083014049 | BW17: =(BW16-BV16)/BV16 -> -0.052924791 | BX17: =(BX16-BW16)/BW16 -> -0.097058824 | BY17: =(BY16-BX16)/BX16 -> -0.13680782 | BZ17: =(BZ16-BY16)/BY16 -> -0.030188679 | ... CB17: =(CB16-CA16)/CA16 -> 0
A18: Segmented Revenue | BA18: men apparel | BB18: 0.0193 | BC18: 1-2% | BQ18: share of home | BR18: =BR16*16% -> 134.24 | BS18: =BS16*16% -> 126.24 | BT18: =BT16*16% -> 125.92 | BU18: =BU16*16% -> 125.28 | BV18: =BV16*16% -> 114.88 | BW18: =BW16*16% -> 108.8 | BX18: =BX16*16% -> 98.24 | BY18: =BY16*16% -> 84.8 | ... CB18: =CB16*16% -> 82.56
A19: Women’s Accessories, Shoes, Cosmetics and Fragrances | F19: 2152 | G19: 2039 | H19: 1960 | I19: =J19-(H19+G19+F19) -> 3303 | J19: 9454 | K19: 1215 | L19: 1381 | M19: 1677 | N19: =O19-(M19+L19+K19) -> 2933 | O19: 7206 | P19: 2023 | Q19: 2092 | R19: 2011 | S19: =T19-(R19+Q19+P19) -> 3709 | T19: 9835 | U19: 2237 | V19: 2099 | W19: 2025 | X19: =Y19-(W19+V19+U19) -> 3236 | Y19: 9597 | Z19: 2025 | AA19: 2050 | AB19: 1992 | AC19: =AD19-(AB19+AA19+Z19) -> 3453 | AD19: 9520 | AE19: 2070 | AF19: 1990 | AG19: 1971 | AH19: =AI19-(AG19+AF19+AE19) -> 3302 | AI19: 9333 | AJ19: =$AN$19/4 -> 2333.2481 | AK19: =$AN$19/4 -> 2333.2481 | AL19: =$AN$19/4 -> 2333.2481 | AM19: =$AN$19/4 -> 2333.2481 | AN19: =BC23 -> 9332.9925 | AO19: =$AS$19/4 -> 2333.2493 | AP19: =$AS$19/4 -> 2333.2493 | AQ19: =$AS$19/4 -> 2333.2493 | AR19: =$AS$19/4 -> 2333.2493 | AS19: =BC24 -> 9332.9972 | AT19: =$AX$19/4 -> 2333.2535 | AU19: =$AX$19/4 -> 2333.2535 | AV19: =$AX$19/4 -> 2333.2535 | AW19: =$AX$19/4 -> 2333.2535 | AX19: =BC25 -> 9333.014 | AY19: =BC26 -> 9333.043 | BA19: home | BB19: 0.0493 | BC19: -0.005 | BQ19: G rate in stores | BS19: =(BS18-BR18)/BR18 -> -0.059594756 | BT19: =(BT18-BS18)/BS18 -> -0.0025348542 | BU19: =(BU18-BT18)/BT18 -> -0.0050825921 | BV19: =(BV18-BU18)/BU18 -> -0.083014049 | BW19: =(BW18-BV18)/BV18 -> -0.052924791 | BX19: =($BX$18-BW$18)/$BW18 -> -0.097058824 | BY19: =(BY18-BX18)/BX18 -> -0.13680782 | BZ19: =(BZ18-BY18)/BY18 -> -0.030188679 | CA19: =(CA18-BZ18)/BZ18 -> 0.0038910506 | CB19: =(CB18-CA18)/CA18 -> 0
A20: Women’s Apparel | F20: 1313 | G20: 1269 | H20: 1197 | I20: =J20-(H20+G20+F20) -> 1632 | J20: 5411 | K20: 579 | L20: 626 | M20: 690 | N20: =O20-(M20+L20+K20) -> 1014 | O20: 2909 | P20: 913 | Q20: 1299 | R20: 1211 | S20: =T20-(R20+Q20+P20) -> 751 | T20: 4174 | U20: 1135 | V20: 1267 | W20: 1223 | X20: =Y20-(W20+V20+U20) -> 1724 | Y20: 5349 | Z20: 1150 | AA20: 1120 | AB20: 1088 | AC20: =AD20-(AB20+AA20+Z20) -> 1503 | AD20: 4861 | AE20: 1145 | AF20: 1110 | AG20: 1077 | AH20: =AI20-(AG20+AF20+AE20) -> 1494 | AI20: 4826 | AJ20: =$AN$20/4 -> 1206.4998 | AK20: =$AN$20/4 -> 1206.4998 | AL20: =$AN$20/4 -> 1206.4998 | AM20: =$AN$20/4 -> 1206.4998 | AN20: =BG23 -> 4825.9993 | AO20: =$AS$20/4 -> 1206.5013 | AP20: =$AS$20/4 -> 1206.5013 | AQ20: =$AS$20/4 -> 1206.5013 | AR20: =$AS$20/4 -> 1206.5013 | AS20: =BG24 -> 4826.0051 | AT20: =$AX$20/4 -> 1206.5043 | AU20: =$AX$20/4 -> 1206.5043 | AV20: =$AX$20/4 -> 1206.5043 | AW20: =$AX$20/4 -> 1206.5043 | AX20: =BG25 -> 4826.0174 | AY20: =BG26 -> 4826.0362
A21: Men’s and Kids’ | F21: 1202 | G21: 1266 | H21: 1195 | I21: =J21-(H21+G21+F21) -> 1965 | J21: 5628 | K21: 573 | L21: 727 | M21: 790 | N21: =O21-(M21+L21+K21) -> 1396 | O21: 3486 | P21: 932 | Q21: 1223 | R21: 1194 | S21: =T21-(R21+Q21+P21) -> 1898 | T21: 5247 | U21: 1086 | V21: 1220 | W21: 1153 | X21: =Y21-(W21+V21+U21) -> 1838 | Y21: 5297 | Z21: 1018 | AA21: 1110 | AB21: 1049 | AC21: =AD21-(AB21+AA21+Z21) -> 1741 | AD21: 4918 | AE21: 981 | AF21: 1056 | AG21: 1034 | AH21: =AI21-(AG21+AF21+AE21) -> 1682 | AI21: 4753 | AJ21: =$AN$21/4 -> 1188.2449 | AK21: =$AN$21/4 -> 1188.2449 | AL21: =$AN$21/4 -> 1188.2449 | AM21: =$AN$21/4 -> 1188.2449 | AN21: =BK23 -> 4752.9795 | AO21: =$AS$21/4 -> 1188.243 | AP21: =$AS$21/4 -> 1188.243 | AQ21: =$AS$21/4 -> 1188.243 | AR21: =$AS$21/4 -> 1188.243 | AS21: =BK24 -> 4752.9722 | AT21: =$AX$21/4 -> 1188.2445 | AU21: =$AX$21/4 -> 1188.2445 | AV21: =$AX$21/4 -> 1188.2445 | AW21: =$AX$21/4 -> 1188.2445 | AX21: =BK25 -> 4752.9779 | AY21: =BK26 -> 4752.9967 | BB21: =(AI19-AD19)/AD19 -> -0.019642857 | BC21: G OF PREV YEAR | BF21: =(AI20-AD20)/AD20 -> -0.0072001646 | BG21: G OF PREV YEAR | BJ21: =(AI21-AD21)/AD21 -> -0.033550224 | BK21: G OF PREV YEAR | BN21: =(AI22-AD22)/AD22 -> -0.10862114 | BO21: G OF PREV YEAR
A22: Home/Other | F22: 837 | G22: 972 | H22: 821 | I22: =J22-(H22+G22+F22) -> 1437 | J22: 4067 | K22: 650 | L22: 825 | M22: 833 | N22: =O22-(M22+L22+K22) -> 1437 | O22: 3745 | P22: 838 | Q22: 1033 | R22: 1024 | S22: =T22-(R22+Q22+P22) -> 1759 | T22: 4654 | U22: 890 | V22: 1014 | W22: 829 | X22: =Y22-(W22+V22+U22) -> 1466 | Y22: 4199 | Z22: 789 | AA22: 860 | AB22: 731 | AC22: =AD22-(AB22+AA22+Z22) -> 1413 | AD22: 3793 | AE22: 650 | AF22: 771 | AG22: 660 | AH22: =AI22-(AG22+AF22+AE22) -> 1300 | AI22: 3381 | AJ22: =$AN$22/4 -> 845.22574 | AK22: =$AN$22/4 -> 845.22574 | AL22: =$AN$22/4 -> 845.22574 | AM22: =$AN$22/4 -> 845.22574 | AN22: =BO23 -> 3380.9029 | AO22: =$AS$22/4 -> 1188.243 | AP22: =$AS$22/4 -> 1188.243 | AQ22: =$AS$22/4 -> 1188.243 | AR22: =$AS$22/4 -> 1188.243 | AS22: =BK24 -> 4752.9722 | AT22: =$AX$22/4 -> 1188.2445 | AU22: =$AX$22/4 -> 1188.2445 | AV22: =$AX$22/4 -> 1188.2445 | AW22: =$AX$22/4 -> 1188.2445 | AX22: =BK25 -> 4752.9779 | AY22: =BK26 -> 4752.9967 | BA22: Accesesories | BB22: 0.029 | BC22: =(BB22-BB21)/4 -> 0.012160714 | BE22: APPAREL Women | BF22: 0.0188 | BG22: =(BF22-BF21)/4 -> 0.0065000411 | BI22: APPAREL Men | BJ22: 0.0188 | BK22: =(BJ22-BJ21)/4 -> 0.013087556 | BM22: Home | BQ22: Other Revenue | BR22: q1 | BS22: q2 | BT22: q3 | BU22: q4
A23: Total Net Sales | F23: =SUM(F19:F22) -> 5504 | G23: =SUM(G19:G22) -> 5546 | H23: =SUM(H19:H22) -> 5173 | I23: =SUM(I19:I22) -> 8337 | J23: =SUM(J19:J22) -> 24560 | K23: =SUM(K19:K22) -> 3017 | L23: =SUM(L19:L22) -> 3559 | M23: =SUM(M19:M22) -> 3990 | ... O23: =SUM(O19:O22) -> 17346 | T23: =SUM(T19:T22) -> 23910 | U23: =SUM(U19:U22) -> 5348 | V23: =SUM(V19:V22) -> 5600 | W23: =SUM(W19:W22) -> 5230 | X23: =SUM(X19:X22) -> 8264 | Y23: =SUM(Y19:Y22) -> 24442 | Z23: =SUM(Z19:Z22) -> 4982 | AA23: =SUM(AA19:AA22) -> 5140 | ... AY23: =SUM(AY19:AY22) -> 23665.073 | BA23: 2025 | BB23: =BC22+BB21 -> -0.0074821429 | BC23: =AI19+BB23 -> 9332.9925 | BE23: 2025 | BF23: =BG22+BF21 -> -0.00070012343 | BG23: =BF23+AI20 -> 4825.9993 | BI23: 2025 | BJ23: =BK22+BJ21 -> -0.020462668 | BK23: =AI21+BJ23 -> 4752.9795 | BM23: 2025 | BN23: =BX19 -> -0.097058824 | BO23: =AI22+BN23 -> 3380.9029 | BQ23: 5 year CAGR quaterly | BR23: =(AE24/F24)^(1/5)-1 -> 0.11006703 | BS23: =(AF24/G24)^(1/5)-1 -> 0.10735729 | BT23: =(AG24/H24)^(1/5)-1 -> -0.065800402 | BU23: =(AH24/I24)^(1/5)-1 -> 0.10769007
A24: other revenue | F24: =F16-F23 -> 194 | G24: =G16-G23 -> 212 | H24: =H16-H23 -> 416 | I24: =I16-I23 -> 358 | J24: =J16-J23 -> 1179 | K24: =K16-K23 -> 2659 | L24: =L16-L23 -> 2163 | M24: =M16-M23 -> 1366 | ... AI24: =AI16-AI23 -> 1573 | AJ24: =$AN$24/4 -> 393.26484 | AK24: =$AN$24/4 -> 393.26484 | AL24: =$AN$24/4 -> 393.26484 | AM24: =$AN$24/4 -> 393.26484 | AN24: =AI24+$BR$24 -> 1573.0594 | AO24: =$AS$24/4 -> 393.27968 | AP24: =$AS$24/4 -> 393.27968 | AQ24: =$AS$24/4 -> 393.27968 | AR24: =$AS$24/4 -> 393.27968 | AS24: =AN24+$BR$24 -> 1573.1187 | AT24: =$AX$24/4 -> 393.29452 | AU24: =$AX$24/4 -> 393.29452 | AV24: =$AX$24/4 -> 393.29452 | AW24: =$AX$24/4 -> 393.29452 | AX24: =AS24+$BR$24 -> 1573.1781 | AY24: =AX24+$BR$24 -> 1573.2374 | BA24: 2026 | BB24: =BB23+BC22 -> 0.0046785714 | BC24: =BC23+BB24 -> 9332.9972 | BE24: 2026 | BF24: =$BG$22+BF23 -> 0.0057999177 | BG24: =BG23+BF24 -> 4826.0051 | BI24: 2026 | BJ24: =BJ23+$BK$22 -> -0.0073751118 | BK24: =BJ24+BK23 -> 4752.9722 | BM24: 2026 | BN24: =BY19 -> -0.13680782 | BO24: =BN24+BO23 -> 3380.7661 | BQ24: 5 year CAGR | BR24: =(AI24/J24)^(1/5)-1 -> 0.059358568
BA25: 2027 | BB25: =BB24+BC22 -> 0.016839286 | BC25: =BC24+BB25 -> 9333.014 | BE25: 2027 | BF25: =$BG$22+BF24 -> 0.012299959 | BG25: =BG24+BF25 -> 4826.0174 | BI25: 2027 | BJ25: =BJ24+$BK$22 -> 0.0057124441 | BK25: =BJ25+BK24 -> 4752.9779 | BM25: 2027 | BN25: =BZ19 -> -0.030188679 | BO25: =BN25+BO24 -> 3380.7359
A26: Working Capital Schedule | BA26: 2028 | BB26: =BC22+BB25 -> 0.029 | BC26: =BC25+BB26 -> 9333.043 | BE26: 2028 | BF26: =$BG$22+BF25 -> 0.0188 | BG26: =BG25+BF26 -> 4826.0362 | BI26: 2028 | BJ26: =BJ25+$BK$22 -> 0.0188 | BK26: =BJ26+BK25 -> 4752.9967 | BM26: 2028 | BN26: =CA19 -> 0.0038910506 | BO26: =BN26+BO25 -> 3380.7398
A28: Inputs
A29: Days in Year | C29: =365 -> 365
A30: Total Revenue | F30: =F16 -> 5698 | G30: =G16 -> 5758 | H30: =H16 -> 5589 | I30: =I16 -> 8695 | J30: =J16 -> 25739 | K30: =K16 -> 5676 | L30: =L16 -> 5722 | M30: =M16 -> 5356 | ... AI30: =AI16 -> 23866
A31: Total COGS | F31: =F5 -> 3382 | G31: =G5 -> 3320 | H31: =H5 -> 3226 | I31: =I5 -> 5288 | J31: =J5 -> 15216 | K31: =K5 -> 3403 | L31: =L5 -> 3395 | M31: =M5 -> 3106 | ... AH31: =AH5 -> 5154 | AI31: s
A33: Current Assets
A34: Accounts Recievables | F34: =BS!C21 -> 250 | G34: =BS!D21 -> 261 | H34: =BS!E21 -> 180 | I34: =BS!F21 -> 400 | J34: =BS!G21 -> 400 | K34: =BS!H21 -> 237 | L34: =BS!I21 -> 240 | M34: =BS!J21 -> 175 | ... AI34: =BS!AF21 -> 293
A35: Days recievable | F35: =(F34/F30)*90 -> 3.9487539 | G35: =(G34/G30)*90 -> 4.0795415 | H35: =(H34/H30)*90 -> 2.8985507 | I35: =(I34/I30)*90 -> 4.1403105 | J35: =(J34/J30)*360 -> 5.5946229 | K35: =(K34/K30)*90 -> 3.7579281 | L35: =(L34/L30)*90 -> 3.7749039 | M35: =(M34/M30)*90 -> 2.9406273 | N35: =(N34/N30)*90 -> 4.2917104 | O35: =(O34/O30)*360 -> 5.8126406 | P35: =(P34/P30)*90 -> 4.8602287 | Q35: =(Q34/Q30)*90 -> 4.4432519 | R35: =(R34/R30)*90 -> 3.9784946 | S35: =(S34/S30)*90 -> 3.5299133 | T35: =(T34/T30)*360 -> 5.4904128 | U35: =(U34/U30)*90 -> 3.7923947 | V35: =(V34/V30)*90 -> 3.4034908 | W35: =(W34/W30)*90 -> 3.375199 | X35: =(X34/X30)*90 -> 2.9932811 | Y35: =(Y34/Y30)*360 -> 4.2096146 | Z35: =(Z34/Z30)*90 -> 3.7681941 | AA35: =(AA34/AA30)*90 -> 3.378471 | AB35: =(AB34/AB30)*90 -> 3.3583318 | AC35: =(AC34/AC30)*90 -> 3.1457532 | AD35: =(AD34/AD30)*360 -> 4.2437817 | AE35: =(AE34/AE30)*90 -> 4.4364972 | AF35: =(AF34/AF30)*90 -> 3.8011364 | AG35: =(AG34/AG30)*90 -> 3.8944025 | AH35: =(AH34/AH30)*90 -> 3.1486567 | AI35: =(AI34/AI30)*360 -> 4.4196765
A36: Inventories | F36: =BS!C25 -> 5291 | G36: =BS!D25 -> 4956 | H36: =BS!E25 -> 7147 | I36: =BS!F25 -> 5263 | J36: =BS!G25 -> 5263 | K36: =BS!H25 -> 5498 | L36: =BS!I25 -> 5029 | M36: =BS!J25 -> 7256 | ... AI36: =BS!AF25 -> 4361
A37: Inventory turnover days | G37: =G31/((F36+G36)/2)*90 -> 58.319508 | H37: =H31/((G36+H36)/2)*90 -> 47.978187 | I37: =I31/((H36+I36)/2)*90 -> 76.699436 | J37: =J31/((I36+J36)/2)*90 -> 260.20141 | K37: =K31/((J36+K36)/2)*90 -> 56.922219 | L37: =L31/((K36+L36)/2)*90 -> 58.050727 | M37: =M31/((L36+M36)/2)*90 -> 45.509158 | N37: =N31/((M36+N36)/2)*90 -> 76.171649 | ... AH37: =AH31/((AG36+AH36)/2)*90 -> 89.32409 | AI37: =AI31/((AD36+AI36)/2)*360 -> #VALUE!
A38: Prepaid expenses and other | F38: =BS!C26+BS!C28 -> 638 | G38: =BS!D26+BS!D28 -> 580 | H38: =BS!E26+BS!E28 -> 594 | I38: =BS!F26+BS!F28 -> 583 | J38: =BS!G26+BS!G28 -> 583 | K38: =BS!H26+BS!H28 -> 633 | L38: =BS!I26+BS!I28 -> 603 | M38: =BS!J26+BS!J28 -> 568 | ... AI38: =BS!AF26+BS!AF28 -> 401
A39: Days prepaid | F39: =(F38/F31)*90 -> 16.978119 | G39: =(G38/G31)*90 -> 15.722892 | H39: =(H38/H31)*90 -> 16.571606 | I39: =(I38/I31)*90 -> 9.922466 | J39: =(J38/J31)*90 -> 3.4483438 | K39: =(K38/K31)*90 -> 16.741111 | L39: =(L38/L31)*90 -> 15.985272 | M39: =(M38/M31)*90 -> 16.458467 | N39: =(N38/N31)*90 -> 8.3915686 | O39: =(O38/O31)*360 -> 11.651945 | P39: =(P38/P31)*90 -> 21.222172 | Q39: =(Q38/Q31)*90 -> 15.562914 | R39: =(R38/R31)*90 -> 16.710782 | S39: =(S38/S31)*90 -> 8.5348062 | T39: =(T38/T31)*360 -> 13.332248 | U39: =(U38/U31)*90 -> 15.17134 | V39: =(V38/V31)*90 -> 11.676111 | W39: =(W38/W31)*90 -> 9.3171188 | X39: =(X38/X31)*90 -> 5.9814781 | Y39: =(Y38/Y31)*360 -> 8.8098422 | Z39: =(Z38/Z31)*90 -> 10.362117 | AA39: =(AA38/AA31)*90 -> 10.178258 | AB39: =(AB38/AB31)*90 -> 11.657303 | AC39: =(AC38/AC31)*90 -> 7.0018349 | AD39: =(AD38/AD31)*360 -> 9.9719083 | AE39: =(AE38/AE31)*90 -> 11.746988 | AF39: =(AF38/AF31)*90 -> 11.646725 | AG39: =(AG38/AG31)*90 -> 12.082616 | AH39: =(AH38/AH31)*90 -> 7.0023283 | AI39: =(AI38/AI31)*360 -> #VALUE!
A41: Total Current assets | F41: =F34+F36+F38 -> 6179 | G41: =G34+G36+G38 -> 5797 | H41: =H34+H36+H38 -> 7921 | I41: =I34+I36+I38 -> 6246 | J41: =J34+J36+J38 -> 6246 | K41: =K34+K36+K38 -> 6368 | L41: =L34+L36+L38 -> 5872 | M41: =M34+M36+M38 -> 7999 | ... AI41: =AI34+AI36+AI38 -> 5055
A43: Current Liabilities
A44: Accounts Payable | F44: =BS!C42 -> 3715 | G44: =BS!D42 -> 3498 | H44: =BS!E42 -> 5403 | I44: =BS!F42 -> 2638 | J44: =BS!G42 -> 2638 | K44: =BS!H42 -> 3443 | L44: =BS!I42 -> 3181 | M44: =BS!J42 -> 5209 | ... AI44: =BS!AF42 -> 2660
A45: Days Payable | F45: =(F44/F31)*360 -> 395.44648 | G45: =(G44/G31)*90 -> 94.825301 | H45: =(H44/H31)*90 -> 150.73466 | I45: =(I44/I31)*90 -> 44.897882 | J45: =(J44/J31)*360 -> 62.413249 | K45: =(K44/K31)*90 -> 91.05789 | L45: =(L44/L31)*90 -> 84.326951 | M45: =(M44/M31)*90 -> 150.9369 | N45: =(N44/N31)*90 -> 45.44436 | O45: =(O44/O31)*360 -> 63.100857 | P45: =(P44/P31)*90 -> 162.29441 | Q45: =(Q44/Q31)*90 -> 115.36424 | R45: =(R44/R31)*90 -> 185.29 | S45: =(S44/S31)*90 -> 53.572322 | T45: =(T44/T31)*360 -> 83.685496 | U45: =(U44/U31)*90 -> 135.60748 | V45: =(V44/V31)*90 -> 117.86162 | W45: =(W44/W31)*90 -> 162.40412 | X45: =(X44/X31)*90 -> 53.604503 | Y45: =(Y44/Y31)*360 -> 78.951591 | Z45: =(Z44/Z31)*90 -> 129.47075 | AA45: =(AA44/AA31)*90 -> 108.17358 | AB45: =(AB44/AB31)*90 -> 167.16292 | AC45: =(AC44/AC31)*90 -> 47.46055 | AD45: =(AD44/AD31)*360 -> 67.592605 | AE45: =(AE44/AE31)*90 -> 122.71084 | AF45: =(AF44/AF31)*90 -> 104.73552 | AG45: =(AG44/AG31)*90 -> 165.06713 | AH45: =(AH44/AH31)*90 -> 46.44936 | AI45: =(AI44/AI31)*360 -> #VALUE!
A46: Accrued Expense | F46: 0 | G46: 0 | H46: 0 | I46: =BS!F43 -> 939 | J46: =BS!G43 -> 939 | K46: 0 | L46: 0 | M46: 0 | N46: =BS!K43 -> 731 | O46: =BS!L43 -> 731 | P46: 0 | Q46: 0 | R46: 0 | S46: =BS!P43 -> 844 | T46: =BS!Q43 -> 844 | U46: 0 | V46: 0 | W46: 0 | X46: =BS!U43 -> 818 | Y46: =BS!V43 -> 818 | Z46: 0 | AA46: 0 | AB46: 0 | AC46: =BS!Z43 -> 719 | AD46: =BS!AA43 -> 719 | AE46: 0 | AF46: 0 | AG46: 0 | AH46: =BS!AE43 -> 680 | AI46: =BS!AF43 -> 680
A47: Days Accrued | F47: =(F46/F10)*90 -> 0 | G47: =(G46/G10)*90 -> 0 | H47: =(H46/H10)*90 -> 0 | I47: =(I46/I10)*90 -> 33.403162 | J47: =(J46/J10)*360 -> 37.555827 | K47: =(K46/K10)*90 -> 0 | L47: =(L46/L10)*90 -> 0 | M47: =(M46/M10)*90 -> 0 | N47: =(N46/N10)*90 -> 26.305478 | O47: =(O46/O10)*360 -> 29.341064 | P47: =(P46/P10)*90 -> 0 | Q47: =(Q46/Q10)*90 -> 0 | R47: =(R46/R10)*90 -> 0 | S47: =(S46/S10)*90 -> 37.4741 | T47: =(T46/T10)*360 -> 45.261433 | U47: =(U46/U10)*90 -> 0 | V47: =(V46/V10)*90 -> 0 | W47: =(W46/W10)*90 -> 0 | X47: =(X46/X10)*90 -> 30.522388 | Y47: =(Y46/Y10)*360 -> 36.893009 | Z47: =(Z46/Z10)*90 -> 0 | AA47: =(AA46/AA10)*90 -> 0 | AB47: =(AB46/AB10)*90 -> 0 | AC47: =(AC46/AC10)*90 -> 26.336996 | AD47: =(AD46/AD10)*360 -> 30.668246 | AE47: =(AE46/AE10)*90 -> 0 | AF47: =(AF46/AF10)*90 -> 0 | AG47: =(AG46/AG10)*90 -> 0 | AH47: =(AH46/AH10)*90 -> 25.457571 | AI47: =(AI46/AI10)*360 -> 29.268293
A48: Unearned Revenue ( Current) | F48: =BS!C48 -> 727 | G48: =BS!D48 -> 662 | H48: =BS!E48 -> 711 | I48: =BS!F48 -> 879 | J48: =BS!G48 -> 879 | K48: =BS!H48 -> 696 | L48: =BS!I48 -> 654 | M48: =BS!J48 -> 705 | ... AI48: =BS!AF48 -> 384
A49: Days Unearned Revenue | F49: =(F48/F16)*365 -> 46.569849 | G49: =(G48/G16)*90 -> 10.347343 | H49: =(H48/H16)*90 -> 11.449275 | I49: =(I48/I16)*90 -> 9.0983324 | J49: =(J48/J16)*365 -> 12.464936 | K49: =(K48/K16)*90 -> 11.035941 | L49: =(L48/L16)*90 -> 10.286613 | M49: =(M48/M16)*90 -> 11.846527 | N49: =(N48/N16)*90 -> 8.8037775 | O49: =(O48/O16)*365 -> 12.089337 | P49: =(P48/P16)*90 -> 20.927573 | Q49: =(Q48/Q16)*90 -> 16.299973 | R49: =(R48/R16)*90 -> 13.741935 | S49: =(S48/S16)*90 -> 7.8783573 | T49: =(T48/T16)*365 -> 12.424159 | U49: =(U48/U16)*90 -> 10.729702 | V49: =(V48/V16)*90 -> 8.4240246 | W49: =(W48/W16)*90 -> 7.960375 | X49: =(X48/X16)*90 -> 4.8477044 | Y49: =(Y48/Y16)*365 -> 6.91228 | Z49: =(Z48/Z16)*90 -> 6.9218329 | AA49: =(AA48/AA16)*90 -> 5.954748 | AB49: =(AB48/AB16)*90 -> 5.8441558 | AC49: =(AC48/AC16)*90 -> 4.1838518 | AD49: =(AD48/AD16)*365 -> 5.7226217 | AE49: =(AE48/AE16)*90 -> 6.2632902 | AF49: =(AF48/AF16)*90 -> 5.7954545 | AG49: =(AG48/AG16)*90 -> 6.0023819 | AH49: =(AH48/AH16)*90 -> 4.1265672 | AI49: =(AI48/AI16)*365 -> 5.8727897
A50: Total Current Liabilities | F50: =F44+F46+F48 -> 4442 | G50: =G44+G46+G48 -> 4160 | H50: =H44+H46+H48 -> 6114 | I50: =I44+I46+I48 -> 4456 | J50: =J44+J46+J48 -> 4456 | K50: =K44+K46+K48 -> 4139 | L50: =L44+L46+L48 -> 3835 | M50: =M44+M46+M48 -> 5914 | ... AI50: =AI44+AI46+AI48 -> 3724
A53: Change in NOWC | E53: USD'm | F53: =F41-F50 -> 1737 | G53: =G41-G50 -> 1637 | H53: =H41-H50 -> 1807 | I53: =I41-I50 -> 1790 | J53: =J41-J50 -> 1790 | K53: =K41-K50 -> 2229 | L53: =L41-L50 -> 2037 | M53: =M41-M50 -> 2085 | ... AI53: =AI41-AI50 -> 1331
A56: Depreciation & Amortisation Schedule
A59: CAPEX
A60: Assumptions:
A61: Useful life of all assets
A62: % change in terminal year CAPEX
A63: PPE at end of 23A
A65: CAPEX
A66: % change in CAPEX
A68: PPE
A70: Beginning PPE
A71: Additions: CAPEX
A72: Additions / (subtractions) in other CAPEX
... A86: Closing PPE
BA88: Scenario | BB88: 1, 2 or 3

Sheet BS
A5: Macy's, Inc. (NYSE:M) > Financials > Balance Sheet
A7: In Millions of USD, except per share items. | C7: Template: | D7: Standard | E7: Restatement: | F7: Latest Filings | G7: Template: | L7: Standard | V7: Restatement: | AA7: Latest Filings
C8: Period Type: | D8: Annual | E8: Order: | F8: Latest on Right | G8: Period Type: | L8: Annual | V8: Order: | AA8: Latest on Right
C9: Currency: | D9: US Dollar | E9: Conversion: | F9: Historical | G9: Currency: | L9: US Dollar | V9: Conversion: | AA9: Historical
C10: Units: | D10: Millions (mm) | E10: Decimals: | F10: Capital IQ (Default) | G10: Units: | L10: Millions (mm) | V10: Decimals: | AA10: Capital IQ (Default)
C11: Source: | D11: Capital IQ & Proprietary Data | G11: Source: | L11: Capital IQ & Proprietary Data
A14: Balance Sheet | G14: 2019 | L14: 2020 | Q14: 2021 | V14: 2022 | AA14: 2023 | AF14: 2024
A15: For the Fiscal Period Ending | C15: 1Q 2019 | D15: 2Q 2019 | E15: 3Q 2019 | F15: 4Q 2019 | G15: 2019A | H15: 1Q 2020 | I15: 2Q 2020 | J15: 3Q 2020 | K15: 4Q 2020 | L15: 2020A | M15: 1Q 2021 | N15: 2Q 2021 | O15: 3Q 2021 | P15: 4Q 2021 | Q15: 2021A | R15: 1Q 2022 | S15: 2Q 2022 | T15: 3Q 2022 | U15: 4Q 2022 | V15: 2022A | W15: 1Q 2023 | X15: 2Q 2023 | Y15: 3Q 2023 | Z15: 4Q 2023 | AA15: 2023A | AB15: 1Q 2024 | AC15: 2Q 2024 | AD15: 3Q 2024 | AE15: 4Q2024 | AF15: 2024A
A16: Currency: USD
A17: ASSETS
A18: Cash And Equivalents | C18: 1531 | D18: 1068 | E18: 736 | F18: 1162 | G18: =F18 -> 1162 | H18: 737 | I18: 674 | J18: 301 | K18: 685 | L18: =K18 -> 685 | M18: 1523 | N18: 1395 | O18: 1551 | P18: 1679 | Q18: =P18 -> 1679 | R18: 1798 | S18: 2137 | T18: 316 | U18: 1712 | V18: =U18 -> 1712 | W18: 672 | X18: 300 | Y18: 326 | Z18: 862 | AA18: =Z18 -> 862 | AB18: 603 | AC18: 438 | AD18: 364 | AE18: 1034 | AF18: =AE18 -> 1034
A19: Total Cash & ST Investments | C19: 1531 | D19: 1068 | E19: 736 | F19: 1162 | G19: =F19 -> 1162 | H19: 737 | I19: 674 | J19: 301 | K19: 685 | L19: =K19 -> 685 | M19: 1523 | N19: 1395 | O19: 1551 | P19: 1679 | Q19: =P19 -> 1679 | R19: 1798 | S19: 2137 | T19: 316 | U19: 1712 | V19: =U19 -> 1712 | W19: 672 | X19: 300 | Y19: 326 | Z19: 862 | AA19: =Z19 -> 862 | AB19: =AB18 -> 603 | AC19: =AC18 -> 438 | AD19: =AD18 -> 364 | AE19: =AE18 -> 1034 | AF19: =AE19 -> 1034
A21: Accounts Receivable | C21: 250 | D21: 261 | E21: 180 | F21: 400 | G21: 400 | H21: 237 | I21: 240 | J21: 175 | K21: 409 | L21: 409 | M21: 170 | N21: 184 | O21: 185 | P21: 276 | Q21: 276 | R21: 205 | S21: 221 | T21: 212 | U21: 297 | V21: 297 | W21: 233 | X21: 219 | Y21: 204 | Z21: 300 | AA21: 300 | AB21: 255 | AC21: 223 | AD21: 218 | AE21: 293 | AF21: 293
A22: Other Receivables | C22: 0 | D22: 0 | E22: 10 | F22: - | G22: - | H22: 0 | I22: 0 | J22: 1 | K22: - | L22: - | M22: 0 | N22: 0 | O22: 0 | P22: 0 | Q22: - | R22: 520 | S22: 520 | T22: 590 | U22: 0 | V22: - | W22: - | X22: - | Y22: - | Z22: - | AA22: - | AB22: - | AC22: 70 | AD22: 73 | AE22: - | AF22: -
A23: Total Receivables | C23: =SUM(C21:C22) -> 250 | D23: =SUM(D21:D22) -> 261 | E23: =SUM(E21:E22) -> 190 | F23: =SUM(F21:F22) -> 400 | G23: 400 | H23: =SUM(H21:H22) -> 237 | I23: =SUM(I21:I22) -> 240 | J23: =SUM(J21:J22) -> 176 | K23: =SUM(K21:K22) -> 409 | L23: 409 | M23: =SUM(M21:M22) -> 170 | N23: =SUM(N21:N22) -> 184 | O23: =SUM(O21:O22) -> 185 | P23: =SUM(P21:P22) -> 276 | Q23: 276 | R23: =SUM(R21:R22) -> 725 | S23: =SUM(S21:S22) -> 741 | T23: =SUM(T21:T22) -> 802 | U23: =SUM(U21:U22) -> 297 | V23: 297 | W23: =SUM(W21:W22) -> 233 | X23: =SUM(X21:X22) -> 219 | Y23: =SUM(Y21:Y22) -> 204 | Z23: =SUM(Z21:Z22) -> 300 | AA23: 300 | AB23: =SUM(AB21:AB22) -> 255 | AC23: =SUM(AC21:AC22) -> 293 | AD23: =SUM(AD21:AD22) -> 291 | AE23: =SUM(AE21:AE22) -> 293 | AF23: 293
A25: Inventory | C25: 5291 | D25: 4956 | E25: 7147 | F25: 5263 | G25: 5263 | H25: 5498 | I25: 5029 | J25: 7256 | K25: 5188 | L25: 5188 | M25: 4923 | N25: 3582 | O25: 5144 | P25: 3774 | Q25: 3774 | R25: 4230 | S25: 4298 | T25: 6141 | U25: 4383 | V25: 4383 | W25: 4956 | X25: 4610 | Y25: 6403 | Z25: 4267 | AA25: 4267 | AB25: 4607 | AC25: 4129 | AD25: 6025 | AE25: 4361 | AF25: 4361
A26: Prepaid Exp. | C26: 434 | D26: 415 | E26: 414 | F26: 368 | G26: 368 | H26: 433 | I26: 449 | J26: 404 | K26: 310 | L26: 310 | M26: 389 | N26: 356 | O26: 361 | P26: 316 | Q26: 316 | R26: 351 | S26: 320 | T26: 190 | U26: 207 | V26: 207 | W26: 228 | X26: 275 | Y26: 273 | Z26: 237 | AA26: 237 | AB26: 263 | AC26: 317 | AD26: 276 | AE26: 276 | AF26: 276
A27: Restricted Cash | C27: - | D27: - | E27: - | F27: 37 | G27: 37 | H27: - | I27: - | J27: - | K27: 37 | L27: 37 | M27: - | N27: - | O27: - | P27: - | Q27: - | R27: - | S27: - | T27: - | U27: - | V27: - | W27: - | X27: - | Y27: - | Z27: - | AA27: - | AB27: - | AC27: - | AD27: - | AE27: - | AF27: -
A28: Other Current Assets | C28: 204 | D28: 165 | E28: 180 | F28: 215 | G28: 215 | H28: 200 | I28: 154 | J28: 164 | K28: 181 | L28: 181 | M28: 130 | N28: 114 | O28: 116 | P28: 139 | Q28: 139 | R28: 136 | S28: 115 | T28: 142 | U28: 159 | V28: 159 | W28: 144 | X28: 112 | Y28: 142 | Z28: 187 | AA28: 187 | AB28: 127 | AC28: 94 | AD28: 114 | AE28: 125 | AF28: 125
A29: Total Current Assets | C29: =SUM(C25:C28)+C23+C19 -> 7710 | D29: =SUM(D25:D28)+D23+D19 -> 6865 | E29: =SUM(E25:E28)+E23+E19 -> 8667 | F29: =SUM(F25:F28)+F23+F19 -> 7445 | G29: 7445 | H29: =SUM(H25:H28)+H23+H19 -> 7105 | I29: =SUM(I25:I28)+I23+I19 -> 6546 | J29: =SUM(J25:J28)+J23+J19 -> 8301 | K29: =SUM(K25:K28)+K23+K19 -> 6810 | L29: 6810 | M29: =SUM(M25:M28)+M23+M19 -> 7135 | N29: =SUM(N25:N28)+N23+N19 -> 5631 | O29: =SUM(O25:O28)+O23+O19 -> 7357 | P29: =SUM(P25:P28)+P23+P19 -> 6184 | Q29: =SUM(Q25:Q28)+Q23+Q19 -> 6184 | R29: =SUM(R25:R28)+R23+R19 -> 7240 | S29: =SUM(S25:S28)+S23+S19 -> 7611 | T29: =SUM(T25:T28)+T23+T19 -> 7591 | ... AF29: =SUM(AF25:AF28)+AF23+AF19 -> 6089
A31: Gross Property, Plant & Equipment | C31: 11340 | D31: 11461 | E31: 11656 | F31: 11132 | G31: 11132 | H31: 13763 | I31: 13879 | J31: 14092 | K31: 13705 | L31: 13705 | M31: 13657 | N31: 13956 | O31: 13966 | P31: 13231 | Q31: 13231 | R31: 13201 | S31: 13221 | T31: 13234 | U31: 13034 | V31: 13034 | W31: 13008 | X31: 13191 | Y31: 13487 | Z31: 13242 | AA31: 13242 | AB31: 13342 | AC31: 13473 | AD31: 13663 | AE31: 11902 | AF31: 11902
A32: Accumulated Depreciation | C32: -4765 | D32: -4914 | E32: -5084 | F32: -4495 | G32: -4495 | H32: -4633 | I32: -4760 | J32: -4938 | K32: -4404 | L32: -4404 | M32: -4560 | N32: -4642 | O32: -4816 | P32: -4413 | Q32: -4413 | R32: -4550 | S32: -4689 | T32: -4826 | U32: -4561 | V32: -4561 | W32: -4671 | X32: -4820 | Y32: -4957 | Z32: -4646 | AA32: -4646 | AB32: -4763 | AC32: -4905 | AD32: -5066 | AE32: -4289 | AF32: -4289
A33: Net Property, Plant & Equipment | C33: =SUM(C31:C32) -> 6575 | D33: =SUM(D31:D32) -> 6547 | E33: =SUM(E31:E32) -> 6572 | F33: =SUM(F31:F32) -> 6637 | G33: 6637 | H33: =SUM(H31:H32) -> 9130 | I33: =SUM(I31:I32) -> 9119 | J33: =SUM(J31:J32) -> 9154 | K33: =SUM(K31:K32) -> 9301 | L33: =SUM(L31:L32) -> 9301 | M33: =SUM(M31:M32) -> 9097 | N33: =SUM(N31:N32) -> 9314 | O33: =SUM(O31:O32) -> 9150 | ... AF33: =SUM(AF31:AF32) -> 7613
A35: Goodwill | C35: 3908 | D35: 3908 | E35: 3908 | F35: 3908 | G35: 3908 | H35: 3908 | I35: 3908 | J35: 3908 | K35: 3908 | L35: 3908 | M35: 838 | N35: 828 | O35: 828 | P35: 828 | Q35: 828 | R35: 828 | S35: 828 | T35: 828 | U35: 828 | V35: 828 | W35: 828 | X35: 828 | Y35: 828 | Z35: 828 | AA35: 828 | AB35: 828 | AC35: 828 | AD35: 828 | AE35: 828 | AF35: 828
A36: Other Intangibles | C36: 486 | D36: 483 | E36: 481 | F36: 1148 | G36: 1148 | H36: 441 | I36: 440 | J36: 440 | K36: 1081 | L36: 1081 | M36: 439 | N36: 438 | O36: 437 | P36: 928 | Q36: 928 | R36: 436 | S36: 436 | T36: 435 | U36: 946 | V36: 946 | W36: 434 | X36: 433 | Y36: 433 | Z36: 1098 | AA36: 1098 | AB36: 432 | AC36: 431 | AD36: 431 | AE36: 1187 | AF36: 1187
A37: Other Long-Term Assets | C37: 889 | D37: 865 | E37: 733 | F37: 56 | G37: 56 | H37: 712 | I37: 728 | J37: 744 | K37: 72 | L37: 72 | M37: 1072 | N37: 1403 | O37: 1442 | P37: 948 | Q37: 948 | R37: 927 | S37: 1010 | T37: 1017 | U37: 585 | V37: 585 | W37: 1140 | X37: 1194 | Y37: 1091 | Z37: 491 | AA37: 491 | AB37: 1174 | AC37: 1206 | AD37: 1185 | AE37: 529 | AF37: 529
A38: Total Non-Current Assets | C38: =C33+SUM(C35:C37) -> 11858 | D38: =D33+SUM(D35:D37) -> 11803 | E38: =E33+SUM(E35:E37) -> 11694 | F38: =F33+SUM(F35:F37) -> 11749 | G38: =G33+SUM(G35:G37) -> 11749 | H38: =H33+SUM(H35:H37) -> 14191 | I38: =I33+SUM(I35:I37) -> 14195 | J38: =J33+SUM(J35:J37) -> 14246 | ... AF38: =AF33+SUM(AF35:AF37) -> 10157
A39: Total Assets | C39: =C29+C38 -> 19568 | D39: =D29+D38 -> 18668 | E39: =E29+E38 -> 20361 | F39: =F29+F38 -> 19194 | G39: =G29+G38 -> 19194 | H39: =H29+H38 -> 21296 | I39: =I29+I38 -> 20741 | J39: =J29+J38 -> 22547 | ... AF39: =AF29+AF38 -> 16246
A41: LIABILITIES
A42: Accounts Payable | C42: 3715 | D42: 3498 | E42: 5403 | F42: 2638 | G42: =F42 -> 2638 | H42: 3443 | I42: 3181 | J42: 5209 | K42: 2659 | L42: =K42 -> 2659 | M42: 3969 | N42: 3484 | O42: 5289 | P42: 2856 | Q42: =P42 -> 2856 | R42: 4353 | S42: 4391 | T42: 5787 | U42: 3280 | V42: =U42 -> 3280 | W42: 4648 | X42: 4113 | Y42: 5951 | Z42: 2874 | AA42: =Z42 -> 2874 | AB42: 4074 | AC42: 3696 | AD42: 5328 | AE42: 2660 | AF42: =AE42 -> 2660
A43: Accrued Exp. | C43: - | D43: - | E43: - | F43: 939 | G43: =F43 -> 939 | H43: - | I43: - | J43: - | K43: 731 | L43: =K43 -> 731 | M43: - | N43: - | O43: - | P43: 844 | Q43: =P43 -> 844 | R43: - | S43: - | T43: - | U43: 818 | V43: =U43 -> 818 | W43: - | X43: - | Y43: - | Z43: 719 | AA43: =Z43 -> 719 | AB43: - | AC43: - | AD43: - | AE43: 680 | AF43: =AE43 -> 680
A44: Short-term Borrowings | C44: - | D44: - | E44: - | F44: - | G44: =F44 -> - | H44: - | I44: - | J44: - | K44: - | L44: =K44 -> - | M44: - | N44: - | O44: - | P44: - | Q44: =P44 -> - | R44: - | S44: - | T44: - | U44: - | V44: =U44 -> - | W44: - | X44: - | Y44: - | Z44: - | AA44: =Z44 -> - | AB44: - | AC44: - | AD44: - | AE44: - | AF44: =AE44 -> -
A45: Curr. Port. of LT Debt | C45: 25 | D45: 63 | E45: 65 | F45: 36 | G45: =F45 -> 36 | H45: 41 | I45: 6 | J45: 6 | K45: 539 | L45: =K45 -> 539 | M45: 739 | N45: 539 | O45: 536 | P45: 452 | Q45: =P45 -> 452 | R45: 294 | S45: 1546 | T45: 140 | U45: - | V45: =U45 -> - | W45: - | X45: - | Y45: 183 | Z45: - | AA45: =Z45 -> - | AB45: - | AC45: - | AD45: 160 | AE45: - | AF45: =AE45 -> -
A46: Curr. Port. of Leases | C46: - | D46: - | E46: - | F46: 7 | G46: =F46 -> 7 | H46: 363 | I46: 351 | J46: 314 | K46: 333 | L46: =K46 -> 333 | M46: - | N46: - | O46: - | P46: 200 | Q46: =P46 -> 200 | R46: - | S46: - | T46: - | U46: 330 | V46: =U46 -> 330 | W46: - | X46: - | Y46: - | Z46: 335 | AA46: =Z46 -> 335 | AB46: - | AC46: - | AD46: - | AE46: 358 | AF46: =AE46 -> 358
A47: Curr. Income Taxes Payable | C47: 312 | D47: 15 | E47: - | F47: 168 | G47: =F47 -> 168 | H47: 182 | I47: 20 | J47: - | K47: 81 | L47: =K47 -> 81 | M47: 80 | N47: - | O47: - | P47: - | Q47: =P47 -> - | R47: 63 | S47: 18 | T47: - | U47: 108 | V47: =U47 -> 108 | W47: 222 | X47: 23 | Y47: 21 | Z47: 58 | AA47: =Z47 -> 58 | AB47: 134 | AC47: - | AD47: - | AE47: 48 | AF47: =AE47 -> 48
A48: Unearned Revenue, Current | C48: 727 | D48: 662 | E48: 711 | F48: 879 | G48: =F48 -> 879 | H48: 696 | I48: 654 | J48: 705 | K48: 839 | L48: =K48 -> 839 | M48: 732 | N48: 675 | O48: 639 | P48: 616 | Q48: =P48 -> 616 | R48: 580 | S48: 547 | T48: 500 | U48: 481 | V48: =U48 -> 481 | W48: 428 | X48: 386 | Y48: 355 | Z48: 399 | AA48: =Z48 -> 399 | AB48: 360 | AC48: 340 | AD48: 336 | AE48: 384 | AF48: =AE48 -> 384
A49: Other Current Liabilities | C49: 298 | D49: 243 | E49: 265 | F49: 565 | G49: =F49 -> 565 | H49: 294 | I49: 227 | J49: 245 | K49: 568 | L49: =K49 -> 568 | M49: 252 | N49: 156 | O49: 187 | P49: 389 | Q49: =P49 -> 389 | R49: 228 | S49: 198 | T49: 244 | U49: 399 | V49: =U49 -> 399 | W49: 245 | X49: 186 | Y49: 233 | Z49: 476 | AA49: =Z49 -> 476 | AB49: 214 | AC49: 148 | AD49: 190 | AE49: 402 | AF49: =AE49 -> 402
A50: Total Current Liabilities | C50: =SUM(C42:C49) -> 5077 | D50: =SUM(D42:D49) -> 4481 | E50: =SUM(E42:E49) -> 6444 | F50: =SUM(F42:F49) -> 5232 | G50: =F50 -> 5232 | H50: =SUM(H42:H49) -> 5019 | I50: =SUM(I42:I49) -> 4439 | J50: =SUM(J42:J49) -> 6479 | K50: =SUM(K42:K49) -> 5750 | L50: =K50 -> 5750 | M50: =SUM(M42:M49) -> 5772 | N50: =SUM(N42:N49) -> 4854 | O50: =SUM(O42:O49) -> 6651 | P50: =SUM(P42:P49) -> 5357 | Q50: =P50 -> 5357 | R50: =SUM(R42:R49) -> 5518 | S50: =SUM(S42:S49) -> 6700 | T50: =SUM(T42:T49) -> 6671 | U50: =SUM(U42:U49) -> 5416 | V50: =U50 -> 5416 | W50: =SUM(W42:W49) -> 5543 | X50: =SUM(X42:X49) -> 4708 | Y50: =SUM(Y42:Y49) -> 6743 | Z50: =SUM(Z42:Z49) -> 4861 | AA50: =Z50 -> 4861 | AB50: =SUM(AB42:AB49) -> 4782 | AC50: =SUM(AC42:AC49) -> 4184 | AD50: =SUM(AD42:AD49) -> 6014 | AE50: =SUM(AE42:AE49) -> 4532 | AF50: =AE50 -> 4532
A52: Long-Term Debt | C52: 5857 | D52: 5473 | E52: 5469 | F52: 4683 | G52: =F52 -> 4683 | H52: 4680 | I52: 4680 | J52: 4677 | K52: 3621 | L52: =K52 -> 3621 | M52: 4918 | N52: 4851 | O52: 4852 | P52: 4407 | Q52: =P52 -> 4407 | R52: 4558 | S52: 3295 | T52: 3295 | U52: 3295 | V52: =U52 -> 3295 | W52: 2994 | X52: 2995 | Y52: 2996 | Z52: 2996 | AA52: =Z52 -> 2996 | AB52: 2996 | AC52: 2997 | AD52: 2997 | AE52: 2998 | AF52: =AE52 -> 2998
A53: Long-Term Leases | C53: - | D53: - | E53: - | F53: 25 | G53: =F53 -> 25 | H53: 2823 | I53: 2836 | J53: 2819 | K53: 2918 | L53: =K53 -> 2918 | M53: 2923 | N53: 3269 | O53: 3266 | P53: 3185 | Q53: =P53 -> 3185 | R53: 3166 | S53: 3096 | T53: 3090 | U53: 3098 | V53: =U53 -> 3098 | W53: 3030 | X53: 3008 | Y53: 2988 | Z53: 2963 | AA53: =Z53 -> 2963 | AB53: 2996 | AC53: 2975 | AD53: 3034 | AE53: 2986 | AF53: =AE53 -> 2986
A54: Pension & Other Post-Retire. Benefits | C54: - | D54: - | E54: - | F54: 698 | G54: =F54 -> 698 | H54: - | I54: - | J54: - | K54: 745 | L54: =K54 -> 745 | M54: - | N54: - | O54: - | P54: 660 | Q54: =P54 -> 660 | R54: - | S54: - | T54: - | U54: 598 | V54: =U54 -> 598 | W54: - | X54: - | Y54: - | Z54: 495 | AA54: =Z54 -> 495 | AB54: - | AC54: - | AD54: - | AE54: 456 | AF54: =AE54 -> 456
A55: Def. Tax Liability, Non-Curr. | C55: 1169 | D55: 1194 | E55: 1185 | F55: 1238 | G55: =F55 -> 1238 | H55: 1193 | I55: 1206 | J55: 1200 | K55: 1169 | L55: =K55 -> 1169 | M55: 944 | N55: 921 | O55: 917 | P55: 908 | Q55: =P55 -> 908 | R55: 868 | S55: 913 | T55: 970 | U55: 983 | V55: =U55 -> 983 | W55: 968 | X55: 948 | Y55: 884 | Z55: 947 | AA55: =Z55 -> 947 | AB55: 916 | AC55: 933 | AD55: 925 | AE55: 745 | AF55: =AE55 -> 745
A56: Other Non-Current Liabilities | C56: 1664 | D56: 1626 | E56: 1618 | F56: 882 | G56: =F56 -> 882 | H56: 1258 | I56: 1265 | J56: 1315 | K56: 592 | L56: =K56 -> 592 | M56: 1327 | N56: 1395 | O56: 1285 | P56: 636 | Q56: =P56 -> 636 | R56: 1297 | S56: 1267 | T56: 1245 | U56: 579 | V56: =U56 -> 579 | W56: 1159 | X56: 1152 | Y56: 1144 | Z56: 522 | AA56: =Z56 -> 522 | AB56: 1008 | AC56: 1005 | AD56: 997 | AE56: 494 | AF56: =AE56 -> 494
A57: Total Non-Current Liabilities | C57: =SUM(C52:C56) -> 8690 | D57: =SUM(D52:D56) -> 8293 | E57: =SUM(E52:E56) -> 8272 | F57: =SUM(F52:F56) -> 7526 | G57: =F57 -> 7526 | H57: =SUM(H52:H56) -> 9954 | I57: =SUM(I52:I56) -> 9987 | J57: =SUM(J52:J56) -> 10011 | K57: =SUM(K52:K56) -> 9045 | L57: =K57 -> 9045 | M57: =SUM(M52:M56) -> 10112 | N57: =SUM(N52:N56) -> 10436 | O57: =SUM(O52:O56) -> 10320 | P57: =SUM(P52:P56) -> 9796 | Q57: =P57 -> 9796 | R57: =SUM(R52:R56) -> 9889 | S57: =SUM(S52:S56) -> 8571 | T57: =SUM(T52:T56) -> 8600 | U57: =SUM(U52:U56) -> 8553 | V57: =U57 -> 8553 | W57: =SUM(W52:W56) -> 8151 | X57: =SUM(X52:X56) -> 8103 | Y57: =SUM(Y52:Y56) -> 8012 | Z57: =SUM(Z52:Z56) -> 7923 | AA57: =Z57 -> 7923 | AB57: =SUM(AB52:AB56) -> 7916 | AC57: =SUM(AC52:AC56) -> 7910 | AD57: =SUM(AD52:AD56) -> 7953 | AE57: =SUM(AE52:AE56) -> 7679 | AF57: =AE57 -> 7679
A59: Total Liabilities | C59: =C50+C57 -> 13767 | D59: =D50+D57 -> 12774 | E59: =E50+E57 -> 14716 | F59: =F50+F57 -> 12758 | G59: =G50+G57 -> 12758 | H59: =H50+H57 -> 14973 | I59: =I50+I57 -> 14426 | J59: =J50+J57 -> 16490 | ... AF59: =AF50+AF57 -> 12211
A61: Common Stock | C61: 5821 | D61: 5916 | E61: 5667 | F61: 3 | G61: =F61 -> 3 | H61: 3 | I61: 3 | J61: 3 | K61: 3 | L61: =K61 -> 3 | M61: 3 | N61: 3 | O61: 3 | P61: 3 | Q61: =P61 -> 3 | R61: 3 | S61: 3 | T61: 3 | U61: 3 | V61: =U61 -> 3 | W61: 3 | X61: 3 | Y61: 3 | Z61: 3 | AA61: =Z61 -> 3 | AB61: 3 | AC61: 3 | AD61: 3 | AE61: 3 | AF61: =AE61 -> 3
A62: Additional Paid In Capital | C62: - | D62: - | E62: - | F62: 652 | G62: =F62 -> 652 | H62: 606 | I62: 617 | J62: 626 | K62: 621 | L62: =K62 -> 621 | M62: 565 | N62: 568 | O62: 575 | P62: 571 | Q62: =P62 -> 571 | R62: 558 | S62: 498 | T62: 507 | U62: 517 | V62: =U62 -> 517 | W62: 476 | X62: 450 | Y62: 463 | Z62: 467 | AA62: =Z62 -> 467 | AB62: 373 | AC62: 352 | AD62: 367 | AE62: 352 | AF62: =AE62 -> 352
A63: Retained Earnings | C63: - | D63: - | E63: - | F63: 8050 | G63: =F63 -> 8050 | H63: 7911 | I63: 7883 | J63: 7649 | K63: 7989 | L63: =K63 -> 7989 | M63: 4291 | N63: 3860 | O63: 3769 | P63: 3928 | Q63: =P63 -> 3928 | R63: 4031 | S63: 4376 | T63: 4523 | U63: 5268 | V63: =U63 -> 5268 | W63: 5509 | X63: 5742 | Y63: 5764 | Z63: 6268 | AA63: =Z63 -> 6268 | AB63: 6378 | AC63: 6310 | AD63: 6261 | AE63: 6088 | AF63: =AE63 -> 6088
A64: Treasury Stock | C64: - | D64: - | E64: - | F64: -1318 | G64: =F64 -> -1318 | H64: -1252 | I64: -1248 | J64: -1244 | K64: -1241 | L64: =K64 -> -1241 | M64: -1180 | N64: -1176 | O64: -1175 | P64: -1161 | Q64: =P64 -> -1161 | R64: -1137 | S64: -1066 | T64: -1364 | U64: -1545 | V64: =U64 -> -1545 | W64: -2092 | X64: -2049 | Y64: -2048 | Z64: -2038 | AA64: =Z64 -> -2038 | AB64: -1967 | AC64: -1929 | AD64: -1928 | AE64: -1912 | AF64: =AE64 -> -1912
A65: Comprehensive Inc. and Other | C65: - | D65: - | E65: - | F65: -951 | G65: =F65 -> -951 | H65: - | I65: - | J65: - | K65: -995 | L65: =K65 -> -995 | M65: - | N65: - | O65: - | P65: -788 | Q65: =P65 -> -788 | R65: - | S65: - | T65: - | U65: -622 | V65: =U65 -> -622 | W65: - | X65: - | Y65: - | Z65: -618 | AA65: =Z65 -> -618 | AB65: - | AC65: - | AD65: - | AE65: -496 | AF65: =AE65 -> -496
A66: Total Common Equity | C66: =SUM(C61:C65) -> 5821 | D66: =SUM(D61:D65) -> 5916 | E66: =SUM(E61:E65) -> 5667 | F66: =SUM(F61:F65) -> 6436 | G66: =F66 -> 6436 | H66: =SUM(H61:H65) -> 7268 | I66: =SUM(I61:I65) -> 7255 | J66: =SUM(J61:J65) -> 7034 | K66: =SUM(K61:K65) -> 6377 | L66: =K66 -> 6377 | M66: =SUM(M61:M65) -> 3679 | N66: =SUM(N61:N65) -> 3255 | O66: =SUM(O61:O65) -> 3172 | P66: =SUM(P61:P65) -> 2553 | Q66: =P66 -> 2553 | R66: =SUM(R61:R65) -> 3455 | S66: =SUM(S61:S65) -> 3811 | T66: =SUM(T61:T65) -> 3669 | U66: =SUM(U61:U65) -> 3621 | V66: =U66 -> 3621 | W66: =SUM(W61:W65) -> 3896 | X66: =SUM(X61:X65) -> 4146 | Y66: =SUM(Y61:Y65) -> 4182 | Z66: =SUM(Z61:Z65) -> 4082 | AA66: =Z66 -> 4082 | AB66: =SUM(AB61:AB65) -> 4787 | AC66: =SUM(AC61:AC65) -> 4736 | AD66: =SUM(AD61:AD65) -> 4703 | AE66: =SUM(AE61:AE65) -> 4035 | AF66: =AE66 -> 4035
A68: Minority Interest | C68: -20 | D68: -22 | E68: -22 | F68: 0 | G68: =F68 -> 0 | H68: 0 | I68: 0 | J68: 0 | K68: 0 | L68: 0 | M68: 0 | N68: 0 | O68: 0 | P68: 0 | Q68: 0 | R68: 0 | S68: 0 | T68: 0 | U68: 0 | V68: 0 | W68: 0 | X68: 0 | Y68: 0 | Z68: 0 | AA68: 0 | AB68: 0 | AC68: 0 | AD68: 0 | AE68: 0 | AF68: 0
A70: Total Equity | C70: =C66+C68 -> 5801 | D70: =D66+D68 -> 5894 | E70: =E66+E68 -> 5645 | F70: =F66+F68 -> 6436 | G70: =G66+G68 -> 6436 | H70: =H66+H68 -> 7268 | I70: =I66+I68 -> 7255 | J70: =J66+J68 -> 7034 | ... AF70: =AF66+AF68 -> 4035
A72: Total Liabilities And Equity | C72: =C59+C70 -> 19568 | D72: =D59+D70 -> 18668 | E72: =E59+E70 -> 20361 | F72: =F59+F70 -> 19194 | G72: =G59+G70 -> 19194 | H72: =H59+H70 -> 22241 | I72: =I59+I70 -> 21681 | J72: =J59+J70 -> 23524 | ... AF72: =AF59+AF70 -> 16246
A75: Check: A = L + E? | C75: =IF(C39=C72, "True", C39-C72) -> True | D75: =IF(D39=D72, "True", D39-D72) -> True | E75: =IF(E39=E72, "True", E39-E72) -> True | F75: =IF(F39=F72, "True", F39-F72) -> True | G75: =IF(G39=G72, "True", G39-G72) -> True | H75: =IF(H39=H72, "True", H39-H72) -> -945 | I75: =IF(I39=I72, "True", I39-I72) -> -940 | J75: =IF(J39=J72, "True", J39-J72) -> -977 | ... AF75: =IF(AF39=AF72, "True", AF39-AF72) -> True

Sheet DCF (2)
A1: WACC & Inputs
L2: Terminal Growth Rate assumptions
A3: Shares Outstanding | B3: 27771 | L3: Fisher Equation = 2.18% +2.9% = 5.08% | O3: (taken the average over the past 10 years (ignored outliers)
A4: Marginal tax rate | B4: 0.2437
A5: Total debt (in millions) | B5: 2779
A6: Market cap (in millions) | B6: 3168.8
A7: Market D/E ratio | B7: 0.061
A8: Equity beta | B8: 1.29
A10: Market risk premium | B10: 0.0412
A11: Risk free rate | B11: 0.0396
A12: Cost of equity | B12: =B11+B8*B10 -> 0.092748
D13: 0.8 to 1.2
A14: Cost of debt | B14: 0.0643 | D14: 2-4 percent
A15: Cost of debt (after tax) | B15: =B14*(1-B4) -> 0.04863009
A17: WACC | B17: =B12*(0.53)+B14*(0.47) -> 0.07937744
AF18: #NAME?
A20: Free Cash Flow (FCF)
C21: 2025 | D21: 2026 | E21: 2027 | F21: 2028 | G21: Term
A22: Assumptions | C22: =DATE(2025,12,31) -> 46022 | D22: =DATE(2026,12,31) -> 46387 | E22: =DATE(2027,12,31) -> 46752 | F22: =DATE(2028,12,31) -> 47118 | G22: =DATE(2029,12,31) -> 47483
A23: Valuation date | B23: 45661
A24: Terminal Growth | B24: =5.08% -> 0.0508
A25: WACC | B25: =B17 -> 0.07937744
A27: FCFF
A28: EBIT | C28: 557.32186 | D28: 591.62367 | E28: 591.62468 | F28: 591.62681
A29: Tax on EBIT | C29: =C28*C30 -> 132.08528 | D29: =D28*D30 -> 140.21481 | E29: =E28*E30 -> 140.21505 | F29: =F28*F30 -> 140.21556
A30: Tax rate | C30: 0.237 | D30: 0.237 | E30: 0.237 | F30: 0.237
A31: NOPAT | C31: =C28-C29 -> 425.23658 | D31: =D28-D29 -> 451.40886 | E31: =E28-E29 -> 451.40963 | F31: =F28-F29 -> 451.41126
A32: Depreciation and amortisation | C32: 7758.8 | D32: 7941.5467 | E32: 8058.7769 | F32: 8114.8584
A33: CAPEX | C33: 631 | D33: 700 | E33: 800 | F33: 800
A34: Change in net working capital | C34: 585.88729 | D34: 456.34483 | E34: 379.90749 | F34: 447.84251 | L34: Terminal Value
A35: Free Cash Flow to Firm (FCFF) | C35: =SUM(C31:C34) -> 9400.9239 | D35: =SUM(D31:D34) -> 9549.3004 | E35: =SUM(E31:E34) -> 9690.094 | F35: =SUM(F31:F34) -> 9814.1122 | G35: =F35*(1+B24) -> 10312.669 | K35: Discounted Cash Flow Total Valuation | N35: Perpetuity Method
K36: Total of Present Value of Cash Flows | N36: =SUM(C38:F38) -> 38454.43
A37: Unadjusted Cash Flow | K37: Present Value of Terminal Value | N37: =F46 -> 95776.05
A38: Discrete forecast | C38: =C35 -> 9400.9239 | D38: =D35 -> 9549.3004 | E38: =E35 -> 9690.094 | F38: =F35 -> 9814.1122 | K38: Total Enterprise Value | N38: =N36+N37 -> 134230.48
A39: Terminal value | F39: =G35/B25-B24 -> 129919.35 | K39: Net Debt, Non-controlling interests, preferred securities | N39: 4950
A40: Total Cash Flow | C40: =SUM(C38:C39) -> 9400.9239 | D40: =SUM(D38:D39) -> 9549.3004 | E40: =SUM(E38:E39) -> 9690.094 | F40: =SUM(F38:F39) -> 139733.46 | K40: Equity Value | N40: =N38-N39 -> 129280.48
K41: Share Count (millions) | N41: =B3 -> 27771
K42: Estimated Equity Value per Share | N42: =N40/N41 -> 4.6552332
A43: Discounted Cash Flow
A44: Years for discounting | C44: =YEARFRAC(B23,C22) -> 0.99166667 | D44: =YEARFRAC(E22,D22)+C44 -> 1.9916667 | E44: =YEARFRAC(F22,E22)+D44 -> 2.9916667 | F44: =YEARFRAC(G22,F22)+E44 -> 3.9916667
A45: Discrete forecast | C45: =C38/(1+$B$25)^C44 -> 8715.1255 | D45: =D38/(1+$B$25)^D44 -> 8201.6517 | E45: =E38/(1+$B$25)^E44 -> 7710.5334 | F45: =F38/(1+$B$25)^F44 -> 7234.9264
A46: Terminal value | F46: =F39/(1+$B$25)^F44 -> 95776.05
A47: Discounted Cash Flow | C47: =SUM(C45:C46) -> 8715.1255 | D47: =SUM(D45:D46) -> 8201.6517 | E47: =SUM(E45:E46) -> 7710.5334 | F47: =SUM(F45:F46) -> 103010.98 | G47: =SUM(G45:G46) -> 0
A48: Total NPV | C48: =SUM(C47:F47) -> 127638.29
A51: TWO STAGE MODEL (H MODEL)
A55: Free Cash Flow (FCF)
C56: 2025 | D56: 2026 | E56: 2027 | F56: 2028 | G56: Term
A57: Assumptions | C57: =DATE(2025,12,31) -> 46022 | D57: =DATE(2026,12,31) -> 46387 | E57: =DATE(2027,12,31) -> 46752 | F57: =DATE(2028,12,31) -> 47118 | G57: =DATE(2029,12,31) -> 47483
A58: Valuation date | B58: 45661
A59: High Growth | B59: 0.06
A60: Long term Stable growth | B60: 0.03
A61: H | B61: 2
A62: WACC | B62: =B17 -> 0.07937744
A64: FCFF
A65: EBIT | C65: =C28 -> 557.32186 | D65: =D28 -> 591.62367 | E65: =E28 -> 591.62468 | F65: =F28 -> 591.62681
A66: Tax on EBIT | C66: =C29 -> 132.08528 | D66: =D29 -> 140.21481 | E66: =E29 -> 140.21505 | F66: =F29 -> 140.21556
A67: Tax rate | C67: =C30 -> 0.237 | D67: =D30 -> 0.237 | E67: =E30 -> 0.237 | F67: =F30 -> 0.237
A68: NOPAT | C68: =C31 -> 425.23658 | D68: =D31 -> 451.40886 | E68: =E31 -> 451.40963 | F68: =F31 -> 451.41126
A69: Depreciation and amortisation | C69: =C32 -> 7758.8 | D69: =D32 -> 7941.5467 | E69: =E32 -> 8058.7769 | F69: =F32 -> 8114.8584
A70: CAPEX | C70: =C33 -> 631 | D70: =D33 -> 700 | E70: =E33 -> 800 | F70: =F33 -> 800 | I70: Discounted Cash Flow Total Valuation | L70: Perpetuity Method
A71: Change in net working capital | C71: =C34 -> 585.88729 | D71: =D34 -> 456.34483 | E71: =E34 -> 379.90749 | F71: =F34 -> 447.84251 | I71: Total of Present Value of Cash Flows | L71: =SUM(C82:F82) -> 31862.237
A72: Free Cash Flow to Firm (FCFF) | C72: =SUM(C68:C71) -> 9400.9239 | D72: =SUM(D68:D71) -> 9549.3004 | E72: =SUM(E68:E71) -> 9690.094 | F72: =SUM(F68:F71) -> 9814.1122 | G72: =F72*(1+B59) -> 10402.959 | I72: Present Value of Terminal Value | L72: =F83 -> 169851.71
I73: Total Enterprise Value | L73: =L71+L72 -> 201713.94
A74: Unadjusted Cash Flow | I74: Net Debt, Non-controlling interests, preferred securities | L74: =N39 -> 4950
A75: Discrete forecast | C75: =C38 -> 9400.9239 | D75: =D38 -> 9549.3004 | E75: =E38 -> 9690.094 | F75: =F38 -> 9814.1122 | I75: Equity Value | L75: =L73-L74 -> 196763.94
A76: Terminal value | F76: =((G72*(1 + B60)) / (B62 - B60)) + ((G72*(1 + B59)) * B61 * (B59 - B60)) / (B62 - B60) -> 230402.3 | I76: Share Count (millions) | L76: =B3 -> 27771
A77: Total Cash Flow | C77: =C75 -> 9400.9239 | D77: =D75 -> 9549.3004 | E77: =E75 -> 9690.094 | F77: =SUM(F75:F76) -> 240216.42 | I77: Estimated Equity Value per Share | L77: =L75/L76 -> 7.0852307
A80: Discounted Cash Flow
A81: Years for discounting | C81: =C44 -> 0.99166667 | D81: =D44 -> 1.9916667 | E81: =E44 -> 2.9916667 | F81: =F44 -> 3.9916667
A82: Discrete forecast | C82: =C72 / (1 + $B$62)^C81 -> 8715.1255 | D82: =D72 / (1 + $B$62)^D81 -> 8201.6517 | E82: =E72 / (1 + $B$62)^E81 -> 7710.5334 | F82: =F72 / (1 + $B$62)^F81 -> 7234.9264
A83: Terminal value | F83: =F76 / (1 + $B$62)^F81 -> 169851.71
A84: Discounted Cash Flow | C84: =SUM(C82) -> 8715.1255 | D84: =SUM(D82:D83) -> 8201.6517 | E84: =SUM(E82:E83) -> 7710.5334 | F84: =SUM(F82:F83) -> 177086.63 | G84: =SUM(G82:G83) -> 0
A85: Total NPV | C85: =SUM(C84:F84) -> 201713.94

Sheet DCF
A1: WACC & Inputs
L2: Terminal Growth Rate assumptions
L3: Fisher Equation = 2.18% +2.9% = 5.08% | O3: (taken the average over the past 10 years (ignored outliers)
A4: Marginal tax rate | B4: 0.2437
A5: Total debt (in millions) | B5: 2779
A6: Market cap (in millions) | B6: 3168.8
A7: Market D/E ratio | B7: 0.061
A8: Equity beta | B8: 1.47 | E8: Not a stable firm ,
A10: Market risk premium | B10: 0.0412
A11: Risk free rate | B11: 0.0396
A12: Cost of equity | B12: =B11+B8*B10 -> 0.100164
D13: 0.8 to 1.2
A14: Cost of debt | B14: 0.0643 | D14: 2-4 percent
A15: Cost of debt (after tax) | B15: =B14*(1-B4) -> 0.04863009
A17: WACC | B17: =B12*(0.53)+B14*(0.47) -> 0.08330792
A20: Free Cash Flow (FCF)
C21: 2025 | D21: 2026 | E21: 2027 | F21: 2028 | G21: 2029 | H21: Term
A22: Assumptions | C22: =DATE(2025,12,31) -> 46022 | D22: =DATE(2026,12,31) -> 46387 | E22: =DATE(2027,12,31) -> 46752 | F22: =DATE(2028,12,31) -> 47118 | G22: =DATE(2029,12,31) -> 47483 | H22: =DATE(2030,12,31) -> 47848
A23: Valuation date | B23: 45661
A24: Terminal Growth | B24: =5.08% -> 0.0508
A25: WACC | B25: =B17 -> 0.08330792
A27: FCFF
A28: EBIT | C28: =IS!BD52 -> 0 | D28: =IS!BE52 -> 0 | E28: =IS!BF52 -> 0 | F28: =IS!BG52 -> 0 | G28: =IS!BH52 -> 0
A29: Tax on EBIT | C29: =C28*C30 -> 0 | D29: =D28*D30 -> 0 | E29: =E28*E30 -> 0 | F29: =F28*F30 -> 0 | G29: =G28*G30 -> 0
A30: Tax rate | C30: 0.237 | D30: 0.237 | E30: 0.237 | F30: 0.237 | G30: 0.237
A31: NOPAT | C31: =C28-C29 -> 0 | D31: =D28-D29 -> 0 | E31: =E28-E29 -> 0 | F31: =F28-F29 -> 0 | G31: =G28-G29 -> 0
A32: Depreciation and amortisation | C32: ='D&A'!AN33 -> 7758.8 | D32: ='D&A'!AS33 -> 7941.5467 | E32: ='D&A'!AX33 -> 8058.7769 | F32: ='D&A'!BC33 -> 8114.8584 | G32: ='D&A'!BH33 -> 8113.8679
A33: CAPEX | C33: 631 | D33: 700 | E33: 800 | F33: 800 | G33: 800
A34: Change in net working capital
A35: Free Cash Flow to Firm (FCFF) | C35: =SUM(C31:C34) -> 8389.8 | D35: =SUM(D31:D34) -> 8641.5467 | E35: =SUM(E31:E34) -> 8858.7769 | F35: =SUM(F31:F34) -> 8914.8584 | G35: =SUM(G31:G34) -> 8913.8679 | H35: =G35*(1+B24) -> 9366.6924
A37: Unadjusted Cash Flow
A38: Discrete forecast | C38: =C35 -> 8389.8 | D38: =D35 -> 8641.5467 | E38: =E35 -> 8858.7769 | F38: =F35 -> 8914.8584 | G38: =G35 -> 8913.8679
A39: Terminal value | G39: =H35/(B25-B24) -> 288135.7
A40: Total Cash Flow | C40: =SUM(C38:C39) -> 8389.8 | D40: =SUM(D38:D39) -> 8641.5467 | E40: =SUM(E38:E39) -> 8858.7769 | F40: =SUM(F38:F39) -> 8914.8584 | G40: =SUM(G38:G39) -> 297049.57
A43: Discounted Cash Flow
A44: Years for discounting | C44: =YEARFRAC(B23,C22) -> 0.99166667 | D44: =YEARFRAC(E22,D22)+C44 -> 1.9916667 | E44: =YEARFRAC(F22,E22)+D44 -> 2.9916667 | F44: =YEARFRAC(G22,F22)+E44 -> 3.9916667 | G44: =YEARFRAC(H22,G22)+F44 -> 4.9916667
A45: Discrete forecast | C45: =C38/(1+$B$25)^C44 -> 7749.7785 | D45: =D38/(1+$B$25)^D44 -> 7368.4687 | E45: =E38/(1+$B$25)^E44 -> 6972.8064 | F45: =F38/(1+$B$25)^F44 -> 6477.3353 | G45: =G38/(1+$B$25)^G44 -> 5978.5546 | H45: =H39/(1+$D$67)^G44 -> 0
A46: Terminal value | H46: =H40/(1+$D$67)^G44 -> 0
A47: Discounted Cash Flow | C47: =SUM(C45:C46) -> 7749.7785 | D47: =SUM(D45:D46) -> 7368.4687 | E47: =SUM(E45:E46) -> 6972.8064 | F47: =SUM(F45:F46) -> 6477.3353 | G47: =SUM(G45:G46) -> 5978.5546 | H47: =SUM(H45:H46) -> 0
A49: Free Cash Flow (Terminal Multiples)
B50: #REF! | C50: =C21 -> 2025 | D50: =D21 -> 2026 | E50: =E21 -> 2027 | F50: =F21 -> 2028 | G50: =G21 -> 2029 | H50: =H21 -> Term
C51: =C22 -> 46022 | D51: =D22 -> 46387 | E51: =E22 -> 46752 | F51: =F22 -> 47118 | G51: =G22 -> 47483 | H51: =H22 -> 47848
A52: Assumptions
A53: Valuation date | B53: =B23 -> 45661
A54: Terminal Multiple (EV/EBITDA)
A55: Terminal Multiple (EV/Sales)
A56: Terminal Multiple (EV/EBIT)
A57: EBITDA (Term)
A58: Sales (Term)
A59: EBIT (Term)
A60: WACC | B60: =B17 -> 0.08330792
A62: Unadjusted Cash Flow (EV/EBITDA)
A63: Discrete forecast | D63: =D36 -> 0 | E63: =E36 -> 0 | F63: =F36 -> 0 | G63: =G36 -> 0 | H63: =H36 -> 0
A64: Terminal value | H64: =B54*#REF! -> #REF!
A65: Total Cash Flow | C65: 0 | D65: =SUM(D63:D64) -> 0 | E65: =SUM(E63:E64) -> 0 | F65: =SUM(F63:F64) -> 0 | G65: =SUM(G63:G64) -> 0 | H65: =SUM(H63:H64) -> #REF!
A67: Discounted Cash Flow
A68: Years for discounting | D68: =D44 -> 1.9916667 | E68: =E44 -> 2.9916667 | F68: =F44 -> 3.9916667 | G68: =G44 -> 4.9916667 | H68: =H44 -> 0
A69: Discrete forecast | D69: =D63/(1+$D$67)^D68 -> 0 | E69: =E63/(1+$D$67)^E68 -> 0 | F69: =F63/(1+$D$67)^F68 -> 0 | G69: =G63/(1+$D$67)^G68 -> 0 | H69: =H63/(1+$D$67)^H68 -> 0
A70: Terminal value | H70: =H64/(1+$D$101)^H68 -> #REF!
A71: Discounted Cash Flow | D71: =SUM(D69:D70) -> 0 | E71: =SUM(E69:E70) -> 0 | F71: =SUM(F69:F70) -> 0 | G71: =SUM(G69:G70) -> 0 | H71: =SUM(H69:H70) -> #REF!
A73: Unadjusted Cash Flow (EV/Sales)
A74: Discrete forecast | D74: =D63 -> 0 | E74: =E63 -> 0 | F74: =F63 -> 0 | G74: =G63 -> 0 | H74: =H63 -> 0
A75: Terminal value | H75: =$D$96*$D$99 -> 0
A76: Total Cash Flow | C76: 0 | D76: =SUM(D74:D75) -> 0 | E76: =SUM(E74:E75) -> 0 | F76: =SUM(F74:F75) -> 0 | G76: =SUM(G74:G75) -> 0 | H76: =SUM(H74:H75) -> 0
A78: Discounted Cash Flow
A79: Years for discounting | D79: =D68 -> 1.9916667 | E79: =E68 -> 2.9916667 | F79: =F68 -> 3.9916667 | G79: =G68 -> 4.9916667 | H79: =H68 -> 0
A80: Discrete forecast | D80: =D74/(1+$D$67)^D79 -> 0 | E80: =E74/(1+$D$67)^E79 -> 0 | F80: =F74/(1+$D$67)^F79 -> 0 | G80: =G74/(1+$D$67)^G79 -> 0 | H80: =H74/(1+$D$67)^H79 -> 0
A81: Terminal value | H81: =H75/(1+$D$101)^H79 -> 0
A82: Discounted Cash Flow | D82: =SUM(D80:D81) -> 0 | E82: =SUM(E80:E81) -> 0 | F82: =SUM(F80:F81) -> 0 | G82: =SUM(G80:G81) -> 0 | H82: =SUM(H80:H81) -> 0
A84: Unadjusted Cash Flow (EV/EBIT)
A85: Discrete forecast | D85: =D74 -> 0 | E85: =E74 -> 0 | F85: =F74 -> 0 | G85: =G74 -> 0 | H85: =H74 -> 0
A86: Terminal value | H86: =$D$97*$D$100 -> 0
A87: Total Cash Flow | C87: 0 | D87: =SUM(D85:D86) -> 0 | E87: =SUM(E85:E86) -> 0 | F87: =SUM(F85:F86) -> 0 | G87: =SUM(G85:G86) -> 0 | H87: =SUM(H85:H86) -> 0
A89: Discounted Cash Flow
A90: Years for discounting | D90: =D79 -> 1.9916667 | E90: =E79 -> 2.9916667 | F90: =F79 -> 3.9916667 | G90: =G79 -> 4.9916667 | H90: =H79 -> 0
A91: Discrete forecast | D91: =D85/(1+$D$67)^D90 -> 0 | E91: =E85/(1+$D$67)^E90 -> 0 | F91: =F85/(1+$D$67)^F90 -> 0 | G91: =G85/(1+$D$67)^G90 -> 0 | H91: =H85/(1+$D$67)^H90 -> 0
A92: Terminal value | H92: =H86/(1+$D$101)^H90 -> 0
A93: Discounted Cash Flow | D93: =SUM(D91:D92) -> 0 | E93: =SUM(E91:E92) -> 0 | F93: =SUM(F91:F92) -> 0 | G93: =SUM(G91:G92) -> 0 | H93: =SUM(H91:H92) -> 0

Sheet IS
A5: Macy's, Inc. (NYSE:M) > Financials > Income Statement
A7: In Millions of USD, except per share items. | AW7: Template: | AX7: Standard | AZ7: Restatement: | BA7: Latest Filings
AW8: Period Type: | AX8: Annual | AZ8: Order: | BA8: Latest on Right
AW9: Currency: | AX9: US Dollar | AZ9: Conversion: | BA9: Historical
AW10: Units: | AX10: Millions (mm) | AZ10: Decimals: | BA10: Capital IQ (Default)
AW11: Source: | AX11: Capital IQ & Proprietary Data
A14: Income Statement | AF14: Projected | AW14: 2019 | AX14: 2020 | AY14: 2021 | AZ14: 2022 | BA14: 2023 | BB14: 2024 | BC14: FORECASTED
A15: For the Fiscal Period Ending | D15: 1Q 2019 | E15: 2Q 2019 | F15: 3Q 2019 | G15: 4Q 2019 | H15: 1Q 2020 | I15: 2Q 2020 | J15: 3Q 2020 | K15: 4Q 2020 | L15: 1Q 2021 | M15: 2Q 2021 | N15: 3Q 2021 | O15: 4Q 2021 | P15: 1Q 2022 | Q15: 2Q 2022 | R15: 3Q 2022 | S15: 4Q 2022 | T15: 1Q 2023 | U15: 2Q 2023 | V15: 3Q 2023 | W15: 4Q2023 | X15: 1Q 2024 | Y15: 2Q 2024 | Z15: 3Q 2024 | AA15: 4Q2024 | AB15: 1Q 2025 | AC15: 2Q2025 | AD15: 3Q2025 | AE15: 4Q2025 | AF15: 1Q2026 | AG15: 2Q2026 | AH15: 3Q2026 | AI15: 4Q2026 | AJ15: 1Q2027 | AK15: 2Q2027 | AL15: 3Q2027 | AM15: 4Q2027 | AN15: 1Q2028 | AO15: 2Q2028 | AP15: 3Q2028 | AQ15: 4Q2028 | AR15: 1Q2029 | AS15: 2Q2029 | AT15: 3Q2029 | AU15: 4Q2029 | AW15: 2019A | AX15: 2020A | AY15: 2021A | AZ15: 2022A | BA15: 2023A | BB15: 2024A | BC15: 2025A | BD15: 2026A | BE15: 2027A | BF15: 2028A | BG15: 2029A
A16: Currency: USD
A18: Revenue | D18: 5541 | E18: 5572 | F18: 5404 | G18: 8455 | H18: 5504 | I18: 5546 | J18: 5173 | K18: 8337 | L18: 3017 | M18: 3559 | N18: 3990 | O18: 6780 | P18: 4706 | Q18: 5647 | R18: 5440 | S18: 8666 | T18: 5348 | U18: 5600 | V18: 5230 | W18: 8264 | X18: 4982 | Y18: 5130 | Z18: 4860 | AA18: 8120 | AB18: =AVERAGE(D18,H18,L18,P18,T18,X180) -> 4823.2 | AC18: =AVERAGE(E18,I18,M18,Q18,U18,Y180) -> 5184.8 | AD18: =AVERAGE(F18,J18,N18,R18,V18,Z180) -> 5047.4 | AE18: =AVERAGE(G18,K18,O18,S18,W18,AA180) -> 8100.4 | AF18: =AVERAGE(H18,L18,P18,T18,X18,AB180,D18,AB18) -> 4845.8857 | AG18: =AVERAGE(I18,M18,Q18,U18,Y18,AC180,E18,AC18) -> 5176.9714 | AH18: =AVERAGE(J18,N18,R18,V18,Z18,AD180,F18,AD18) -> 5020.6286 | AI18: =AVERAGE(K18,O18,S18,W18,AA18,AE180,G18,AE18) -> 8103.2 | AJ18: =AVERAGE(L18,P18,T18,X18,AB18,AF180,H18,AF18,D18) -> 4845.8857 | AK18: =AVERAGE(M18,Q18,U18,Y18,AC18,AG180,I18,AG18,E18) -> 5176.9714 | AL18: =AVERAGE(N18,R18,V18,Z18,AD18,AH180,J18,AH18,F18) -> 5020.6286 | AM18: =AVERAGE(O18,S18,W18,AA18,AE18,AI180,K18,AI18,G18) -> 8103.2 | AN18: =AVERAGE(P18,T18,X18,AB18,AF18,AJ180,L18,AJ18,H18,D18) -> 4845.8857 | AO18: =AVERAGE(Q18,U18,Y18,AC18,AG18,AK180,M18,AK18,I18,E18) -> 5176.9714 | AP18: =AVERAGE(R18,V18,Z18,AD18,AH18,AL180,N18,AL18,J18,F18) -> 5020.6286 | AQ18: =AVERAGE(S18,W18,AA18,AE18,AI18,AM180,O18,AM18,K18,G18) -> 8103.2 | AR18: =AVERAGE(T18,X18,AB18,AF18,AJ18,AN180,P18,AN18,L18,H18,D18) -> 4845.8857 | AS18: =AVERAGE(U18,Y18,AC18,AG18,AK18,AO180,Q18,AO18,M18,I18) -> 5133.0794 | AT18: =AVERAGE(V18,Z18,AD18,AH18,AL18,AP180,R18,AP18,N18,J18) -> 4978.0317 | AU18: =AVERAGE(W18,AA18,AE18,AI18,AM18,AQ180,S18,AQ18,O18,K18) -> 8064.1111 | AW18: =SUM(D18:G18) -> 24972 | AX18: =SUM(H18:K18) -> 24560 | AY18: =SUM(L18:O18) -> 17346 | AZ18: =SUM(P21:S21) -> 25292 | BA18: =SUM(T18:W18) -> 24442 | BB18: =22293 -> 22293 | BC18: =SUM(AB21:AE21) -> 23973.133 | BD18: =SUM(AF18:AI18) -> 23146.686 | BE18: =SUM(AD21:AG21) -> 23987.99 | BF18: =SUM(AE21:AH21) -> 23961.219 | BG18: =SUM(AF21:AI21) -> 23964.019
A19: Other Revenue | D19: 157 | E19: 186 | F19: 185 | G19: 240 | H19: 172 | I19: 176 | J19: 183 | K19: 240 | L19: 131 | M19: 168 | N19: 195 | O19: 257 | P19: 159 | Q19: 197 | R19: 213 | S19: 264 | T19: 217 | U19: 234 | V19: 237 | W19: 319 | X19: 191 | Y19: 150 | Z19: 178 | AA19: 255 | AB19: =AVERAGE(D19,H19,L19,P19,T19,X181,X19) -> 171.16667 | AC19: =AVERAGE(E19,I19,M19,Q19,U19,Y181,Y19) -> 185.16667 | AD19: =AVERAGE(F19,J19,N19,R19,V19,Z181,Z19) -> 198.5 | AE19: =AVERAGE(G19,K19,O19,S19,W19,AA181,AA19) -> 262.5 | AF19: =AVERAGE(H19,L19,P19,T19,X19,AB181,AB19,D19) -> 171.16667 | AG19: =AVERAGE(I19,M19,Q19,U19,Y19,AC181,AC19,E19) -> 185.16667 | AH19: =AVERAGE(J19,N19,R19,V19,Z19,AD181,AD19,F19) -> 198.5 | AI19: =AVERAGE(K19,O19,S19,W19,AA19,AE181,AE19,G19) -> 262.5 | AJ19: =AVERAGE(L19,P19,T19,X19,AB19,AF181,AF19,H19,D19) -> 171.16667 | AK19: =AVERAGE(M19,Q19,U19,Y19,AC19,AG181,AG19,I19,E19) -> 185.16667 | AL19: =AVERAGE(N19,R19,V19,Z19,AD19,AH181,AH19,J19,F19) -> 198.5 | AM19: =AVERAGE(O19,S19,W19,AA19,AE19,AI181,AI19,K19,G19) -> 262.5 | AN19: =AVERAGE(P19,T19,X19,AB19,AF19,AJ181,AJ19,L19,H19,D19) -> 171.16667 | AO19: =AVERAGE(Q19,U19,Y19,AC19,AG19,AK181,AK19,M19,I19,E19,A19) -> 185.16667 | AP19: =AVERAGE(R19,V19,Z19,AD19,AH19,AL181,AL19,N19,J19,F19) -> 198.5 | AQ19: =AVERAGE(S19,W19,AA19,AE19,AI19,AM181,AM19,O19,K19,G19) -> 262.5 | AR19: =AVERAGE(T19,X19,AB19,AF19,AJ19,AN181,AN19,P19,L19,H19,D19) -> 171.16667 | AS19: =AVERAGE(U19,Y19,AC19,AG19,AK19,AO181,AO19,Q19,M19,I19,E19) -> 185.16667 | AT19: =AVERAGE(V19,Z19,AD19,AH19,AL19,AP181,AP19,R19,N19,J19,F19) -> 198.5 | AU19: =AVERAGE(W19,AA19,AE19,AI19,AM19,AQ181,AQ19,S19,O19,K19,G19) -> 262.5 | AW19: =SUM(D19:G19) -> 768 | AX19: =SUM(H19:K19) -> 771 | AY19: =SUM(L19:O19) -> 751 | AZ19: =SUM(P19:S19) -> 833 | BA19: =SUM(T19:W19) -> 1007 | BB19: =SUM(X19:AI19) -> 2408.6667 | BC19: =SUM(AB19:AE19) -> 817.33333 | BD19: =SUM(AF19:AI19) -> 817.33333 | BE19: =SUM(AD19:AG19) -> 817.33333 | BF19: =SUM(AE19:AH19) -> 817.33333 | BG19: =SUM(AF19:AI19) -> 817.33333
A20: Year end adjustments | D20: - | E20: - | F20: - | G20: - | H20: - | I20: - | J20: - | K20: - | L20: - | M20: - | N20: - | O20: - | P20: - | Q20: - | R20: - | S20: - | T20: - | U20: - | V20: - | W20: - | X20: - | Y20: - | Z20: - | AA20: - | AW20: -1 | AX20: 0 | AY20: 0 | AZ20: 107 | BA20: 0 | BB20: 0 | BC20: =SUM(AB20:AE20) -> 0
A21: Total Revenue | D21: =SUM(D18:D19) -> 5698 | E21: =SUM(E18:E19) -> 5758 | F21: =SUM(F18:F19) -> 5589 | G21: =SUM(G18:G19) -> 8695 | H21: =SUM(H18:H19) -> 5676 | I21: =SUM(I18:I19) -> 5722 | J21: =SUM(J18:J19) -> 5356 | K21: =SUM(K18:K19) -> 8577 | ... AU21: =SUM(AU18:AU19) -> 8326.6111 | AW21: =SUM(AW18:AW20) -> 25739 | AX21: =SUM(AX18:AX20) -> 25331 | AY21: =SUM(AY18:AY20) -> 18097 | AZ21: =SUM(AZ18:AZ20) -> 26232 | BA21: =SUM(BA18:BA20) -> 25449 | BB21: =SUM(BB18:BB20) -> 24701.667 | BC21: =SUM(AB21:AE21) -> 23973.133
AZ22: 25339 | BC22: =SUM(AB22:AE22) -> 0
A23: Cost Of Goods Sold | D23: 3382 | E23: 3320 | F23: 3226 | G23: 5288 | H23: 3403 | I23: 3395 | J23: 3106 | K23: 5266 | L23: 2201 | M23: 2718 | N23: 2569 | O23: 4798 | P23: 2889 | Q23: 3353 | R23: 3207 | S23: 5507 | T23: 3231 | U23: 3422 | V23: 3204 | W23: 5450 | X23: 2988 | Y23: 3176 | Z23: 2905 | AA23: 5154 | AB23: =AVERAGE(X23,T23,P23,L23,H23,D23) -> 3015.6667 | AC23: =AVERAGE(Y23,U23,Q23,M23,I23,E23) -> 3230.6667 | AD23: =AVERAGE(Z23,V23,R23,N23,J23,F23) -> 3036.1667 | AE23: =AVERAGE(AA23,W23,S23,O23,K23,G23) -> 5243.8333 | AF23: =AVERAGE(AB23,X23,T23,P23,L23,H23) -> 2954.6111 | AG23: =AVERAGE(AC23,Y23,U23,Q23,M23,I23) -> 3215.7778 | AH23: =AVERAGE(AD23,Z23,V23,R23,N23,J23) -> 3004.5278 | AI23: =AVERAGE(AE23,AA23,W23,S23,O23,K23) -> 5236.4722 | ... AU23: =AVERAGE(AQ23,AM23,AI23,AE23,AA23,W23) -> 5269.9443 | AW23: =SUM(D23:G23) -> 15216 | AX23: =SUM(H23:K23) -> 15170 | AY23: =SUM(L23:O23) -> 12286 | AZ23: =SUM(P23:S23) -> 14956 | BA23: =SUM(T23:W23) -> 15307 | BB23: =SUM(X23:AI23) -> 43160.722 | BC23: =SUM(AB23:AE23) -> 14526.333
A24: Year end adjustments | D24: - | E24: - | F24: - | G24: - | H24: - | I24: - | J24: - | K24: - | L24: - | M24: - | N24: - | O24: - | P24: - | Q24: - | R24: - | S24: - | T24: - | U24: - | V24: - | W24: - | X24: - | Y24: - | Z24: - | AA24: - | AW24: 1 | AX24: -1 | AY24: 0 | AZ24: 0 | BA24: -40 | BB24: -1 | BC24: =SUM(AB24:AE24) -> 0
A25: Gross Profit | D25: =D21-D23 -> 2316 | E25: =E21-E23 -> 2438 | F25: =F21-F23 -> 2363 | G25: =G21-G23 -> 3407 | H25: =H21-H23 -> 2273 | I25: =I21-I23 -> 2327 | J25: =J21-J23 -> 2250 | K25: =K21-K23 -> 3311 | ... AU25: =AU21-AU23 -> 3056.6668 | AW25: =AW21-AW23+AW24 -> 10524 | AX25: =AX21-AX23+AX24 -> 10160 | AY25: =AY21-AY23+AY24 -> 5811 | AZ25: =AZ21-AZ23+AZ24 -> 11276 | BA25: =BA21-BA23+BA24 -> 10102 | BB25: =BB21-BB23+BB24 -> -18460.056 | BC25: =SUM(AB25:AE25) -> 9446.8
BC26: =SUM(AB26:AE26) -> 0
A27: Selling General & Admin Exp. | D27: 2072 | E27: 2153 | F27: 2246 | G27: 2530 | H27: 2105 | I27: 2169 | J27: 2194 | K27: 2501 | L27: 1589 | M27: 1386 | N27: 1710 | O27: 2027 | P27: 1733 | Q27: 1881 | R27: 1956 | S27: 2412 | T27: 1898 | U27: 2004 | V27: 2081 | W27: 2457 | X27: 1946 | Y27: 1976 | Z27: 2038 | AA27: 2404 | AB27: =AVERAGE(X27,T27,P27,L27,H27,D27) -> 1890.5 | AC27: =AVERAGE(Y27,U27,Q27,M27,I27,E27) -> 1928.1667 | AD27: =AVERAGE(Z27,V27,R27,N27,J27,F27) -> 2037.5 | AE27: =AVERAGE(AA27,W27,S27,O27,K27,G27) -> 2388.5 | AF27: =AVERAGE(AB27,X27,T27,P27,L27,H27) -> 1860.25 | AG27: =AVERAGE(AC27,Y27,U27,Q27,M27,I27) -> 1890.6944 | AH27: =AVERAGE(AD27,Z27,V27,R27,N27,J27) -> 2002.75 | AI27: =AVERAGE(AE27,AA27,W27,S27,O27,K27) -> 2364.9167 | ... AU27: =AVERAGE(AQ27,AM27,AI27,AE27,AA27,W27) -> 2391.9047 | AW27: =SUM(D27:G27) -> 9001 | AX27: =SUM(H27:K27) -> 8969 | AY27: 6713 | AZ27: =SUM(P27:S27) -> 7982 | BA27: =SUM(T27:W27) -> 8440 | BB27: =SUM(X27:AI27) -> 24727.278 | BC27: =SUM(AB27:AE27) -> 8244.6667
A28: R & D Exp. | D28: - | E28: - | F28: - | G28: - | H28: - | I28: - | J28: - | K28: - | L28: - | M28: - | N28: - | O28: - | P28: - | Q28: - | R28: - | S28: - | T28: - | U28: - | V28: - | W28: - | X28: - | Y28: - | Z28: - | AA28: - | AW28: =SUM(D28:G28) -> 0 | AX28: =SUM(H28:K28) -> 0 | AY28: - | AZ28: =SUM(P28:S28) -> 0 | BA28: =SUM(T28:W28) -> 0 | BB28: - | BC28: =SUM(AB28:AE28) -> 0
A29: Depreciation & Amort. | D29: - | E29: - | F29: - | G29: - | H29: - | I29: - | J29: - | K29: - | L29: - | M29: - | N29: - | O29: - | P29: - | Q29: - | R29: - | S29: - | T29: - | U29: - | V29: - | W29: - | X29: - | Y29: - | Z29: - | AA29: - | AW29: =SUM(D29:G29) -> 0 | AX29: =SUM(H29:K29) -> 0 | AY29: - | AZ29: =SUM(P29:S29) -> 0 | BA29: =SUM(T29:W29) -> 0 | BB29: - | BC29: =SUM(AB29:AE29) -> 0
A30: Other Operating Expense/(Income) | D30: - | E30: - | F30: - | G30: -8 | H30: 1 | I30: 1 | J30: 8 | K30: -10 | L30: 9 | M30: 58 | N30: 12 | O30: -79 | P30: - | Q30: - | R30: - | S30: 21 | T30: - | U30: - | V30: - | W30: 21 | X30: - | Y30: - | Z30: - | AA30: 15 | AB30: =AVERAGE(X30,T30,P30,L30,H30,D30) -> 5 | AC30: =AVERAGE(Y30,U30,Q30,M30,I30,E30) -> 29.5 | AD30: =AVERAGE(Z30,V30,R30,N30,J30,F30) -> 10 | AE30: =AVERAGE(AA30,W30,S30,O30,K30,G30) -> -6.6666667 | AF30: =AVERAGE(AB30,X30,T30,P30,L30,H30) -> 5 | AG30: =AVERAGE(AC30,Y30,U30,Q30,M30,I30) -> 29.5 | AH30: =AVERAGE(AD30,Z30,V30,R30,N30,J30) -> 10 | AI30: =AVERAGE(AE30,AA30,W30,S30,O30,K30) -> -6.4444444 | ... AU30: =AVERAGE(AQ30,AM30,AI30,AE30,AA30,W30) -> 3.8960905 | AW30: =SUM(D30:G30) -> -8 | AX30: =SUM(H30:K30) -> 0 | AY30: - | AZ30: =SUM(P30:S30) -> 21 | BA30: =SUM(T30:W30) -> 21 | BB30: 15 | BC30: =SUM(AB30:AE30) -> 37.833333
A31: Year-end Adjustments | D31: - | E31: - | F31: - | G31: - | H31: - | I31: - | J31: - | K31: - | L31: - | M31: - | N31: - | O31: - | P31: - | Q31: - | R31: - | S31: - | T31: - | U31: - | V31: - | W31: - | X31: - | Y31: - | Z31: - | AA31: - | AW31: -1 | AX31: 32 | AY31: 0 | AZ31: 106 | BA31: 1 | BB31: 0 | BC31: =SUM(AB31:AE31) -> 0
A32: Other Operating Exp., Total | D32: =SUM(D27:D30) -> 2072 | E32: =SUM(E27:E30) -> 2153 | F32: =SUM(F27:F30) -> 2246 | G32: =SUM(G27:G30) -> 2522 | H32: =SUM(H27:H30) -> 2106 | I32: =SUM(I27:I30) -> 2170 | J32: =SUM(J27:J30) -> 2202 | K32: =SUM(K27:K30) -> 2491 | ... AU32: =SUM(AU27:AU30) -> 2395.8008 | AW32: =SUM(AW27:AW31) -> 8992 | AX32: =SUM(AX27:AX31) -> 9001 | AY32: =SUM(AY27:AY31) -> 6713 | AZ32: =SUM(AZ27:AZ31) -> 8109 | BA32: =SUM(BA27:BA31) -> 8462 | BB32: =SUM(BB27:BB31) -> 24742.278 | BC32: =SUM(AB32:AE32) -> 8282.5
BC33: =SUM(AB33:AE33) -> 0
A34: Year-end Adjustments | D34: - | E34: - | F34: - | G34: - | H34: - | I34: - | J34: - | K34: - | L34: - | M34: - | N34: - | O34: - | P34: - | Q34: - | R34: - | S34: - | T34: - | U34: - | V34: - | W34: - | X34: - | Y34: - | Z34: - | AA34: - | AW34: 1 | AX34: -1 | AY34: 0 | AZ34: 0 | BA34: -40 | BB34: -1 | BC34: =SUM(AB34:AE34) -> 0
A35: Operating Income | D35: =D25-D32 -> 244 | E35: =E25-E32 -> 285 | F35: =F25-F32 -> 117 | G35: =G25-G32 -> 885 | H35: =H25-H32 -> 167 | I35: =I25-I32 -> 157 | J35: =J25-J32 -> 48 | K35: =K25-K32 -> 820 | ... AU35: =AU25-AU32 -> 660.866 | AW35: =(AW25-AW32)+AW34 -> 1533 | AX35: =(AX25-AX32)+AX34 -> 1158 | AY35: =(AY25-AY32)+AY34 -> -902 | AZ35: =(AZ25-AZ32)+AZ34 -> 3167 | BA35: =(BA25-BA32)+BA34 -> 1600 | BB35: =(BB25-BB32)+BB34 -> -43203.333 | BC35: =SUM(AB35:AE35) -> 1164.3
BC36: =SUM(AB36:AE36) -> 0
A37: Interest Expense | D37: -71 | E37: -69 | F37: -64 | G37: -57 | H37: -54 | I37: -52 | J37: -52 | K37: -46 | L37: -49 | M37: -70 | N37: -80 | O37: -85 | P37: -79 | Q37: -80 | R37: -53 | S37: -44 | T37: -47 | U37: -42 | V37: -42 | W37: -31 | X37: -37 | Y37: -36 | Z37: -35 | AA37: -27 | AB37: -27 | AC37: -27 | AD37: -27 | AE37: -27 | AF37: -27 | AG37: -27 | AH37: -27 | AI37: -27 | AJ37: -27 | AK37: -27 | AL37: -27 | AM37: -27 | AN37: -27 | AO37: -27 | AP37: -27 | AQ37: -27 | AR37: -27 | AS37: -27 | AT37: -27 | AU37: -27 | AW37: =SUM(D37:G37) -> -261 | AX37: =SUM(H37:K37) -> -204 | AY37: =SUM(L37:O37) -> -284 | AZ37: =SUM(P37:S37) -> -256 | BA37: =SUM(T37:W37) -> -162 | BB37: =SUM(X37:AI37) -> -351 | BC37: =SUM(AB37:AE37) -> -108
A38: Interest and Invest. Income | D38: 5 | E38: 7 | F38: 5 | G38: 8 | H38: 7 | I38: 5 | J38: 4 | K38: 4 | L38: 2 | M38: 1 | N38: - | O38: 1 | P38: - | Q38: - | R38: - | S38: 0 | T38: - | U38: - | V38: - | W38: - | X38: - | Y38: - | Z38: - | AA38: - | AB38: - | AC38: - | AD38: - | AE38: - | AF38: - | AG38: - | AH38: - | AI38: - | AJ38: - | AK38: - | AL38: - | AM38: - | AN38: - | AO38: - | AP38: - | AQ38: - | AR38: - | AS38: - | AT38: - | AU38: - | AW38: =SUM(D38:G38) -> 25 | AX38: =SUM(H38:K38) -> 20 | AY38: =SUM(L38:O38) -> 4 | AZ38: =SUM(P38:S38) -> 0 | BA38: =SUM(T38:W38) -> 0 | BB38: =SUM(X38:AI38) -> 0 | BC38: =SUM(AB38:AE38) -> 0
A39: Year-end adjustments | D39: - | E39: - | F39: - | G39: - | H39: - | I39: - | J39: - | K39: - | L39: - | M39: - | N39: - | O39: - | P39: - | Q39: - | R39: - | S39: - | T39: - | U39: - | V39: - | W39: - | X39: - | Y39: - | Z39: - | AA39: - | AB39: - | AC39: - | AD39: - | AE39: - | AF39: - | AG39: - | AH39: - | AI39: - | AJ39: - | AK39: - | AL39: - | AM39: - | AN39: - | AO39: - | AP39: - | AQ39: - | AR39: - | AS39: - | AT39: - | AU39: - | AW39: 0 | AX39: -1 | AY39: 0 | AZ39: 1 | BA39: 0 | BB39: 0 | BC39: =SUM(AB39:AE39) -> 0
A40: Net Interest Exp. | D40: =SUM(D37:D38) -> -66 | E40: =SUM(E37:E38) -> -62 | F40: =SUM(F37:F38) -> -59 | G40: =SUM(G37:G38) -> -49 | H40: =SUM(H37:H38) -> -47 | I40: =SUM(I37:I38) -> -47 | J40: =SUM(J37:J38) -> -48 | K40: =SUM(K37:K38) -> -42 | ... AU40: =SUM(AU37:AU38) -> -27 | AW40: =SUM(AW37:AW39) -> -236 | AX40: =SUM(AX37:AX39) -> -185 | AY40: =SUM(AY37:AY39) -> -280 | AZ40: =SUM(AZ37:AZ39) -> -255 | BA40: =SUM(BA37:BA39) -> -162 | BB40: =SUM(BB37:BB39) -> -351 | BC40: =SUM(AB40:AE40) -> -108
BC41: =SUM(AB41:AE41) -> 0
A42: Other Non-Operating Inc. (Exp.) | D42: - | E42: - | F42: - | G42: - | H42: - | I42: - | J42: - | K42: - | L42: - | M42: -3 | N42: - | O42: -1 | P42: - | Q42: - | R42: - | S42: - | T42: - | U42: - | V42: - | W42: - | X42: - | Y42: - | Z42: - | AA42: - | AW42: - | AX42: - | AY42: =SUM(L42:O42) -> -4 | AZ42: - | BA42: - | BB42: - | BC42: =SUM(AB42:AE42) -> 0
A43: Year-end Adjustments | D43: - | E43: - | F43: - | G43: - | H43: - | I43: - | J43: - | K43: - | L43: - | M43: - | N43: - | O43: - | P43: - | Q43: - | R43: - | S43: - | T43: - | U43: - | V43: - | W43: - | X43: - | Y43: - | Z43: - | AA43: - | AW43: -1 | AX43: 1 | AY43: -5 | AZ43: 0 | BA43: 40 | BB43: 1 | BC43: =SUM(AB43:AE43) -> 0
A44: EBT Excl. Unusual Items | D44: =D35+D40 -> 178 | E44: =E35+E40 -> 223 | F44: =F35+F40 -> 58 | G44: =G35+G40 -> 836 | H44: =H35+H40 -> 120 | I44: =I35+I40 -> 110 | J44: =J35+J40 -> 0 | K44: =K35+K40 -> 778 | ... AU44: =AU35+AU40 -> 633.866 | AW44: =AW35+AW40+AW43 -> 1296 | AX44: =AX35+AX40+AX43 -> 974 | AY44: =AY35+AY40+AY43 -> -1187 | AZ44: =AZ35+AZ40+AZ43 -> 2912 | BA44: =BA35+BA40+BA43 -> 1478 | BB44: =BB35+BB40+BB43 -> -43553.333 | BC44: =SUM(AB44:AE44) -> 1056.3
BC45: =SUM(AB45:AE45) -> 0
A46: Restructuring Charges | D46: -19 | E46: -17 | F46: -3 | G46: -41 | H46: - | I46: - | J46: -5 | K46: -313 | L46: -25 | M46: -169 | N46: -2 | O46: -28 | P46: - | Q46: - | R46: - | S46: -3 | T46: - | U46: - | V46: - | W46: -5 | X46: - | Y46: - | Z46: - | AA46: -55 | AW46: =SUM(D46:G46) -> -80 | AX46: =SUM(H46:K46) -> -318 | AY46: =SUM(L46:O46) -> -224 | AZ46: =SUM(P46:S46) -> -3 | BA46: =SUM(T46:W46) -> -5 | BB46: =SUM(X46:AI46) -> -55 | BC46: =SUM(AB46:AE46) -> 0
A47: Impairment of Goodwill | D47: - | E47: - | F47: - | G47: - | H47: - | I47: - | J47: - | K47: - | L47: -3070 | M47: - | N47: - | O47: 0 | P47: - | Q47: - | R47: - | S47: - | T47: - | U47: - | V47: - | W47: - | X47: - | Y47: - | Z47: - | AA47: - | AW47: =SUM(D47:G47) -> 0 | AX47: =SUM(H47:K47) -> 0 | AY47: =SUM(L47:O47) -> -3070 | AZ47: =SUM(P47:S47) -> 0 | BA47: =SUM(T47:W47) -> 0 | BB47: =SUM(X47:AI47) -> 0 | BC47: =SUM(AB47:AE47) -> 0
A48: Gain (Loss) On Sale Of Assets | D48: 24 | E48: 46 | F48: 42 | G48: 278 | H48: 43 | I48: 7 | J48: 17 | K48: 95 | L48: 16 | M48: - | N48: 3 | O48: 40 | P48: 6 | Q48: 6 | R48: 50 | S48: 30 | T48: 42 | U48: - | V48: 32 | W48: 15 | X48: 11 | Y48: 4 | Z48: 5 | AA48: 41 | AW48: =SUM(D48:G48) -> 390 | AX48: =SUM(H48:K48) -> 162 | AY48: =SUM(L48:O48) -> 59 | AZ48: =SUM(P48:S48) -> 92 | BA48: =SUM(T48:W48) -> 89 | BB48: =SUM(X48:AI48) -> 61 | BC48: =SUM(AB48:AE48) -> 0
A49: Asset Writedown | D49: - | E49: - | F49: - | G49: -64 | H49: - | I49: -1 | J49: - | K49: -35 | L49: -380 | M49: -15 | N49: -6 | O49: 190 | P49: -19 | Q49: -2 | R49: - | S49: 15 | T49: -8 | U49: -2 | V49: -15 | W49: 10 | X49: -2 | Y49: -4 | Z49: -15 | AA49: -936 | AW49: =SUM(D49:G49) -> -64 | AX49: =SUM(H49:K49) -> -36 | AY49: =SUM(L49:O49) -> -211 | AZ49: =SUM(P49:S49) -> -6 | BA49: =SUM(T49:W49) -> -15 | BB49: =SUM(X49:AI49) -> -957 | BC49: =SUM(AB49:AE49) -> 0
A50: Other Unusual Items, incl Gain/ Loss on Early retirement of Debt Settlement Charges | D50: - | E50: -55 | F50: -23 | G50: -43 | H50: - | I50: - | J50: -12 | K50: -76 | L50: - | M50: -38 | N50: -26 | O50: -94 | P50: -11 | Q50: -84 | R50: -193 | S50: -6 | T50: -31 | U50: - | V50: -32 | W50: -7 | X50: - | Y50: -122 | Z50: -7 | AA50: -5 | AW50: =SUM(D50:G50) -> -121 | AX50: =SUM(H50:K50) -> -88 | AY50: =SUM(L50:O50) -> -158 | AZ50: =SUM(P50:S50) -> -294 | BA50: =SUM(T50:W50) -> -70 | BB50: =SUM(X50:AI50) -> -134 | BC50: =SUM(AB50:AE50) -> 0
A51: Year-end Adjustments | D51: - | E51: - | F51: - | G51: - | H51: - | I51: - | J51: - | K51: - | L51: - | M51: - | N51: - | O51: - | P51: - | Q51: - | R51: - | S51: - | T51: - | U51: - | V51: - | W51: - | X51: - | Y51: - | Z51: - | AA51: - | AW51: -1 | AX51: 34 | AY51: 1 | AZ51: -2 | BA51: 0 | BB51: 0 | BC51: =SUM(AB51:AE51) -> 0
A52: EBT Incl. Unusual Items | D52: =D44+SUM(D46:D51) -> 183 | E52: =E44+SUM(E46:E51) -> 197 | F52: =F44+SUM(F46:F51) -> 74 | G52: =G44+SUM(G46:G51) -> 966 | H52: =H44+SUM(H46:H50) -> 163 | I52: =I44+SUM(I46:I50) -> 116 | J52: =J44+SUM(J46:J50) -> 0 | K52: =K44+SUM(K46:K50) -> 449 | L52: =L44+SUM(L46:L50) -> -4157 | M52: =M44+SUM(M46:M50) -> -726 | N52: =N44+SUM(N46:N50) -> -217 | O52: =O44+SUM(O46:O50) -> 315 | ... AA52: =AA44+SUM(AA46:AA50) -> -180 | AW52: =AW44+SUM(AW46:AW51) -> 1420 | AX52: =AX44+SUM(AX46:AX51) -> 728 | AY52: =AY44+SUM(AY46:AY51) -> -4790 | AZ52: =AZ44+SUM(AZ46:AZ51) -> 2699 | BA52: =BA44+SUM(BA46:BA51) -> 1477 | BB52: =BB44+SUM(BB46:BB51) -> -44638.333 | BC52: =SUM(AB52:AE52) -> 0
BC53: =SUM(AB53:AE53) -> 0
A54: Income Tax Expense | D54: 52 | E54: 33 | F54: 12 | G54: 226 | H54: 27 | I54: 30 | J54: -2 | K54: 109 | L54: -576 | M54: -298 | N54: -126 | O54: 154 | P54: 37 | Q54: 105 | R54: 55 | S54: 239 | T54: 106 | U54: 89 | V54: 17 | W54: 128 | X54: 56 | Y54: -8 | Z54: 2 | AA54: -52 | AW54: 322 | AX54: =SUM(H54:K54) -> 164 | AY54: =SUM(L54:O54) -> -846 | AZ54: =SUM(P54:S54) -> 436 | BA54: 331 | BB54: =SUM(X54:AI54) -> -2 | BC54: =SUM(AB54:AE54) -> 0
A55: Net Income to Company | D55: =D52-D54 -> 131 | E55: =E52-E54 -> 164 | F55: =F52-F54 -> 62 | G55: =G52-G54 -> 740 | H55: =H52-H54 -> 136 | I55: =I52-I54 -> 86 | J55: =J52-J54 -> 2 | K55: =K52-K54 -> 340 | ... AA55: =AA52-AA54 -> -128 | AW55: =AW52-AW54 -> 1098 | AX55: =AX52-AX54 -> 564 | AY55: =AY52-AY54 -> -3944 | AZ55: =AZ52-AZ54 -> 2263 | BA55: =BA52-BA54 -> 1146 | BB55: =BB52-BB54 -> -44636.333 | BC55: =SUM(AB55:AE55) -> 0
BC56: =SUM(AB56:AE56) -> 0
A57: Minority Int. in Earnings | D57: 8 | E57: 2 | F57: 0 | G57: 0 | H57: 0 | I57: 0 | J57: 0 | K57: 0 | L57: 0 | M57: 0 | N57: 0 | O57: 0 | P57: 0 | Q57: 0 | R57: 0 | S57: 0 | T57: 0 | U57: 0 | V57: 0 | W57: 0 | X57: 0 | Y57: 0 | Z57: 0 | AA57: 0 | AW57: =SUM(D57:G57) -> 10 | AX57: 0 | AY57: 0 | AZ57: 0 | BA57: 0 | BB57: 0 | BC57: =SUM(AB57:AE57) -> 0
A58: Net Income | D58: =D55+D57 -> 139 | E58: =E55+E57 -> 166 | F58: =F55+F57 -> 62 | G58: =G55+G57 -> 740 | H58: =H55+H57 -> 136 | I58: =I55+I57 -> 86 | J58: =J55+J57 -> 2 | K58: =K55+K57 -> 340 | ... AA58: =AA55+AA57 -> -128 | AW58: =AW55+AW57 -> 1108 | AX58: =AX55+AX57 -> 564 | AY58: =AY55+AY57 -> -3944 | AZ58: =AZ55+AZ57 -> 2263 | BA58: =BA55+BA57 -> 1146 | BB58: =BB55+BB57 -> -44636.333 | BC58: =SUM(AB58:AE58) -> 0
BC59: =SUM(AB59:AE59) -> 0
BC60: =SUM(AB60:AE60) -> 0
A61: Basic EPS | D61: 0.45 | E61: 0.54 | F61: 0.2 | G61: 2.4 | H61: 0.44 | I61: 0.28 | J61: 0.01 | K61: 1.1 | L61: -11.53 | M61: -1.38 | N61: -0.29 | O61: 0.51 | P61: 0.33 | Q61: 1.1 | R61: 0.78 | S61: 2.51 | T61: 1.01 | U61: 1.01 | V61: 0.4 | W61: 1.87 | X61: 0.57 | Y61: -0.08 | Z61: 0.15 | AA61: -0.47 | AW61: 3.6 | AX61: 1.82 | AY61: -12.68 | AZ61: 4.66 | BA61: 4.17 | BB61: 0.16 | BC61: =SUM(AB61:AE61) -> 0
A62: Weighted Avg. Basic Shares Out. | D62: 306.6 | E62: 307.7 | F62: 308.1 | G62: 308.4 | H62: 309.1 | I62: 309.8 | J62: 309.9 | K62: 309.9 | L62: 310.6 | M62: 311.2 | N62: 311.2 | O62: 311.4 | P62: 311.6 | Q62: 312.4 | R62: 306.9 | S62: 296.5 | T62: 283.6 | U62: 271.1 | V62: 272 | W62: 272.2 | X62: 273.1 | Y62: 273.8 | Z62: 274.7 | AA62: 275 | AW62: 307.7 | AX62: 309.7 | AY62: 311.1 | AZ62: 306.8 | BA62: 274.7 | BB62: 274.2 | BC62: =SUM(AB62:AE62) -> 0
BC63: =SUM(AB63:AE63) -> 0
A64: Diluted EPS | D64: 0.45 | E64: 0.53 | F64: 0.2 | G64: 2.38 | H64: 0.44 | I64: 0.28 | J64: 0.01 | K64: 1.09 | L64: -11.53 | M64: -1.39 | N64: -0.29 | O64: 0.51 | P64: 0.32 | Q64: 1.08 | R64: 0.76 | S64: 2.43 | T64: 0.98 | U64: 0.99 | V64: 0.39 | W64: 1.83 | X64: 0.56 | Y64: -0.08 | Z64: 0.15 | AA64: -0.47 | AW64: 3.56 | AX64: 1.81 | AY64: -12.68 | AZ64: 4.55 | BA64: 4.08 | BB64: 0.16 | BC64: =SUM(AB64:AE64) -> 0
A65: Weighted Avg. Diluted Shares Out. | D65: 309.4 | E65: 312 | F65: 312.2 | G65: 311.9 | H65: 311.4 | I65: 311.6 | J65: 311 | K65: 311.5 | L65: 310.6 | M65: 311.2 | N65: 311.2 | O65: 316.6 | P65: 318.6 | Q65: 318.6 | R65: 313.8 | S65: 304.8 | T65: 290.9 | U65: 277.4 | V65: 277.7 | W65: 278.5 | X65: 277.8 | Y65: 273.8 | Z65: 277.6 | AA65: 275 | AW65: 311.4 | AX65: 311.4 | AY65: 311.1 | AZ65: 314 | BA65: 281.1 | BB65: 278.2 | BC65: =SUM(AB65:AE65) -> 0

Sheet CFS
A5: Macy's, Inc. (NYSE:M) > Financials > Cash Flow Statement
A7: In Millions of USD, except per share items. | C7: Template: | D7: Standard | E7: Restatement: | F7: Latest Filings | AA7: Template: | AB7: Standard | AD7: Restatement: | AE7: Latest Filings
C8: Period Type: | D8: Annual | E8: Order: | F8: Latest on Right | AA8: Period Type: | AB8: Annual | AD8: Order: | AE8: Latest on Right
C9: Currency: | D9: US Dollar | E9: Conversion: | F9: Historical | AA9: Currency: | AB9: US Dollar | AD9: Conversion: | AE9: Historical
C10: Units: | D10: Millions (mm) | E10: Decimals: | F10: Capital IQ (Default) | AA10: Units: | AB10: Millions (mm) | AD10: Decimals: | AE10: Capital IQ (Default)
C11: Source: | D11: Capital IQ & Proprietary Data | AA11: Source: | AB11: Capital IQ & Proprietary Data
A14: Cash Flow Statement | AA14: 2019 | AB14: 2020 | AC14: 2021 | AD14: 2022 | AE14: 2023 | AF14: 2024
A15: For the Fiscal Period Ending | C15: 1Q 2019 | D15: 2Q 2019 | E15: 3Q 2019 | F15: 4Q 2019 | G15: 1Q 2020 | H15: 2Q 2020 | I15: 3Q 2020 | J15: 4Q 2020 | K15: 1Q 2021 | L15: 2Q 2021 | M15: 3Q 2021 | N15: 4Q 2021 | O15: 1Q 2022 | P15: 2Q 2022 | Q15: 3Q 2022 | R15: 4Q 2022 | S15: 1Q 2023 | T15: 2Q 2023 | U15: 3Q 2023 | V15: 4Q 2023 | W15: 1Q 2024 | X15: 2Q 2024 | Y15: 3Q 2024 | Z15: 4Q2024 | AA15: 2019A | AB15: 2020A | AC15: 2021A | AD15: 2022A | AE15: 2023A | AF15: 2024A
A16: Currency: USD
A18: Net Income | C18: 139 | D18: 167 | E18: 62 | F18: 740 | G18: 136 | H18: 87 | I18: 1 | J18: 340 | K18: -3581 | L18: -431 | M18: -92 | N18: 160 | O18: 103 | P18: 345 | Q18: 239 | R18: 743 | S18: 286 | T18: 275 | U18: 107 | V18: 509 | W18: 155 | X18: -22 | Y18: 40 | Z18: -128 | AA18: =SUM(C18:F18) -> 1108 | AB18: =SUM(G18:J18) -> 564 | AC18: =SUM(K18:N18) -> -3944 | AD18: =SUM(O18:R18) -> 1430 | AE18: =SUM(S18:V18) -> 1177 | AF18: =SUM(W18:Z18) -> 45
A19: Depreciation & Amort. | C19: 235 | D19: 235 | E19: 248 | F19: -52 | G19: 236 | H19: 236 | I19: 253 | J19: -29 | K19: 237 | L19: 235 | M19: 250 | N19: -31 | O19: 224 | P19: 220 | Q19: 224 | R19: -32 | S19: 206 | T19: 207 | U19: 225 | V19: -16 | W19: 218 | X19: 215 | Y19: 232 | Z19: -37 | AA19: =SUM(C19:F19) -> 666 | AB19: =SUM(G19:J19) -> 696 | AC19: =SUM(K19:N19) -> 691 | AD19: =SUM(O19:R19) -> 636 | AE19: =SUM(S19:V19) -> 622 | AF19: =SUM(W19:Z19) -> 628
A20: Depreciation & Amort., Total | C20: =C19 -> 235 | D20: =D19 -> 235 | E20: =E19 -> 248 | F20: =F19 -> -52 | G20: =G19 -> 236 | H20: =H19 -> 236 | I20: =I19 -> 253 | J20: =J19 -> -29 | ... AF20: =AF19 -> 628
A22: Other Amortization | C22: - | D22: -5 | E22: 0 | F22: 286 | G22: - | H22: 1 | I22: 0 | J22: 288 | K22: - | L22: 4 | M22: 7 | N22: 275 | O22: 8 | P22: 6 | Q22: 52 | R22: 242 | S22: 2 | T22: 3 | U22: 3 | V22: 238 | W22: 3 | X22: 2 | Y22: 3 | Z22: 271 | AA22: =SUM(C22:F22) -> 281 | AB22: =SUM(G22:J22) -> 289 | AC22: =SUM(K22:N22) -> 286 | AD22: =SUM(O22:R22) -> 308 | AE22: =SUM(S22:V22) -> 246 | AF22: =SUM(W22:Z22) -> 279
A23: (Gain) Loss From Sale Of Assets | C23: -24 | D23: -46 | E23: -41 | F23: -278 | G23: -43 | H23: -6 | I23: -18 | J23: -95 | K23: -16 | L23: 0 | M23: -4 | N23: -40 | O23: -6 | P23: -6 | Q23: -49 | R23: -30 | S23: -42 | T23: 0 | U23: -32 | V23: -15 | W23: -11 | X23: -4 | Y23: -5 | Z23: -41 | AA23: =SUM(C23:F23) -> -389 | AB23: =SUM(G23:J23) -> -162 | AC23: =SUM(K23:N23) -> -60 | AD23: =SUM(O23:R23) -> -91 | AE23: =SUM(S23:V23) -> -89 | AF23: =SUM(W23:Z23) -> -61
A24: Asset Writedown & Restructuring Costs | C24: 19 | D24: 17 | E24: 3 | F24: 105 | G24: - | H24: 1 | I24: 5 | J24: 348 | K24: 3175 | L24: 183 | M24: 8 | N24: 138 | O24: 19 | P24: 2 | Q24: 0 | R24: -12 | S24: 8 | T24: 2 | U24: 15 | V24: -5 | W24: 2 | X24: 4 | Y24: 15 | Z24: 991 | AA24: =SUM(C24:F24) -> 144 | AB24: =SUM(G24:J24) -> 354 | AC24: =SUM(K24:N24) -> 3504 | AD24: =SUM(O24:R24) -> 9 | AE24: =SUM(S24:V24) -> 20 | AF24: =SUM(W24:Z24) -> 1012
A25: Stock-Based Compensation | C25: 17 | D25: 14 | E25: 17 | F25: 15 | G25: 14 | H25: 14 | I25: 12 | J25: -2 | K25: 6 | L25: 7 | M25: 8 | N25: 10 | O25: 11 | P25: 11 | Q25: 10 | R25: 23 | S25: 13 | T25: 17 | U25: 14 | V25: 10 | W25: 14 | X25: 16 | Y25: 15 | Z25: 2 | AA25: =SUM(C25:F25) -> 63 | AB25: =SUM(G25:J25) -> 38 | AC25: =SUM(K25:N25) -> 31 | AD25: =SUM(O25:R25) -> 55 | AE25: =SUM(S25:V25) -> 54 | AF25: =SUM(W25:Z25) -> 47
A26: Other Operating Activities | C26: 20 | D26: 74 | E26: 56 | F26: 62 | G26: 16 | H26: 18 | I26: 36 | J26: 13 | K26: -204 | L26: 68 | M26: 46 | N26: -31 | O26: -33 | P26: 97 | Q26: 72 | R26: 34 | S26: -12 | T26: -16 | U26: 5 | V26: 62 | W26: -30 | X26: 109 | Y26: 11 | Z26: -181 | AA26: =SUM(C26:F26) -> 212 | AB26: =SUM(G26:J26) -> 83 | AC26: =SUM(K26:N26) -> -121 | AD26: =SUM(O26:R26) -> 170 | AE26: =SUM(S26:V26) -> 39 | AF26: =SUM(W26:Z26) -> -91
A27: Change in Acc. Receivable | C27: 105 | D27: -17 | E27: 75 | F27: -224 | G27: 163 | H27: -3 | I27: 64 | J27: -233 | K27: 236 | L27: -14 | M27: 1 | N27: -91 | O27: 71 | P27: -16 | Q27: 9 | R27: -85 | S27: 65 | T27: 13 | U27: 15 | V27: -96 | W27: 45 | X27: 32 | Y27: 5 | Z27: -75 | AA27: =SUM(C27:F27) -> -61 | AB27: =SUM(G27:J27) -> -9 | AC27: =SUM(K27:N27) -> 132 | AD27: =SUM(O27:R27) -> -21 | AE27: =SUM(S27:V27) -> -3 | AF27: =SUM(W27:Z27) -> 7
A28: Change In Inventories | C28: -115 | D28: 336 | E28: -2190 | F28: 1882 | G28: -235 | H28: 469 | I28: -2227 | J28: 2068 | K28: 265 | L28: 1333 | M28: -1564 | N28: 1372 | O28: -457 | P28: -68 | Q28: -1842 | R28: 1757 | S28: -573 | T28: 346 | U28: -1792 | V28: 2135 | W28: -340 | X28: 478 | Y28: -1895 | Z28: 1658 | AA28: =SUM(C28:F28) -> -87 | AB28: =SUM(G28:J28) -> 75 | AC28: =SUM(K28:N28) -> 1406 | AD28: =SUM(O28:R28) -> -610 | AE28: =SUM(S28:V28) -> 116 | AF28: =SUM(W28:Z28) -> -99
A29: Change in Acc. Payable | C29: 415 | D29: -196 | E29: 1445 | F29: -1609 | G29: 247 | H29: -192 | I29: 1593 | J29: -1608 | K29: 629 | L29: -817 | M29: 1800 | N29: -2134 | O29: 674 | P29: -27 | Q29: 1111 | R29: -1295 | S29: 639 | T29: -994 | U29: 1691 | V29: -1639 | W29: -41 | X29: -430 | Y29: 1503 | Z29: -1411 | AA29: =SUM(C29:F29) -> 55 | AB29: =SUM(G29:J29) -> 40 | AC29: =SUM(K29:N29) -> -522 | AD29: =SUM(O29:R29) -> 463 | AE29: =SUM(S29:V29) -> -303 | AF29: =SUM(W29:Z29) -> -379
A30: Change in Inc. Taxes | C30: 25 | D30: -296 | E30: -30 | F30: 165 | G30: 8 | H30: -157 | I30: -19 | J30: 108 | K30: -353 | L30: -342 | M30: -123 | N30: 201 | O30: 75 | P30: -63 | Q30: -62 | R30: 638 | S30: 122 | T30: -194 | U30: -1 | V30: -2 | W30: 82 | X30: -203 | Y30: -3 | Z30: 127 | AA30: =SUM(C30:F30) -> -136 | AB30: =SUM(G30:J30) -> -60 | AC30: =SUM(K30:N30) -> -617 | AD30: =SUM(O30:R30) -> 588 | AE30: =SUM(S30:V30) -> -75 | AF30: =SUM(W30:Z30) -> 3
A31: Change in Other Net Operating Assets | C31: -514 | D31: -61 | E31: 240 | F31: 214 | G31: -580 | H31: -80 | I31: 122 | J31: 238 | K31: -558 | L31: -69 | M31: -86 | N31: 576 | O31: -195 | P31: -30 | Q31: 112 | R31: -112 | S31: -466 | T31: 396 | U31: -65 | V31: -54 | W31: 8 | X31: -31 | Y31: -34 | Z31: -29 | AA31: =SUM(C31:F31) -> -121 | AB31: =SUM(G31:J31) -> -300 | AC31: =SUM(K31:N31) -> -137 | AD31: =SUM(O31:R31) -> -225 | AE31: =SUM(S31:V31) -> -189 | AF31: =SUM(W31:Z31) -> -86
A32: Cash Flow from Operating | C32: =SUM(C22:C31)+C20+C18 -> 322 | D32: =SUM(D22:D31)+D20+D18 -> 222 | E32: =SUM(E22:E31)+E20+E18 -> -115 | F32: =SUM(F22:F31)+F20+F18 -> 1306 | G32: =SUM(G22:G31)+G20+G18 -> -38 | H32: =SUM(H22:H31)+H20+H18 -> 388 | I32: =SUM(I22:I31)+I20+I18 -> -178 | J32: =SUM(J22:J31)+J20+J18 -> 1436 | ... AF32: =SUM(AF22:AF31)+AF20+AF18 -> 1305
A34: Capital Expenditure | C34: -132 | D34: -143 | E34: -193 | F34: -189 | G34: -204 | H34: -174 | I34: -245 | J34: -279 | K34: -122 | L34: -106 | M34: -62 | N34: -48 | O34: -61 | P34: -81 | Q34: -88 | R34: -124 | S34: -171 | T34: -207 | U34: -277 | V34: -233 | W34: -215 | X34: -175 | Y34: -95 | Z34: -146 | AA34: =SUM(C34:F34) -> -657 | AB34: =SUM(G34:J34) -> -902 | AC34: =SUM(K34:N34) -> -338 | AD34: =SUM(O34:R34) -> -354 | AE34: =SUM(S34:V34) -> -888 | AF34: =SUM(W34:Z34) -> -631
A35: Sale of Property, Plant, and Equipment | C35: 23 | D35: 65 | E35: 33 | F35: 353 | G35: 34 | H35: 25 | I35: 14 | J35: 112 | K35: 21 | L35: 10 | M35: 8 | N35: 74 | O35: 8 | P35: 26 | Q35: 84 | R35: 46 | S35: 73 | T35: 0 | U35: 49 | V35: 15 | W35: 25 | X35: 7 | Y35: 4 | Z35: 50 | AA35: =SUM(C35:F35) -> 474 | AB35: =SUM(G35:J35) -> 185 | AC35: =SUM(K35:N35) -> 113 | AD35: =SUM(O35:R35) -> 164 | AE35: =SUM(S35:V35) -> 137 | AF35: =SUM(W35:Z35) -> 86
A36: Cash Acquisitions | C36: - | D36: - | E36: - | F36: - | G36: - | H36: - | I36: - | J36: - | K36: - | L36: - | M36: - | N36: - | O36: - | P36: - | Q36: - | R36: - | S36: - | T36: - | U36: - | V36: - | W36: - | X36: - | Y36: - | Z36: - | AA36: =SUM(C36:F36) -> 0 | AB36: =SUM(G36:J36) -> 0 | AC36: =SUM(K36:N36) -> 0 | AD36: =SUM(O36:R36) -> 0 | AE36: =SUM(S36:V36) -> 0 | AF36: =SUM(W36:Z36) -> 0
A37: Divestitures | C37: - | D37: - | E37: - | F37: - | G37: - | H37: - | I37: - | J37: - | K37: - | L37: - | M37: - | N37: - | O37: - | P37: - | Q37: - | R37: - | S37: - | T37: - | U37: - | V37: - | W37: - | X37: - | Y37: - | Z37: - | AA37: =SUM(C37:F37) -> 0 | AB37: =SUM(G37:J37) -> 0 | AC37: =SUM(K37:N37) -> 0 | AD37: =SUM(O37:R37) -> 0 | AE37: =SUM(S37:V37) -> 0 | AF37: =SUM(W37:Z37) -> 0
A38: Sale (Purchase) of Intangible assets | C38: -58 | D38: -75 | E38: -76 | F38: -66 | G38: -60 | H38: -63 | I38: -66 | J38: -66 | K38: -38 | L38: -23 | M38: -35 | N38: -32 | O38: -38 | P38: -50 | Q38: -67 | R38: -88 | S38: -90 | T38: -114 | U38: -124 | V38: -79 | W38: -81 | X38: -93 | Y38: -90 | Z38: -98 | AA38: =SUM(C38:F38) -> -275 | AB38: =SUM(G38:J38) -> -255 | AC38: =SUM(K38:N38) -> -128 | AD38: =SUM(O38:R38) -> -243 | AE38: =SUM(S38:V38) -> -407 | AF38: =SUM(W38:Z38) -> -362
A39: Invest. in Marketable & Equity Securt. | C39: - | D39: - | E39: - | F39: - | G39: - | H39: - | I39: - | J39: - | K39: - | L39: - | M39: - | N39: - | O39: - | P39: - | Q39: - | R39: - | S39: - | T39: - | U39: - | V39: - | W39: - | X39: - | Y39: - | Z39: - | AA39: =SUM(C39:F39) -> 0 | AB39: =SUM(G39:J39) -> 0 | AC39: =SUM(K39:N39) -> 0 | AD39: =SUM(O39:R39) -> 0 | AE39: =SUM(S39:V39) -> 0 | AF39: =SUM(W39:Z39) -> 0
A40: Net (Inc.) Dec. in Loans Originated/Sold | C40: - | D40: - | E40: - | F40: - | G40: - | H40: - | I40: - | J40: - | K40: - | L40: - | M40: - | N40: - | O40: - | P40: - | Q40: - | R40: - | S40: - | T40: - | U40: - | V40: - | W40: - | X40: - | Y40: - | Z40: - | AA40: =SUM(C40:F40) -> 0 | AB40: =SUM(G40:J40) -> 0 | AC40: =SUM(K40:N40) -> 0 | AD40: =SUM(O40:R40) -> 0 | AE40: =SUM(S40:V40) -> 0 | AF40: =SUM(W40:Z40) -> 0
A41: Other Investing Activities | C41: 11 | D41: -3 | E41: -1 | F41: -5 | G41: -7 | H41: -5 | I41: 22 | J41: -40 | K41: 26 | L41: -40 | M41: 47 | N41: -5 | O41: 17 | P41: 35 | Q41: 12 | R41: -1 | S41: -6 | T41: 0 | U41: -2 | V41: -3 | W41: 1 | X41: 0 | Y41: -4 | Z41: -3 | AA41: =SUM(C41:F41) -> 2 | AB41: =SUM(G41:J41) -> -30 | AC41: =SUM(K41:N41) -> 28 | AD41: =SUM(O41:R41) -> 63 | AE41: =SUM(S41:V41) -> -11 | AF41: =SUM(W41:Z41) -> -6
A42: Cash Flow from Investing | C42: =SUM(C34:C41) -> -156 | D42: =SUM(D34:D41) -> -156 | E42: =SUM(E34:E41) -> -237 | F42: =SUM(F34:F41) -> 93 | G42: =SUM(G34:G41) -> -237 | H42: =SUM(H34:H41) -> -217 | I42: =SUM(I34:I41) -> -275 | J42: =SUM(J34:J41) -> -273 | ... AF42: =SUM(AF34:AF41) -> -913
A44: Total Debt Issued | C44: - | D44: - | E44: 44 | F44: -28 | G44: - | H44: - | I44: 49 | J44: -49 | K44: 1500 | L44: 1280 | M44: 0 | N44: 181 | O44: 500 | P44: 0 | Q44: 475 | R44: 110 | S44: 850 | T44: 0 | U44: 1041 | V44: 918 | W44: - | X44: - | Y44: 387 | Z44: 576 | AA44: =SUM(C44:F44) -> 16 | AB44: =SUM(G44:J44) -> 0 | AC44: =SUM(K44:N44) -> 2961 | AD44: =SUM(O44:R44) -> 1085 | AE44: =SUM(S44:V44) -> 2809 | AF44: =SUM(W44:Z44) -> 963
A45: Total Debt Repaid | C45: -13 | D45: -434 | E45: 86 | F45: -788 | G45: -48 | H45: -119 | I45: 125 | J45: -617 | K45: -235 | L45: -1380 | M45: 17 | N45: -444 | O45: -779 | P45: -57 | Q45: -1709 | R45: -177 | S45: -1265 | T45: -47 | U45: -803 | V45: -1166 | W45: -14 | X45: -22 | Y45: -117 | Z45: -810 | AA45: =SUM(C45:F45) -> -1149 | AB45: =SUM(G45:J45) -> -659 | AC45: =SUM(K45:N45) -> -2042 | AD45: =SUM(O45:R45) -> -2722 | AE45: =SUM(S45:V45) -> -3281 | AF45: =SUM(W45:Z45) -> -963
A47: Issuance of Common Stock | C47: 28 | D47: 10 | E47: 3 | F47: 4 | G47: 6 | H47: 0 | I47: 0 | J47: 0 | K47: - | L47: - | M47: - | N47: - | O47: - | P47: - | Q47: - | R47: 7 | S47: - | T47: - | U47: - | V47: - | W47: - | X47: - | Y47: - | Z47: - | AA47: =SUM(C47:F47) -> 45 | AB47: =SUM(G47:J47) -> 6 | AC47: =SUM(K47:N47) -> 0 | AD47: =SUM(O47:R47) -> 7 | AE47: =SUM(S47:V47) -> 0 | AF47: =SUM(W47:Z47) -> 0
A48: Repurchase of Common Stock | C48: - | D48: - | E48: - | F48: - | G48: - | H48: - | I48: -1 | J48: 0 | K48: - | L48: - | M48: - | N48: -1 | O48: - | P48: - | Q48: -294 | R48: -206 | S48: -584 | T48: -17 | U48: 0 | V48: 0 | W48: -35 | X48: -3 | Y48: 0 | Z48: 0 | AA48: =SUM(C48:F48) -> 0 | AB48: =SUM(G48:J48) -> -1 | AC48: =SUM(K48:N48) -> -1 | AD48: =SUM(O48:R48) -> -500 | AE48: =SUM(S48:V48) -> -601 | AF48: =SUM(W48:Z48) -> -38
A50: Common Dividends Paid | C50: -116 | D50: -116 | E50: -115 | F50: -116 | G50: -116 | H50: -117 | I50: -116 | J50: -117 | K50: -117 | L50: 0 | M50: 0 | N50: 0 | O50: 0 | P50: 0 | Q50: -46 | R50: -44 | S50: -45 | T50: -42 | U50: -43 | V50: -43 | W50: -45 | X50: -45 | Y50: -45 | Z50: -46 | AA50: =SUM(C50:F50) -> -463 | AB50: =SUM(G50:J50) -> -466 | AC50: =SUM(K50:N50) -> -117 | AD50: =SUM(O50:R50) -> -90 | AE50: =SUM(S50:V50) -> -173 | AF50: =SUM(W50:Z50) -> -181
A51: Total Dividends Paid | C51: =C50 -> -116 | D51: =D50 -> -116 | E51: =E50 -> -115 | F51: =F50 -> -116 | G51: =G50 -> -116 | H51: =H50 -> -117 | I51: =I50 -> -116 | J51: =J50 -> -117 | ... AF51: =AF50 -> -181
A53: Special Dividend Paid | C53: - | D53: - | E53: - | F53: - | G53: - | H53: - | I53: - | J53: - | K53: - | L53: - | M53: - | N53: - | O53: - | P53: - | Q53: - | R53: - | S53: - | T53: - | U53: - | V53: - | W53: - | X53: - | Y53: - | Z53: - | AA53: =SUM(C53:F53) -> 0 | AB53: =SUM(G53:J53) -> 0 | AC53: =SUM(K53:N53) -> 0 | AD53: =SUM(O53:R53) -> 0 | AE53: =SUM(S53:V53) -> 0 | AF53: =SUM(W53:Z53) -> 0
A54: Other Financing Activities | C54: 2 | D54: 3 | E54: 2 | F54: 0 | G54: - | H54: -3 | I54: 0 | J54: 0 | K54: - | L54: -98 | M54: -4 | N54: 0 | O54: -21 | P54: -3 | Q54: -137 | R54: 0 | S54: -50 | T54: 0 | U54: 0 | V54: 0 | W54: - | X54: - | Y54: -1 | Z54: 0 | AA54: =SUM(C54:F54) -> 7 | AB54: =SUM(G54:J54) -> -3 | AC54: =SUM(K54:N54) -> -102 | AD54: =SUM(O54:R54) -> -161 | AE54: =SUM(S54:V54) -> -50 | AF54: =SUM(W54:Z54) -> -1
A55: Cash Flow from Financing | C55: =SUM(C44:C45)+SUM(C47:C48)+C51+SUM(C53:C54) -> -99 | D55: =SUM(D44:D45)+SUM(D47:D48)+D51+SUM(D53:D54) -> -537 | E55: =SUM(E44:E45)+SUM(E47:E48)+E51+SUM(E53:E54) -> 20 | F55: =SUM(F44:F45)+SUM(F47:F48)+F51+SUM(F53:F54) -> -928 | G55: =SUM(G44:G45)+SUM(G47:G48)+G51+SUM(G53:G54) -> -158 | H55: =SUM(H44:H45)+SUM(H47:H48)+H51+SUM(H53:H54) -> -239 | I55: =SUM(I44:I45)+SUM(I47:I48)+I51+SUM(I53:I54) -> 57 | J55: =SUM(J44:J45)+SUM(J47:J48)+J51+SUM(J53:J54) -> -783 | ... AF55: =SUM(AF44:AF45)+SUM(AF47:AF48)+AF51+SUM(AF53:AF54) -> -220
A57: Net Change in Cash | C57: =C32+C42+C55 -> 67 | D57: =D32+D42+D55 -> -471 | E57: =E32+E42+E55 -> -332 | F57: =F32+F42+F55 -> 471 | G57: =G32+G42+G55 -> -433 | H57: =H32+H42+H55 -> -68 | I57: =I32+I42+I55 -> -396 | J57: =J32+J42+J55 -> 380 | ... AF57: =AF32+AF42+AF55 -> 172

Sheet Relative Valuation
B3: Company Name | C3: LTM EV/Revenue | D3: LTM EV/ EBITDA | E3: LTM/ EBIT | F3: NTM EV/Forward Revenue | G3: NTM EV/ EBITDA
B4: The TJX Companies, Inc. (NYSE:TJX) | C4: 2.523192 | D4: 19.201607 | E4: 22.565392 | F4: 2.41 | G4: 18.15
B5: Kohl's Corporation (NYSE:KSS) | C5: 0.49587572 | D5: 6.4815471 | E5: 16.151807 | F5: 0.55 | G5: 7.31
B6: The Gap, Inc. (NYSE:GAP) | C6: 0.72715763 | D6: 6.7925077 | E6: 9.8384753 | F6: 0.72 | G6: 6.32
B7: Nordstrom, Inc. (NYSE:JWN) | C7: 0.48716702 | D7: 6.3666667 | E7: 13.397985 | F7: 0.48 | G7: 6.27
B8: Dillard's, Inc. (NYSE:DDS) | C8: 0.81276744 | D8: 5.8341139 | E8: 7.2362875 | F8: 0.83 | G8: 7.08
B9: Macy's, Inc. (NYSE:M) | C9: 0.37113796 | D9: 5.7536388 | E9: 9.3520263 | F9: 0.4 | G9: 4.69
B11: Mean | C11: =AVERAGE(C4:C9) -> 0.90288296 | D11: =AVERAGE(D4:D9) -> 8.4050135 | E11: =AVERAGE(E4:E9) -> 13.090329 | F11: =AVERAGE(F4:F9) -> 0.89833333 | G11: =AVERAGE(G4:G9) -> 8.3033333
B12: Median | C12: =MEDIAN(C4:C9) -> 0.61151667 | D12: =MEDIAN(D4:D9) -> 6.4241069 | E12: =MEDIAN(E4:E9) -> 11.61823 | F12: =MEDIAN(F4:F9) -> 0.635 | G12: =MEDIAN(G4:G9) -> 6.7
B13: 25th quartile | C13: =QUARTILE(C4:C9,1) -> 0.4893442 | D13: =QUARTILE(D4:D9,1) -> 5.9672521 | E13: =QUARTILE(E4:E9,1) -> 9.4736385 | F13: =QUARTILE(F4:F9,1) -> 0.4975 | G13: =QUARTILE(G4:G9,1) -> 6.2825
B14: 75th quartile | C14: =QUARTILE(C5:C10,3) -> 0.72715763 | D14: =QUARTILE(D5:D10,3) -> 6.4815471 | E14: =QUARTILE(E5:E10,3) -> 13.397985 | F14: =QUARTILE(F5:F10,3) -> 0.72 | G14: =QUARTILE(G5:G10,3) -> 7.08
B18: Company Name | C18: LTM EPS | D18: Stock Price (as of 26/3/2025) | E18: LTM P/E | F18: NTM Forward P/E | G18: 5 Year Beta
B19: The TJX Companies, Inc. (NYSE:TJX) | C19: 4.3 | D19: 119.88 | E19: 27.87907 | F19: 26.6 | G19: 0.96
B20: Kohl's Corporation (NYSE:KSS) | C20: 1.5 | D20: 9.15 | E20: 6.1 | F20: 23.07 | G20: 1.96
B21: The Gap, Inc. (NYSE:GAP) | C21: 2.2 | D21: 21.56 | E21: 9.8 | F21: 8.97 | G21: 2.37
B22: Nordstrom, Inc. (NYSE:JWN) | C22: 2.1 | D22: 24.37 | E22: 11.604762 | F22: 11.11 | G22: 2.61
B23: Dillard's, Inc. (NYSE:DDS) | C23: 36.8 | D23: 367.49 | E23: 9.9861413 | F23: 12.85 | G23: 0.93
B24: Macy's, Inc. (NYSE:M) | C24: 2.3 | D24: 13.58 | E24: 5.9043478 | F24: 6.42 | G24: 1.47
B26: Mean | E26: =AVERAGE(E19:E24) -> 11.879053 | F26: =AVERAGE(F19:F24) -> 14.836667 | G26: =AVERAGE(G19:G24) -> 1.7166667
B27: Median | E27: =MEDIAN(E19:E24) -> 9.8930707 | F27: =MEDIAN(F19:F24) -> 11.98 | G27: =MEDIAN(G19:G24) -> 1.715
B28: 25th quartile | E28: =QUARTILE(E19:E24,1) -> 7.025 | F28: =QUARTILE(F19:F24,1) -> 9.505 | G28: =QUARTILE(G19:G24,1) -> 1.0875
B29: 75th quartile | E29: =QUARTILE(E20:E25,3) -> 9.9861413 | F29: =QUARTILE(F20:F25,3) -> 12.85 | G29: =QUARTILE(G20:G25,3) -> 2.37

Sheet Comparables' info
A4: Macy's, Inc. (NYSE:M) > Quick Comparable Analysis > Business Description
A7: Details
A8: Template: | B8: Capital IQ Default Comps
A9: Currency: | B9: US Dollar
A10: As-Of Date: | B10: 45742
A13: Company Comp Set
A14: Company Name | B14: Business Description | C14: Headquarters
A15: The TJX Companies, Inc. (NYSE:TJX) | B15: The TJX Companies, Inc., together with its subsidiaries, operates as an off-price apparel and home fashions retailer in the United States, Canada, Europe, and Australia. It operates through four segments: Marmaxx, HomeGoods, TJX Canada, and TJX International. The company sells family apparel, including footwear and accessories; home fashions, such as home basics, furniture, rugs, lighting products, giftware, soft home products, decorative accessories, tabletop, and cookware, as well as expanded pet, and gourmet food departments; jewelry and accessories; and other merchandise. It offers its products through stores and e-commerce sites. The TJX Companies, Inc. was incorporated in 1962 and is headquartered in Framingham, Massachusetts. | C15: 770 Cochituate Road, Framingham, Massachusetts, 01701, United States
A16: Kohl's Corporation (NYSE:KSS) | B16: Kohl's Corporation operates as an omnichannel retailer in the United States. It offers branded apparel, footwear, accessories, beauty, and home products through its stores and website. The company provides its products primarily under the brand names of Apt. 9, Croft & Barrow, Jumping Beans, SO, Sonoma Goods for Life, and Tek Gear, as well as LC Lauren Conrad, Nine West, and Simply Vera Vera Wang. Kohl's Corporation was founded in 1988 and is headquartered in Menomonee Falls, Wisconsin. | C16: N56 W17000 Ridgewood Drive, Menomonee Falls, Wisconsin, 53051, United States
A17: The Gap, Inc. (NYSE:GAP) | B17: The Gap, Inc. operates as an apparel retail company. The company offers apparel, accessories, and personal care products for men, women, and children under the Old Navy, Gap, Banana Republic, and Athleta brands. Its products include adult apparel and accessories; and lifestyle products for use in yoga, training, travel, and recovery activities for women and girls. The company offers its products through company-operated stores, franchise stores, websites, and third-party arrangements, as well as licensing partnerships. It has franchise agreements to operate Old Navy, Gap, Banana Republic, and Athleta in Asia, Europe, Latin America, the Middle East, and Africa. The Gap, Inc. was incorporated in 1969 and is headquartered in San Francisco, California. | C17: Two Folsom Street, San Francisco, California, 94105, United States
A18: Nordstrom, Inc. (NYSE:JWN) | B18: Nordstrom, Inc. operates as a fashion retailer in the United States. The company provides apparel, shoes, beauty, accessories, and home goods for women, men, young adults, and children. It also offers a range of third-party and private-label merchandise through various channels, such as Nordstrom stores, and Nordstrom.com website and mobile application; Nordstrom Rack stores; Nordstrom Locals; NordstromRack.com website and mobile application; and clearance stores under the Last Chance name. Nordstrom, Inc. was founded in 1901 and is headquartered in Seattle, Washington. | C18: 1617 Sixth Avenue, Seattle, Washington, 98101-1707, United States
A19: Dillard's, Inc. (NYSE:DDS) | B19: Dillard's, Inc. operates retail department stores in the southeastern, southwestern, and midwestern areas of the United States. The company’s stores offer merchandise, including fashion apparel for women, men, and children; and accessories, cosmetics, home furnishings, and other consumer goods. It also engages in the general contracting construction activities. Dillard's, Inc. was founded in 1938 and is based in Little Rock, Arkansas. | C19: 1600 Cantrell Road, Little Rock, Arkansas, 72201, United States
A22: Macy's, Inc. (NYSE:M) | B22: Macy's, Inc., an omni-channel retail organization, operates stores, websites, and mobile applications in the United States. It sells a range of merchandise, such as apparel and accessories for men, women, and kids; cosmetics; home furnishings; and other consumer goods under the Macy's, Bloomingdale's, and Bluemercury brands. The company also operates in Dubai, the United Arab Emirates, and Al Zahra, Kuwait under the license agreements. The company was formerly known as Federated Department Stores, Inc. and changed its name to Macy's, Inc. in June 2007. Macy's, Inc. was founded in 1830 and is based in New York, New York. | C22: 151 West 34th Street, New York, New York, 10001, United States
A25: Displaying 64 Companies.
A30: Values converted at today's spot rate.
A31: Companies by default are sorted by S&P Capital IQ’s proprietary relevancy score.
A39: Historical Equity Pricing Data supplied by Interactive Data Pricing and Reference Data LLC

Sheet Other stuff

Sheet Segments
A2: Macy's Inc (M US) - By Measure
A4: In Millions of USD except Per Share | C4: FY 2016 | E4: FY 2017 | G4: FY 2018 | I4: FY 2019 | K4: FY 2020 | M4: FY 2021 | O4: FY 2022 | Q4: FY 2023 | S4: FY 2024 | U4: FY 2025
A5: 12 Months Ending | C5: 01/30/2016 | E5: 01/28/2017 | G5: 02/03/2018 | I5: 02/02/2019 | K5: 02/01/2020 | M5: 01/30/2021 | O5: 01/29/2022 | Q5: 01/28/2023 | S5: 02/03/2024 | U5: 02/01/2025
A6: Revenue | C6: 27079 | D6: 1 | E6: 25778 | F6: 1 | G6: 25641 | H6: 1 | I6: 25739 | J6: 1 | K6: 25331 | L6: 1 | M6: 18097 | N6: 1 | O6: 25292 | P6: 1 | Q6: 25449 | R6: 1 | S6: 23866 | T6: 1 | U6: 23006 | V6: 1
A7: Non Credit Card | C7: 0 | E7: 0 | G7: 24939 | H7: 0.97262197 | I7: 24971 | J7: 0.97016201 | K7: 24560 | L7: 0.96956299 | M7: 17346 | N7: 0.95850141 | O7: 24460 | P7: 0.96710422 | Q7: 24442 | R7: 0.96043067 | S7: 23092 | T7: 0.96756893 | U7: 22293 | V7: 0.96900808
A8: Women’s Accessories, Intimate Apparel, Shoes and Cosmetics | C8: 10290.02 | D8: 0.38 | E8: 9845.8 | F8: 0.38194585 | G8: 9444 | H8: 0.36831637 | I8: 9457 | J8: 0.36741909 | K8: 9454 | L8: 0.37321859 | M8: 7206 | N8: 0.39818754 | O8: 10119 | P8: 0.40008698 | Q8: 9597 | R8: 0.37710716 | S8: 9520 | T8: 0.39889382 | U8: 0
A9: Men’s and Kids | C9: 4332.64 | D9: 0.16 | E9: 4013.6 | F9: 0.15569866 | G9: 5610 | H9: 0.21879022 | I9: 5699 | J9: 0.22141497 | K9: 5628 | L9: 0.22217836 | M9: 3486 | N9: 0.19262861 | O9: 5252 | P9: 0.20765459 | Q9: 5297 | R9: 0.20814177 | S9: 4918 | T9: 0.20606721 | U9: 0
A10: Women’s Apparel | C10: 6228.17 | D10: 0.23 | E10: 5959.3 | F10: 0.23117775 | G10: 5765 | H10: 0.22483522 | I10: 5642 | J10: 0.21920044 | K10: 5411 | L10: 0.21361178 | M10: 2909 | N10: 0.16074487 | O10: 4433 | P10: 0.17527281 | Q10: 5349 | R10: 0.21018508 | S10: 4861 | T10: 0.20367887 | U10: 0
A11: Home/Other | C11: 6228.17 | D11: 0.23 | E11: 5959.3 | F11: 0.23117775 | G11: 4120 | H11: 0.16068016 | I11: 4173 | J11: 0.16212751 | K11: 4067 | L11: 0.16055426 | M11: 3745 | N11: 0.20694038 | O11: 4656 | P11: 0.18408983 | Q11: 4199 | R11: 0.16499666 | S11: 3793 | T11: 0.15892902 | U11: 0
A12: Credit Card | C12: 0 | E12: 0 | G12: 702 | H12: 0.027378027 | I12: 768 | J12: 0.029837989 | K12: 771 | L12: 0.030437014 | M12: 751 | N12: 0.041498591 | O12: 832 | P12: 0.032895777 | Q12: 863 | R12: 0.033910959 | S12: 619 | T12: 0.025936479 | U12: 537 | V12: 0.023341737
A13: Macy's Media Network | C13: 0 | E13: 0 | G13: 0 | I13: 0 | K13: 0 | M13: 0 | O13: 0 | Q13: 144 | R13: 0.0056583756 | S13: 155 | T13: 0.0064945948 | U13: 176 | V13: 0.0076501782
A14: Department Stores | C14: 27079 | D14: 1 | E14: 25778 | F14: 1 | G14: 0 | I14: 0 | K14: 0 | M14: 0 | O14: 0 | Q14: 0 | S14: 0 | U14: 0
A15: Percentage of Revenue | C15: 0 | E15: 0 | G15: 0 | I15: 0 | K15: 0 | M15: 0 | O15: 0 | Q15: 0 | S15: 0 | U15: 0
A16: Bloomingdale's | C16: 0 | E16: 0 | G16: 0 | I16: 10 | K16: 11 | M16: 0 | O16: 0 | Q16: 0 | S16: 0 | U16: 0
A17: Bloomingdale's Digital | C17: 0 | E17: 0 | G17: 0 | I17: 2 | K17: 3 | M17: 0 | O17: 0 | Q17: 0 | S17: 0 | U17: 0
A18: Bloomingdale's Stores | C18: 0 | E18: 0 | G18: 0 | I18: 8 | K18: 8 | M18: 0 | O18: 0 | Q18: 0 | S18: 0 | U18: 0
A19: Macy's | C19: 0 | E19: 0 | G19: 0 | I19: 89 | K19: 88 | M19: 0 | O19: 0 | Q19: 0 | S19: 0 | U19: 0
