Workbook
Name IQ_CH: 110000
Name IQ_CQ: 5000
Name IQ_CY: 10000
Name IQ_DAILY: 500000
Name IQ_FH: 100000
Name IQ_FQ: 500
Name IQ_FY: 1000
Name IQ_LTM: 2000
Name IQ_MONTH: 15000
Name IQ_NTM: 6000
Name IQ_WEEK: 50000
Name IQ_YTD: 3000

Sheet Output
F3: Drivers set to | H3: 1
C6: Valuation Summary
D8: Equity Value | F8: Low | G8: Med | H8: High
D9: DCF - EV/EBITDA | F9: =MIN(F56:H58) -> 2.0181311e+08 | G9: =G46+O35 -> 2.2430205e+08 | H9: =MAX(F45:H47)+O35 -> 2.4773805e+08
D10: DCF - EV/EBIT | F10: =MIN(DCF!F201:H203)+O35 -> 2.88114e+08 | G10: =DCF!G202 -> 3.2206483e+08 | H10: =MAX(DCF!F201:H203)+O35 -> 3.3728752e+08
D11: DCF - EV/Sales | F11: =MIN(DCF!F194:H196)+O35 -> 1.2747693e+08 | G11: =DCF!G195+O35 -> 1.414094e+08 | H11: =MAX(DCF!F194:H196)+O35 -> 1.5593122e+08
D12: DCF - Perpetuity | F12: =MIN(F77:H79)+O35 -> 2.7428634e+08 | G12: =G78+O35 -> 3.069946e+08 | H12: =MAX(F77:H79)+O35 -> 3.4803423e+08
D13: Trading Comps | F13: =DCF!E169 -> 60907755 | G13: =DCF!E163 -> 90668714 | H13: =DCF!E175 -> 1.211517e+08
D15: Percentiles | F15: Low | G15: Med | H15: High
C16: 2 | D16: DCF - EV/EBITDA | F16: =F9/$O$36 -> 452.96854 | G16: =(G9-F9)/O36 -> 50.476308 | H16: =(H9-G9)/$O$36 -> 52.601979 | I16: 2
C17: 3 | D17: DCF - EV/EBIT | F17: =F10/$O$36 -> 646.67047 | G17: =(G10-F10)/O36 -> 76.202462 | H17: =(H10-G10)/$O$36 -> 34.167257 | I17: 3
C18: 4 | D18: DCF - EV/Sales | F18: =F11/O36 -> 286.12134 | G18: =(G11-F11)/O36 -> 31.271361 | H18: =(H11-G11)/$O$36 -> 32.59416 | I18: 4
C19: 1 | D19: DCF - Perpetuity | F19: =F12/O36 -> 615.63435 | G19: =(G12-F12)/O36 -> 73.413521 | H19: =(H12-G12)/$O$36 -> 92.113244 | I19: 1
C20: 5 | D20: Trading Comps | F20: =F13/O36 -> 136.70716 | G20: =(G13-F13)/O36 -> 66.798325 | H20: =(H13-G13)/$O$36 -> 68.418909 | I20: 5
D22: Sorted EV | F22: Low | G22: Med | H22: High
C23: {=_xlfn._xlws.SORT(C16:D20,1,-1)} -> 5 | D23: Trading Comps | F23: {=_xlfn._xlws.SORT(F16:I20,4,-1)} -> 136.70716 | G23: 66.798325 | H23: 68.418909 | I23: 5 | J23: =SUM(F23:H23) -> 271.92439
C24: 4 | D24: DCF - EV/Sales | F24: 286.12134 | G24: 31.271361 | H24: 32.59416 | I24: 4 | J24: =SUM(F24:H24) -> 349.98686
C25: 3 | D25: DCF - EV/EBIT | F25: 646.67047 | G25: 76.202462 | H25: 34.167257 | I25: 3 | J25: =SUM(F25:H25) -> 757.04019
C26: 2 | D26: DCF - EV/EBITDA | F26: 452.96854 | G26: 50.476308 | H26: 52.601979 | I26: 2 | J26: =SUM(F26:H26) -> 556.04683
C27: 1 | D27: DCF - Perpetuity | F27: 615.63435 | G27: 73.413521 | H27: 92.113244 | I27: 1 | J27: =SUM(F27:H27) -> 781.16111
C29: Dashboard: Multiples Method (EV/EBITDA)
E31: Main Outputs | M31: Selected Inputs
G32: Enterprise | H32: Equity | I32: Equity | M32: Valuation Date | O32: =DCF!D65 -> 45383
G33: Value | H33: Value | I33: Per Share | M33: Terminal Multiple | O33: =DCF!D95 -> 9.48
G34: =DCF!D178 -> 2.3341836e+08 | M34: WACC | O34: =DCF!D101 -> 0.090421772
E35: Base Case | F35: 1 | G35: 2.3341836e+08 | H35: =G35+$O$35 -> 2.235619e+08 | I35: =H35/$O$36 -> 501.78358 | M35: Net Debt | O35: =DCF!E151 -> -9856461
E36: Bull Case | F36: 2 | G36: 2.7099062e+08 | H36: =G36+$O$35 -> 2.6113416e+08 | I36: =H36/$O$36 -> 586.11435 | M36: Shares Outstanding | O36: =AVERAGE('Financial Statements'!AF32:AF33) -> 445534.5
E37: Bear Case | F37: 3 | G37: 2.1925023e+08 | H37: =G37+$O$35 -> 2.0939377e+08 | I37: =H37/$O$36 -> 469.98329 | M37: Actual Stock Price | O37: 607.33
E40: Enterprise Value | M40: Equity Value per Share
E42: Terminal Multiple | M42: Terminal Multiple
D43: =DCF!E142 -> 2.3086839e+08 | E43: =DCF!E178 -> 7.5 | F43: =DCF!F178 -> 8.5 | G43: =DCF!G178 -> 9.5 | H43: =DCF!H178 -> 10.5 | I43: =DCF!I178 -> 11.5 | M43: =E43 -> 7.5 | N43: =F43 -> 8.5 | O43: =G43 -> 9.5 | P43: =H43 -> 10.5 | Q43: =I43 -> 11.5
C44: WACC | D44: =DCF!D179 -> 0.08 | E44: =DCF!E179 -> 2.0431305e+08 | F44: =DCF!F179 -> 2.2373868e+08 | G44: =DCF!G179 -> 2.4316432e+08 | H44: =DCF!H179 -> 2.6258995e+08 | I44: =DCF!I179 -> 2.8201559e+08 | K44: WACC | L44: =D44 -> 0.08 | M44: =E55/$O$36 -> 436.45685 | N44: =F55/$O$36 -> 480.05759 | O44: =G55/$O$36 -> 523.65834 | P44: =H55/$O$36 -> 567.25908 | Q44: =I55/$O$36 -> 610.85983
D45: =DCF!D180 -> 0.085 | E45: =DCF!E180 -> 2.006152e+08 | F45: =DCF!F180 -> 2.196083e+08 | G45: =DCF!G180 -> 2.3860141e+08 | H45: =DCF!H180 -> 2.5759451e+08 | I45: =DCF!I180 -> 2.7658761e+08 | L45: =D45 -> 0.085 | M45: =E56/$O$36 -> 428.15706 | N45: =F56/$O$36 -> 470.78699 | O45: =G56/$O$36 -> 513.41691 | P45: =H56/$O$36 -> 556.04683 | Q45: =I56/$O$36 -> 598.67675
D46: =DCF!D181 -> 0.09 | E46: =DCF!E181 -> 1.9701426e+08 | F46: =DCF!F181 -> 2.1558638e+08 | G46: =DCF!G181 -> 2.3415851e+08 | H46: =DCF!H181 -> 2.5273063e+08 | I46: =DCF!I181 -> 2.7130276e+08 | L46: =D46 -> 0.09 | M46: =E57/$O$36 -> 420.07476 | N46: =F57/$O$36 -> 461.7598 | O46: =G57/$O$36 -> 503.44485 | P46: =H57/$O$36 -> 545.12989 | Q46: =I57/$O$36 -> 586.81494
D47: =DCF!D182 -> 0.095 | E47: =DCF!E182 -> 1.9350722e+08 | F47: =DCF!F182 -> 2.1166957e+08 | G47: =DCF!G182 -> 2.2983192e+08 | H47: =DCF!H182 -> 2.4799427e+08 | I47: =DCF!I182 -> 2.6615662e+08 | L47: =D47 -> 0.095 | M47: =E58/$O$36 -> 412.20323 | N47: =F58/$O$36 -> 452.96854 | O47: =G58/$O$36 -> 493.73384 | P47: =H58/$O$36 -> 534.49915 | Q47: =I58/$O$36 -> 575.26445
D48: =DCF!D183 -> 0.1 | E48: =DCF!E183 -> 1.9009122e+08 | F48: =DCF!F183 -> 2.0785464e+08 | G48: =DCF!G183 -> 2.2561807e+08 | H48: =DCF!H183 -> 2.433815e+08 | I48: =DCF!I183 -> 2.6114492e+08 | L48: =D48 -> 0.1 | M48: =E59/$O$36 -> 404.53602 | N48: =F59/$O$36 -> 444.40595 | O48: =G59/$O$36 -> 484.27587 | P48: =H59/$O$36 -> 524.1458 | Q48: =I59/$O$36 -> 564.01572
E51: Equity Value | M51: Premium (Discount) to Stock Price
E53: Terminal Multiple | M53: Terminal Multiple
D54: =DCF!E157 -> 592.95658 | E54: =E43 -> 7.5 | F54: =F43 -> 8.5 | G54: =G43 -> 9.5 | H54: =H43 -> 10.5 | I54: =I43 -> 11.5 | M54: =E43 -> 7.5 | N54: =F43 -> 8.5 | O54: =G43 -> 9.5 | P54: =H43 -> 10.5 | Q54: =I43 -> 11.5
C55: WACC | D55: =D44 -> 0.08 | E55: =E44+$O$35 -> 1.9445658e+08 | F55: =F44+$O$35 -> 2.1388222e+08 | G55: =G44+$O$35 -> 2.3330786e+08 | H55: =H44+$O$35 -> 2.5273349e+08 | I55: =I44+$O$35 -> 2.7215913e+08 | K55: WACC | L55: =D44 -> 0.08 | M55: =M44/$O$37-1 -> -0.28135141 | N55: =N44/$O$37-1 -> -0.20956055 | O55: =O44/$O$37-1 -> -0.13776968 | P55: =P44/$O$37-1 -> -0.065978821 | Q55: =Q44/$O$37-1 -> 0.0058120411
D56: =D45 -> 0.085 | E56: =E45+$O$35 -> 1.9075874e+08 | F56: =F45+$O$35 -> 2.0975184e+08 | G56: =G45+$O$35 -> 2.2874494e+08 | H56: =H45+$O$35 -> 2.4773805e+08 | I56: =I45+$O$35 -> 2.6673115e+08 | L56: =D45 -> 0.085 | M56: =M45/$O$37-1 -> -0.29501743 | N56: =N45/$O$37-1 -> -0.22482508 | O56: =O45/$O$37-1 -> -0.15463273 | P56: =P45/$O$37-1 -> -0.084440375 | Q56: =Q45/$O$37-1 -> -0.014248023
D57: =D46 -> 0.09 | E57: =E46+$O$35 -> 1.871578e+08 | F57: =F46+$O$35 -> 2.0572992e+08 | G57: =G46+$O$35 -> 2.2430205e+08 | H57: =H46+$O$35 -> 2.4287417e+08 | I57: =I46+$O$35 -> 2.614463e+08 | L57: =D46 -> 0.09 | M57: =M46/$O$37-1 -> -0.30832536 | N57: =N46/$O$37-1 -> -0.2396888 | O57: =O46/$O$37-1 -> -0.17105223 | P57: =P46/$O$37-1 -> -0.10241567 | Q57: =Q46/$O$37-1 -> -0.033779106
D58: =D47 -> 0.095 | E58: =E47+$O$35 -> 1.8365076e+08 | F58: =F47+$O$35 -> 2.0181311e+08 | G58: =G47+$O$35 -> 2.1997546e+08 | H58: =H47+$O$35 -> 2.3813781e+08 | I58: =I47+$O$35 -> 2.5630016e+08 | L58: =D47 -> 0.095 | M58: =M47/$O$37-1 -> -0.32128623 | N58: =N47/$O$37-1 -> -0.25416406 | O58: =O47/$O$37-1 -> -0.1870419 | P58: =P47/$O$37-1 -> -0.11991973 | Q58: =Q47/$O$37-1 -> -0.052797566
D59: =D48 -> 0.1 | E59: =E48+$O$35 -> 1.8023475e+08 | F59: =F48+$O$35 -> 1.9799818e+08 | G59: =G48+$O$35 -> 2.1576161e+08 | H59: =H48+$O$35 -> 2.3352504e+08 | I59: =I48+$O$35 -> 2.5128846e+08 | L59: =D48 -> 0.1 | M59: =M48/$O$37-1 -> -0.33391069 | N59: =N48/$O$37-1 -> -0.26826281 | O59: =O48/$O$37-1 -> -0.20261494 | P59: =P48/$O$37-1 -> -0.13696706 | Q59: =Q48/$O$37-1 -> -0.071319183
C62: Dashboard: Perpetuity Method
E64: Main Outputs | M64: Selected Inputs
G65: Enterprise | H65: Equity | I65: Equity | M65: Terminal Multiple | O65: =O33 -> 9.48
G66: Value | H66: Value | I66: Per Share | M66: WACC | O66: =O34 -> 0.090421772
G67: =DCF!D185 -> 3.1465979e+08 | M67: Net Debt | O67: =O35 -> -9856461
E68: Base Case | F68: 1 | G68: 3.1465979e+08 | H68: =G68+$O$35 -> 3.0480332e+08 | I68: =H68/$O$36 -> 684.12957 | M68: Shares Outstanding | O68: =O36 -> 445534.5
E69: Bull Case | F69: 2 | G69: 3.7071283e+08 | H69: =G69+$O$35 -> 3.6085636e+08 | I69: =H69/$O$36 -> 809.94034 | M69: Actual Stock Price | O69: =O37 -> 607.33
E70: Bear Case | F70: 3 | G70: 2.9761003e+08 | H70: =G70+$O$35 -> 2.8775356e+08 | I70: =H70/$O$36 -> 645.86146
E72: Enterprise Value | M72: Equity Value per Share
E74: Terminal Growth Rate | M74: Terminal Growth Rate
D75: =DCF!D185 -> 3.1465979e+08 | E75: =DCF!E185 -> 0.024 | F75: =DCF!F185 -> 0.026 | G75: =DCF!G185 -> 0.028 | H75: =DCF!H185 -> 0.03 | I75: =DCF!I185 -> 0.032 | M75: =E75 -> 0.024 | N75: =F75 -> 0.026 | O75: =G75 -> 0.028 | P75: =H75 -> 0.03 | Q75: =I75 -> 0.032
C76: WACC | D76: =DCF!D186 -> 0.08 | E76: =DCF!E186 -> 3.5837123e+08 | F76: =DCF!F186 -> 3.7004576e+08 | G76: =DCF!G186 -> 3.8261833e+08 | H76: =DCF!H186 -> 3.9619671e+08 | I76: =DCF!I186 -> 4.1090663e+08 | K76: WACC | L76: =D76 -> 0.08 | M76: =E87/$O$36 -> 782.23968 | N76: =F87/$O$36 -> 808.44312 | O76: =G87/$O$36 -> 836.6622 | P76: =H87/$O$36 -> 867.1388 | Q76: =I87/$O$36 -> 900.15513
D77: =DCF!D187 -> 0.085 | E77: =DCF!E187 -> 3.2688248e+08 | F77: =DCF!F187 -> 3.365178e+08 | G77: =DCF!G187 -> 3.4682928e+08 | H77: =DCF!H187 -> 3.5789069e+08 | I77: =DCF!I187 -> 3.6978692e+08 | L77: =D77 -> 0.085 | M77: =E88/$O$36 -> 711.56335 | N77: =F88/$O$36 -> 733.18977 | O77: =G88/$O$36 -> 756.33384 | P77: =H88/$O$36 -> 781.16111 | Q77: =I88/$O$36 -> 807.86214
D78: =DCF!D188 -> 0.09 | E78: =DCF!E188 -> 3.0020142e+08 | F78: =DCF!F188 -> 3.0826609e+08 | G78: =DCF!G188 -> 3.1685106e+08 | H78: =DCF!H188 -> 3.2600836e+08 | I78: =DCF!I188 -> 3.357972e+08 | L78: =D78 -> 0.09 | M78: =E89/$O$36 -> 651.67784 | N78: =F89/$O$36 -> 669.77895 | O78: =G89/$O$36 -> 689.04787 | P78: =H89/$O$36 -> 709.60139 | Q78: =I89/$O$36 -> 731.57239
D79: =DCF!D189 -> 0.095 | E79: =DCF!E189 -> 2.7731154e+08 | F79: =DCF!F189 -> 2.841428e+08 | G79: =DCF!G189 -> 2.913819e+08 | H79: =DCF!H189 -> 2.9906649e+08 | I79: =DCF!I189 -> 3.0723898e+08 | L79: =D79 -> 0.095 | M79: =E90/$O$36 -> 600.30161 | N79: =F90/$O$36 -> 615.63435 | O79: =G90/$O$36 -> 631.88247 | P79: =H90/$O$36 -> 649.13048 | Q79: =I90/$O$36 -> 667.4736
D80: =DCF!D190 -> 0.1 | E80: =DCF!E190 -> 2.5746385e+08 | F80: =DCF!F190 -> 2.6331035e+08 | G80: =DCF!G190 -> 2.6948167e+08 | H80: =DCF!H190 -> 2.7600563e+08 | I80: =DCF!I190 -> 2.8291335e+08 | L80: =D80 -> 0.1 | M80: =E91/$O$36 -> 555.75356 | N80: =F91/$O$36 -> 568.87602 | O80: =G91/$O$36 -> 582.7275 | P80: =H91/$O$36 -> 597.37049 | Q80: =I91/$O$36 -> 612.87484
E83: Equity Value | M83: Premium (Discount) to Stock Price
E85: Terminal Growth Rate | M85: Terminal Growth Rate
D86: =DCF!E224 -> 0 | E86: =E75 -> 0.024 | F86: =F75 -> 0.026 | G86: =G75 -> 0.028 | H86: =H75 -> 0.03 | I86: =I75 -> 0.032 | M86: =E75 -> 0.024 | N86: =F75 -> 0.026 | O86: =G75 -> 0.028 | P86: =H75 -> 0.03 | Q86: =I75 -> 0.032
C87: WACC | D87: =D76 -> 0.08 | E87: =E76+$O$35 -> 3.4851477e+08 | F87: =F76+$O$35 -> 3.601893e+08 | G87: =G76+$O$35 -> 3.7276187e+08 | H87: =H76+$O$35 -> 3.8634025e+08 | I87: =I76+$O$35 -> 4.0105017e+08 | K87: WACC | L87: =D76 -> 0.08 | M87: =M76/$O$37-1 -> 0.28799777 | N87: =N76/$O$37-1 -> 0.33114306 | O87: =O76/$O$37-1 -> 0.37760723 | P87: =P76/$O$37-1 -> 0.42778852 | Q87: =Q76/$O$37-1 -> 0.4821516
D88: =D77 -> 0.085 | E88: =E77+$O$35 -> 3.1702602e+08 | F88: =F77+$O$35 -> 3.2666134e+08 | G88: =G77+$O$35 -> 3.3697282e+08 | H88: =H77+$O$35 -> 3.4803423e+08 | I88: =I77+$O$35 -> 3.5993046e+08 | L88: =D77 -> 0.085 | M88: =M77/$O$37-1 -> 0.17162555 | N88: =N77/$O$37-1 -> 0.20723457 | O88: =O77/$O$37-1 -> 0.24534247 | P88: =P77/$O$37-1 -> 0.28622185 | Q88: =Q77/$O$37-1 -> 0.33018646
D89: =D78 -> 0.09 | E89: =E78+$O$35 -> 2.9034496e+08 | F89: =F78+$O$35 -> 2.9840963e+08 | G89: =G78+$O$35 -> 3.069946e+08 | H89: =H78+$O$35 -> 3.161519e+08 | I89: =I78+$O$35 -> 3.2594074e+08 | L89: =D78 -> 0.09 | M89: =M78/$O$37-1 -> 0.073020994 | N89: =N78/$O$37-1 -> 0.1028254 | O89: =O78/$O$37-1 -> 0.13455266 | P89: =P78/$O$37-1 -> 0.16839508 | Q89: =Q78/$O$37-1 -> 0.20457146
D90: =D79 -> 0.095 | E90: =E79+$O$35 -> 2.6745508e+08 | F90: =F79+$O$35 -> 2.7428634e+08 | G90: =G79+$O$35 -> 2.8152544e+08 | H90: =H79+$O$35 -> 2.8921002e+08 | I90: =I79+$O$35 -> 2.9738252e+08 | L90: =D79 -> 0.095 | M90: =M79/$O$37-1 -> -0.011572602 | N90: =N79/$O$37-1 -> 0.013673536 | O90: =O79/$O$37-1 -> 0.040426906 | P90: =P79/$O$37-1 -> 0.068826637 | Q90: =Q79/$O$37-1 -> 0.099029526
D91: =D80 -> 0.1 | E91: =E80+$O$35 -> 2.4760739e+08 | F91: =F80+$O$35 -> 2.5345389e+08 | G91: =G80+$O$35 -> 2.5962521e+08 | H91: =H80+$O$35 -> 2.6614916e+08 | I91: =I80+$O$35 -> 2.7305689e+08 | L91: =D80 -> 0.1 | M91: =M80/$O$37-1 -> -0.084923246 | N91: =N80/$O$37-1 -> -0.063316451 | O91: =O80/$O$37-1 -> -0.040509278 | P91: =P80/$O$37-1 -> -0.016398837 | Q91: =Q80/$O$37-1 -> 0.0091298639

Sheet Financial Statements
C5: Key Financial Statements | L5: Historicals | AK5: Forecasts | BC5: CAGR
G6: Units | H6: 19Q1 | I6: 19Q2 | J6: 19Q3 | K6: 19Q4 | L6: 2019A | M6: 20Q1 | N6: 20Q2 | O6: 20Q3 | P6: 20Q4 | Q6: 2020A | R6: 21Q1 | S6: 21Q2 | T6: 21Q3 | U6: 21Q4 | V6: 2021A | W6: 22Q1 | X6: 22Q2 | Y6: 22Q3 | Z6: 22Q4 | AA6: 2022A | AB6: 23Q1 | AC6: 23Q2 | AD6: 23Q3 | AE6: 23Q4 | AF6: 2023A | AG6: 24Q1 | AH6: 24Q2 | AI6: 24Q3 | AJ6: 24Q4 | AK6: 2024E | AL6: 25Q1 | AM6: 25Q2 | AN6: 25Q3 | AO6: 25Q4 | AP6: 2025E | AQ6: 26Q1 | AR6: 26Q2 | AS6: 26Q3 | AT6: 26Q4 | AU6: 2026E | AV6: 27Q1 | AW6: 27Q2 | AX6: 27Q3 | AY6: 27Q4 | AZ6: 2027E | BA6: 2028E | BC6: 2020A - 2022A | BD6: 2023E - 2026E | BE6: 2027E - 2030E | BF6: 2023E - 2030E
A8: I | C8: Income Statement
C9: -1 | AF9: =(AF10/L10)^(1/5)-1 -> 0.10841708
C10: Revenues | G10: USD'k | H10: =Operating!H13 -> 4520992 | I10: =Operating!I13 -> 4923116 | J10: =Operating!J13 -> 5244905 | K10: =Operating!K13 -> 5467434 | L10: =Operating!L13 -> 20156447 | M10: =Operating!M13 -> 5767691 | N10: =Operating!N13 -> 6148286 | O10: =Operating!O13 -> 6435637 | ... BA10: =Operating!BA13 -> 71196534 | BC10: =IFERROR((Q10/#REF!)^(1/(_xlfn.NUMBERVALUE(LEFT(Q$6,4))-_xlfn.NUMBERVALUE(LEFT(#REF!,4))))-1,"NA") -> NA | BD10: =IFERROR((AZ10/AK10)^(1/(_xlfn.NUMBERVALUE(LEFT(AZ$6,4))-_xlfn.NUMBERVALUE(LEFT(AK$6,4))))-1,"NA") -> 0.17857271 | BE10: =IFERROR((#REF!/BA10)^(1/(_xlfn.NUMBERVALUE(LEFT(#REF!,4))-_xlfn.NUMBERVALUE(LEFT(BA$6,4))))-1,"NA") -> NA | BF10: =IFERROR((#REF!/AK10)^(1/(_xlfn.NUMBERVALUE(LEFT(#REF!,4))-_xlfn.NUMBERVALUE(LEFT(AK$6,4))))-1,"NA") -> NA
C11: Cost of sales | G11: USD'k | H11: -2870614 | I11: -3005657 | J11: -3097919 | K11: -3466023 | L11: =SUM(H11:K11) -> -12440213 | M11: -3599701 | N11: -3643707 | O11: -3867751 | P11: -4165160 | Q11: =SUM(M11:P11) -> -15276319 | R11: -3868511 | S11: -4018008 | T11: -4206589 | U11: -5239575 | V11: =SUM(R11:U11) -> -17332683 | W11: -4284705 | X11: -4690755 | Y11: -4788665 | Z11: -5404160 | AA11: =SUM(W11:Z11) -> -19168285 | AB11: -4803625 | AC11: -4673470 | AD11: -4930788 | AE11: -5307485 | AF11: =SUM(AB11:AE11) -> -19715368 | AG11: =Operating!AG62*$C$9 -> -5457841.8 | AH11: =Operating!AH62*$C$9 -> -5468641.3 | AI11: =Operating!AI62*$C$9 -> -5581365.1 | AJ11: =Operating!AJ62*$C$9 -> -5768530.6 | AK11: =Operating!AK62*$C$9 -> -22276379 | AL11: =Operating!AL62*$C$9 -> -6190160.3 | AM11: =Operating!AM62*$C$9 -> -6311335.8 | AN11: =Operating!AN62*$C$9 -> -6521826.6 | ... BA11: =Operating!BA62*$C$9 -> -33700392 | BC11: =IFERROR((Q11/#REF!)^(1/(_xlfn.NUMBERVALUE(LEFT(Q$6,4))-_xlfn.NUMBERVALUE(LEFT(#REF!,4))))-1,"NA") -> NA | BD11: =IFERROR((AZ11/AK11)^(1/(_xlfn.NUMBERVALUE(LEFT(AZ$6,4))-_xlfn.NUMBERVALUE(LEFT(AK$6,4))))-1,"NA") -> 0.11640728 | BE11: =IFERROR((#REF!/BA11)^(1/(_xlfn.NUMBERVALUE(LEFT(#REF!,4))-_xlfn.NUMBERVALUE(LEFT(BA$6,4))))-1,"NA") -> NA | BF11: =IFERROR((#REF!/AK11)^(1/(_xlfn.NUMBERVALUE(LEFT(#REF!,4))-_xlfn.NUMBERVALUE(LEFT(AK$6,4))))-1,"NA") -> NA
C12: Gross Profit | G12: USD'k | H12: =SUM(H10:H11) -> 1650378 | I12: =SUM(I10:I11) -> 1917459 | J12: =SUM(J10:J11) -> 2146986 | K12: =SUM(K10:K11) -> 2001411 | L12: =SUM(L10:L11) -> 7716234 | M12: =SUM(M10:M11) -> 2167990 | N12: =SUM(N10:N11) -> 2504579 | O12: =SUM(O10:O11) -> 2567886 | ... BA12: =SUM(BA10:BA11) -> 37496142 | BC12: =IFERROR((Q12/#REF!)^(1/(_xlfn.NUMBERVALUE(LEFT(Q$6,4))-_xlfn.NUMBERVALUE(LEFT(#REF!,4))))-1,"NA") -> NA | BD12: =IFERROR((AZ12/AK12)^(1/(_xlfn.NUMBERVALUE(LEFT(AZ$6,4))-_xlfn.NUMBERVALUE(LEFT(AK$6,4))))-1,"NA") -> 0.25165791 | BE12: =IFERROR((#REF!/BA12)^(1/(_xlfn.NUMBERVALUE(LEFT(#REF!,4))-_xlfn.NUMBERVALUE(LEFT(BA$6,4))))-1,"NA") -> NA | BF12: =IFERROR((#REF!/AK12)^(1/(_xlfn.NUMBERVALUE(LEFT(#REF!,4))-_xlfn.NUMBERVALUE(LEFT(AK$6,4))))-1,"NA") -> NA
AK13: =AK12/AK10 -> 0.43133469 | AL13: =AL12/AL10 -> 0.43211806 | AM13: =AM12/AM10 -> 0.43511806 | AN13: =AN12/AN10 -> 0.44211806 | AO13: =AO12/AO10 -> 0.45111806 | AP13: =AP12/AP10 -> 0.44048844 | AQ13: =AQ12/AQ10 -> 0.46111806 | AR13: =AR12/AR10 -> 0.47111806 | ... BA13: =BA12/BA10 -> 0.52665685
C14: Marketing | G14: USD'k | H14: -616578 | I14: -603150 | J14: -553797 | K14: -878937 | L14: =SUM(H14:K14) -> -2652462 | M14: -503830 | N14: -434370 | O14: -527597 | P14: -762565 | Q14: =SUM(M14:P14) -> -2228362 | R14: -512512 | S14: -603973 | T14: -635948 | U14: -792713 | V14: =SUM(R14:U14) -> -2545146 | W14: -555978 | X14: -574960 | Y14: -567954 | Z14: -831610 | AA14: =SUM(W14:Z14) -> -2530502 | AB14: -555362 | AC14: -627168 | AD14: -558736 | AE14: -916617 | AF14: =SUM(AB14:AE14) -> -2657883 | AG14: =Operating!AG95*$C$9 -> -713278.54 | AH14: =Operating!AH95*$C$9 -> -715337.05 | AI14: =Operating!AI95*$C$9 -> -723451.49 | AJ14: =Operating!AJ95*$C$9 -> -740509.13 | AK14: =Operating!AK95*$C$9 -> -2892576.2 | AL14: =Operating!AL95*$C$9 -> -795298.44 | AM14: =Operating!AM95*$C$9 -> -843105.29 | AN14: =Operating!AN95*$C$9 -> -876310.38 | ... BA14: =Operating!BA95*$C$9 -> -3877380.8 | BC14: =IFERROR((Q14/#REF!)^(1/(_xlfn.NUMBERVALUE(LEFT(Q$6,4))-_xlfn.NUMBERVALUE(LEFT(#REF!,4))))-1,"NA") -> NA | BD14: =IFERROR((AZ14/AK14)^(1/(_xlfn.NUMBERVALUE(LEFT(AZ$6,4))-_xlfn.NUMBERVALUE(LEFT(AK$6,4))))-1,"NA") -> 0.095814504 | BE14: =IFERROR((#REF!/BA14)^(1/(_xlfn.NUMBERVALUE(LEFT(#REF!,4))-_xlfn.NUMBERVALUE(LEFT(BA$6,4))))-1,"NA") -> NA | BF14: =IFERROR((#REF!/AK14)^(1/(_xlfn.NUMBERVALUE(LEFT(#REF!,4))-_xlfn.NUMBERVALUE(LEFT(AK$6,4))))-1,"NA") -> NA
C15: Technology and development | G15: USD'k | H15: -372764 | I15: -383233 | J15: -379776 | K15: -409376 | L15: =SUM(H15:K15) -> -1545149 | M15: -453817 | N15: -435045 | O15: -453802 | P15: -486936 | Q15: =SUM(M15:P15) -> -1829600 | R15: -525207 | S15: -537321 | T15: -563887 | U15: -647470 | V15: =SUM(R15:U15) -> -2273885 | W15: -657530 | X15: -716846 | Y15: -662739 | Z15: -673926 | AA15: =SUM(W15:Z15) -> -2711041 | AB15: -687275 | AC15: -657983 | AD15: -657159 | AE15: -673341 | AF15: =SUM(AB15:AE15) -> -2675758 | AG15: =Operating!AG96*$C$9 -> -722334.13 | AH15: =Operating!AH96*$C$9 -> -724599.3 | AI15: =Operating!AI96*$C$9 -> -733139.78 | AJ15: =Operating!AJ96*$C$9 -> -750777.71 | AK15: =Operating!AK96*$C$9 -> -2930850.9 | AL15: =Operating!AL96*$C$9 -> -805948.9 | AM15: =Operating!AM96*$C$9 -> -854021.9 | AN15: =Operating!AN96*$C$9 -> -887732.61 | ... BA15: =Operating!BA96*$C$9 -> -3946944.5 | BC15: =IFERROR((Q15/#REF!)^(1/(_xlfn.NUMBERVALUE(LEFT(Q$6,4))-_xlfn.NUMBERVALUE(LEFT(#REF!,4))))-1,"NA") -> NA | BD15: =IFERROR((AZ15/AK15)^(1/(_xlfn.NUMBERVALUE(LEFT(AZ$6,4))-_xlfn.NUMBERVALUE(LEFT(AK$6,4))))-1,"NA") -> 0.096977705 | BE15: =IFERROR((#REF!/BA15)^(1/(_xlfn.NUMBERVALUE(LEFT(#REF!,4))-_xlfn.NUMBERVALUE(LEFT(BA$6,4))))-1,"NA") -> NA | BF15: =IFERROR((#REF!/AK15)^(1/(_xlfn.NUMBERVALUE(LEFT(#REF!,4))-_xlfn.NUMBERVALUE(LEFT(AK$6,4))))-1,"NA") -> NA
C16: General and administrative | G16: USD'k | H16: -201952 | I16: -224657 | J16: -233174 | K16: -254586 | L16: =SUM(H16:K16) -> -914369 | M16: -252087 | N16: -277236 | O16: -271624 | P16: -275539 | Q16: =SUM(M16:P16) -> -1076486 | R16: -297196 | S16: -334845 | T16: -321790 | U16: -397790 | V16: =SUM(R16:U16) -> -1351621 | W16: -397928 | X16: -409297 | Y16: -373213 | Z16: -392453 | AA16: =SUM(W16:Z16) -> -1572891 | AB16: -400924 | AC16: -401497 | AD16: -478591 | AE16: -439273 | AF16: =SUM(AB16:AE16) -> -1720285 | AG16: =Operating!AG97*$C$9 -> -458592.29 | AH16: =Operating!AH97*$C$9 -> -454838.51 | AI16: =Operating!AI97*$C$9 -> -450970.68 | AJ16: =Operating!AJ97*$C$9 -> -451707.89 | AK16: =Operating!AK97*$C$9 -> -1816109.4 | AL16: =Operating!AL97*$C$9 -> -495757.2 | AM16: =Operating!AM97*$C$9 -> -536078.42 | AN16: =Operating!AN97*$C$9 -> -555062.89 | ... BA16: =Operating!BA97*$C$9 -> -1920917.7
C17: Operating Expenses | G17: USD'k | H17: =SUM(H14:H16) -> -1191294 | I17: =SUM(I14:I16) -> -1211040 | J17: =SUM(J14:J16) -> -1166747 | K17: =SUM(K14:K16) -> -1542899 | L17: =SUM(L14:L16) -> -5111980 | M17: =SUM(M14:M16) -> -1209734 | N17: =SUM(N14:N16) -> -1146651 | O17: =SUM(O14:O16) -> -1253023 | ... BA17: =SUM(BA14:BA16) -> -9745243
C19: EBIT | G19: USD'k | H19: =SUM(H12,H17) -> 459084 | I19: =SUM(I12,I17) -> 706419 | J19: =SUM(J12,J17) -> 980239 | K19: =SUM(K12,K17) -> 458512 | L19: =SUM(L12,L17) -> 2604254 | M19: =SUM(M12,M17) -> 958256 | N19: =SUM(N12,N17) -> 1357928 | O19: =SUM(O12,O17) -> 1314863 | ... BA19: =SUM(BA12,BA17) -> 27750899
C21: Interest expense | G21: % | H21: -135529 | I21: -152033 | J21: -160660 | K21: -177801 | L21: =SUM(H21:K21) -> -626023 | M21: -184083 | N21: -189151 | O21: -197079 | P21: -197186 | Q21: =SUM(M21:P21) -> -767499 | R21: -194440 | S21: -191322 | T21: -190429 | U21: -189429 | V21: =SUM(R21:U21) -> -765620 | W21: -187579 | X21: -175455 | Y21: -172575 | Z21: -170603 | AA21: =SUM(W21:Z21) -> -706212 | AB21: -174239 | AC21: -174812 | AD21: -175563 | AE21: -175212 | AF21: =SUM(AB21:AE21) -> -699826
C22: Interest and other income (expense) | G22: % | H22: 76104 | I22: -53470 | J22: 192744 | K22: -131378 | L22: =SUM(H22:K22) -> 84000 | M22: 21697 | N22: -133175 | O22: -256324 | P22: -250639 | Q22: =SUM(M22:P22) -> -618441 | R22: 269086 | S22: -62519 | T22: 96135 | U22: 108512 | V22: =SUM(R22:U22) -> 411214 | W22: 195645 | X22: 220226 | Y22: 261404 | Z22: -339965 | AA22: =SUM(W22:Z22) -> 337310 | AB22: -71204 | AC22: 26961 | AD22: 168218 | AE22: -172747 | AF22: =SUM(AB22:AE22) -> -48772
C23: EBT | G23: USD'k | H23: =SUM(H21:H22,H19) -> 399659 | I23: =SUM(I21:I22,I19) -> 500916 | J23: =SUM(J21:J22,J19) -> 1012323 | K23: =SUM(K21:K22,K19) -> 149333 | L23: =SUM(L21:L22,L19) -> 2062231 | M23: =SUM(M21:M22,M19) -> 795870 | N23: =SUM(N21:N22,N19) -> 1035602 | O23: =SUM(O21:O22,O19) -> 861460 | ... AF23: =SUM(AF21:AF22,AF19) -> 6205405
C25: Benefit from (provision for) income taxes | G25: USD'k | H25: -55607 | I25: -230266 | J25: -347079 | K25: 437637 | L25: =SUM(H25:K25) -> -195315 | M25: -86803 | N25: -315406 | O25: -71484 | P25: 35739 | Q25: =SUM(M25:P25) -> -437954 | R25: -327787 | S25: -240776 | T25: -211888 | U25: 56576 | V25: =SUM(R25:U25) -> -723875 | W25: -382245 | X25: -182103 | Y25: -223605 | Z25: 15948 | AA25: =SUM(W25:Z25) -> -772005 | AB25: -163754 | AC25: -191722 | AD25: -231627 | AE25: -210312 | AF25: =SUM(AB25:AE25) -> -797415
C27: Net Income (loss) | G27: USD'k | H27: =SUM(H23,H25) -> 344052 | I27: =SUM(I23,I25) -> 270650 | J27: =SUM(J23,J25) -> 665244 | K27: =SUM(K23,K25) -> 586970 | L27: =SUM(L23,L25) -> 1866916 | M27: =SUM(M23,M25) -> 709067 | N27: =SUM(N23,N25) -> 720196 | O27: =SUM(O23,O25) -> 789976 | ... AF27: =SUM(AF23,AF25) -> 5407990 | BC27: =IFERROR((Q27/#REF!)^(1/(_xlfn.NUMBERVALUE(LEFT(Q$6,4))-_xlfn.NUMBERVALUE(LEFT(#REF!,4))))-1,"NA") -> NA | BD27: =IFERROR((AZ27/AK27)^(1/(_xlfn.NUMBERVALUE(LEFT(AZ$6,4))-_xlfn.NUMBERVALUE(LEFT(AK$6,4))))-1,"NA") -> NA | BE27: =IFERROR((#REF!/BA27)^(1/(_xlfn.NUMBERVALUE(LEFT(#REF!,4))-_xlfn.NUMBERVALUE(LEFT(BA$6,4))))-1,"NA") -> NA | BF27: =IFERROR((#REF!/AK27)^(1/(_xlfn.NUMBERVALUE(LEFT(#REF!,4))-_xlfn.NUMBERVALUE(LEFT(AK$6,4))))-1,"NA") -> NA
AB28: =AB27/AB10 -> 0.15951122 | AC28: =AC27/AC10 -> 0.18156109 | AD28: =AD27/AD10 -> 0.1968748 | AE28: =AE27/AE10 -> 0.10617645 | AF28: =AF27/AF10 -> 0.16036362
C29: Basic EPS | G29: USD | H29: 0.79 | I29: 0.62 | J29: 1.52 | K29: 1.34 | L29: =ROUND(L$27/L32,2) -> 4.26 | M29: 1.61 | N29: 1.63 | O29: 1.79 | P29: 1.23 | Q29: =ROUND(Q$27/Q32,2) -> 6.26 | R29: 3.85 | S29: 3.05 | T29: 3.27 | U29: 1.37 | V29: =ROUND(V$27/V32,2) -> 11.55 | W29: 3.6 | X29: 3.24 | Y29: 3.14 | Z29: 0.12 | AA29: =ROUND(AA$27/AA32,2) -> 10.1 | AB29: 2.93 | AC29: 3.35 | AD29: 3.8 | AE29: 2.15 | AF29: =ROUND(AF$27/AF32,2) -> 12.25
C30: Diluted EPS | G30: USD | H30: 0.76 | I30: 0.6 | J30: 1.47 | K30: 1.3 | L30: =ROUND(L$27/L33,2) -> 4.13 | M30: 1.57 | N30: 1.59 | O30: 1.74 | P30: 1.19 | Q30: =ROUND(Q$27/Q33,2) -> 6.08 | R30: 3.75 | S30: 2.97 | T30: 3.19 | U30: 1.33 | V30: =ROUND(V$27/V33,2) -> 11.24 | W30: 3.53 | X30: 3.2 | Y30: 3.1 | Z30: 0.12 | AA30: =ROUND(AA$27/AA33,2) -> 9.95 | AB30: 2.88 | AC30: 3.29 | AD30: 3.73 | AE30: 2.11 | AF30: =ROUND(AF$27/AF33,2) -> 12.03
C32: Basic weighted-average shares of common stock outstanding | G32: # | H32: 436947 | I32: 437587 | J32: 438090 | K32: 438547 | L32: 437799 | M32: 439352 | N32: 440569 | O32: 441526 | P32: 442220 | Q32: 440922 | R32: 443224 | S32: 443159 | T32: 442778 | U32: 443462 | V32: 443155 | W32: 444146 | X32: 444557 | Y32: 444878 | Z32: 445200 | AA32: 444698 | AB32: 445244 | AC32: 443881 | AD32: 441537 | AE32: 435923 | AF32: 441571
C33: Diluted weighted-average shares of common stock outstanding | G33: # | H33: 451922 | I33: 452195 | J33: 451552 | K33: 451367 | L33: 451765 | M33: 452494 | N33: 453945 | O33: 455088 | P33: 455283 | Q33: 454208 | R33: 455641 | S33: 455129 | T33: 454925 | U33: 455795 | V33: 455372 | W33: 452984 | X33: 450169 | Y33: 450344 | Z33: 451649 | AA33: 451290 | AB33: 452417 | AC33: 451572 | AD33: 450011 | AE33: 444292 | AF33: 449498
C35: EBITDA | G35: USD'k | H35: =SUM(H19,H81) -> 482645 | I35: =SUM(I19,I81) -> 731915 | J35: =SUM(J19,J81) -> 1006943 | K35: =SUM(K19,K81) -> 486330 | L35: =SUM(L19,L81) -> 2707833 | M35: =SUM(M19,M81) -> 986773 | N35: =SUM(N19,N81) -> 1384589 | O35: =SUM(O19,O81) -> 1343452 | ... AF35: =SUM(AF19,AF81) -> 7310950 | AK35: =AK19+Operating!AK242 -> 9141530 | AP35: =AP19+Operating!AP242 -> 11104331 | AU35: =AU19+Operating!AU242 -> 16118464 | AZ35: =AZ19+Operating!AZ242 -> 23198378 | BA35: =BA19+Operating!BA242 -> 27230790
A37: B | C37: Balance Sheet
C38: Check | H38: =ROUND(H50-H72,0) -> 0 | I38: =ROUND(I50-I72,0) -> 0 | J38: =ROUND(J50-J72,0) -> 0 | K38: =ROUND(K50-K72,0) -> 0 | L38: =ROUND(L50-L72,0) -> 0 | M38: =ROUND(M50-M72,0) -> 0 | N38: =ROUND(N50-N72,0) -> 0 | O38: =ROUND(O50-O72,0) -> 0 | ... AF38: =ROUND(AF50-AF72,0) -> 0
C40: Cash and cash equivalents | G40: USD'k | H40: 3348557 | I40: 5004247 | J40: 4435018 | K40: 5018437 | L40: =K40 -> 5018437 | M40: 5151884 | N40: 7153248 | O40: 8392391 | P40: 8205550 | Q40: =P40 -> 8205550 | R40: 8403705 | S40: 7777530 | T40: 7526681 | U40: 6027804 | V40: =U40 -> 6027804 | W40: 6008946 | X40: 5819449 | Y40: 6113733 | Z40: 5147176 | AA40: =Z40 -> 5147176 | AB40: 6714594 | AC40: 7662788 | AD40: 7353245 | AE40: 7116913 | AF40: =AE40 -> 7116913
C41: Current content assets, net | G41: USD'k | H41: 0 | I41: 0 | J41: 0 | K41: 0 | L41: =K41 -> 0 | M41: 0 | N41: 0 | O41: 0 | P41: 0 | Q41: =P41 -> 0 | R41: 0 | S41: 0 | T41: 0 | U41: 0 | V41: =U41 -> 0 | W41: 0 | X41: 0 | Y41: 0 | Z41: 911276 | AA41: =Z41 -> 911276 | AB41: 1112910 | AC41: 914201 | AD41: 514201 | AE41: 20973 | AF41: =AE41 -> 20973
C42: Other current assets | G42: USD'k | H42: 820350 | I42: 872910 | J42: 892740 | K42: 1160067 | L42: =K42 -> 1160067 | M42: 1295897 | N42: 1410891 | O42: 1434089 | P42: 1556030 | Q42: =P42 -> 1556030 | R42: 1703803 | S42: 1826746 | T42: 1889106 | U42: 2042021 | V42: =U42 -> 2042021 | W42: 2089069 | X42: 2021329 | Y42: 2703170 | Z42: 3208021 | AA42: =Z42 -> 3208021 | AB42: 2655119 | AC42: 2929347 | AD42: 2912028 | AE42: 2780247 | AF42: =AE42 -> 2780247
C43: Total current assets | G43: USD'k | H43: =SUM(H40:H42) -> 4168907 | I43: =SUM(I40:I42) -> 5877157 | J43: =SUM(J40:J42) -> 5327758 | K43: =SUM(K40:K42) -> 6178504 | L43: =SUM(L40:L42) -> 6178504 | M43: =SUM(M40:M42) -> 6447781 | N43: =SUM(N40:N42) -> 8564139 | O43: =SUM(O40:O42) -> 9826480 | ... AF43: =SUM(AF40:AF42) -> 9918133
C45: Non-current content assets, net | G45: USD'k | H45: 20878317 | I45: 21937845 | J45: 23227772 | K45: 24504567 | L45: =K45 -> 24504567 | M45: 25266889 | N45: 25155117 | O45: 25067633 | P45: 25383950 | Q45: =P45 -> 25383950 | R45: 26043991 | S45: 27291640 | T45: 28974045 | U45: 30919539 | V45: =U45 -> 30919539 | W45: 31191920 | X45: 32533199 | Y45: 32777340 | Z45: 32736713 | AA45: =Z45 -> 32736713 | AB45: 32349184 | AC45: 32520774 | AD45: 31749861 | AE45: 31658056 | AF45: =AE45 -> 31658056
C46: Property and equipment, net | G46: USD'k | H46: 434372 | I46: 452399 | J46: 481992 | K46: 565221 | L46: =K46 -> 565221 | M46: 650455 | N46: 751941 | O46: 828118 | P46: 960183 | Q46: =P46 -> 960183 | R46: 1015419 | S46: 1107437 | T46: 1220114 | U46: 1323453 | V46: =U46 -> 1323453 | W46: 1383763 | X46: 1361920 | Y46: 1372754 | Z46: 1398257 | AA46: =Z46 -> 1398257 | AB46: 1413094 | AC46: 1471968 | AD46: 1498391 | AE46: 1491444 | AF46: =AE46 -> 1491444
C47: Other non-current assets | G47: USD'k | H47: 1737036 | I47: 1903938 | J47: 1904189 | K47: 2727420 | L47: =K47 -> 2727420 | M47: 2694785 | N47: 2704084 | O47: 2900312 | P47: 3174646 | Q47: =P47 -> 3174646 | R47: 2956096 | S47: 2967616 | T47: 3129911 | U47: 4271846 | V47: =U47 -> 4271846 | W47: 4657206 | X47: 4615038 | Y47: 4595190 | Z47: 5193325 | AA47: =Z47 -> 5193325 | AB47: 5245444 | AC47: 5318395 | AD47: 5474060 | AE47: 5664359 | AF47: =AE47 -> 5664359
C48: Total non-current assets | G48: USD'k | H48: =SUM(H45:H47) -> 23049725 | I48: =SUM(I45:I47) -> 24294182 | J48: =SUM(J45:J47) -> 25613953 | K48: =SUM(K45:K47) -> 27797208 | L48: =SUM(L45:L47) -> 27797208 | M48: =SUM(M45:M47) -> 28612129 | N48: =SUM(N45:N47) -> 28611142 | O48: =SUM(O45:O47) -> 28796063 | ... AF48: =SUM(AF45:AF47) -> 38813859
C50: Total assets | G50: USD'k | H50: =H48+H43 -> 27218632 | I50: =I48+I43 -> 30171339 | J50: =J48+J43 -> 30941711 | K50: =K48+K43 -> 33975712 | L50: =L48+L43 -> 33975712 | M50: =M48+M43 -> 35059910 | N50: =N48+N43 -> 37175281 | O50: =O48+O43 -> 38622543 | ... AF50: =AF48+AF43 -> 48731992
C52: Current content liabilities | G52: USD'k | H52: 4858899 | I52: 4846525 | J52: 4857520 | K52: 4413561 | L52: =K52 -> 4413561 | M52: 4761585 | N52: 4664733 | O52: 4599654 | P52: 4429536 | Q52: =P52 -> 4429536 | R52: 4297957 | S52: 4197874 | T52: 4110962 | U52: 4292967 | V52: =U52 -> 4292967 | W52: 4066289 | X52: 4174966 | Y52: 4225890 | Z52: 4480150 | AA52: =Z52 -> 4480150 | AB52: 4344580 | AC52: 4440412 | AD52: 4259582 | AE52: 4466470 | AF52: =AE52 -> 4466470
C53: Accounts payable | G53: USD'k | H53: 439496 | I53: 442194 | J53: 444129 | K53: 674347 | L53: =K53 -> 674347 | M53: 545488 | N53: 446668 | O53: 541298 | P53: 656183 | Q53: =P53 -> 656183 | R53: 532942 | S53: 622931 | T53: 643059 | U53: 837483 | V53: =U53 -> 837483 | W53: 617202 | X53: 504278 | Y53: 560156 | Z53: 671513 | AA53: =Z53 -> 671513 | AB53: 591987 | AC53: 615374 | AD53: 534429 | AE53: 747412 | AF53: =AE53 -> 747412
C54: Accrued expenses and other liabilities | G54: USD'k | H54: 750720 | I54: 752488 | J54: 1040745 | K54: 843043 | L54: =K54 -> 843043 | M54: 1061090 | N54: 986595 | O54: 1259124 | P54: 1102196 | Q54: =P54 -> 1102196 | R54: 1291812 | S54: 1125591 | T54: 1413120 | U54: 1449351 | V54: =U54 -> 1449351 | W54: 1817117 | X54: 1596035 | Y54: 1803555 | Z54: 1514650 | AA54: =Z54 -> 1514650 | AB54: 1718069 | AC54: 1908714 | AD54: 1838908 | AE54: 1803960 | AF54: =AE54 -> 1803960
C55: Deferred revenue | G55: USD'k | H55: 808692 | I55: 892777 | J55: 915506 | K55: 924745 | L55: =K55 -> 924745 | M55: 986753 | N55: 1029261 | O55: 1040202 | P55: 1117992 | Q55: =P55 -> 1117992 | R55: 1140271 | S55: 1187364 | T55: 1182632 | U55: 1209342 | V55: =U55 -> 1209342 | W55: 1239048 | X55: 1224743 | Y55: 1176323 | Z55: 1264661 | AA55: =Z55 -> 1264661 | AB55: 1262271 | AC55: 1311918 | AD55: 1306185 | AE55: 1442969 | AF55: =AE55 -> 1442969
C56: Short-term debt | G56: USD'k | H56: 0 | I56: 0 | J56: 0 | K56: 0 | L56: =K56 -> 0 | M56: 498809 | N56: 499161 | O56: 499517 | P56: 499878 | Q56: =P56 -> 499878 | R56: 698788 | S56: 699128 | T56: 699473 | U56: 699823 | V56: =U56 -> 699823 | W56: 0 | X56: 0 | Y56: 0 | Z56: 0 | AA56: =Z56 -> 0 | AB56: 399163 | AC56: 399387 | AD56: 399614 | AE56: 399844 | AF56: =AE56 -> 399844
C57: Total current liabilities | G57: USD'k | H57: =SUM(H52:H56) -> 6857807 | I57: =SUM(I52:I56) -> 6933984 | J57: =SUM(J52:J56) -> 7257900 | K57: =SUM(K52:K56) -> 6855696 | L57: =SUM(L52:L56) -> 6855696 | M57: =SUM(M52:M56) -> 7853725 | N57: =SUM(N52:N56) -> 7626418 | O57: =SUM(O52:O56) -> 7939795 | ... AF57: =SUM(AF52:AF56) -> 8860655
C59: Non-current content liabilities | G59: USD'k | H59: 3560364 | I59: 3564440 | J59: 3419552 | K59: 3334323 | L59: =K59 -> 3334323 | M59: 3206051 | N59: 3208164 | O59: 2926574 | P59: 2618084 | Q59: =P59 -> 2618084 | R59: 2465626 | S59: 2265286 | T59: 2301026 | U59: 3094213 | V59: =U59 -> 3094213 | W59: 2945221 | X59: 2989961 | Y59: 2955368 | Z59: 3081277 | AA59: =Z59 -> 3081277 | AB59: 2908029 | AC59: 2849387 | AD59: 2668472 | AE59: 2578173 | AF59: =AE59 -> 2578173
C60: Long-term debt | G60: USD'k | H60: 10305023 | I60: 12594135 | J60: 12425746 | K60: 14759260 | L60: =K60 -> 14759260 | M60: 14170692 | N60: 15294998 | O60: 15547616 | P60: 15809095 | Q60: =P60 -> 15809095 | R60: 14860552 | S60: 14926889 | T60: 14793691 | U60: 14693072 | V60: =U60 -> 14693072 | W60: 14534561 | X60: 14233303 | Y60: 13888117 | Z60: 14353076 | AA60: =Z60 -> 14353076 | AB60: 14037965 | AC60: 14070151 | AD60: 13900754 | AE60: 14143417 | AF60: =AE60 -> 14143417
C61: Other non-current liabilities | G61: USD'k | H61: 792380 | I61: 973232 | J61: 977008 | K61: 1444276 | L61: =K61 -> 1444276 | M61: 1420148 | N61: 1710948 | O61: 1875235 | P61: 1982155 | Q61: =P61 -> 1982155 | R61: 1950986 | S61: 2082035 | T61: 2281277 | U61: 2459164 | V61: =U61 -> 2459164 | W61: 2567427 | X61: 2551675 | Y61: 2424637 | Z61: 2452040 | AA61: =Z61 -> 2452040 | AB61: 2400085 | AC61: 2389915 | AD61: 2486215 | AE61: 2561434 | AF61: =AE61 -> 2561434
C62: Total non-current assets | G62: USD'k | H62: =SUM(H59:H61) -> 14657767 | I62: =SUM(I59:I61) -> 17131807 | J62: =SUM(J59:J61) -> 16822306 | K62: =SUM(K59:K61) -> 19537859 | L62: =SUM(L59:L61) -> 19537859 | M62: =SUM(M59:M61) -> 18796891 | N62: =SUM(N59:N61) -> 20214110 | O62: =SUM(O59:O61) -> 20349425 | ... AF62: =SUM(AF59:AF61) -> 19283024
C64: Total liabilities | G64: USD'k | H64: =H62+H57 -> 21515574 | I64: =I62+I57 -> 24065791 | J64: =J62+J57 -> 24080206 | K64: =K62+K57 -> 26393555 | L64: =L62+L57 -> 26393555 | M64: =M62+M57 -> 26650616 | N64: =N62+N57 -> 27840528 | O64: =O62+O57 -> 28289220 | ... AF64: =AF62+AF57 -> 28143679
C66: Common stock | G66: USD'k | H66: 2439773 | I66: 2566365 | J66: 2677972 | K66: 2793929 | L66: =K66 -> 2793929 | M66: 2935532 | N66: 3127813 | O66: 3303482 | P66: 3447698 | Q66: =P66 -> 3447698 | R66: 3600084 | S66: 3721246 | T66: 3852531 | U66: 4024561 | V66: =U66 -> 4024561 | W66: 4155580 | X66: 4316870 | Y66: 4473962 | Z66: 4637601 | AA66: =Z66 -> 4637601 | AB66: 4762395 | AC66: 4874208 | AD66: 5011427 | AE66: 5145172 | AF66: =AE66 -> 5145172
C67: Treasury stock at cost | G67: USD'k | H67: 0 | I67: 0 | J67: 0 | K67: 0 | L67: =K67 -> 0 | M67: 0 | N67: 0 | O67: 0 | P67: 0 | Q67: =P67 -> 0 | R67: 0 | S67: -500022 | T67: -600022 | U67: -824190 | V67: =U67 -> -824190 | W67: -824190 | X67: -824190 | Y67: -824190 | Z67: -824190 | AA67: =Z67 -> -824190 | AB67: -1228920 | AC67: -1876753 | AD67: -4399677 | AE67: -6922200 | AF67: =AE67 -> -6922200
C68: Accumulated other comprehensive income (loss) | G68: USD'k | H68: -25600 | I68: -20352 | J68: -41246 | K68: -23521 | L68: =K68 -> -23521 | M68: -47054 | N68: -34072 | O68: -1147 | P68: 44398 | Q68: =P68 -> 44398 | R68: 4137 | S68: 9775 | T68: -19835 | U68: -40495 | V68: =U68 -> -40495 | W68: -74170 | X68: -144476 | Y68: -247643 | Z68: -217306 | AA68: =Z68 -> -217306 | AB68: -191695 | AC68: -139266 | AD68: -155571 | AE68: -223945 | AF68: =AE68 -> -223945
C69: Retained earnings | G69: USD'k | H69: 3288885 | I69: 3559535 | J69: 4224779 | K69: 4811749 | L69: =K69 -> 4811749 | M69: 5520816 | N69: 6241012 | O69: 7030988 | P69: 7573144 | Q69: =P69 -> 7573144 | R69: 9279859 | S69: 10632872 | T69: 12081943 | U69: 12689372 | V69: =U69 -> 12689372 | W69: 14286819 | X69: 15727770 | Y69: 17126012 | Z69: 17181296 | AA69: =Z69 -> 17181296 | AB69: 18486416 | AC69: 19974026 | AD69: 21651448 | AE69: 22589286 | AF69: =AE69 -> 22589286
C70: Total stockholder's equity | G70: USD'k | H70: =SUM(H66:H69) -> 5703058 | I70: =SUM(I66:I69) -> 6105548 | J70: =SUM(J66:J69) -> 6861505 | K70: =SUM(K66:K69) -> 7582157 | L70: =SUM(L66:L69) -> 7582157 | M70: =SUM(M66:M69) -> 8409294 | N70: =SUM(N66:N69) -> 9334753 | O70: =SUM(O66:O69) -> 10333323 | ... AF70: =SUM(AF66:AF69) -> 20588313
C72: Total liabilities and stockholder's equity | G72: USD'k | H72: =SUM(H64,H70) -> 27218632 | I72: =SUM(I64,I70) -> 30171339 | J72: =SUM(J64,J70) -> 30941711 | K72: =SUM(K64,K70) -> 33975712 | L72: =SUM(L64,L70) -> 33975712 | M72: =SUM(M64,M70) -> 35059910 | N72: =SUM(N64,N70) -> 37175281 | O72: =SUM(O64,O70) -> 38622543 | ... AF72: =SUM(AF64,AF70) -> 48731992
A74: C | C74: Cash Flow Statement
C76: Net income (loss) | G76: USD'k | H76: =H27 -> 344052 | I76: =I27 -> 270650 | J76: =J27 -> 665244 | K76: =K27 -> 586970 | L76: =L27 -> 1866916 | M76: =M27 -> 709067 | N76: =N27 -> 720196 | O76: =O27 -> 789976 | ... AF76: =AF27 -> 5407990
C78: Additions to content assets | G78: USD'k | H78: -2997746 | I78: -3325103 | J78: -3648292 | K78: -3945542 | L78: =SUM(H78:K78) -> -13916683 | M78: -3294275 | N78: -2510782 | O78: -2653886 | P78: -3320341 | Q78: =SUM(M78:P78) -> -11779284 | R78: -3284576 | S78: -4096750 | T78: -4666237 | U78: -5654639 | V78: =SUM(R78:U78) -> -17702202 | W78: -3584164 | X78: -4687011 | Y78: -4582671 | Z78: -3985192 | AA78: =SUM(W78:Z78) -> -16839038 | AB78: -2458666 | AC78: -3683007 | AD78: -2883839 | AE78: -3529191 | AF78: =SUM(AB78:AE78) -> -12554703
C79: Change in content liabilities | G79: USD'k | H79: -14698 | I79: -12414 | J79: -95548 | K79: -571351 | L79: =SUM(H79:K79) -> -694011 | M79: 258945 | N79: -108432 | O79: -379458 | P79: -528488 | Q79: =SUM(M79:P79) -> -757433 | R79: -266040 | S79: -312208 | T79: -29246 | U79: 840392 | V79: =SUM(R79:U79) -> 232898 | W79: -347149 | X79: 191228 | Y79: 60867 | Z79: 274364 | AA79: =SUM(W79:Z79) -> 179310 | AB79: -354791 | AC79: 46119 | AD79: -325989 | AE79: 49059 | AF79: =SUM(AB79:AE79) -> -585602
C80: Amortization of content assets | G80: USD'k | H80: 2124686 | I80: 2231915 | J80: 2279977 | K80: 2579669 | L80: =SUM(H80:K80) -> 9216247 | M80: 2483385 | N80: 2607159 | O80: 2733743 | P80: 2982625 | Q80: =SUM(M80:P80) -> 10806912 | R80: 2719196 | S80: 2806803 | T80: 2963051 | U80: 3741317 | V80: =SUM(R80:U80) -> 12230367 | W80: 3166365 | X80: 3261348 | Y80: 3653592 | Z80: 3944827 | AA80: =SUM(W80:Z80) -> 14026132 | AB80: 3459984 | AC80: 3410021 | AD80: 3573353 | AE80: 3754079 | AF80: =SUM(AB80:AE80) -> 14197437 | AK80: =Q80/L80-1 -> 0.17259357 | AL80: =R80/M80-1 -> 0.094955474 | AM80: =S80/N80-1 -> 0.076575307 | AN80: =T80/O80-1 -> 0.083880599 | AO80: =U80/P80-1 -> 0.25437056 | AP80: =V80/Q80-1 -> 0.13171709 | AQ80: =W80/R80-1 -> 0.16444898 | AR80: =X80/S80-1 -> 0.16194403 | ... BA80: =AG80/AB80-1 -> -1
C81: Depreciation and amortization of property, equipment and intangibles | G81: USD'k | H81: 23561 | I81: 25496 | J81: 26704 | K81: 27818 | L81: =SUM(H81:K81) -> 103579 | M81: 28517 | N81: 26661 | O81: 28589 | P81: 31943 | Q81: =SUM(M81:P81) -> 115710 | R81: 35741 | S81: 38434 | T81: 70253 | U81: 63984 | V81: =SUM(R81:U81) -> 208412 | W81: 74602 | X81: 83505 | Y81: 85188 | Z81: 93387 | AA81: =SUM(W81:Z81) -> 336682 | AB81: 90335 | AC81: 89385 | AD81: 90660 | AE81: 86567 | AF81: =SUM(AB81:AE81) -> 356947
C82: Stock-based compensation expense | G82: USD'k | H82: 101200 | I82: 103848 | J82: 100262 | K82: 100066 | L82: =SUM(H82:K82) -> 405376 | M82: 97019 | N82: 104210 | O82: 106357 | P82: 107594 | Q82: =SUM(M82:P82) -> 415180 | R82: 107230 | S82: 101583 | T82: 95078 | U82: 99329 | V82: =SUM(R82:U82) -> 403220 | W82: 119209 | X82: 150392 | Y82: 152062 | Z82: 153789 | AA82: =SUM(W82:Z82) -> 575452 | AB82: 99099 | AC82: 78030 | AD82: 79720 | AE82: 82519 | AF82: =SUM(AB82:AE82) -> 339368
C83: Foreign currency remeasurement loss (gain) on debt | G83: USD'k | H83: -57600 | I83: 61284 | J83: -171360 | K83: 122100 | L83: =SUM(H83:K83) -> -45576 | M83: -93060 | N83: 119161 | O83: 249194 | P83: 257983 | Q83: =SUM(M83:P83) -> 533278 | R83: -253330 | S83: 63074 | T83: -136488 | U83: -103917 | V83: =SUM(R83:U83) -> -430661 | W83: -161821 | X83: -304513 | Y83: -348458 | Z83: 461681 | AA83: =SUM(W83:Z83) -> -353111 | AB83: 80651 | AC83: 28952 | AD83: -172678 | AE83: 239371 | AF83: =SUM(AB83:AE83) -> 176296
C84: Other non-cash items | G84: USD'k | H84: 45708 | I84: 60695 | J84: 57934 | K84: 63893 | L84: =SUM(H84:K84) -> 228230 | M84: 65448 | N84: 70301 | O84: 83851 | P84: 73526 | Q84: =SUM(M84:P84) -> 293126 | R84: 72657 | S84: 108103 | T84: 102211 | U84: 93806 | V84: =SUM(R84:U84) -> 376777 | W84: 101968 | X84: 205374 | Y84: 102513 | Z84: 123688 | AA84: =SUM(W84:Z84) -> 533543 | AB84: 120008 | AC84: 121483 | AD84: 115688 | AE84: 154896 | AF84: =SUM(AB84:AE84) -> 512075
C85: Deferred income taxes | G85: USD'k | H85: 6627 | I85: 35519 | J85: 52105 | K85: -188694 | L85: =SUM(H85:K85) -> -94443 | M85: 46619 | N85: 223308 | O85: -40277 | P85: -159584 | Q85: =SUM(M85:P85) -> 70066 | R85: 159733 | S85: 51127 | T85: 50967 | U85: -62279 | V85: =SUM(R85:U85) -> 199548 | W85: -68906 | X85: -115820 | Y85: -57797 | Z85: 75973 | AA85: =SUM(W85:Z85) -> -166550 | AB85: -98782 | AC85: -103172 | AD85: -86277 | AE85: -171128 | AF85: =SUM(AB85:AE85) -> -459359
C86: Other current assets | G86: USD'k | H86: -32076 | I86: -24231 | J86: 145 | K86: -195951 | L86: =SUM(H86:K86) -> -252113 | M86: -127353 | N86: 3066 | O86: -22974 | P86: -40362 | Q86: =SUM(M86:P86) -> -187623 | R86: -221555 | S86: -52373 | T86: -95145 | U86: -608 | V86: =SUM(R86:U86) -> -369681 | W86: 41157 | X86: 123399 | Y86: -120071 | Z86: -398319 | AA86: =SUM(W86:Z86) -> -353834 | AB86: -88522 | AC86: -183049 | AD86: 103766 | AE86: -13198 | AF86: =SUM(AB86:AE86) -> -181003
C87: Accounts payable | G87: USD'k | H87: -124467 | I87: -2674 | J87: -7643 | K87: 230847 | L87: =SUM(H87:K87) -> 96063 | M87: -149153 | N87: -112027 | O87: 111677 | P87: 107898 | Q87: =SUM(M87:P87) -> -41605 | R87: -137313 | S87: 72313 | T87: 24836 | U87: 185279 | V87: =SUM(R87:U87) -> 145115 | W87: -215444 | X87: -122048 | Y87: 53875 | Z87: 125074 | AA87: =SUM(W87:Z87) -> -158543 | AB87: -89668 | AC87: 38332 | AD87: -68390 | AE87: 213228 | AF87: =SUM(AB87:AE87) -> 93502
C88: Accrued expenses and other liabilities | G88: USD'k | H88: 157647 | I88: -26705 | J88: 260872 | K88: -234036 | L88: =SUM(H88:K88) -> 157778 | M88: 214191 | N88: -105450 | O88: 266027 | P88: -176585 | Q88: =SUM(M88:P88) -> 198183 | R88: 177897 | S88: -171430 | T88: 269774 | U88: -95903 | V88: =SUM(R88:U88) -> 180338 | W88: 350763 | X88: -238719 | Y88: 212072 | Z88: -379629 | AA88: =SUM(W88:Z88) -> -55513 | AB88: 185299 | AC88: 177831 | AD88: -65029 | AE88: -194536 | AF88: =SUM(AB88:AE88) -> 103565
C89: Deferred revenue | G89: USD'k | H89: 47793 | I89: 84085 | J89: 22729 | K89: 9239 | L89: =SUM(H89:K89) -> 163846 | M89: 62008 | N89: 42508 | O89: 10941 | P89: 77790 | Q89: =SUM(M89:P89) -> 193247 | R89: 22279 | S89: 47093 | T89: -4732 | U89: 26710 | V89: =SUM(R89:U89) -> 91350 | W89: 16743 | X89: -10376 | Y89: -48420 | Z89: 69409 | AA89: =SUM(W89:Z89) -> 27356 | AB89: -2390 | AC89: 49647 | AD89: -5733 | AE89: 137184 | AF89: =SUM(AB89:AE89) -> 178708
C90: Other non-current assets and liabilities | G90: USD'k | H90: -4486 | I90: -26119 | J90: -44923 | K90: -47003 | L90: =SUM(H90:K90) -> -122531 | M90: -41446 | N90: -38803 | O90: -19999 | P90: -93827 | Q90: =SUM(M90:P90) -> -194075 | R90: -61368 | S90: -72543 | T90: -11014 | U90: -144174 | V90: =SUM(R90:U90) -> -289099 | W90: -167931 | X90: 125040 | Y90: -4184 | Z90: -170478 | AA90: =SUM(W90:Z90) -> -217553 | AB90: -68937 | AC90: -117950 | AD90: -40359 | AE90: -83674 | AF90: =SUM(AB90:AE90) -> -310920
C91: Net cash provided by (used in) operating activities | G91: USD'k | H91: =SUM(H76:H90) -> -379799 | I91: =SUM(I76:I90) -> -543754 | J91: =SUM(J76:J90) -> -501794 | K91: =SUM(K76:K90) -> -1461975 | L91: =SUM(L76:L90) -> -2887322 | M91: =SUM(M76:M90) -> 259912 | N91: =SUM(N76:N90) -> 1041076 | O91: =SUM(O76:O90) -> 1263761 | ... AF91: =SUM(AF76:AF90) -> 7274301
C93: Purchases of property and equipment | G93: USD'k | H93: -60381 | I93: -39584 | J93: -45333 | K93: -107737 | L93: =SUM(H93:K93) -> -253035 | M93: -98015 | N93: -141741 | O93: -109811 | P93: -148356 | Q93: =SUM(M93:P93) -> -497923 | R93: -81001 | S93: -110278 | T93: -167327 | U93: -165979 | V93: =SUM(R93:U93) -> -524585 | W93: -121158 | X93: -90018 | Y93: -84960 | Z93: -111593 | AA93: =SUM(W93:Z93) -> -407729 | AB93: -62019 | AC93: -100972 | AD93: -103929 | AE93: -81632 | AF93: =SUM(AB93:AE93) -> -348552
C94: Change in other assets | G94: USD'k | H94: -19722 | I94: -10452 | J94: -4021 | K94: -99834 | L94: =SUM(H94:K94) -> -134029 | M94: -288 | N94: -260 | O94: -8840 | P94: 1957 | Q94: =SUM(M94:P94) -> -7431 | R94: -4615 | S94: -1000 | T94: -21304 | U94: 0 | V94: =SUM(R94:U94) -> -26919 | W94: 0 | X94: 0 | Y94: 0 | Z94: 0 | AA94: =SUM(W94:Z94) -> 0 | AB94: 0 | AC94: 0 | AD94: 0 | AE94: 0 | AF94: =SUM(AB94:AE94) -> 0
C95: Acquisitions | G95: USD'k | H95: 0 | I95: 0 | J95: 0 | K95: 0 | L95: =SUM(H95:K95) -> 0 | M95: 0 | N95: 0 | O95: 0 | P95: 0 | Q95: =SUM(M95:P95) -> 0 | R95: 0 | S95: 0 | T95: 0 | U95: -788349 | V95: =SUM(R95:U95) -> -788349 | W95: -124521 | X95: -68876 | Y95: 0 | Z95: -563990 | AA95: =SUM(W95:Z95) -> -757387 | AB95: 0 | AC95: 0 | AD95: 0 | AE95: 0 | AF95: =SUM(AB95:AE95) -> 0
C96: Purchases of short-term investments | G96: USD'k | H96: 0 | I96: 0 | J96: 0 | K96: 0 | L96: =SUM(H96:K96) -> 0 | M96: 0 | N96: 0 | O96: 0 | P96: 0 | Q96: =SUM(M96:P96) -> 0 | R96: 0 | S96: 0 | T96: 0 | U96: 0 | V96: =SUM(R96:U96) -> 0 | W96: 0 | X96: 0 | Y96: 0 | Z96: -911276 | AA96: =SUM(W96:Z96) -> -911276 | AB96: -201634 | AC96: -303228 | AD96: 0 | AE96: 0 | AF96: =SUM(AB96:AE96) -> -504862
C97: Proceeds from maturities of short-term investments | G97: USD'k | H97: 0 | I97: 0 | J97: 0 | K97: 0 | L97: =SUM(H97:K97) -> 0 | M97: 0 | N97: 0 | O97: 0 | P97: 0 | Q97: =SUM(M97:P97) -> 0 | R97: 0 | S97: 0 | T97: 0 | U97: 0 | V97: =SUM(R97:U97) -> 0 | W97: 0 | X97: 0 | Y97: 0 | Z97: 0 | AA97: =SUM(W97:Z97) -> 0 | AB97: 0 | AC97: 501937 | AD97: 400000 | AE97: 493228 | AF97: =SUM(AB97:AE97) -> 1395165
C98: Net cash provided by (used in) investing activities | G98: USD'k | H98: =SUM(H93:H97) -> -80103 | I98: =SUM(I93:I97) -> -50036 | J98: =SUM(J93:J97) -> -49354 | K98: =SUM(K93:K97) -> -207571 | L98: =SUM(L93:L97) -> -387064 | M98: =SUM(M93:M97) -> -98303 | N98: =SUM(N93:N97) -> -142001 | O98: =SUM(O93:O97) -> -118651 | ... AF98: =SUM(AF93:AF97) -> 541751
C100: Proceeds from issuance of debt | G100: USD'k | H100: 0 | I100: 2243196 | J100: 0 | K100: 2226110 | L100: =SUM(H100:K100) -> 4469306 | M100: 0 | N100: 1009464 | O100: 0 | P100: 0 | Q100: =SUM(M100:P100) -> 1009464 | R100: 0 | S100: 0 | T100: 0 | U100: 0 | V100: =SUM(R100:U100) -> 0 | W100: 0 | X100: 0 | Y100: 0 | Z100: 0 | AA100: =SUM(W100:Z100) -> 0 | AB100: 0 | AC100: 0 | AD100: 0 | AE100: 0 | AF100: =SUM(AB100:AE100) -> 0
C101: Debt issuance costs | G101: USD'k | H101: 0 | I101: -18192 | J101: 0 | K101: -17942 | L101: =SUM(H101:K101) -> -36134 | M101: 0 | N101: -7559 | O101: 0 | P101: 0 | Q101: =SUM(M101:P101) -> -7559 | R101: 0 | S101: 0 | T101: 0 | U101: 0 | V101: =SUM(R101:U101) -> 0 | W101: 0 | X101: 0 | Y101: 0 | Z101: 0 | AA101: =SUM(W101:Z101) -> 0 | AB101: 0 | AC101: 0 | AD101: 0 | AE101: 0 | AF101: =SUM(AB101:AE101) -> 0
C102: Proceeds from issuance of common stock | G102: USD'k | H102: 22972 | I102: 21896 | J102: 11989 | K102: 15633 | L102: =SUM(H102:K102) -> 72490 | M102: 43694 | N102: 89060 | O102: 68665 | P102: 33987 | Q102: =SUM(M102:P102) -> 235406 | R102: 48071 | S102: 19749 | T102: 18445 | U102: 88149 | V102: =SUM(R102:U102) -> 174414 | W102: 13678 | X102: 11250 | Y102: 4113 | Z102: 6705 | AA102: =SUM(W102:Z102) -> 35746 | AB102: 26028 | AC102: 34717 | AD102: 57818 | AE102: 51427 | AF102: =SUM(AB102:AE102) -> 169990
C103: Repurchases of common stock | G103: USD'k | H103: 0 | I103: 0 | J103: 0 | K103: 0 | L103: =SUM(H103:K103) -> 0 | M103: 0 | N103: 0 | O103: 0 | P103: 0 | Q103: =SUM(M103:P103) -> 0 | R103: 0 | S103: -500022 | T103: -100000 | U103: 0 | V103: =SUM(R103:U103) -> -600022 | W103: 0 | X103: 0 | Y103: 0 | Z103: 0 | AA103: =SUM(W103:Z103) -> 0 | AB103: -400101 | AC103: -645146 | AD103: -2500100 | AE103: -2500000 | AF103: =SUM(AB103:AE103) -> -6045347
C104: Taxes paid related to net share settlement of equity awards | G104: USD'k | H104: 0 | I104: 0 | J104: 0 | K104: 0 | L104: =SUM(H104:K104) -> 0 | M104: 0 | N104: 0 | O104: 0 | P104: 0 | Q104: =SUM(M104:P104) -> 0 | R104: 0 | S104: 0 | T104: 0 | U104: -224168 | V104: =SUM(R104:U104) -> -224168 | W104: 0 | X104: 0 | Y104: 0 | Z104: 0 | AA104: =SUM(W104:Z104) -> 0 | AB104: 0 | AC104: 0 | AD104: 0 | AE104: 0 | AF104: =SUM(AB104:AE104) -> 0
C105: Repayments of debt | G105: USD'k | H105: 0 | I105: 0 | J105: 0 | K105: 0 | L105: =SUM(H105:K105) -> 0 | M105: 0 | N105: 0 | O105: 0 | P105: 0 | Q105: =SUM(M105:P105) -> 0 | R105: -500000 | S105: 0 | T105: 0 | U105: 0 | V105: =SUM(R105:U105) -> -500000 | W105: -700000 | X105: 0 | Y105: 0 | Z105: 0 | AA105: =SUM(W105:Z105) -> -700000 | AB105: 0 | AC105: 0 | AD105: 0 | AE105: 0 | AF105: =SUM(AB105:AE105) -> 0
C106: Other financing activities | G106: USD'k | H106: 0 | I106: 0 | J106: 0 | K106: 0 | L106: =SUM(H106:K106) -> 0 | M106: 0 | N106: 0 | O106: 0 | P106: 0 | Q106: =SUM(M106:P106) -> 0 | R106: 0 | S106: 0 | T106: 0 | U106: 0 | V106: =SUM(R106:U106) -> 0 | W106: 0 | X106: 0 | Y106: 0 | Z106: 0 | AA106: =SUM(W106:Z106) -> 0 | AB106: 0 | AC106: -38920 | AD106: -32826 | AE106: -3700 | AF106: =SUM(AB106:AE106) -> -75446
C107: Net cash provided by (used in) financing activities | G107: USD'k | H107: =SUM(H100:H106) -> 22972 | I107: =SUM(I100:I106) -> 2246900 | J107: =SUM(J100:J106) -> 11989 | K107: =SUM(K100:K106) -> 2223801 | L107: =SUM(L100:L106) -> 4505662 | M107: =SUM(M100:M106) -> 43694 | N107: =SUM(N100:N106) -> 1090965 | O107: =SUM(O100:O106) -> 68665 | ... AF107: =SUM(AF100:AF106) -> -5950803
C109: Effect on exchange rate changes on cash and equivalents | G109: USD'k | H109: -5014 | I109: 4998 | J109: -29325 | K109: 29810 | L109: =SUM(H109:K109) -> 469 | M109: -70902 | N109: 11819 | O109: 28459 | P109: 66674 | Q109: =SUM(M109:P109) -> 36050 | R109: -42138 | S109: 23477 | T109: -63843 | U109: -4236 | V109: =SUM(R109:U109) -> -86740 | W109: -11448 | X109: -145198 | Y109: -180058 | Z109: 166564 | AA109: =SUM(W109:Z109) -> -170140 | AB109: 26423 | AC109: 39626 | AD109: -122707 | AE109: 139342 | AF109: =SUM(AB109:AE109) -> 82684
C111: Net increase (decrease) in cash and equivalents | G111: USD'k | H111: =SUM(H91,H98,H107,H109) -> -441944 | I111: =SUM(I91,I98,I107,I109) -> 1658108 | J111: =SUM(J91,J98,J107,J109) -> -568484 | K111: =SUM(K91,K98,K107,K109) -> 584065 | L111: =SUM(L91,L98,L107,L109) -> 1231745 | M111: =SUM(M91,M98,M107,M109) -> 134401 | N111: =SUM(N91,N98,N107,N109) -> 2001859 | O111: =SUM(O91,O98,O107,O109) -> 1242234 | ... AF111: =SUM(AF91,AF98,AF107,AF109) -> 1947933
C113: Cash and equivalents at beginning of period | G113: USD'k | H113: 3812041 | I113: =H114 -> 3370097 | J113: =I114 -> 5028205 | K113: =J114 -> 4459721 | L113: =H113 -> 3812041 | M113: =L114 -> 5043786 | N113: =M114 -> 5178187 | O113: =N114 -> 7180046 | P113: =O114 -> 8422280 | Q113: =M113 -> 5043786 | R113: =Q114 -> 8238870 | S113: =R114 -> 8436453 | T113: =S114 -> 7804618 | U113: =T114 -> 7552968 | V113: =R113 -> 8238870 | W113: =V114 -> 6055111 | X113: =W114 -> 6034501 | Y113: =X114 -> 5844409 | Z113: =Y114 -> 6140314 | AA113: =W113 -> 6055111 | AB113: =AA114 -> 5170581 | AC113: =AB114 -> 6734129 | AD113: =AC114 -> 7661013 | AE113: =AD114 -> 7356835 | AF113: =AB113 -> 5170581
C114: Cash and equivalents at end of period | G114: USD'k | H114: =H111+H113 -> 3370097 | I114: =I111+I113 -> 5028205 | J114: =J111+J113 -> 4459721 | K114: =K111+K113 -> 5043786 | L114: =L111+L113 -> 5043786 | M114: =M111+M113 -> 5178187 | N114: =N111+N113 -> 7180046 | O114: =O111+O113 -> 8422280 | ... AF114: =AF111+AF113 -> 7118514
C116: Relevant Financial Information
C118: Debt
C119: Current portion of long-term debt | G119: USD'k | H119: =H56 -> 0 | I119: =I56 -> 0 | J119: =J56 -> 0 | K119: =K56 -> 0 | L119: =K119 -> 0 | M119: =M56 -> 498809 | N119: =N56 -> 499161 | O119: =O56 -> 499517 | P119: =P56 -> 499878 | Q119: =P119 -> 499878 | R119: =R56 -> 698788 | S119: =S56 -> 699128 | T119: =T56 -> 699473 | U119: =U56 -> 699823 | V119: =U119 -> 699823 | W119: =W56 -> 0 | X119: =X56 -> 0 | Y119: =Y56 -> 0 | Z119: =Z56 -> 0 | AA119: =Z119 -> 0 | AB119: =AB56 -> 399163 | AC119: =AC56 -> 399387 | AD119: =AD56 -> 399614 | AE119: =AE56 -> 399844 | AF119: =AE119 -> 399844
C120: Current portion of lease liabilities | G120: USD'k | L120: 190622 | Q120: 256222 | V120: 315189 | AA120: 355985 | AF120: 383312
C121: Long-term debt | G121: USD'k | H121: =H60 -> 10305023 | I121: =I60 -> 12594135 | J121: =J60 -> 12425746 | K121: =K60 -> 14759260 | L121: =L60 -> 14759260 | M121: =M60 -> 14170692 | N121: =N60 -> 15294998 | O121: =O60 -> 15547616 | ... AF121: =AF60 -> 14143417
C122: Long-term leases | G122: USD'k | L122: 1422612 | Q122: 1945631 | V122: 2408486 | AA122: 2222503 | AF122: 2046801
C123: Total debt | G123: USD'k | H123: =SUM(H119:H122) -> 10305023 | I123: =SUM(I119:I122) -> 12594135 | J123: =SUM(J119:J122) -> 12425746 | K123: =SUM(K119:K122) -> 14759260 | L123: =SUM(L119:L122) -> 16372494 | M123: =SUM(M119:M122) -> 14669501 | N123: =SUM(N119:N122) -> 15794159 | O123: =SUM(O119:O122) -> 16047133 | ... AF123: =SUM(AF119:AF122) -> 16973374
C125: Receivables
C126: Accounts receivable | G126: USD'k | L126: 454399 | Q126: 610819 | V126: 804320 | AA126: 988898 | AF126: 1287054
C127: Other receivables | G127: USD'k | L127: 0 | Q127: 0 | V127: 0 | AA127: 598000 | AF127: 555000
C128: Accounts and other receivables | G128: USD'k | L128: =SUM(L126:L127) -> 454399 | Q128: =SUM(Q126:Q127) -> 610819 | V128: =SUM(V126:V127) -> 804320 | AA128: =SUM(AA126:AA127) -> 1586898 | AF128: =SUM(AF126:AF127) -> 1842054
BC515: =IFERROR((Q515/#REF!)^(1/(_xlfn.NUMBERVALUE(LEFT(Q$6,4))-_xlfn.NUMBERVALUE(LEFT(#REF!,4))))-1,"NA") -> NA | BD515: =IFERROR((AZ515/AK515)^(1/(_xlfn.NUMBERVALUE(LEFT(AZ$6,4))-_xlfn.NUMBERVALUE(LEFT(AK$6,4))))-1,"NA") -> NA | BE515: =IFERROR((#REF!/BA515)^(1/(_xlfn.NUMBERVALUE(LEFT(#REF!,4))-_xlfn.NUMBERVALUE(LEFT(BA$6,4))))-1,"NA") -> NA | BF515: =IFERROR((#REF!/AK515)^(1/(_xlfn.NUMBERVALUE(LEFT(#REF!,4))-_xlfn.NUMBERVALUE(LEFT(AK$6,4))))-1,"NA") -> NA
BC518: =IFERROR((Q518/#REF!)^(1/(_xlfn.NUMBERVALUE(LEFT(Q$6,4))-_xlfn.NUMBERVALUE(LEFT(#REF!,4))))-1,"NA") -> NA | BD518: =IFERROR((AZ518/AK518)^(1/(_xlfn.NUMBERVALUE(LEFT(AZ$6,4))-_xlfn.NUMBERVALUE(LEFT(AK$6,4))))-1,"NA") -> NA | BE518: =IFERROR((#REF!/BA518)^(1/(_xlfn.NUMBERVALUE(LEFT(#REF!,4))-_xlfn.NUMBERVALUE(LEFT(BA$6,4))))-1,"NA") -> NA | BF518: =IFERROR((#REF!/AK518)^(1/(_xlfn.NUMBERVALUE(LEFT(#REF!,4))-_xlfn.NUMBERVALUE(LEFT(AK$6,4))))-1,"NA") -> NA
BC524: =IFERROR((Q524/#REF!)^(1/(_xlfn.NUMBERVALUE(LEFT(Q$6,4))-_xlfn.NUMBERVALUE(LEFT(#REF!,4))))-1,"NA") -> NA | BD524: =IFERROR((AZ524/AK524)^(1/(_xlfn.NUMBERVALUE(LEFT(AZ$6,4))-_xlfn.NUMBERVALUE(LEFT(AK$6,4))))-1,"NA") -> NA | BE524: =IFERROR((#REF!/BA524)^(1/(_xlfn.NUMBERVALUE(LEFT(#REF!,4))-_xlfn.NUMBERVALUE(LEFT(BA$6,4))))-1,"NA") -> NA | BF524: =IFERROR((#REF!/AK524)^(1/(_xlfn.NUMBERVALUE(LEFT(#REF!,4))-_xlfn.NUMBERVALUE(LEFT(AK$6,4))))-1,"NA") -> NA
...

Sheet Operating
C5: Operating Schedules | L5: Historicals | AK5: Forecasts | BC5: CAGR
G6: Units | H6: 19Q1 | I6: 19Q2 | J6: 19Q3 | K6: 19Q4 | L6: 2019A | M6: 20Q1 | N6: 20Q2 | O6: 20Q3 | P6: 20Q4 | Q6: 2020A | R6: 21Q1 | S6: 21Q2 | T6: 21Q3 | U6: 21Q4 | V6: 2021A | W6: 22Q1 | X6: 22Q2 | Y6: 22Q3 | Z6: 22Q4 | AA6: 2022A | AB6: 23Q1 | AC6: 23Q2 | AD6: 23Q3 | AE6: 23Q4 | AF6: 2023A | AG6: 24Q1 | AH6: 24Q2 | AI6: 24Q3 | AJ6: 24Q4 | AK6: 2024E | AL6: 25Q1 | AM6: 25Q2 | AN6: 25Q3 | AO6: 25Q4 | AP6: 2025E | AQ6: 26Q1 | AR6: 26Q2 | AS6: 26Q3 | AT6: 26Q4 | AU6: 2026E | AV6: 27Q1 | AW6: 27Q2 | AX6: 27Q3 | AY6: 27Q4 | AZ6: 2027E | BA6: ='Financial Statements'!BA6 -> 2028E | BC6: 2019A - 2020A | BD6: 2020A - 2021A | BE6: 2021A - 2022A | BF6: 2022A - 2023A
A8: R | C8: Revenue Schedule
C10: Summary
C11: Total streaming revenue | G11: USD'k | H11: =H54 -> 4440304 | I11: =I54 -> 4846916 | J11: =J54 -> 5173028 | K11: =K54 -> 5398982 | L11: =L54 -> 19859230 | M11: =M54 -> 5703363 | N11: =N54 -> 6086715 | O11: =O54 -> 6376803 | ... BA11: =BA54 -> 71196534 | BC11: =IFERROR((Q11/L11)^(1/(_xlfn.NUMBERVALUE(LEFT(Q$6,4))-_xlfn.NUMBERVALUE(LEFT(L$6,4))))-1,"NA") -> 0.246608 | BD11: =IFERROR((V11/Q11)^(1/(_xlfn.NUMBERVALUE(LEFT(V$6,4))-_xlfn.NUMBERVALUE(LEFT(Q$6,4))))-1,"NA") -> 0.19222375 | BE11: =IFERROR((AA11/V11)^(1/(_xlfn.NUMBERVALUE(LEFT(AA$6,4))-_xlfn.NUMBERVALUE(LEFT(V$6,4))))-1,"NA") -> 0.066214574 | BF11: =IFERROR((AF11/AA11)^(1/(_xlfn.NUMBERVALUE(LEFT(AF$6,4))-_xlfn.NUMBERVALUE(LEFT(AA$6,4))))-1,"NA") -> 0.068974141
C12: Domestic DVD revenue | G12: USD'k | H12: =H57 -> 80688 | I12: =I57 -> 76200 | J12: =J57 -> 71877 | K12: =K57 -> 68452 | L12: =SUM(H12:K12) -> 297217 | M12: =SUM(M50) -> 64328 | N12: =SUM(N50) -> 61571 | O12: =SUM(O50) -> 58834 | P12: =SUM(P50) -> 54648 | Q12: =SUM(M12:P12) -> 239381 | R12: =SUM(R50) -> 49575 | S12: =SUM(S50) -> 46292 | T12: =SUM(T50) -> 44232 | U12: =SUM(U50) -> 42249 | V12: =SUM(R12:U12) -> 182348 | W12: =SUM(W50) -> 39810 | X12: =SUM(X50) -> 37090 | Y12: =SUM(Y50) -> 35228 | Z12: =SUM(Z50) -> 33569 | AA12: =SUM(W12:Z12) -> 145697 | AB12: =SUM(AB50) -> 27613 | AC12: =SUM(AC50) -> 27613 | AD12: =SUM(AD50) -> 27613 | AF12: =SUM(AB12:AE12) -> 82839 | BC12: =IFERROR((Q12/L12)^(1/(_xlfn.NUMBERVALUE(LEFT(Q$6,4))-_xlfn.NUMBERVALUE(LEFT(L$6,4))))-1,"NA") -> -0.19459183 | BD12: =IFERROR((V12/Q12)^(1/(_xlfn.NUMBERVALUE(LEFT(V$6,4))-_xlfn.NUMBERVALUE(LEFT(Q$6,4))))-1,"NA") -> -0.23825199 | BE12: =IFERROR((AA12/V12)^(1/(_xlfn.NUMBERVALUE(LEFT(AA$6,4))-_xlfn.NUMBERVALUE(LEFT(V$6,4))))-1,"NA") -> -0.2009948 | BF12: =IFERROR((AF12/AA12)^(1/(_xlfn.NUMBERVALUE(LEFT(AF$6,4))-_xlfn.NUMBERVALUE(LEFT(AA$6,4))))-1,"NA") -> -0.43142961
C13: Total revenue | G13: USD'k | H13: =SUM(H11:H12) -> 4520992 | I13: =SUM(I11:I12) -> 4923116 | J13: =SUM(J11:J12) -> 5244905 | K13: =SUM(K11:K12) -> 5467434 | L13: =SUM(L11:L12) -> 20156447 | M13: =SUM(M11:M12) -> 5767691 | N13: =SUM(N11:N12) -> 6148286 | O13: =SUM(O11:O12) -> 6435637 | ... BA13: =SUM(BA11:BA12) -> 71196534 | BC13: =IFERROR((Q13/L13)^(1/(_xlfn.NUMBERVALUE(LEFT(Q$6,4))-_xlfn.NUMBERVALUE(LEFT(L$6,4))))-1,"NA") -> 0.24010229 | BD13: =IFERROR((V13/Q13)^(1/(_xlfn.NUMBERVALUE(LEFT(V$6,4))-_xlfn.NUMBERVALUE(LEFT(Q$6,4))))-1,"NA") -> 0.18810119 | BE13: =IFERROR((AA13/V13)^(1/(_xlfn.NUMBERVALUE(LEFT(AA$6,4))-_xlfn.NUMBERVALUE(LEFT(V$6,4))))-1,"NA") -> 0.06457388 | BF13: =IFERROR((AF13/AA13)^(1/(_xlfn.NUMBERVALUE(LEFT(AF$6,4))-_xlfn.NUMBERVALUE(LEFT(AA$6,4))))-1,"NA") -> 0.066668082
C14: YoY growth rate | G14: % | M14: =M13/H13-1 -> 0.27575784 | N14: =N13/I13-1 -> 0.24886068 | O14: =O13/J13-1 -> 0.22702642 | P14: =P13/K13-1 -> 0.21527612 | Q14: =Q13/L13-1 -> 0.24010229 | R14: =R13/M13-1 -> 0.24196702 | S14: =S13/N13-1 -> 0.19411768 | T14: =T13/O13-1 -> 0.16281683 | ... AZ14: =AZ13/AU13-1 -> 0.17617793
C16: Streaming as a % of total revenue | G16: % | H16: =H11/H$13 -> 0.98215259 | I16: =I11/I$13 -> 0.984522 | J16: =J11/J$13 -> 0.98629584 | K16: =K11/K$13 -> 0.98748005 | L16: =L11/L$13 -> 0.98525449 | M16: =M11/M$13 -> 0.98884684 | N16: =N11/N$13 -> 0.98998566 | O16: =O11/O$13 -> 0.99085809 | ... BA16: =BA11/BA$13 -> 1
C17: Domestic DVD as a % of total revenue | G17: % | H17: =H12/H$13 -> 0.01784741 | I17: =I12/I$13 -> 0.015478002 | J17: =J12/J$13 -> 0.013704157 | K17: =K12/K$13 -> 0.01251995 | L17: =L12/L$13 -> 0.014745505 | M17: =M12/M$13 -> 0.011153163 | N17: =N12/N$13 -> 0.010014336 | O17: =O12/O$13 -> 0.0091419078 | ... BA17: =BA12/BA$13 -> 0
C19: Streaming revenue breakdown
C20: Europe, Middle East, and Africa (EMEA)
C21: Revenues | G21: USD'k | H21: 1233379 | I21: 1319087 | J21: 1428040 | K21: 1562561 | L21: =SUM(H21:K21) -> 5543067 | M21: 1723474 | N21: 1892537 | O21: 2019083 | P21: 2137158 | Q21: =SUM(M21:P21) -> 7772252 | R21: 2343674 | S21: 2400480 | T21: 2432239 | U21: 2523426 | V21: =SUM(R21:U21) -> 9699819 | W21: 2561831 | X21: 2457235 | Y21: 2375814 | Z21: 2350135 | AA21: =SUM(W21:Z21) -> 9745015 | AB21: 2517641 | AC21: 2562170 | AD21: 2693146 | AE21: 2783530 | AF21: =SUM(AB21:AE21) -> 10556487 | AG21: =AG25*AG24*3 -> 2931364.9 | AH21: =AH25*AH24*3 -> 3019324.8 | AI21: =AI25*AI24*3 -> 3197240.7 | AJ21: =AJ25*AJ24*3 -> 3419632.9 | AK21: =SUM(AG21:AJ21) -> 12567563 | AL21: =AL25*AL24*3 -> 3543626.9 | AM21: =AM25*AM24*3 -> 3653048.8 | AN21: =AN25*AN24*3 -> 3873990.5 | AO21: =AO25*AO24*3 -> 4161759.6 | AP21: =SUM(AL21:AO21) -> 15232426 | AQ21: =AQ25*AQ24*3 -> 4295722.9 | AR21: =AR25*AR24*3 -> 4425555.7 | AS21: =AS25*AS24*3 -> 4688650.5 | AT21: =AT25*AT24*3 -> 5036755.7 | AU21: =SUM(AQ21:AT21) -> 18446685 | AV21: =AV25*AV24*3 -> 5187849.2 | AW21: =AW25*AW24*3 -> 5336066.5 | AX21: =AX25*AX24*3 -> 5639880.8 | AY21: =AY25*AY24*3 -> 6045278.6 | AZ21: =SUM(AV21:AY21) -> 22209075 | BA21: =BA25*BA24*3 -> 6228019.5 | BC21: =IFERROR((Q21/L21)^(1/(_xlfn.NUMBERVALUE(LEFT(Q$6,4))-_xlfn.NUMBERVALUE(LEFT(L$6,4))))-1,"NA") -> 0.40215733 | BD21: =IFERROR((V21/Q21)^(1/(_xlfn.NUMBERVALUE(LEFT(V$6,4))-_xlfn.NUMBERVALUE(LEFT(Q$6,4))))-1,"NA") -> 0.24800624 | BE21: =IFERROR((AA21/V21)^(1/(_xlfn.NUMBERVALUE(LEFT(AA$6,4))-_xlfn.NUMBERVALUE(LEFT(V$6,4))))-1,"NA") -> 0.0046594684 | BF21: =IFERROR((AF21/AA21)^(1/(_xlfn.NUMBERVALUE(LEFT(AF$6,4))-_xlfn.NUMBERVALUE(LEFT(AA$6,4))))-1,"NA") -> 0.083270472
C22: Paid net membership additions | G22: #'k | H22: 4724 | I22: 1687 | J22: 3126 | K22: 4423 | L22: =SUM(H22:K22) -> 13960 | M22: 6956 | N22: 2749 | O22: 759 | P22: 4456 | Q22: =SUM(M22:P22) -> 14920 | R22: 1810 | S22: 188 | T22: 1804 | U22: 3536 | V22: =SUM(R22:U22) -> 7338 | W22: -303 | X22: -767 | Y22: 568 | Z22: 3195 | AA22: =SUM(W22:Z22) -> 2693 | AB22: 644 | AC22: 2434 | AD22: 3953 | AE22: 5053 | AF22: =SUM(AB22:AE22) -> 12084 | AG22: =Drivers!H13 -> 798.56 | AH22: =Drivers!I13 -> 2726.08 | AI22: =Drivers!J13 -> 4617.104 | AJ22: =Drivers!K13 -> 6144.448 | AK22: =SUM(AG22:AJ22) -> 14286.192 | AL22: =Drivers!M13 -> 977.43744 | AM22: =Drivers!N13 -> 3069.5661 | AN22: =Drivers!O13 -> 5328.138 | AO22: =Drivers!P13 -> 7348.7598 | AP22: =SUM(AL22:AO22) -> 16723.901 | AQ22: =Drivers!R13 -> 1135.7823 | AR22: =Drivers!S13 -> 3401.0792 | AS22: =Drivers!T13 -> 6047.4366 | AT22: =Drivers!U13 -> 8539.2589 | AU22: =SUM(AQ22:AT22) -> 19123.557 | AV22: =Drivers!W13 -> 1274.9156 | AW22: =Drivers!X13 -> 3692.7218 | AX22: =Drivers!Y13 -> 6714.1665 | AY22: =Drivers!Z13 -> 9585.3181 | AZ22: =SUM(AV22:AY22) -> 21267.122 | BA22: =Drivers!AB13 -> 1415.4751 | BC22: =IFERROR((Q22/L22)^(1/(_xlfn.NUMBERVALUE(LEFT(Q$6,4))-_xlfn.NUMBERVALUE(LEFT(L$6,4))))-1,"NA") -> 0.068767908 | BD22: =IFERROR((V22/Q22)^(1/(_xlfn.NUMBERVALUE(LEFT(V$6,4))-_xlfn.NUMBERVALUE(LEFT(Q$6,4))))-1,"NA") -> -0.50817694 | BE22: =IFERROR((AA22/V22)^(1/(_xlfn.NUMBERVALUE(LEFT(AA$6,4))-_xlfn.NUMBERVALUE(LEFT(V$6,4))))-1,"NA") -> -0.63300627 | BF22: =IFERROR((AF22/AA22)^(1/(_xlfn.NUMBERVALUE(LEFT(AF$6,4))-_xlfn.NUMBERVALUE(LEFT(AA$6,4))))-1,"NA") -> 3.487189
C23: Paid memberships at end of period | G23: #'k | H23: 42542 | I23: 44229 | J23: 47355 | K23: 51778 | L23: =K23 -> 51778 | M23: 58734 | N23: 61483 | O23: 62242 | P23: 66698 | Q23: =P23 -> 66698 | R23: 68508 | S23: 68696 | T23: 70500 | U23: 74036 | V23: =U23 -> 74036 | W23: 73733 | X23: 72966 | Y23: 73534 | Z23: 76729 | AA23: =Z23 -> 76729 | AB23: 77373 | AC23: 79807 | AD23: 83760 | AE23: 88813 | AF23: =AE23 -> 88813 | AG23: =AF23+AG22 -> 89611.56 | AH23: =AG23+AH22 -> 92337.64 | AI23: =AH23+AI22 -> 96954.744 | AJ23: =AI23+AJ22 -> 103099.19 | AK23: =AJ23 -> 103099.19 | AL23: =AK23+AL22 -> 104076.63 | AM23: =AL23+AM22 -> 107146.2 | AN23: =AM23+AN22 -> 112474.33 | AO23: =AN23+AO22 -> 119823.09 | AP23: =AO23 -> 119823.09 | AQ23: =AP23+AQ22 -> 120958.88 | AR23: =AQ23+AR22 -> 124359.95 | AS23: =AR23+AS22 -> 130407.39 | AT23: =AS23+AT22 -> 138946.65 | AU23: =AT23 -> 138946.65 | AV23: =AU23+AV22 -> 140221.57 | AW23: =AV23+AW22 -> 143914.29 | AX23: =AW23+AX22 -> 150628.45 | AY23: =AX23+AY22 -> 160213.77 | AZ23: =AY23 -> 160213.77 | BA23: =AZ23+BA22 -> 161629.25 | BC23: =IFERROR((Q23/L23)^(1/(_xlfn.NUMBERVALUE(LEFT(Q$6,4))-_xlfn.NUMBERVALUE(LEFT(L$6,4))))-1,"NA") -> 0.28815327 | BD23: =IFERROR((V23/Q23)^(1/(_xlfn.NUMBERVALUE(LEFT(V$6,4))-_xlfn.NUMBERVALUE(LEFT(Q$6,4))))-1,"NA") -> 0.11001829 | BE23: =IFERROR((AA23/V23)^(1/(_xlfn.NUMBERVALUE(LEFT(AA$6,4))-_xlfn.NUMBERVALUE(LEFT(V$6,4))))-1,"NA") -> 0.036374196 | BF23: =IFERROR((AF23/AA23)^(1/(_xlfn.NUMBERVALUE(LEFT(AF$6,4))-_xlfn.NUMBERVALUE(LEFT(AA$6,4))))-1,"NA") -> 0.15748935
C24: Average paying memberships | G24: #'k | H24: 40180 | I24: 43386 | J24: 45792 | K24: 49567 | L24: =AVERAGE(H24:K24) -> 44731.25 | M24: 55256 | N24: 60109 | O24: 61863 | P24: 64470 | Q24: =AVERAGE(M24:P24) -> 60424.5 | R24: 67603 | S24: 68602 | T24: 69598 | U24: 72268 | V24: =AVERAGE(R24:U24) -> 69517.75 | W24: 73885 | X24: 73350 | Y24: 73250 | Z24: 75132 | AA24: =AVERAGE(W24:Z24) -> 73904.25 | AB24: 77051 | AC24: 78590 | AD24: 81784 | AE24: 86287 | AF24: =AVERAGE(AB24:AE24) -> 80928 | AG24: =Drivers!$I$62*Operating!AG23 -> 86936.809 | AH24: =Drivers!$I$62*Operating!AH23 -> 89581.52 | AI24: =Drivers!$I$62*Operating!AI23 -> 94060.812 | AJ24: =Drivers!$I$62*Operating!AJ23 -> 100021.86 | AK24: =AVERAGE(AG24:AJ24) -> 92650.25 | AL24: =Drivers!$I$62*Operating!AL23 -> 100970.12 | AM24: =Drivers!$I$62*Operating!AM23 -> 103948.07 | AN24: =Drivers!$I$62*Operating!AN23 -> 109117.17 | AO24: =Drivers!$I$62*Operating!AO23 -> 116246.58 | AP24: =AVERAGE(AL24:AO24) -> 107570.48 | AQ24: =Drivers!$I$62*Operating!AQ23 -> 117348.46 | AR24: =Drivers!$I$62*Operating!AR23 -> 120648.02 | AS24: =Drivers!$I$62*Operating!AS23 -> 126514.96 | AT24: =Drivers!$I$62*Operating!AT23 -> 134799.33 | AU24: =AVERAGE(AQ24:AT24) -> 124827.69 | AV24: =Drivers!$I$62*Operating!AV23 -> 136036.19 | AW24: =Drivers!$I$62*Operating!AW23 -> 139618.69 | AX24: =Drivers!$I$62*Operating!AX23 -> 146132.45 | AY24: =Drivers!$I$62*Operating!AY23 -> 155431.67 | AZ24: =AVERAGE(AV24:AY24) -> 144304.75 | BA24: =Drivers!$I$62*Operating!BA23 -> 156804.89 | BC24: =IFERROR((Q24/L24)^(1/(_xlfn.NUMBERVALUE(LEFT(Q$6,4))-_xlfn.NUMBERVALUE(LEFT(L$6,4))))-1,"NA") -> 0.35083415 | BD24: =IFERROR((V24/Q24)^(1/(_xlfn.NUMBERVALUE(LEFT(V$6,4))-_xlfn.NUMBERVALUE(LEFT(Q$6,4))))-1,"NA") -> 0.15048945 | BE24: =IFERROR((AA24/V24)^(1/(_xlfn.NUMBERVALUE(LEFT(AA$6,4))-_xlfn.NUMBERVALUE(LEFT(V$6,4))))-1,"NA") -> 0.063098993 | BF24: =IFERROR((AF24/AA24)^(1/(_xlfn.NUMBERVALUE(LEFT(AF$6,4))-_xlfn.NUMBERVALUE(LEFT(AA$6,4))))-1,"NA") -> 0.095038513
C25: Average monthly revenue per paying membership (ARPU) | G25: USD | H25: 10.23 | I25: 10.13 | J25: 10.4 | K25: 10.51 | L25: =AVERAGE(H25:K25) -> 10.3175 | M25: 10.4 | N25: 10.5 | O25: 10.88 | P25: 11.05 | Q25: =AVERAGE(M25:P25) -> 10.7075 | R25: 11.56 | S25: 11.66 | T25: 11.65 | U25: 11.64 | V25: =AVERAGE(R25:U25) -> 11.6275 | W25: 11.56 | X25: 11.17 | Y25: 10.81 | Z25: 10.43 | AA25: =AVERAGE(W25:Z25) -> 10.9925 | AB25: 10.89 | AC25: 10.87 | AD25: 10.98 | AE25: 10.75 | AF25: =AVERAGE(AB25:AE25) -> 10.8725 | AG25: =Drivers!H40 -> 11.239447 | AH25: =Drivers!I40 -> 11.234924 | AI25: =Drivers!J40 -> 11.330403 | AJ25: =Drivers!K40 -> 11.396285 | AK25: =AVERAGE(AG25:AJ25) -> 11.300265 | AL25: =Drivers!M40 -> 11.698599 | AM25: =Drivers!N40 -> 11.71434 | AN25: =Drivers!O40 -> 11.834345 | AO25: =Drivers!P40 -> 11.933712 | AP25: =AVERAGE(AL25:AO25) -> 11.795249 | AQ25: =Drivers!R40 -> 12.202185 | AR25: =Drivers!S40 -> 12.227181 | AS25: =Drivers!T40 -> 12.35335 | AT25: =Drivers!U40 -> 12.454947 | AU25: =AVERAGE(AQ25:AT25) -> 12.309416 | AV25: =Drivers!W40 -> 12.711934 | AW25: =Drivers!X40 -> 12.739618 | AX25: =Drivers!Y40 -> 12.864769 | AY25: =Drivers!Z40 -> 12.964494 | AZ25: =AVERAGE(AV25:AY25) -> 12.820204 | BA25: =Drivers!AB40 -> 13.239424 | BC25: =IFERROR((Q25/L25)^(1/(_xlfn.NUMBERVALUE(LEFT(Q$6,4))-_xlfn.NUMBERVALUE(LEFT(L$6,4))))-1,"NA") -> 0.037799855 | BD25: =IFERROR((V25/Q25)^(1/(_xlfn.NUMBERVALUE(LEFT(V$6,4))-_xlfn.NUMBERVALUE(LEFT(Q$6,4))))-1,"NA") -> 0.085921083 | BE25: =IFERROR((AA25/V25)^(1/(_xlfn.NUMBERVALUE(LEFT(AA$6,4))-_xlfn.NUMBERVALUE(LEFT(V$6,4))))-1,"NA") -> -0.054611911 | BF25: =IFERROR((AF25/AA25)^(1/(_xlfn.NUMBERVALUE(LEFT(AF$6,4))-_xlfn.NUMBERVALUE(LEFT(AA$6,4))))-1,"NA") -> -0.010916534
Q26: =Q24/L24-1 -> 0.35083415 | V26: =V24/Q24-1 -> 0.15048945 | AA26: =AA24/V24-1 -> 0.063098993 | AF26: =AF24/AA24-1 -> 0.095038513 | AK26: =AK24/AF24-1 -> 0.14484789 | AP26: =AP24/AK24-1 -> 0.16103825 | AU26: =AU24/AP24-1 -> 0.16042699 | AZ26: =AZ24/AU24-1 -> 0.15603155 | BA26: =BA24/AV24-1 -> 0.15267039 | BC26: =(BA24/AF24)^(1/5)-1 -> 0.14143756
C27: United States and Canada (UCAN) | Q27: =Q25/L25-1 -> 0.037799855 | V27: =V25/Q25-1 -> 0.085921083 | AA27: =AA25/V25-1 -> -0.054611911 | AF27: =AF25/AA25-1 -> -0.010916534 | AK27: =AK25/AF25-1 -> 0.039343743 | AP27: =AP25/AK25-1 -> 0.043802867 | AU27: =AU25/AP25-1 -> 0.04359102 | AZ27: =AZ25/AU25-1 -> 0.041495701 | BA27: =BA25/AV25-1 -> 0.041495701
C28: Revenues | G28: USD'k | H28: 2256851 | I28: 2501199 | J28: 2621250 | K28: 2671908 | L28: =SUM(H28:K28) -> 10051208 | M28: 2702776 | N28: 2839670 | O28: 2933445 | P28: 2979505 | Q28: =SUM(M28:P28) -> 11455396 | R28: 3170972 | S28: 3234643 | T28: 3257697 | U28: 3308788 | V28: =SUM(R28:U28) -> 12972100 | W28: 3350424 | X28: 3537863 | Y28: 3601565 | Z28: 3594791 | AA28: =SUM(W28:Z28) -> 14084643 | AB28: 3608645 | AC28: 3599448 | AD28: 3735133 | AE28: 3930557 | AF28: =SUM(AB28:AE28) -> 14873783 | AG28: =AG32*AG31*3 -> 4039647.5 | AH28: =AH32*AH31*3 -> 4111214.9 | AI28: =AI32*AI31*3 -> 4266096.3 | AJ28: =AJ32*AJ31*3 -> 4477534.2 | AK28: =SUM(AG28:AJ28) -> 16894493 | AL28: =AL32*AL31*3 -> 4605516.7 | AM28: =AM32*AM31*3 -> 4694782 | AN28: =AN32*AN31*3 -> 4870025.6 | AO28: =AO32*AO31*3 -> 5127072.2 | AP28: =SUM(AL28:AO28) -> 19297396 | AQ28: =AQ32*AQ31*3 -> 5271862 | AR28: =AR32*AR31*3 -> 5375112.5 | AS28: =AS32*AS31*3 -> 5574463.2 | AT28: =AT32*AT31*3 -> 5879467.1 | AU28: =SUM(AQ28:AT28) -> 22100905 | AV28: =AV32*AV31*3 -> 6034203.3 | AW28: =AW32*AW31*3 -> 6151954.5 | AX28: =AX32*AX31*3 -> 6375997.2 | AY28: =AY32*AY31*3 -> 6724480 | AZ28: =SUM(AV28:AY28) -> 25286635 | BA28: =BA32*BA31*3 -> 6906421.5 | BC28: =IFERROR((Q28/L28)^(1/(_xlfn.NUMBERVALUE(LEFT(Q$6,4))-_xlfn.NUMBERVALUE(LEFT(L$6,4))))-1,"NA") -> 0.13970341 | BD28: =IFERROR((V28/Q28)^(1/(_xlfn.NUMBERVALUE(LEFT(V$6,4))-_xlfn.NUMBERVALUE(LEFT(Q$6,4))))-1,"NA") -> 0.13240084 | BE28: =IFERROR((AA28/V28)^(1/(_xlfn.NUMBERVALUE(LEFT(AA$6,4))-_xlfn.NUMBERVALUE(LEFT(V$6,4))))-1,"NA") -> 0.085764294 | BF28: =IFERROR((AF28/AA28)^(1/(_xlfn.NUMBERVALUE(LEFT(AF$6,4))-_xlfn.NUMBERVALUE(LEFT(AA$6,4))))-1,"NA") -> 0.056028399
C29: Paid net membership additions | G29: #'k | H29: 1876 | I29: -132 | J29: 613 | K29: 548 | L29: =SUM(H29:K29) -> 2905 | M29: 2307 | N29: 2935 | O29: 177 | P29: 855 | Q29: =SUM(M29:P29) -> 6274 | R29: 448 | S29: -433 | T29: 73 | U29: 1191 | V29: =SUM(R29:U29) -> 1279 | W29: -636 | X29: -1296 | Y29: 104 | Z29: 909 | AA29: =SUM(W29:Z29) -> -919 | AB29: 102 | AC29: 1173 | AD29: 1750 | AE29: 2807 | AF29: =SUM(AB29:AE29) -> 5832 | AG29: =Drivers!H14 -> 126.48 | AH29: =Drivers!I14 -> 1299.684 | AI29: =Drivers!J14 -> 1897 | AJ29: =Drivers!K14 -> 3278.576 | AK29: =SUM(AG29:AJ29) -> 6601.74 | AL29: =Drivers!M14 -> 150.32148 | AM29: =Drivers!N14 -> 1450.4473 | AN29: =Drivers!O14 -> 2144.5585 | AO29: =Drivers!P14 -> 3849.0482 | AP29: =SUM(AL29:AO29) -> 7594.3755 | AQ29: =Drivers!R14 -> 171.36649 | AR29: =Drivers!S14 -> 1592.5912 | AS29: =Drivers!T14 -> 2354.7252 | AT29: =Drivers!U14 -> 4387.915 | AU29: =SUM(AQ29:AT29) -> 8506.5979 | AV29: =Drivers!W14 -> 188.84587 | AW29: =Drivers!X14 -> 1734.7299 | AX29: =Drivers!Y14 -> 2564.8845 | AY29: =Drivers!Z14 -> 4835.4823 | AZ29: =SUM(AV29:AY29) -> 9323.9426 | BA29: =Drivers!AB14 -> 206.90426 | BC29: =IFERROR((Q29/L29)^(1/(_xlfn.NUMBERVALUE(LEFT(Q$6,4))-_xlfn.NUMBERVALUE(LEFT(L$6,4))))-1,"NA") -> 1.1597246 | BD29: =IFERROR((V29/Q29)^(1/(_xlfn.NUMBERVALUE(LEFT(V$6,4))-_xlfn.NUMBERVALUE(LEFT(Q$6,4))))-1,"NA") -> -0.79614281 | BE29: =IFERROR((AA29/V29)^(1/(_xlfn.NUMBERVALUE(LEFT(AA$6,4))-_xlfn.NUMBERVALUE(LEFT(V$6,4))))-1,"NA") -> -1.7185301 | BF29: =IFERROR((AF29/AA29)^(1/(_xlfn.NUMBERVALUE(LEFT(AF$6,4))-_xlfn.NUMBERVALUE(LEFT(AA$6,4))))-1,"NA") -> -7.3460283
C30: Paid memberships at end of period | G30: #'k | H30: 66633 | I30: 66501 | J30: 67114 | K30: 67662 | L30: =K30 -> 67662 | M30: 69969 | N30: 72904 | O30: 73081 | P30: 73936 | Q30: =P30 -> 73936 | R30: 74384 | S30: 73951 | T30: 74024 | U30: 75215 | V30: =U30 -> 75215 | W30: 74579 | X30: 73283 | Y30: 73387 | Z30: 74296 | AA30: =Z30 -> 74296 | AB30: 74398 | AC30: 75571 | AD30: 77321 | AE30: 80128 | AF30: =AE30 -> 80128 | AG30: =AF30+AG29 -> 80254.48 | AH30: =AG30+AH29 -> 81554.164 | AI30: =AH30+AI29 -> 83451.164 | AJ30: =AI30+AJ29 -> 86729.74 | AK30: =AJ30 -> 86729.74 | AL30: =AK30+AL29 -> 86880.061 | AM30: =AL30+AM29 -> 88330.509 | AN30: =AM30+AN29 -> 90475.067 | AO30: =AN30+AO29 -> 94324.116 | AP30: =AO30 -> 94324.116 | AQ30: =AP30+AQ29 -> 94495.482 | AR30: =AQ30+AR29 -> 96088.073 | AS30: =AR30+AS29 -> 98442.798 | AT30: =AS30+AT29 -> 102830.71 | AU30: =AT30 -> 102830.71 | AV30: =AU30+AV29 -> 103019.56 | AW30: =AV30+AW29 -> 104754.29 | AX30: =AW30+AX29 -> 107319.17 | AY30: =AX30+AY29 -> 112154.66 | AZ30: =AY30 -> 112154.66 | BA30: =AZ30+BA29 -> 112361.56 | BC30: =IFERROR((Q30/L30)^(1/(_xlfn.NUMBERVALUE(LEFT(Q$6,4))-_xlfn.NUMBERVALUE(LEFT(L$6,4))))-1,"NA") -> 0.092725607 | BD30: =IFERROR((V30/Q30)^(1/(_xlfn.NUMBERVALUE(LEFT(V$6,4))-_xlfn.NUMBERVALUE(LEFT(Q$6,4))))-1,"NA") -> 0.017298745 | BE30: =IFERROR((AA30/V30)^(1/(_xlfn.NUMBERVALUE(LEFT(AA$6,4))-_xlfn.NUMBERVALUE(LEFT(V$6,4))))-1,"NA") -> -0.012218308 | BF30: =IFERROR((AF30/AA30)^(1/(_xlfn.NUMBERVALUE(LEFT(AF$6,4))-_xlfn.NUMBERVALUE(LEFT(AA$6,4))))-1,"NA") -> 0.078496824
C31: Average paying memberships | G31: #'k | H31: 65695 | I31: 66567 | J31: 66808 | K31: 67388 | L31: =AVERAGE(H31:K31) -> 66614.5 | M31: 68816 | N31: 71437 | O31: 72993 | P31: 73509 | Q31: =AVERAGE(M31:P31) -> 71688.75 | R31: 74160 | S31: 74168 | T31: 73988 | U31: 74620 | V31: =AVERAGE(R31:U31) -> 74234 | W31: 74897 | X31: 73931 | Y31: 73335 | Z31: 73842 | AA31: =AVERAGE(W31:Z31) -> 74001.25 | AB31: 74347 | AC31: 74985 | AD31: 76446 | AE31: 78725 | AF31: =AVERAGE(AB31:AE31) -> 76125.75 | AG31: =Drivers!$I$63*Operating!AG30 -> 79590.685 | AH31: =Drivers!$I$63*Operating!AH30 -> 80879.619 | AI31: =Drivers!$I$63*Operating!AI30 -> 82760.929 | AJ31: =Drivers!$I$63*Operating!AJ30 -> 86012.387 | AK31: =AVERAGE(AG31:AJ31) -> 82310.905 | AL31: =Drivers!$I$63*Operating!AL30 -> 86161.465 | AM31: =Drivers!$I$63*Operating!AM30 -> 87599.916 | AN31: =Drivers!$I$63*Operating!AN30 -> 89726.736 | AO31: =Drivers!$I$63*Operating!AO30 -> 93543.949 | AP31: =AVERAGE(AL31:AO31) -> 89258.017 | AQ31: =Drivers!$I$63*Operating!AQ30 -> 93713.898 | AR31: =Drivers!$I$63*Operating!AR30 -> 95293.316 | AS31: =Drivers!$I$63*Operating!AS30 -> 97628.565 | AT31: =Drivers!$I$63*Operating!AT30 -> 101980.19 | AU31: =AVERAGE(AQ31:AT31) -> 97153.992 | AV31: =Drivers!$I$63*Operating!AV30 -> 102167.47 | AW31: =Drivers!$I$63*Operating!AW30 -> 103887.85 | AX31: =Drivers!$I$63*Operating!AX30 -> 106431.52 | AY31: =Drivers!$I$63*Operating!AY30 -> 111227.01 | AZ31: =AVERAGE(AV31:AY31) -> 105928.46 | BA31: =Drivers!$I$63*Operating!BA30 -> 111432.2 | BC31: =IFERROR((Q31/L31)^(1/(_xlfn.NUMBERVALUE(LEFT(Q$6,4))-_xlfn.NUMBERVALUE(LEFT(L$6,4))))-1,"NA") -> 0.076173356 | BD31: =IFERROR((V31/Q31)^(1/(_xlfn.NUMBERVALUE(LEFT(V$6,4))-_xlfn.NUMBERVALUE(LEFT(Q$6,4))))-1,"NA") -> 0.035504176 | BE31: =IFERROR((AA31/V31)^(1/(_xlfn.NUMBERVALUE(LEFT(AA$6,4))-_xlfn.NUMBERVALUE(LEFT(V$6,4))))-1,"NA") -> -0.0031353558 | BF31: =IFERROR((AF31/AA31)^(1/(_xlfn.NUMBERVALUE(LEFT(AF$6,4))-_xlfn.NUMBERVALUE(LEFT(AA$6,4))))-1,"NA") -> 0.028708975
C32: Average monthly revenue per paying membership (ARPU) | G32: USD | H32: 11.45 | I32: 12.52 | J32: 13.08 | K32: 13.22 | L32: =AVERAGE(H32:K32) -> 12.5675 | M32: 13.09 | N32: 13.25 | O32: 13.4 | P32: 13.51 | Q32: =AVERAGE(M32:P32) -> 13.3125 | R32: 14.25 | S32: 14.54 | T32: 14.68 | U32: 14.78 | V32: =AVERAGE(R32:U32) -> 14.5625 | W32: 14.91 | X32: 15.95 | Y32: 16.37 | Z32: 16.23 | AA32: =AVERAGE(W32:Z32) -> 15.865 | AB32: 16.18 | AC32: 16 | AD32: 16.29 | AE32: 16.64 | AF32: =AVERAGE(AB32:AE32) -> 16.2775 | AG32: =Drivers!H41 -> 16.918427 | AH32: =Drivers!I41 -> 16.943761 | AI32: =Drivers!J41 -> 17.182409 | AJ32: =Drivers!K41 -> 17.352285 | AK32: =AVERAGE(AG32:AJ32) -> 17.09922 | AL32: =Drivers!M41 -> 17.817388 | AM32: =Drivers!N41 -> 17.864484 | AN32: =Drivers!O41 -> 18.092064 | AO32: =Drivers!P41 -> 18.269745 | AP32: =AVERAGE(AL32:AO32) -> 18.01092 | AQ32: =Drivers!R41 -> 18.751619 | AR32: =Drivers!S41 -> 18.801992 | AS32: =Drivers!T41 -> 19.032897 | AT32: =Drivers!U41 -> 19.217678 | AU32: =AVERAGE(AQ32:AT32) -> 18.951046 | AV32: =Drivers!W41 -> 19.687295 | AW32: =Drivers!X41 -> 19.739088 | AX32: =Drivers!Y41 -> 19.969012 | AY32: =Drivers!Z41 -> 20.152419 | AZ32: =AVERAGE(AV32:AY32) -> 19.886954 | BA32: =Drivers!AB41 -> 20.659562 | BC32: =IFERROR((Q32/L32)^(1/(_xlfn.NUMBERVALUE(LEFT(Q$6,4))-_xlfn.NUMBERVALUE(LEFT(L$6,4))))-1,"NA") -> 0.059279889 | BD32: =IFERROR((V32/Q32)^(1/(_xlfn.NUMBERVALUE(LEFT(V$6,4))-_xlfn.NUMBERVALUE(LEFT(Q$6,4))))-1,"NA") -> 0.093896714 | BE32: =IFERROR((AA32/V32)^(1/(_xlfn.NUMBERVALUE(LEFT(AA$6,4))-_xlfn.NUMBERVALUE(LEFT(V$6,4))))-1,"NA") -> 0.08944206 | BF32: =IFERROR((AF32/AA32)^(1/(_xlfn.NUMBERVALUE(LEFT(AF$6,4))-_xlfn.NUMBERVALUE(LEFT(AA$6,4))))-1,"NA") -> 0.02600063
Q33: =Q31/L31-1 -> 0.076173356 | V33: =V31/Q31-1 -> 0.035504176 | AA33: =AA31/V31-1 -> -0.0031353558 | AF33: =AF31/AA31-1 -> 0.028708975 | AK33: =AK31/AF31-1 -> 0.081249183 | AP33: =AP31/AK31-1 -> 0.084400865 | AU33: =AU31/AP31-1 -> 0.088462364 | AZ33: =AZ31/AU31-1 -> 0.090315102 | BA33: =BA31/AV31-1 -> 0.090681818 | BC33: =(BA31/AF31)^(1/5)-1 -> 0.079184817
C34: Latin America (LATAM) | Q34: =Q32/L32-1 -> 0.059279889 | V34: =V32/Q32-1 -> 0.093896714 | AA34: =AA32/V32-1 -> 0.08944206 | AF34: =AF32/AA32-1 -> 0.02600063 | AK34: =AK32/AF32-1 -> 0.050481971 | AP34: =AP32/AK32-1 -> 0.05331821 | AU34: =AU32/AP32-1 -> 0.052197572 | AZ34: =AZ32/AU32-1 -> 0.049385516 | BA34: =BA32/AV32-1 -> 0.049385516
C35: Revenues | G35: USD'k | H35: 630472 | I35: 677136 | J35: 741434 | K35: 746392 | L35: =SUM(H35:K35) -> 2795434 | M35: 793453 | N35: 785368 | O35: 789384 | P35: 788522 | Q35: =SUM(M35:P35) -> 3156727 | R35: 836647 | S35: 860882 | T35: 915297 | U35: 964150 | V35: =SUM(R35:U35) -> 3576976 | W35: 998948 | X35: 1030234 | Y35: 1023945 | Z35: 1016846 | AA35: =SUM(W35:Z35) -> 4069973 | AB35: 1070192 | AC35: 1077435 | AD35: 1142811 | AE35: 1156023 | AF35: =SUM(AB35:AE35) -> 4446461 | AG35: =AG39*AG38*3 -> 1226574.3 | AH35: =AH39*AH38*3 -> 1264263.7 | AI35: =AI39*AI38*3 -> 1309499.3 | AJ35: =AJ39*AJ38*3 -> 1383646.1 | AK35: =SUM(AG35:AJ35) -> 5183983.4 | AL35: =AL39*AL38*3 -> 1443079.2 | AM35: =AM39*AM38*3 -> 1486651.5 | AN35: =AN39*AN38*3 -> 1536201.7 | AO35: =AO39*AO38*3 -> 1629174.1 | AP35: =SUM(AL35:AO35) -> 6095106.5 | AQ35: =AQ39*AQ38*3 -> 1693218.4 | AR35: =AR39*AR38*3 -> 1743247.4 | AS35: =AS39*AS38*3 -> 1798935.1 | AT35: =AT39*AT38*3 -> 1906238.2 | AU35: =SUM(AQ35:AT35) -> 7141639.1 | AV35: =AV39*AV38*3 -> 1978218.2 | AW35: =AW39*AW38*3 -> 2034511.1 | AX35: =AX39*AX38*3 -> 2097116.3 | AY35: =AY39*AY38*3 -> 2216702.6 | AZ35: =SUM(AV35:AY35) -> 8326548.2 | BA35: =BA39*BA38*3 -> 2298326.8 | BC35: =IFERROR((Q35/L35)^(1/(_xlfn.NUMBERVALUE(LEFT(Q$6,4))-_xlfn.NUMBERVALUE(LEFT(L$6,4))))-1,"NA") -> 0.12924397 | BD35: =IFERROR((V35/Q35)^(1/(_xlfn.NUMBERVALUE(LEFT(V$6,4))-_xlfn.NUMBERVALUE(LEFT(Q$6,4))))-1,"NA") -> 0.13312808 | BE35: =IFERROR((AA35/V35)^(1/(_xlfn.NUMBERVALUE(LEFT(AA$6,4))-_xlfn.NUMBERVALUE(LEFT(V$6,4))))-1,"NA") -> 0.13782508 | BF35: =IFERROR((AF35/AA35)^(1/(_xlfn.NUMBERVALUE(LEFT(AF$6,4))-_xlfn.NUMBERVALUE(LEFT(AA$6,4))))-1,"NA") -> 0.092503808
C36: Paid net membership additions | G36: #'k | H36: 1470 | I36: 343 | J36: 1490 | K36: 2037 | L36: =SUM(H36:K36) -> 5340 | M36: 2901 | N36: 1750 | O36: 256 | P36: 1213 | Q36: =SUM(M36:P36) -> 6120 | R36: 357 | S36: 764 | T36: 330 | U36: 973 | V36: =SUM(R36:U36) -> 2424 | W36: -351 | X36: 14 | Y36: 312 | Z36: 1763 | AA36: =SUM(W36:Z36) -> 1738 | AB36: -450 | AC36: 1217 | AD36: 1179 | AE36: 2352 | AF36: =SUM(AB36:AE36) -> 4298 | AG36: =Drivers!H15 -> 973.896 | AH36: =Drivers!I15 -> 1363.04 | AI36: =Drivers!J15 -> 1278.036 | AJ36: =Drivers!K15 -> 2718.912 | AK36: =SUM(AG36:AJ36) -> 6333.884 | AL36: =Drivers!M15 -> 1118.5196 | AM36: =Drivers!N15 -> 1528.6494 | AN36: =Drivers!O15 -> 1381.5569 | AO36: =Drivers!P15 -> 3049.2598 | AP36: =SUM(AL36:AO36) -> 7077.9856 | AQ36: =Drivers!R15 -> 1220.3048 | AR36: =Drivers!S15 -> 1687.6289 | AS36: =Drivers!T15 -> 1471.3581 | AT36: =Drivers!U15 -> 3366.3828 | AU36: =SUM(AQ36:AT36) -> 7745.6747 | AV36: =Drivers!W15 -> 1306.3363 | AW36: =Drivers!X15 -> 1826.4364 | AX36: =Drivers!Y15 -> 1575.0889 | AY36: =Drivers!Z15 -> 3603.7128 | AZ36: =SUM(AV36:AY36) -> 8311.5744 | BA36: =Drivers!AB15 -> 1402.2704 | BC36: =IFERROR((Q36/L36)^(1/(_xlfn.NUMBERVALUE(LEFT(Q$6,4))-_xlfn.NUMBERVALUE(LEFT(L$6,4))))-1,"NA") -> 0.14606742 | BD36: =IFERROR((V36/Q36)^(1/(_xlfn.NUMBERVALUE(LEFT(V$6,4))-_xlfn.NUMBERVALUE(LEFT(Q$6,4))))-1,"NA") -> -0.60392157 | BE36: =IFERROR((AA36/V36)^(1/(_xlfn.NUMBERVALUE(LEFT(AA$6,4))-_xlfn.NUMBERVALUE(LEFT(V$6,4))))-1,"NA") -> -0.2830033 | BF36: =IFERROR((AF36/AA36)^(1/(_xlfn.NUMBERVALUE(LEFT(AF$6,4))-_xlfn.NUMBERVALUE(LEFT(AA$6,4))))-1,"NA") -> 1.4729574
C37: Paid memberships at end of period | G37: #'k | H37: 27547 | I37: 27890 | J37: 29380 | K37: 31417 | L37: =K37 -> 31417 | M37: 34318 | N37: 36068 | O37: 36324 | P37: 37537 | Q37: =P37 -> 37537 | R37: 37894 | S37: 38658 | T37: 38988 | U37: 39961 | V37: =U37 -> 39961 | W37: 39610 | X37: 39624 | Y37: 39936 | Z37: 41699 | AA37: =Z37 -> 41699 | AB37: 41249 | AC37: 42466 | AD37: 43645 | AE37: 45997 | AF37: =AE37 -> 45997 | AG37: =AF37+AG36 -> 46970.896 | AH37: =AG37+AH36 -> 48333.936 | AI37: =AH37+AI36 -> 49611.972 | AJ37: =AI37+AJ36 -> 52330.884 | AK37: =AJ37 -> 52330.884 | AL37: =AK37+AL36 -> 53449.404 | AM37: =AL37+AM36 -> 54978.053 | AN37: =AM37+AN36 -> 56359.61 | AO37: =AN37+AO36 -> 59408.87 | AP37: =AO37 -> 59408.87 | AQ37: =AP37+AQ36 -> 60629.174 | AR37: =AQ37+AR36 -> 62316.803 | AS37: =AR37+AS36 -> 63788.161 | AT37: =AS37+AT36 -> 67154.544 | AU37: =AT37 -> 67154.544 | AV37: =AU37+AV36 -> 68460.881 | AW37: =AV37+AW36 -> 70287.317 | AX37: =AW37+AX36 -> 71862.406 | AY37: =AX37+AY36 -> 75466.119 | AZ37: =AY37 -> 75466.119 | BA37: =AZ37+BA36 -> 76868.389 | BC37: =IFERROR((Q37/L37)^(1/(_xlfn.NUMBERVALUE(LEFT(Q$6,4))-_xlfn.NUMBERVALUE(LEFT(L$6,4))))-1,"NA") -> 0.19479899 | BD37: =IFERROR((V37/Q37)^(1/(_xlfn.NUMBERVALUE(LEFT(V$6,4))-_xlfn.NUMBERVALUE(LEFT(Q$6,4))))-1,"NA") -> 0.064576285 | BE37: =IFERROR((AA37/V37)^(1/(_xlfn.NUMBERVALUE(LEFT(AA$6,4))-_xlfn.NUMBERVALUE(LEFT(V$6,4))))-1,"NA") -> 0.043492405 | BF37: =IFERROR((AF37/AA37)^(1/(_xlfn.NUMBERVALUE(LEFT(AF$6,4))-_xlfn.NUMBERVALUE(LEFT(AA$6,4))))-1,"NA") -> 0.10307202
C38: Average paying memberships | G38: #'k | H38: 26812 | I38: 27719 | J38: 28635 | K38: 30399 | L38: =AVERAGE(H38:K38) -> 28391.25 | M38: 32868 | N38: 35193 | O38: 36196 | P38: 36931 | Q38: =AVERAGE(M38:P38) -> 35297 | R38: 37716 | S38: 38276 | T38: 38823 | U38: 39475 | V38: =AVERAGE(R38:U38) -> 38572.5 | W38: 39786 | X38: 39617 | Y38: 39780 | Z38: 40818 | AA38: =AVERAGE(W38:Z38) -> 40000.25 | AB38: 41474 | AC38: 41858 | AD38: 43056 | AE38: 44821 | AF38: =AVERAGE(AB38:AE38) -> 42802.25 | AG38: =Drivers!$I$64*Operating!AG37 -> 45961.931 | AH38: =Drivers!$I$64*Operating!AH37 -> 47295.692 | AI38: =Drivers!$I$64*Operating!AI37 -> 48546.275 | AJ38: =Drivers!$I$64*Operating!AJ37 -> 51206.783 | AK38: =AVERAGE(AG38:AJ38) -> 48252.67 | AL38: =Drivers!$I$64*Operating!AL37 -> 52301.276 | AM38: =Drivers!$I$64*Operating!AM37 -> 53797.089 | AN38: =Drivers!$I$64*Operating!AN37 -> 55148.969 | AO38: =Drivers!$I$64*Operating!AO37 -> 58132.728 | AP38: =AVERAGE(AL38:AO38) -> 54845.015 | AQ38: =Drivers!$I$64*Operating!AQ37 -> 59326.82 | AR38: =Drivers!$I$64*Operating!AR37 -> 60978.198 | AS38: =Drivers!$I$64*Operating!AS37 -> 62417.95 | AT38: =Drivers!$I$64*Operating!AT37 -> 65712.021 | AU38: =AVERAGE(AQ38:AT38) -> 62108.747 | AV38: =Drivers!$I$64*Operating!AV37 -> 66990.296 | AW38: =Drivers!$I$64*Operating!AW37 -> 68777.5 | AX38: =Drivers!$I$64*Operating!AX37 -> 70318.755 | AY38: =Drivers!$I$64*Operating!AY37 -> 73845.057 | AZ38: =AVERAGE(AV38:AY38) -> 69982.902 | BA38: =Drivers!$I$64*Operating!BA37 -> 75217.206 | BC38: =IFERROR((Q38/L38)^(1/(_xlfn.NUMBERVALUE(LEFT(Q$6,4))-_xlfn.NUMBERVALUE(LEFT(L$6,4))))-1,"NA") -> 0.24323515 | BD38: =IFERROR((V38/Q38)^(1/(_xlfn.NUMBERVALUE(LEFT(V$6,4))-_xlfn.NUMBERVALUE(LEFT(Q$6,4))))-1,"NA") -> 0.092798255 | BE38: =IFERROR((AA38/V38)^(1/(_xlfn.NUMBERVALUE(LEFT(AA$6,4))-_xlfn.NUMBERVALUE(LEFT(V$6,4))))-1,"NA") -> 0.037014713 | BF38: =IFERROR((AF38/AA38)^(1/(_xlfn.NUMBERVALUE(LEFT(AF$6,4))-_xlfn.NUMBERVALUE(LEFT(AA$6,4))))-1,"NA") -> 0.070049562
C39: Average monthly revenue per paying membership (ARPU) | G39: USD | H39: 7.84 | I39: 8.14 | J39: 8.63 | K39: 8.18 | L39: =AVERAGE(H39:K39) -> 8.1975 | M39: 8.05 | N39: 7.44 | O39: 7.27 | P39: 7.12 | Q39: =AVERAGE(M39:P39) -> 7.47 | R39: 7.39 | S39: 7.5 | T39: 7.86 | U39: 8.14 | V39: =AVERAGE(R39:U39) -> 7.7225 | W39: 8.37 | X39: 8.67 | Y39: 8.58 | Z39: 8.3 | AA39: =AVERAGE(W39:Z39) -> 8.48 | AB39: 8.6 | AC39: 8.58 | AD39: 8.85 | AE39: 8.6 | AF39: =AVERAGE(AB39:AE39) -> 8.6575 | AG39: =Drivers!H42 -> 8.8955813 | AH39: =Drivers!I42 -> 8.9103516 | AI39: =Drivers!J42 -> 8.9914165 | AJ39: =Drivers!K42 -> 9.0069193 | AK39: =AVERAGE(AG39:AJ39) -> 8.9510672 | AL39: =Drivers!M42 -> 9.1972215 | AM39: =Drivers!N42 -> 9.2114744 | AN39: =Drivers!O42 -> 9.2851642 | AO39: =Drivers!P42 -> 9.3416915 | AP39: =AVERAGE(AL39:AO39) -> 9.2588879 | AQ39: =Drivers!R42 -> 9.5135073 | AR39: =Drivers!S42 -> 9.5293479 | AS39: =Drivers!T42 -> 9.6069326 | AT39: =Drivers!U42 -> 9.6696573 | AU39: =AVERAGE(AQ39:AT39) -> 9.5798613 | AV39: =Drivers!W42 -> 9.8433075 | AW39: =Drivers!X42 -> 9.8603521 | AX39: =Drivers!Y42 -> 9.9410005 | AY39: =Drivers!Z42 -> 10.006098 | AZ39: =AVERAGE(AV39:AY39) -> 9.9126894 | BA39: =Drivers!AB42 -> 10.185288 | BC39: =IFERROR((Q39/L39)^(1/(_xlfn.NUMBERVALUE(LEFT(Q$6,4))-_xlfn.NUMBERVALUE(LEFT(L$6,4))))-1,"NA") -> -0.088746569 | BD39: =IFERROR((V39/Q39)^(1/(_xlfn.NUMBERVALUE(LEFT(V$6,4))-_xlfn.NUMBERVALUE(LEFT(Q$6,4))))-1,"NA") -> 0.033801874 | BE39: =IFERROR((AA39/V39)^(1/(_xlfn.NUMBERVALUE(LEFT(AA$6,4))-_xlfn.NUMBERVALUE(LEFT(V$6,4))))-1,"NA") -> 0.098089997 | BF39: =IFERROR((AF39/AA39)^(1/(_xlfn.NUMBERVALUE(LEFT(AF$6,4))-_xlfn.NUMBERVALUE(LEFT(AA$6,4))))-1,"NA") -> 0.020931604
Q40: =Q38/L38-1 -> 0.24323515 | V40: =V38/Q38-1 -> 0.092798255 | AA40: =AA38/V38-1 -> 0.037014713 | AF40: =AF38/AA38-1 -> 0.070049562 | AK40: =AK38/AF38-1 -> 0.12733956 | AP40: =AP38/AK38-1 -> 0.13662136 | AU40: =AU38/AP38-1 -> 0.13244106 | AZ40: =AZ38/AU38-1 -> 0.12678012 | BA40: =BA38/AV38-1 -> 0.12280748 | BC40: =(BA38/AF38)^(1/5)-1 -> 0.11936087
C41: Asia Pacific (APAC) | Q41: =Q39/L39-1 -> -0.088746569 | V41: =V39/Q39-1 -> 0.033801874 | AA41: =AA39/V39-1 -> 0.098089997 | AF41: =AF39/AA39-1 -> 0.020931604 | AK41: =AK39/AF39-1 -> 0.033908998 | AP41: =AP39/AK39-1 -> 0.03438928 | AU41: =AU39/AP39-1 -> 0.034666513 | AZ41: =AZ39/AU39-1 -> 0.034742482 | BA41: =BA39/AV39-1 -> 0.034742482
C42: Revenues | G42: USD'k | H42: 319602 | I42: 349494 | J42: 382304 | K42: 418121 | L42: =SUM(H42:K42) -> 1469521 | M42: 483660 | N42: 569140 | O42: 634891 | P42: 684609 | Q42: =SUM(M42:P42) -> 2372300 | R42: 762414 | S42: 799480 | T42: 834002 | U42: 870705 | V42: =SUM(R42:U42) -> 3266601 | W42: 916754 | X42: 907719 | Y42: 889037 | Z42: 856711 | AA42: =SUM(W42:Z42) -> 3570221 | AB42: 933523 | AC42: 919273 | AD42: 948216 | AE42: 962715 | AF42: =SUM(AB42:AE42) -> 3763727 | AG42: =AG46*AG45*3 -> 1070555.9 | AH42: =AH46*AH45*3 -> 1084850.9 | AI42: =AI46*AI45*3 -> 1142857.7 | AJ42: =AJ46*AJ45*3 -> 1228788.6 | AK42: =SUM(AG42:AJ42) -> 4527053.2 | AL42: =AL46*AL45*3 -> 1308212.5 | AM42: =AM46*AM45*3 -> 1338358.1 | AN42: =AN46*AN45*3 -> 1410117.1 | AO42: =AO46*AO45*3 -> 1518228.1 | AP42: =SUM(AL42:AO42) -> 5574915.8 | AQ42: =AQ46*AQ45*3 -> 1605937.6 | AR42: =AR46*AR45*3 -> 1644086.7 | AS42: =AS46*AS45*3 -> 1727824 | AT42: =AT46*AT45*3 -> 1856455 | AU42: =SUM(AQ42:AT42) -> 6834303.3 | AV42: =AV46*AV45*3 -> 1958851.7 | AW42: =AW46*AW45*3 -> 2002448.5 | AX42: =AX46*AX45*3 -> 2098535.4 | AY42: =AY46*AY45*3 -> 2247280.7 | AZ42: =SUM(AV42:AY42) -> 8307116.4 | BA42: =BA46*BA45*3 -> 2366365.6 | BC42: =IFERROR((Q42/L42)^(1/(_xlfn.NUMBERVALUE(LEFT(Q$6,4))-_xlfn.NUMBERVALUE(LEFT(L$6,4))))-1,"NA") -> 0.61433556 | BD42: =IFERROR((V42/Q42)^(1/(_xlfn.NUMBERVALUE(LEFT(V$6,4))-_xlfn.NUMBERVALUE(LEFT(Q$6,4))))-1,"NA") -> 0.37697635 | BE42: =IFERROR((AA42/V42)^(1/(_xlfn.NUMBERVALUE(LEFT(AA$6,4))-_xlfn.NUMBERVALUE(LEFT(V$6,4))))-1,"NA") -> 0.092946766 | BF42: =IFERROR((AF42/AA42)^(1/(_xlfn.NUMBERVALUE(LEFT(AF$6,4))-_xlfn.NUMBERVALUE(LEFT(AA$6,4))))-1,"NA") -> 0.054200006
C43: Paid net membership additions | G43: #'k | H43: 1534 | I43: 801 | J43: 1543 | K43: 1748 | L43: =SUM(H43:K43) -> 5626 | M43: 3602 | N43: 2657 | O43: 1012 | P43: 1988 | Q43: =SUM(M43:P43) -> 9259 | R43: 1361 | S43: 1022 | T43: 2176 | U43: 2581 | V43: =SUM(R43:U43) -> 7140 | W43: 1087 | X43: 1080 | Y43: 1429 | Z43: 1795 | AA43: =SUM(W43:Z43) -> 5391 | AB43: 1455 | AC43: 1068 | AD43: 1881 | AE43: 2911 | AF43: =SUM(AB43:AE43) -> 7315 | AG43: =Drivers!H16 -> 1804.2 | AH43: =Drivers!I16 -> 1221.792 | AI43: =Drivers!J16 -> 2242.152 | AJ43: =Drivers!K16 -> 3539.776 | AK43: =SUM(AG43:AJ43) -> 8807.92 | AL43: =Drivers!M16 -> 2179.4736 | AM43: =Drivers!N16 -> 1364.7417 | AN43: =Drivers!O16 -> 2562.7797 | AO43: =Drivers!P16 -> 4184.0152 | AP43: =SUM(AL43:AO43) -> 10291.01 | AQ43: =Drivers!R16 -> 2506.3946 | AR43: =Drivers!S16 -> 1501.2158 | AS43: =Drivers!T16 -> 2883.1272 | AT43: =Drivers!U16 -> 4811.6175 | AU43: =SUM(AQ43:AT43) -> 11702.355 | AV43: =Drivers!W16 -> 2788.364 | AW43: =Drivers!X16 -> 1619.4366 | AX43: =Drivers!Y16 -> 3175.0438 | AY43: =Drivers!Z16 -> 5352.9245 | AZ43: =SUM(AV43:AY43) -> 12935.769 | BA43: =Drivers!AB16 -> 3070.6859 | BC43: =IFERROR((Q43/L43)^(1/(_xlfn.NUMBERVALUE(LEFT(Q$6,4))-_xlfn.NUMBERVALUE(LEFT(L$6,4))))-1,"NA") -> 0.64575187 | BD43: =IFERROR((V43/Q43)^(1/(_xlfn.NUMBERVALUE(LEFT(V$6,4))-_xlfn.NUMBERVALUE(LEFT(Q$6,4))))-1,"NA") -> -0.22885841 | BE43: =IFERROR((AA43/V43)^(1/(_xlfn.NUMBERVALUE(LEFT(AA$6,4))-_xlfn.NUMBERVALUE(LEFT(V$6,4))))-1,"NA") -> -0.24495798 | BF43: =IFERROR((AF43/AA43)^(1/(_xlfn.NUMBERVALUE(LEFT(AF$6,4))-_xlfn.NUMBERVALUE(LEFT(AA$6,4))))-1,"NA") -> 0.35689111
C44: Paid memberships at end of period | G44: #'k | H44: 12141 | I44: 12942 | J44: 14485 | K44: 16233 | L44: =K44 -> 16233 | M44: 19835 | N44: 22492 | O44: 23504 | P44: 25492 | Q44: =P44 -> 25492 | R44: 26853 | S44: 27875 | T44: 30051 | U44: 32632 | V44: =U44 -> 32632 | W44: 33719 | X44: 34799 | Y44: 36228 | Z44: 38023 | AA44: =Z44 -> 38023 | AB44: 39478 | AC44: 40546 | AD44: 42427 | AE44: 45338 | AF44: =AE44 -> 45338 | AG44: =AF44+AG43 -> 47142.2 | AH44: =AG44+AH43 -> 48363.992 | AI44: =AH44+AI43 -> 50606.144 | AJ44: =AI44+AJ43 -> 54145.92 | AK44: =AJ44 -> 54145.92 | AL44: =AK44+AL43 -> 56325.394 | AM44: =AL44+AM43 -> 57690.135 | AN44: =AM44+AN43 -> 60252.915 | AO44: =AN44+AO43 -> 64436.93 | AP44: =AO44 -> 64436.93 | AQ44: =AP44+AQ43 -> 66943.325 | AR44: =AQ44+AR43 -> 68444.541 | AS44: =AR44+AS43 -> 71327.668 | AT44: =AS44+AT43 -> 76139.285 | AU44: =AT44 -> 76139.285 | AV44: =AU44+AV43 -> 78927.649 | AW44: =AV44+AW43 -> 80547.086 | AX44: =AW44+AX43 -> 83722.13 | AY44: =AX44+AY43 -> 89075.054 | AZ44: =AY44 -> 89075.054 | BA44: =AZ44+BA43 -> 92145.74 | BC44: =IFERROR((Q44/L44)^(1/(_xlfn.NUMBERVALUE(LEFT(Q$6,4))-_xlfn.NUMBERVALUE(LEFT(L$6,4))))-1,"NA") -> 0.57038132 | BD44: =IFERROR((V44/Q44)^(1/(_xlfn.NUMBERVALUE(LEFT(V$6,4))-_xlfn.NUMBERVALUE(LEFT(Q$6,4))))-1,"NA") -> 0.28008787 | BE44: =IFERROR((AA44/V44)^(1/(_xlfn.NUMBERVALUE(LEFT(AA$6,4))-_xlfn.NUMBERVALUE(LEFT(V$6,4))))-1,"NA") -> 0.16520593 | BF44: =IFERROR((AF44/AA44)^(1/(_xlfn.NUMBERVALUE(LEFT(AF$6,4))-_xlfn.NUMBERVALUE(LEFT(AA$6,4))))-1,"NA") -> 0.19238356
C45: Average paying memberships | G45: #'k | H45: 11374 | I45: 12542 | J45: 13714 | K45: 15359 | L45: =AVERAGE(H45:K45) -> 13247.25 | M45: 18034 | N45: 21164 | O45: 22998 | P45: 24498 | Q45: =AVERAGE(M45:P45) -> 21673.5 | R45: 26173 | S45: 27364 | T45: 28963 | U45: 31342 | V45: =AVERAGE(R45:U45) -> 28460.5 | W45: 33176 | X45: 34259 | Y45: 35514 | Z45: 37126 | AA45: =AVERAGE(W45:Z45) -> 35018.75 | AB45: 38751 | AC45: 40012 | AD45: 41487 | AE45: 43883 | AF45: =AVERAGE(AB45:AE45) -> 41033.25 | AG45: =Drivers!$I$65*Operating!AG44 -> 45369.195 | AH45: =Drivers!$I$65*Operating!AH44 -> 46545.036 | AI45: =Drivers!$I$65*Operating!AI44 -> 48702.861 | AJ45: =Drivers!$I$65*Operating!AJ44 -> 52109.507 | AK45: =AVERAGE(AG45:AJ45) -> 48181.65 | AL45: =Drivers!$I$65*Operating!AL44 -> 54207.012 | AM45: =Drivers!$I$65*Operating!AM44 -> 55520.426 | AN45: =Drivers!$I$65*Operating!AN44 -> 57986.82 | AO45: =Drivers!$I$65*Operating!AO44 -> 62013.476 | AP45: =AVERAGE(AL45:AO45) -> 57431.933 | AQ45: =Drivers!$I$65*Operating!AQ44 -> 64425.605 | AR45: =Drivers!$I$65*Operating!AR44 -> 65870.361 | AS45: =Drivers!$I$65*Operating!AS44 -> 68645.055 | AT45: =Drivers!$I$65*Operating!AT44 -> 73275.708 | AU45: =AVERAGE(AQ45:AT45) -> 68054.182 | AV45: =Drivers!$I$65*Operating!AV44 -> 75959.203 | AW45: =Drivers!$I$65*Operating!AW44 -> 77517.733 | AX45: =Drivers!$I$65*Operating!AX44 -> 80573.364 | AY45: =Drivers!$I$65*Operating!AY44 -> 85724.967 | AZ45: =AVERAGE(AV45:AY45) -> 79943.817 | BA45: =Drivers!$I$65*Operating!BA44 -> 88680.165 | BC45: =IFERROR((Q45/L45)^(1/(_xlfn.NUMBERVALUE(LEFT(Q$6,4))-_xlfn.NUMBERVALUE(LEFT(L$6,4))))-1,"NA") -> 0.63607541 | BD45: =IFERROR((V45/Q45)^(1/(_xlfn.NUMBERVALUE(LEFT(V$6,4))-_xlfn.NUMBERVALUE(LEFT(Q$6,4))))-1,"NA") -> 0.31314739 | BE45: =IFERROR((AA45/V45)^(1/(_xlfn.NUMBERVALUE(LEFT(AA$6,4))-_xlfn.NUMBERVALUE(LEFT(V$6,4))))-1,"NA") -> 0.23043341 | BF45: =IFERROR((AF45/AA45)^(1/(_xlfn.NUMBERVALUE(LEFT(AF$6,4))-_xlfn.NUMBERVALUE(LEFT(AA$6,4))))-1,"NA") -> 0.17175085
C46: Average monthly revenue per paying membership (ARPU) | G46: USD | H46: 9.37 | I46: 9.29 | J46: 9.29 | K46: 9.07 | L46: =AVERAGE(H46:K46) -> 9.255 | M46: 8.94 | N46: 8.96 | O46: 9.2 | P46: 9.32 | Q46: =AVERAGE(M46:P46) -> 9.105 | R46: 9.71 | S46: 9.74 | T46: 9.6 | U46: 9.26 | V46: =AVERAGE(R46:U46) -> 9.5775 | W46: 9.21 | X46: 8.83 | Y46: 8.34 | Z46: 7.69 | AA46: =AVERAGE(W46:Z46) -> 8.5175 | AB46: 8.03 | AC46: 7.66 | AD46: 7.62 | AE46: 7.31 | AF46: =AVERAGE(AB46:AE46) -> 7.655 | AG46: =Drivers!H43 -> 7.8655125 | AH46: =Drivers!I43 -> 7.7691844 | AI46: =Drivers!J43 -> 7.8219754 | AJ46: =Drivers!K43 -> 7.8602971 | AK46: =AVERAGE(AG46:AJ46) -> 7.8292424 | AL46: =Drivers!M43 -> 8.0445465 | AM46: =Drivers!N43 -> 8.0352296 | AN46: =Drivers!O43 -> 8.1059633 | AO46: =Drivers!P43 -> 8.160743 | AP46: =AVERAGE(AL46:AO46) -> 8.0866206 | AQ46: =Drivers!R43 -> 8.3090027 | AR46: =Drivers!S43 -> 8.3198104 | AS46: =Drivers!T43 -> 8.3901359 | AT46: =Drivers!U43 -> 8.4450679 | AU46: =AVERAGE(AQ46:AT46) -> 8.3660042 | AV46: =Drivers!W43 -> 8.5960693 | AW46: =Drivers!X43 -> 8.6107116 | AX46: =Drivers!Y43 -> 8.6816756 | AY46: =Drivers!Z43 -> 8.738336 | AZ46: =AVERAGE(AV46:AY46) -> 8.6566981 | BA46: =Drivers!AB43 -> 8.8947573 | BC46: =IFERROR((Q46/L46)^(1/(_xlfn.NUMBERVALUE(LEFT(Q$6,4))-_xlfn.NUMBERVALUE(LEFT(L$6,4))))-1,"NA") -> -0.016207455 | BD46: =IFERROR((V46/Q46)^(1/(_xlfn.NUMBERVALUE(LEFT(V$6,4))-_xlfn.NUMBERVALUE(LEFT(Q$6,4))))-1,"NA") -> 0.051894563 | BE46: =IFERROR((AA46/V46)^(1/(_xlfn.NUMBERVALUE(LEFT(AA$6,4))-_xlfn.NUMBERVALUE(LEFT(V$6,4))))-1,"NA") -> -0.11067606 | BF46: =IFERROR((AF46/AA46)^(1/(_xlfn.NUMBERVALUE(LEFT(AF$6,4))-_xlfn.NUMBERVALUE(LEFT(AA$6,4))))-1,"NA") -> -0.10126211
Q47: =Q45/L45-1 -> 0.63607541 | V47: =V45/Q45-1 -> 0.31314739 | AA47: =AA45/V45-1 -> 0.23043341 | AF47: =AF45/AA45-1 -> 0.17175085 | AK47: =AK45/AF45-1 -> 0.17420994 | AP47: =AP45/AK45-1 -> 0.19198768 | AU47: =AU45/AP45-1 -> 0.18495371 | AZ47: =AZ45/AU45-1 -> 0.17470836 | BA47: =BA45/AV45-1 -> 0.16747098 | BC47: =(BA45/AF45)^(1/5)-1 -> 0.16664336
Q48: =Q46/L46-1 -> -0.016207455 | V48: =V46/Q46-1 -> 0.051894563 | AA48: =AA46/V46-1 -> -0.11067606 | AF48: =AF46/AA46-1 -> -0.10126211 | AK48: =AK46/AF46-1 -> 0.022761901 | AP48: =AP46/AK46-1 -> 0.032873965 | AU48: =AU46/AP46-1 -> 0.034548872 | AZ48: =AZ46/AU46-1 -> 0.034747044 | BA48: =BA46/AV46-1 -> 0.034747044
C49: DVD revenue breakdown
C50: Revenues | H50: 80688 | I50: 76200 | J50: 71877 | K50: 68452 | L50: =SUM(H50:K50) -> 297217 | M50: 64328 | N50: 61571 | O50: 58834 | P50: 54648 | Q50: =SUM(M50:P50) -> 239381 | R50: 49575 | S50: 46292 | T50: 44232 | U50: 42249 | V50: =SUM(R50:U50) -> 182348 | W50: 39810 | X50: 37090 | Y50: 35228 | Z50: 33569 | AA50: =SUM(W50:Z50) -> 145697 | AB50: 27613 | AC50: 27613 | AD50: 27613
C52: Profitability by business segment
C53: Streaming
C54: Revenues | G54: USD'k | H54: =SUM(H21,H28,H35,H42) -> 4440304 | I54: =SUM(I21,I28,I35,I42) -> 4846916 | J54: =SUM(J21,J28,J35,J42) -> 5173028 | K54: =SUM(K21,K28,K35,K42) -> 5398982 | L54: =SUM(H54:K54) -> 19859230 | M54: =SUM(M21,M28,M35,M42) -> 5703363 | N54: =SUM(N21,N28,N35,N42) -> 6086715 | O54: =SUM(O21,O28,O35,O42) -> 6376803 | P54: =SUM(P21,P28,P35,P42) -> 6589794 | Q54: =SUM(M54:P54) -> 24756675 | R54: =SUM(R21,R28,R35,R42) -> 7113707 | S54: =SUM(S21,S28,S35,S42) -> 7295485 | T54: =SUM(T21,T28,T35,T42) -> 7439235 | U54: =SUM(U21,U28,U35,U42) -> 7667069 | V54: =SUM(R54:U54) -> 29515496 | W54: =SUM(W21,W28,W35,W42) -> 7827957 | X54: =SUM(X21,X28,X35,X42) -> 7933051 | Y54: =SUM(Y21,Y28,Y35,Y42) -> 7890361 | Z54: =SUM(Z21,Z28,Z35,Z42) -> 7818483 | AA54: =SUM(W54:Z54) -> 31469852 | AB54: =SUM(AB21,AB28,AB35,AB42) -> 8130001 | AC54: =SUM(AC21,AC28,AC35,AC42) -> 8158326 | AD54: =SUM(AD21,AD28,AD35,AD42) -> 8519306 | AE54: =SUM(AE21,AE28,AE35,AE42) -> 8832825 | AF54: =SUM(AB54:AE54) -> 33640458 | AG54: =SUM(AG21,AG28,AG35,AG42) -> 9268142.6 | AH54: =SUM(AH21,AH28,AH35,AH42) -> 9479654.3 | AI54: =SUM(AI21,AI28,AI35,AI42) -> 9915694.1 | AJ54: =SUM(AJ21,AJ28,AJ35,AJ42) -> 10509602 | AK54: =SUM(AG54:AJ54) -> 39173093 | AL54: =SUM(AL21,AL28,AL35,AL42) -> 10900435 | AM54: =SUM(AM21,AM28,AM35,AM42) -> 11172840 | AN54: =SUM(AN21,AN28,AN35,AN42) -> 11690335 | AO54: =SUM(AO21,AO28,AO35,AO42) -> 12436234 | AP54: =SUM(AL54:AO54) -> 46199845 | AQ54: =SUM(AQ21,AQ28,AQ35,AQ42) -> 12866741 | AR54: =SUM(AR21,AR28,AR35,AR42) -> 13188002 | AS54: =SUM(AS21,AS28,AS35,AS42) -> 13789873 | AT54: =SUM(AT21,AT28,AT35,AT42) -> 14678916 | AU54: =SUM(AQ54:AT54) -> 54523532 | AV54: =SUM(AV21,AV28,AV35,AV42) -> 15159122 | AW54: =SUM(AW21,AW28,AW35,AW42) -> 15524981 | AX54: =SUM(AX21,AX28,AX35,AX42) -> 16211530 | AY54: =SUM(AY21,AY28,AY35,AY42) -> 17233742 | AZ54: =SUM(AV54:AY54) -> 64129375 | BA54: =SUM(BA21,BA28,BA35,BA42)*4 -> 71196534
C56: Domestic DVD
C57: Revenues | G57: USD'k | H57: =H50 -> 80688 | I57: =I50 -> 76200 | J57: =J50 -> 71877 | K57: =K50 -> 68452 | L57: =L50 -> 297217 | M57: =M50 -> 64328 | N57: =N50 -> 61571 | O57: =O50 -> 58834 | ... AD57: =AD50 -> 27613
C59: Cost Schedule
C61: Summary
C62: Cost of sales | G62: USD'k | H62: ='Financial Statements'!H11*-1 -> 2870614 | I62: ='Financial Statements'!I11*-1 -> 3005657 | J62: ='Financial Statements'!J11*-1 -> 3097919 | K62: ='Financial Statements'!K11*-1 -> 3466023 | L62: =SUM(H62:K62) -> 12440213 | M62: ='Financial Statements'!M11*-1 -> 3599701 | N62: ='Financial Statements'!N11*-1 -> 3643707 | O62: ='Financial Statements'!O11*-1 -> 3867751 | P62: ='Financial Statements'!P11*-1 -> 4165160 | Q62: =SUM(M62:P62) -> 15276319 | R62: ='Financial Statements'!R11*-1 -> 3868511 | S62: ='Financial Statements'!S11*-1 -> 4018008 | T62: ='Financial Statements'!T11*-1 -> 4206589 | U62: ='Financial Statements'!U11*-1 -> 5239575 | V62: =SUM(R62:U62) -> 17332683 | W62: ='Financial Statements'!W11*-1 -> 4284705 | X62: ='Financial Statements'!X11*-1 -> 4690755 | Y62: ='Financial Statements'!Y11*-1 -> 4788665 | Z62: ='Financial Statements'!Z11*-1 -> 5404160 | AA62: =SUM(W62:Z62) -> 19168285 | AB62: ='Financial Statements'!AB11*-1 -> 4803625 | AC62: ='Financial Statements'!AC11*-1 -> 4673470 | AD62: ='Financial Statements'!AD11*-1 -> 4930788 | AE62: ='Financial Statements'!AE11*-1 -> 5307485 | AF62: =SUM(AB62:AE62) -> 19715368 | AG62: =SUM(AG67,AG76) -> 5457841.8 | AH62: =SUM(AH67,AH76) -> 5468641.3 | AI62: =SUM(AI67,AI76) -> 5581365.1 | AJ62: =SUM(AJ67,AJ76) -> 5768530.6 | AK62: =SUM(AK67,AK76) -> 22276379 | AL62: =SUM(AL67,AL76) -> 6190160.3 | AM62: =SUM(AM67,AM76) -> 6311335.8 | AN62: =SUM(AN67,AN76) -> 6521826.6 | ... BA62: =SUM(BA67,BA76) -> 33700392
C63: COGS margin | G63: % | H63: =H62/H13 -> 0.63495224 | I63: =I62/I13 -> 0.61051923 | J63: =J62/J13 -> 0.59065302 | K63: =K62/K13 -> 0.63393961 | L63: =L62/L13 -> 0.61718283 | M63: =M62/M13 -> 0.62411475 | N63: =N62/N13 -> 0.59263785 | O63: =O62/O13 -> 0.60098961 | ... BA63: =BA62/BA13 -> 0.47334315
C64: Gross margin | G64: % | H64: =1-H63 -> 0.36504776 | I64: =1-I63 -> 0.38948077 | J64: =1-J63 -> 0.40934698 | K64: =1-K63 -> 0.36606039 | L64: =1-L63 -> 0.38281717 | M64: =1-M63 -> 0.37588525 | N64: =1-N63 -> 0.40736215 | O64: =1-O63 -> 0.39901039 | ... BA64: =1-BA63 -> 0.52665685
C66: Amortisation of content assets
C67: Amortisation of content assets | G67: USD'k | H67: ='Financial Statements'!H80 -> 2124686 | I67: ='Financial Statements'!I80 -> 2231915 | J67: ='Financial Statements'!J80 -> 2279977 | K67: ='Financial Statements'!K80 -> 2579669 | L67: =SUM(H67:K67) -> 9216247 | M67: ='Financial Statements'!M80 -> 2483385 | N67: ='Financial Statements'!N80 -> 2607159 | O67: ='Financial Statements'!O80 -> 2733743 | P67: ='Financial Statements'!P80 -> 2982625 | Q67: =SUM(M67:P67) -> 10806912 | R67: ='Financial Statements'!R80 -> 2719196 | S67: ='Financial Statements'!S80 -> 2806803 | T67: ='Financial Statements'!T80 -> 2963051 | U67: ='Financial Statements'!U80 -> 3741317 | V67: =SUM(R67:U67) -> 12230367 | W67: ='Financial Statements'!W80 -> 3166365 | X67: ='Financial Statements'!X80 -> 3261348 | Y67: ='Financial Statements'!Y80 -> 3653592 | Z67: ='Financial Statements'!Z80 -> 3944827 | AA67: =SUM(W67:Z67) -> 14026132 | AB67: ='Financial Statements'!AB80 -> 3459984 | AC67: ='Financial Statements'!AC80 -> 3410021 | AD67: ='Financial Statements'!AD80 -> 3573353 | AE67: ='Financial Statements'!AE80 -> 3754079 | AF67: =SUM(AB67:AE67) -> 14197437 | AG67: =AG69*AG13 -> 3883486.4 | AH67: =AH69*AH13 -> 3915235 | AI67: =AI69*AI13 -> 4025915.9 | AJ67: =AJ69*AJ13 -> 4193483.9 | AK67: =SUM(AG67:AJ67) -> 16018121 | AL67: =AL69*AL13 -> 4452986.2 | AM67: =AM69*AM13 -> 4547508.4 | AN67: =AN69*AN13 -> 4717220 | AO67: =AO69*AO13 -> 4962238.1 | AP67: =SUM(AL67:AO67) -> 18679953 | AQ67: =AQ69*AQ13 -> 5069682.9 | AR67: =AR69*AR13 -> 5130324.6 | AS67: =AS69*AS13 -> 5295511.6 | AT67: =AT69*AT13 -> 5563522.5 | AU67: =SUM(AQ67:AT67) -> 21059042 | AV67: =AV69*AV13 -> 5669732.1 | AW67: =AW69*AW13 -> 5728943.5 | AX67: =AX69*AX13 -> 5901232.5 | AY67: =AY69*AY13 -> 6187163.8 | AZ67: =SUM(AV67:AY67) -> 23487072 | BA67: =BA69*BA13 -> 25719402
C68: % of COGS | G68: % | H68: =H67/H62 -> 0.74015037 | I68: =I67/I62 -> 0.74257142 | J68: =J67/J62 -> 0.7359705 | K68: =K67/K62 -> 0.74427348 | L68: =L67/L62 -> 0.74084318 | M68: =M67/M62 -> 0.68988647 | N68: =N67/N62 -> 0.71552378 | O68: =O67/O62 -> 0.70680429 | ... BA68: =BA67/BA62 -> 0.76317813
C69: % of sales | G69: % | H69: =H67/H13 -> 0.46996013 | I69: =I67/I13 -> 0.45335414 | J69: =J67/J13 -> 0.4347032 | K69: =K67/K13 -> 0.47182444 | L69: =L67/L13 -> 0.45723569 | M69: =M67/M13 -> 0.43056832 | N69: =N67/N13 -> 0.42404647 | O69: =O67/O13 -> 0.42478204 | ... AF69: =AF67/AF13 -> 0.42099789 | AG69: =AE69+SUM(AG71:AG73) -> 0.41901453 | AH69: =AG69+SUM(AH71:AH73) -> 0.41301453 | AI69: =AH69+SUM(AI71:AI73) -> 0.40601453 | AJ69: =AI69+SUM(AJ71:AJ73) -> 0.39901453 | AK69: =AK67/AK13 -> 0.40890622 | AL69: =AJ69+SUM(AL71:AL73) -> 0.40851453 | AM69: =AL69+SUM(AM71:AM73) -> 0.40701453 | AN69: =AM69+SUM(AN71:AN73) -> 0.40351453 | AO69: =AN69+SUM(AO71:AO73) -> 0.39901453 | AP69: =AP67/AP13 -> 0.40432934 | AQ69: =AO69+SUM(AQ71:AQ73) -> 0.39401453 | AR69: =AQ69+SUM(AR71:AR73) -> 0.38901453 | AS69: =AR69+SUM(AS71:AS73) -> 0.38401453 | AT69: =AS69+SUM(AT71:AT73) -> 0.37901453 | AU69: =AU67/AU13 -> 0.38623766 | AV69: =AT69+SUM(AV71:AV73) -> 0.37401453 | AW69: =AV69+SUM(AW71:AW73) -> 0.36901453 | AX69: =AW69+SUM(AX71:AX73) -> 0.36401453 | AY69: =AX69+SUM(AY71:AY73) -> 0.35901453 | AZ69: =AZ67/AZ13 -> 0.36624514 | BA69: =AZ69+SUM(BA71:BA73) -> 0.36124514
C71: Content assets COGS margin incremental step-up / step-down | G71: % | AG71: =Drivers!H72+SUM(AG72:AG73) -> -0.008 | AH71: =Drivers!I72+SUM(AH72:AH73) -> -0.008 | AI71: =Drivers!J72+SUM(AI72:AI73) -> -0.0085 | AJ71: =Drivers!K72+SUM(AJ72:AJ73) -> -0.0085 | AK71: =Drivers!L72 -> -0.01 | AL71: =Drivers!M72+SUM(AL72:AL73) -> 0.001 | AM71: =Drivers!N72+SUM(AM72:AM73) -> -0.0045 | AN71: =Drivers!O72+SUM(AN72:AN73) -> -0.0055 | AO71: =Drivers!P72+SUM(AO72:AO73) -> -0.006 | AP71: =Drivers!Q72 -> -0.0075 | AQ71: =Drivers!R72+SUM(AQ72:AQ73) -> -0.005 | AR71: =Drivers!S72+SUM(AR72:AR73) -> -0.005 | AS71: =Drivers!T72+SUM(AS72:AS73) -> -0.005 | AT71: =Drivers!U72+SUM(AT72:AT73) -> -0.005 | AU71: =Drivers!V72 -> -0.005 | AV71: =Drivers!W72+SUM(AV72:AV73) -> -0.005 | AW71: =Drivers!X72+SUM(AW72:AW73) -> -0.005 | AX71: =Drivers!Y72+SUM(AX72:AX73) -> -0.005 | AY71: =Drivers!Z72+SUM(AY72:AY73) -> -0.005 | AZ71: =Drivers!AA72 -> -0.005 | BA71: =Drivers!AB72+SUM(BA72:BA73) -> -0.005
C72: WWE impact on COGS | G72: % | AG72: =Drivers!H94 -> 0 | AH72: =Drivers!I94 -> 0 | AI72: =Drivers!J94 -> 0 | AJ72: =Drivers!K94 -> 0 | AK72: =Drivers!L94 -> 0 | AL72: =Drivers!M94 -> 0.0075 | AM72: =Drivers!N94 -> 0.002 | AN72: =Drivers!O94 -> 0.0015 | ... BA72: =Drivers!AB94 -> 0
C73: Gaming impact on COGS | G73: % | AG73: =Drivers!H112 -> 0.002 | AH73: =Drivers!I112 -> 0.002 | AI73: =Drivers!J112 -> 0.0015 | AJ73: =Drivers!K112 -> 0.0015 | AK73: =Drivers!L112 -> 0.00175 | AL73: =Drivers!M112 -> 0.001 | AM73: =Drivers!N112 -> 0.001 | AN73: =Drivers!O112 -> 0.0005 | ... BA73: =Drivers!AB112 -> 0
C75: Other cost of sales
C76: Other cost of sales | G76: USD'k | H76: =H62-H67 -> 745928 | I76: =I62-I67 -> 773742 | J76: =J62-J67 -> 817942 | K76: =K62-K67 -> 886354 | L76: =SUM(H76:K76) -> 3223966 | M76: =M62-M67 -> 1116316 | N76: =N62-N67 -> 1036548 | O76: =O62-O67 -> 1134008 | P76: =P62-P67 -> 1182535 | Q76: =SUM(M76:P76) -> 4469407 | R76: =R62-R67 -> 1149315 | S76: =S62-S67 -> 1211205 | T76: =T62-T67 -> 1243538 | U76: =U62-U67 -> 1498258 | V76: =SUM(R76:U76) -> 5102316 | W76: =W62-W67 -> 1118340 | X76: =X62-X67 -> 1429407 | Y76: =Y62-Y67 -> 1135073 | Z76: =Z62-Z67 -> 1459333 | AA76: =SUM(W76:Z76) -> 5142153 | AB76: =AB62-AB67 -> 1343641 | AC76: =AC62-AC67 -> 1263449 | AD76: =AD62-AD67 -> 1357435 | AE76: =AE62-AE67 -> 1553406 | AF76: =SUM(AB76:AE76) -> 5517931 | AG76: =AG78*AG13 -> 1574355.3 | AH76: =AH78*AH13 -> 1553406.3 | AI76: =AI78*AI13 -> 1555449.2 | AJ76: =AJ78*AJ13 -> 1575046.7 | AK76: =SUM(AG76:AJ76) -> 6258257.6 | AL76: =AL78*AL13 -> 1737174.1 | AM76: =AM78*AM13 -> 1763827.3 | AN76: =AN78*AN13 -> 1804606.6 | AO76: =AO78*AO13 -> 1863786.1 | AP76: =SUM(AL76:AO76) -> 7169394.1 | AQ76: =AQ78*AQ13 -> 1863971.3 | AR76: =AR78*AR13 -> 1844571.6 | AS76: =AS78*AS13 -> 1859804.3 | AT76: =AT78*AT13 -> 1906312.7 | AU76: =SUM(AQ76:AT76) -> 7474660 | AV76: =AV78*AV13 -> 1892880.3 | AW76: =AW78*AW13 -> 1860939.1 | AX76: =AX78*AX13 -> 1862176.3 | AY76: =AY78*AY13 -> 1893426.5 | AZ76: =SUM(AV76:AY76) -> 7509422.2 | BA76: =BA78*BA13 -> 7980989.8
C77: % of COGS | G77: % | H77: =H76/H62 -> 0.25984963 | I77: =I76/I62 -> 0.25742858 | J77: =J76/J62 -> 0.2640295 | K77: =K76/K62 -> 0.25572652 | L77: =L76/L62 -> 0.25915682 | M77: =M76/M62 -> 0.31011353 | N77: =N76/N62 -> 0.28447622 | O77: =O76/O62 -> 0.29319571 | ... BA77: =BA76/BA62 -> 0.23682187
C78: % of sales | G78: % | H78: =H76/H13 -> 0.16499211 | I78: =I76/I13 -> 0.1571651 | J78: =J76/J13 -> 0.15594982 | K78: =K76/K13 -> 0.16211517 | L78: =L76/L13 -> 0.15994714 | M78: =M76/M13 -> 0.19354643 | N78: =N76/N13 -> 0.16859138 | O78: =O76/O13 -> 0.17620758 | ... AF78: =AF76/AF13 -> 0.16362371 | AG78: =AE78+SUM(AG80:AG82) -> 0.1698674 | AH78: =AG78+SUM(AH80:AH82) -> 0.1638674 | AI78: =AH78+SUM(AI80:AI82) -> 0.1568674 | AJ78: =AI78+SUM(AJ80:AJ82) -> 0.1498674 | AK78: =AK76/AK13 -> 0.15975909 | AL78: =AJ78+SUM(AL80:AL82) -> 0.1593674 | AM78: =AL78+SUM(AM80:AM82) -> 0.1578674 | AN78: =AM78+SUM(AN80:AN82) -> 0.1543674 | AO78: =AN78+SUM(AO80:AO82) -> 0.1498674 | AP78: =AP76/AP13 -> 0.15518221 | AQ78: =AO78+SUM(AQ80:AQ82) -> 0.1448674 | AR78: =AQ78+SUM(AR80:AR82) -> 0.1398674 | AS78: =AR78+SUM(AS80:AS82) -> 0.1348674 | AT78: =AS78+SUM(AT80:AT82) -> 0.1298674 | AU78: =AU76/AU13 -> 0.13709053 | AV78: =AT78+SUM(AV80:AV82) -> 0.1248674 | AW78: =AV78+SUM(AW80:AW82) -> 0.1198674 | AX78: =AW78+SUM(AX80:AX82) -> 0.1148674 | AY78: =AX78+SUM(AY80:AY82) -> 0.1098674 | AZ78: =AZ76/AZ13 -> 0.11709801 | BA78: =AZ78+SUM(BA80:BA82) -> 0.11209801
C80: Other COS margin incremental step-up / step-down | G80: % | AG80: =Drivers!H71+SUM(AG81:AG82) -> -0.008 | AH80: =Drivers!I71+SUM(AH81:AH82) -> -0.008 | AI80: =Drivers!J71+SUM(AI81:AI82) -> -0.0085 | AJ80: =Drivers!K71+SUM(AJ81:AJ82) -> -0.0085 | AK80: =Drivers!L71 -> -0.01 | AL80: =Drivers!M71+SUM(AL81:AL82) -> 0.001 | AM80: =Drivers!N71+SUM(AM81:AM82) -> -0.0045 | AN80: =Drivers!O71+SUM(AN81:AN82) -> -0.0055 | AO80: =Drivers!P71+SUM(AO81:AO82) -> -0.006 | AP80: =Drivers!Q71 -> -0.0075 | AQ80: =Drivers!R71+SUM(AQ81:AQ82) -> -0.005 | AR80: =Drivers!S71+SUM(AR81:AR82) -> -0.005 | AS80: =Drivers!T71+SUM(AS81:AS82) -> -0.005 | AT80: =Drivers!U71+SUM(AT81:AT82) -> -0.005 | AU80: =Drivers!V71 -> -0.005 | AV80: =Drivers!W71+SUM(AV81:AV82) -> -0.005 | AW80: =Drivers!X71+SUM(AW81:AW82) -> -0.005 | AX80: =Drivers!Y71+SUM(AX81:AX82) -> -0.005 | AY80: =Drivers!Z71+SUM(AY81:AY82) -> -0.005 | AZ80: =Drivers!AA71 -> -0.005 | BA80: =Drivers!AB71+SUM(BA81:BA82) -> -0.005
C81: WWE impact on COGS | G81: % | AG81: =Drivers!H95 -> 0 | AH81: =Drivers!I95 -> 0 | AI81: =Drivers!J95 -> 0 | AJ81: =Drivers!K95 -> 0 | AK81: =Drivers!L94 -> 0 | AL81: =Drivers!M95 -> 0.0075 | AM81: =Drivers!N95 -> 0.002 | AN81: =Drivers!O95 -> 0.0015 | AO81: =Drivers!P95 -> 0.001 | AP81: =Drivers!Q94 -> 0.003 | AQ81: =Drivers!R95 -> 0 | AR81: =Drivers!S95 -> 0 | AS81: =Drivers!T95 -> 0 | AT81: =Drivers!U95 -> 0 | AU81: =Drivers!V94 -> 0 | AV81: =Drivers!W95 -> 0 | AW81: =Drivers!X95 -> 0 | AX81: =Drivers!Y95 -> 0 | AY81: =Drivers!Z95 -> 0 | AZ81: =Drivers!AA94 -> 0 | BA81: =Drivers!AB95 -> 0
C82: Gaming impact on COGS | G82: % | AG82: =Drivers!H113 -> 0.002 | AH82: =Drivers!I113 -> 0.002 | AI82: =Drivers!J113 -> 0.0015 | AJ82: =Drivers!K113 -> 0.0015 | AK82: =Drivers!L112 -> 0.00175 | AL82: =Drivers!M113 -> 0.001 | AM82: =Drivers!N113 -> 0.001 | AN82: =Drivers!O113 -> 0.0005 | AO82: =Drivers!P113 -> 0.0005 | AP82: =Drivers!Q112 -> 0.00075 | AQ82: =Drivers!R113 -> 0 | AR82: =Drivers!S113 -> 0 | AS82: =Drivers!T113 -> 0 | AT82: =Drivers!U113 -> 0 | AU82: =Drivers!V112 -> 0 | AV82: =Drivers!W113 -> 0 | AW82: =Drivers!X113 -> 0 | AX82: =Drivers!Y113 -> 0 | AY82: =Drivers!Z113 -> 0 | AZ82: =Drivers!AA112 -> 0 | BA82: =Drivers!AB113 -> 0
C84: Operating expenses
C85: Revenue for the year | G85: USD'k | H85: =H13 -> 4520992 | I85: =I13 -> 4923116 | J85: =J13 -> 5244905 | K85: =K13 -> 5467434 | L85: =L13 -> 20156447 | M85: =M13 -> 5767691 | N85: =N13 -> 6148286 | O85: =O13 -> 6435637 | ... BA85: =BA13 -> 71196534
C87: Marketing as % of sales | G87: % | H87: =H95/H$85 -> 0.13638113 | I87: =I95/I$85 -> 0.12251387 | J87: =J95/J$85 -> 0.10558761 | K87: =K95/K$85 -> 0.16075859 | L87: =L95/L$85 -> 0.13159373 | M87: =M95/M$85 -> 0.087353847 | N87: =N95/N$85 -> 0.070648958 | O87: =O95/O$85 -> 0.081980541 | ... AF87: =AF95/AF$85 -> 0.078814447 | AG87: =SUM(AF91,AG99) -> 0.076960246 | AH87: =SUM(AG87,AH99) -> 0.075460246 | AI87: =SUM(AH87,AI99) -> 0.072960246 | AJ87: =SUM(AI87,AJ99) -> 0.070460246 | AK87: =AK95/$AK$85 -> 0.073840894 | AL87: =SUM(AJ87,AL99) -> 0.072960246 | AM87: =SUM(AL87,AM99) -> 0.075460246 | AN87: =SUM(AM87,AN99) -> 0.074960246 | AO87: =SUM(AN87,AO99) -> 0.074460246 | AP87: =AP95/$AK$85 -> 0.087833738 | AQ87: =SUM(AO87,AQ99) -> 0.071960246 | AR87: =SUM(AQ87,AR99) -> 0.069460246 | AS87: =SUM(AR87,AS99) -> 0.066960246 | AT87: =SUM(AS87,AT99) -> 0.064460246 | AU87: =AU95/$AK$85 -> 0.094746554 | AV87: =SUM(AT87,AV99) -> 0.062460246 | AW87: =SUM(AV87,AW99) -> 0.060460246 | AX87: =SUM(AW87,AX99) -> 0.058460246 | AY87: =SUM(AX87,AY99) -> 0.056460246 | AZ87: =AZ95/$AK$85 -> 0.097164603 | BA87: =SUM(AY87,BA99) -> 0.054460246
C88: Tech & development as % of sales | G88: % | H88: =H96/H$85 -> 0.082451816 | I88: =I96/I$85 -> 0.077843585 | J88: =J96/J$85 -> 0.072408556 | K88: =K96/K$85 -> 0.074875344 | L88: =L96/L$85 -> 0.076657806 | M88: =M96/M$85 -> 0.078682613 | N88: =N96/N$85 -> 0.070758745 | O88: =O96/O$85 -> 0.070513921 | ... AF88: =AF96/AF$85 -> 0.079344496 | AG88: =SUM(AF92,AG100) -> 0.077937313 | AH88: =SUM(AG88,AH100) -> 0.076437313 | AI88: =SUM(AH88,AI100) -> 0.073937313 | AJ88: =SUM(AI88,AJ100) -> 0.071437313 | AK88: =AK96/$AK$85 -> 0.074817961 | AL88: =SUM(AJ88,AL100) -> 0.073937313 | AM88: =SUM(AL88,AM100) -> 0.076437313 | AN88: =SUM(AM88,AN100) -> 0.075937313 | AO88: =SUM(AN88,AO100) -> 0.075437313 | AP88: =AP96/$AK$85 -> 0.088986067 | AQ88: =SUM(AO88,AQ100) -> 0.072937313 | AR88: =SUM(AQ88,AR100) -> 0.070437313 | AS88: =SUM(AR88,AS100) -> 0.067937313 | AT88: =SUM(AS88,AT100) -> 0.065437313 | AU88: =AU96/$AK$85 -> 0.096106496 | AV88: =SUM(AT88,AV100) -> 0.063437313 | AW88: =SUM(AV88,AW100) -> 0.061437313 | AX88: =SUM(AW88,AX100) -> 0.059437313 | AY88: =SUM(AX88,AY100) -> 0.057437313 | AZ88: =AZ96/$AK$85 -> 0.098764136 | BA88: =SUM(AY88,BA100) -> 0.055437313
C89: SG&A as % of sales | G89: % | H89: =H97/H$85 -> 0.044669842 | I89: =I97/I$85 -> 0.045633091 | J89: =J97/J$85 -> 0.04445724 | K89: =K97/K$85 -> 0.046564074 | L89: =L97/L$85 -> 0.0453636 | M89: =M97/M$85 -> 0.043706745 | N89: =N97/N$85 -> 0.045091591 | O89: =O97/O$85 -> 0.042206234 | ... AF89: =AF97/AF$85 -> 0.051011768 | AG89: =SUM(AF93,AG101) -> 0.049480495 | AH89: =SUM(AG89,AH101) -> 0.047980495 | AI89: =SUM(AH89,AI101) -> 0.045480495 | AJ89: =SUM(AI89,AJ101) -> 0.042980495 | AK89: =AK97/$AK$85 -> 0.046361143 | AL89: =SUM(AJ89,AL101) -> 0.045480495 | AM89: =SUM(AL89,AM101) -> 0.047980495 | AN89: =SUM(AM89,AN101) -> 0.047480495 | AO89: =SUM(AN89,AO101) -> 0.046980495 | AP89: =AP97/$AK$85 -> 0.055424751 | AQ89: =SUM(AO89,AQ101) -> 0.044480495 | AR89: =SUM(AQ89,AR101) -> 0.041980495 | AS89: =SUM(AR89,AS101) -> 0.039480495 | AT89: =SUM(AS89,AT101) -> 0.036980495 | AU89: =AU97/$AK$85 -> 0.056498538 | AV89: =SUM(AT89,AV101) -> 0.034980495 | AW89: =SUM(AV89,AW101) -> 0.032980495 | AX89: =SUM(AW89,AX101) -> 0.030980495 | AY89: =SUM(AX89,AY101) -> 0.028980495 | AZ89: =AZ97/$AK$85 -> 0.052178131 | BA89: =SUM(AY89,BA101) -> 0.026980495
C91: Average marketing % of actual | AF91: =AVERAGE(AB87:AE87) -> 0.078460246
C92: Average tech & development % of actual | AF92: =AVERAGE(AB88:AE88) -> 0.079437313
C93: Average SG&A % of actual | AF93: =AVERAGE(AB89:AE89) -> 0.050980495
C94: -1
C95: Marketing expenses | G95: USD'k | H95: ='Financial Statements'!H14*$C$94 -> 616578 | I95: ='Financial Statements'!I14*$C$94 -> 603150 | J95: ='Financial Statements'!J14*$C$94 -> 553797 | K95: ='Financial Statements'!K14*$C$94 -> 878937 | L95: =SUM(H95:K95) -> 2652462 | M95: ='Financial Statements'!M14*$C$94 -> 503830 | N95: ='Financial Statements'!N14*$C$94 -> 434370 | O95: ='Financial Statements'!O14*$C$94 -> 527597 | P95: ='Financial Statements'!P14*$C$94 -> 762565 | Q95: =SUM(M95:P95) -> 2228362 | R95: ='Financial Statements'!R14*$C$94 -> 512512 | S95: ='Financial Statements'!S14*$C$94 -> 603973 | T95: ='Financial Statements'!T14*$C$94 -> 635948 | U95: ='Financial Statements'!U14*$C$94 -> 792713 | V95: =SUM(R95:U95) -> 2545146 | W95: ='Financial Statements'!W14*$C$94 -> 555978 | X95: ='Financial Statements'!X14*$C$94 -> 574960 | Y95: ='Financial Statements'!Y14*$C$94 -> 567954 | Z95: ='Financial Statements'!Z14*$C$94 -> 831610 | AA95: =SUM(W95:Z95) -> 2530502 | AB95: ='Financial Statements'!AB14*$C$94 -> 555362 | AC95: ='Financial Statements'!AC14*$C$94 -> 627168 | AD95: ='Financial Statements'!AD14*$C$94 -> 558736 | AE95: ='Financial Statements'!AE14*$C$94 -> 916617 | AF95: =SUM(AB95:AE95) -> 2657883 | AG95: =AG87*AG$85 -> 713278.54 | AH95: =AH87*AH$85 -> 715337.05 | AI95: =AI87*AI$85 -> 723451.49 | AJ95: =AJ87*AJ$85 -> 740509.13 | AK95: =SUM(AG95:AJ95) -> 2892576.2 | AL95: =AL87*AL$85 -> 795298.44 | AM95: =AM87*AM$85 -> 843105.29 | AN95: =AN87*AN$85 -> 876310.38 | AO95: =AO87*AO$85 -> 926005.04 | AP95: =SUM(AL95:AO95) -> 3440719.2 | AQ95: =AQ87*AQ$85 -> 925893.84 | AR95: =AR87*AR$85 -> 916041.89 | AS95: =AS87*AS$85 -> 923373.28 | AT95: =AT87*AT$85 -> 946206.54 | AU95: =SUM(AQ95:AT95) -> 3711515.6 | AV95: =AV87*AV$85 -> 946842.52 | AW95: =AW87*AW$85 -> 938644.15 | AX95: =AX87*AX$85 -> 947730.02 | AY95: =AY87*AY$85 -> 973021.31 | AZ95: =SUM(AV95:AY95) -> 3806238 | BA95: =BA87*BA$85 -> 3877380.8
C96: Tech and development expenses | G96: USD'k | H96: ='Financial Statements'!H15*$C$94 -> 372764 | I96: ='Financial Statements'!I15*$C$94 -> 383233 | J96: ='Financial Statements'!J15*$C$94 -> 379776 | K96: ='Financial Statements'!K15*$C$94 -> 409376 | L96: =SUM(H96:K96) -> 1545149 | M96: ='Financial Statements'!M15*$C$94 -> 453817 | N96: ='Financial Statements'!N15*$C$94 -> 435045 | O96: ='Financial Statements'!O15*$C$94 -> 453802 | P96: ='Financial Statements'!P15*$C$94 -> 486936 | Q96: =SUM(M96:P96) -> 1829600 | R96: ='Financial Statements'!R15*$C$94 -> 525207 | S96: ='Financial Statements'!S15*$C$94 -> 537321 | T96: ='Financial Statements'!T15*$C$94 -> 563887 | U96: ='Financial Statements'!U15*$C$94 -> 647470 | V96: =SUM(R96:U96) -> 2273885 | W96: ='Financial Statements'!W15*$C$94 -> 657530 | X96: ='Financial Statements'!X15*$C$94 -> 716846 | Y96: ='Financial Statements'!Y15*$C$94 -> 662739 | Z96: ='Financial Statements'!Z15*$C$94 -> 673926 | AA96: =SUM(W96:Z96) -> 2711041 | AB96: ='Financial Statements'!AB15*$C$94 -> 687275 | AC96: ='Financial Statements'!AC15*$C$94 -> 657983 | AD96: ='Financial Statements'!AD15*$C$94 -> 657159 | AE96: ='Financial Statements'!AE15*$C$94 -> 673341 | AF96: =SUM(AB96:AE96) -> 2675758 | AG96: =AG88*AG$85 -> 722334.13 | AH96: =AH88*AH$85 -> 724599.3 | AI96: =AI88*AI$85 -> 733139.78 | AJ96: =AJ88*AJ$85 -> 750777.71 | AK96: =SUM(AG96:AJ96) -> 2930850.9 | AL96: =AL88*AL$85 -> 805948.9 | AM96: =AM88*AM$85 -> 854021.9 | AN96: =AN88*AN$85 -> 887732.61 | AO96: =AO88*AO$85 -> 938156.07 | AP96: =SUM(AL96:AO96) -> 3485859.5 | AQ96: =AQ88*AQ$85 -> 938465.5 | AR96: =AR88*AR$85 -> 928927.45 | AS96: =AS88*AS$85 -> 936846.91 | AT96: =AT88*AT$85 -> 960548.82 | AU96: =SUM(AQ96:AT96) -> 3764788.7 | AV96: =AV88*AV$85 -> 961654 | AW96: =AW88*AW$85 -> 953813.09 | AX96: =AX88*AX$85 -> 963569.77 | AY96: =AY88*AY$85 -> 989859.83 | AZ96: =SUM(AV96:AY96) -> 3868896.7 | BA96: =BA88*BA$85 -> 3946944.5
C97: SG&A | G97: USD'k | H97: ='Financial Statements'!H16*$C$94 -> 201952 | I97: ='Financial Statements'!I16*$C$94 -> 224657 | J97: ='Financial Statements'!J16*$C$94 -> 233174 | K97: ='Financial Statements'!K16*$C$94 -> 254586 | L97: =SUM(H97:K97) -> 914369 | M97: ='Financial Statements'!M16*$C$94 -> 252087 | N97: ='Financial Statements'!N16*$C$94 -> 277236 | O97: ='Financial Statements'!O16*$C$94 -> 271624 | P97: ='Financial Statements'!P16*$C$94 -> 275539 | Q97: =SUM(M97:P97) -> 1076486 | R97: ='Financial Statements'!R16*$C$94 -> 297196 | S97: ='Financial Statements'!S16*$C$94 -> 334845 | T97: ='Financial Statements'!T16*$C$94 -> 321790 | U97: ='Financial Statements'!U16*$C$94 -> 397790 | V97: =SUM(R97:U97) -> 1351621 | W97: ='Financial Statements'!W16*$C$94 -> 397928 | X97: ='Financial Statements'!X16*$C$94 -> 409297 | Y97: ='Financial Statements'!Y16*$C$94 -> 373213 | Z97: ='Financial Statements'!Z16*$C$94 -> 392453 | AA97: =SUM(W97:Z97) -> 1572891 | AB97: ='Financial Statements'!AB16*$C$94 -> 400924 | AC97: ='Financial Statements'!AC16*$C$94 -> 401497 | AD97: ='Financial Statements'!AD16*$C$94 -> 478591 | AE97: ='Financial Statements'!AE16*$C$94 -> 439273 | AF97: =SUM(AB97:AE97) -> 1720285 | AG97: =AG89*AG$85 -> 458592.29 | AH97: =AH89*AH$85 -> 454838.51 | AI97: =AI89*AI$85 -> 450970.68 | AJ97: =AJ89*AJ$85 -> 451707.89 | AK97: =SUM(AG97:AJ97) -> 1816109.4 | AL97: =AL89*AL$85 -> 495757.2 | AM97: =AM89*AM$85 -> 536078.42 | AN97: =AN89*AN$85 -> 555062.89 | AO97: =AO89*AO$85 -> 584260.43 | AP97: =SUM(AL97:AO97) -> 2171158.9 | AQ97: =AQ89*AQ$85 -> 572319.01 | AR97: =AR89*AR$85 -> 553638.87 | AS97: =AS89*AS$85 -> 544431.01 | AT97: =AT89*AT$85 -> 542833.58 | AU97: =SUM(AQ97:AT97) -> 2213222.5 | AV97: =AV89*AV$85 -> 530273.61 | AW97: =AW89*AW$85 -> 512021.55 | AX97: =AX89*AX$85 -> 502241.22 | AY97: =AY89*AY$85 -> 499442.38 | AZ97: =SUM(AV97:AY97) -> 2043978.8 | BA97: =BA89*BA$85 -> 1920917.7
C99: % change in marketing | G99: % | AG99: =Drivers!H75+AG103 -> -0.0015 | AH99: =Drivers!I75+AH103 -> -0.0015 | AI99: =Drivers!J75+AI103 -> -0.0025 | AJ99: =Drivers!K75+AJ103 -> -0.0025 | AK99: =AVERAGE(AG99:AJ99) -> -0.002 | AL99: =Drivers!M75+AL103 -> 0.0025 | AM99: =Drivers!N75+AM103 -> 0.0025 | AN99: =Drivers!O75+AN103 -> -0.0005 | AO99: =Drivers!P75+AO103 -> -0.0005 | AP99: =AVERAGE(AL99:AO99) -> 0.001 | AQ99: =Drivers!R75+AQ103 -> -0.0025 | AR99: =Drivers!S75+AR103 -> -0.0025 | AS99: =Drivers!T75+AS103 -> -0.0025 | AT99: =Drivers!U75+AT103 -> -0.0025 | AU99: =AVERAGE(AQ99:AT99) -> -0.0025 | AV99: =Drivers!W75+AV103 -> -0.002 | AW99: =Drivers!X75+AW103 -> -0.002 | AX99: =Drivers!Y75+AX103 -> -0.002 | AY99: =Drivers!Z75+AY103 -> -0.002 | AZ99: =AVERAGE(AV99:AY99) -> -0.002 | BA99: =Drivers!AB75+BA103 -> -0.002
C100: % change in tech & development | G100: % | AG100: =Drivers!H76+AG104 -> -0.0015 | AH100: =Drivers!I76+AH104 -> -0.0015 | AI100: =Drivers!J76+AI104 -> -0.0025 | AJ100: =Drivers!K76+AJ104 -> -0.0025 | AK100: =AVERAGE(AG100:AJ100) -> -0.002 | AL100: =Drivers!M76+AL104 -> 0.0025 | AM100: =Drivers!N76+AM104 -> 0.0025 | AN100: =Drivers!O76+AN104 -> -0.0005 | AO100: =Drivers!P76+AO104 -> -0.0005 | AP100: =AVERAGE(AL100:AO100) -> 0.001 | AQ100: =Drivers!R76+AQ104 -> -0.0025 | AR100: =Drivers!S76+AR104 -> -0.0025 | AS100: =Drivers!T76+AS104 -> -0.0025 | AT100: =Drivers!U76+AT104 -> -0.0025 | AU100: =AVERAGE(AQ100:AT100) -> -0.0025 | AV100: =Drivers!W76+AV104 -> -0.002 | AW100: =Drivers!X76+AW104 -> -0.002 | AX100: =Drivers!Y76+AX104 -> -0.002 | AY100: =Drivers!Z76+AY104 -> -0.002 | AZ100: =AVERAGE(AV100:AY100) -> -0.002 | BA100: =Drivers!AB76+BA104 -> -0.002
C101: % change in SG&A | G101: % | AG101: =Drivers!H77+AG105 -> -0.0015 | AH101: =Drivers!I77+AH105 -> -0.0015 | AI101: =Drivers!J77+AI105 -> -0.0025 | AJ101: =Drivers!K77+AJ105 -> -0.0025 | AK101: =AVERAGE(AG101:AJ101) -> -0.002 | AL101: =Drivers!M77+AL105 -> 0.0025 | AM101: =Drivers!N77+AM105 -> 0.0025 | AN101: =Drivers!O77+AN105 -> -0.0005 | AO101: =Drivers!P77+AO105 -> -0.0005 | AP101: =AVERAGE(AL101:AO101) -> 0.001 | AQ101: =Drivers!R77+AQ105 -> -0.0025 | AR101: =Drivers!S77+AR105 -> -0.0025 | AS101: =Drivers!T77+AS105 -> -0.0025 | AT101: =Drivers!U77+AT105 -> -0.0025 | AU101: =AVERAGE(AQ101:AT101) -> -0.0025 | AV101: =Drivers!W77+AV105 -> -0.002 | AW101: =Drivers!X77+AW105 -> -0.002 | AX101: =Drivers!Y77+AX105 -> -0.002 | AY101: =Drivers!Z77+AY105 -> -0.002 | AZ101: =AVERAGE(AV101:AY101) -> -0.002 | BA101: =Drivers!AB77+BA105 -> -0.002
C103: Bolt-on % change in marketing | G103: % | AG103: =Drivers!H97+Drivers!H115 -> 0.002 | AH103: =Drivers!I97+Drivers!I115 -> 0.002 | AI103: =Drivers!J97+Drivers!J115 -> 0.001 | AJ103: =Drivers!K97+Drivers!K115 -> 0.001 | AK103: =AVERAGE(AG103:AJ103) -> 0.0015 | AL103: =Drivers!M97+Drivers!M115 -> 0.0055 | AM103: =Drivers!N97+Drivers!N115 -> 0.0055 | AN103: =Drivers!O97+Drivers!O115 -> 0.0025 | AO103: =Drivers!P97+Drivers!P115 -> 0.0025 | AP103: =AVERAGE(AL103:AO103) -> 0.004 | AQ103: =Drivers!R97+Drivers!R115 -> 0 | AR103: =Drivers!S97+Drivers!S115 -> 0 | AS103: =Drivers!T97+Drivers!T115 -> 0 | AT103: =Drivers!U97+Drivers!U115 -> 0 | AU103: =AVERAGE(AQ103:AT103) -> 0 | AV103: =Drivers!W97+Drivers!W115 -> 0 | AW103: =Drivers!X97+Drivers!X115 -> 0 | AX103: =Drivers!Y97+Drivers!Y115 -> 0 | AY103: =Drivers!Z97+Drivers!Z115 -> 0 | AZ103: =AVERAGE(AV103:AY103) -> 0 | BA103: =Drivers!AB97+Drivers!AB115 -> 0
C104: Bolt-on % change in tech & development | G104: % | AG104: =Drivers!H98+Drivers!H116 -> 0.002 | AH104: =Drivers!I98+Drivers!I116 -> 0.002 | AI104: =Drivers!J98+Drivers!J116 -> 0.001 | AJ104: =Drivers!K98+Drivers!K116 -> 0.001 | AK104: =AVERAGE(AG104:AJ104) -> 0.0015 | AL104: =Drivers!M98+Drivers!M116 -> 0.0055 | AM104: =Drivers!N98+Drivers!N116 -> 0.0055 | AN104: =Drivers!O98+Drivers!O116 -> 0.0025 | AO104: =Drivers!P98+Drivers!P116 -> 0.0025 | AP104: =AVERAGE(AL104:AO104) -> 0.004 | AQ104: =Drivers!R98+Drivers!R116 -> 0 | AR104: =Drivers!S98+Drivers!S116 -> 0 | AS104: =Drivers!T98+Drivers!T116 -> 0 | AT104: =Drivers!U98+Drivers!U116 -> 0 | AU104: =AVERAGE(AQ104:AT104) -> 0 | AV104: =Drivers!W98+Drivers!W116 -> 0 | AW104: =Drivers!X98+Drivers!X116 -> 0 | AX104: =Drivers!Y98+Drivers!Y116 -> 0 | AY104: =Drivers!Z98+Drivers!Z116 -> 0 | AZ104: =AVERAGE(AV104:AY104) -> 0 | BA104: =Drivers!AB98+Drivers!AB116 -> 0
C105: Bolt-on % change in SG&A | G105: % | AG105: =Drivers!H99+Drivers!H117 -> 0.002 | AH105: =Drivers!I99+Drivers!I117 -> 0.002 | AI105: =Drivers!J99+Drivers!J117 -> 0.001 | AJ105: =Drivers!K99+Drivers!K117 -> 0.001 | AK105: =AVERAGE(AG105:AJ105) -> 0.0015 | AL105: =Drivers!M99+Drivers!M117 -> 0.0055 | AM105: =Drivers!N99+Drivers!N117 -> 0.0055 | AN105: =Drivers!O99+Drivers!O117 -> 0.0025 | AO105: =Drivers!P99+Drivers!P117 -> 0.0025 | AP105: =AVERAGE(AL105:AO105) -> 0.004 | AQ105: =Drivers!R99+Drivers!R117 -> 0 | AR105: =Drivers!S99+Drivers!S117 -> 0 | AS105: =Drivers!T99+Drivers!T117 -> 0 | AT105: =Drivers!U99+Drivers!U117 -> 0 | AU105: =AVERAGE(AQ105:AT105) -> 0 | AV105: =Drivers!W99+Drivers!W117 -> 0 | AW105: =Drivers!X99+Drivers!X117 -> 0 | AX105: =Drivers!Y99+Drivers!Y117 -> 0 | AY105: =Drivers!Z99+Drivers!Z117 -> 0 | AZ105: =AVERAGE(AV105:AY105) -> 0 | BA105: =Drivers!AB99+Drivers!AB117 -> 0
C107: Derived OPEX | G107: USD'k | H107: =SUM(H95:H97) -> 1191294 | I107: =SUM(I95:I97) -> 1211040 | J107: =SUM(J95:J97) -> 1166747 | K107: =SUM(K95:K97) -> 1542899 | L107: =SUM(L95:L97) -> 5111980 | M107: =SUM(M95:M97) -> 1209734 | N107: =SUM(N95:N97) -> 1146651 | O107: =SUM(O95:O97) -> 1253023 | ... BA107: =SUM(BA95:BA97) -> 9745243
C108: OPEX as % of sales | G108: % | H108: =H107/H85 -> 0.26350279 | I108: =I107/I85 -> 0.24599055 | J108: =J107/J85 -> 0.22245341 | K108: =K107/K85 -> 0.28219801 | L108: =L107/L85 -> 0.25361513 | M108: =M107/M85 -> 0.20974321 | N108: =N107/N85 -> 0.18649929 | O108: =O107/O85 -> 0.1947007 | ... BA108: =BA107/BA85 -> 0.13687805
C110: Base Schedule
C112: Summary
C113: Revenues | AG113: =SUM(AG119,AG126,AG133,AG140) -> 9231734.9 | AH113: =SUM(AH119,AH126,AH133,AH140) -> 9438660 | AI113: =SUM(AI119,AI126,AI133,AI140) -> 9866412.3 | AJ113: =SUM(AJ119,AJ126,AJ133,AJ140) -> 10444117 | AK113: =SUM(AK119,AK126,AK133,AK140) -> 38980924 | AL113: =SUM(AL119,AL126,AL133,AL140) -> 10811147 | AM113: =SUM(AM119,AM126,AM133,AM140) -> 11074462 | AN113: =SUM(AN119,AN126,AN133,AN140) -> 11575413 | ... AZ113: =SUM(AZ119,AZ126,AZ133,AZ140) -> 63322793
C114: COGS | AG114: =-SUM(AG147,AG151) -> -5420769.2 | AH114: =-SUM(AH147,AH151) -> -5430722.7 | AI114: =-SUM(AI147,AI151) -> -5551618 | AJ114: =-SUM(AJ147,AJ151) -> -5737001.8 | AK114: =-SUM(AK147,AK151) -> -22140112 | AL114: =-SUM(AL147,AL151) -> -6004852.9 | AM114: =-SUM(AM147,AM151) -> -6244298.7 | AN114: =-SUM(AN147,AN151) -> -6475065.3 | ... AZ114: =-SUM(AZ147,AZ151) -> -30996494
C115: Gross Profit | G115: USD'k | AG115: =SUM(AG113:AG114) -> 3810965.7 | AH115: =SUM(AH113:AH114) -> 4007937.3 | AI115: =SUM(AI113:AI114) -> 4314794.3 | AJ115: =SUM(AJ113:AJ114) -> 4707114.8 | AK115: =SUM(AK113:AK114) -> 16840812 | AL115: =SUM(AL113:AL114) -> 4806294.5 | AM115: =SUM(AM113:AM114) -> 4830163.1 | AN115: =SUM(AN113:AN114) -> 5100348.1 | ... AZ115: =SUM(AZ113:AZ114) -> 32326299 | BC115: =IFERROR((Q115/L115)^(1/(_xlfn.NUMBERVALUE(LEFT(Q$6,4))-_xlfn.NUMBERVALUE(LEFT(L$6,4))))-1,"NA") -> NA | BD115: =IFERROR((V115/Q115)^(1/(_xlfn.NUMBERVALUE(LEFT(V$6,4))-_xlfn.NUMBERVALUE(LEFT(Q$6,4))))-1,"NA") -> NA | BE115: =IFERROR((AA115/V115)^(1/(_xlfn.NUMBERVALUE(LEFT(AA$6,4))-_xlfn.NUMBERVALUE(LEFT(V$6,4))))-1,"NA") -> NA | BF115: =IFERROR((AF115/AA115)^(1/(_xlfn.NUMBERVALUE(LEFT(AF$6,4))-_xlfn.NUMBERVALUE(LEFT(AA$6,4))))-1,"NA") -> NA
C117: Streaming revenue breakdown
C118: Europe, Middle East, and Africa (EMEA)
C119: Revenues | G119: USD'k | AF119: =AF21 -> 10556487 | AG119: =AG123*AG122*3 -> 2919891.6 | AH119: =AH123*AH122*3 -> 3005946.7 | AI119: =AI123*AI122*3 -> 3179559.9 | AJ119: =AJ123*AJ122*3 -> 3395098.2 | AK119: =SUM(AG119:AJ119) -> 12500496 | AL119: =AL123*AL122*3 -> 3511491.6 | AM119: =AM123*AM122*3 -> 3617010.6 | AN119: =AN123*AN122*3 -> 3829690.6 | AO119: =AO123*AO122*3 -> 4103902.9 | AP119: =SUM(AL119:AO119) -> 15062096 | AQ119: =AQ123*AQ122*3 -> 4237979.7 | AR119: =AR123*AR122*3 -> 4364122.5 | AS119: =AS123*AS122*3 -> 4618961.9 | AT119: =AT123*AT122*3 -> 4954007.8 | AU119: =SUM(AQ119:AT119) -> 18175072 | AV119: =AV123*AV122*3 -> 5111140.6 | AW119: =AW123*AW122*3 -> 5256851.9 | AX119: =AX123*AX122*3 -> 5554657.5 | AY119: =AY123*AY122*3 -> 5951218.4 | AZ119: =SUM(AV119:AY119) -> 21873868
C120: Paid net membership additions | G120: #'k | AF120: =AF22 -> 12084 | AG120: =Drivers!H18 -> 772.8 | AH120: =Drivers!I18 -> 2677.4 | AI120: =Drivers!J18 -> 4506.42 | AJ120: =Drivers!K18 -> 5962.54 | AK120: =SUM(AG120:AJ120) -> 13919.16 | AL120: =Drivers!M18 -> 926.3296 | AM120: =Drivers!N18 -> 2971.4272 | AN120: =Drivers!O18 -> 5124.9854 | AO120: =Drivers!P18 -> 7004.6707 | AP120: =SUM(AL120:AO120) -> 16027.413 | AQ120: =Drivers!R18 -> 1094.7299 | AR120: =Drivers!S18 -> 3315.1314 | AS120: =Drivers!T18 -> 5860.9518 | AT120: =Drivers!U18 -> 8230.611 | AU120: =SUM(AQ120:AT120) -> 18501.424 | AV120: =Drivers!W18 -> 1249.3605 | AW120: =Drivers!X18 -> 3639.1548 | AX120: =Drivers!Y18 -> 6591.7059 | AY120: =Drivers!Z18 -> 9393.1848 | AZ120: =SUM(AV120:AY120) -> 20873.406
C121: Paid memberships at end of period | G121: #'k | AF121: =AF23 -> 88813 | AG121: =AF121+AG120 -> 89585.8 | AH121: =AG121+AH120 -> 92263.2 | AI121: =AH121+AI120 -> 96769.62 | AJ121: =AI121+AJ120 -> 102732.16 | AK121: =AJ121 -> 102732.16 | AL121: =AK121+AL120 -> 103658.49 | AM121: =AL121+AM120 -> 106629.92 | AN121: =AM121+AN120 -> 111754.9 | AO121: =AN121+AO120 -> 118759.57 | AP121: =AO121 -> 118759.57 | AQ121: =AP121+AQ120 -> 119854.3 | AR121: =AQ121+AR120 -> 123169.43 | AS121: =AR121+AS120 -> 129030.39 | AT121: =AS121+AT120 -> 137261 | AU121: =AT121 -> 137261 | AV121: =AU121+AV120 -> 138510.36 | AW121: =AV121+AW120 -> 142149.51 | AX121: =AW121+AX120 -> 148741.22 | AY121: =AX121+AY120 -> 158134.4 | AZ121: =AY121 -> 158134.4
C122: Average paying memberships | G122: #'k | AF122: =AF24 -> 80928 | AG122: =Drivers!$I$62*Operating!AG121 -> 86911.818 | AH122: =Drivers!$I$62*Operating!AH121 -> 89509.302 | AI122: =Drivers!$I$62*Operating!AI121 -> 93881.213 | AJ122: =Drivers!$I$62*Operating!AJ121 -> 99665.782 | AK122: =AVERAGE(AG122:AJ122) -> 92492.029 | AL122: =Drivers!$I$62*Operating!AL121 -> 100564.46 | AM122: =Drivers!$I$62*Operating!AM121 -> 103447.2 | AN122: =Drivers!$I$62*Operating!AN121 -> 108419.21 | AO122: =Drivers!$I$62*Operating!AO121 -> 115214.8 | AP122: =AVERAGE(AL122:AO122) -> 106911.42 | AQ122: =Drivers!$I$62*Operating!AQ121 -> 116276.86 | AR122: =Drivers!$I$62*Operating!AR121 -> 119493.04 | AS122: =Drivers!$I$62*Operating!AS121 -> 125179.05 | AT122: =Drivers!$I$62*Operating!AT121 -> 133163.99 | AU122: =AVERAGE(AQ122:AT122) -> 123528.23 | AV122: =Drivers!$I$62*Operating!AV121 -> 134376.06 | AW122: =Drivers!$I$62*Operating!AW121 -> 137906.59 | AX122: =Drivers!$I$62*Operating!AX121 -> 144301.55 | AY122: =Drivers!$I$62*Operating!AY121 -> 153414.36 | AZ122: =AVERAGE(AV122:AY122) -> 142499.64
C123: Average monthly revenue per paying membership (ARPU) | G123: USD | AF123: =AF25 -> 10.8725 | AG123: =Drivers!H45 -> 11.198675 | AH123: =Drivers!I45 -> 11.194169 | AI123: =Drivers!J45 -> 11.289301 | AJ123: =Drivers!K45 -> 11.354944 | AK123: =AVERAGE(AG123:AJ123) -> 11.259272 | AL123: =Drivers!M45 -> 11.639273 | AM123: =Drivers!N45 -> 11.654933 | AN123: =Drivers!O45 -> 11.77433 | AO123: =Drivers!P45 -> 11.873193 | AP123: =AVERAGE(AL123:AO123) -> 11.735432 | AQ123: =Drivers!R45 -> 12.149106 | AR123: =Drivers!S45 -> 12.173994 | AS123: =Drivers!T45 -> 12.299614 | AT123: =Drivers!U45 -> 12.400769 | AU123: =AVERAGE(AQ123:AT123) -> 12.255871 | AV123: =Drivers!W45 -> 12.678698 | AW123: =Drivers!X45 -> 12.70631 | AX123: =Drivers!Y45 -> 12.831134 | AY123: =Drivers!Z45 -> 12.930598 | AZ123: =AVERAGE(AV123:AY123) -> 12.786685
C125: United States and Canada (UCAN)
C126: Revenues | G126: USD'k | AF126: =AF28 -> 14873783 | AG126: =AG130*AG129*3 -> 4022439 | AH126: =AH130*AH129*3 -> 4092645 | AI126: =AI130*AI129*3 -> 4245609.5 | AJ126: =AJ130*AJ129*3 -> 4452091.9 | AK126: =SUM(AG126:AJ126) -> 16812785 | AL126: =AL130*AL129*3 -> 4567432.9 | AM126: =AM130*AM129*3 -> 4653609.6 | AN126: =AN130*AN129*3 -> 4823445.5 | AO126: =AO130*AO129*3 -> 5069070.4 | AP126: =SUM(AL126:AO126) -> 19113558 | AQ126: =AQ130*AQ129*3 -> 5216313.3 | AR126: =AR130*AR129*3 -> 5316632.1 | AS126: =AS130*AS129*3 -> 5511099.8 | AT126: =AT130*AT129*3 -> 5805261.4 | AU126: =SUM(AQ126:AT126) -> 21849307 | AV126: =AV130*AV129*3 -> 5970947 | AW126: =AW130*AW129*3 -> 6086360.5 | AX126: =AX130*AX129*3 -> 6306391.3 | AY126: =AY130*AY129*3 -> 6647393.9 | AZ126: =SUM(AV126:AY126) -> 25011093
...

Sheet Drivers
C5: Drivers | L5: Forecasts
G6: Units | H6: 24Q1 | I6: 24Q2 | J6: 24Q3 | K6: 24Q4 | L6: 2024E | M6: 25Q1 | N6: 25Q2 | O6: 25Q3 | P6: 25Q4 | Q6: 2025E | R6: 26Q1 | S6: 26Q2 | T6: 26Q3 | U6: 26Q4 | V6: 2026E | W6: 27Q1 | X6: 27Q2 | Y6: 27Q3 | Z6: 27Q4 | AA6: 2027E | AB6: =Operating!BA6 -> 2028E
C8: Live Case
C10: Scenario | G10: =IF(H10=1,"Base",IF(H10=2,"Bull","Bear")) -> Base | H10: =Output!H3 -> 1
C12: Derived paid net membership additions
C13: Total Q growth in EMEA memberships | G13: # | H13: =IF(((1+Drivers!H29)*Operating!AB22)<0,((1+Drivers!H29)*AVERAGE(Operating!AB22,Operating!W22,Operating!R22,Operating!M22,Operating!H22)),((1+Drivers!H29)*Operating!AB22)) -> 798.56 | I13: =IF(((1+Drivers!I29)*Operating!AC22)<0,((1+Drivers!I29)*AVERAGE(Operating!AC22,Operating!X22,Operating!S22,Operating!N22,Operating!I22)),((1+Drivers!I29)*Operating!AC22)) -> 2726.08 | J13: =IF(((1+Drivers!J29)*Operating!AD22)<0,((1+Drivers!J29)*AVERAGE(Operating!AD22,Operating!Y22,Operating!T22,Operating!O22,Operating!J22)),((1+Drivers!J29)*Operating!AD22)) -> 4617.104 | K13: =IF(((1+Drivers!K29)*Operating!AE22)<0,((1+Drivers!K29)*AVERAGE(Operating!AE22,Operating!Z22,Operating!U22,Operating!P22,Operating!K22)),((1+Drivers!K29)*Operating!AE22)) -> 6144.448 | L13: =SUM(H13:K13) -> 14286.192 | M13: =IF(((1+Drivers!M29)*Operating!AG22)<0,((1+Drivers!M29)*AVERAGE(Operating!AG22,Operating!AB22,Operating!W22,Operating!R22,Operating!M22)),((1+Drivers!M29)*Operating!AG22)) -> 977.43744 | N13: =IF(((1+Drivers!N29)*Operating!AH22)<0,((1+Drivers!N29)*AVERAGE(Operating!AH22,Operating!AC22,Operating!X22,Operating!S22,Operating!N22)),((1+Drivers!N29)*Operating!AH22)) -> 3069.5661 | O13: =IF(((1+Drivers!O29)*Operating!AI22)<0,((1+Drivers!O29)*AVERAGE(Operating!AI22,Operating!AD22,Operating!Y22,Operating!T22,Operating!O22)),((1+Drivers!O29)*Operating!AI22)) -> 5328.138 | P13: =IF(((1+Drivers!P29)*Operating!AJ22)<0,((1+Drivers!P29)*AVERAGE(Operating!AJ22,Operating!AE22,Operating!Z22,Operating!U22,Operating!P22)),((1+Drivers!P29)*Operating!AJ22)) -> 7348.7598 | Q13: =SUM(M13:P13) -> 16723.901 | R13: =IF(((1+Drivers!R29)*Operating!AL22)<0,((1+Drivers!R29)*AVERAGE(Operating!AL22,Operating!AG22,Operating!AB22,Operating!W22,Operating!R22)),((1+Drivers!R29)*Operating!AL22)) -> 1135.7823 | S13: =IF(((1+Drivers!S29)*Operating!AM22)<0,((1+Drivers!S29)*AVERAGE(Operating!AM22,Operating!AH22,Operating!AC22,Operating!X22,Operating!S22)),((1+Drivers!S29)*Operating!AM22)) -> 3401.0792 | T13: =IF(((1+Drivers!T29)*Operating!AN22)<0,((1+Drivers!T29)*AVERAGE(Operating!AN22,Operating!AI22,Operating!AD22,Operating!Y22,Operating!T22)),((1+Drivers!T29)*Operating!AN22)) -> 6047.4366 | U13: =IF(((1+Drivers!U29)*Operating!AO22)<0,((1+Drivers!U29)*AVERAGE(Operating!AO22,Operating!AJ22,Operating!AE22,Operating!Z22,Operating!U22)),((1+Drivers!U29)*Operating!AO22)) -> 8539.2589 | V13: =SUM(R13:U13) -> 19123.557 | W13: =IF(((1+Drivers!W29)*Operating!AQ22)<0,((1+Drivers!W29)*AVERAGE(Operating!AQ22,Operating!AL22,Operating!AG22,Operating!AB22,Operating!W22)),((1+Drivers!W29)*Operating!AQ22)) -> 1274.9156 | X13: =IF(((1+Drivers!X29)*Operating!AR22)<0,((1+Drivers!X29)*AVERAGE(Operating!AR22,Operating!AM22,Operating!AH22,Operating!AC22,Operating!X22)),((1+Drivers!X29)*Operating!AR22)) -> 3692.7218 | Y13: =IF(((1+Drivers!Y29)*Operating!AS22)<0,((1+Drivers!Y29)*AVERAGE(Operating!AS22,Operating!AN22,Operating!AI22,Operating!AD22,Operating!Y22)),((1+Drivers!Y29)*Operating!AS22)) -> 6714.1665 | Z13: =IF(((1+Drivers!Z29)*Operating!AT22)<0,((1+Drivers!Z29)*AVERAGE(Operating!AT22,Operating!AO22,Operating!AJ22,Operating!AE22,Operating!Z22)),((1+Drivers!Z29)*Operating!AT22)) -> 9585.3181 | AA13: =SUM(W13:Z13) -> 21267.122 | AB13: =IF(((1+Drivers!AB29)*Operating!AV22)<0,((1+Drivers!AB29)*AVERAGE(Operating!AV22,Operating!AQ22,Operating!AL22,Operating!AG22,Operating!AB22)),((1+Drivers!AB29)*Operating!AV22)) -> 1415.4751
C14: Total Q growth in UCAN memberships | G14: # | H14: =IF(((1+Drivers!H30)*Operating!AB29)<0,((1+Drivers!H30)*AVERAGE(Operating!AB29,Operating!W29,Operating!R29,Operating!M29,Operating!H29)),((1+Drivers!H30)*Operating!AB29)) -> 126.48 | I14: =IF(((1+Drivers!I30)*Operating!AC29)<0,((1+Drivers!I30)*AVERAGE(Operating!AC29,Operating!X29,Operating!S29,Operating!N29,Operating!I29)),((1+Drivers!I30)*Operating!AC29)) -> 1299.684 | J14: =IF(((1+Drivers!J30)*Operating!AD29)<0,((1+Drivers!J30)*AVERAGE(Operating!AD29,Operating!Y29,Operating!T29,Operating!O29,Operating!J29)),((1+Drivers!J30)*Operating!AD29)) -> 1897 | K14: =IF(((1+Drivers!K30)*Operating!AE29)<0,((1+Drivers!K30)*AVERAGE(Operating!AE29,Operating!Z29,Operating!U29,Operating!P29,Operating!K29)),((1+Drivers!K30)*Operating!AE29)) -> 3278.576 | L14: =SUM(H14:K14) -> 6601.74 | M14: =IF(((1+Drivers!M30)*Operating!AG29)<0,((1+Drivers!M30)*AVERAGE(Operating!AG29,Operating!AB29,Operating!W29,Operating!R29,Operating!M29)),((1+Drivers!M30)*Operating!AG29)) -> 150.32148 | N14: =IF(((1+Drivers!N30)*Operating!AH29)<0,((1+Drivers!N30)*AVERAGE(Operating!AH29,Operating!AC29,Operating!X29,Operating!S29,Operating!N29)),((1+Drivers!N30)*Operating!AH29)) -> 1450.4473 | O14: =IF(((1+Drivers!O30)*Operating!AI29)<0,((1+Drivers!O30)*AVERAGE(Operating!AI29,Operating!AD29,Operating!Y29,Operating!T29,Operating!O29)),((1+Drivers!O30)*Operating!AI29)) -> 2144.5585 | P14: =IF(((1+Drivers!P30)*Operating!AJ29)<0,((1+Drivers!P30)*AVERAGE(Operating!AJ29,Operating!AE29,Operating!Z29,Operating!U29,Operating!P29)),((1+Drivers!P30)*Operating!AJ29)) -> 3849.0482 | Q14: =SUM(M14:P14) -> 7594.3755 | R14: =IF(((1+Drivers!R30)*Operating!AL29)<0,((1+Drivers!R30)*AVERAGE(Operating!AL29,Operating!AG29,Operating!AB29,Operating!W29,Operating!R29)),((1+Drivers!R30)*Operating!AL29)) -> 171.36649 | S14: =IF(((1+Drivers!S30)*Operating!AM29)<0,((1+Drivers!S30)*AVERAGE(Operating!AM29,Operating!AH29,Operating!AC29,Operating!X29,Operating!S29)),((1+Drivers!S30)*Operating!AM29)) -> 1592.5912 | T14: =IF(((1+Drivers!T30)*Operating!AN29)<0,((1+Drivers!T30)*AVERAGE(Operating!AN29,Operating!AI29,Operating!AD29,Operating!Y29,Operating!T29)),((1+Drivers!T30)*Operating!AN29)) -> 2354.7252 | U14: =IF(((1+Drivers!U30)*Operating!AO29)<0,((1+Drivers!U30)*AVERAGE(Operating!AO29,Operating!AJ29,Operating!AE29,Operating!Z29,Operating!U29)),((1+Drivers!U30)*Operating!AO29)) -> 4387.915 | V14: =SUM(R14:U14) -> 8506.5979 | W14: =IF(((1+Drivers!W30)*Operating!AQ29)<0,((1+Drivers!W30)*AVERAGE(Operating!AQ29,Operating!AL29,Operating!AG29,Operating!AB29,Operating!W29)),((1+Drivers!W30)*Operating!AQ29)) -> 188.84587 | X14: =IF(((1+Drivers!X30)*Operating!AR29)<0,((1+Drivers!X30)*AVERAGE(Operating!AR29,Operating!AM29,Operating!AH29,Operating!AC29,Operating!X29)),((1+Drivers!X30)*Operating!AR29)) -> 1734.7299 | Y14: =IF(((1+Drivers!Y30)*Operating!AS29)<0,((1+Drivers!Y30)*AVERAGE(Operating!AS29,Operating!AN29,Operating!AI29,Operating!AD29,Operating!Y29)),((1+Drivers!Y30)*Operating!AS29)) -> 2564.8845 | Z14: =IF(((1+Drivers!Z30)*Operating!AT29)<0,((1+Drivers!Z30)*AVERAGE(Operating!AT29,Operating!AO29,Operating!AJ29,Operating!AE29,Operating!Z29)),((1+Drivers!Z30)*Operating!AT29)) -> 4835.4823 | AA14: =SUM(W14:Z14) -> 9323.9426 | AB14: =IF(((1+Drivers!AB30)*Operating!AV29)<0,((1+Drivers!AB30)*AVERAGE(Operating!AV29,Operating!AQ29,Operating!AL29,Operating!AG29,Operating!AB29)),((1+Drivers!AB30)*Operating!AV29)) -> 206.90426
C15: Total Q growth in LATAM memberships | G15: # | H15: =IF(((1+Drivers!H31)*Operating!AB36)<0,((1+Drivers!H31)*AVERAGE(Operating!AB36,Operating!W36,Operating!R36,Operating!M36,Operating!H36)),((1+Drivers!H31)*Operating!AB36)) -> 973.896 | I15: =IF(((1+Drivers!I31)*Operating!AC36)<0,((1+Drivers!I31)*AVERAGE(Operating!AC36,Operating!X36,Operating!S36,Operating!N36,Operating!I36)),((1+Drivers!I31)*Operating!AC36)) -> 1363.04 | J15: =IF(((1+Drivers!J31)*Operating!AD36)<0,((1+Drivers!J31)*AVERAGE(Operating!AD36,Operating!Y36,Operating!T36,Operating!O36,Operating!J36)),((1+Drivers!J31)*Operating!AD36)) -> 1278.036 | K15: =IF(((1+Drivers!K31)*Operating!AE36)<0,((1+Drivers!K31)*AVERAGE(Operating!AE36,Operating!Z36,Operating!U36,Operating!P36,Operating!K36)),((1+Drivers!K31)*Operating!AE36)) -> 2718.912 | L15: =SUM(H15:K15) -> 6333.884 | M15: =IF(((1+Drivers!M31)*Operating!AG36)<0,((1+Drivers!M31)*AVERAGE(Operating!AG36,Operating!AB36,Operating!W36,Operating!R36,Operating!M36)),((1+Drivers!M31)*Operating!AG36)) -> 1118.5196 | N15: =IF(((1+Drivers!N31)*Operating!AH36)<0,((1+Drivers!N31)*AVERAGE(Operating!AH36,Operating!AC36,Operating!X36,Operating!S36,Operating!N36)),((1+Drivers!N31)*Operating!AH36)) -> 1528.6494 | O15: =IF(((1+Drivers!O31)*Operating!AI36)<0,((1+Drivers!O31)*AVERAGE(Operating!AI36,Operating!AD36,Operating!Y36,Operating!T36,Operating!O36)),((1+Drivers!O31)*Operating!AI36)) -> 1381.5569 | P15: =IF(((1+Drivers!P31)*Operating!AJ36)<0,((1+Drivers!P31)*AVERAGE(Operating!AJ36,Operating!AE36,Operating!Z36,Operating!U36,Operating!P36)),((1+Drivers!P31)*Operating!AJ36)) -> 3049.2598 | Q15: =SUM(M15:P15) -> 7077.9856 | R15: =IF(((1+Drivers!R31)*Operating!AL36)<0,((1+Drivers!R31)*AVERAGE(Operating!AL36,Operating!AG36,Operating!AB36,Operating!W36,Operating!R36)),((1+Drivers!R31)*Operating!AL36)) -> 1220.3048 | S15: =IF(((1+Drivers!S31)*Operating!AM36)<0,((1+Drivers!S31)*AVERAGE(Operating!AM36,Operating!AH36,Operating!AC36,Operating!X36,Operating!S36)),((1+Drivers!S31)*Operating!AM36)) -> 1687.6289 | T15: =IF(((1+Drivers!T31)*Operating!AN36)<0,((1+Drivers!T31)*AVERAGE(Operating!AN36,Operating!AI36,Operating!AD36,Operating!Y36,Operating!T36)),((1+Drivers!T31)*Operating!AN36)) -> 1471.3581 | U15: =IF(((1+Drivers!U31)*Operating!AO36)<0,((1+Drivers!U31)*AVERAGE(Operating!AO36,Operating!AJ36,Operating!AE36,Operating!Z36,Operating!U36)),((1+Drivers!U31)*Operating!AO36)) -> 3366.3828 | V15: =SUM(R15:U15) -> 7745.6747 | W15: =IF(((1+Drivers!W31)*Operating!AQ36)<0,((1+Drivers!W31)*AVERAGE(Operating!AQ36,Operating!AL36,Operating!AG36,Operating!AB36,Operating!W36)),((1+Drivers!W31)*Operating!AQ36)) -> 1306.3363 | X15: =IF(((1+Drivers!X31)*Operating!AR36)<0,((1+Drivers!X31)*AVERAGE(Operating!AR36,Operating!AM36,Operating!AH36,Operating!AC36,Operating!X36)),((1+Drivers!X31)*Operating!AR36)) -> 1826.4364 | Y15: =IF(((1+Drivers!Y31)*Operating!AS36)<0,((1+Drivers!Y31)*AVERAGE(Operating!AS36,Operating!AN36,Operating!AI36,Operating!AD36,Operating!Y36)),((1+Drivers!Y31)*Operating!AS36)) -> 1575.0889 | Z15: =IF(((1+Drivers!Z31)*Operating!AT36)<0,((1+Drivers!Z31)*AVERAGE(Operating!AT36,Operating!AO36,Operating!AJ36,Operating!AE36,Operating!Z36)),((1+Drivers!Z31)*Operating!AT36)) -> 3603.7128 | AA15: =SUM(W15:Z15) -> 8311.5744 | AB15: =IF(((1+Drivers!AB31)*Operating!AV36)<0,((1+Drivers!AB31)*AVERAGE(Operating!AV36,Operating!AQ36,Operating!AL36,Operating!AG36,Operating!AB36)),((1+Drivers!AB31)*Operating!AV36)) -> 1402.2704
C16: Total Q growth in APAC memberships | G16: # | H16: =IF(((1+Drivers!H32)*Operating!AB43)<0,((1+Drivers!H32)*AVERAGE(Operating!AB43,Operating!W43,Operating!R43,Operating!M43,Operating!H43)),((1+Drivers!H32)*Operating!AB43)) -> 1804.2 | I16: =IF(((1+Drivers!I32)*Operating!AC43)<0,((1+Drivers!I32)*AVERAGE(Operating!AC43,Operating!X43,Operating!S43,Operating!N43,Operating!I43)),((1+Drivers!I32)*Operating!AC43)) -> 1221.792 | J16: =IF(((1+Drivers!J32)*Operating!AD43)<0,((1+Drivers!J32)*AVERAGE(Operating!AD43,Operating!Y43,Operating!T43,Operating!O43,Operating!J43)),((1+Drivers!J32)*Operating!AD43)) -> 2242.152 | K16: =IF(((1+Drivers!K32)*Operating!AE43)<0,((1+Drivers!K32)*AVERAGE(Operating!AE43,Operating!Z43,Operating!U43,Operating!P43,Operating!K43)),((1+Drivers!K32)*Operating!AE43)) -> 3539.776 | L16: =SUM(H16:K16) -> 8807.92 | M16: =IF(((1+Drivers!M32)*Operating!AG43)<0,((1+Drivers!M32)*AVERAGE(Operating!AG43,Operating!AB43,Operating!W43,Operating!R43,Operating!M43)),((1+Drivers!M32)*Operating!AG43)) -> 2179.4736 | N16: =IF(((1+Drivers!N32)*Operating!AH43)<0,((1+Drivers!N32)*AVERAGE(Operating!AH43,Operating!AC43,Operating!X43,Operating!S43,Operating!N43)),((1+Drivers!N32)*Operating!AH43)) -> 1364.7417 | O16: =IF(((1+Drivers!O32)*Operating!AI43)<0,((1+Drivers!O32)*AVERAGE(Operating!AI43,Operating!AD43,Operating!Y43,Operating!T43,Operating!O43)),((1+Drivers!O32)*Operating!AI43)) -> 2562.7797 | P16: =IF(((1+Drivers!P32)*Operating!AJ43)<0,((1+Drivers!P32)*AVERAGE(Operating!AJ43,Operating!AE43,Operating!Z43,Operating!U43,Operating!P43)),((1+Drivers!P32)*Operating!AJ43)) -> 4184.0152 | Q16: =SUM(M16:P16) -> 10291.01 | R16: =IF(((1+Drivers!R32)*Operating!AL43)<0,((1+Drivers!R32)*AVERAGE(Operating!AL43,Operating!AG43,Operating!AB43,Operating!W43,Operating!R43)),((1+Drivers!R32)*Operating!AL43)) -> 2506.3946 | S16: =IF(((1+Drivers!S32)*Operating!AM43)<0,((1+Drivers!S32)*AVERAGE(Operating!AM43,Operating!AH43,Operating!AC43,Operating!X43,Operating!S43)),((1+Drivers!S32)*Operating!AM43)) -> 1501.2158 | T16: =IF(((1+Drivers!T32)*Operating!AN43)<0,((1+Drivers!T32)*AVERAGE(Operating!AN43,Operating!AI43,Operating!AD43,Operating!Y43,Operating!T43)),((1+Drivers!T32)*Operating!AN43)) -> 2883.1272 | U16: =IF(((1+Drivers!U32)*Operating!AO43)<0,((1+Drivers!U32)*AVERAGE(Operating!AO43,Operating!AJ43,Operating!AE43,Operating!Z43,Operating!U43)),((1+Drivers!U32)*Operating!AO43)) -> 4811.6175 | V16: =SUM(R16:U16) -> 11702.355 | W16: =IF(((1+Drivers!W32)*Operating!AQ43)<0,((1+Drivers!W32)*AVERAGE(Operating!AQ43,Operating!AL43,Operating!AG43,Operating!AB43,Operating!W43)),((1+Drivers!W32)*Operating!AQ43)) -> 2788.364 | X16: =IF(((1+Drivers!X32)*Operating!AR43)<0,((1+Drivers!X32)*AVERAGE(Operating!AR43,Operating!AM43,Operating!AH43,Operating!AC43,Operating!X43)),((1+Drivers!X32)*Operating!AR43)) -> 1619.4366 | Y16: =IF(((1+Drivers!Y32)*Operating!AS43)<0,((1+Drivers!Y32)*AVERAGE(Operating!AS43,Operating!AN43,Operating!AI43,Operating!AD43,Operating!Y43)),((1+Drivers!Y32)*Operating!AS43)) -> 3175.0438 | Z16: =IF(((1+Drivers!Z32)*Operating!AT43)<0,((1+Drivers!Z32)*AVERAGE(Operating!AT43,Operating!AO43,Operating!AJ43,Operating!AE43,Operating!Z43)),((1+Drivers!Z32)*Operating!AT43)) -> 5352.9245 | AA16: =SUM(W16:Z16) -> 12935.769 | AB16: =IF(((1+Drivers!AB32)*Operating!AV43)<0,((1+Drivers!AB32)*AVERAGE(Operating!AV43,Operating!AQ43,Operating!AL43,Operating!AG43,Operating!AB43)),((1+Drivers!AB32)*Operating!AV43)) -> 3070.6859
C18: Base Q growth in EMEA memberships | G18: # | H18: =IF(((1+Drivers!H24)*Operating!AB22)<0,((1+Drivers!H24)*AVERAGE(Operating!AB22,Operating!W22,Operating!R22,Operating!M22,Operating!H22)),((1+Drivers!H24)*Operating!AB22)) -> 772.8 | I18: =IF(((1+Drivers!I24)*Operating!AC22)<0,((1+Drivers!I24)*AVERAGE(Operating!AC22,Operating!X22,Operating!S22,Operating!N22,Operating!I22)),((1+Drivers!I24)*Operating!AC22)) -> 2677.4 | J18: =IF(((1+Drivers!J24)*Operating!AD22)<0,((1+Drivers!J24)*AVERAGE(Operating!AD22,Operating!Y22,Operating!T22,Operating!O22,Operating!J22)),((1+Drivers!J24)*Operating!AD22)) -> 4506.42 | K18: =IF(((1+Drivers!K24)*Operating!AE22)<0,((1+Drivers!K24)*AVERAGE(Operating!AE22,Operating!Z22,Operating!U22,Operating!P22,Operating!K22)),((1+Drivers!K24)*Operating!AE22)) -> 5962.54 | L18: =SUM(H18:K18) -> 13919.16 | M18: =IF(((1+Drivers!M24)*Operating!AG22)<0,((1+Drivers!M24)*AVERAGE(Operating!AG22,Operating!AB22,Operating!W22,Operating!R22,Operating!M22)),((1+Drivers!M24)*Operating!AG22)) -> 926.3296 | N18: =IF(((1+Drivers!N24)*Operating!AH22)<0,((1+Drivers!N24)*AVERAGE(Operating!AH22,Operating!AC22,Operating!X22,Operating!S22,Operating!N22)),((1+Drivers!N24)*Operating!AH22)) -> 2971.4272 | O18: =IF(((1+Drivers!O24)*Operating!AI22)<0,((1+Drivers!O24)*AVERAGE(Operating!AI22,Operating!AD22,Operating!Y22,Operating!T22,Operating!O22)),((1+Drivers!O24)*Operating!AI22)) -> 5124.9854 | P18: =IF(((1+Drivers!P24)*Operating!AJ22)<0,((1+Drivers!P24)*AVERAGE(Operating!AJ22,Operating!AE22,Operating!Z22,Operating!U22,Operating!P22)),((1+Drivers!P24)*Operating!AJ22)) -> 7004.6707 | Q18: =SUM(M18:P18) -> 16027.413 | R18: =IF(((1+Drivers!R24)*Operating!AL22)<0,((1+Drivers!R24)*AVERAGE(Operating!AL22,Operating!AG22,Operating!AB22,Operating!W22,Operating!R22)),((1+Drivers!R24)*Operating!AL22)) -> 1094.7299 | S18: =IF(((1+Drivers!S24)*Operating!AM22)<0,((1+Drivers!S24)*AVERAGE(Operating!AM22,Operating!AH22,Operating!AC22,Operating!X22,Operating!S22)),((1+Drivers!S24)*Operating!AM22)) -> 3315.1314 | T18: =IF(((1+Drivers!T24)*Operating!AN22)<0,((1+Drivers!T24)*AVERAGE(Operating!AN22,Operating!AI22,Operating!AD22,Operating!Y22,Operating!T22)),((1+Drivers!T24)*Operating!AN22)) -> 5860.9518 | U18: =IF(((1+Drivers!U24)*Operating!AO22)<0,((1+Drivers!U24)*AVERAGE(Operating!AO22,Operating!AJ22,Operating!AE22,Operating!Z22,Operating!U22)),((1+Drivers!U24)*Operating!AO22)) -> 8230.611 | V18: =SUM(R18:U18) -> 18501.424 | W18: =IF(((1+Drivers!W24)*Operating!AQ22)<0,((1+Drivers!W24)*AVERAGE(Operating!AQ22,Operating!AL22,Operating!AG22,Operating!AB22,Operating!W22)),((1+Drivers!W24)*Operating!AQ22)) -> 1249.3605 | X18: =IF(((1+Drivers!X24)*Operating!AR22)<0,((1+Drivers!X24)*AVERAGE(Operating!AR22,Operating!AM22,Operating!AH22,Operating!AC22,Operating!X22)),((1+Drivers!X24)*Operating!AR22)) -> 3639.1548 | Y18: =IF(((1+Drivers!Y24)*Operating!AS22)<0,((1+Drivers!Y24)*AVERAGE(Operating!AS22,Operating!AN22,Operating!AI22,Operating!AD22,Operating!Y22)),((1+Drivers!Y24)*Operating!AS22)) -> 6591.7059 | Z18: =IF(((1+Drivers!Z24)*Operating!AT22)<0,((1+Drivers!Z24)*AVERAGE(Operating!AT22,Operating!AO22,Operating!AJ22,Operating!AE22,Operating!Z22)),((1+Drivers!Z24)*Operating!AT22)) -> 9393.1848 | AA18: =SUM(W18:Z18) -> 20873.406 | AB18: =IF(((1+Drivers!AB24)*Operating!AV22)<0,((1+Drivers!AB24)*AVERAGE(Operating!AV22,Operating!AQ22,Operating!AL22,Operating!AG22,Operating!AB22)),((1+Drivers!AB24)*Operating!AV22)) -> 1389.658
C19: Base Q growth in UCAN memberships | G19: # | H19: =IF(((1+Drivers!H25)*Operating!AB29)<0,((1+Drivers!H25)*AVERAGE(Operating!AB29,Operating!W29,Operating!R29,Operating!M29,Operating!H29)),((1+Drivers!H25)*Operating!AB29)) -> 122.4 | I19: =IF(((1+Drivers!I25)*Operating!AC29)<0,((1+Drivers!I25)*AVERAGE(Operating!AC29,Operating!X29,Operating!S29,Operating!N29,Operating!I29)),((1+Drivers!I25)*Operating!AC29)) -> 1278.57 | J19: =IF(((1+Drivers!J25)*Operating!AD29)<0,((1+Drivers!J25)*AVERAGE(Operating!AD29,Operating!Y29,Operating!T29,Operating!O29,Operating!J29)),((1+Drivers!J25)*Operating!AD29)) -> 1872.5 | K19: =IF(((1+Drivers!K25)*Operating!AE29)<0,((1+Drivers!K25)*AVERAGE(Operating!AE29,Operating!Z29,Operating!U29,Operating!P29,Operating!K29)),((1+Drivers!K25)*Operating!AE29)) -> 3199.98 | L19: =SUM(H19:K19) -> 6473.45 | M19: =IF(((1+Drivers!M25)*Operating!AG29)<0,((1+Drivers!M25)*AVERAGE(Operating!AG29,Operating!AB29,Operating!W29,Operating!R29,Operating!M29)),((1+Drivers!M25)*Operating!AG29)) -> 142.9224 | N19: =IF(((1+Drivers!N25)*Operating!AH29)<0,((1+Drivers!N25)*AVERAGE(Operating!AH29,Operating!AC29,Operating!X29,Operating!S29,Operating!N29)),((1+Drivers!N25)*Operating!AH29)) -> 1403.6587 | O19: =IF(((1+Drivers!O25)*Operating!AI29)<0,((1+Drivers!O25)*AVERAGE(Operating!AI29,Operating!AD29,Operating!Y29,Operating!T29,Operating!O29)),((1+Drivers!O25)*Operating!AI29)) -> 2067.73 | P19: =IF(((1+Drivers!P25)*Operating!AJ29)<0,((1+Drivers!P25)*AVERAGE(Operating!AJ29,Operating!AE29,Operating!Z29,Operating!U29,Operating!P29)),((1+Drivers!P25)*Operating!AJ29)) -> 3672.0051 | Q19: =SUM(M19:P19) -> 7286.3162 | R19: =IF(((1+Drivers!R25)*Operating!AL29)<0,((1+Drivers!R25)*AVERAGE(Operating!AL29,Operating!AG29,Operating!AB29,Operating!W29,Operating!R29)),((1+Drivers!R25)*Operating!AL29)) -> 165.35363 | S19: =IF(((1+Drivers!S25)*Operating!AM29)<0,((1+Drivers!S25)*AVERAGE(Operating!AM29,Operating!AH29,Operating!AC29,Operating!X29,Operating!S29)),((1+Drivers!S25)*Operating!AM29)) -> 1551.9787 | T19: =IF(((1+Drivers!T25)*Operating!AN29)<0,((1+Drivers!T25)*AVERAGE(Operating!AN29,Operating!AI29,Operating!AD29,Operating!Y29,Operating!T29)),((1+Drivers!T25)*Operating!AN29)) -> 2294.6776 | U19: =IF(((1+Drivers!U25)*Operating!AO29)<0,((1+Drivers!U25)*AVERAGE(Operating!AO29,Operating!AJ29,Operating!AE29,Operating!Z29,Operating!U29)),((1+Drivers!U25)*Operating!AO29)) -> 4233.953 | V19: =SUM(R19:U19) -> 8245.9629 | W19: =IF(((1+Drivers!W25)*Operating!AQ29)<0,((1+Drivers!W25)*AVERAGE(Operating!AQ29,Operating!AL29,Operating!AG29,Operating!AB29,Operating!W29)),((1+Drivers!W25)*Operating!AQ29)) -> 185.07581 | X19: =IF(((1+Drivers!X25)*Operating!AR29)<0,((1+Drivers!X25)*AVERAGE(Operating!AR29,Operating!AM29,Operating!AH29,Operating!AC29,Operating!X29)),((1+Drivers!X25)*Operating!AR29)) -> 1704.0726 | Y19: =IF(((1+Drivers!Y25)*Operating!AS29)<0,((1+Drivers!Y25)*AVERAGE(Operating!AS29,Operating!AN29,Operating!AI29,Operating!AD29,Operating!Y29)),((1+Drivers!Y25)*Operating!AS29)) -> 2519.556 | Z19: =IF(((1+Drivers!Z25)*Operating!AT29)<0,((1+Drivers!Z25)*AVERAGE(Operating!AT29,Operating!AO29,Operating!AJ29,Operating!AE29,Operating!Z29)),((1+Drivers!Z25)*Operating!AT29)) -> 4738.9482 | AA19: =SUM(W19:Z19) -> 9147.6525 | AB19: =IF(((1+Drivers!AB25)*Operating!AV29)<0,((1+Drivers!AB25)*AVERAGE(Operating!AV29,Operating!AQ29,Operating!AL29,Operating!AG29,Operating!AB29)),((1+Drivers!AB25)*Operating!AV29)) -> 203.00931
C20: Base Q growth in LATAM memberships | G20: # | H20: =IF(((1+Drivers!H26)*Operating!AB36)<0,((1+Drivers!H26)*AVERAGE(Operating!AB36,Operating!W36,Operating!R36,Operating!M36,Operating!H36)),((1+Drivers!H26)*Operating!AB36)) -> 942.48 | I20: =IF(((1+Drivers!I26)*Operating!AC36)<0,((1+Drivers!I26)*AVERAGE(Operating!AC36,Operating!X36,Operating!S36,Operating!N36,Operating!I36)),((1+Drivers!I26)*Operating!AC36)) -> 1338.7 | J20: =IF(((1+Drivers!J26)*Operating!AD36)<0,((1+Drivers!J26)*AVERAGE(Operating!AD36,Operating!Y36,Operating!T36,Operating!O36,Operating!J36)),((1+Drivers!J26)*Operating!AD36)) -> 1261.53 | K20: =IF(((1+Drivers!K26)*Operating!AE36)<0,((1+Drivers!K26)*AVERAGE(Operating!AE36,Operating!Z36,Operating!U36,Operating!P36,Operating!K36)),((1+Drivers!K26)*Operating!AE36)) -> 2657.76 | L20: =SUM(H20:K20) -> 6200.47 | M20: =IF(((1+Drivers!M26)*Operating!AG36)<0,((1+Drivers!M26)*AVERAGE(Operating!AG36,Operating!AB36,Operating!W36,Operating!R36,Operating!M36)),((1+Drivers!M26)*Operating!AG36)) -> 1081.0246 | N20: =IF(((1+Drivers!N26)*Operating!AH36)<0,((1+Drivers!N26)*AVERAGE(Operating!AH36,Operating!AC36,Operating!X36,Operating!S36,Operating!N36)),((1+Drivers!N26)*Operating!AH36)) -> 1485.7136 | O20: =IF(((1+Drivers!O26)*Operating!AI36)<0,((1+Drivers!O26)*AVERAGE(Operating!AI36,Operating!AD36,Operating!Y36,Operating!T36,Operating!O36)),((1+Drivers!O26)*Operating!AI36)) -> 1354.7182 | P20: =IF(((1+Drivers!P26)*Operating!AJ36)<0,((1+Drivers!P26)*AVERAGE(Operating!AJ36,Operating!AE36,Operating!Z36,Operating!U36,Operating!P36)),((1+Drivers!P26)*Operating!AJ36)) -> 2963.6141 | Q20: =SUM(M20:P20) -> 6885.0704 | R20: =IF(((1+Drivers!R26)*Operating!AL36)<0,((1+Drivers!R26)*AVERAGE(Operating!AL36,Operating!AG36,Operating!AB36,Operating!W36,Operating!R36)),((1+Drivers!R26)*Operating!AL36)) -> 1196.8159 | S20: =IF(((1+Drivers!S26)*Operating!AM36)<0,((1+Drivers!S26)*AVERAGE(Operating!AM36,Operating!AH36,Operating!AC36,Operating!X36,Operating!S36)),((1+Drivers!S26)*Operating!AM36)) -> 1650.9413 | T20: =IF(((1+Drivers!T26)*Operating!AN36)<0,((1+Drivers!T26)*AVERAGE(Operating!AN36,Operating!AI36,Operating!AD36,Operating!Y36,Operating!T36)),((1+Drivers!T26)*Operating!AN36)) -> 1450.6348 | U20: =IF(((1+Drivers!U26)*Operating!AO36)<0,((1+Drivers!U26)*AVERAGE(Operating!AO36,Operating!AJ36,Operating!AE36,Operating!Z36,Operating!U36)),((1+Drivers!U26)*Operating!AO36)) -> 3293.2006 | V20: =SUM(R20:U20) -> 7591.5926 | W20: =IF(((1+Drivers!W26)*Operating!AQ36)<0,((1+Drivers!W26)*AVERAGE(Operating!AQ36,Operating!AL36,Operating!AG36,Operating!AB36,Operating!W36)),((1+Drivers!W26)*Operating!AQ36)) -> 1293.5231 | X20: =IF(((1+Drivers!X26)*Operating!AR36)<0,((1+Drivers!X26)*AVERAGE(Operating!AR36,Operating!AM36,Operating!AH36,Operating!AC36,Operating!X36)),((1+Drivers!X26)*Operating!AR36)) -> 1805.7629 | Y20: =IF(((1+Drivers!Y26)*Operating!AS36)<0,((1+Drivers!Y26)*AVERAGE(Operating!AS36,Operating!AN36,Operating!AI36,Operating!AD36,Operating!Y36)),((1+Drivers!Y26)*Operating!AS36)) -> 1559.6396 | Z20: =IF(((1+Drivers!Z26)*Operating!AT36)<0,((1+Drivers!Z26)*AVERAGE(Operating!AT36,Operating!AO36,Operating!AJ36,Operating!AE36,Operating!Z36)),((1+Drivers!Z26)*Operating!AT36)) -> 3568.3658 | AA20: =SUM(W20:Z20) -> 8227.2914 | AB20: =IF(((1+Drivers!AB26)*Operating!AV36)<0,((1+Drivers!AB26)*AVERAGE(Operating!AV36,Operating!AQ36,Operating!AL36,Operating!AG36,Operating!AB36)),((1+Drivers!AB26)*Operating!AV36)) -> 1387.9823
C21: Base Q growth in APAC memberships | G21: # | H21: =IF(((1+Drivers!H27)*Operating!AB43)<0,((1+Drivers!H27)*AVERAGE(Operating!AB43,Operating!W43,Operating!R43,Operating!M43,Operating!H43)),((1+Drivers!H27)*Operating!AB43)) -> 1746 | I21: =IF(((1+Drivers!I27)*Operating!AC43)<0,((1+Drivers!I27)*AVERAGE(Operating!AC43,Operating!X43,Operating!S43,Operating!N43,Operating!I43)),((1+Drivers!I27)*Operating!AC43)) -> 1196.16 | J21: =IF(((1+Drivers!J27)*Operating!AD43)<0,((1+Drivers!J27)*AVERAGE(Operating!AD43,Operating!Y43,Operating!T43,Operating!O43,Operating!J43)),((1+Drivers!J27)*Operating!AD43)) -> 2181.96 | K21: =IF(((1+Drivers!K27)*Operating!AE43)<0,((1+Drivers!K27)*AVERAGE(Operating!AE43,Operating!Z43,Operating!U43,Operating!P43,Operating!K43)),((1+Drivers!K27)*Operating!AE43)) -> 3434.98 | L21: =SUM(H21:K21) -> 8559.1 | M21: =IF(((1+Drivers!M27)*Operating!AG43)<0,((1+Drivers!M27)*AVERAGE(Operating!AG43,Operating!AB43,Operating!W43,Operating!R43,Operating!M43)),((1+Drivers!M27)*Operating!AG43)) -> 2092.872 | N21: =IF(((1+Drivers!N27)*Operating!AH43)<0,((1+Drivers!N27)*AVERAGE(Operating!AH43,Operating!AC43,Operating!X43,Operating!S43,Operating!N43)),((1+Drivers!N27)*Operating!AH43)) -> 1331.7533 | O21: =IF(((1+Drivers!O27)*Operating!AI43)<0,((1+Drivers!O27)*AVERAGE(Operating!AI43,Operating!AD43,Operating!Y43,Operating!T43,Operating!O43)),((1+Drivers!O27)*Operating!AI43)) -> 2488.7887 | P21: =IF(((1+Drivers!P27)*Operating!AJ43)<0,((1+Drivers!P27)*AVERAGE(Operating!AJ43,Operating!AE43,Operating!Z43,Operating!U43,Operating!P43)),((1+Drivers!P27)*Operating!AJ43)) -> 4035.3446 | Q21: =SUM(M21:P21) -> 9948.7586 | R21: =IF(((1+Drivers!R27)*Operating!AL43)<0,((1+Drivers!R27)*AVERAGE(Operating!AL43,Operating!AG43,Operating!AB43,Operating!W43,Operating!R43)),((1+Drivers!R27)*Operating!AL43)) -> 2441.0104 | S21: =IF(((1+Drivers!S27)*Operating!AM43)<0,((1+Drivers!S27)*AVERAGE(Operating!AM43,Operating!AH43,Operating!AC43,Operating!X43,Operating!S43)),((1+Drivers!S27)*Operating!AM43)) -> 1473.921 | T21: =IF(((1+Drivers!T27)*Operating!AN43)<0,((1+Drivers!T27)*AVERAGE(Operating!AN43,Operating!AI43,Operating!AD43,Operating!Y43,Operating!T43)),((1+Drivers!T27)*Operating!AN43)) -> 2819.0577 | U21: =IF(((1+Drivers!U27)*Operating!AO43)<0,((1+Drivers!U27)*AVERAGE(Operating!AO43,Operating!AJ43,Operating!AE43,Operating!Z43,Operating!U43)),((1+Drivers!U27)*Operating!AO43)) -> 4686.0971 | V21: =SUM(R21:U21) -> 11420.086 | W21: =IF(((1+Drivers!W27)*Operating!AQ43)<0,((1+Drivers!W27)*AVERAGE(Operating!AQ43,Operating!AL43,Operating!AG43,Operating!AB43,Operating!W43)),((1+Drivers!W27)*Operating!AQ43)) -> 2757.0341 | X21: =IF(((1+Drivers!X27)*Operating!AR43)<0,((1+Drivers!X27)*AVERAGE(Operating!AR43,Operating!AM43,Operating!AH43,Operating!AC43,Operating!X43)),((1+Drivers!X27)*Operating!AR43)) -> 1606.3009 | Y21: =IF(((1+Drivers!Y27)*Operating!AS43)<0,((1+Drivers!Y27)*AVERAGE(Operating!AS43,Operating!AN43,Operating!AI43,Operating!AD43,Operating!Y43)),((1+Drivers!Y27)*Operating!AS43)) -> 3142.6087 | Z21: =IF(((1+Drivers!Z27)*Operating!AT43)<0,((1+Drivers!Z27)*AVERAGE(Operating!AT43,Operating!AO43,Operating!AJ43,Operating!AE43,Operating!Z43)),((1+Drivers!Z27)*Operating!AT43)) -> 5292.7793 | AA21: =SUM(W21:Z21) -> 12798.723 | AB21: =IF(((1+Drivers!AB27)*Operating!AV43)<0,((1+Drivers!AB27)*AVERAGE(Operating!AV43,Operating!AQ43,Operating!AL43,Operating!AG43,Operating!AB43)),((1+Drivers!AB27)*Operating!AV43)) -> 3039.3168
C23: Expected % increase in memberships
C24: Base growth in EMEA memberships | G24: % | H24: =CHOOSE($H$10,H130,H206,H282) -> 0.2 | I24: =CHOOSE($H$10,I130,I206,I282) -> 0.1 | J24: =CHOOSE($H$10,J130,J206,J282) -> 0.14 | K24: =CHOOSE($H$10,K130,K206,K282) -> 0.18 | L24: =AVERAGE(H24:K24) -> 0.155 | M24: =CHOOSE($H$10,M130,M206,M282) -> 0.16 | N24: =CHOOSE($H$10,N130,N206,N282) -> 0.09 | O24: =CHOOSE($H$10,O130,O206,O282) -> 0.11 | P24: =CHOOSE($H$10,P130,P206,P282) -> 0.14 | Q24: =AVERAGE(M24:P24) -> 0.125 | R24: =CHOOSE($H$10,R130,R206,R282) -> 0.12 | S24: =CHOOSE($H$10,S130,S206,S282) -> 0.08 | T24: =CHOOSE($H$10,T130,T206,T282) -> 0.1 | U24: =CHOOSE($H$10,U130,U206,U282) -> 0.12 | V24: =AVERAGE(R24:U24) -> 0.105 | W24: =CHOOSE($H$10,W130,W206,W282) -> 0.1 | X24: =CHOOSE($H$10,X130,X206,X282) -> 0.07 | Y24: =CHOOSE($H$10,Y130,Y206,Y282) -> 0.09 | Z24: =CHOOSE($H$10,Z130,Z206,Z282) -> 0.1 | AA24: =AVERAGE(W24:Z24) -> 0.09 | AB24: =CHOOSE($H$10,AB130,AB206,AB282) -> 0.09
C25: Base growth in UCAN memberships | G25: % | H25: =CHOOSE($H$10,H131,H207,H283) -> 0.2 | I25: =CHOOSE($H$10,I131,I207,I283) -> 0.09 | J25: =CHOOSE($H$10,J131,J207,J283) -> 0.07 | K25: =CHOOSE($H$10,K131,K207,K283) -> 0.14 | L25: =AVERAGE(H25:K25) -> 0.125 | M25: =CHOOSE($H$10,M131,M207,M283) -> 0.13 | N25: =CHOOSE($H$10,N131,N207,N283) -> 0.08 | O25: =CHOOSE($H$10,O131,O207,O283) -> 0.09 | P25: =CHOOSE($H$10,P131,P207,P283) -> 0.12 | Q25: =AVERAGE(M25:P25) -> 0.105 | R25: =CHOOSE($H$10,R131,R207,R283) -> 0.1 | S25: =CHOOSE($H$10,S131,S207,S283) -> 0.07 | T25: =CHOOSE($H$10,T131,T207,T283) -> 0.07 | U25: =CHOOSE($H$10,U131,U207,U283) -> 0.1 | V25: =AVERAGE(R25:U25) -> 0.085 | W25: =CHOOSE($H$10,W131,W207,W283) -> 0.08 | X25: =CHOOSE($H$10,X131,X207,X283) -> 0.07 | Y25: =CHOOSE($H$10,Y131,Y207,Y283) -> 0.07 | Z25: =CHOOSE($H$10,Z131,Z207,Z283) -> 0.08 | AA25: =AVERAGE(W25:Z25) -> 0.075 | AB25: =CHOOSE($H$10,AB131,AB207,AB283) -> 0.075
C26: Base growth in LATAM memberships | G26: % | H26: =CHOOSE($H$10,H132,H208,H284) -> 0.2 | I26: =CHOOSE($H$10,I132,I208,I284) -> 0.1 | J26: =CHOOSE($H$10,J132,J208,J284) -> 0.07 | K26: =CHOOSE($H$10,K132,K208,K284) -> 0.13 | L26: =AVERAGE(H26:K26) -> 0.125 | M26: =CHOOSE($H$10,M132,M208,M284) -> 0.11 | N26: =CHOOSE($H$10,N132,N208,N284) -> 0.09 | O26: =CHOOSE($H$10,O132,O208,O284) -> 0.06 | P26: =CHOOSE($H$10,P132,P208,P284) -> 0.09 | Q26: =AVERAGE(M26:P26) -> 0.0875 | R26: =CHOOSE($H$10,R132,R208,R284) -> 0.07 | S26: =CHOOSE($H$10,S132,S208,S284) -> 0.08 | T26: =CHOOSE($H$10,T132,T208,T284) -> 0.05 | U26: =CHOOSE($H$10,U132,U208,U284) -> 0.08 | V26: =AVERAGE(R26:U26) -> 0.07 | W26: =CHOOSE($H$10,W132,W208,W284) -> 0.06 | X26: =CHOOSE($H$10,X132,X208,X284) -> 0.07 | Y26: =CHOOSE($H$10,Y132,Y208,Y284) -> 0.06 | Z26: =CHOOSE($H$10,Z132,Z208,Z284) -> 0.06 | AA26: =AVERAGE(W26:Z26) -> 0.0625 | AB26: =CHOOSE($H$10,AB132,AB208,AB284) -> 0.0625
C27: Base growth in APAC memberships | G27: % | H27: =CHOOSE($H$10,H133,H209,H285) -> 0.2 | I27: =CHOOSE($H$10,I133,I209,I285) -> 0.12 | J27: =CHOOSE($H$10,J133,J209,J285) -> 0.16 | K27: =CHOOSE($H$10,K133,K209,K285) -> 0.18 | L27: =AVERAGE(H27:K27) -> 0.165 | M27: =CHOOSE($H$10,M133,M209,M285) -> 0.16 | N27: =CHOOSE($H$10,N133,N209,N285) -> 0.09 | O27: =CHOOSE($H$10,O133,O209,O285) -> 0.11 | P27: =CHOOSE($H$10,P133,P209,P285) -> 0.14 | Q27: =AVERAGE(M27:P27) -> 0.125 | R27: =CHOOSE($H$10,R133,R209,R285) -> 0.12 | S27: =CHOOSE($H$10,S133,S209,S285) -> 0.08 | T27: =CHOOSE($H$10,T133,T209,T285) -> 0.1 | U27: =CHOOSE($H$10,U133,U209,U285) -> 0.12 | V27: =AVERAGE(R27:U27) -> 0.105 | W27: =CHOOSE($H$10,W133,W209,W285) -> 0.1 | X27: =CHOOSE($H$10,X133,X209,X285) -> 0.07 | Y27: =CHOOSE($H$10,Y133,Y209,Y285) -> 0.09 | Z27: =CHOOSE($H$10,Z133,Z209,Z285) -> 0.1 | AA27: =AVERAGE(W27:Z27) -> 0.09 | AB27: =CHOOSE($H$10,AB133,AB209,AB285) -> 0.09
AB28: 4
C29: YoY growth in EMEA memberships | G29: % | H29: =H24*(1+H34) -> 0.24 | I29: =I24*(1+I34) -> 0.12 | J29: =J24*(1+J34) -> 0.168 | K29: =K24*(1+K34) -> 0.216 | L29: =AVERAGE(H29:K29) -> 0.186 | M29: =M24*(1+M34) -> 0.224 | N29: =N24*(1+N34) -> 0.126 | O29: =O24*(1+O34) -> 0.154 | P29: =P24*(1+P34) -> 0.196 | Q29: =AVERAGE(M29:P29) -> 0.175 | R29: =R24*(1+R34) -> 0.162 | S29: =S24*(1+S34) -> 0.108 | T29: =T24*(1+T34) -> 0.135 | U29: =U24*(1+U34) -> 0.162 | V29: =AVERAGE(R29:U29) -> 0.14175 | W29: =W24*(1+W34) -> 0.1225 | X29: =X24*(1+X34) -> 0.08575 | Y29: =Y24*(1+Y34) -> 0.11025 | Z29: =Z24*(1+Z34) -> 0.1225 | AA29: =AVERAGE(W29:Z29) -> 0.11025 | AB29: =AB24*(1+AB34) -> 0.11025
C30: YoY growth in UCAN memberships | G30: % | H30: =H25*(1+H35) -> 0.24 | I30: =I25*(1+I35) -> 0.108 | J30: =J25*(1+J35) -> 0.084 | K30: =K25*(1+K35) -> 0.168 | L30: =AVERAGE(H30:K30) -> 0.15 | M30: =M25*(1+M35) -> 0.1885 | N30: =N25*(1+N35) -> 0.116 | O30: =O25*(1+O35) -> 0.1305 | P30: =P25*(1+P35) -> 0.174 | Q30: =AVERAGE(M30:P30) -> 0.15225 | R30: =R25*(1+R35) -> 0.14 | S30: =S25*(1+S35) -> 0.098 | T30: =T25*(1+T35) -> 0.098 | U30: =U25*(1+U35) -> 0.14 | V30: =AVERAGE(R30:U30) -> 0.119 | W30: =W25*(1+W35) -> 0.102 | X30: =X25*(1+X35) -> 0.08925 | Y30: =Y25*(1+Y35) -> 0.08925 | Z30: =Z25*(1+Z35) -> 0.102 | AA30: =AVERAGE(W30:Z30) -> 0.095625 | AB30: =AB25*(1+AB35) -> 0.095625
C31: YoY growth in LATAM memberships | G31: % | H31: =H26*(1+H36) -> 0.24 | I31: =I26*(1+I36) -> 0.12 | J31: =J26*(1+J36) -> 0.084 | K31: =K26*(1+K36) -> 0.156 | L31: =AVERAGE(H31:K31) -> 0.15 | M31: =M26*(1+M36) -> 0.1485 | N31: =N26*(1+N36) -> 0.1215 | O31: =O26*(1+O36) -> 0.081 | P31: =P26*(1+P36) -> 0.1215 | Q31: =AVERAGE(M31:P31) -> 0.118125 | R31: =R26*(1+R36) -> 0.091 | S31: =S26*(1+S36) -> 0.104 | T31: =T26*(1+T36) -> 0.065 | U31: =U26*(1+U36) -> 0.104 | V31: =AVERAGE(R31:U31) -> 0.091 | W31: =W26*(1+W36) -> 0.0705 | X31: =X26*(1+X36) -> 0.08225 | Y31: =Y26*(1+Y36) -> 0.0705 | Z31: =Z26*(1+Z36) -> 0.0705 | AA31: =AVERAGE(W31:Z31) -> 0.0734375 | AB31: =AB26*(1+AB36) -> 0.0734375
C32: YoY growth in APAC memberships | G32: % | H32: =H27*(1+H37) -> 0.24 | I32: =I27*(1+I37) -> 0.144 | J32: =J27*(1+J37) -> 0.192 | K32: =K27*(1+K37) -> 0.216 | L32: =AVERAGE(H32:K32) -> 0.198 | M32: =M27*(1+M37) -> 0.208 | N32: =N27*(1+N37) -> 0.117 | O32: =O27*(1+O37) -> 0.143 | P32: =P27*(1+P37) -> 0.182 | Q32: =AVERAGE(M32:P32) -> 0.1625 | R32: =R27*(1+R37) -> 0.15 | S32: =S27*(1+S37) -> 0.1 | T32: =T27*(1+T37) -> 0.125 | U32: =U27*(1+U37) -> 0.15 | V32: =AVERAGE(R32:U32) -> 0.13125 | W32: =W27*(1+W37) -> 0.1125 | X32: =X27*(1+X37) -> 0.07875 | Y32: =Y27*(1+Y37) -> 0.10125 | Z32: =Z27*(1+Z37) -> 0.1125 | AA32: =AVERAGE(W32:Z32) -> 0.10125 | AB32: =AB27*(1+AB37) -> 0.10125
C34: EMEA growth from bolt-on expansions | G34: % | H34: =H89+H107 -> 0.2 | I34: =I89+I107 -> 0.2 | J34: =J89+J107 -> 0.2 | K34: =K89+K107 -> 0.2 | L34: =AVERAGE(H34:K34) -> 0.2 | M34: =M89+M107 -> 0.4 | N34: =N89+N107 -> 0.4 | O34: =O89+O107 -> 0.4 | P34: =P89+P107 -> 0.4 | Q34: =AVERAGE(M34:P34) -> 0.4 | R34: =R89+R107 -> 0.35 | S34: =S89+S107 -> 0.35 | T34: =T89+T107 -> 0.35 | U34: =U89+U107 -> 0.35 | V34: =AVERAGE(R34:U34) -> 0.35 | W34: =W89+W107 -> 0.225 | X34: =X89+X107 -> 0.225 | Y34: =Y89+Y107 -> 0.225 | Z34: =Z89+Z107 -> 0.225 | AA34: =AVERAGE(W34:Z34) -> 0.225 | AB34: =AB89+AB107 -> 0.225
C35: UCAN growth from bolt-on expansions | G35: % | H35: =H90+H108 -> 0.2 | I35: =I90+I108 -> 0.2 | J35: =J90+J108 -> 0.2 | K35: =K90+K108 -> 0.2 | L35: =AVERAGE(H35:K35) -> 0.2 | M35: =M90+M108 -> 0.45 | N35: =N90+N108 -> 0.45 | O35: =O90+O108 -> 0.45 | P35: =P90+P108 -> 0.45 | Q35: =AVERAGE(M35:P35) -> 0.45 | R35: =R90+R108 -> 0.4 | S35: =S90+S108 -> 0.4 | T35: =T90+T108 -> 0.4 | U35: =U90+U108 -> 0.4 | V35: =AVERAGE(R35:U35) -> 0.4 | W35: =W90+W108 -> 0.275 | X35: =X90+X108 -> 0.275 | Y35: =Y90+Y108 -> 0.275 | Z35: =Z90+Z108 -> 0.275 | AA35: =AVERAGE(W35:Z35) -> 0.275 | AB35: =AB90+AB108 -> 0.275
C36: LATAM growth from bolt-on expansions | G36: % | H36: =H91+H109 -> 0.2 | I36: =I91+I109 -> 0.2 | J36: =J91+J109 -> 0.2 | K36: =K91+K109 -> 0.2 | L36: =AVERAGE(H36:K36) -> 0.2 | M36: =M91+M109 -> 0.35 | N36: =N91+N109 -> 0.35 | O36: =O91+O109 -> 0.35 | P36: =P91+P109 -> 0.35 | Q36: =AVERAGE(M36:P36) -> 0.35 | R36: =R91+R109 -> 0.3 | S36: =S91+S109 -> 0.3 | T36: =T91+T109 -> 0.3 | U36: =U91+U109 -> 0.3 | V36: =AVERAGE(R36:U36) -> 0.3 | W36: =W91+W109 -> 0.175 | X36: =X91+X109 -> 0.175 | Y36: =Y91+Y109 -> 0.175 | Z36: =Z91+Z109 -> 0.175 | AA36: =AVERAGE(W36:Z36) -> 0.175 | AB36: =AB91+AB109 -> 0.175
C37: APAC growth from bolt-on expansions | G37: % | H37: =H92+H110 -> 0.2 | I37: =I92+I110 -> 0.2 | J37: =J92+J110 -> 0.2 | K37: =K92+K110 -> 0.2 | L37: =AVERAGE(H37:K37) -> 0.2 | M37: =M92+M110 -> 0.3 | N37: =N92+N110 -> 0.3 | O37: =O92+O110 -> 0.3 | P37: =P92+P110 -> 0.3 | Q37: =AVERAGE(M37:P37) -> 0.3 | R37: =R92+R110 -> 0.25 | S37: =S92+S110 -> 0.25 | T37: =T92+T110 -> 0.25 | U37: =U92+U110 -> 0.25 | V37: =AVERAGE(R37:U37) -> 0.25 | W37: =W92+W110 -> 0.125 | X37: =X92+X110 -> 0.125 | Y37: =Y92+Y110 -> 0.125 | Z37: =Z92+Z110 -> 0.125 | AA37: =AVERAGE(W37:Z37) -> 0.125 | AB37: =AB92+AB110 -> 0.125
C39: Derived monthly revenue per paying membership
C40: EMEA | G40: US$ | H40: {=AVERAGE(Operating!AB25:AE25*(1+H50))} -> 11.239447 | I40: {=AVERAGE(Operating!AC25:AF25*(1+I50))} -> 11.234924 | J40: {=AVERAGE(Operating!AD25:AG25*(1+J50))} -> 11.330403 | K40: {=AVERAGE(Operating!AE25:AH25*(1+K50))} -> 11.396285 | L40: =AVERAGE(H40:K40) -> 11.300265 | M40: {=AVERAGE(Operating!AG25:AJ25*(1+M50))} -> 11.698599 | N40: {=AVERAGE(Operating!AH25:AK25*(1+N50))} -> 11.71434 | O40: {=AVERAGE(Operating!AI25:AL25*(1+O50))} -> 11.834345 | P40: {=AVERAGE(Operating!AJ25:AM25*(1+P50))} -> 11.933712 | Q40: =AVERAGE(M40:P40) -> 11.795249 | R40: {=AVERAGE(Operating!AL25:AO25*(1+R50))} -> 12.202185 | S40: {=AVERAGE(Operating!AM25:AP25*(1+S50))} -> 12.227181 | T40: {=AVERAGE(Operating!AN25:AQ25*(1+T50))} -> 12.35335 | U40: {=AVERAGE(Operating!AO25:AR25*(1+U50))} -> 12.454947 | V40: =AVERAGE(R40:U40) -> 12.309416 | W40: {=AVERAGE(Operating!AQ25:AT25*(1+W50))} -> 12.711934 | X40: {=AVERAGE(Operating!AR25:AU25*(1+X50))} -> 12.739618 | Y40: {=AVERAGE(Operating!AS25:AV25*(1+Y50))} -> 12.864769 | Z40: {=AVERAGE(Operating!AT25:AW25*(1+Z50))} -> 12.964494 | AA40: =AVERAGE(W40:Z40) -> 12.820204 | AB40: {=AVERAGE(Operating!AV25:AY25*(1+AB50))} -> 13.239424
C41: UCAN | G41: US$ | H41: {=AVERAGE(Operating!AB32:AE32*(1+H51))} -> 16.918427 | I41: {=AVERAGE(Operating!AC32:AF32*(1+I51))} -> 16.943761 | J41: {=AVERAGE(Operating!AD32:AG32*(1+J51))} -> 17.182409 | K41: {=AVERAGE(Operating!AE32:AH32*(1+K51))} -> 17.352285 | L41: =AVERAGE(H41:K41) -> 17.09922 | M41: {=AVERAGE(Operating!AG32:AJ32*(1+M51))} -> 17.817388 | N41: {=AVERAGE(Operating!AH32:AK32*(1+N51))} -> 17.864484 | O41: {=AVERAGE(Operating!AI32:AL32*(1+O51))} -> 18.092064 | P41: {=AVERAGE(Operating!AJ32:AM32*(1+P51))} -> 18.269745 | Q41: =AVERAGE(M41:P41) -> 18.01092 | R41: {=AVERAGE(Operating!AL32:AO32*(1+R51))} -> 18.751619 | S41: {=AVERAGE(Operating!AM32:AP32*(1+S51))} -> 18.801992 | T41: {=AVERAGE(Operating!AN32:AQ32*(1+T51))} -> 19.032897 | U41: {=AVERAGE(Operating!AO32:AR32*(1+U51))} -> 19.217678 | V41: =AVERAGE(R41:U41) -> 18.951046 | W41: {=AVERAGE(Operating!AQ32:AT32*(1+W51))} -> 19.687295 | X41: {=AVERAGE(Operating!AR32:AU32*(1+X51))} -> 19.739088 | Y41: {=AVERAGE(Operating!AS32:AV32*(1+Y51))} -> 19.969012 | Z41: {=AVERAGE(Operating!AT32:AW32*(1+Z51))} -> 20.152419 | AA41: =AVERAGE(W41:Z41) -> 19.886954 | AB41: {=AVERAGE(Operating!AV32:AY32*(1+AB51))} -> 20.659562
C42: LATAM | G42: US$ | H42: {=AVERAGE(Operating!AB39:AE39*(1+Drivers!$H$52))} -> 8.8955813 | I42: {=AVERAGE(Operating!AC39:AF39*(1+Drivers!$H$52))} -> 8.9103516 | J42: {=AVERAGE(Operating!AD39:AG39*(1+Drivers!$H$52))} -> 8.9914165 | K42: {=AVERAGE(Operating!AE39:AH39*(1+Drivers!$H$52))} -> 9.0069193 | L42: =AVERAGE(H42:K42) -> 8.9510672 | M42: {=AVERAGE(Operating!AG39:AJ39*(1+Drivers!$H$52))} -> 9.1972215 | N42: {=AVERAGE(Operating!AH39:AK39*(1+Drivers!$H$52))} -> 9.2114744 | O42: {=AVERAGE(Operating!AI39:AL39*(1+Drivers!$H$52))} -> 9.2851642 | P42: {=AVERAGE(Operating!AJ39:AM39*(1+Drivers!$H$52))} -> 9.3416915 | Q42: =AVERAGE(M42:P42) -> 9.2588879 | R42: {=AVERAGE(Operating!AL39:AO39*(1+Drivers!$H$52))} -> 9.5135073 | S42: {=AVERAGE(Operating!AM39:AP39*(1+Drivers!$H$52))} -> 9.5293479 | T42: {=AVERAGE(Operating!AN39:AQ39*(1+Drivers!$H$52))} -> 9.6069326 | U42: {=AVERAGE(Operating!AO39:AR39*(1+Drivers!$H$52))} -> 9.6696573 | V42: =AVERAGE(R42:U42) -> 9.5798613 | W42: {=AVERAGE(Operating!AQ39:AT39*(1+Drivers!$H$52))} -> 9.8433075 | X42: {=AVERAGE(Operating!AR39:AU39*(1+Drivers!$H$52))} -> 9.8603521 | Y42: {=AVERAGE(Operating!AS39:AV39*(1+Drivers!$H$52))} -> 9.9410005 | Z42: {=AVERAGE(Operating!AT39:AW39*(1+Drivers!$H$52))} -> 10.006098 | AA42: =AVERAGE(W42:Z42) -> 9.9126894 | AB42: {=AVERAGE(Operating!AV39:AY39*(1+Drivers!$H$52))} -> 10.185288
C43: APAC | G43: US$ | H43: {=AVERAGE(Operating!AB46:AE46*(1+Drivers!$H$53))} -> 7.8655125 | I43: {=AVERAGE(Operating!AC46:AF46*(1+Drivers!$H$53))} -> 7.7691844 | J43: {=AVERAGE(Operating!AD46:AG46*(1+Drivers!$H$53))} -> 7.8219754 | K43: {=AVERAGE(Operating!AE46:AH46*(1+Drivers!$H$53))} -> 7.8602971 | L43: =AVERAGE(H43:K43) -> 7.8292424 | M43: {=AVERAGE(Operating!AG46:AJ46*(1+Drivers!$H$53))} -> 8.0445465 | N43: {=AVERAGE(Operating!AH46:AK46*(1+Drivers!$H$53))} -> 8.0352296 | O43: {=AVERAGE(Operating!AI46:AL46*(1+Drivers!$H$53))} -> 8.1059633 | P43: {=AVERAGE(Operating!AJ46:AM46*(1+Drivers!$H$53))} -> 8.160743 | Q43: =AVERAGE(M43:P43) -> 8.0866206 | R43: {=AVERAGE(Operating!AL46:AO46*(1+Drivers!$H$53))} -> 8.3090027 | S43: {=AVERAGE(Operating!AM46:AP46*(1+Drivers!$H$53))} -> 8.3198104 | T43: {=AVERAGE(Operating!AN46:AQ46*(1+Drivers!$H$53))} -> 8.3901359 | U43: {=AVERAGE(Operating!AO46:AR46*(1+Drivers!$H$53))} -> 8.4450679 | V43: =AVERAGE(R43:U43) -> 8.3660042 | W43: {=AVERAGE(Operating!AQ46:AT46*(1+Drivers!$H$53))} -> 8.5960693 | X43: {=AVERAGE(Operating!AR46:AU46*(1+Drivers!$H$53))} -> 8.6107116 | Y43: {=AVERAGE(Operating!AS46:AV46*(1+Drivers!$H$53))} -> 8.6816756 | Z43: {=AVERAGE(Operating!AT46:AW46*(1+Drivers!$H$53))} -> 8.738336 | AA43: =AVERAGE(W43:Z43) -> 8.6566981 | AB43: {=AVERAGE(Operating!AV46:AY46*(1+Drivers!$H$53))} -> 8.8947573
C45: EMEA (base) | G45: US$ | H45: {=AVERAGE(Operating!AB25:AE25*(1+$H$56))} -> 11.198675 | I45: {=AVERAGE(Operating!AC25:AF25*(1+$H$56))} -> 11.194169 | J45: {=AVERAGE(Operating!AD25:AG25*(1+$H$56))} -> 11.289301 | K45: {=AVERAGE(Operating!AE25:AH25*(1+$H$56))} -> 11.354944 | L45: =AVERAGE(H45:K45) -> 11.259272 | M45: {=AVERAGE(Operating!AG25:AJ25*(1+$H$56))} -> 11.639273 | N45: {=AVERAGE(Operating!AH25:AK25*(1+$H$56))} -> 11.654933 | O45: {=AVERAGE(Operating!AI25:AL25*(1+$H$56))} -> 11.77433 | P45: {=AVERAGE(Operating!AJ25:AM25*(1+$H$56))} -> 11.873193 | Q45: =AVERAGE(M45:P45) -> 11.735432 | R45: {=AVERAGE(Operating!AL25:AO25*(1+$H$56))} -> 12.149106 | S45: {=AVERAGE(Operating!AM25:AP25*(1+$H$56))} -> 12.173994 | T45: {=AVERAGE(Operating!AN25:AQ25*(1+$H$56))} -> 12.299614 | U45: {=AVERAGE(Operating!AO25:AR25*(1+$H$56))} -> 12.400769 | V45: =AVERAGE(R45:U45) -> 12.255871 | W45: {=AVERAGE(Operating!AQ25:AT25*(1+$H$56))} -> 12.678698 | X45: {=AVERAGE(Operating!AR25:AU25*(1+$H$56))} -> 12.70631 | Y45: {=AVERAGE(Operating!AS25:AV25*(1+$H$56))} -> 12.831134 | Z45: {=AVERAGE(Operating!AT25:AW25*(1+$H$56))} -> 12.930598 | AA45: =AVERAGE(W45:Z45) -> 12.786685 | AB45: {=AVERAGE(Operating!AV25:AY25*(1+$H$56))} -> 13.20481
C46: UCAN (base) | G46: US$ | H46: {=AVERAGE(Operating!AB32:AE32*(1+$H$57))} -> 16.847212 | I46: {=AVERAGE(Operating!AC32:AF32*(1+$H$57))} -> 16.872441 | J46: {=AVERAGE(Operating!AD32:AG32*(1+$H$57))} -> 17.110083 | K46: {=AVERAGE(Operating!AE32:AH32*(1+$H$57))} -> 17.279244 | L46: =AVERAGE(H46:K46) -> 17.027245 | M46: {=AVERAGE(Operating!AG32:AJ32*(1+$H$57))} -> 17.697693 | N46: {=AVERAGE(Operating!AH32:AK32*(1+$H$57))} -> 17.744473 | O46: {=AVERAGE(Operating!AI32:AL32*(1+$H$57))} -> 17.970524 | P46: {=AVERAGE(Operating!AJ32:AM32*(1+$H$57))} -> 18.147011 | Q46: =AVERAGE(M46:P46) -> 17.889925 | R46: {=AVERAGE(Operating!AL32:AO32*(1+$H$57))} -> 18.641302 | S46: {=AVERAGE(Operating!AM32:AP32*(1+$H$57))} -> 18.691379 | T46: {=AVERAGE(Operating!AN32:AQ32*(1+$H$57))} -> 18.920925 | U46: {=AVERAGE(Operating!AO32:AR32*(1+$H$57))} -> 19.104619 | V46: =AVERAGE(R46:U46) -> 18.839556 | W46: {=AVERAGE(Operating!AQ32:AT32*(1+$H$57))} -> 19.614333 | X46: {=AVERAGE(Operating!AR32:AU32*(1+$H$57))} -> 19.665935 | Y46: {=AVERAGE(Operating!AS32:AV32*(1+$H$57))} -> 19.895007 | Z46: {=AVERAGE(Operating!AT32:AW32*(1+$H$57))} -> 20.077734 | AA46: =AVERAGE(W46:Z46) -> 19.813252 | AB46: {=AVERAGE(Operating!AV32:AY32*(1+$H$57))} -> 20.582997
C47: LATAM (base) | G47: US$ | H47: {=AVERAGE(Operating!AB39:AE39*(1+$H$58))} -> 8.8739375 | I47: {=AVERAGE(Operating!AC39:AF39*(1+$H$58))} -> 8.8886719 | J47: {=AVERAGE(Operating!AD39:AG39*(1+$H$58))} -> 8.9695396 | K47: {=AVERAGE(Operating!AE39:AH39*(1+$H$58))} -> 8.9850047 | L47: =AVERAGE(H47:K47) -> 8.9292884 | M47: {=AVERAGE(Operating!AG39:AJ39*(1+$H$58))} -> 9.1748438 | N47: {=AVERAGE(Operating!AH39:AK39*(1+$H$58))} -> 9.1890621 | O47: {=AVERAGE(Operating!AI39:AL39*(1+$H$58))} -> 9.2625725 | P47: {=AVERAGE(Operating!AJ39:AM39*(1+$H$58))} -> 9.3189624 | Q47: =AVERAGE(M47:P47) -> 9.2363602 | R47: {=AVERAGE(Operating!AL39:AO39*(1+$H$58))} -> 9.4903601 | S47: {=AVERAGE(Operating!AM39:AP39*(1+$H$58))} -> 9.5061621 | T47: {=AVERAGE(Operating!AN39:AQ39*(1+$H$58))} -> 9.5835581 | U47: {=AVERAGE(Operating!AO39:AR39*(1+$H$58))} -> 9.6461301 | V47: =AVERAGE(R47:U47) -> 9.5565526 | W47: {=AVERAGE(Operating!AQ39:AT39*(1+$H$58))} -> 9.8193578 | X47: {=AVERAGE(Operating!AR39:AU39*(1+$H$58))} -> 9.836361 | Y47: {=AVERAGE(Operating!AS39:AV39*(1+$H$58))} -> 9.9168131 | Z47: {=AVERAGE(Operating!AT39:AW39*(1+$H$58))} -> 9.9817519 | AA47: =AVERAGE(W47:Z47) -> 9.888571 | AB47: {=AVERAGE(Operating!AV39:AY39*(1+$H$58))} -> 10.160507
C48: APAC (base) | G48: US$ | H48: {=AVERAGE(Operating!AB46:AE46*(1+$H$59))} -> 7.846375 | I48: {=AVERAGE(Operating!AC46:AF46*(1+$H$59))} -> 7.7502812 | J48: {=AVERAGE(Operating!AD46:AG46*(1+$H$59))} -> 7.8029438 | K48: {=AVERAGE(Operating!AE46:AH46*(1+$H$59))} -> 7.8411723 | L48: =AVERAGE(H48:K48) -> 7.8101931 | M48: {=AVERAGE(Operating!AG46:AJ46*(1+$H$59))} -> 8.0249734 | N48: {=AVERAGE(Operating!AH46:AK46*(1+$H$59))} -> 8.0156792 | O48: {=AVERAGE(Operating!AI46:AL46*(1+$H$59))} -> 8.0862407 | P48: {=AVERAGE(Operating!AJ46:AM46*(1+$H$59))} -> 8.1408871 | Q48: =AVERAGE(M48:P48) -> 8.0669451 | R48: {=AVERAGE(Operating!AL46:AO46*(1+$H$59))} -> 8.2887861 | S48: {=AVERAGE(Operating!AM46:AP46*(1+$H$59))} -> 8.2995676 | T48: {=AVERAGE(Operating!AN46:AQ46*(1+$H$59))} -> 8.3697219 | U48: {=AVERAGE(Operating!AO46:AR46*(1+$H$59))} -> 8.4245203 | V48: =AVERAGE(R48:U48) -> 8.345649 | W48: {=AVERAGE(Operating!AQ46:AT46*(1+$H$59))} -> 8.5751543 | X48: {=AVERAGE(Operating!AR46:AU46*(1+$H$59))} -> 8.589761 | Y48: {=AVERAGE(Operating!AS46:AV46*(1+$H$59))} -> 8.6605523 | Z48: {=AVERAGE(Operating!AT46:AW46*(1+$H$59))} -> 8.7170748 | AA48: =AVERAGE(W48:Z48) -> 8.6356356 | AB48: {=AVERAGE(Operating!AV46:AY46*(1+$H$59))} -> 8.8731156
C50: Net growth in EMEA take rate | G50: % | H50: =$H56*(1+(H84+H102)) -> 0.03375 | I50: =$H56*(1+(I84+I102)) -> 0.03375 | J50: =$H56*(1+(J84+J102)) -> 0.03375 | K50: =$H56*(1+(K84+K102)) -> 0.03375 | L50: =AVERAGE(H50:K50) -> 0.03375 | M50: =$H56*(1+(M84+M102)) -> 0.03525 | N50: =$H56*(1+(N84+N102)) -> 0.03525 | O50: =$H56*(1+(O84+O102)) -> 0.03525 | P50: =$H56*(1+(P84+P102)) -> 0.03525 | Q50: =AVERAGE(M50:P50) -> 0.03525 | R50: =$H56*(1+(R84+R102)) -> 0.0345 | S50: =$H56*(1+(S84+S102)) -> 0.0345 | T50: =$H56*(1+(T84+T102)) -> 0.0345 | U50: =$H56*(1+(U84+U102)) -> 0.0345 | V50: =AVERAGE(R50:U50) -> 0.0345 | W50: =$H56*(1+(W84+W102)) -> 0.0327 | X50: =$H56*(1+(X84+X102)) -> 0.0327 | Y50: =$H56*(1+(Y84+Y102)) -> 0.0327 | Z50: =$H56*(1+(Z84+Z102)) -> 0.0327 | AA50: =AVERAGE(W50:Z50) -> 0.0327 | AB50: =$H56*(1+(AB84+AB102))*$AB$54 -> 0.0327
C51: Net growth on UCAN take rate | G51: % | H51: =$H57*(1+(H85+H103)) -> 0.039375 | I51: =$H57*(1+(I85+I103)) -> 0.039375 | J51: =$H57*(1+(J85+J103)) -> 0.039375 | K51: =$H57*(1+(K85+K103)) -> 0.039375 | L51: =AVERAGE(H51:K51) -> 0.039375 | M51: =$H57*(1+(M85+M103)) -> 0.042 | N51: =$H57*(1+(N85+N103)) -> 0.042 | O51: =$H57*(1+(O85+O103)) -> 0.042 | P51: =$H57*(1+(P85+P103)) -> 0.042 | Q51: =AVERAGE(M51:P51) -> 0.042 | R51: =$H57*(1+(R85+R103)) -> 0.041125 | S51: =$H57*(1+(S85+S103)) -> 0.041125 | T51: =$H57*(1+(T85+T103)) -> 0.041125 | U51: =$H57*(1+(U85+U103)) -> 0.041125 | V51: =AVERAGE(R51:U51) -> 0.041125 | W51: =$H57*(1+(W85+W103)) -> 0.03885 | X51: =$H57*(1+(X85+X103)) -> 0.03885 | Y51: =$H57*(1+(Y85+Y103)) -> 0.03885 | Z51: =$H57*(1+(Z85+Z103)) -> 0.03885 | AA51: =AVERAGE(W51:Z51) -> 0.03885 | AB51: =$H57*(1+(AB85+AB103))*$AB$54 -> 0.03885
C52: Net growth in LATAM take rate | G52: % | H52: =$H58*(1+(H86+H104)) -> 0.0275 | I52: =$H58*(1+(I86+I104)) -> 0.0275 | J52: =$H58*(1+(J86+J104)) -> 0.0275 | K52: =$H58*(1+(K86+K104)) -> 0.0275 | L52: =AVERAGE(H52:K52) -> 0.0275 | M52: =$H58*(1+(M86+M104)) -> 0.028125 | N52: =$H58*(1+(N86+N104)) -> 0.028125 | O52: =$H58*(1+(O86+O104)) -> 0.028125 | P52: =$H58*(1+(P86+P104)) -> 0.028125 | Q52: =AVERAGE(M52:P52) -> 0.028125 | R52: =$H58*(1+(R86+R104)) -> 0.0275 | S52: =$H58*(1+(S86+S104)) -> 0.0275 | T52: =$H58*(1+(T86+T104)) -> 0.0275 | U52: =$H58*(1+(U86+U104)) -> 0.0275 | V52: =AVERAGE(R52:U52) -> 0.0275 | W52: =$H58*(1+(W86+W104)) -> 0.026125 | X52: =$H58*(1+(X86+X104)) -> 0.026125 | Y52: =$H58*(1+(Y86+Y104)) -> 0.026125 | Z52: =$H58*(1+(Z86+Z104)) -> 0.026125 | AA52: =AVERAGE(W52:Z52) -> 0.026125 | AB52: =$H58*(1+(AB86+AB104))*$AB$54 -> 0.026125
C53: Net growth in APAC take rate | G53: % | H53: =$H59*(1+(H87+H105)) -> 0.0275 | I53: =$H59*(1+(I87+I105)) -> 0.0275 | J53: =$H59*(1+(J87+J105)) -> 0.0275 | K53: =$H59*(1+(K87+K105)) -> 0.0275 | L53: =AVERAGE(H53:K53) -> 0.0275 | M53: =$H59*(1+(M87+M105)) -> 0.0275 | N53: =$H59*(1+(N87+N105)) -> 0.0275 | O53: =$H59*(1+(O87+O105)) -> 0.0275 | P53: =$H59*(1+(P87+P105)) -> 0.0275 | Q53: =AVERAGE(M53:P53) -> 0.0275 | R53: =$H59*(1+(R87+R105)) -> 0.026875 | S53: =$H59*(1+(S87+S105)) -> 0.026875 | T53: =$H59*(1+(T87+T105)) -> 0.026875 | U53: =$H59*(1+(U87+U105)) -> 0.026875 | V53: =AVERAGE(R53:U53) -> 0.026875 | W53: =$H59*(1+(W87+W105)) -> 0.02575 | X53: =$H59*(1+(X87+X105)) -> 0.02575 | Y53: =$H59*(1+(Y87+Y105)) -> 0.02575 | Z53: =$H59*(1+(Z87+Z105)) -> 0.02575 | AA53: =AVERAGE(W53:Z53) -> 0.02575 | AB53: =$H59*(1+(AB87+AB105))*$AB$54 -> 0.02575
AB54: 1
C55: Growth in take rate per membership
C56: Q growth in EMEA take rate | G56: % | H56: =CHOOSE($H$10,H136,H212,H288) -> 0.03
C57: Q growth in UCAN take rate | G57: % | H57: 0.035
C58: Q growth in LATAM take rate | G58: % | H58: =CHOOSE($H$10,H138,H214,H290) -> 0.025
C59: Q growth in APAC take rate | G59: % | H59: =CHOOSE($H$10,H139,H215,H291) -> 0.025
C61: Average paying memberships
C62: EMEA paying membership % | G62: % | H62: =I62 -> 0.97015172 | I62: =CHOOSE($H$10,I142,I218,I294) -> 0.97015172
C63: UCAN paying membership % | G63: % | H63: =I63 -> 0.99172887 | I63: =CHOOSE($H$10,I143,I219,I295) -> 0.99172887
C64: LATAM paying membership % | G64: % | H64: =I64 -> 0.97851935 | I64: =CHOOSE($H$10,I144,I220,I296) -> 0.97851935
C65: APAC paying membership % | G65: % | H65: =I65 -> 0.96239028 | I65: =CHOOSE($H$10,I145,I221,I297) -> 0.96239028
C67: Content Assets
C68: Q growth in content assets (net) | G68: % | H68: =CHOOSE($H$10,H148,H224,H300) -> -0.1 | I68: =CHOOSE($H$10,I148,I224,I300) -> -0.1 | J68: =CHOOSE($H$10,J148,J224,J300) -> -0.1 | K68: =CHOOSE($H$10,K148,K224,K300) -> -0.1 | L68: =AVERAGE(H68:K68) -> -0.1 | M68: =CHOOSE($H$10,M148,M224,M300) -> 0.05 | N68: =CHOOSE($H$10,N148,N224,N300) -> 0.05 | O68: =CHOOSE($H$10,O148,O224,O300) -> 0.05 | P68: =CHOOSE($H$10,P148,P224,P300) -> 0.05 | Q68: =AVERAGE(M68:P68) -> 0.05 | R68: =CHOOSE($H$10,R148,R224,R300) -> -0.025 | S68: =CHOOSE($H$10,S148,S224,S300) -> -0.025 | T68: =CHOOSE($H$10,T148,T224,T300) -> -0.025 | U68: =CHOOSE($H$10,U148,U224,U300) -> -0.025 | V68: =AVERAGE(R68:U68) -> -0.025 | W68: =CHOOSE($H$10,W148,W224,W300) -> -0.005 | X68: =CHOOSE($H$10,X148,X224,X300) -> -0.005 | Y68: =CHOOSE($H$10,Y148,Y224,Y300) -> -0.005 | Z68: =CHOOSE($H$10,Z148,Z224,Z300) -> -0.005 | AA68: =AVERAGE(W68:Z68) -> -0.005 | AB68: =CHOOSE($H$10,AB148,AB224,AB300) -> -0.005
C70: Cost of Sales
C71: Other COS margin incremental step-up / step-down | G71: % | H71: =CHOOSE($H$10,H151,H227,H303) -> -0.01 | I71: =CHOOSE($H$10,I151,I227,I303) -> -0.01 | J71: =CHOOSE($H$10,J151,J227,J303) -> -0.01 | K71: =CHOOSE($H$10,K151,K227,K303) -> -0.01 | L71: =AVERAGE(H71:K71) -> -0.01 | M71: =CHOOSE($H$10,M151,M227,M303) -> -0.0075 | N71: =CHOOSE($H$10,N151,N227,N303) -> -0.0075 | O71: =CHOOSE($H$10,O151,O227,O303) -> -0.0075 | P71: =CHOOSE($H$10,P151,P227,P303) -> -0.0075 | Q71: =AVERAGE(M71:P71) -> -0.0075 | R71: =CHOOSE($H$10,R151,R227,R303) -> -0.005 | S71: =CHOOSE($H$10,S151,S227,S303) -> -0.005 | T71: =CHOOSE($H$10,T151,T227,T303) -> -0.005 | U71: =CHOOSE($H$10,U151,U227,U303) -> -0.005 | V71: =AVERAGE(R71:U71) -> -0.005 | W71: =CHOOSE($H$10,W151,W227,W303) -> -0.005 | X71: =CHOOSE($H$10,X151,X227,X303) -> -0.005 | Y71: =CHOOSE($H$10,Y151,Y227,Y303) -> -0.005 | Z71: =CHOOSE($H$10,Z151,Z227,Z303) -> -0.005 | AA71: =AVERAGE(W71:Z71) -> -0.005 | AB71: =CHOOSE($H$10,AB151,AB227,AB303) -> -0.005
C72: Content assets COGS margin incremental step-up / step-down | G72: % | H72: =CHOOSE($H$10,H152,H228,H304) -> -0.01 | I72: =CHOOSE($H$10,I152,I228,I304) -> -0.01 | J72: =CHOOSE($H$10,J152,J228,J304) -> -0.01 | K72: =CHOOSE($H$10,K152,K228,K304) -> -0.01 | L72: =AVERAGE(H72:K72) -> -0.01 | M72: =CHOOSE($H$10,M152,M228,M304) -> -0.0075 | N72: =CHOOSE($H$10,N152,N228,N304) -> -0.0075 | O72: =CHOOSE($H$10,O152,O228,O304) -> -0.0075 | P72: =CHOOSE($H$10,P152,P228,P304) -> -0.0075 | Q72: =AVERAGE(M72:P72) -> -0.0075 | R72: =CHOOSE($H$10,R152,R228,R304) -> -0.005 | S72: =CHOOSE($H$10,S152,S228,S304) -> -0.005 | T72: =CHOOSE($H$10,T152,T228,T304) -> -0.005 | U72: =CHOOSE($H$10,U152,U228,U304) -> -0.005 | V72: =AVERAGE(R72:U72) -> -0.005 | W72: =CHOOSE($H$10,W152,W228,W304) -> -0.005 | X72: =CHOOSE($H$10,X152,X228,X304) -> -0.005 | Y72: =CHOOSE($H$10,Y152,Y228,Y304) -> -0.005 | Z72: =CHOOSE($H$10,Z152,Z228,Z304) -> -0.005 | AA72: =AVERAGE(W72:Z72) -> -0.005 | AB72: =CHOOSE($H$10,AB152,AB228,AB304) -> -0.005
AB73: 4
C74: Operating Expenses
C75: Marketing incremental % change | G75: % | H75: =CHOOSE($H$10,H155,H231,H307) -> -0.0035 | I75: =CHOOSE($H$10,I155,I231,I307) -> -0.0035 | J75: =CHOOSE($H$10,J155,J231,J307) -> -0.0035 | K75: =CHOOSE($H$10,K155,K231,K307) -> -0.0035 | L75: =AVERAGE(H75:K75) -> -0.0035 | M75: =CHOOSE($H$10,M155,M231,M307) -> -0.003 | N75: =CHOOSE($H$10,N155,N231,N307) -> -0.003 | O75: =CHOOSE($H$10,O155,O231,O307) -> -0.003 | P75: =CHOOSE($H$10,P155,P231,P307) -> -0.003 | Q75: =AVERAGE(M75:P75) -> -0.003 | R75: =CHOOSE($H$10,R155,R231,R307) -> -0.0025 | S75: =CHOOSE($H$10,S155,S231,S307) -> -0.0025 | T75: =CHOOSE($H$10,T155,T231,T307) -> -0.0025 | U75: =CHOOSE($H$10,U155,U231,U307) -> -0.0025 | V75: =AVERAGE(R75:U75) -> -0.0025 | W75: =CHOOSE($H$10,W155,W231,W307) -> -0.002 | X75: =CHOOSE($H$10,X155,X231,X307) -> -0.002 | Y75: =CHOOSE($H$10,Y155,Y231,Y307) -> -0.002 | Z75: =CHOOSE($H$10,Z155,Z231,Z307) -> -0.002 | AA75: =AVERAGE(W75:Z75) -> -0.002 | AB75: =CHOOSE($H$10,AB155,AB231,AB307) -> -0.002
C76: Technology and development incremental % change | G76: % | H76: =CHOOSE($H$10,H156,H232,H308) -> -0.0035 | I76: =CHOOSE($H$10,I156,I232,I308) -> -0.0035 | J76: =CHOOSE($H$10,J156,J232,J308) -> -0.0035 | K76: =CHOOSE($H$10,K156,K232,K308) -> -0.0035 | L76: =AVERAGE(H76:K76) -> -0.0035 | M76: =CHOOSE($H$10,M156,M232,M308) -> -0.003 | N76: =CHOOSE($H$10,N156,N232,N308) -> -0.003 | O76: =CHOOSE($H$10,O156,O232,O308) -> -0.003 | P76: =CHOOSE($H$10,P156,P232,P308) -> -0.003 | Q76: =AVERAGE(M76:P76) -> -0.003 | R76: =CHOOSE($H$10,R156,R232,R308) -> -0.0025 | S76: =CHOOSE($H$10,S156,S232,S308) -> -0.0025 | T76: =CHOOSE($H$10,T156,T232,T308) -> -0.0025 | U76: =CHOOSE($H$10,U156,U232,U308) -> -0.0025 | V76: =AVERAGE(R76:U76) -> -0.0025 | W76: =CHOOSE($H$10,W156,W232,W308) -> -0.002 | X76: =CHOOSE($H$10,X156,X232,X308) -> -0.002 | Y76: =CHOOSE($H$10,Y156,Y232,Y308) -> -0.002 | Z76: =CHOOSE($H$10,Z156,Z232,Z308) -> -0.002 | AA76: =AVERAGE(W76:Z76) -> -0.002 | AB76: =CHOOSE($H$10,AB156,AB232,AB308) -> -0.002
C77: General and administrative incremental % change | G77: % | H77: =CHOOSE($H$10,H157,H233,H309) -> -0.0035 | I77: =CHOOSE($H$10,I157,I233,I309) -> -0.0035 | J77: =CHOOSE($H$10,J157,J233,J309) -> -0.0035 | K77: =CHOOSE($H$10,K157,K233,K309) -> -0.0035 | L77: =AVERAGE(H77:K77) -> -0.0035 | M77: =CHOOSE($H$10,M157,M233,M309) -> -0.003 | N77: =CHOOSE($H$10,N157,N233,N309) -> -0.003 | O77: =CHOOSE($H$10,O157,O233,O309) -> -0.003 | P77: =CHOOSE($H$10,P157,P233,P309) -> -0.003 | Q77: =AVERAGE(M77:P77) -> -0.003 | R77: =CHOOSE($H$10,R157,R233,R309) -> -0.0025 | S77: =CHOOSE($H$10,S157,S233,S309) -> -0.0025 | T77: =CHOOSE($H$10,T157,T233,T309) -> -0.0025 | U77: =CHOOSE($H$10,U157,U233,U309) -> -0.0025 | V77: =AVERAGE(R77:U77) -> -0.0025 | W77: =CHOOSE($H$10,W157,W233,W309) -> -0.002 | X77: =CHOOSE($H$10,X157,X233,X309) -> -0.002 | Y77: =CHOOSE($H$10,Y157,Y233,Y309) -> -0.002 | Z77: =CHOOSE($H$10,Z157,Z233,Z309) -> -0.002 | AA77: =AVERAGE(W77:Z77) -> -0.002 | AB77: =CHOOSE($H$10,AB157,AB233,AB309) -> -0.002
AB78: 4
C79: Marketing implied % of sales | G79: % | H79: =Operating!AG87 -> 0.076960246 | I79: =Operating!AH87 -> 0.075460246 | J79: =Operating!AI87 -> 0.072960246 | K79: =Operating!AJ87 -> 0.070460246 | L79: =AVERAGE(H79:K79) -> 0.073960246 | M79: =Operating!AL87 -> 0.072960246 | N79: =Operating!AM87 -> 0.075460246 | O79: =Operating!AN87 -> 0.074960246 | P79: =Operating!AO87 -> 0.074460246 | Q79: =AVERAGE(M79:P79) -> 0.074460246 | R79: =Operating!AQ87 -> 0.071960246 | S79: =Operating!AR87 -> 0.069460246 | T79: =Operating!AS87 -> 0.066960246 | U79: =Operating!AT87 -> 0.064460246 | V79: =AVERAGE(R79:U79) -> 0.068210246 | W79: =Operating!AV87 -> 0.062460246 | X79: =Operating!AW87 -> 0.060460246 | Y79: =Operating!AX87 -> 0.058460246 | Z79: =Operating!AY87 -> 0.056460246 | AA79: =AVERAGE(W79:Z79) -> 0.059460246 | AB79: =Operating!BA87 -> 0.054460246
C80: Technology and development implied % of sales | G80: % | H80: =Operating!AG88 -> 0.077937313 | I80: =Operating!AH88 -> 0.076437313 | J80: =Operating!AI88 -> 0.073937313 | K80: =Operating!AJ88 -> 0.071437313 | L80: =AVERAGE(H80:K80) -> 0.074937313 | M80: =Operating!AL88 -> 0.073937313 | N80: =Operating!AM88 -> 0.076437313 | O80: =Operating!AN88 -> 0.075937313 | P80: =Operating!AO88 -> 0.075437313 | Q80: =AVERAGE(M80:P80) -> 0.075437313 | R80: =Operating!AQ88 -> 0.072937313 | S80: =Operating!AR88 -> 0.070437313 | T80: =Operating!AS88 -> 0.067937313 | U80: =Operating!AT88 -> 0.065437313 | V80: =AVERAGE(R80:U80) -> 0.069187313 | W80: =Operating!AV88 -> 0.063437313 | X80: =Operating!AW88 -> 0.061437313 | Y80: =Operating!AX88 -> 0.059437313 | Z80: =Operating!AY88 -> 0.057437313 | AA80: =AVERAGE(W80:Z80) -> 0.060437313 | AB80: =Operating!BA88 -> 0.055437313
C81: General and administrative implied % of sales | G81: % | H81: =Operating!AG89 -> 0.049480495 | I81: =Operating!AH89 -> 0.047980495 | J81: =Operating!AI89 -> 0.045480495 | K81: =Operating!AJ89 -> 0.042980495 | L81: =AVERAGE(H81:K81) -> 0.046480495 | M81: =Operating!AL89 -> 0.045480495 | N81: =Operating!AM89 -> 0.047980495 | O81: =Operating!AN89 -> 0.047480495 | P81: =Operating!AO89 -> 0.046980495 | Q81: =AVERAGE(M81:P81) -> 0.046980495 | R81: =Operating!AQ89 -> 0.044480495 | S81: =Operating!AR89 -> 0.041980495 | T81: =Operating!AS89 -> 0.039480495 | U81: =Operating!AT89 -> 0.036980495 | V81: =AVERAGE(R81:U81) -> 0.040730495 | W81: =Operating!AV89 -> 0.034980495 | X81: =Operating!AW89 -> 0.032980495 | Y81: =Operating!AX89 -> 0.030980495 | Z81: =Operating!AY89 -> 0.028980495 | AA81: =AVERAGE(W81:Z81) -> 0.031980495 | AB81: =Operating!BA89 -> 0.026980495
C83: WWE expansion
C84: Effect on EMEA take rate | G84: % | M84: =CHOOSE($H$10,M160,M236,M312) -> 0.075 | N84: =CHOOSE($H$10,N160,N236,N312) -> 0.075 | O84: =CHOOSE($H$10,O160,O236,O312) -> 0.075 | P84: =CHOOSE($H$10,P160,P236,P312) -> 0.075 | Q84: =AVERAGE(M84:P84) -> 0.075 | R84: =CHOOSE($H$10,R160,R236,R312) -> 0.075 | S84: =CHOOSE($H$10,S160,S236,S312) -> 0.075 | T84: =CHOOSE($H$10,T160,T236,T312) -> 0.075 | U84: =CHOOSE($H$10,U160,U236,U312) -> 0.075 | V84: =AVERAGE(R84:U84) -> 0.075 | W84: =CHOOSE($H$10,W160,W236,W312) -> 0.04 | X84: =CHOOSE($H$10,X160,X236,X312) -> 0.04 | Y84: =CHOOSE($H$10,Y160,Y236,Y312) -> 0.04 | Z84: =CHOOSE($H$10,Z160,Z236,Z312) -> 0.04 | AA84: =AVERAGE(W84:Z84) -> 0.04 | AB84: =CHOOSE($H$10,AB160,AB236,AB312) -> 0.04
C85: Effect on UCAN take rate | G85: % | M85: =CHOOSE($H$10,M161,M237,M313) -> 0.1 | N85: =CHOOSE($H$10,N161,N237,N313) -> 0.1 | O85: =CHOOSE($H$10,O161,O237,O313) -> 0.1 | P85: =CHOOSE($H$10,P161,P237,P313) -> 0.1 | Q85: =AVERAGE(M85:P85) -> 0.1 | R85: =CHOOSE($H$10,R161,R237,R313) -> 0.1 | S85: =CHOOSE($H$10,S161,S237,S313) -> 0.1 | T85: =CHOOSE($H$10,T161,T237,T313) -> 0.1 | U85: =CHOOSE($H$10,U161,U237,U313) -> 0.1 | V85: =AVERAGE(R85:U85) -> 0.1 | W85: =CHOOSE($H$10,W161,W237,W313) -> 0.06 | X85: =CHOOSE($H$10,X161,X237,X313) -> 0.06 | Y85: =CHOOSE($H$10,Y161,Y237,Y313) -> 0.06 | Z85: =CHOOSE($H$10,Z161,Z237,Z313) -> 0.06 | AA85: =AVERAGE(W85:Z85) -> 0.06 | AB85: =CHOOSE($H$10,AB161,AB237,AB313) -> 0.06
C86: Effect on LATAM take rate | G86: % | M86: =CHOOSE($H$10,M162,M238,M314) -> 0.05 | N86: =CHOOSE($H$10,N162,N238,N314) -> 0.05 | O86: =CHOOSE($H$10,O162,O238,O314) -> 0.05 | P86: =CHOOSE($H$10,P162,P238,P314) -> 0.05 | Q86: =AVERAGE(M86:P86) -> 0.05 | R86: =CHOOSE($H$10,R162,R238,R314) -> 0.05 | S86: =CHOOSE($H$10,S162,S238,S314) -> 0.05 | T86: =CHOOSE($H$10,T162,T238,T314) -> 0.05 | U86: =CHOOSE($H$10,U162,U238,U314) -> 0.05 | V86: =AVERAGE(R86:U86) -> 0.05 | W86: =CHOOSE($H$10,W162,W238,W314) -> 0.02 | X86: =CHOOSE($H$10,X162,X238,X314) -> 0.02 | Y86: =CHOOSE($H$10,Y162,Y238,Y314) -> 0.02 | Z86: =CHOOSE($H$10,Z162,Z238,Z314) -> 0.02 | AA86: =AVERAGE(W86:Z86) -> 0.02 | AB86: =CHOOSE($H$10,AB162,AB238,AB314) -> 0.02
C87: Effect on APAC take rate | G87: % | M87: =CHOOSE($H$10,M163,M239,M315) -> 0.025 | N87: =CHOOSE($H$10,N163,N239,N315) -> 0.025 | O87: =CHOOSE($H$10,O163,O239,O315) -> 0.025 | P87: =CHOOSE($H$10,P163,P239,P315) -> 0.025 | Q87: =AVERAGE(M87:P87) -> 0.025 | R87: =CHOOSE($H$10,R163,R239,R315) -> 0.025 | S87: =CHOOSE($H$10,S163,S239,S315) -> 0.025 | T87: =CHOOSE($H$10,T163,T239,T315) -> 0.025 | U87: =CHOOSE($H$10,U163,U239,U315) -> 0.025 | V87: =AVERAGE(R87:U87) -> 0.025 | W87: =CHOOSE($H$10,W163,W239,W315) -> 0.005 | X87: =CHOOSE($H$10,X163,X239,X315) -> 0.005 | Y87: =CHOOSE($H$10,Y163,Y239,Y315) -> 0.005 | Z87: =CHOOSE($H$10,Z163,Z239,Z315) -> 0.005 | AA87: =AVERAGE(W87:Z87) -> 0.005 | AB87: =CHOOSE($H$10,AB163,AB239,AB315) -> 0.005
C89: Effect on EMEA growth in subs | G89: % | M89: =CHOOSE($H$10,M165,M241,M317) -> 0.25 | N89: =CHOOSE($H$10,N165,N241,N317) -> 0.25 | O89: =CHOOSE($H$10,O165,O241,O317) -> 0.25 | P89: =CHOOSE($H$10,P165,P241,P317) -> 0.25 | Q89: =AVERAGE(M89:P89) -> 0.25 | R89: =CHOOSE($H$10,R165,R241,R317) -> 0.25 | S89: =CHOOSE($H$10,S165,S241,S317) -> 0.25 | T89: =CHOOSE($H$10,T165,T241,T317) -> 0.25 | U89: =CHOOSE($H$10,U165,U241,U317) -> 0.25 | V89: =AVERAGE(R89:U89) -> 0.25 | W89: =CHOOSE($H$10,W165,W241,W317) -> 0.15 | X89: =CHOOSE($H$10,X165,X241,X317) -> 0.15 | Y89: =CHOOSE($H$10,Y165,Y241,Y317) -> 0.15 | Z89: =CHOOSE($H$10,Z165,Z241,Z317) -> 0.15 | AA89: =AVERAGE(W89:Z89) -> 0.15 | AB89: =CHOOSE($H$10,AB165,AB241,AB317) -> 0.15
