Workbook
Name IQ_CH: 110000
Name IQ_CQ: 5000
Name IQ_CY: 10000
Name IQ_DAILY: 500000
Name IQ_FH: 100000
Name IQ_FQ: 500
Name IQ_FY: 1000
Name IQ_LTM: 2000
Name IQ_MONTH: 15000
Name IQ_NTM: 6000
Name IQ_WEEK: 50000
Name IQ_YTD: 3000

Sheet Master
B4: Nanyang Capital Stock Pitch Competition 2026
B5: Valuation Model
B7: NISSIN TSE: 2879

Sheet Drivers
B2: Nissin Foods Holdings Co Ltd
B3: (2897 JT)
G5: Period Start | H5: 44105 | I5: =H6+1 -> 44197 | J5: =I6+1 -> 44287 | K5: =J6+1 -> 44378 | L5: =K6+1 -> 44470 | M5: =L6+1 -> 44562 | N5: =M6+1 -> 44652 | O5: =N6+1 -> 44743 | P5: =O6+1 -> 44835 | ... AB5: =AA6+1 -> 45931
G6: Period End | H6: =EOMONTH(H5,2) -> 44196 | I6: =EOMONTH(I5,2) -> 44286 | J6: =EOMONTH(J5,2) -> 44377 | K6: =EOMONTH(K5,2) -> 44469 | L6: =EOMONTH(L5,2) -> 44561 | M6: =EOMONTH(M5,2) -> 44651 | N6: =EOMONTH(N5,2) -> 44742 | O6: =EOMONTH(O5,2) -> 44834 | ... AB6: =EOMONTH(AB5,2) -> 46022
G7: FY | H7: =IF(MONTH(H6)>3,YEAR(H6)+1,YEAR(H6)) -> 2021 | I7: =IF(MONTH(I6)>3,YEAR(I6)+1,YEAR(I6)) -> 2021 | J7: =IF(MONTH(J6)>3,YEAR(J6)+1,YEAR(J6)) -> 2022 | K7: =IF(MONTH(K6)>3,YEAR(K6)+1,YEAR(K6)) -> 2022 | L7: =IF(MONTH(L6)>3,YEAR(L6)+1,YEAR(L6)) -> 2022 | M7: =IF(MONTH(M6)>3,YEAR(M6)+1,YEAR(M6)) -> 2022 | N7: =IF(MONTH(N6)>3,YEAR(N6)+1,YEAR(N6)) -> 2023 | O7: =IF(MONTH(O6)>3,YEAR(O6)+1,YEAR(O6)) -> 2023 | ... AB7: =IF(MONTH(AB6)>3,YEAR(AB6)+1,YEAR(AB6)) -> 2026
B8: In Thousands of JPY | G8: Quarter | H8: =IF(MONTH(H5)=4,"Q1",IF(MONTH(H5)=7,"Q2",IF(MONTH(H5)=10,"Q3","Q4"))) -> Q3 | I8: =IF(MONTH(I5)=4,"Q1",IF(MONTH(I5)=7,"Q2",IF(MONTH(I5)=10,"Q3","Q4"))) -> Q4 | J8: =IF(MONTH(J5)=4,"Q1",IF(MONTH(J5)=7,"Q2",IF(MONTH(J5)=10,"Q3","Q4"))) -> Q1 | K8: =IF(MONTH(K5)=4,"Q1",IF(MONTH(K5)=7,"Q2",IF(MONTH(K5)=10,"Q3","Q4"))) -> Q2 | L8: =IF(MONTH(L5)=4,"Q1",IF(MONTH(L5)=7,"Q2",IF(MONTH(L5)=10,"Q3","Q4"))) -> Q3 | M8: =IF(MONTH(M5)=4,"Q1",IF(MONTH(M5)=7,"Q2",IF(MONTH(M5)=10,"Q3","Q4"))) -> Q4 | N8: =IF(MONTH(N5)=4,"Q1",IF(MONTH(N5)=7,"Q2",IF(MONTH(N5)=10,"Q3","Q4"))) -> Q1 | O8: =IF(MONTH(O5)=4,"Q1",IF(MONTH(O5)=7,"Q2",IF(MONTH(O5)=10,"Q3","Q4"))) -> Q2 | ... AB8: =IF(MONTH(AB5)=4,"Q1",IF(MONTH(AB5)=7,"Q2",IF(MONTH(AB5)=10,"Q3","Q4"))) -> Q3
G9: Days | H9: =_xlfn.DAYS(H6,H5)+1 -> 92 | I9: =_xlfn.DAYS(I6,I5)+1 -> 90 | J9: =_xlfn.DAYS(J6,J5)+1 -> 91 | K9: =_xlfn.DAYS(K6,K5)+1 -> 92 | L9: =_xlfn.DAYS(L6,L5)+1 -> 92 | M9: =_xlfn.DAYS(M6,M5)+1 -> 90 | N9: =_xlfn.DAYS(N6,N5)+1 -> 91 | O9: =_xlfn.DAYS(O6,O5)+1 -> 92 | ... AB9: =_xlfn.DAYS(AB6,AB5)+1 -> 92
A10: # | B10: Historical Quarterly Results
B12: Revenue | E12: Latest % of Revenue
B13: Instant Noodles | H13: =SUM(H14:H17) -> 96613 | I13: =SUM(I14:I17) -> 90658 | J13: =SUM(J14:J17) -> 88456 | K13: =SUM(K14:K17) -> 97060 | L13: =SUM(L14:L17) -> 104735 | M13: =SUM(M14:M17) -> 101254 | N13: =SUM(N14:N17) -> 102667 | O13: =SUM(O14:O17) -> 118232 | ... AB13: =SUM(AB14:AB17) -> 145992 | AN13: $
B14: Nissin Food Products | E14: =AB14/$AB$24 -> 0.33112536 | H14: 57884 | I14: 50707 | J14: 46577 | K14: 51948 | L14: 59620 | M14: 52637 | N14: 47791 | O14: 54071 | P14: 65104 | Q14: 53237 | R14: 51448 | S14: 56355 | T14: 69302 | U14: 55116 | V14: 53363 | W14: 57768 | X14: 69008 | Y14: 58642 | Z14: 52940 | AA14: 60064 | AB14: 70635
B15: Myojo Foods | E15: =AB15/$AB$24 -> 0.06135441 | H15: 9912 | I15: 9516 | J15: 9411 | K15: 9283 | L15: 9562 | M15: 9663 | N15: 9257 | O15: 10014 | P15: 10737 | Q15: 10502 | R15: 9963 | S15: 10388 | T15: 11582 | U15: 11516 | V15: 10751 | W15: 11498 | X15: 11862 | Y15: 11263 | Z15: 11635 | AA15: 11543 | AB15: 13088
B16: The Americas | E16: =AB16/$AB$24 -> 0.20909628 | H16: 17767 | I16: 17590 | J16: 20221 | K16: 22196 | L16: 21412 | M16: 23497 | N16: 29899 | O16: 36119 | P16: 38719 | Q16: 35304 | R16: 34433 | S16: 42276 | T16: 42470 | U16: 41154 | V16: 41981 | W16: 42476 | X16: 41151 | Y16: 42955 | Z16: 33380 | AA16: 41043 | AB16: 44604
B17: China | E17: =AB17/$AB$24 -> 0.08281064 | H17: 11050 | I17: 12845 | J17: 12247 | K17: 13633 | L17: 14141 | M17: 15457 | N17: 15720 | O17: 18028 | P17: 16389 | Q17: 16834 | R17: 14859 | S17: 18076 | T17: 15910 | U17: 17606 | V17: 16458 | W17: 18999 | X17: 18071 | Y17: 19945 | Z17: 16689 | AA17: 19190 | AB17: 17665
B18: Chilled / Frozen Foods & Beverages | E18: =AB18/$AB$24 -> 0.12651534 | H18: 19265 | I18: 19107 | J18: 20216 | K18: 20773 | L18: 20232 | M18: 19645 | N18: 20354 | O18: 21235 | P18: 22939 | Q18: 22309 | R18: 23213 | S18: 23559 | T18: 24769 | U18: 23679 | V18: 25462 | W18: 25474 | X18: 25828 | Y18: 24584 | Z18: 26154 | AA18: 26096 | AB18: 26988
B19: Confectionery / Snack | E19: =AB19/$AB$24 -> 0.11684902 | H19: 10433 | I19: 15931 | J19: 17063 | K19: 17740 | L19: 17222 | M19: 17006 | N19: 17561 | O19: 17647 | P19: 19754 | Q19: 19093 | R19: 20750 | S19: 20129 | T19: 22377 | U19: 21893 | V19: 23072 | W19: 22388 | X19: 24325 | Y19: 22658 | Z19: 23743 | AA19: 23460 | AB19: 24926
B20: Others | H20: 6412 | I20: 6552 | J20: =SUM(J21:J23) -> 6719 | K20: =SUM(K21:K23) -> 7003 | L20: =SUM(L21:L23) -> 7565 | M20: =SUM(M21:M23) -> 7023 | N20: =SUM(N21:N23) -> 8677 | O20: =SUM(O21:O23) -> 10573 | P20: =SUM(P21:P23) -> 10867 | Q20: =SUM(Q21:Q23) -> 10500 | ... AB20: =SUM(AB21:AB23) -> 15412
B21: Domestic | E21: =AB21/$AB$24 -> 0.01092266 | J21: 498 | K21: 564 | L21: 589 | M21: 520 | N21: 701 | O21: 1526 | P21: 1169 | Q21: 1282 | R21: 1442 | S21: 1678 | T21: 1393 | U21: 1569 | V21: 1761 | W21: 2100 | X21: 1721 | Y21: 2210 | Z21: 1907 | AA21: 2383 | AB21: 2330
B22: Asia | E22: =AB22/$AB$24 -> 0.027897318 | J22: 3391 | K22: 3879 | L22: 3905 | M22: 3602 | N22: 4557 | O22: 4867 | P22: 4966 | Q22: 4205 | R22: 5201 | S22: 5244 | T22: 5196 | U22: 5081 | V22: 6005 | W22: 5891 | X22: 5682 | Y22: 5691 | Z22: 5064 | AA22: 5656 | AB22: 5951
B23: EMEA | E23: =AB23/$AB$24 -> 0.033428965 | J23: 2830 | K23: 2560 | L23: 3071 | M23: 2901 | N23: 3419 | O23: 4180 | P23: 4732 | Q23: 5013 | R23: 5156 | S23: 6191 | T23: 5549 | U23: 6397 | V23: 6180 | W23: 6455 | X23: 6535 | Y23: 6368 | Z23: 5515 | AA23: 6772 | AB23: 7131
B24: Total Revenue | H24: =SUM(H13,H18:H20) -> 132723 | I24: =SUM(I13,I18:I20) -> 132248 | J24: =SUM(J13,J18:J20) -> 132454 | K24: =SUM(K13,K18:K20) -> 142576 | L24: =SUM(L13,L18:L20) -> 149754 | M24: =SUM(M13,M18:M20) -> 144928 | N24: =SUM(N13,N18:N20) -> 149259 | O24: =SUM(O13,O18:O20) -> 167687 | ... AB24: =SUM(AB13,AB18:AB20) -> 213318
B26: COGS | H26: -84730 | I26: -87484 | J26: -85725 | K26: -93381 | L26: -96905 | M26: -99207 | N26: -100150 | O26: -112100 | P26: -121274 | Q26: -114646 | R26: -108485 | S26: -117321 | T26: -125522 | U26: -122975 | V26: -117980 | W26: -124434 | X26: -132337 | Y26: -128891 | Z26: -116570 | AA26: -128399 | AB26: -138740
B27: Gross Profit | H27: 47993 | I27: 44764 | J27: 46729 | K27: 49195 | L27: 52849 | M27: 45721 | N27: 49109 | O27: 55587 | P27: 63235 | Q27: 53133 | R27: 57980 | S27: 66575 | T27: 73026 | U27: 61036 | V27: 67053 | W27: 68615 | X27: 71846 | Y27: 65425 | Z27: 60457 | AA27: 67808 | AB27: 74578
E28: Mean
B29: COGS Margin % | E29: =AVERAGE(H29:AB29) -> 0.65527909 | H29: =-H26/H$24 -> 0.63839726 | I29: =-I26/I$24 -> 0.66151473 | J29: =-J26/J$24 -> 0.64720582 | K29: =-K26/K$24 -> 0.65495595 | L29: =-L26/L$24 -> 0.64709457 | M29: =-M26/M$24 -> 0.68452611 | N29: =-N26/N$24 -> 0.67098131 | O29: =-O26/O$24 -> 0.6685074 | ... AB29: =-AB26/AB$24 -> 0.6503905
B30: Gross Profit Margin % | E30: =AVERAGE(H30:AB30) -> 0.34472091 | H30: =H27/H$24 -> 0.36160274 | I30: =I27/I$24 -> 0.33848527 | J30: =J27/J$24 -> 0.35279418 | K30: =K27/K$24 -> 0.34504405 | L30: =L27/L$24 -> 0.35290543 | M30: =M27/M$24 -> 0.31547389 | N30: =N27/N$24 -> 0.32901869 | O30: =O27/O$24 -> 0.3314926 | ... AB30: =AB27/AB$24 -> 0.3496095
B32: Accounts Receivable And Other Receivables | H32: 91511 | I32: 84837 | J32: 76286 | K32: 83738 | L32: 93222 | M32: 89600 | N32: 82290 | O32: 99864 | P32: 113040 | Q32: 101483 | R32: 94722 | S32: 109021 | T32: 120651 | U32: 116407 | V32: 107252 | W32: 105775 | X32: 125298 | Y32: 115072 | Z32: 103765 | AA32: 118174 | AB32: 135291
B33: Inventories | H33: 38262 | I33: 40901 | J33: 44193 | K33: 43723 | L33: 45965 | M33: 47638 | N33: 57773 | O33: 59626 | P33: 57292 | Q33: 57187 | R33: 66079 | S33: 69344 | T33: 67438 | U33: 64060 | V33: 71625 | W33: 71173 | X33: 75789 | Y33: 70536 | Z33: 74010 | AA33: 73824 | AB33: 76205
B34: Trade Payable And Other Payables | H34: 120225 | I34: 119275 | J34: 112877 | K34: 110398 | L34: 124017 | M34: 123251 | N34: 121933 | O34: 126624 | P34: 139750 | Q34: 140346 | R34: 127672 | S34: 144655 | T34: 150766 | U34: 161453 | V34: 144432 | W34: 131800 | X34: 156566 | Y34: 144703 | Z34: 132757 | AA34: 147672 | AB34: 155466
E35: Average
C36: Q1 | D36: Q2 | E36: Q3 | F36: Q4
B37: DSO | C37: =AVERAGEIF($I8:$AB8,C36,$I37:$AB37) -> 54.524052 | D37: =AVERAGEIF($I8:$AB8,D36,$I37:$AB37) -> 51.071129 | E37: =AVERAGEIF($I8:$AB8,E36,$I37:$AB37) -> 53.472447 | F37: =AVERAGEIF($I8:$AB8,F36,$I37:$AB37) -> 57.718245 | I37: =ABS(AVERAGE(H32:I32)/I$24*I$9) -> 60.005898 | J37: =ABS(AVERAGE(I32:J32)/J$24*J$9) -> 55.348245 | K37: =ABS(AVERAGE(J32:K32)/K$24*K$9) -> 51.629335 | L37: =ABS(AVERAGE(K32:L32)/L$24*L$9) -> 54.356879 | M37: =ABS(AVERAGE(L32:M32)/M$24*M$9) -> 56.766049 | N37: =ABS(AVERAGE(M32:N32)/N$24*N$9) -> 52.398817 | O37: =ABS(AVERAGE(N32:O32)/O$24*O$9) -> 49.968596 | P37: =ABS(AVERAGE(O32:P32)/P$24*P$9) -> 53.079167 | ... AB37: =ABS(AVERAGE(AA32:AB32)/AB$24*AB$9) -> 54.657319
B38: DIO | C38: =AVERAGEIF($I8:$AB8,C36,$I38:$AB38) -> 50.700474 | D38: =AVERAGEIF($I8:$AB8,D36,$I38:$AB38) -> 50.066267 | E38: =AVERAGEIF($I8:$AB8,E36,$I38:$AB38) -> 47.574976 | F38: =AVERAGEIF($I8:$AB8,F36,$I38:$AB38) -> 45.570514 | I38: =ABS(AVERAGE(H33:I33)/I$26*I$9) -> 40.719846 | J38: =ABS(AVERAGE(I33:J33)/J$26*J$9) -> 45.165086 | K38: =ABS(AVERAGE(J33:K33)/K$26*K$9) -> 43.307911 | L38: =ABS(AVERAGE(K33:L33)/L$26*L$9) -> 42.57415 | M38: =ABS(AVERAGE(L33:M33)/M$26*M$9) -> 42.458042 | N38: =ABS(AVERAGE(M33:N33)/N$26*N$9) -> 47.89017 | O38: =ABS(AVERAGE(N33:O33)/O$26*O$9) -> 48.174434 | P38: =ABS(AVERAGE(O33:P33)/P$26*P$9) -> 44.347741 | ... AB38: =ABS(AVERAGE(AA33:AB33)/AB$26*AB$9) -> 49.742929
B39: DPO | C39: =AVERAGEIF($I8:$AB8,C36,$I39:$AB39) -> 114.65735 | D39: =AVERAGEIF($I8:$AB8,D36,$I39:$AB39) -> 104.26778 | E39: =AVERAGEIF($I8:$AB8,E36,$I39:$AB39) -> 104.26347 | F39: =AVERAGEIF($I8:$AB8,F36,$I39:$AB39) -> 113.19941 | I39: =ABS(AVERAGE(H34:I34)/I$26*I$9) -> 123.19396 | J39: =ABS(AVERAGE(I34:J34)/J$26*J$9) -> 123.21862 | K39: =ABS(AVERAGE(J34:K34)/K$26*K$9) -> 109.98651 | L39: =ABS(AVERAGE(K34:L34)/L$26*L$9) -> 111.27486 | M39: =ABS(AVERAGE(L34:M34)/M$26*M$9) -> 112.16003 | N39: =ABS(AVERAGE(M34:N34)/N$26*N$9) -> 111.39163 | O39: =ABS(AVERAGE(N34:O34)/O$26*O$9) -> 101.99484 | P39: =ABS(AVERAGE(O34:P34)/P$26*P$9) -> 101.03735 | ... AB39: =ABS(AVERAGE(AA34:AB34)/AB$26*AB$9) -> 100.50705
A41: # | B41: YoY Quarterly Growth Rate (in %)
B43: Revenue | AE43: Arethmetic Mean | AF43: Geometric Mean
B44: Instant Noodles | L44: =L13/H13-1 -> 0.084067362 | M44: =M13/I13-1 -> 0.11687882 | N44: =N13/J13-1 -> 0.16065615 | O44: =O13/K13-1 -> 0.21813311 | P44: =P13/L13-1 -> 0.25028882 | Q44: =Q13/M13-1 -> 0.14441899 | R44: =R13/N13-1 -> 0.078272473 | S44: =S13/O13-1 -> 0.074962785 | ... AB44: =AB13/X13-1 -> 0.042115181 | AE44: =AVERAGE(L44:AB44) -> 0.085886455 | AF44: =(AB13/H13)^(1/((($AB$7-$H$7))))-1 -> 0.086072202
B45: Nissin Food Products | L45: =L14/H14-1 -> 0.029991017 | M45: =M14/I14-1 -> 0.038061806 | N45: =N14/J14-1 -> 0.026064367 | O45: =O14/K14-1 -> 0.040867791 | P45: =P14/L14-1 -> 0.091982556 | Q45: =Q14/M14-1 -> 0.011398826 | R45: =R14/N14-1 -> 0.076520684 | S45: =S14/O14-1 -> 0.042240758 | ... AB45: =AB14/X14-1 -> 0.023576977 | AE45: =AVERAGE(L45:AB45) -> 0.037313334 | AF45: =(AB14/H14)^(1/((($AB$7-$H$7))))-1 -> 0.040620274
B46: Myojo Foods | L46: =L15/H15-1 -> -0.035310734 | M46: =M15/I15-1 -> 0.015447667 | N46: =N15/J15-1 -> -0.01636383 | O46: =O15/K15-1 -> 0.078746095 | P46: =P15/L15-1 -> 0.12288224 | Q46: =Q15/M15-1 -> 0.086826037 | R46: =R15/N15-1 -> 0.076266609 | S46: =S15/O15-1 -> 0.037347713 | ... AB46: =AB15/X15-1 -> 0.10335525 | AE46: =AVERAGE(L46:AB46) -> 0.054043604 | AF46: =(AB15/H15)^(1/((($AB$7-$H$7))))-1 -> 0.057164081
B47: The Americas | L47: =L16/H16-1 -> 0.20515563 | M47: =M16/I16-1 -> 0.3358158 | N47: =N16/J16-1 -> 0.47861134 | O47: =O16/K16-1 -> 0.62727518 | P47: =P16/L16-1 -> 0.80828507 | Q47: =Q16/M16-1 -> 0.50248968 | R47: =R16/N16-1 -> 0.15164387 | S47: =S16/O16-1 -> 0.1704643 | ... AB47: =AB16/X16-1 -> 0.083910476 | AE47: =AVERAGE(L47:AB47) -> 0.21319187 | AF47: =(AB16/H16)^(1/((($AB$7-$H$7))))-1 -> 0.2021314
B48: China | L48: =L17/H17-1 -> 0.27972851 | M48: =M17/I17-1 -> 0.20334761 | N48: =N17/J17-1 -> 0.28357965 | O48: =O17/K17-1 -> 0.32237952 | P48: =P17/L17-1 -> 0.15897037 | Q48: =Q17/M17-1 -> 0.089085851 | R48: =R17/N17-1 -> -0.054770992 | S48: =S17/O17-1 -> 0.002662525 | ... AB48: =AB17/X17-1 -> -0.022466936 | AE48: =AVERAGE(L48:AB48) -> 0.10179943 | AF48: =(AB17/H17)^(1/((($AB$7-$H$7))))-1 -> 0.098374073
B49: Chilled / Frozen Foods & Beverages | L49: =L18/H18-1 -> 0.050194654 | M49: =M18/I18-1 -> 0.02815722 | N49: =N18/J18-1 -> 0.0068262762 | O49: =O18/K18-1 -> 0.022240408 | P49: =P18/L18-1 -> 0.13379794 | Q49: =Q18/M18-1 -> 0.13560702 | R49: =R18/N18-1 -> 0.14046379 | S49: =S18/O18-1 -> 0.10944196 | ... AB49: =AB18/X18-1 -> 0.044912498 | AE49: =AVERAGE(L49:AB49) -> 0.066092282 | AF49: =(AB18/H18)^(1/((($AB$7-$H$7))))-1 -> 0.069745178
B50: Confectionery / Snack | L50: =L19/H19-1 -> 0.65072367 | M50: =M19/I19-1 -> 0.067478501 | N50: =N19/J19-1 -> 0.029185958 | O50: =O19/K19-1 -> -0.0052423901 | P50: =P19/L19-1 -> 0.14702125 | Q50: =Q19/M19-1 -> 0.12272139 | R50: =R19/N19-1 -> 0.18159558 | S50: =S19/O19-1 -> 0.14064714 | ... AB50: =AB19/X19-1 -> 0.024707091 | AE50: =AVERAGE(L50:AB50) -> 0.12125669 | AF50: =(AB19/H19)^(1/((($AB$7-$H$7))))-1 -> 0.19027874
B51: Others | L51: =L20/H20-1 -> 0.17981909 | M51: =M20/I20-1 -> 0.071886447 | N51: =N20/J20-1 -> 0.29141241 | O51: =O20/K20-1 -> 0.50978152 | P51: =P20/L20-1 -> 0.43648381 | Q51: =Q20/M20-1 -> 0.49508757 | R51: =R20/N20-1 -> 0.35980177 | S51: =S20/O20-1 -> 0.24023456 | ... AB51: =AB20/X20-1 -> 0.10575405 | AE51: =AVERAGE(L51:AB51) -> 0.2056438 | AF51: =(AB20/H20)^(1/((($AB$7-$H$7))))-1 -> 0.1917169
B52: Domestic | N52: =N21/J21-1 -> 0.40763052 | O52: =O21/K21-1 -> 1.7056738 | P52: =P21/L21-1 -> 0.98471986 | Q52: =Q21/M21-1 -> 1.4653846 | R52: =R21/N21-1 -> 1.0570613 | S52: =S21/O21-1 -> 0.099606815 | T52: =T21/P21-1 -> 0.19161677 | U52: =U21/Q21-1 -> 0.22386895 | ... AB52: =AB21/X21-1 -> 0.35386403 | AE52: =AVERAGE(L52:AB52) -> 0.52158733 | AF52: =(AB21/J21)^(1/((($AB$7-$J$7))))-1 -> 0.47072557
B53: Asia | N53: =N22/J22-1 -> 0.34385137 | O53: =O22/K22-1 -> 0.25470482 | P53: =P22/L22-1 -> 0.27170294 | Q53: =Q22/M22-1 -> 0.167407 | R53: =R22/N22-1 -> 0.14132104 | S53: =S22/O22-1 -> 0.077460448 | T53: =T22/P22-1 -> 0.046314942 | U53: =U22/Q22-1 -> 0.20832342 | ... AB53: =AB22/X22-1 -> 0.047342485 | AE53: =AVERAGE(L53:AB53) -> 0.12355918 | AF53: =(Z22/J22)^(1/((($Z$7-$J$7))))-1 -> 0.10545604
B54: EMEA | N54: =N23/J23-1 -> 0.20812721 | O54: =O23/K23-1 -> 0.6328125 | P54: =P23/L23-1 -> 0.54086617 | Q54: =Q23/M23-1 -> 0.72802482 | R54: =R23/N23-1 -> 0.50804329 | S54: =S23/O23-1 -> 0.48110048 | T54: =T23/P23-1 -> 0.17265427 | U54: =U23/Q23-1 -> 0.27608219 | ... AB54: =AB23/X23-1 -> 0.091201224 | AE54: =AVERAGE(L54:AB54) -> 0.26632124 | AF54: =(Z23/J23)^(1/((($Z$7-$J$7))))-1 -> 0.18151644
B55: Total Revenue | L55: =L24/H24-1 -> 0.12831988 | M55: =M24/I24-1 -> 0.095880467 | N55: =N24/J24-1 -> 0.12687424 | O55: =O24/K24-1 -> 0.17612361 | P55: =P24/L24-1 -> 0.23208061 | Q55: =Q24/M24-1 -> 0.1576714 | R55: =R24/N24-1 -> 0.11527613 | S55: =S24/O24-1 -> 0.096662234 | ... AB55: =AB24/X24-1 -> 0.044739278 | AE55: =AVERAGE(L55:AB55) -> 0.092073646 | AF55: =(AB24/H24)^(1/((($AB$7-$H$7))))-1 -> 0.09955324
A58: # | B58: Historical Revenue (Annual)
G59: Period Start | H59: 43922 | I59: =H60+1 -> 44287 | J59: =I60+1 -> 44652 | K59: =J60+1 -> 45017 | L59: =K60+1 -> 45383 | M59: =Y5 -> 45658
G60: Period End | H60: =EOMONTH(H59,11) -> 44286 | I60: =EOMONTH(I59,11) -> 44651 | J60: =EOMONTH(J59,11) -> 45016 | K60: =EOMONTH(K59,11) -> 45382 | L60: =EOMONTH(L59,11) -> 45747 | M60: =EOMONTH(M59,11) -> 46022
G61: FY | H61: =IF(MONTH(H60)>3,YEAR(H60)+1,YEAR(H60)) -> 2021 | I61: =H61+1 -> 2022 | J61: =I61+1 -> 2023 | K61: =J61+1 -> 2024 | L61: =K61+1 -> 2025 | M61: =L61+1 -> 2026
G62: Days | H62: =_xlfn.DAYS(H60,H59)+1 -> 365 | I62: =_xlfn.DAYS(I60,I59)+1 -> 365 | J62: =_xlfn.DAYS(J60,J59)+1 -> 365 | K62: =_xlfn.DAYS(K60,K59)+1 -> 366 | L62: =_xlfn.DAYS(L60,L59)+1 -> 365 | M62: =(_xlfn.DAYS(M60,M59)+1) & " - TTM" -> 365 - TTM
B63: Instant Noodles | I63: =SUMIF($H$7:$AB$7,I$61,$H13:$AB13) -> 391505 | J63: =SUMIF($H$7:$AB$7,J$61,$H13:$AB13) -> 467725 | K63: =SUMIF($H$7:$AB$7,K$61,$H13:$AB13) -> 502454 | L63: =SUMIF($H$7:$AB$7,L$61,$H13:$AB13) -> 526191 | M63: =Y13+SUMIF($H$7:$AB$7,M$61,$H13:$AB13) -> 525281
B64: Nissin Food Products | I64: =SUMIF($H$7:$AB$7,I$61,$H14:$AB14) -> 210782 | J64: =SUMIF($H$7:$AB$7,J$61,$H14:$AB14) -> 220203 | K64: =SUMIF($H$7:$AB$7,K$61,$H14:$AB14) -> 232221 | L64: =SUMIF($H$7:$AB$7,L$61,$H14:$AB14) -> 238781 | M64: =Y14+SUMIF($H$7:$AB$7,M$61,$H14:$AB14) -> 242281
B65: Myojo Foods | I65: =SUMIF($H$7:$AB$7,I$61,$H15:$AB15) -> 37919 | J65: =SUMIF($H$7:$AB$7,J$61,$H15:$AB15) -> 40510 | K65: =SUMIF($H$7:$AB$7,K$61,$H15:$AB15) -> 43449 | L65: =SUMIF($H$7:$AB$7,L$61,$H15:$AB15) -> 45374 | M65: =Y15+SUMIF($H$7:$AB$7,M$61,$H15:$AB15) -> 47529
B66: The Americas | I66: =SUMIF($H$7:$AB$7,I$61,$H16:$AB16) -> 87326 | J66: =SUMIF($H$7:$AB$7,J$61,$H16:$AB16) -> 140041 | K66: =SUMIF($H$7:$AB$7,K$61,$H16:$AB16) -> 160333 | L66: =SUMIF($H$7:$AB$7,L$61,$H16:$AB16) -> 168563 | M66: =Y16+SUMIF($H$7:$AB$7,M$61,$H16:$AB16) -> 161982
B67: China | I67: =SUMIF($H$7:$AB$7,I$61,$H17:$AB17) -> 55478 | J67: =SUMIF($H$7:$AB$7,J$61,$H17:$AB17) -> 66971 | K67: =SUMIF($H$7:$AB$7,K$61,$H17:$AB17) -> 66451 | L67: =SUMIF($H$7:$AB$7,L$61,$H17:$AB17) -> 73473 | M67: =Y17+SUMIF($H$7:$AB$7,M$61,$H17:$AB17) -> 73489
B68: Chilled / Frozen Foods & Beverages | I68: =SUMIF($H$7:$AB$7,I$61,$H18:$AB18) -> 80866 | J68: =SUMIF($H$7:$AB$7,J$61,$H18:$AB18) -> 86837 | K68: =SUMIF($H$7:$AB$7,K$61,$H18:$AB18) -> 95220 | L68: =SUMIF($H$7:$AB$7,L$61,$H18:$AB18) -> 101348 | M68: =Y18+SUMIF($H$7:$AB$7,M$61,$H18:$AB18) -> 103822
B69: Confectionery / Snack | I69: =SUMIF($H$7:$AB$7,I$61,$H19:$AB19) -> 69031 | J69: =SUMIF($H$7:$AB$7,J$61,$H19:$AB19) -> 74055 | K69: =SUMIF($H$7:$AB$7,K$61,$H19:$AB19) -> 85149 | L69: =SUMIF($H$7:$AB$7,L$61,$H19:$AB19) -> 92443 | M69: =Y19+SUMIF($H$7:$AB$7,M$61,$H19:$AB19) -> 94787
B70: Others | I70: =SUMIF($H$7:$AB$7,I$61,$H20:$AB20) -> 28310 | J70: =SUMIF($H$7:$AB$7,J$61,$H20:$AB20) -> 40617 | K70: =SUMIF($H$7:$AB$7,K$61,$H20:$AB20) -> 50097 | L70: =SUMIF($H$7:$AB$7,L$61,$H20:$AB20) -> 56599 | M70: =Y20+SUMIF($H$7:$AB$7,M$61,$H20:$AB20) -> 56978
B71: Domestic | I71: =SUMIF($H$7:$AB$7,I$61,$H21:$AB21) -> 2171 | J71: =SUMIF($H$7:$AB$7,J$61,$H21:$AB21) -> 4678 | K71: =SUMIF($H$7:$AB$7,K$61,$H21:$AB21) -> 6082 | L71: =SUMIF($H$7:$AB$7,L$61,$H21:$AB21) -> 7792 | M71: =Y21+SUMIF($H$7:$AB$7,M$61,$H21:$AB21) -> 8830
B72: Asia | I72: =SUMIF($H$7:$AB$7,I$61,$H22:$AB22) -> 14777 | J72: =SUMIF($H$7:$AB$7,J$61,$H22:$AB22) -> 18595 | K72: =SUMIF($H$7:$AB$7,K$61,$H22:$AB22) -> 20722 | L72: =SUMIF($H$7:$AB$7,L$61,$H22:$AB22) -> 23269 | M72: =Y22+SUMIF($H$7:$AB$7,M$61,$H22:$AB22) -> 22362
B73: EMEA | I73: =SUMIF($H$7:$AB$7,I$61,$H23:$AB23) -> 11362 | J73: =SUMIF($H$7:$AB$7,J$61,$H23:$AB23) -> 17344 | K73: =SUMIF($H$7:$AB$7,K$61,$H23:$AB23) -> 23293 | L73: =SUMIF($H$7:$AB$7,L$61,$H23:$AB23) -> 25538 | M73: =Y23+SUMIF($H$7:$AB$7,M$61,$H23:$AB23) -> 25786
B74: Total Revenue | I74: =SUMIF($H$7:$AB$7,I$61,$H24:$AB24) -> 569712 | J74: =SUMIF($H$7:$AB$7,J$61,$H24:$AB24) -> 669234 | K74: =SUMIF($H$7:$AB$7,K$61,$H24:$AB24) -> 732920 | L74: =SUMIF($H$7:$AB$7,L$61,$H24:$AB24) -> 776581 | M74: =Y24+SUMIF($H$7:$AB$7,M$61,$H24:$AB24) -> 780868
A76: # | B76: YoY Annual Growth Rate (in %)
B78: Revenue
B79: Instant Noodles | J79: =J63/I63-1 -> 0.19468461 | K79: =K63/J63-1 -> 0.074250895 | L79: =L63/K63-1 -> 0.047242136 | M79: =M63/L63-1 -> -0.00172941
B80: Nissin Food Products | J80: =J64/I64-1 -> 0.044695467 | K80: =K64/J64-1 -> 0.054576913 | L80: =L64/K64-1 -> 0.028248953 | M80: =M64/L64-1 -> 0.014657783
B81: Myojo Foods | J81: =J65/I65-1 -> 0.068329861 | K81: =K65/J65-1 -> 0.072549988 | L81: =L65/K65-1 -> 0.044304817 | M81: =M65/L65-1 -> 0.04749416
B82: The Americas | J82: =J66/I66-1 -> 0.60365756 | K82: =K66/J66-1 -> 0.14490042 | L82: =L66/K66-1 -> 0.051330668 | M82: =M66/L66-1 -> -0.039041783
B83: China | J83: =J67/I67-1 -> 0.2071632 | K83: =K67/J67-1 -> -0.0077645548 | L83: =L67/K67-1 -> 0.10567185 | M83: =M67/L67-1 -> 0.00021776707
B84: Chilled / Frozen Foods & Beverages | J84: =J68/I68-1 -> 0.073838201 | K84: =K68/J68-1 -> 0.09653719 | L84: =L68/K68-1 -> 0.064356228 | M84: =M68/L68-1 -> 0.024410941
B85: Confectionery / Snack | J85: =J69/I69-1 -> 0.072778896 | K85: =K69/J69-1 -> 0.14980758 | L85: =L69/K69-1 -> 0.085661605 | M85: =M69/L69-1 -> 0.025356165
B86: Others | J86: =J70/I70-1 -> 0.43472271 | K86: =K70/J70-1 -> 0.23339981 | L86: =L70/K70-1 -> 0.12978821 | M86: =M70/L70-1 -> 0.0066962314
B87: Domestic | J87: =J71/I71-1 -> 1.1547674 | K87: =K71/J71-1 -> 0.30012826 | L87: =L71/K71-1 -> 0.28115751 | M87: =M71/L71-1 -> 0.13321355
B88: Asia | J88: =J72/I72-1 -> 0.2583745 | K88: =K72/J72-1 -> 0.11438559 | L88: =L72/K72-1 -> 0.12291285 | M88: =M72/L72-1 -> -0.038978899
B89: EMEA | J89: =J73/I73-1 -> 0.52649181 | K89: =K73/J73-1 -> 0.34300046 | L89: =L73/K73-1 -> 0.096380887 | M89: =M73/L73-1 -> 0.0097110189
B90: Total Revenue | J90: =J74/I74-1 -> 0.17468826 | K90: =K74/J74-1 -> 0.095162529 | L90: =L74/K74-1 -> 0.059571304 | M90: =M74/L74-1 -> 0.0055203514
A93: # | B93: COGS & Revenue Schedule
B94: *Yellow box in column D is for the estimated annual growth in costs for these inputs
B95: *Table on right is for what % of total cost each input takes up for each revenue segment. If no info available about cost breakdown of each segment, just take average of inputs
G97: Annual Growth Portion
B98: Inputs | D98: Annual Growth % | G98: Instant Noodles
B99: Palm Oil | D99: -0.025 | G99: Nissin | H99: Myojo | I99: Americas | J99: China
B100: Wheat | D100: 0.025 | G100: 0.25 | H100: 0.25 | I100: 0.25 | J100: 0.25
B101: Packaging (plastic) | D101: 0.042 | G101: 0.25 | H101: 0.25 | I101: 0.25 | J101: 0.25
B102: Raw ingredients | D102: 0.05 | G102: 0.25 | H102: 0.25 | I102: 0.25 | J102: 0.25
B103: Input 5 | G103: 0.25 | H103: 0.25 | I103: 0.25 | J103: 0.25
B104: Input 6 | G104: 0 | H104: 0 | I104: 0 | J104: 0
G105: 0 | H105: 0 | I105: 0 | J105: 0
G106: =$D99*G100+$D100*G101+$D101*G102+$D102*G103+$D103*G104+$D104*G105 -> 0.023 | H106: =$D99*H100+$D100*H101+$D101*H102+$D102*H103+$D103*H104+$D104*H105 -> 0.023 | I106: =$D99*I100+$D100*I101+$D101*I102+$D102*I103+$D103*I104+$D104*I105 -> 0.023 | J106: =$D99*J100+$D100*J101+$D101*J102+$D102*J103+$D103*J104+$D104*J105 -> 0.023 | K106: Total Cost Increase (YoY %)
G107: =SUM(G100:G105) -> 1 | H107: =SUM(H100:H105) -> 1 | I107: =SUM(I100:I105) -> 1 | J107: =SUM(J100:J105) -> 1 | K107: Check Total %
B108: Growth Portion % | D108: =G106 -> 0.023
B109: Revenue Margin Portion % | D109: =E29 -> 0.65527909
B113: *% Growth = % Price Increase (Cost) + % Premium + % Customer growth
B114: *Fill in Yellow (Premiumisation products adjustment) and Light grey (customer increase %) | K114: Actual | L114: Actual | M114: Actual | N114: Actual | O114: Projected
J115: Period Start | K115: 45658 | L115: =K116+1 -> 45748 | M115: =L116+1 -> 45839 | N115: =M116+1 -> 45931 | O115: =N116+1 -> 46023 | P115: =O116+1 -> 46113 | Q115: =P116+1 -> 46204 | R115: =Q116+1 -> 46296 | S115: =R116+1 -> 46388 | ... AI115: =AH116+1 -> 47849
J116: Period End | K116: =EOMONTH(K115,2) -> 45747 | L116: =EOMONTH(L115,2) -> 45838 | M116: =EOMONTH(M115,2) -> 45930 | N116: =EOMONTH(N115,2) -> 46022 | O116: =EOMONTH(O115,2) -> 46112 | P116: =EOMONTH(P115,2) -> 46203 | Q116: =EOMONTH(Q115,2) -> 46295 | R116: =EOMONTH(R115,2) -> 46387 | ... AI116: =EOMONTH(AI115,2) -> 47938
J117: FY | K117: =IF(MONTH(K116)>3,YEAR(K116)+1,YEAR(K116)) -> 2025 | L117: =IF(MONTH(L116)>3,YEAR(L116)+1,YEAR(L116)) -> 2026 | M117: =IF(MONTH(M116)>3,YEAR(M116)+1,YEAR(M116)) -> 2026 | N117: =IF(MONTH(N116)>3,YEAR(N116)+1,YEAR(N116)) -> 2026 | O117: =IF(MONTH(O116)>3,YEAR(O116)+1,YEAR(O116)) -> 2026 | P117: =IF(MONTH(P116)>3,YEAR(P116)+1,YEAR(P116)) -> 2027 | Q117: =IF(MONTH(Q116)>3,YEAR(Q116)+1,YEAR(Q116)) -> 2027 | R117: =IF(MONTH(R116)>3,YEAR(R116)+1,YEAR(R116)) -> 2027 | ... AI117: =IF(MONTH(AI116)>3,YEAR(AI116)+1,YEAR(AI116)) -> 2031
...

Sheet Operating Model
B2: Nissin Foods Holdings Co Ltd
B3: (2897 JT)
F4: Actual or Forecast | G4: Actual | H4: Actual | I4: Actual | J4: Actual | K4: Actual | L4: Actual | M4: Actual | N4: Actual | O4: Actual | P4: Actual | Q4: Actual | R4: Actual | S4: Actual | T4: Actual | U4: Actual | V4: Actual | W4: Actual | X4: Actual | Y4: Actual | Z4: Actual | AA4: Actual | AB4: Forecast | AC4: Forecast | AD4: Forecast | AE4: Forecast | AF4: Forecast | AG4: Forecast | AH4: Forecast | AI4: Forecast | AJ4: Forecast | AK4: Forecast | AL4: Forecast | AM4: Forecast | AN4: Forecast | AO4: Forecast | AP4: Forecast | AQ4: Forecast | AR4: Forecast | AS4: Forecast | AT4: Forecast | AU4: Forecast | AV4: Forecast
F5: Period Start | G5: 44105 | H5: =G6+1 -> 44197 | I5: =H6+1 -> 44287 | J5: =I6+1 -> 44378 | K5: =J6+1 -> 44470 | L5: =K6+1 -> 44562 | M5: =L6+1 -> 44652 | N5: =M6+1 -> 44743 | O5: =N6+1 -> 44835 | ... AV5: =AU6+1 -> 47849
F6: Period End | G6: =EOMONTH(G5,2) -> 44196 | H6: =EOMONTH(H5,2) -> 44286 | I6: =EOMONTH(I5,2) -> 44377 | J6: =EOMONTH(J5,2) -> 44469 | K6: =EOMONTH(K5,2) -> 44561 | L6: =EOMONTH(L5,2) -> 44651 | M6: =EOMONTH(M5,2) -> 44742 | N6: =EOMONTH(N5,2) -> 44834 | ... AV6: =EOMONTH(AV5,2) -> 47938
F7: FY | G7: =IF(MONTH(G6)>3,YEAR(G6)+1,YEAR(G6)) -> 2021 | H7: =IF(MONTH(H6)>3,YEAR(H6)+1,YEAR(H6)) -> 2021 | I7: =IF(MONTH(I6)>3,YEAR(I6)+1,YEAR(I6)) -> 2022 | J7: =IF(MONTH(J6)>3,YEAR(J6)+1,YEAR(J6)) -> 2022 | K7: =IF(MONTH(K6)>3,YEAR(K6)+1,YEAR(K6)) -> 2022 | L7: =IF(MONTH(L6)>3,YEAR(L6)+1,YEAR(L6)) -> 2022 | M7: =IF(MONTH(M6)>3,YEAR(M6)+1,YEAR(M6)) -> 2023 | N7: =IF(MONTH(N6)>3,YEAR(N6)+1,YEAR(N6)) -> 2023 | ... AV7: =IF(MONTH(AV6)>3,YEAR(AV6)+1,YEAR(AV6)) -> 2031
B8: In Thousands of JPY | C8: Note | F8: Quarter | G8: =IF(MONTH(G5)=4,"Q1",IF(MONTH(G5)=7,"Q2",IF(MONTH(G5)=10,"Q3","Q4"))) -> Q3 | H8: =IF(MONTH(H5)=4,"Q1",IF(MONTH(H5)=7,"Q2",IF(MONTH(H5)=10,"Q3","Q4"))) -> Q4 | I8: =IF(MONTH(I5)=4,"Q1",IF(MONTH(I5)=7,"Q2",IF(MONTH(I5)=10,"Q3","Q4"))) -> Q1 | J8: =IF(MONTH(J5)=4,"Q1",IF(MONTH(J5)=7,"Q2",IF(MONTH(J5)=10,"Q3","Q4"))) -> Q2 | K8: =IF(MONTH(K5)=4,"Q1",IF(MONTH(K5)=7,"Q2",IF(MONTH(K5)=10,"Q3","Q4"))) -> Q3 | L8: =IF(MONTH(L5)=4,"Q1",IF(MONTH(L5)=7,"Q2",IF(MONTH(L5)=10,"Q3","Q4"))) -> Q4 | M8: =IF(MONTH(M5)=4,"Q1",IF(MONTH(M5)=7,"Q2",IF(MONTH(M5)=10,"Q3","Q4"))) -> Q1 | N8: =IF(MONTH(N5)=4,"Q1",IF(MONTH(N5)=7,"Q2",IF(MONTH(N5)=10,"Q3","Q4"))) -> Q2 | ... AV8: =IF(MONTH(AV5)=4,"Q1",IF(MONTH(AV5)=7,"Q2",IF(MONTH(AV5)=10,"Q3","Q4"))) -> Q4
F9: Days | G9: =_xlfn.DAYS(G6,G5)+1 -> 92 | H9: =_xlfn.DAYS(H6,H5)+1 -> 90 | I9: =_xlfn.DAYS(I6,I5)+1 -> 91 | J9: =_xlfn.DAYS(J6,J5)+1 -> 92 | K9: =_xlfn.DAYS(K6,K5)+1 -> 92 | L9: =_xlfn.DAYS(L6,L5)+1 -> 90 | M9: =_xlfn.DAYS(M6,M5)+1 -> 91 | N9: =_xlfn.DAYS(N6,N5)+1 -> 92 | ... AV9: =_xlfn.DAYS(AV6,AV5)+1 -> 90
A10: # | B10: Income Statement
B12: Revenue
B13: Instant Noodles | G13: =SUM(G14:G17) -> 96613 | H13: =SUM(H14:H17) -> 90658 | I13: =SUM(I14:I17) -> 88456 | J13: =SUM(J14:J17) -> 97060 | K13: =SUM(K14:K17) -> 104735 | L13: =SUM(L14:L17) -> 101254 | M13: =SUM(M14:M17) -> 102667 | N13: =SUM(N14:N17) -> 118232 | ... AV13: =SUM(AV14:AV17) -> 232432.67
B14: Nissin Food Products | C14: Revenue Schedule | G14: 57884 | H14: 50707 | I14: 46577 | J14: 51948 | K14: 59620 | L14: 52637 | M14: 47791 | N14: 54071 | O14: 65104 | P14: 53237 | Q14: 51448 | R14: 56355 | S14: 69302 | T14: 55116 | U14: 53363 | V14: 57768 | W14: 69008 | X14: 58642 | Y14: 52940 | Z14: 60064 | AA14: 70635 | AB14: =Drivers!O121 -> 63509.286 | AC14: =Drivers!P121 -> 57334.02 | AD14: =Drivers!Q121 -> 65049.312 | AE14: =Drivers!R121 -> 76497.705 | AF14: =Drivers!S121 -> 68780.557 | AG14: =Drivers!T121 -> 62092.744 | AH14: =Drivers!U121 -> 70448.405 | AI14: =Drivers!V121 -> 82847.015 | ... AV14: =Drivers!AI121 -> 94619.253
B15: Myojo Foods | C15: Revenue Schedule | G15: 9912 | H15: 9516 | I15: 9411 | J15: 9283 | K15: 9562 | L15: 9663 | M15: 9257 | N15: 10014 | O15: 10737 | P15: 10502 | Q15: 9963 | R15: 10388 | S15: 11582 | T15: 11516 | U15: 10751 | V15: 11498 | W15: 11862 | X15: 11263 | Y15: 11635 | Z15: 11543 | AA15: 13088 | AB15: =Drivers!O122 -> 12197.829 | AC15: =Drivers!P122 -> 12600.705 | AD15: =Drivers!Q122 -> 12501.069 | AE15: =Drivers!R122 -> 14174.304 | AF15: =Drivers!S122 -> 13210.249 | AG15: =Drivers!T122 -> 13646.564 | AH15: =Drivers!U122 -> 13538.658 | AI15: =Drivers!V122 -> 15350.771 | ... AV15: =Drivers!AI122 -> 18172.925
B16: The Americas | C16: Revenue Schedule | G16: 17767 | H16: 17590 | I16: 20221 | J16: 22196 | K16: 21412 | L16: 23497 | M16: 29899 | N16: 36119 | O16: 38719 | P16: 35304 | Q16: 34433 | R16: 42276 | S16: 42470 | T16: 41154 | U16: 41981 | V16: 42476 | W16: 41151 | X16: 42955 | Y16: 33380 | Z16: 41043 | AA16: 44604 | AB16: =Drivers!O123 -> 48668.015 | AC16: =Drivers!P123 -> 37819.54 | AD16: =Drivers!Q123 -> 46501.719 | AE16: =Drivers!R123 -> 50536.332 | AF16: =Drivers!S123 -> 55140.861 | AG16: =Drivers!T123 -> 42849.539 | AH16: =Drivers!U123 -> 52686.448 | AI16: =Drivers!V123 -> 57257.664 | ... AV16: =Drivers!AI123 -> 90864.279
B17: China | C17: Revenue Schedule | G17: 11050 | H17: 12845 | I17: 12247 | J17: 13633 | K17: 14141 | L17: 15457 | M17: 15720 | N17: 18028 | O17: 16389 | P17: 16834 | Q17: 14859 | R17: 18076 | S17: 15910 | T17: 17606 | U17: 16458 | V17: 18999 | W17: 18071 | X17: 19945 | Y17: 16689 | Z17: 19190 | AA17: 17665 | AB17: =Drivers!O124 -> 21201.535 | AC17: =Drivers!P124 -> 17740.407 | AD17: =Drivers!Q124 -> 20398.97 | AE17: =Drivers!R124 -> 18777.895 | AF17: =Drivers!S124 -> 22537.232 | AG17: =Drivers!T124 -> 18858.053 | AH17: =Drivers!U124 -> 21684.105 | AI17: =Drivers!V124 -> 19960.902 | ... AV17: =Drivers!AI124 -> 28776.212
B18: Chilled / Frozen Foods & Beverages | C18: Historical | G18: 19265 | H18: 19107 | I18: 20216 | J18: 20773 | K18: 20232 | L18: 19645 | M18: 20354 | N18: 21235 | O18: 22939 | P18: 22309 | Q18: 23213 | R18: 23559 | S18: 24769 | T18: 23679 | U18: 25462 | V18: 25474 | W18: 25828 | X18: 24584 | Y18: 26154 | Z18: 26096 | AA18: 26988 | AB18: =Drivers!O125 -> 26298.615 | AC18: =Drivers!P125 -> 27978.115 | AD18: =Drivers!Q125 -> 27916.07 | AE18: =Drivers!R125 -> 28870.283 | AF18: =Drivers!S125 -> 28132.817 | AG18: =Drivers!T125 -> 29929.454 | AH18: =Drivers!U125 -> 29863.081 | AI18: =Drivers!V125 -> 30883.846 | ... AV18: =Drivers!AI125 -> 36841.268
B19: Confectionery / Snack | C19: Historical | G19: 10433 | H19: 15931 | I19: 17063 | J19: 17740 | K19: 17222 | L19: 17006 | M19: 17561 | N19: 17647 | O19: 19754 | P19: 19093 | Q19: 20750 | R19: 20129 | S19: 22377 | T19: 21893 | U19: 23072 | V19: 22388 | W19: 24325 | X19: 22658 | Y19: 23743 | Z19: 23460 | AA19: 24926 | AB19: =Drivers!O126 -> 26969.336 | AC19: =Drivers!P126 -> 28260.788 | AD19: =Drivers!Q126 -> 27923.939 | AE19: =Drivers!R126 -> 29668.888 | AF19: =Drivers!S126 -> 32101.027 | AG19: =Drivers!T126 -> 33638.215 | AH19: =Drivers!U126 -> 33237.271 | AI19: =Drivers!V126 -> 35314.246 | ... AV19: =Drivers!AI126 -> 64433.783
B20: Others | G20: =SUM(G21:G23) -> 6412 | H20: =SUM(H21:H23) -> 6552 | I20: =SUM(I21:I23) -> 6719 | J20: =SUM(J21:J23) -> 7003 | K20: =SUM(K21:K23) -> 7565 | L20: =SUM(L21:L23) -> 7023 | M20: =SUM(M21:M23) -> 8677 | N20: =SUM(N21:N23) -> 10573 | ... AV20: =SUM(AV21:AV23) -> 51963.208
B21: Domestic | C21: Historical | G21: 6412 | H21: 6552 | I21: 498 | J21: 564 | K21: 589 | L21: 520 | M21: 701 | N21: 1526 | O21: 1169 | P21: 1282 | Q21: 1442 | R21: 1678 | S21: 1393 | T21: 1569 | U21: 1761 | V21: 2100 | W21: 1721 | X21: 2210 | Y21: 1907 | Z21: 2383 | AA21: 2330 | AB21: =Drivers!O127 -> 3294.5035 | AC21: =Drivers!P127 -> 2842.8137 | AD21: =Drivers!Q127 -> 3552.399 | AE21: =Drivers!R127 -> 3473.3906 | AF21: =Drivers!S127 -> 4911.2007 | AG21: =Drivers!T127 -> 4237.855 | AH21: =Drivers!U127 -> 5295.6521 | AI21: =Drivers!V127 -> 5177.8722 | ... AV21: =Drivers!AI127 -> 24253.727
B22: Asia | C22: Historical | I22: 3391 | J22: 3879 | K22: 3905 | L22: 3602 | M22: 4557 | N22: 4867 | O22: 4966 | P22: 4205 | Q22: 5201 | R22: 5244 | S22: 5196 | T22: 5081 | U22: 6005 | V22: 5891 | W22: 5682 | X22: 5691 | Y22: 5064 | Z22: 5656 | AA22: 5951 | AB22: =Drivers!O128 -> 6291.1503 | AC22: =Drivers!P128 -> 5598.0294 | AD22: =Drivers!Q128 -> 6252.4594 | AE22: =Drivers!R128 -> 6578.5689 | AF22: =Drivers!S128 -> 6954.5901 | AG22: =Drivers!T128 -> 6188.3754 | AH22: =Drivers!U128 -> 6911.819 | AI22: =Drivers!V128 -> 7272.3187 | ... AV22: =Drivers!AI128 -> 10385.74
B23: EMEA | C23: Historical | I23: 2830 | J23: 2560 | K23: 3071 | L23: 2901 | M23: 3419 | N23: 4180 | O23: 4732 | P23: 5013 | Q23: 5156 | R23: 6191 | S23: 5549 | T23: 6397 | U23: 6180 | V23: 6455 | W23: 6535 | X23: 6368 | Y23: 5515 | Z23: 6772 | AA23: 7131 | AB23: =Drivers!O129 -> 7523.8967 | AC23: =Drivers!P129 -> 6516.0632 | AD23: =Drivers!Q129 -> 8001.2294 | AE23: =Drivers!R129 -> 8425.3938 | AF23: =Drivers!S129 -> 8889.6077 | AG23: =Drivers!T129 -> 7698.8358 | AH23: =Drivers!U129 -> 9453.5841 | AI23: =Drivers!V129 -> 9954.7413 | ... AV23: =Drivers!AI129 -> 17323.741
B24: Total Revenue | G24: =SUM(G13,G18:G20) -> 132723 | H24: =SUM(H13,H18:H20) -> 132248 | I24: =SUM(I13,I18:I20) -> 132454 | J24: =SUM(J13,J18:J20) -> 142576 | K24: =SUM(K13,K18:K20) -> 149754 | L24: =SUM(L13,L18:L20) -> 144928 | M24: =SUM(M13,M18:M20) -> 149259 | N24: =SUM(N13,N18:N20) -> 167687 | ... AV24: =SUM(AV13,AV18:AV20) -> 385670.93
D25: Growth % | E25: Margin %
B26: Cost of Sales | C26: Cost Schedule | D26: =Drivers!D108 -> 0.023 | E26: =Drivers!D109 -> 0.65527909 | G26: -84730 | H26: -87484 | I26: -85725 | J26: -93381 | K26: -96905 | L26: -99207 | M26: -100150 | N26: -112100 | O26: -121274 | P26: -114646 | Q26: -108485 | R26: -117321 | S26: -125522 | T26: -122975 | U26: -117980 | V26: -124434 | W26: -132337 | X26: -128891 | Y26: -116570 | Z26: -128399 | AA26: -138740 | AB26: =Drivers!O132 -> -135001.89 | AC26: =Drivers!P132 -> -122739.06 | AD26: =Drivers!Q132 -> -135256.5 | AE26: =Drivers!R132 -> -146276.37 | AF26: =Drivers!S132 -> -144700.04 | AG26: =Drivers!T132 -> -132285.51 | AH26: =Drivers!U132 -> -145669.14 | AI26: =Drivers!V132 -> -157482.07 | ... AV26: =Drivers!AI132 -> -220936.52
B27: Gross Profit | G27: =SUM(G24:G24,G26) -> 47993 | H27: =SUM(H24:H24,H26) -> 44764 | I27: =SUM(I24:I24,I26) -> 46729 | J27: =SUM(J24:J24,J26) -> 49195 | K27: =SUM(K24:K24,K26) -> 52849 | L27: =SUM(L24:L24,L26) -> 45721 | M27: =SUM(M24:M24,M26) -> 49109 | N27: =SUM(N24:N24,N26) -> 55587 | ... AV27: =SUM(AV24:AV24,AV26) -> 164734.41
B30: Operating Expenses
B31: SG&A Expense | C31: SG&A Schedule | G31: -36072 | H31: -40102 | I31: -34857 | J31: -36324 | K31: -38115 | L31: -42221 | M31: -37081 | N31: -42732 | O31: -44378 | P31: -49632 | Q31: -40223 | R31: -46180 | S31: -51890 | T31: -58959 | U31: -48178 | V31: -51575 | W31: -53561 | X31: -55956 | Y31: -47460 | Z31: -54053 | AA31: -56125 | AB31: =Drivers!H195 -> -57345.895 | AC31: =Drivers!I195 -> -52230.489 | AD31: =Drivers!J195 -> -60146.918 | AE31: =Drivers!K195 -> -65360.71 | AF31: =Drivers!L195 -> -66368.792 | AG31: =Drivers!M195 -> -60434.41 | AH31: =Drivers!N195 -> -67047.455 | AI31: =Drivers!O195 -> -72811.362 | ... AV31: =Drivers!AB195 -> -106360.47
B32: Other Income | C32: Normalised | G32: 5104 | H32: 868 | I32: =0.46*(1000) -> 460 | J32: =0.452*(1000) -> 452 | K32: =0.283*(1000) -> 283 | L32: =0.791*(1000) -> 791 | M32: =0.55*(1000) -> 550 | N32: =0.307*(1000) -> 307 | O32: =0.425*(1000) -> 425 | P32: =0.839*(1000) -> 839 | Q32: =0.39*(1000) -> 390 | R32: =0.397*(1000) -> 397 | S32: =0.342*(1000) -> 342 | T32: =1.203*(1000) -> 1203 | U32: =0.252*(1000) -> 252 | V32: =0.275*(1000) -> 275 | W32: =0.467*(1000) -> 467 | X32: =0.836*(1000) -> 836 | Y32: 254 | Z32: 298 | AA32: 279 | AB32: =AVERAGE(H32,L32,P32,T32,X32) -> 907.4 | AC32: =AVERAGE(I32,M32,Q32,U32,Y32) -> 381.2 | AD32: =AVERAGE(J32,N32,R32,V32,Z32) -> 345.8 | AE32: =AVERAGE(K32,O32,S32,W32,AA32) -> 359.2 | AF32: =AVERAGE(L32,P32,T32,X32,AB32) -> 915.28 | AG32: =AVERAGE(M32,Q32,U32,Y32,AC32) -> 365.44 | AH32: =AVERAGE(N32,R32,V32,Z32,AD32) -> 324.56 | AI32: =AVERAGE(O32,S32,W32,AA32,AE32) -> 374.44 | ... AV32: =AVERAGE(AB32,AF32,AJ32,AN32,AR32) -> 927.00301
B33: Other Expense | C33: Normalised | G33: -436 | H33: -867 | I33: -198 | J33: -318 | K33: -352 | L33: -1145 | M33: -156 | N33: -507 | O33: -492 | P33: -582 | Q33: -409 | R33: -349 | S33: -701 | T33: -1928 | U33: -459 | V33: -231 | W33: -3035 | X33: -635 | Y33: -427 | Z33: -321 | AA33: -584 | AB33: =AVERAGE(H33,L33,P33,T33,X33) -> -1031.4 | AC33: =AVERAGE(I33,M33,Q33,U33,Y33) -> -329.8 | AD33: =AVERAGE(J33,N33,R33,V33,Z33) -> -345.2 | AE33: =AVERAGE(K33,O33,S33,W33,AA33) -> -1032.8 | AF33: =AVERAGE(L33,P33,T33,X33,AB33) -> -1064.28 | AG33: =AVERAGE(M33,Q33,U33,Y33,AC33) -> -356.16 | AH33: =AVERAGE(N33,R33,V33,Z33,AD33) -> -350.64 | AI33: =AVERAGE(O33,S33,W33,AA33,AE33) -> -1168.96 | ... AV33: =AVERAGE(AB33,AF33,AJ33,AN33,AR33) -> -1053.843
B34: Gain on investments accounted for using the equity method | C34: Historical | D34: =AVERAGE(X34/T34-1,Y34/U34-1,Z34/V34-1,AA34/W34-1) -> 0.022821813 | G34: 1533 | H34: 903 | I34: 1112 | J34: 579 | K34: 1083 | L34: 880 | M34: 832 | N34: 1116 | O34: 2880 | P34: 3170 | Q34: 3136 | R34: 3576 | S34: 2876 | T34: 3449 | U34: 3186 | V34: 2723 | W34: 3111 | X34: 4197 | Y34: 3017 | Z34: 2241 | AA34: 3436 | AB34: =X34*(1+$D$34) -> 4292.7832 | AC34: =Y34*(1+$D$34) -> 3085.8534 | AD34: =Z34*(1+$D$34) -> 2292.1437 | AE34: =AA34*(1+$D$34) -> 3514.4158 | AF34: =AB34*(1+$D$34) -> 4390.7522 | AG34: =AC34*(1+$D$34) -> 3156.2782 | AH34: =AD34*(1+$D$34) -> 2344.4546 | AI34: =AE34*(1+$D$34) -> 3594.6211 | ... AV34: =AR34*(1+$D$34) -> 4805.5031
B35: Total Operating Income | G35: =SUM(G27,G31:G34) -> 18122 | H35: =SUM(H27,H31:H34) -> 5566 | I35: =SUM(I27,I31:I34) -> 13246 | J35: =SUM(J27,J31:J34) -> 13584 | K35: =SUM(K27,K31:K34) -> 15748 | L35: =SUM(L27,L31:L34) -> 4026 | M35: =SUM(M27,M31:M34) -> 13254 | N35: =SUM(N27,N31:N34) -> 13771 | ... AV35: =SUM(AV27,AV31:AV34) -> 63052.603
B37: Finance Income | C37: Normalised | G37: 607 | H37: 262 | I37: =-0.895*(-1000) -> 895 | J37: =-0.403*(-1000) -> 403 | K37: =-1.131*(-1000) -> 1131 | L37: =-0.641*(-1000) -> 641 | M37: =-1.035*(-1000) -> 1035 | N37: =-0.616*(-1000) -> 616 | O37: =-1.023*(-1000) -> 1023 | P37: =-0.582*(-1000) -> 582 | Q37: =-1.213*(-1000) -> 1213 | R37: =-0.756*(-1000) -> 756 | S37: =-1.155*(-1000) -> 1155 | T37: =-1.212*(-1000) -> 1212 | U37: =1.383*(1000) -> 1383 | V37: =-0.518*(-1000) -> 518 | W37: =-1.477*(-1000) -> 1477 | X37: 873 | Y37: 1512 | Z37: 969 | AA37: 1763 | AB37: =AVERAGE(H37,L37,P37,T37,X37) -> 714 | AC37: =AVERAGE(I37,M37,Q37,U37,Y37) -> 1207.6 | AD37: =AVERAGE(J37,N37,R37,V37,Z37) -> 652.4 | AE37: =AVERAGE(K37,O37,S37,W37,AA37) -> 1309.8 | AF37: =AVERAGE(L37,P37,T37,X37,AB37) -> 804.4 | AG37: =AVERAGE(M37,Q37,U37,Y37,AC37) -> 1270.12 | AH37: =AVERAGE(N37,R37,V37,Z37,AD37) -> 702.28 | AI37: =AVERAGE(O37,S37,W37,AA37,AE37) -> 1345.56 | ... AV37: =AVERAGE(AB37,AF37,AJ37,AN37,AR37) -> 813.37824
B38: Finance Costs | C38: Normalised | G38: -201 | H38: -273 | I38: =0.141*(-1000) -> -141 | J38: =0.125*(-1000) -> -125 | K38: =0.129*(-1000) -> -129 | L38: =0.107*(-1000) -> -107 | M38: =0.301*(-1000) -> -301 | N38: =0.322*(-1000) -> -322 | O38: =0.175*(-1000) -> -175 | P38: =0.145*(-1000) -> -145 | Q38: =0.132*(-1000) -> -132 | R38: =0.264*(-1000) -> -264 | S38: =0.386*(-1000) -> -386 | T38: 0 | U38: -315 | V38: -1091 | W38: -415 | X38: 0 | Y38: -747 | Z38: -252 | AA38: -648 | AB38: =AVERAGE(H38,L38,P38,T38,X38) -> -105 | AC38: =AVERAGE(I38,M38,Q38,U38,Y38) -> -327.2 | AD38: =AVERAGE(J38,N38,R38,V38,Z38) -> -410.8 | AE38: =AVERAGE(K38,O38,S38,W38,AA38) -> -350.6 | AF38: =AVERAGE(L38,P38,T38,X38,AB38) -> -71.4 | AG38: =AVERAGE(M38,Q38,U38,Y38,AC38) -> -364.44 | AH38: =AVERAGE(N38,R38,V38,Z38,AD38) -> -467.96 | AI38: =AVERAGE(O38,S38,W38,AA38,AE38) -> -394.92 | ... AV38: =AVERAGE(AB38,AF38,AJ38,AN38,AR38) -> -69.31584
B39: Profit before Tax | G39: =SUM(G35,G37:G38) -> 18528 | H39: =SUM(H35,H37:H38) -> 5555 | I39: =SUM(I35,I37:I38) -> 14000 | J39: =SUM(J35,J37:J38) -> 13862 | K39: =SUM(K35,K37:K38) -> 16750 | L39: =SUM(L35,L37:L38) -> 4560 | M39: =SUM(M35,M37:M38) -> 13988 | N39: =SUM(N35,N37:N38) -> 14065 | ... AV39: =SUM(AV35,AV37:AV38) -> 63796.665
B41: Income Tax Expense | C41: Eff Tax Rate | D41: =SUM(G41:AA41)/SUM(G39:AA39) -> -0.22016411 | G41: -3719 | H41: -429 | I41: -5438 | J41: -3890 | K41: -2269 | L41: 669 | M41: -5770 | N41: -3472 | O41: -3849 | P41: 3521 | Q41: -6819 | R41: -5392 | S41: -6101 | T41: 115 | U41: -5958 | V41: -4981 | W41: -4771 | X41: -2195 | Y41: -4792 | Z41: -4420 | AA41: -5088 | AB41: =AB39*$D$41 -> -6249.1743 | AC41: =AC39*$D$41 -> -5666.7132 | AD41: =AD39*$D$41 -> -5554.3214 | AE41: =AE39*$D$41 -> -6421.2396 | AF41: =AF39*$D$41 -> -7609.7648 | AG41: =AG39*$D$41 -> -6713.0138 | AH41: =AH39*$D$41 -> -7255.5348 | AI41: =AI39*$D$41 -> -8251.0206 | ... AV41: =AV39*$D$41 -> -14045.736
B42: Profit after Tax | G42: =SUM(G39,G41) -> 14809 | H42: =SUM(H39,H41) -> 5126 | I42: =SUM(I39,I41) -> 8562 | J42: =SUM(J39,J41) -> 9972 | K42: =SUM(K39,K41) -> 14481 | L42: =SUM(L39,L41) -> 5229 | M42: =SUM(M39,M41) -> 8218 | N42: =SUM(N39,N41) -> 10593 | ... AV42: =SUM(AV39,AV41) -> 49750.929
B44: NCI claim of Profit | C44: Historical Proportion | D44: =SUM(G44:AA44)/SUM(G42:AA42) -> 0.070072416 | G44: 505 | H44: =2511-1934 -> 577 | I44: 671 | J44: 746 | K44: 860 | L44: 564 | M44: 691 | N44: 744 | O44: 1134 | P44: 1051 | Q44: 1110 | R44: 1144 | S44: 1284 | T44: 1009 | U44: 1093 | V44: 1083 | W44: 593 | X44: 1105 | Y44: 598 | Z44: 893 | AA44: 1172 | AB44: =$D$44*AB42 -> 1551.0523 | AC44: =$D$44*AC42 -> 1406.4847 | AD44: =$D$44*AD42 -> 1378.589 | AE44: =$D$44*AE42 -> 1593.7591 | AF44: =$D$44*AF42 -> 1888.7524 | AG44: =$D$44*AG42 -> 1666.1778 | AH44: =$D$44*AH42 -> 1800.8321 | AI44: =$D$44*AI42 -> 2047.9128 | ... AV44: =$D$44*AV42 -> 3486.1678
B45: Profit to owners of parent | G45: =G42-G44 -> 14304 | H45: =H42-H44 -> 4549 | I45: =I42-I44 -> 7891 | J45: =J42-J44 -> 9226 | K45: =K42-K44 -> 13621 | L45: =L42-L44 -> 4665 | M45: =M42-M44 -> 7527 | N45: =N42-N44 -> 9849 | ... AV45: =AV42-AV44 -> 46264.761
B47: Total OCI | C47: Normalised | G47: 270 | H47: =27347-16346 -> 11001 | I47: 1987 | J47: 1078 | K47: 565 | L47: 16426 | M47: 13858 | N47: 11983 | O47: -10314 | P47: -7599 | Q47: 18841 | R47: 10866 | S47: -12421 | T47: 8680 | U47: 8489 | V47: -13232 | W47: 6704 | X47: -7402 | Y47: -292 | Z47: 14852 | AA47: 9633 | AB47: =AVERAGE(H47,L47,P47,T47,X47) -> 4221.2 | AC47: =AVERAGE(I47,M47,Q47,U47,Y47) -> 8576.6 | AD47: =AVERAGE(J47,N47,R47,V47,Z47) -> 5109.4 | AE47: =AVERAGE(K47,O47,S47,W47,AA47) -> -1166.6 | AF47: =AVERAGE(L47,P47,T47,X47,AB47) -> 2865.24 | AG47: =AVERAGE(M47,Q47,U47,Y47,AC47) -> 9894.52 | AH47: =AVERAGE(N47,R47,V47,Z47,AD47) -> 5915.68 | AI47: =AVERAGE(O47,S47,W47,AA47,AE47) -> -1512.92 | ... AV47: =AVERAGE(AB47,AF47,AJ47,AN47,AR47) -> 1850.2481
B48: Total Comprehensive Income | G48: =SUM(G42,G47) -> 15079 | H48: =SUM(H42,H47) -> 16127 | I48: =SUM(I42,I47) -> 10549 | J48: =SUM(J42,J47) -> 11050 | K48: =SUM(K42,K47) -> 15046 | L48: =SUM(L42,L47) -> 21655 | M48: =SUM(M42,M47) -> 22076 | N48: =SUM(N42,N47) -> 22576 | ... AA48: =SUM(AA42,AA47) -> 27244 | AB48: =SUM(AB45,AB47) -> 24805.138 | AC48: =SUM(AC45,AC47) -> 27241.99 | AD48: =SUM(AD45,AD47) -> 23404.586 | AE48: =SUM(AE45,AE47) -> 19984.098 | AF48: =SUM(AF45,AF47) -> 27930.78 | AG48: =SUM(AG45,AG47) -> 32006.283 | AH48: =SUM(AH45,AH47) -> 29814.434 | AI48: =SUM(AI45,AI47) -> 25664.83 | ... AV48: =SUM(AV45,AV47) -> 48115.01
B50: NCI claim of Comprehensive Income | C50: Historical Proportion | D50: =SUM(G50:AA50)/SUM(G48:AA48) -> 0.077756305 | G50: 576 | H50: 1866 | I50: 592 | J50: 1003 | K50: 1577 | L50: 2298 | M50: 2604 | N50: 1166 | O50: -477 | P50: 1478 | Q50: 2451 | R50: 1809 | S50: 442 | T50: 2042 | U50: 2701 | V50: -1515 | W50: 2907 | X50: -350 | Y50: 137 | Z50: 1685 | AA50: 2207 | AB50: =$D$50*AB48 -> 1928.7559 | AC50: =$D$50*AC48 -> 2118.2365 | AD50: =$D$50*AD48 -> 1819.8541 | AE50: =$D$50*AE48 -> 1553.8896 | AF50: =$D$50*AF48 -> 2171.7942 | AG50: =$D$50*AG48 -> 2488.6903 | AH50: =$D$50*AH48 -> 2318.2602 | AI50: =$D$50*AI48 -> 1995.6024 | ... AV50: =$D$50*AV48 -> 3741.2454
B51: Comprehensive Income to owners of parent | G51: =G48-G50 -> 14503 | H51: =H48-H50 -> 14261 | I51: =I48-I50 -> 9957 | J51: =J48-J50 -> 10047 | K51: =K48-K50 -> 13469 | L51: =L48-L50 -> 19357 | M51: =M48-M50 -> 19472 | N51: =N48-N50 -> 21410 | ... AV51: =AV48-AV50 -> 44373.764
A55: # | B55: Statement of Cashflows
B57: Operating Activities
B58: Profit before tax | C58: P&L | G58: =G39 -> 18528 | H58: =H39 -> 5555 | I58: =I39 -> 14000 | J58: =J39 -> 13862 | K58: =K39 -> 16750 | L58: =L39 -> 4560 | M58: =M39 -> 13988 | N58: =N39 -> 14065 | ... AV58: =AV39 -> 63796.665
B59: Depreciation and Amortisation | C59: PPE Schedule | G59: 6486 | H59: 6483 | I59: 6892 | J59: 7122 | K59: 6983 | L59: 7243 | M59: 7189 | N59: 7314 | O59: 7320 | P59: 7375 | Q59: 7438 | R59: 7851 | S59: 7971 | T59: 8002 | U59: 8101 | V59: 8372 | W59: 8395 | X59: 8369 | Y59: 8220 | Z59: =16921-Y59 -> 8701 | AA59: 9176 | AB59: =Drivers!H170 -> 9531.8664 | AC59: =Drivers!I170 -> 8681.5986 | AD59: =Drivers!J170 -> 11858.412 | AE59: =Drivers!K170 -> 12886.35 | AF59: =Drivers!L170 -> 13085.101 | AG59: =Drivers!M170 -> 11915.093 | AH59: =Drivers!N170 -> 13218.904 | AI59: =Drivers!O170 -> 14355.301 | ... AV59: =Drivers!AB170 -> 20969.758
B60: Increase (decrease) in defined benefit liabilities | C60: Normalised | G60: 9 | H60: -2608 | I60: 20 | J60: 4 | K60: 192 | L60: -942 | M60: 125 | N60: 70 | O60: 44 | P60: -2849 | Q60: -17 | R60: -35 | S60: -184 | T60: 4741 | U60: -217 | V60: -17 | W60: 9 | X60: 513 | Y60: -111 | Z60: =-165-Y60 -> -54 | AA60: 112 | AB60: =AVERAGE(H60,L60,P60,T60,X60) -> -229 | AC60: =AVERAGE(I60,M60,Q60,U60,Y60) -> -40 | AD60: =AVERAGE(J60,N60,R60,V60,Z60) -> -6.4 | AE60: =AVERAGE(K60,O60,S60,W60,AA60) -> 34.6 | AF60: =AVERAGE(L60,P60,T60,X60,AB60) -> 246.8 | AG60: =AVERAGE(M60,Q60,U60,Y60,AC60) -> -52 | AH60: =AVERAGE(N60,R60,V60,Z60,AD60) -> -8.48 | AI60: =AVERAGE(O60,S60,W60,AA60,AE60) -> 3.12 | ... AV60: =AVERAGE(AB60,AF60,AJ60,AN60,AR60) -> 417.39168
B61: Finance income and costs | C61: None | G61: -484 | H61: -138 | I61: -802 | J61: -246 | K61: -882 | L61: -333 | M61: -674 | N61: -244 | O61: -936 | P61: -557 | Q61: -1166 | R61: -257 | S61: -1017 | T61: -680 | U61: -994 | V61: -44 | W61: -292 | X61: -1148 | Y61: -1164 | Z61: =-1758-Y61 -> -594 | AA61: -1123 | AB61: 0 | AC61: 0 | AD61: 0 | AE61: 0 | AF61: 0 | AG61: 0 | AH61: 0 | AI61: 0 | AJ61: 0 | AK61: 0 | AL61: 0 | AM61: 0 | AN61: 0 | AO61: 0 | AP61: 0 | AQ61: 0 | AR61: 0 | AS61: 0 | AT61: 0 | AU61: 0 | AV61: 0
B62: (Gain) loss on investments using equity method | C62: P&L | G62: =-G34 -> -1533 | H62: -5492 | I62: =-I34 -> -1112 | J62: =-J34 -> -579 | K62: =-K34 -> -1083 | L62: =-L34 -> -880 | M62: =-M34 -> -832 | N62: =-N34 -> -1116 | O62: =-O34 -> -2880 | P62: =-P34 -> -3170 | ... AV62: =-AV34 -> -4805.5031
B63: (Gain) loss on sales and retirement of PPE and others | C63: Normalised | G63: 37 | H63: 220 | I63: -12 | J63: 6 | K63: 108 | L63: 287 | M63: 1 | N63: 53 | O63: 61 | P63: 163 | Q63: 58 | R63: 40 | S63: 115 | T63: 166 | U63: 82 | V63: 43 | W63: 22 | X63: 234 | Y63: 27 | Z63: =97-Y63 -> 70 | AA63: 66 | AB63: =AVERAGE(H63,L63,P63,T63,X63) -> 214 | AC63: =AVERAGE(I63,M63,Q63,U63,Y63) -> 31.2 | AD63: =AVERAGE(J63,N63,R63,V63,Z63) -> 42.4 | AE63: =AVERAGE(K63,O63,S63,W63,AA63) -> 74.4 | AF63: =AVERAGE(L63,P63,T63,X63,AB63) -> 212.8 | AG63: =AVERAGE(M63,Q63,U63,Y63,AC63) -> 39.84 | AH63: =AVERAGE(N63,R63,V63,Z63,AD63) -> 49.68 | AI63: =AVERAGE(O63,S63,W63,AA63,AE63) -> 67.68 | ... AV63: =AVERAGE(AB63,AF63,AJ63,AN63,AR63) -> 208.49088
B64: (Increase) decrease in inventories | C64: WC Schedule | G64: 3172 | H64: -1981 | I64: -2854 | J64: 283 | K64: -1852 | L64: 289 | M64: -8240 | N64: -851 | O64: 570 | P64: 653 | Q64: -6094 | R64: -3169 | S64: 986 | T64: 4907 | U64: -6460 | V64: -3167 | W64: -2163 | X64: 4399 | Y64: -3646 | Z64: =-2237-Y64 -> 1409 | AA64: -743 | AB64: =Drivers!M145 -> 7848.2725 | AC64: =Drivers!N145 -> -27.101717 | AD64: =Drivers!O145 -> -5222.561 | AE64: =Drivers!P145 -> -2035.9444 | AF64: =Drivers!Q145 -> 2375.0534 | AG64: =Drivers!R145 -> -435.33336 | AH64: =Drivers!S145 -> -5570.3225 | AI64: =Drivers!T145 -> -2164.0827 | ... AV64: =Drivers!AG145 -> -1306.6543
B65: (Increase) decrease in trade and other receivables | C65: WC Schedule | G65: -10793 | H65: 11003 | I65: 5648 | J65: -7520 | K65: -9523 | L65: 5814 | M65: 9044 | N65: -16265 | O65: -15192 | P65: 12181 | Q65: 9710 | R65: -13637 | S65: -12799 | T65: 6158 | U65: 10586 | V65: -2047 | W65: -16983 | X65: 8602 | Y65: 10165 | Z65: =-1923-Y65 -> -12088 | AA65: -14375 | AB65: =Drivers!M146 -> -3203.3954 | AC65: =Drivers!N146 -> 20644.262 | AD65: =Drivers!O146 -> -3220.1778 | AE65: =Drivers!P146 -> -16680.965 | AF65: =Drivers!Q146 -> -16586.12 | AG65: =Drivers!R146 -> 23036.507 | AH65: =Drivers!S146 -> -3659.5791 | AI65: =Drivers!T146 -> -18493.467 | ... AV65: =Drivers!AG146 -> -30689.625
B66: Increase (decrease) in trade and other payables | C66: WC Schedule | G66: 12549 | H66: -3599 | I66: -4935 | J66: -2201 | K66: 13127 | L66: -5005 | M66: -2952 | N66: 2083 | O66: 16286 | P66: -4961 | Q66: -10948 | R66: 15052 | S66: 7261 | T66: 2990 | U66: -16892 | V66: -7917 | W66: 21142 | X66: -15241 | Y66: -7294 | Z66: 8918 | AA66: 9839 | AB66: =Drivers!M147 -> 14335.488 | AC66: =Drivers!N147 -> -15153.849 | AD66: =Drivers!O147 -> -1355.3086 | AE66: =Drivers!P147 -> 12482.475 | AF66: =Drivers!Q147 -> 16224.74 | AG66: =Drivers!R147 -> -15323.66 | AH66: =Drivers!S147 -> -1582.4313 | AI66: =Drivers!T147 -> 13380.758 | ... AV66: =Drivers!AG147 -> 35583.911
B67: Impairments | C67: Ignore | G67: 1 | H67: 68 | I67: 0 | J67: 0 | K67: 0 | L67: 431 | M67: 0 | N67: 0 | O67: 179 | P67: -2 | Q67: 0 | R67: 0 | S67: 160 | T67: 318 | U67: 0 | V67: 0 | W67: 2659 | X67: 182 | Y67: 0 | Z67: 0 | AA67: 39 | AB67: 0 | AC67: 0 | AD67: 0 | AE67: 0 | AF67: 0 | AG67: 0 | AH67: 0 | AI67: 0 | AJ67: 0 | AK67: 0 | AL67: 0 | AM67: 0 | AN67: 0 | AO67: 0 | AP67: 0 | AQ67: 0 | AR67: 0 | AS67: 0 | AT67: 0 | AU67: 0 | AV67: 0
B68: Other | C68: P&L | G68: -5025 | H68: 10312 | I68: -5596 | J68: 1329 | K68: 2102 | L68: 710 | M68: -1972 | N68: 5047 | O68: -602 | P68: 3716 | Q68: -1253 | R68: -730 | S68: 711 | T68: 4189 | U68: -5789 | V68: 1345 | W68: -131 | X68: 1627 | Y68: -3507 | Z68: 735 | AA68: 681 | AB68: =SUM(AA32:AA33) -> -305 | AC68: =SUM(AB32:AB33) -> -124 | AD68: =SUM(AC32:AC33) -> 51.4 | AE68: =SUM(AD32:AD33) -> 0.6 | AF68: =SUM(AE32:AE33) -> -673.6 | AG68: =SUM(AF32:AF33) -> -149 | AH68: =SUM(AG32:AG33) -> 9.28 | AI68: =SUM(AH32:AH33) -> -26.08 | ... AV68: =SUM(AU32:AU33) -> -753.87456
B69: Subtotal | G69: =SUM(G58:G68) -> 22947 | H69: =SUM(H58:H68) -> 19823 | I69: =SUM(I58:I68) -> 11249 | J69: =SUM(J58:J68) -> 12060 | K69: =SUM(K58:K68) -> 25922 | L69: =SUM(L58:L68) -> 12174 | M69: =SUM(M58:M68) -> 15677 | N69: =SUM(N58:N68) -> 10156 | ... AV69: =SUM(AV58:AV68) -> 83420.56
B70: Interest and dividends received | C70: P&L Finance Income | G70: 610 | H70: 267 | I70: 1274 | J70: 923 | K70: 3459 | L70: 326 | M70: 1479 | N70: 2061 | O70: 1067 | P70: 549 | Q70: 1943 | R70: 2176 | S70: 3152 | T70: 793 | U70: 1807 | V70: 2495 | W70: 3077 | X70: 805 | Y70: 2840 | Z70: 2171 | AA70: 4335 | AB70: =AB37 -> 714 | AC70: =AC37 -> 1207.6 | AD70: =AD37 -> 652.4 | AE70: =AE37 -> 1309.8 | AF70: =AF37 -> 804.4 | AG70: =AG37 -> 1270.12 | AH70: =AH37 -> 702.28 | AI70: =AI37 -> 1345.56 | ... AV70: =AV37 -> 813.37824
B71: Interest paid | C71: P&L Finance Costs | G71: -105 | H71: -136 | I71: -125 | J71: -122 | K71: -134 | L71: -106 | M71: -196 | N71: -173 | O71: -175 | P71: -161 | Q71: -118 | R71: -265 | S71: -247 | T71: -632 | U71: =U38 -> -315 | V71: -337 | W71: -1148 | X71: 446 | Y71: -592 | Z71: -729 | AA71: -830 | AB71: =AB38 -> -105 | AC71: =AC38 -> -327.2 | AD71: =AD38 -> -410.8 | AE71: =AE38 -> -350.6 | AF71: =AF38 -> -71.4 | AG71: =AG38 -> -364.44 | AH71: =AH38 -> -467.96 | AI71: =AI38 -> -394.92 | ... AV71: =AV38 -> -69.31584
B72: Income taxes paid | C72: Use eff tax rate | G72: -5196 | H72: 190 | I72: -8675 | J72: 437 | K72: -5072 | L72: -662 | M72: -7636 | N72: -404 | O72: -4434 | P72: -296 | Q72: -4129 | R72: 790 | S72: -4767 | T72: -5289 | U72: -7965 | V72: -2940 | W72: -6203 | X72: -1417 | Y72: -5285 | Z72: -1577 | AA72: -5528 | AB72: =AB41 -> -6249.1743 | AC72: =AC41 -> -5666.7132 | AD72: =AD41 -> -5554.3214 | AE72: =AE41 -> -6421.2396 | AF72: =AF41 -> -7609.7648 | AG72: =AG41 -> -6713.0138 | AH72: =AH41 -> -7255.5348 | AI72: =AI41 -> -8251.0206 | ... AV72: =AV41 -> -14045.736
B73: Cashflows from Operating Activities | G73: =SUM(G69:G72) -> 18256 | H73: =SUM(H69:H72) -> 20144 | I73: =SUM(I69:I72) -> 3723 | J73: =SUM(J69:J72) -> 13298 | K73: =SUM(K69:K72) -> 24175 | L73: =SUM(L69:L72) -> 11732 | M73: =SUM(M69:M72) -> 9324 | N73: =SUM(N69:N72) -> 11640 | ... AV73: =SUM(AV69:AV72) -> 70118.887
B75: Investing Activities
B76: Payment into time deposits | C76: Constant | G76: 2470 | H76: 5833 | I76: -1119 | J76: -468 | K76: -635 | L76: 216 | M76: 957 | N76: -144 | O76: -834 | P76: -294 | Q76: -497 | R76: -1677 | S76: -1562 | T76: -2647 | U76: -709 | V76: -903 | W76: -3129 | X76: -48 | Y76: -1805 | Z76: =-4916-Y76 -> -3111 | AA76: -3273 | AB76: =AA76 -> -3273 | AC76: =AB76 -> -3273 | AD76: =AC76 -> -3273 | AE76: =AD76 -> -3273 | AF76: =AE76 -> -3273 | AG76: =AF76 -> -3273 | AH76: =AG76 -> -3273 | AI76: =AH76 -> -3273 | ... AV76: =AU76 -> -3273
B77: Proceeds from redemption of time deposits | C77: 1 year later | G77: 0 | H77: 0 | I77: 0 | J77: 0 | K77: 0 | L77: 0 | M77: 0 | N77: 0 | O77: 0 | P77: 0 | Q77: 0 | R77: 0 | S77: 0 | T77: 0 | U77: 3113 | V77: 0 | W77: 0 | X77: 0 | Y77: 4064 | Z77: =11229-Y77 -> 7165 | AA77: 1977 | AB77: 0 | AC77: 0 | AD77: 0 | AE77: 0 | AF77: =-AB76 -> 3273 | AG77: =-AC76 -> 3273 | AH77: =-AD76 -> 3273 | AI77: =-AE76 -> 3273 | AJ77: =-AF76 -> 3273 | AK77: =-AG76 -> 3273 | AL77: =-AH76 -> 3273 | AM77: =-AI76 -> 3273 | ... AV77: =-AR76 -> 3273
B78: Payment for purchases of PPE and others | C78: PPE Schedule | G78: -7745 | H78: -6818 | I78: -7440 | J78: -5277 | K78: -5889 | L78: -5213 | M78: -5534 | N78: -5102 | O78: -6130 | P78: -8513 | Q78: -20983 | R78: -6191 | S78: -9321 | T78: -25593 | U78: -17942 | V78: -15833 | W78: -19192 | X78: -17755 | Y78: -20734 | Z78: -23481 | AA78: -23993 | AB78: =Drivers!H169 -> -26847.665 | AC78: =Drivers!I169 -> -24452.782 | AD78: =Drivers!J169 -> -12725.756 | AE78: =Drivers!K169 -> -13828.879 | AF78: =Drivers!L169 -> -14042.167 | AG78: =Drivers!M169 -> -12786.583 | AH78: =Drivers!N169 -> -14185.757 | AI78: =Drivers!O169 -> -15405.272 | ... AV78: =Drivers!AB169 -> -22503.521
B79: Proceeds from sales of PPE and others | C79: Normalised | G79: 204 | H79: 11 | I79: 367 | J79: 252 | K79: 0 | L79: 33 | M79: 24 | N79: 22 | O79: 6 | P79: 159 | Q79: 20 | R79: 11 | S79: 31 | T79: 25 | U79: 83 | V79: 11 | W79: 144 | X79: 0 | Y79: 12 | Z79: 30 | AA79: 37 | AB79: =AVERAGE(H79,L79,P79,T79,X79) -> 45.6 | AC79: =AVERAGE(I79,M79,Q79,U79,Y79) -> 101.2 | AD79: =AVERAGE(J79,N79,R79,V79,Z79) -> 65.2 | AE79: =AVERAGE(K79,O79,S79,W79,AA79) -> 43.6 | AF79: =AVERAGE(L79,P79,T79,X79,AB79) -> 52.52 | AG79: =AVERAGE(M79,Q79,U79,Y79,AC79) -> 48.04 | AH79: =AVERAGE(N79,R79,V79,Z79,AD79) -> 27.84 | AI79: =AVERAGE(O79,S79,W79,AA79,AE79) -> 52.32 | ... AV79: =AVERAGE(AB79,AF79,AJ79,AN79,AR79) -> 45.708672
B80: Payment for acquisition of intangible assets | C80: Normalised | G80: -175 | H80: -432 | I80: -360 | J80: -12 | K80: -56 | L80: -298 | M80: -126 | N80: -63 | O80: -67 | P80: -168 | Q80: -40 | R80: -174 | S80: -94 | T80: -170 | U80: -160 | V80: -183 | W80: -245 | X80: -203 | Y80: -60 | Z80: -74 | AA80: -112 | AB80: =AVERAGE(H80,L80,P80,T80,X80) -> -254.2 | AC80: =AVERAGE(I80,M80,Q80,U80,Y80) -> -149.2 | AD80: =AVERAGE(J80,N80,R80,V80,Z80) -> -101.2 | AE80: =AVERAGE(K80,O80,S80,W80,AA80) -> -114.8 | AF80: =AVERAGE(L80,P80,T80,X80,AB80) -> -218.64 | AG80: =AVERAGE(M80,Q80,U80,Y80,AC80) -> -107.04 | AH80: =AVERAGE(N80,R80,V80,Z80,AD80) -> -119.04 | AI80: =AVERAGE(O80,S80,W80,AA80,AE80) -> -126.56 | ... AV80: =AVERAGE(AB80,AF80,AJ80,AN80,AR80) -> -220.5991
B81: Payment for purchases of investments in securities | C81: Previous year | G81: -566 | H81: -66 | I81: -12 | J81: -635 | K81: -60 | L81: -597 | M81: -6488 | N81: -3536 | O81: -510 | P81: -20 | Q81: -52 | R81: -2 | S81: -82 | T81: -521 | U81: -15 | V81: -79 | W81: -19 | X81: -49 | Y81: -2 | Z81: -125 | AA81: -1249 | AB81: =X81 -> -49 | AC81: =Y81 -> -2 | AD81: =Z81 -> -125 | AE81: =AA81 -> -1249 | AF81: =AB81 -> -49 | AG81: =AC81 -> -2 | AH81: =AD81 -> -125 | AI81: =AE81 -> -1249 | ... AV81: =AR81 -> -49
B82: Proceeds from sales & redemption of investments in securities | C82: Previous year | G82: 303 | H82: 6140 | I82: 13420 | J82: 3953 | K82: 1010 | L82: 5993 | M82: 405 | N82: 581 | O82: 1162 | P82: 2149 | Q82: 0 | R82: 1836 | S82: 747 | T82: 6268 | U82: 8 | V82: 27 | W82: 4431 | X82: 436 | Y82: 12 | Z82: 130 | AA82: 224 | AB82: =X82 -> 436 | AC82: =Y82 -> 12 | AD82: =Z82 -> 130 | AE82: =AA82 -> 224 | AF82: =AB82 -> 436 | AG82: =AC82 -> 12 | AH82: =AD82 -> 130 | AI82: =AE82 -> 224 | ... AV82: =AR82 -> 436
B83: Other | C83: No other investments | G83: 1208 | H83: -2752 | I83: -648 | J83: 2 | K83: 2 | L83: 3 | M83: 0 | N83: 2 | O83: 2 | P83: 3 | Q83: 4 | R83: 3 | S83: -1254 | T83: 3 | U83: -1950 | V83: -3597 | W83: -3146 | X83: 194 | Y83: 0 | Z83: 0 | AA83: 0 | AB83: 0 | AC83: 0 | AD83: 0 | AE83: 0 | AF83: 0 | AG83: 0 | AH83: 0 | AI83: 0 | AJ83: 0 | AK83: 0 | AL83: 0 | AM83: 0 | AN83: 0 | AO83: 0 | AP83: 0 | AQ83: 0 | AR83: 0 | AS83: 0 | AT83: 0 | AU83: 0 | AV83: 0
B84: Cashflows from Investing Activities | G84: =SUM(G76:G83) -> -4301 | H84: =SUM(H76:H83) -> 1916 | I84: =SUM(I76:I83) -> 4208 | J84: =SUM(J76:J83) -> -2185 | K84: =SUM(K76:K83) -> -5628 | L84: =SUM(L76:L83) -> 137 | M84: =SUM(M76:M83) -> -10762 | N84: =SUM(N76:N83) -> -8240 | ... AV84: =SUM(AV76:AV83) -> -22291.411
B86: Financing Activities
B87: Net increase (decrease) in short-term borrowings | C87: Normalised | G87: -247 | H87: -22 | I87: -36 | J87: 192 | K87: -200 | L87: -8 | M87: 3077 | N87: 1678 | O87: -4002 | P87: -1354 | Q87: 8306 | R87: -248 | S87: -9011 | T87: 404 | U87: 22913 | V87: 23745 | W87: -29881 | X87: 1934 | Y87: -5930 | Z87: 583 | AA87: 13177 | AB87: =AVERAGE(H87,L87,P87,T87,X87) -> 190.8 | AC87: =AVERAGE(I87,M87,Q87,U87,Y87) -> 5666 | AD87: =AVERAGE(J87,N87,R87,V87,Z87) -> 5190 | AE87: =AVERAGE(K87,O87,S87,W87,AA87) -> -5983.4 | AF87: =AVERAGE(L87,P87,T87,X87,AB87) -> 233.36 | AG87: =AVERAGE(M87,Q87,U87,Y87,AC87) -> 6806.4 | AH87: =AVERAGE(N87,R87,V87,Z87,AD87) -> 6189.6 | AI87: =AVERAGE(O87,S87,W87,AA87,AE87) -> -7140.08 | ... AV87: =AVERAGE(AB87,AF87,AJ87,AN87,AR87) -> 392.8521
B88: Net increase (decrease) in commercial papers | C88: No new borrowings | G88: 0 | H88: 0 | I88: 0 | J88: 0 | K88: 0 | L88: 0 | M88: 0 | N88: 0 | O88: 0 | P88: 0 | Q88: 0 | R88: 0 | S88: 0 | T88: 0 | U88: 0 | V88: 0 | W88: 0 | X88: 0 | Y88: 40000 | Z88: -27000 | AA88: 15000 | AB88: 0 | AC88: 0 | AD88: 0 | AE88: 0 | AF88: 0 | AG88: 0 | AH88: 0 | AI88: 0 | AJ88: 0 | AK88: 0 | AL88: 0 | AM88: 0 | AN88: 0 | AO88: 0 | AP88: 0 | AQ88: 0 | AR88: 0 | AS88: 0 | AT88: 0 | AU88: 0 | AV88: 0
B89: Proceeds from long-term borrowings | C89: No new borrowings | G89: 2000 | H89: 131 | I89: 803 | J89: 0 | K89: 1111 | L89: 13 | M89: 0 | N89: 0 | O89: 0 | P89: 0 | Q89: 1019 | R89: 1065 | S89: 5252 | T89: 559 | U89: 0 | V89: 1925 | W89: 16399 | X89: 2164 | Y89: 1600 | Z89: 40000 | AA89: 2600 | AB89: 0 | AC89: 0 | AD89: 0 | AE89: 0 | AF89: 0 | AG89: 0 | AH89: 0 | AI89: 0 | AJ89: 0 | AK89: 0 | AL89: 0 | AM89: 0 | AN89: 0 | AO89: 0 | AP89: 0 | AQ89: 0 | AR89: 0 | AS89: 0 | AT89: 0 | AU89: 0 | AV89: 0
B90: Repayment of long-term borrowings | C90: Indefinite Rollover | G90: -805 | H90: -857 | I90: -608 | J90: -559 | K90: -530 | L90: -3739 | M90: -650 | N90: -3648 | O90: -634 | P90: -3743 | Q90: -646 | R90: -4659 | S90: -639 | T90: -3776 | U90: -559 | V90: -3573 | W90: -555 | X90: -3383 | Y90: -460 | Z90: -3664 | AA90: -5151 | AB90: 0 | AC90: 0 | AD90: 0 | AE90: 0 | AF90: 0 | AG90: 0 | AH90: 0 | AI90: 0 | AJ90: 0 | AK90: 0 | AL90: 0 | AM90: 0 | AN90: 0 | AO90: 0 | AP90: 0 | AQ90: 0 | AR90: 0 | AS90: 0 | AT90: 0 | AU90: 0 | AV90: 0
B91: Proceeds Of issuance Of Bonds | C91: No new issuances | G91: 0 | H91: 0 | I91: 0 | J91: 0 | K91: 0 | L91: 0 | M91: 0 | N91: 0 | O91: 0 | P91: 0 | Q91: 0 | R91: 0 | S91: 0 | T91: 0 | U91: 0 | V91: 0 | W91: 49829 | X91: 0 | Y91: 0 | Z91: 0 | AA91: 0 | AB91: 0 | AC91: 0 | AD91: 0 | AE91: 0 | AF91: 0 | AG91: 0 | AH91: 0 | AI91: 0 | AJ91: 0 | AK91: 0 | AL91: 0 | AM91: 0 | AN91: 0 | AO91: 0 | AP91: 0 | AQ91: 0 | AR91: 0 | AS91: 0 | AT91: 0 | AU91: 0 | AV91: 0
B92: Repayment of Lease Liabilities | C92: No Leases | G92: 0 | H92: -5119 | I92: 0 | J92: 0 | K92: 0 | L92: -5507 | M92: 0 | N92: 0 | O92: 0 | P92: -5479 | Q92: 0 | R92: 0 | S92: 0 | T92: -5467 | U92: 0 | V92: 0 | W92: 0 | X92: -5312 | Y92: 0 | Z92: 0 | AA92: 0 | AB92: 0 | AC92: 0 | AD92: 0 | AE92: 0 | AF92: 0 | AG92: 0 | AH92: 0 | AI92: 0 | AJ92: 0 | AK92: 0 | AL92: 0 | AM92: 0 | AN92: 0 | AO92: 0 | AP92: 0 | AQ92: 0 | AR92: 0 | AS92: 0 | AT92: 0 | AU92: 0 | AV92: 0
B93: Net increase in treasury shares | C93: No new buybacks | G93: -1 | H93: -1 | I93: -5245 | J93: -4047 | K93: -2735 | L93: -2637 | M93: -6295 | N93: -3512 | O93: -2 | P93: -3 | Q93: 0 | R93: -4 | S93: -4 | T93: -3 | U93: -11998 | V93: -8453 | W93: -11268 | X93: -8763 | Y93: -9045 | Z93: -11427 | AA93: -1 | AB93: 0 | AC93: 0 | AD93: 0 | AE93: 0 | AF93: 0 | AG93: 0 | AH93: 0 | AI93: 0 | AJ93: 0 | AK93: 0 | AL93: 0 | AM93: 0 | AN93: 0 | AO93: 0 | AP93: 0 | AQ93: 0 | AR93: 0 | AS93: 0 | AT93: 0 | AU93: 0 | AV93: 0
B94: Cash dividends paid | C94: None | G94: -5729 | H94: 0 | I94: -6771 | J94: 0 | K94: -7213 | L94: 0 | M94: -6146 | N94: 0 | O94: -6590 | P94: 0 | Q94: -7600 | R94: 0 | S94: -8109 | T94: 0 | U94: -12163 | V94: 0 | W94: -10470 | X94: 0 | Y94: -10284 | Z94: 0 | AA94: -10047 | AB94: 0 | AC94: 0 | AD94: 0 | AE94: 0 | AF94: 0 | AG94: 0 | AH94: 0 | AI94: 0 | AJ94: 0 | AK94: 0 | AL94: 0 | AM94: 0 | AN94: 0 | AO94: 0 | AP94: 0 | AQ94: 0 | AR94: 0 | AS94: 0 | AT94: 0 | AU94: 0 | AV94: 0
B95: Cash dividends paid to NCI shareholders | C95: None | G95: -11 | H95: -276 | I95: -3487 | J95: -210 | K95: -9 | L95: -386 | M95: -1572 | N95: -872 | O95: -37 | P95: 0 | Q95: -1095 | R95: 0 | S95: 0 | T95: 0 | U95: -1416 | V95: 0 | W95: 0 | X95: 0 | Y95: -1330 | Z95: 0 | AA95: 0 | AB95: 0 | AC95: 0 | AD95: 0 | AE95: 0 | AF95: 0 | AG95: 0 | AH95: 0 | AI95: 0 | AJ95: 0 | AK95: 0 | AL95: 0 | AM95: 0 | AN95: 0 | AO95: 0 | AP95: 0 | AQ95: 0 | AR95: 0 | AS95: 0 | AT95: 0 | AU95: 0 | AV95: 0
B96: Other Distributions to NCI shareholders | C96: No other distributions | G96: 0 | H96: 0 | I96: 0 | J96: 0 | K96: 178 | L96: 0 | M96: 0 | N96: 0 | O96: 354 | P96: 0 | Q96: 0 | R96: 0 | S96: 0 | T96: 0 | U96: 0 | V96: 0 | W96: 0 | X96: 0 | Y96: 0 | Z96: 0 | AA96: 0 | AB96: 0 | AC96: 0 | AD96: 0 | AE96: 0 | AF96: 0 | AG96: 0 | AH96: 0 | AI96: 0 | AJ96: 0 | AK96: 0 | AL96: 0 | AM96: 0 | AN96: 0 | AO96: 0 | AP96: 0 | AQ96: 0 | AR96: 0 | AS96: 0 | AT96: 0 | AU96: 0 | AV96: 0
B97: Other | C97: Plug from B/S | G97: -948 | H97: 3696 | I97: -1310 | J97: -2950 | K97: -2059 | L97: 3502 | M97: -2641 | N97: -1346 | O97: -8370 | P97: 4114 | Q97: -1347 | R97: -1956 | S97: -1365 | T97: 3004 | U97: -1446 | V97: -1227 | W97: -10942 | X97: 1909 | Y97: -999 | Z97: -1328 | AA97: -1363 | AB97: -3530.6523 | AC97: -3689.6847 | AD97: -1489.389 | AE97: -2758.1591 | AF97: -3630.4724 | AG97: -3999.2178 | AH97: -1749.5921 | AI97: -2922.3928 | AJ97: -3379.525 | AK97: -4308.0556 | AL97: -2004.462 | AM97: -4005.9929 | AN97: -3685.7795 | AO97: -4558.6617 | AP97: -1889.9512 | AQ97: -4900.6251 | AR97: -3542.3826 | AS97: -4809.6135 | AT97: -3243.769 | AU97: -5039.7988 | AV97: -4719.7824
B98: Cashflows from Financing Activities | G98: =SUM(G87:G97) -> -5741 | H98: =SUM(H87:H97) -> -2448 | I98: =SUM(I87:I97) -> -16654 | J98: =SUM(J87:J97) -> -7574 | K98: =SUM(K87:K97) -> -11457 | L98: =SUM(L87:L97) -> -8762 | M98: =SUM(M87:M97) -> -14227 | N98: =SUM(N87:N97) -> -7700 | ... AV98: =SUM(AV87:AV97) -> -4326.9303
B100: Effect of exchange rate changes on cash and cash equivalents | C100: Normalised | G100: 1405 | H100: 1885 | I100: 924 | J100: 123 | K100: 1370 | L100: 4275 | M100: 2016 | N100: -163 | O100: -3185 | P100: 1638 | Q100: 1964 | R100: 1691 | S100: -1884 | T100: 1612 | U100: 1147 | V100: -4798 | W100: 2205 | X100: -1935 | Y100: 921 | Z100: 1698 | AA100: 1927 | AB100: =AVERAGE(H100,L100,P100,T100,X100) -> 1495 | AC100: =AVERAGE(I100,M100,Q100,U100,Y100) -> 1394.4 | AD100: =AVERAGE(J100,N100,R100,V100,Z100) -> -289.8 | AE100: =AVERAGE(K100,O100,S100,W100,AA100) -> 86.6 | AF100: =AVERAGE(L100,P100,T100,X100,AB100) -> 1417 | AG100: =AVERAGE(M100,Q100,U100,Y100,AC100) -> 1488.48 | AH100: =AVERAGE(N100,R100,V100,Z100,AD100) -> -372.36 | AI100: =AVERAGE(O100,S100,W100,AA100,AE100) -> -170.08 | ... AV100: =AVERAGE(AB100,AF100,AJ100,AN100,AR100) -> 989.2272
B101: Net increase (decrease) in cash and cash equivalents | G101: =SUM(G73,G84,G98,G100) -> 9619 | H101: =SUM(H73,H84,H98,H100) -> 21497 | I101: =SUM(I73,I84,I98,I100) -> -7799 | J101: =SUM(J73,J84,J98,J100) -> 3662 | K101: =SUM(K73,K84,K98,K100) -> 8460 | L101: =SUM(L73,L84,L98,L100) -> 7382 | M101: =SUM(M73,M84,M98,M100) -> -13649 | N101: =SUM(N73,N84,N98,N100) -> -4463 | ... AV101: =SUM(AV73,AV84,AV98,AV100) -> 44489.772
B103: Cash and cash equivalents at the beginning of the period | G103: 59173 | H103: =G104 -> 68792 | I103: =H104 -> 90289 | J103: =I104 -> 82490 | K103: =J104 -> 86152 | L103: =K104 -> 94612 | M103: =L104 -> 101994 | N103: =M104 -> 88345 | O103: =N104 -> 83882 | ... T103: =S104 -> 94701 | U103: 96659 | V103: =U104 -> 77245 | W103: =V104 -> 76604 | X103: =W104 -> 85928 | Y103: 73036 | Z103: =Y104 -> 82238 | AA103: =Z104 -> 83045 | AB103: =AA104 -> 93710 | AC103: =AB104 -> 108566.32 | AD103: =AC104 -> 116051.79 | AE103: =AD104 -> 123203.84 | AF103: =AE104 -> 123301.56 | AG103: =AF104 -> 145681.47 | ... AV103: =AU104 -> 512286.22
B104: Cash and cash equivalents at the end of the period | G104: =SUM(G101,G103) -> 68792 | H104: =SUM(H101,H103) -> 90289 | I104: =SUM(I101,I103) -> 82490 | J104: =SUM(J101,J103) -> 86152 | K104: =SUM(K101,K103) -> 94612 | L104: =SUM(L101,L103) -> 101994 | M104: =SUM(M101,M103) -> 88345 | N104: =SUM(N101,N103) -> 83882 | ... AV104: =SUM(AV101,AV103) -> 556775.99
A108: # | B108: Balance Sheet
B110: Assets
B111: Current Assets
B112: Cash and Equivalents | C112: CF Statement | G112: =G104 -> 68792 | H112: =H104 -> 90289 | I112: =I104 -> 82490 | J112: =J104 -> 86152 | K112: =K104 -> 94612 | L112: =L104 -> 101994 | M112: =M104 -> 88345 | N112: =N104 -> 83882 | ... AV112: =AV104 -> 556775.99
B113: Accounts Receivable And Other Receivables | C113: WC Schedule | G113: 91511 | H113: 84837 | I113: 76286 | J113: 83738 | K113: 93222 | L113: 89600 | M113: 82290 | N113: 99864 | O113: 113040 | P113: 101483 | Q113: 94722 | R113: 109021 | S113: 120651 | T113: 116407 | U113: 107252 | V113: 105775 | W113: 125298 | X113: 115072 | Y113: 103765 | Z113: 118174 | AA113: 135291 | AB113: =Drivers!M141 -> 138494.4 | AC113: =Drivers!N141 -> 117850.13 | AD113: =Drivers!O141 -> 121070.31 | AE113: =Drivers!P141 -> 137751.28 | AF113: =Drivers!Q141 -> 154337.4 | AG113: =Drivers!R141 -> 131300.89 | AH113: =Drivers!S141 -> 134960.47 | AI113: =Drivers!T141 -> 153453.93 | ... AV113: =Drivers!AG141 -> 247336.1
B114: Inventories | C114: WC Schedule | G114: 38262 | H114: 40901 | I114: 44193 | J114: 43723 | K114: 45965 | L114: 47638 | M114: 57773 | N114: 59626 | O114: 57292 | P114: 57187 | Q114: 66079 | R114: 69344 | S114: 67438 | T114: 64060 | U114: 71625 | V114: 71173 | W114: 75789 | X114: 70536 | Y114: 74010 | Z114: 73824 | AA114: 76205 | AB114: =Drivers!M142 -> 68356.727 | AC114: =Drivers!N142 -> 68383.829 | AD114: =Drivers!O142 -> 73606.39 | AE114: =Drivers!P142 -> 75642.335 | AF114: =Drivers!Q142 -> 73267.281 | AG114: =Drivers!R142 -> 73702.615 | AH114: =Drivers!S142 -> 79272.937 | AI114: =Drivers!T142 -> 81437.02 | ... AV114: =Drivers!AG142 -> 111868.78
B115: Taxes Receivable | C115: None | G115: 838 | H115: 1629 | I115: 1908 | J115: 791 | K115: 1092 | L115: 590 | M115: 593 | N115: 793 | O115: 1364 | P115: 2092 | Q115: 3520 | R115: 456 | S115: 999 | T115: 1137 | U115: 1756 | V115: 1129 | W115: 1382 | X115: 465 | Y115: 359 | Z115: 247 | AA115: 78 | AB115: 0 | AC115: 0 | AD115: 0 | AE115: 0 | AF115: 0 | AG115: 0 | AH115: 0 | AI115: 0 | AJ115: 0 | AK115: 0 | AL115: 0 | AM115: 0 | AN115: 0 | AO115: 0 | AP115: 0 | AQ115: 0 | AR115: 0 | AS115: 0 | AT115: 0 | AU115: 0 | AV115: 0
B116: Short-Term Investments | C116: CF Statement | G116: 12185 | H116: 6890 | I116: 7962 | J116: 8409 | K116: 9791 | L116: 10271 | M116: 10257 | N116: 10156 | O116: 10202 | P116: 10770 | Q116: 11969 | R116: 14301 | S116: 15194 | T116: 18752 | U116: 17920 | V116: 18013 | W116: 17760 | X116: 16259 | Y116: 13993 | Z116: 10620 | AA116: 13626 | AB116: =AA116-AB81-AB82-AB76-AB77 -> 16512 | AC116: =AB116-AC81-AC82-AC76-AC77 -> 19775 | AD116: =AC116-AD81-AD82-AD76-AD77 -> 23043 | AE116: =AD116-AE81-AE82-AE76-AE77 -> 27341 | AF116: =AE116-AF81-AF82-AF76-AF77 -> 26954 | AG116: =AF116-AG81-AG82-AG76-AG77 -> 26944 | AH116: =AG116-AH81-AH82-AH76-AH77 -> 26939 | AI116: =AH116-AI81-AI82-AI76-AI77 -> 27964 | ... AV116: =AU116-AV81-AV82-AV76-AV77 -> 29446
B117: Other Current Assets | C117: Plug | G117: 6833 | H117: 4563 | I117: 13660 | J117: 10530 | K117: 9322 | L117: 9520 | M117: 11662 | N117: 8543 | O117: 9743 | P117: 7240 | Q117: 10053 | R117: 14531 | S117: 14802 | T117: 7832 | U117: 11918 | V117: 11724 | W117: 13382 | X117: 12973 | Y117: 12892 | Z117: 13078 | AA117: 15449 | AB117: =AA117+AB47 -> 19670.2 | AC117: =AB117+AC47 -> 28246.8 | AD117: =AC117+AD47 -> 33356.2 | AE117: =AD117+AE47 -> 32189.6 | AF117: =AE117+AF47 -> 35054.84 | AG117: =AF117+AG47 -> 44949.36 | AH117: =AG117+AH47 -> 50865.04 | AI117: =AH117+AI47 -> 49352.12 | ... AV117: =AU117+AV47 -> 96515.991
B118: Total Current Assets | G118: =SUM(G112:G117) -> 218421 | H118: =SUM(H112:H117) -> 229109 | I118: =SUM(I112:I117) -> 226499 | J118: =SUM(J112:J117) -> 233343 | K118: =SUM(K112:K117) -> 254004 | L118: =SUM(L112:L117) -> 259613 | M118: =SUM(M112:M117) -> 250920 | N118: =SUM(N112:N117) -> 262864 | ... AV118: =SUM(AV112:AV117) -> 1041942.9
B120: Non-Current Assets
B121: Property Plant & Equipment - Net | C121: PPE Schedule | G121: 253880 | H121: 257135 | I121: 258662 | J121: 256618 | K121: 255692 | L121: 260506 | M121: 262824 | N121: 264140 | O121: 258241 | P121: 265839 | Q121: 283808 | R121: 286501 | S121: 286027 | T121: 315573 | U121: 328098 | V121: 325214 | W121: 343027 | X121: 351790 | Y121: 361049 | Z121: 393797 | AA121: 410981 | AB121: =AA121-Drivers!H169-Drivers!H170 -> 428296.8 | AC121: =AB121-Drivers!I169-Drivers!I170 -> 444067.98 | AD121: =AC121-Drivers!J169-Drivers!J170 -> 444935.33 | AE121: =AD121-Drivers!K169-Drivers!K170 -> 445877.85 | AF121: =AE121-Drivers!L169-Drivers!L170 -> 446834.92 | AG121: =AF121-Drivers!M169-Drivers!M170 -> 447706.41 | AH121: =AG121-Drivers!N169-Drivers!N170 -> 448673.26 | AI121: =AH121-Drivers!O169-Drivers!O170 -> 449723.23 | ... AV121: =AU121-Drivers!AB169-Drivers!AB170 -> 509763.74
B122: Goodwill & Other Intangible Assets - Net | C122: CF Statement | G122: 12264 | H122: 12476 | I122: 12545 | J122: 12246 | K122: 12030 | L122: 12205 | M122: 12256 | N122: 12084 | O122: 11725 | P122: 11651 | Q122: 11535 | R122: 11478 | S122: 12086 | T122: 12207 | U122: 12234 | V122: 16167 | W122: 19165 | X122: 19245 | Y122: 19272 | Z122: 19656 | AA122: 20111 | AB122: =AA122-AB80 -> 20365.2 | AC122: =AB122-AC80 -> 20514.4 | AD122: =AC122-AD80 -> 20615.6 | AE122: =AD122-AE80 -> 20730.4 | AF122: =AE122-AF80 -> 20949.04 | AG122: =AF122-AG80 -> 21056.08 | AH122: =AG122-AH80 -> 21175.12 | AI122: =AH122-AI80 -> 21301.68 | ... AV122: =AU122-AV80 -> 23253.278
...

Sheet Valuation
B2: Nissin Foods Holdings Co Ltd
B3: (2897 JT)
B5: DCF Model
B7: Discounted Cash Flow | L7: Terminal Value
D8: Period Start | E8: 45931 | F8: 46023 | G8: =F9+1 -> 46113 | H8: =G9+1 -> 46478 | I8: =H9+1 -> 46844 | J8: =I9+1 -> 47209 | K8: =J9+1 -> 47574 | L8: 47574
D9: Period End | E9: ='Operating Model'!AA6 -> 46022 | F9: 46112 | G9: =EOMONTH(G8,11) -> 46477 | H9: =EOMONTH(H8,11) -> 46843 | I9: =EOMONTH(I8,11) -> 47208 | J9: =EOMONTH(J8,11) -> 47573 | K9: =EOMONTH(K8,11) -> 47938 | L9: 47938
D10: FY | E10: ='Operating Model'!AA7 -> 2026 | F10: 2026 | G10: =F10+1 -> 2027 | H10: =G10+1 -> 2028 | I10: =H10+1 -> 2029 | J10: =I10+1 -> 2030 | K10: =J10+1 -> 2031 | L10: 2031
D11: Year Frac. | F11: =YEARFRAC(F9,E9) -> 0.25 | G11: =YEARFRAC(G9,F9) -> 1 | H11: =YEARFRAC(H9,G9) -> 1 | I11: =YEARFRAC(I9,H9) -> 1 | J11: =YEARFRAC(J9,I9) -> 1 | K11: =YEARFRAC(K9,J9) -> 1 | L11: =K11 -> 1
B13: EBIT | F13: ='Operating Model'!AB35 -> 27775.165 | G13: =SUM('Operating Model'!AC35:AF35) -> 111882.24 | H13: =SUM('Operating Model'!AG35:AJ35) -> 140175.92 | I13: =SUM('Operating Model'!AK35:AN35) -> 170862.69 | J13: =SUM('Operating Model'!AO35:AR35) -> 197556.3 | K13: =SUM('Operating Model'!AS35:AV35) -> 222646.77
B14: Less: Tax paid in Cash | F14: =SUM('Operating Model'!AB72) -> -6249.1743 | G14: =SUM('Operating Model'!AC72:AF72) -> -25252.039 | H14: =SUM('Operating Model'!AG72:AJ72) -> -31492.133 | I14: =SUM('Operating Model'!AK72:AN72) -> -38272.495 | J14: =SUM('Operating Model'!AO72:AR72) -> -44123.91 | K14: =SUM('Operating Model'!AS72:AV72) -> -49666.753
B15: NOPAT | F15: =SUM(F13:F14) -> 21525.99 | G15: =SUM(G13:G14) -> 86630.199 | H15: =SUM(H13:H14) -> 108683.79 | I15: =SUM(I13:I14) -> 132590.19 | J15: =SUM(J13:J14) -> 153432.39 | K15: =SUM(K13:K14) -> 172980.02
B16: Add: D&A | F16: ='Operating Model'!AB59 -> 9531.8664 | G16: =SUM('Operating Model'!AC59:AF59) -> 46511.462 | H16: =SUM('Operating Model'!AG59:AJ59) -> 54117.816 | I16: =SUM('Operating Model'!AK59:AN59) -> 57469.346 | J16: =SUM('Operating Model'!AO59:AR59) -> 65224.509 | K16: =SUM('Operating Model'!AS59:AV59) -> 76800.275
B17: Less: CapEx | F17: ='Operating Model'!AB78 -> -26847.665 | G17: =SUM('Operating Model'!AC78:AF78) -> -65049.583 | H17: =SUM('Operating Model'!AG78:AJ78) -> -58076.082 | I17: =SUM('Operating Model'!AK78:AN78) -> -84906.214 | J17: =SUM('Operating Model'!AO78:AR78) -> -91140.901 | K17: =SUM('Operating Model'!AS78:AV78) -> -82417.574
B18: Add: Cash from sale of PPE | F18: ='Operating Model'!AB79 -> 45.6 | G18: =SUM('Operating Model'!AC79:AF79) -> 262.52 | H18: =SUM('Operating Model'!AG79:AJ79) -> 184.624 | I18: =SUM('Operating Model'!AK79:AN79) -> 179.3488 | J18: =SUM('Operating Model'!AO79:AR79) -> 197.81856 | K18: =SUM('Operating Model'!AS79:AV79) -> 189.78227
B19: Less: Change in NCWC | F19: =SUM('Operating Model'!AB64:AB66) -> 18980.365 | G19: =SUM('Operating Model'!AC64:AF66) -> -8555.4961 | H19: =SUM('Operating Model'!AG64:AJ66) -> -7703.5271 | I19: =SUM('Operating Model'!AK64:AN66) -> -9044.3213 | J19: =SUM('Operating Model'!AO64:AR66) -> -9003.0248 | K19: =SUM('Operating Model'!AS64:AV66) -> -9961.2984
B20: Unlevered FCFF | F20: =SUM(F15:F19) -> 23236.157 | G20: =SUM(G15:G19) -> 59799.101 | H20: =SUM(H15:H19) -> 97206.618 | I20: =SUM(I15:I19) -> 96288.35 | J20: =SUM(J15:J19) -> 118710.79 | K20: =SUM(K15:K19) -> 157591.2 | L20: =K20*(1+0.035)/(D55-0.035) -> 24819281
B22: Intrinsic Value
B23: Enterprise Value | D23: =XNPV(D55,F20:L20,F9:L9) -> 20728760
B24: Add: Cash | D24: ='Operating Model'!AA112 -> 93710
B25: Less: Debt | D25: =-D43*1000 -> -135500
B26: Equity Value | D26: =SUM(D23:D25) -> 20686970
B27: Shares Outstanding (thousands) | D27: =10527344/1000 -> 10527.344
B28: Equity Value / Share | D28: =D26/D27 -> 1965.0702
B30: Bottom up Beta
B31: Company name | D31: 2Y Equity Beta | G31: Mkt cap | H31: D/E | I31: Marginal Tax Rate | K31: Asset Beta
B32: Ajinomoto | D32: 0.867 | G32: 3534.5 | H32: ='Relative Valuation'!AO11 -> 43.95 | I32: 0.22 | K32: =D32/(1+(1-I32)*H32) -> 0.024574133
B33: Kikkoman | D33: 0.776 | G33: 1467.7 | H33: ='Relative Valuation'!AO13 -> -10.47 | I33: 0.22 | K33: =D33/(1+(1-I33)*H33) -> -0.10828008
B34: Calbee | D34: 0.548 | G34: 405.8 | H34: ='Relative Valuation'!AO15 -> 7.94 | I34: 0.22 | K34: =D34/(1+(1-I34)*H34) -> 0.076183062
B35: Nisshin Seifun Group | D35: 0.582 | G35: 611.7 | H35: ='Relative Valuation'!AO17 -> -4.99 | I35: 0.22 | K35: =D35/(1+(1-I35)*H35) -> -0.2012309
B36: Ezaki Glico | D36: 0.516 | G36: 394 | H36: ='Relative Valuation'!AO19 -> -19.15 | I36: 0.22 | K36: =D36/(1+(1-I36)*H36) -> -0.03702375
B37: House Foods Group | D37: 0.487 | G37: 305.4 | H37: ='Relative Valuation'!AO21 -> -20.1 | I37: 0.22 | K37: =D37/(1+(1-I37)*H37) -> -0.033178907
B38: Average Beta | K38: =AVERAGE(K32:K37) -> -0.046492739
B40: WACC
G41: Source
B42: Marginal Tax rate | D42: 0.22 | G42: Bloomberg
B43: Total Debt | D43: =42.5+93 -> 135.5
B44: Mkt Cap | D44: ='Relative Valuation'!G5 -> 951.7
B45: Mkt D/E Ratio | D45: ='Relative Valuation'!AO5 -> 15.22
B46: Equity Beta | D46: ='Relative Valuation'!AE5 -> 0.579
B48: Market Risk Prem | D48: 0.04959
B49: Risk free rate | D49: 0.0165
B50: Cost of equity | D50: =D49+D46*D48 -> 0.04521261
B52: Cost of debt | D52: =D53/(1-D42) -> 0.020512821
B53: Cost of debt (after tax) | D53: 0.016
B55: WACC | D55: =(D43/(D43+D44))*D53+(D44/(D44+D43))*D50 -> 0.041571782

Sheet Relative Valuation
G2: Market Valuation | J2: LTM Financial Statistics | O2: LTM Profitability Margins | T2: Growth Rates | AE2: General | AG2: Return On Investment | AL2: LTM Leverage Ratios | AQ2: LTM Coverage Ratios | AU2: Enterprise Value | BJ2: Price / | BQ2: EV/EBITDA | CA2: P/E | CG2: PEG | CJ2: FCF Yield
E3: In Billions | T3: Sales | V3: EBITDA | Y3: EPS | BQ3: EV/EBITDA | CA3: P/E | CG3: PEG | CJ3: FCF Yield
B4: Company | E4: Ticker | F4: Currency | G4: Market Cap | H4: Enterprise Value | J4: Sales | K4: Gross Profit | L4: EBITDA (adj.) | M4: Net Income | O4: Gross Profit (%) | P4: EBITDA (%) | Q4: EBIT(%) | R4: Net Income (%) | T4: Hist. 1 year | U4: Est 1-year | V4: Hist 1. Year | W4: Est 1-year | Y4: Current | Z4: Hist 1-year. | AA4: Est. 1-year | AB4: Est. LT | AE4: 2 yr Regressional Beta | AG4: ROIC | AH4: ROE | AI4: ROA | AJ4: Implied Div. Yield | AL4: Debt/Total Assets | AM4: Debt/EBITDA | AN4: Net Debt / EBITDA | AO4: Net Debt/Equity | AQ4: EBITDA/Int. Exp. | AV4: LTM Sales | AW4: 2026E Sales | AX4: 2027E Sales | AZ4: LTM EBITDA | BA4: 2026E EBITDA | BB4: 2027E EBITDA | BD4: LTM EBIT | BE4: 2026E EBIT | BF4: 2027E EBIT | BH4: LTM EBITDA MARGIN | BJ4: LTM EPS | BK4: 2026E EPS | BL4: 2027E EPS | BN4: LT EPS GROWTH | BQ4: Current | BR4: 2026E | BS4: 2027E | BU4: 2026E EBITDA Margin | BV4: LTM Debt/ EBITDA | BW4: LTM Int Exp / EBITDA | BX4: EV/Sales | BY4: EV/EBIT | CA4: Current | CB4: 2026E | CC4: 2027E | CE4: LT EPS Growth | CG4: 2-Year Forward PEG | CH4: Dividend Yield | CJ4: 2026E
B5: NISSIN | E5: 2897 JT | F5: JPY | G5: 951.7 | H5: 1072 | J5: 780.9 | K5: 268.3 | L5: 89.5 | M5: 51 | O5: =K5/J5 -> 0.34357792 | P5: =L5/J5 -> 0.11461135 | Q5: =BD5/J5 -> 0.070431553 | R5: =M5/J5 -> 0.065309259 | T5: 732.9 | U5: 790.5 | V5: 92.4 | W5: 100.5 | Y5: 174.92 | Z5: 178.99 | AA5: 159.76 | AB5: 177.71 | AE5: 0.579 | AG5: 0.0611 | AH5: 0.1046 | AI5: 0.0555 | AJ5: =CH5 -> 0.0219 | AL5: 0.1596 | AM5: 2.11 | AN5: 0.91 | AO5: 15.22 | AQ5: 75.49 | AV5: 780.9 | AW5: 790.5 | AX5: 826.6 | AZ5: 89.5 | BA5: 100.5 | BB5: 110.3 | BD5: 55 | BE5: 64.8 | BF5: 70.9 | BH5: =AZ5/AV5 -> 0.11461135 | BJ5: =Y5 -> 174.92 | BK5: =AA5 -> 159.76 | BL5: =AB5 -> 177.71 | BN5: =(BL5/BJ5)-1 -> 0.015950149 | BQ5: 11.98 | BR5: 10.67 | BS5: 9.72 | BU5: =BA5/AW5 -> 0.12713472 | BV5: =AM5 -> 2.11 | BW5: =1/AQ5 -> 0.013246788 | BX5: =H5/AV5 -> 1.372775 | BY5: =H5/BD5 -> 19.490909 | CA5: 18.36 | CB5: 20.02 | CC5: 18 | CE5: =BN5 -> 0.015950149 | CG5: =CC5/1.6 -> 11.25 | CH5: 0.0219 | CJ5: -1.35
B6: Values | Y6: -0.0087 | Z6: -1.17857 | AA6: -0.45 | AB6: -0.26833 | AN6: =AN5*L5 -> 81.445
Z7: -1.17857 | AA7: -0.45 | AB7: -0.26833
B8: Tier 1: Core Japan Packaged Food Peers | AE8: Tier 1: Core Japan Packaged Food Peers | AU8: Tier 1: Core Japan Packaged Food Peers | BP8: Tier 1: Core Japan Packaged Food Peers
B11: Ajinomoto | E11: 2802 JT | F11: JPY | G11: 3534.5 | H11: 3970.4 | J11: 1543.7 | K11: 574.1 | L11: 241.1 | M11: 110.9 | O11: =K11/$J$11 -> 0.37189868 | P11: =L11/$J$11 -> 0.1561832 | Q11: =BD11/J11 -> 0.099501198 | R11: =M11/J11 -> 0.071840383 | T11: 1439.2 | U11: 1567.6 | V11: 214.3 | W11: 269.5 | Y11: 113.12 | Z11: 79.76 | AA11: 122.6 | AB11: 138.98 | AE11: 0.867 | AG11: 0.061 | AH11: 0.1047 | AI11: 0.044 | AJ11: 0.0122 | AL11: 0.2882 | AM11: 2.33 | AN11: 1.49 | AO11: 43.95 | AQ11: 27.17 | AV11: 1543.7 | AW11: 1567.6 | AX11: 1655.9 | AZ11: 241.1 | BA11: 269.5 | BB11: 294.4 | BD11: 153.6 | BE11: 181.5 | BF11: 202.3 | BH11: =AZ11/AV11 -> 0.1561832 | BJ11: 79.66 | BK11: 121.69 | BL11: 138.47 | BN11: =(BL11/BJ11)-1 -> 0.73826262 | BQ11: =H11/AZ11 -> 16.467856 | BR11: 14.73 | BS11: 13.49 | BU11: =BA11/AW11 -> 0.17191886 | BV11: =AN11 -> 1.49 | BW11: =1/AQ11 -> 0.0368053 | BX11: =H11/J11 -> 2.5720023 | BY11: =H11/BD11 -> 25.848958 | CA11: 45.38 | CB11: 29.49 | CC11: 26.01 | CE11: =BN11 -> 0.73826262 | CG11: =CC11/78.83 -> 0.32995053 | CH11: 0.0122 | CJ11: 3.37
B13: Kikkoman | E13: 2801 JT | F13: JPY | G13: 1467.7 | H13: 1417.3 | J13: 726.3 | K13: 244.4 | L13: 102.2 | M13: 60.8 | O13: =K13/J13 -> 0.33650007 | P13: =L13/J13 -> 0.1407132 | Q13: =BD13/J13 -> 0.10395154 | R13: =M13/J13 -> 0.083711965 | T13: 660.8 | U13: 732.9 | V13: 94.1 | W13: 104.4 | Y13: 64.92 | Z13: 60.5 | AA13: 65.01 | AB13: 68.27 | AE13: 0.776 | AG13: 0.0792 | AH13: 0.1092 | AI13: 0.0539 | AJ13: 0.0165 | AL13: 0.0869 | AM13: 0.59 | AN13: -0.57 | AO13: -10.47 | AQ13: 60.27 | AV13: =J11 -> 1543.7 | AW13: =U13 -> 732.9 | AX13: 773.5 | AZ13: =L13 -> 102.2 | BA13: =W13 -> 104.4 | BB13: 112.2 | BD13: 75.5 | BE13: 75.9 | BF13: 80 | BH13: =AZ13/AV13 -> 0.066204573 | BJ13: =Y13 -> 64.92 | BK13: =AA13 -> 65.01 | BL13: =AB13 -> 68.27 | BN13: =(BL13/BJ13)-1 -> 0.051601972 | BQ13: =H13/AZ13 -> 13.867906 | BR13: 13.57 | BS13: 12.64 | BU13: =BA13/AW13 -> 0.14244781 | BV13: =AN13 -> -0.57 | BW13: =1/AQ13 -> 0.016592003 | BX13: =H13/J13 -> 1.9513975 | BY13: =H13/BD13 -> 18.772185 | CA13: 23.86 | CB13: 23.29 | CC13: 22.18 | CE13: =BN13 -> 0.051601972 | CG13: =CC13/5.16 -> 4.2984496 | CH13: 0.0165 | CJ13: - | CS13: EV/EBITDA
CS14: FY | CU14: EBITDA | CW14: Range | CY14: 25th | CZ14: Diff | DA14: 75th | DB14: Enterprise Value | DE14: Debt | DF14: Equity Value | DI14: Shares outstanding | DK14: Low | DL14: Diff | DM14: High | DN14: Mean
B15: Calbee | E15: 2229 JT | F15: JPY | G15: 405.8 | H15: 434.2 | J15: 335.5 | K15: 108.4 | L15: 40.7 | M15: 16.8 | O15: =K15/J15 -> 0.32309985 | P15: =L15/J15 -> 0.12131148 | Q15: =BD15/J15 -> 0.070938897 | R15: =M15/J15 -> 0.050074516 | T15: 303 | U15: 337.3 | V15: 40 | W15: 42.5 | Y15: 135.35 | Z15: 163.75 | AA15: 141.86 | AB15: 160.08 | AE15: 0.548 | AG15: 0.0654 | AH15: 0.082 | AI15: 0.0522 | AJ15: =CH15 -> 0.0191 | AL15: 0.1145 | AM15: 1.28 | AN15: 0.42 | AO15: 7.94 | AQ15: 121.46 | AV15: =J15 -> 335.5 | AW15: =U15 -> 337.3 | AX15: 352.3 | AZ15: =L15 -> 40.7 | BA15: =W15 -> 42.5 | BB15: 45.9 | BD15: 23.8 | BE15: 26 | BF15: 29 | BH15: =AZ15/AV15 -> 0.12131148 | BJ15: =Y15 -> 135.35 | BK15: =AA15 -> 141.86 | BL15: =AB15 -> 160.08 | BN15: =(BL15/BJ15)-1 -> 0.18271149 | BQ15: =H15/AZ15 -> 10.668305 | BR15: 10.21 | BS15: 9.46 | BU15: =BA15/AW15 -> 0.12600059 | BV15: =AN15 -> 0.42 | BW15: =1/AQ15 -> 0.0082331632 | BX15: =H15/J15 -> 1.2941878 | BY15: =H15/BD15 -> 18.243697 | CA15: 23.35 | CB15: 21.36 | CC15: 18.93 | CE15: =BN15 -> 0.18271149 | CG15: =CC15/18.27 -> 1.0361248 | CH15: 0.0191 | CJ15: 2.65 | CS15: LTM Tier 1 | CU15: =AZ5 -> 89.5 | CW15: 9.18x-13.61x | CY15: 9.18 | CZ15: =DA15-CY15 -> 4.43 | DA15: 13.61 | DB15: =CU15*CY15 -> 821.61 | DC15: =CU15*CZ15 -> 396.485 | DD15: =CU15*DA15 -> 1218.095 | DE15: =AN6 -> 81.445 | DF15: =DB15-DE15 -> 740.165 | DG15: =DC15-DE15 -> 315.04 | DH15: =DD15-DE15 -> 1136.65 | DI15: 0.303 | DK15: =DF15/DI15 -> 2442.7888 | DL15: =DG15/DI15 -> 1039.736 | DM15: =DH15/DI15 -> 3751.3201 | DN15: =(DK15+DM15)/2 -> 3097.0545
CS16: 2026E Tier 1 | CU16: =BA5 -> 100.5 | CW16: 8.56x-13.15x | CY16: 8.56 | CZ16: =DA16-CY16 -> 4.59 | DA16: 13.15 | DB16: =CU16*CY16 -> 860.28 | DC16: =CU16*CZ16 -> 461.295 | DD16: =CU16*DA16 -> 1321.575 | DE16: 81.445 | DF16: =DB16-DE16 -> 778.835 | DG16: =DC16-DE16 -> 379.85 | DH16: =DD16-DE16 -> 1240.13 | DI16: 0.303 | DK16: =DF16/DI16 -> 2570.4125 | DL16: =DG16/DI16 -> 1253.6304 | DM16: =DH16/DI16 -> 4092.8383 | DN16: =(DK16+DM16)/2 -> 3331.6254
B17: Nisshin Seifun Group | E17: 2002 JT | F17: JPY | G17: 611.7 | H17: 604.7 | J17: 858 | K17: 191 | L17: 71.4 | M17: 29.1 | O17: =K17/J17 -> 0.22261072 | P17: =L17/J17 -> 0.083216783 | Q17: =BD17/J17 -> 0.051748252 | R17: =M17/J17 -> 0.033916084 | T17: 858.2 | U17: 862.7 | V17: 72.1 | W17: 75.8 | Y17: 100.54 | Z17: 109.4 | AA17: 110.51 | AB17: 138.88 | AE17: 0.582 | AG17: 0.0418 | AH17: 0.057 | AI17: 0.0346 | AJ17: =CH17 -> 0.0285 | AL17: 0.1085 | AM17: 1.24 | AN17: -0.37 | AO17: -4.99 | AQ17: 18.9 | AV17: =J17 -> 858 | AW17: =U17 -> 862.7 | AX17: 885.2 | AZ17: =L17 -> 71.4 | BA17: =W17 -> 75.8 | BB17: 80.5 | BD17: 44.4 | BE17: 47 | BF17: 50.9 | BH17: =AZ17/AV17 -> 0.083216783 | BJ17: =Y17 -> 100.54 | BK17: =AA17 -> 110.51 | BL17: =AB17 -> 138.88 | BN17: =(BL17/BJ17)-1 -> 0.38134076 | BQ17: =H17/AZ17 -> 8.4691877 | BR17: 7.98 | BS17: 7.51 | BU17: =BA17/AW17 -> 0.087863684 | BV17: =AN17 -> -0.37 | BW17: =1/AQ17 -> 0.052910053 | BX17: =H17/J17 -> 0.70477855 | BY17: =H17/BD17 -> 13.619369 | CA17: 22.47 | CB17: 19.04 | CC17: 15.15 | CE17: =BN17 -> 0.38134076 | CG17: =CC17/38.13 -> 0.39732494 | CH17: 0.0285 | CJ17: - | CS17: 2027E Tier 1 | CU17: =BB5 -> 110.3 | CW17: 8.00x-12.00x | CY17: 8 | CZ17: =DA17-CY17 -> 4 | DA17: 12 | DB17: =CU17*CY17 -> 882.4 | DC17: =CU17*CZ17 -> 441.2 | DD17: =CU17*DA17 -> 1323.6 | DE17: 81.445 | DF17: =DB17-DE17 -> 800.955 | DG17: =DC17-DE17 -> 359.755 | DH17: =DD17-DE17 -> 1242.155 | DI17: 0.303 | DK17: =DF17/DI17 -> 2643.4158 | DL17: =DG17/DI17 -> 1187.3102 | DM17: =DH17/DI17 -> 4099.5215 | DN17: =(DK17+DM17)/2 -> 3371.4686
CS18: LTM Tier 2 | CU18: =CU15 -> 89.5 | CW18: 8.9x-12.81x | CY18: 8.9 | CZ18: =DA18-CY18 -> 3.91 | DA18: 12.81 | DB18: =CU18*CY18 -> 796.55 | DC18: =CU18*CZ18 -> 349.945 | DD18: =CU18*DA18 -> 1146.495 | DE18: 81.445 | DF18: =DB18-DE18 -> 715.105 | DG18: =DC18-DE18 -> 268.5 | DH18: =DD18-DE18 -> 1065.05 | DI18: 0.303 | DK18: =DF18/DI18 -> 2360.0825 | DL18: =DG18/DI18 -> 886.13861 | DM18: =DH18/DI18 -> 3515.0165 | DN18: =(DK18+DM18)/2 -> 2937.5495
B19: Ezaki Glico | E19: 2206 JT | F19: JPY | G19: 394 | H19: 342.4 | J19: 354.7 | K19: 132.4 | L19: 26.7 | M19: 5.6 | O19: =K19/J19 -> 0.37327319 | P19: =L19/J19 -> 0.07527488 | Q19: =BD19/J19 -> 0.020862701 | R19: =M19/J19 -> 0.01578799 | T19: 332.6 | U19: 353.5 | V19: 32.6 | W19: 28.8 | Y19: 88.64 | Z19: 238.4 | AA19: 132.31 | AB19: 179.17 | AE19: 0.516 | AG19: 0.0173 | AH19: 0.021 | AI19: 0.0153 | AJ19: =CH19 -> 0.0165 | AL19: 0.0089 | AM19: 0.11 | AN19: -1.95 | AO19: -19.15 | AQ19: 302.38 | AV19: =J19 -> 354.7 | AW19: =U19 -> 353.5 | AX19: 362.8 | AZ19: =L19 -> 26.7 | BA19: =W19 -> 28.8 | BB19: 33.9 | BD19: 7.4 | BE19: 10.5 | BF19: 15.2 | BH19: =AZ19/AV19 -> 0.07527488 | BJ19: =Y19 -> 88.64 | BK19: =AA19 -> 132.31 | BL19: =AB19 -> 179.17 | BN19: =(BL19/BJ19)-1 -> 1.0213222 | BQ19: =H19/AZ19 -> 12.82397 | BR19: 11.89 | BS19: 10.09 | BU19: =BA19/AW19 -> 0.081471004 | BV19: =AN19 -> -1.95 | BW19: =1/AQ19 -> 0.003307097 | BX19: =H19/J19 -> 0.96532281 | BY19: =H19/BD19 -> 46.27027 | CA19: 51.12 | CB19: 43.5 | CC19: 32.12 | CE19: =BN19 -> 1.0213222 | CG19: =CC19/102.13 -> 0.31450113 | CH19: 0.0165 | CJ19: - | CS19: 2026E Tier 2 | CU19: =CU16 -> 100.5 | CW19: 7.91x-12.33x | CY19: 7.91 | CZ19: =DA19-CY19 -> 4.42 | DA19: 12.33 | DB19: =CU19*CY19 -> 794.955 | DC19: =CU19*CZ19 -> 444.21 | DD19: =CU19*DA19 -> 1239.165 | DE19: 81.445 | DF19: =DB19-DE19 -> 713.51 | DG19: =DC19-DE19 -> 362.765 | DH19: =DD19-DE19 -> 1157.72 | DI19: 0.303 | DK19: =DF19/DI19 -> 2354.8185 | DL19: =DG19/DI19 -> 1197.2442 | DM19: =DH19/DI19 -> 3820.8581 | DN19: =(DK19+DM19)/2 -> 3087.8383
CS20: 2027E Tier 2 | CU20: =CU17 -> 110.3 | CW20: 7.53x-9.68x | CY20: 7.53 | CZ20: =DA20-CY20 -> 2.15 | DA20: 9.68 | DB20: =CU20*CY20 -> 830.559 | DC20: =CU20*CZ20 -> 237.145 | DD20: =CU20*DA20 -> 1067.704 | DE20: 81.445 | DF20: =DB20-DE20 -> 749.114 | DG20: =DC20-DE20 -> 155.7 | DH20: =DD20-DE20 -> 986.259 | DI20: 0.303 | DK20: =DF20/DI20 -> 2472.3234 | DL20: =DG20/DI20 -> 513.86139 | DM20: =DH20/DI20 -> 3254.9802 | DN20: =(DK20+DM20)/2 -> 2863.6518
B21: House Foods Group | E21: 2810 JT | F21: JPY | G21: 305.4 | H21: 270 | J21: 318 | K21: 116.8 | L21: 31.1 | M21: 13 | O21: =K21/J21 -> 0.3672956 | P21: =L21/J21 -> 0.097798742 | Q21: =BD21/J21 -> 0.05408805 | R21: =M21/J21 -> 0.040880503 | T21: 299.6 | U21: 321.3 | V21: 33.1 | W21: 33.7 | Y21: 140.06 | Z21: 187.36 | AA21: 141.3 | AB21: 148.44 | AE21: 0.487 | AG21: 0.0376 | AH21: 0.0448 | AI21: 0.0302 | AJ21: =CH21 -> 0.0155 | AL21: 0.047 | AM21: 0.59 | AN21: -2.08 | AO21: -20.1 | AQ21: 347.67 | AV21: =J21 -> 318 | AW21: =U21 -> 321.3 | AX21: 322.1 | AZ21: =L21 -> 31.1 | BA21: =W21 -> 33.7 | BB21: 36 | BD21: 17.2 | BE21: 18.3 | BF21: 19.8 | BH21: =AZ21/AV21 -> 0.097798742 | BJ21: =Y21 -> 140.06 | BK21: =AA21 -> 141.3 | BL21: =AB21 -> 148.44 | BN21: =(BL21/BJ21)-1 -> 0.059831501 | BQ21: 8.68 | BR21: 8.01 | BS21: 7.5 | BU21: =BA21/AW21 -> 0.1048864 | BV21: =AN21 -> -2.08 | BW21: =1/AQ21 -> 0.0028762907 | BX21: =H21/J21 -> 0.8490566 | BY21: =H21/BD21 -> 15.697674 | CA21: 23.77 | CB21: 21.95 | CC21: 20.89 | CE21: =BN21 -> 0.059831501 | CG21: =CC21/5.98 -> 3.493311 | CH21: 0.0155 | CJ21: - | CS21: LTM Tier 3 | CU21: =CU15 -> 89.5 | CW21: 5.91x-12.96x | CY21: 5.91 | CZ21: =DA21-CY21 -> 7.05 | DA21: 12.96 | DB21: =CU21*CY21 -> 528.945 | DC21: =CU21*CZ21 -> 630.975 | DD21: =CU21*DA21 -> 1159.92 | DE21: 81.445 | DF21: =DB21-DE21 -> 447.5 | DG21: =DC21-DE21 -> 549.53 | DH21: =DD21-DE21 -> 1078.475 | DI21: 0.303 | DK21: =DF21/DI21 -> 1476.8977 | DL21: =DG21/DI21 -> 1813.6304 | DM21: =DH21/DI21 -> 3559.3234 | DN21: =(DK21+DM21)/2 -> 2518.1106
CS22: 2026E Tier 3 | CU22: =CU16 -> 100.5 | CW22: 5.26x-12.08x | CY22: 5.26 | CZ22: =DA22-CY22 -> 6.82 | DA22: 12.08 | DB22: =CU22*CY22 -> 528.63 | DC22: =CU22*CZ22 -> 685.41 | DD22: =CU22*DA22 -> 1214.04 | DE22: 81.445 | DF22: =DB22-DE22 -> 447.185 | DG22: =DC22-DE22 -> 603.965 | DH22: =DD22-DE22 -> 1132.595 | DI22: 0.303 | DK22: =DF22/DI22 -> 1475.8581 | DL22: =DG22/DI22 -> 1993.2838 | DM22: =DH22/DI22 -> 3737.9373 | DN22: =(DK22+DM22)/2 -> 2606.8977
B23: Mean | G23: =AVERAGE(G11:G21) -> 1119.85 | H23: =AVERAGE(H11:H21) -> 1173.1667 | J23: =AVERAGE(J11:J21) -> 689.36667 | K23: =AVERAGE(K11:K21) -> 227.85 | L23: =AVERAGE(L11:L21) -> 85.533333 | M23: =AVERAGE(M11:M21) -> 39.366667 | O23: =AVERAGE(O11:O21) -> 0.33244635 | P23: =AVERAGE(P11:P21) -> 0.11241638 | Q23: =AVERAGE(Q11:Q21) -> 0.066848439 | R23: =AVERAGE(R11:R21) -> 0.049368573 | T23: =AVERAGE(T11:T21) -> 648.9 | U23: =AVERAGE(U11:U21) -> 695.88333 | V23: =AVERAGE(V11:V21) -> 81.033333 | W23: =AVERAGE(W11:W21) -> 92.45 | Y23: =AVERAGE(Y11:Y21) -> 107.105 | Z23: =AVERAGE(Z11:Z21) -> 139.86167 | AA23: =AVERAGE(AA11:AA21) -> 118.93167 | AB23: =AVERAGE(AB11:AB21) -> 138.97 | AE23: Mean | AG23: =AVERAGE(AG11:AG21) -> 0.050383333 | AH23: =AVERAGE(AH11:AH21) -> 0.069783333 | AI23: =AVERAGE(AI11:AI21) -> 0.038366667 | AJ23: =AVERAGE(AJ11:AJ21) -> 0.01805 | AL23: =AVERAGE(AL11:AL21) -> 0.109 | AM23: =AVERAGE(AM11:AM21) -> 1.0233333 | AN23: =AVERAGE(AN11:AN21) -> -0.51 | AO23: =AVERAGE(AO11:AO21) -> -0.47 | AQ23: =AVERAGE(AQ11:AQ21) -> 146.30833 | AU23: Mean | AV23: =AVERAGE(AV11:AV21) -> 825.6 | AW23: =AVERAGE(AW11:AW21) -> 695.88333 | AX23: =AVERAGE(AX11:AX21) -> 725.3 | AZ23: =AVERAGE(AZ11:AZ21) -> 85.533333 | BA23: =AVERAGE(BA11:BA21) -> 92.45 | BB23: =AVERAGE(BB11:BB21) -> 100.48333 | BD23: =AVERAGE(BD11:BD21) -> 53.65 | BE23: =AVERAGE(BE11:BE21) -> 59.866667 | BF23: =AVERAGE(BF11:BF21) -> 66.2 | BH23: =AVERAGE(BH11:BH21) -> 0.099998275 | BJ23: =AVERAGE(BJ11:BJ21) -> 101.52833 | BK23: =AVERAGE(BK11:BK21) -> 118.78 | BL23: =AVERAGE(BL11:BL21) -> 138.885 | BN23: =AVERAGE(BN11:BN21) -> 0.40584509 | BP23: Mean | BQ23: =AVERAGE(BQ11:BQ21) -> 11.829537 | BR23: =AVERAGE(BR11:BR21) -> 11.065 | BS23: =AVERAGE(BS11:BS21) -> 10.115 | BU23: =AVERAGE(BU11:BU21) -> 0.11909806 | BV23: =AVERAGE(BV11:BV21) -> -0.51 | BW23: =AVERAGE(BW11:BW21) -> 0.020120651 | BX23: =AVERAGE(BX11:BX21) -> 1.3894576 | BY23: =AVERAGE(BY11:BY21) -> 23.075359 | CA23: =AVERAGE(CA11:CA21) -> 31.658333 | CB23: =AVERAGE(CB11:CB21) -> 26.438333 | CC23: =AVERAGE(CC11:CC21) -> 22.546667 | CE23: =AVERAGE(CE11:CE21) -> 0.40584509 | CG23: =AVERAGE(CG11:CG21) -> 1.6449437 | CH23: =AVERAGE(CH11:CH21) -> 0.01805 | CJ23: =AVERAGE(CJ11:CJ21) -> 3.01 | CS23: 2027E Tier 3 | CU23: =CU17 -> 110.3 | CW23: 6.50x-10.60x | CY23: 6.5 | CZ23: =DA23-CY23 -> 4.1 | DA23: 10.6 | DB23: =CU23*CY23 -> 716.95 | DC23: =CU23*CZ23 -> 452.23 | DD23: =CU23*DA23 -> 1169.18 | DE23: 81.445 | DF23: =DB23-DE23 -> 635.505 | DG23: =DC23-DE23 -> 370.785 | DH23: =DD23-DE23 -> 1087.735 | DI23: 0.303 | DK23: =DF23/DI23 -> 2097.3762 | DL23: =DG23/DI23 -> 1223.7129 | DM23: =DH23/DI23 -> 3589.8845 | DN23: =(DK23+DM23)/2 -> 2843.6304
B24: Median | G24: =MEDIAN(G11:G21) -> 508.75 | H24: =MEDIAN(H11:H21) -> 519.45 | J24: =MEDIAN(J11:J21) -> 540.5 | K24: =MEDIAN(K11:K21) -> 161.7 | L24: =MEDIAN(L11:L21) -> 56.05 | M24: =MEDIAN(M11:M21) -> 22.95 | O24: =MEDIAN(O11:O21) -> 0.35189783 | P24: =MEDIAN(P11:P21) -> 0.10955511 | Q24: =MEDIAN(Q11:Q21) -> 0.062513474 | R24: =MEDIAN(R11:R21) -> 0.045477509 | T24: =MEDIAN(T11:T21) -> 496.7 | U24: =MEDIAN(U11:U21) -> 543.2 | V24: =MEDIAN(V11:V21) -> 56.05 | W24: =MEDIAN(W11:W21) -> 59.15 | Y24: =MEDIAN(Y11:Y21) -> 106.83 | Z24: =MEDIAN(Z11:Z21) -> 136.575 | AA24: =MEDIAN(AA11:AA21) -> 127.455 | AB24: =MEDIAN(AB11:AB21) -> 143.71 | AE24: Median | AG24: =MEDIAN(AG11:AG21) -> 0.0514 | AH24: =MEDIAN(AH11:AH21) -> 0.0695 | AI24: =MEDIAN(AI11:AI21) -> 0.0393 | AJ24: =MEDIAN(AJ11:AJ21) -> 0.0165 | AL24: =MEDIAN(AL11:AL21) -> 0.0977 | AM24: =MEDIAN(AM11:AM21) -> 0.915 | AN24: =MEDIAN(AN11:AN21) -> -0.47 | AO24: =MEDIAN(AO11:AO21) -> -7.73 | AQ24: =MEDIAN(AQ11:AQ21) -> 90.865 | AU24: Median | AV24: =MEDIAN(AV11:AV21) -> 606.35 | AW24: =MEDIAN(AW11:AW21) -> 543.2 | AX24: =MEDIAN(AX11:AX21) -> 568.15 | AZ24: =MEDIAN(AZ11:AZ21) -> 56.05 | BA24: =MEDIAN(BA11:BA21) -> 59.15 | BB24: =MEDIAN(BB11:BB21) -> 63.2 | BD24: =MEDIAN(BD11:BD21) -> 34.1 | BE24: =MEDIAN(BE11:BE21) -> 36.5 | BF24: =MEDIAN(BF11:BF21) -> 39.95 | BH24: =MEDIAN(BH11:BH21) -> 0.090507763 | BJ24: =MEDIAN(BJ11:BJ21) -> 94.59 | BK24: =MEDIAN(BK11:BK21) -> 127 | BL24: =MEDIAN(BL11:BL21) -> 143.66 | BN24: =MEDIAN(BN11:BN21) -> 0.28202612 | BP24: Median | BQ24: =MEDIAN(BQ11:BQ21) -> 11.746137 | BR24: =MEDIAN(BR11:BR21) -> 11.05 | BS24: =MEDIAN(BS11:BS21) -> 9.775 | BU24: =MEDIAN(BU11:BU21) -> 0.1154435 | BV24: =MEDIAN(BV11:BV21) -> -0.47 | BW24: =MEDIAN(BW11:BW21) -> 0.012412583 | BX24: =MEDIAN(BX11:BX21) -> 1.1297553 | BY24: =MEDIAN(BY11:BY21) -> 18.507941 | CA24: =MEDIAN(CA11:CA21) -> 23.815 | CB24: =MEDIAN(CB11:CB21) -> 22.62 | CC24: =MEDIAN(CC11:CC21) -> 21.535 | CE24: =MEDIAN(CE11:CE21) -> 0.28202612 | CG24: =MEDIAN(CG11:CG21) -> 0.71672487 | CH24: =MEDIAN(CH11:CH21) -> 0.0165 | CJ24: =MEDIAN(CJ11:CJ21) -> 3.01
B25: 25th | G25: =_xlfn.PERCENTILE.INC(G11:G21,0.25) -> 396.95 | H25: =_xlfn.PERCENTILE.INC(H11:H21,0.25) -> 365.35 | J25: =_xlfn.PERCENTILE.INC(J11:J21,0.25) -> 340.3 | K25: =_xlfn.PERCENTILE.INC(K11:K21,0.25) -> 120.7 | L25: =_xlfn.PERCENTILE.INC(L11:L21,0.25) -> 33.5 | M25: =_xlfn.PERCENTILE.INC(M11:M21,0.25) -> 13.95 | O25: =_xlfn.PERCENTILE.INC(O11:O21,0.25) -> 0.32644991 | P25: =_xlfn.PERCENTILE.INC(P11:P21,0.25) -> 0.086862273 | Q25: =_xlfn.PERCENTILE.INC(Q11:Q21,0.25) -> 0.052333201 | R25: =_xlfn.PERCENTILE.INC(R11:R21,0.25) -> 0.035657189 | T25: =_xlfn.PERCENTILE.INC(T11:T21,0.25) -> 310.4 | U25: =_xlfn.PERCENTILE.INC(U11:U21,0.25) -> 341.35 | V25: =_xlfn.PERCENTILE.INC(V11:V21,0.25) -> 34.825 | W25: =_xlfn.PERCENTILE.INC(W11:W21,0.25) -> 35.9 | Y25: =_xlfn.PERCENTILE.INC(Y11:Y21,0.25) -> 91.615 | Z25: =_xlfn.PERCENTILE.INC(Z11:Z21,0.25) -> 87.17 | AA25: =_xlfn.PERCENTILE.INC(AA11:AA21,0.25) -> 113.5325 | AB25: =_xlfn.PERCENTILE.INC(AB11:AB21,0.25) -> 138.905 | AE25: 25th | AG25: =_xlfn.PERCENTILE.INC(AG11:AG21,0.25) -> 0.03865 | AH25: =_xlfn.PERCENTILE.INC(AH11:AH21,0.25) -> 0.04785 | AI25: =_xlfn.PERCENTILE.INC(AI11:AI21,0.25) -> 0.0313 | AJ25: =_xlfn.PERCENTILE.INC(AJ11:AJ21,0.25) -> 0.01575 | AL25: =_xlfn.PERCENTILE.INC(AL11:AL21,0.25) -> 0.056975 | AM25: =_xlfn.PERCENTILE.INC(AM11:AM21,0.25) -> 0.59 | AN25: =_xlfn.PERCENTILE.INC(AN11:AN21,0.25) -> -1.605 | AO25: =_xlfn.PERCENTILE.INC(AO11:AO21,0.25) -> -16.98 | AQ25: =_xlfn.PERCENTILE.INC(AQ11:AQ21,0.25) -> 35.445 | AU25: 25th | AV25: =_xlfn.PERCENTILE.INC(AV11:AV21,0.25) -> 340.3 | AW25: =_xlfn.PERCENTILE.INC(AW11:AW21,0.25) -> 341.35 | AX25: =_xlfn.PERCENTILE.INC(AX11:AX21,0.25) -> 354.925 | AZ25: =_xlfn.PERCENTILE.INC(AZ11:AZ21,0.25) -> 33.5 | BA25: =_xlfn.PERCENTILE.INC(BA11:BA21,0.25) -> 35.9 | BB25: =_xlfn.PERCENTILE.INC(BB11:BB21,0.25) -> 38.475 | BD25: =_xlfn.PERCENTILE.INC(BD11:BD21,0.25) -> 18.85 | BE25: =_xlfn.PERCENTILE.INC(BE11:BE21,0.25) -> 20.225 | BF25: =_xlfn.PERCENTILE.INC(BF11:BF21,0.25) -> 22.1 | BH25: =_xlfn.PERCENTILE.INC(BH11:BH21,0.25) -> 0.077260356 | BJ25: =_xlfn.PERCENTILE.INC(BJ11:BJ21,0.25) -> 81.905 | BK25: =_xlfn.PERCENTILE.INC(BK11:BK21,0.25) -> 113.305 | BL25: =_xlfn.PERCENTILE.INC(BL11:BL21,0.25) -> 138.5725 | BN25: =_xlfn.PERCENTILE.INC(BN11:BN21,0.25) -> 0.090551498 | BP25: 25th | BQ25: =_xlfn.PERCENTILE.INC(BQ11:BQ21,0.25) -> 9.1770762 | BR25: =_xlfn.PERCENTILE.INC(BR11:BR21,0.25) -> 8.56 | BS25: =_xlfn.PERCENTILE.INC(BS11:BS21,0.25) -> 7.9975 | BU25: =_xlfn.PERCENTILE.INC(BU11:BU21,0.25) -> 0.092119363 | BV25: =_xlfn.PERCENTILE.INC(BV11:BV21,0.25) -> -1.605 | BW25: =_xlfn.PERCENTILE.INC(BW11:BW21,0.25) -> 0.0045386136 | BX25: =_xlfn.PERCENTILE.INC(BX11:BX21,0.25) -> 0.87812315 | BY25: =_xlfn.PERCENTILE.INC(BY11:BY21,0.25) -> 16.33418 | CA25: =_xlfn.PERCENTILE.INC(CA11:CA21,0.25) -> 23.455 | CB25: =_xlfn.PERCENTILE.INC(CB11:CB21,0.25) -> 21.5075 | CC25: =_xlfn.PERCENTILE.INC(CC11:CC21,0.25) -> 19.42 | CE25: =_xlfn.PERCENTILE.INC(CE11:CE21,0.25) -> 0.090551498 | CG25: =_xlfn.PERCENTILE.INC(CG11:CG21,0.25) -> 0.34679413 | CH25: =_xlfn.PERCENTILE.INC(CH11:CH21,0.25) -> 0.01575 | CJ25: =_xlfn.PERCENTILE.INC(CJ11:CJ21,0.25) -> 2.83
B26: 75th | G26: =_xlfn.PERCENTILE.INC(G11:G21,0.75) -> 1253.7 | H26: =_xlfn.PERCENTILE.INC(H11:H21,0.75) -> 1214.15 | J26: =_xlfn.PERCENTILE.INC(J11:J21,0.75) -> 825.075 | K26: =_xlfn.PERCENTILE.INC(K11:K21,0.75) -> 231.05 | L26: =_xlfn.PERCENTILE.INC(L11:L21,0.75) -> 94.5 | M26: =_xlfn.PERCENTILE.INC(M11:M21,0.75) -> 52.875 | O26: =_xlfn.PERCENTILE.INC(O11:O21,0.75) -> 0.37074791 | P26: =_xlfn.PERCENTILE.INC(P11:P21,0.75) -> 0.13586277 | Q26: =_xlfn.PERCENTILE.INC(Q11:Q21,0.75) -> 0.092360623 | R26: =_xlfn.PERCENTILE.INC(R11:R21,0.75) -> 0.066398917 | T26: =_xlfn.PERCENTILE.INC(T11:T21,0.75) -> 808.85 | U26: =_xlfn.PERCENTILE.INC(U11:U21,0.75) -> 830.25 | V26: =_xlfn.PERCENTILE.INC(V11:V21,0.75) -> 88.6 | W26: =_xlfn.PERCENTILE.INC(W11:W21,0.75) -> 97.25 | Y26: =_xlfn.PERCENTILE.INC(Y11:Y21,0.75) -> 129.7925 | Z26: =_xlfn.PERCENTILE.INC(Z11:Z21,0.75) -> 181.4575 | AA26: =_xlfn.PERCENTILE.INC(AA11:AA21,0.75) -> 139.0525 | AB26: =_xlfn.PERCENTILE.INC(AB11:AB21,0.75) -> 157.17 | AE26: 75th | AG26: =_xlfn.PERCENTILE.INC(AG11:AG21,0.75) -> 0.0643 | AH26: =_xlfn.PERCENTILE.INC(AH11:AH21,0.75) -> 0.099025 | AI26: =_xlfn.PERCENTILE.INC(AI11:AI21,0.75) -> 0.05015 | AJ26: =_xlfn.PERCENTILE.INC(AJ11:AJ21,0.75) -> 0.01845 | AL26: =_xlfn.PERCENTILE.INC(AL11:AL21,0.75) -> 0.113 | AM26: =_xlfn.PERCENTILE.INC(AM11:AM21,0.75) -> 1.27 | AN26: =_xlfn.PERCENTILE.INC(AN11:AN21,0.75) -> 0.2225 | AO26: =_xlfn.PERCENTILE.INC(AO11:AO21,0.75) -> 4.7075 | AQ26: =_xlfn.PERCENTILE.INC(AQ11:AQ21,0.75) -> 257.15 | AU26: 75th | AV26: =_xlfn.PERCENTILE.INC(AV11:AV21,0.75) -> 1372.275 | AW26: =_xlfn.PERCENTILE.INC(AW11:AW21,0.75) -> 830.25 | AX26: =_xlfn.PERCENTILE.INC(AX11:AX21,0.75) -> 857.275 | AZ26: =_xlfn.PERCENTILE.INC(AZ11:AZ21,0.75) -> 94.5 | BA26: =_xlfn.PERCENTILE.INC(BA11:BA21,0.75) -> 97.25 | BB26: =_xlfn.PERCENTILE.INC(BB11:BB21,0.75) -> 104.275 | BD26: =_xlfn.PERCENTILE.INC(BD11:BD21,0.75) -> 67.725 | BE26: =_xlfn.PERCENTILE.INC(BE11:BE21,0.75) -> 68.675 | BF26: =_xlfn.PERCENTILE.INC(BF11:BF21,0.75) -> 72.725 | BH26: =_xlfn.PERCENTILE.INC(BH11:BH21,0.75) -> 0.11543329 | BJ26: =_xlfn.PERCENTILE.INC(BJ11:BJ21,0.75) -> 126.6475 | BK26: =_xlfn.PERCENTILE.INC(BK11:BK21,0.75) -> 139.0525 | BL26: =_xlfn.PERCENTILE.INC(BL11:BL21,0.75) -> 157.17 | BN26: =_xlfn.PERCENTILE.INC(BN11:BN21,0.75) -> 0.64903215 | BP26: 75th | BQ26: =_xlfn.PERCENTILE.INC(BQ11:BQ21,0.75) -> 13.606922 | BR26: =_xlfn.PERCENTILE.INC(BR11:BR21,0.75) -> 13.15 | BS26: =_xlfn.PERCENTILE.INC(BS11:BS21,0.75) -> 12.0025 | BU26: =_xlfn.PERCENTILE.INC(BU11:BU21,0.75) -> 0.13833601 | BV26: =_xlfn.PERCENTILE.INC(BV11:BV21,0.75) -> 0.2225 | BW26: =_xlfn.PERCENTILE.INC(BW11:BW21,0.75) -> 0.031751976 | BX26: =_xlfn.PERCENTILE.INC(BX11:BX21,0.75) -> 1.7870951 | BY26: =_xlfn.PERCENTILE.INC(BY11:BY21,0.75) -> 24.079765 | CA26: =_xlfn.PERCENTILE.INC(CA11:CA21,0.75) -> 40 | CB26: =_xlfn.PERCENTILE.INC(CB11:CB21,0.75) -> 27.94 | CC26: =_xlfn.PERCENTILE.INC(CC11:CC21,0.75) -> 25.0525 | CE26: =_xlfn.PERCENTILE.INC(CE11:CE21,0.75) -> 0.64903215 | CG26: =_xlfn.PERCENTILE.INC(CG11:CG21,0.75) -> 2.8790145 | CH26: =_xlfn.PERCENTILE.INC(CH11:CH21,0.75) -> 0.01845 | CJ26: =_xlfn.PERCENTILE.INC(CJ11:CJ21,0.75) -> 3.19 | CS26: P/E and PEG
CS27: FY | CU27: 25th | CV27: 75th | CW27: Diff | CY27: 25th | CZ27: 75th | DA27: Diff
B28: Tier 2: Broader Japan Food Staples | AE28: Tier 2: Broader Japan Food Staples | AU28: Tier 2: Broader Japan Food Staples | BP28: Tier 2: Broader Japan Food Staples | CS28: LTM Tier 1 | CU28: 31.658333 | CV28: 40 | CW28: =CV28-CU28 -> 8.3416667
CS29: FY1 Tier 1 | CU29: 21.5075 | CV29: 27.94 | CW29: =CV29-CU29 -> 6.4325
B30: Yakult Honsha | E30: 2267 JT | F30: JPY | G30: 865.5 | H30: 775.8 | J30: 485.8 | K30: 284.6 | L30: 76.1 | M30: 39.9 | O30: =K30/J30 -> 0.58583779 | P30: =L30/J30 -> 0.15664883 | Q30: =BD30/J30 -> 0.096541787 | R30: =M30/J30 -> 0.082132565 | T30: 503.1 | U30: 488.1 | V30: 91.2 | W30: 77.8 | Y30: 134.01 | Z30: 160.47 | AA30: 148.97 | AB30: 147.1 | AE30: 0.44 | AG30: 0.044 | AH30: 0.0689 | AI30: 0.0469 | AJ30: =CH30 -> 0.0249 | AL30: 0.121 | AM30: 0.93 | AN30: -1.77 | AO30: -22.16 | AQ30: 97.68 | AV30: =J30 -> 485.8 | AW30: =U30 -> 488.1 | AX30: 499.2 | AZ30: =L30 -> 76.1 | BA30: =W30 -> 77.8 | BB30: 82 | BD30: 46.9 | BE30: 48.8 | BF30: 50.2 | BH30: =AZ30/AV30 -> 0.15664883 | BJ30: =Y30 -> 134.01 | BK30: =AA30 -> 148.97 | BL30: =AB30 -> 147.1 | BN30: =(BL30/BJ30)-1 -> 0.097679278 | BQ30: 10.19 | BR30: 9.98 | BS30: 9.46 | BU30: =BA30/AW30 -> 0.15939357 | BV30: =AN30 -> -1.77 | BW30: =1/AQ30 -> 0.01023751 | BX30: =H30/J30 -> 1.5969535 | BY30: =H30/AV30 -> 1.5969535 | CA30: 18.23 | CB30: 17.5 | CC30: 17.72 | CE30: =BN30 -> 0.097679278 | CG30: =CC30/9.77 -> 1.8137155 | CH30: 0.0249 | CJ30: - | CS30: FY2 Tier 1 | CU30: 19.42 | CV30: 25.0525 | CW30: =CV30-CU30 -> 5.6325 | CY30: 0.34679413 | CZ30: 2.8790145 | DA30: =CZ30-CY30 -> 2.5322203
CS31: LTM Tier 2 | CU31: 18.195 | CV31: 21.96 | CW31: =CV31-CU31 -> 3.765
B32: Kewpie | E32: 2809 JT | F32: JPY | G32: 647.5 | H32: 611.2 | J32: 513.4 | K32: 150.9 | L32: 52.9 | M32: 23.5 | O32: =K32/J32 -> 0.29392287 | P32: =L32/J32 -> 0.10303857 | Q32: =BD32/J32 -> 0.067393845 | R32: =M32/J32 -> 0.045773276 | T32: 484 | U32: 529.8 | V32: 52 | W32: 57.3 | Y32: 170.32 | Z32: 168.22 | AA32: 186.9 | AB32: 207.15 | AE32: 0.598 | AG32: 0.046 | AH32: 0.0752 | AI32: 0.0499 | AJ32: =CH32 -> 0.014 | AL32: 0.0433 | AM32: 0.39 | AN32: -1.13 | AO32: -17.2 | AQ32: 199.72 | AV32: =J32 -> 513.4 | AW32: =U32 -> 529.8 | AX32: 548.3 | AZ32: =L32 -> 52.9 | BA32: =W32 -> 57.3 | BB32: 61.8 | BD32: 34.6 | BE32: 38.8 | BF32: 42.5 | BH32: =AZ32/AV32 -> 0.10303857 | BJ32: =Y32 -> 170.32 | BK32: =AA32 -> 186.9 | BL32: =AB32 -> 207.15 | BN32: =(BL32/BJ32)-1 -> 0.21624002 | BQ32: =H32/AZ32 -> 11.553875 | BR32: 10.67 | BS32: 9.89 | BU32: =BA32/AW32 -> 0.10815402 | BV32: =AN32 -> -1.13 | BW32: =1/AQ32 -> 0.0050070098 | BX32: =H32/J32 -> 1.1904947 | BY32: =H32/AV32 -> 1.1904947 | CA32: 20.77 | CB32: 24.48 | CC32: 22.09 | CE32: =BN32 -> 0.21624002 | CG32: =CC32/21.62 -> 1.0217391 | CH32: 0.014 | CJ32: - | CS32: FY1 Tier 2 | CU32: 17.35 | CV32: 18.76 | CW32: =CV32-CU32 -> 1.41
CS33: FY2 Tier 2 | CU33: 15.395 | CV33: 17.55 | CW33: =CV33-CU33 -> 2.155 | CY33: =CG46 -> 0.81672428 | CZ33: =CG47 -> 1.1947921 | DA33: =CZ33-CY33 -> 0.37806784
B34: Toyo Suisan Kaisha | E34: 2875 JT | F34: JPY | G34: 1305.1 | H34: 1087.8 | J34: 515 | K34: 154.3 | L34: 95.1 | M34: 64 | O34: =K34/J34 -> 0.29961165 | P34: =L34/J34 -> 0.18466019 | Q34: =BD34/J34 -> 0.15106796 | R34: =M34/J34 -> 0.12427184 | T34: 489 | U34: 531.3 | V34: 83.8 | W34: 100.2 | Y34: 647.2 | Z34: 557.52 | AA34: 681.74 | AB34: 724.11 | AE34: 0.878 | AG34: 0.1124 | AH34: 0.1298 | AI34: 0.1044 | AJ34: =CH34 -> 0.017 | AL34: 0.0057 | AM34: 0.03 | AN34: -2.42 | AO34: -44.48 | AQ34: 454.42 | AV34: =J34 -> 515 | AW34: =U34 -> 531.3 | AX34: 555.4 | AZ34: =L34 -> 95.1 | BA34: =W34 -> 100.2 | BB34: 106.7 | BD34: 77.8 | BE34: 81.4 | BF34: 85 | BH34: =AZ34/AV34 -> 0.18466019 | BJ34: =Y34 -> 647.2 | BK34: =AA34 -> 681.74 | BL34: =AB34 -> 724.11 | BN34: =(BL34/BJ34)-1 -> 0.11883498 | BQ34: =H34/AZ34 -> 11.438486 | BR34: 10.85 | BS34: 10.2 | BU34: =BA34/AW34 -> 0.18859401 | BV34: =AN34 -> -2.42 | BW34: =1/AQ34 -> 0.0022006074 | BX34: =H34/J34 -> 2.112233 | BY34: =H34/AV34 -> 2.112233 | CA34: 18.16 | CB34: 17.26 | CC34: 16.25 | CE34: =BN34 -> 0.11883498 | CG34: =CC34/11.88 -> 1.3678451 | CH34: 0.017 | CJ34: - | CS34: LTM Tier 3 | CU34: 13.2675 | CV34: 15.09 | CW34: =CV34-CU34 -> 1.8225
CS35: FY 1 Tier 3 | CU35: 13.2575 | CV35: 14.57 | CW35: =CV35-CU35 -> 1.3125
B36: Morinaga Milk Industry | E36: 2264 JT | F36: JPY | G36: 365.5 | H36: 440.4 | J36: 563.9 | K36: 138.3 | L36: 57.7 | M36: 17.9 | O36: =K36/J36 -> 0.24525625 | P36: =L36/J36 -> 0.10232311 | Q36: =BD36/J36 -> 0.058521014 | R36: =M36/J36 -> 0.031743217 | T36: 547.1 | U36: 574.6 | V36: 54.3 | W36: 57 | Y36: 216.31 | Z36: 203.4 | AA36: 235.42 | AB36: 282.01 | AE36: 0.514 | AG36: 0.0137 | AH36: 0.0651 | AI36: 0.0327 | AJ36: =CH36 -> 0.0219 | AL36: 0.2198 | AM36: 2.11 | AN36: 1.22 | AO36: 25.65 | AQ36: 36 | AV36: =J36 -> 563.9 | AW36: =U36 -> 574.6 | AX36: 584.1 | AZ36: =L36 -> 57.7 | BA36: =W36 -> 57 | BB36: 59.6 | BD36: 33 | BE36: 32.7 | BF36: 34.9 | BH36: =AZ36/AV36 -> 0.10232311 | BJ36: =Y36 -> 216.31 | BK36: =AA36 -> 235.42 | BL36: =AB36 -> 282.01 | BN36: =(BL36/BJ36)-1 -> 0.30373076 | BQ36: =H36/AZ36 -> 7.6325823 | BR36: 7.72 | BS36: 7.38 | BU36: =BA36/AW36 -> 0.099199443 | BV36: =AN36 -> 1.22 | BW36: =1/AQ36 -> 0.027777778 | BX36: =H36/J36 -> 0.78098954 | BY36: =H36/AV36 -> 0.78098954 | CA36: 32.53 | CB36: 17.44 | CC36: 14.56 | CE36: =BN36 -> 0.30373076 | CG36: =CC36/30.37 -> 0.47942048 | CH36: 0.0219 | CJ36: - | CS36: FY3 Tier 3 | CU36: 10.585 | CV36: 13.17 | CW36: =CV36-CU36 -> 2.585 | CY36: =CG65 -> 0.012281746 | CZ36: =CG66 -> 0.70716927 | DA36: =CZ36-CY36 -> 0.69488752
B38: Meiji Holdings | E38: 2269 JT | F38: JPY | G38: 1070.1 | H38: 1145.5 | J38: 1160 | K38: 342.5 | L38: 135.7 | M38: 47 | O38: =K38/J38 -> 0.29525862 | P38: =L38/J38 -> 0.11698276 | Q38: =BD38/J38 -> 0.070086207 | R38: =M38/J38 -> 0.040517241 | T38: 1105.5 | U38: 1174.9 | V38: 139.7 | W38: 145.1 | Y38: 173.66 | Z38: 150.32 | AA38: 202.37 | AB38: 218.24 | AE38: 0.357 | AG38: 0.0601 | AH38: 0.0635 | AI38: 0.0391 | AJ38: =CH38 -> 0.027 | AL38: 0.044 | AM38: 0.74 | AN38: 0.22 | AO38: 3.85 | AQ38: 365.66 | AV38: =J38 -> 1160 | AW38: =U38 -> 1174.9 | AX38: 1195.7 | AZ38: =L38 -> 135.7 | BA38: =W38 -> 145.1 | BB38: 151.9 | BD38: 81.3 | BE38: 89.5 | BF38: 94.1 | BH38: =AZ38/AV38 -> 0.11698276 | BJ38: =Y38 -> 173.66 | BK38: =AA38 -> 202.37 | BL38: =AB38 -> 218.24 | BN38: =(BL38/BJ38)-1 -> 0.25670851 | BQ38: =H38/AZ38 -> 8.4414149 | BR38: 7.89 | BS38: 7.54 | BU38: =BA38/AW38 -> 0.12349987 | BV38: =AN38 -> 0.22 | BW38: =1/AQ38 -> 0.0027347809 | BX38: =H38/J38 -> 0.9875 | BY38: =H38/AV38 -> 0.9875 | CA38: 22.62 | CB38: 18.74 | CC38: 17.38 | CE38: =BN38 -> 0.25670851 | CG38: =CC38/25.67 -> 0.67705493 | CH38: 0.027 | CJ38: -
B40: NH Foods | E40: 2282 JT | F40: JPY | G40: 674.5 | H40: 863.7 | J40: 1424.1 | K40: 241.4 | L40: 98.4 | M40: 35.1 | O40: =K40/J40 -> 0.16951057 | P40: =L40/J40 -> 0.069096271 | Q40: =BD40/J40 -> 0.037778246 | R40: =M40/J40 -> 0.024647146 | T40: 1303.4 | U40: 1427.4 | V40: 73.9 | W40: 99 | Y40: 358.48 | Z40: 293.66 | AA40: 362.41 | AB40: 419.31 | AE40: 0.449 | AG40: 0.0483 | AH40: 0.0655 | AI40: 0.0351 | AJ40: =CH40 -> 0.0198 | AL40: 0.2493 | AM40: 2.41 | AN40: 1.77 | AO40: 31.37 | AQ40: 42.99 | AV40: =J40 -> 1424.1 | AW40: =U40 -> 1427.4 | AX40: 1454.9 | AZ40: =L40 -> 98.4 | BA40: =W40 -> 99 | BB40: 101.8 | BD40: 53.8 | BE40: 55.9 | BF40: 59.1 | BH40: =AZ40/AV40 -> 0.069096271 | BJ40: =Y40 -> 358.48 | BK40: =AA40 -> 362.41 | BL40: =AB40 -> 419.31 | BN40: =(BL40/BJ40)-1 -> 0.16968869 | BQ40: =H40/AZ40 -> 8.777439 | BR40: 8.73 | BS40: 8.48 | BU40: =BA40/AW40 -> 0.069356873 | BV40: =AN40 -> 1.77 | BW40: =1/AQ40 -> 0.023261224 | BX40: =H40/J40 -> 0.60648831 | BY40: =H40/AV40 -> 0.60648831 | CA40: 21.3 | CB40: 18.78 | CC40: 16.23 | CE40: =BN40 -> 0.16968869 | CG40: =CC40/16.97 -> 0.95639364 | CH40: 0.0198 | CJ40: -
B42: Nippn Corp | E42: 2001 JT | F42: JPY | G42: 231.7 | H42: 256.9 | J42: 415.8 | K42: 103.6 | L42: 33.2 | M42: 16.5 | O42: =K42/J42 -> 0.24915825 | P42: =L42/J42 -> 0.07984608 | Q42: =BD42/J42 -> 0.053391053 | R42: =M42/J42 -> 0.03968254 | T42: 400.5 | U42: 424 | V42: 30.7 | W42: 32.3 | Y42: 188.51 | Z42: 196.49 | AA42: 222.54 | AB42: 213.36 | AE42: 0.554 | AG42: 0.0338 | AH42: 0.064 | AI42: 0.0388 | AJ42: =CH42 -> 0.0242 | AL42: 0.1472 | AM42: 1.78 | AN42: 0.53 | AO42: 6.26 | AQ42: 123.12 | AV42: =J42 -> 415.8 | AW42: =U42 -> 424 | AX42: 439.3 | AZ42: =L42 -> 33.2 | BA42: =W42 -> 32.3 | BB42: 34.1 | BD42: 22.2 | BE42: 21.5 | BF42: 22.6 | BH42: =AZ42/AV42 -> 0.07984608 | BJ42: =Y42 -> 188.51 | BK42: =AA42 -> 222.54 | BL42: =AB42 -> 213.36 | BN42: =(BL42/BJ42)-1 -> 0.13182325 | BQ42: =H42/AZ42 -> 7.7379518 | BR42: 7.93 | BS42: 7.51 | BU42: =BH42 -> 0.07984608 | BV42: =AM42 -> 1.78 | BW42: =1/AQ42 -> 0.0081221572 | BX42: =H42/J42 -> 0.61784512 | BY42: =H42/AV42 -> 0.61784512 | CA42: 10.71 | CB42: 12.26 | CC42: 12.79 | CE42: =BN42 -> 0.13182325 | CG42: =CC42/13.18 -> 0.97040971 | CH42: 0.0242 | CJ42: -
B44: Mean | G44: =AVERAGE(G30:G42) -> 737.12857 | H44: =AVERAGE(H30:H42) -> 740.18571 | J44: =AVERAGE(J30:J42) -> 725.42857 | K44: =AVERAGE(K30:K42) -> 202.22857 | L44: =AVERAGE(L30:L42) -> 78.442857 | M44: =AVERAGE(M30:M42) -> 34.842857 | O44: =AVERAGE(O30:O42) -> 0.305508 | P44: =AVERAGE(P30:P42) -> 0.11608511 | Q44: =AVERAGE(Q30:Q42) -> 0.076397159 | R44: =AVERAGE(R30:R42) -> 0.055538261 | T44: =AVERAGE(T30:T42) -> 690.37143 | U44: =AVERAGE(U30:U42) -> 735.72857 | V44: =AVERAGE(V30:V42) -> 75.085714 | W44: =AVERAGE(W30:W42) -> 81.242857 | Y44: =AVERAGE(Y30:Y42) -> 269.78429 | Z44: =AVERAGE(Z30:Z42) -> 247.15429 | AA44: =AVERAGE(AA30:AA42) -> 291.47857 | AB44: =AVERAGE(AB30:AB42) -> 315.89714 | AG44: =AVERAGE(AG30:AG42) -> 0.051185714 | AH44: =AVERAGE(AH30:AH42) -> 0.076 | AI44: =AVERAGE(AI30:AI42) -> 0.049557143 | AJ44: =AVERAGE(AJ30:AJ42) -> 0.021257143 | AL44: =AVERAGE(AL30:AL42) -> 0.11861429 | AM44: =AVERAGE(AM30:AM42) -> 1.1985714 | AN44: =AVERAGE(AN30:AN42) -> -0.22571429 | AO44: =AVERAGE(AO30:AO42) -> -2.3871429 | AQ44: =AVERAGE(AQ30:AQ42) -> 188.51286 | AU44: Mean | AV44: =AVERAGE(AV30:AV42) -> 725.42857 | AW44: =AVERAGE(AW30:AW42) -> 735.72857 | AX44: =AVERAGE(AX30:AX42) -> 753.84286 | AZ44: =AVERAGE(AZ30:AZ42) -> 78.442857 | BA44: =AVERAGE(BA30:BA42) -> 81.242857 | BB44: =AVERAGE(BB30:BB42) -> 85.414286 | BD44: =AVERAGE(BD30:BD42) -> 49.942857 | BE44: =AVERAGE(BE30:BE42) -> 52.657143 | BF44: =AVERAGE(BF30:BF42) -> 55.485714 | BH44: =AVERAGE(BH30:BH42) -> 0.11608511 | BJ44: =AVERAGE(BJ30:BJ42) -> 269.78429 | BK44: =AVERAGE(BK30:BK42) -> 291.47857 | BL44: =AVERAGE(BL30:BL42) -> 315.89714 | BN44: =AVERAGE(BN30:BN42) -> 0.18495793 | BP44: Mean | BQ44: =AVERAGE(BQ30:BQ42) -> 9.3959642 | BR44: =AVERAGE(BR30:BR42) -> 9.11 | BS44: =AVERAGE(BS30:BS42) -> 8.6371429 | BU44: =AVERAGE(BU30:BU42) -> 0.11829198 | BV44: =AVERAGE(BV30:BV42) -> -0.047142857 | BW44: =AVERAGE(BW30:BW42) -> 0.011334438 | BX44: =AVERAGE(BX30:BX42) -> 1.1275006 | BY44: =AVERAGE(BY30:BY42) -> 1.1275006 | CA44: =AVERAGE(CA30:CA42) -> 20.617143 | CB44: =AVERAGE(CB30:CB42) -> 18.065714 | CC44: =AVERAGE(CC30:CC42) -> 16.717143 | CE44: =AVERAGE(CE30:CE42) -> 0.18495793 | CG44: =AVERAGE(CG30:CG42) -> 1.0409398 | CH44: =AVERAGE(CH30:CH42) -> 0.021257143
B45: Median | G45: =MEDIAN(G30:G42) -> 674.5 | H45: =MEDIAN(H30:H42) -> 775.8 | J45: =MEDIAN(J30:J42) -> 515 | K45: =MEDIAN(K30:K42) -> 154.3 | L45: =MEDIAN(L30:L42) -> 76.1 | M45: =MEDIAN(M30:M42) -> 35.1 | O45: =MEDIAN(O30:O42) -> 0.29392287 | P45: =MEDIAN(P30:P42) -> 0.10303857 | Q45: =MEDIAN(Q30:Q42) -> 0.067393845 | R45: =MEDIAN(R30:R42) -> 0.040517241 | T45: =MEDIAN(T30:T42) -> 503.1 | U45: =MEDIAN(U30:U42) -> 531.3 | V45: =MEDIAN(V30:V42) -> 73.9 | W45: =MEDIAN(W30:W42) -> 77.8 | Y45: =MEDIAN(Y30:Y42) -> 188.51 | Z45: =MEDIAN(Z30:Z42) -> 196.49 | AA45: =MEDIAN(AA30:AA42) -> 222.54 | AB45: =MEDIAN(AB30:AB42) -> 218.24 | AG45: =MEDIAN(AG30:AG42) -> 0.046 | AH45: =MEDIAN(AH30:AH42) -> 0.0655 | AI45: =MEDIAN(AI30:AI42) -> 0.0391 | AJ45: =MEDIAN(AJ30:AJ42) -> 0.0219 | AL45: =MEDIAN(AL30:AL42) -> 0.121 | AM45: =MEDIAN(AM30:AM42) -> 0.93 | AN45: =MEDIAN(AN30:AN42) -> 0.22 | AO45: =MEDIAN(AO30:AO42) -> 3.85 | AQ45: =MEDIAN(AQ30:AQ42) -> 123.12 | AU45: Median | AV45: =MEDIAN(AV30:AV42) -> 515 | AW45: =MEDIAN(AW30:AW42) -> 531.3 | AX45: =MEDIAN(AX30:AX42) -> 555.4 | AZ45: =MEDIAN(AZ30:AZ42) -> 76.1 | BA45: =MEDIAN(BA30:BA42) -> 77.8 | BB45: =MEDIAN(BB30:BB42) -> 82 | BD45: =MEDIAN(BD30:BD42) -> 46.9 | BE45: =MEDIAN(BE30:BE42) -> 48.8 | BF45: =MEDIAN(BF30:BF42) -> 50.2 | BH45: =MEDIAN(BH30:BH42) -> 0.10303857 | BJ45: =MEDIAN(BJ30:BJ42) -> 188.51 | BK45: =MEDIAN(BK30:BK42) -> 222.54 | BL45: =MEDIAN(BL30:BL42) -> 218.24 | BN45: =MEDIAN(BN30:BN42) -> 0.16968869 | BP45: Median | BQ45: =MEDIAN(BQ30:BQ42) -> 8.777439 | BR45: =MEDIAN(BR30:BR42) -> 8.73 | BS45: =MEDIAN(BS30:BS42) -> 8.48 | BU45: =MEDIAN(BU30:BU42) -> 0.10815402 | BV45: =MEDIAN(BV30:BV42) -> 0.22 | BW45: =MEDIAN(BW30:BW42) -> 0.0081221572 | BX45: =MEDIAN(BX30:BX42) -> 0.9875 | BY45: =MEDIAN(BY30:BY42) -> 0.9875 | CA45: =MEDIAN(CA30:CA42) -> 20.77 | CB45: =MEDIAN(CB30:CB42) -> 17.5 | CC45: =MEDIAN(CC30:CC42) -> 16.25 | CE45: =MEDIAN(CE30:CE42) -> 0.16968869 | CG45: =MEDIAN(CG30:CG42) -> 0.97040971 | CH45: =MEDIAN(CH30:CH42) -> 0.0219
B46: 25th | G46: =_xlfn.PERCENTILE.INC(G30:G42,0.25) -> 506.5 | H46: =_xlfn.PERCENTILE.INC(H30:H42,0.25) -> 525.8 | J46: =_xlfn.PERCENTILE.INC(J30:J42,0.25) -> 499.6 | K46: =_xlfn.PERCENTILE.INC(K30:K42,0.25) -> 144.6 | L46: =_xlfn.PERCENTILE.INC(L30:L42,0.25) -> 55.3 | M46: =_xlfn.PERCENTILE.INC(M30:M42,0.25) -> 20.7 | O46: =_xlfn.PERCENTILE.INC(O30:O42,0.25) -> 0.24720725 | P46: =_xlfn.PERCENTILE.INC(P30:P42,0.25) -> 0.091084593 | Q46: =_xlfn.PERCENTILE.INC(Q30:Q42,0.25) -> 0.055956034 | R46: =_xlfn.PERCENTILE.INC(R30:R42,0.25) -> 0.035712878 | T46: =_xlfn.PERCENTILE.INC(T30:T42,0.25) -> 486.5 | U46: =_xlfn.PERCENTILE.INC(U30:U42,0.25) -> 508.95 | V46: =_xlfn.PERCENTILE.INC(V30:V42,0.25) -> 53.15 | W46: =_xlfn.PERCENTILE.INC(W30:W42,0.25) -> 57.15 | Y46: =_xlfn.PERCENTILE.INC(Y30:Y42,0.25) -> 171.99 | Z46: =_xlfn.PERCENTILE.INC(Z30:Z42,0.25) -> 164.345 | AA46: =_xlfn.PERCENTILE.INC(AA30:AA42,0.25) -> 194.635 | AB46: =_xlfn.PERCENTILE.INC(AB30:AB42,0.25) -> 210.255 | AG46: =_xlfn.PERCENTILE.INC(AG30:AG42,0.25) -> 0.0389 | AH46: =_xlfn.PERCENTILE.INC(AH30:AH42,0.25) -> 0.06455 | AI46: =_xlfn.PERCENTILE.INC(AI30:AI42,0.25) -> 0.03695 | AJ46: =_xlfn.PERCENTILE.INC(AJ30:AJ42,0.25) -> 0.0184 | AL46: =_xlfn.PERCENTILE.INC(AL30:AL42,0.25) -> 0.04365 | AM46: =_xlfn.PERCENTILE.INC(AM30:AM42,0.25) -> 0.565 | AN46: =_xlfn.PERCENTILE.INC(AN30:AN42,0.25) -> -1.45 | AO46: =_xlfn.PERCENTILE.INC(AO30:AO42,0.25) -> -19.68 | AQ46: =_xlfn.PERCENTILE.INC(AQ30:AQ42,0.25) -> 70.335 | AU46: 25th | AV46: =_xlfn.PERCENTILE.INC(AV30:AV42,0.25) -> 499.6 | AW46: =_xlfn.PERCENTILE.INC(AW30:AW42,0.25) -> 508.95 | AX46: =_xlfn.PERCENTILE.INC(AX30:AX42,0.25) -> 523.75 | AZ46: =_xlfn.PERCENTILE.INC(AZ30:AZ42,0.25) -> 55.3 | BA46: =_xlfn.PERCENTILE.INC(BA30:BA42,0.25) -> 57.15 | BB46: =_xlfn.PERCENTILE.INC(BB30:BB42,0.25) -> 60.7 | BD46: =_xlfn.PERCENTILE.INC(BD30:BD42,0.25) -> 33.8 | BE46: =_xlfn.PERCENTILE.INC(BE30:BE42,0.25) -> 35.75 | BF46: =_xlfn.PERCENTILE.INC(BF30:BF42,0.25) -> 38.7 | BH46: =_xlfn.PERCENTILE.INC(BH30:BH42,0.25) -> 0.091084593 | BJ46: =_xlfn.PERCENTILE.INC(BJ30:BJ42,0.25) -> 171.99 | BK46: =_xlfn.PERCENTILE.INC(BK30:BK42,0.25) -> 194.635 | BL46: =_xlfn.PERCENTILE.INC(BL30:BL42,0.25) -> 210.255 | BN46: =_xlfn.PERCENTILE.INC(BN30:BN42,0.25) -> 0.12532911 | BP46: 25th | BQ46: =_xlfn.PERCENTILE.INC(BQ30:BQ42,0.25) -> 8.0896833 | BR46: =_xlfn.PERCENTILE.INC(BR30:BR42,0.25) -> 7.91 | BS46: =_xlfn.PERCENTILE.INC(BS30:BS42,0.25) -> 7.525 | BU46: =_xlfn.PERCENTILE.INC(BU30:BU42,0.25) -> 0.089522761 | BV46: =_xlfn.PERCENTILE.INC(BV30:BV42,0.25) -> -1.45 | BW46: =_xlfn.PERCENTILE.INC(BW30:BW42,0.25) -> 0.0038708954 | BX46: =_xlfn.PERCENTILE.INC(BX30:BX42,0.25) -> 0.69941733 | BY46: =_xlfn.PERCENTILE.INC(BY30:BY42,0.25) -> 0.69941733 | CA46: =_xlfn.PERCENTILE.INC(CA30:CA42,0.25) -> 18.195 | CB46: =_xlfn.PERCENTILE.INC(CB30:CB42,0.25) -> 17.35 | CC46: =_xlfn.PERCENTILE.INC(CC30:CC42,0.25) -> 15.395 | CE46: =_xlfn.PERCENTILE.INC(CE30:CE42,0.25) -> 0.12532911 | CG46: =_xlfn.PERCENTILE.INC(CG30:CG42,0.25) -> 0.81672428 | CH46: =_xlfn.PERCENTILE.INC(CH30:CH42,0.25) -> 0.0184
B47: 75th | G47: =_xlfn.PERCENTILE.INC(G30:G42,0.75) -> 967.8 | H47: =_xlfn.PERCENTILE.INC(H30:H42,0.75) -> 975.75 | J47: =_xlfn.PERCENTILE.INC(J30:J42,0.75) -> 861.95 | K47: =_xlfn.PERCENTILE.INC(K30:K42,0.75) -> 263 | L47: =_xlfn.PERCENTILE.INC(L30:L42,0.75) -> 96.75 | M47: =_xlfn.PERCENTILE.INC(M30:M42,0.75) -> 43.45 | O47: =_xlfn.PERCENTILE.INC(O30:O42,0.75) -> 0.29743514 | P47: =_xlfn.PERCENTILE.INC(P30:P42,0.75) -> 0.13681579 | Q47: =_xlfn.PERCENTILE.INC(Q30:Q42,0.75) -> 0.083313997 | R47: =_xlfn.PERCENTILE.INC(R30:R42,0.75) -> 0.063952921 | T47: =_xlfn.PERCENTILE.INC(T30:T42,0.75) -> 826.3 | U47: =_xlfn.PERCENTILE.INC(U30:U42,0.75) -> 874.75 | V47: =_xlfn.PERCENTILE.INC(V30:V42,0.75) -> 87.5 | W47: =_xlfn.PERCENTILE.INC(W30:W42,0.75) -> 99.6 | Y47: =_xlfn.PERCENTILE.INC(Y30:Y42,0.75) -> 287.395 | Z47: =_xlfn.PERCENTILE.INC(Z30:Z42,0.75) -> 248.53 | AA47: =_xlfn.PERCENTILE.INC(AA30:AA42,0.75) -> 298.915 | AB47: =_xlfn.PERCENTILE.INC(AB30:AB42,0.75) -> 350.66 | AG47: =_xlfn.PERCENTILE.INC(AG30:AG42,0.75) -> 0.0542 | AH47: =_xlfn.PERCENTILE.INC(AH30:AH42,0.75) -> 0.07205 | AI47: =_xlfn.PERCENTILE.INC(AI30:AI42,0.75) -> 0.0484 | AJ47: =_xlfn.PERCENTILE.INC(AJ30:AJ42,0.75) -> 0.02455 | AL47: =_xlfn.PERCENTILE.INC(AL30:AL42,0.75) -> 0.1835 | AM47: =_xlfn.PERCENTILE.INC(AM30:AM42,0.75) -> 1.945 | AN47: =_xlfn.PERCENTILE.INC(AN30:AN42,0.75) -> 0.875 | AO47: =_xlfn.PERCENTILE.INC(AO30:AO42,0.75) -> 15.955 | AQ47: =_xlfn.PERCENTILE.INC(AQ30:AQ42,0.75) -> 282.69 | AV47: =_xlfn.PERCENTILE.INC(AV30:AV42,0.75) -> 861.95 | AW47: =_xlfn.PERCENTILE.INC(AW30:AW42,0.75) -> 874.75 | AX47: =_xlfn.PERCENTILE.INC(AX30:AX42,0.75) -> 889.9 | AZ47: =_xlfn.PERCENTILE.INC(AZ30:AZ42,0.75) -> 96.75 | BA47: =_xlfn.PERCENTILE.INC(BA30:BA42,0.75) -> 99.6 | BB47: =_xlfn.PERCENTILE.INC(BB30:BB42,0.75) -> 104.25 | BD47: =_xlfn.PERCENTILE.INC(BD30:BD42,0.75) -> 65.8 | BE47: =_xlfn.PERCENTILE.INC(BE30:BE42,0.75) -> 68.65 | BF47: =_xlfn.PERCENTILE.INC(BF30:BF42,0.75) -> 72.05 | BH47: =_xlfn.PERCENTILE.INC(BH30:BH42,0.75) -> 0.13681579 | BJ47: =_xlfn.PERCENTILE.INC(BJ30:BJ42,0.75) -> 287.395 | BK47: =_xlfn.PERCENTILE.INC(BK30:BK42,0.75) -> 298.915 | BL47: =_xlfn.PERCENTILE.INC(BL30:BL42,0.75) -> 350.66 | BN47: =_xlfn.PERCENTILE.INC(BN30:BN42,0.75) -> 0.23647426 | BQ47: =_xlfn.PERCENTILE.INC(BQ30:BQ42,0.75) -> 10.814243 | BR47: =_xlfn.PERCENTILE.INC(BR30:BR42,0.75) -> 10.325 | BS47: =_xlfn.PERCENTILE.INC(BS30:BS42,0.75) -> 9.675 | BU47: =_xlfn.PERCENTILE.INC(BU30:BU42,0.75) -> 0.14144672 | BV47: =_xlfn.PERCENTILE.INC(BV30:BV42,0.75) -> 1.495 | BW47: =_xlfn.PERCENTILE.INC(BW30:BW42,0.75) -> 0.016749367 | BX47: =_xlfn.PERCENTILE.INC(BX30:BX42,0.75) -> 1.3937241 | BY47: =_xlfn.PERCENTILE.INC(BY30:BY42,0.75) -> 1.3937241 | CA47: =_xlfn.PERCENTILE.INC(CA30:CA42,0.75) -> 21.96 | CB47: =_xlfn.PERCENTILE.INC(CB30:CB42,0.75) -> 18.76 | CC47: =_xlfn.PERCENTILE.INC(CC30:CC42,0.75) -> 17.55 | CE47: =_xlfn.PERCENTILE.INC(CE30:CE42,0.75) -> 0.23647426 | CG47: =_xlfn.PERCENTILE.INC(CG30:CG42,0.75) -> 1.1947921 | CH47: =_xlfn.PERCENTILE.INC(CH30:CH42,0.75) -> 0.02455
B49: Tier 3: Global Packaged Food competitors | AE49: Tier 3: Global Packaged Food competitors | AU49: Tier 3: Global Packaged Food competitors | BP49: Tier 3: Global Packaged Food competitors
CE50: x | CQ50: EV/EBITDA | DA50: PE
B51: Tingyi (Cayman) Hldg | E51: 322 HK | F51: HKD to JPY | G51: 1412.1 | H51: 1548.3 | J51: 1650 | K51: 561.6 | L51: 206.2 | M51: 85.4 | O51: =K51/J51 -> 0.34036364 | P51: =L51/J51 -> 0.1249697 | Q51: =BD51/J51 -> 0.030242424 | R51: =M51/J51 -> 0.051757576 | T51: 1698.6 | U51: 1803.3 | V51: 200.1 | W51: 230 | Y51: 15.15 | Z51: 13.94 | AA51: 16.96 | AB51: 18.1 | AE51: 0.577 | AG51: 0.14 | AH51: 0.3257 | AI51: 0.0735 | AL51: 0.2544 | AM51: - | AN51: - | AO51: - | AQ51: 22.44 | AV51: =J51 -> 1650 | AW51: =U51 -> 1803.3 | AX51: 323.2 | AZ51: =L51 -> 206.2 | BA51: =U51 -> 1803.3 | BB51: 84.6 | BD51: 49.9 | BE51: 56.5 | BF51: 76.2 | BH51: =P51 -> 0.1249697 | BJ51: =Y51 -> 15.15 | BK51: =AA51 -> 16.96 | BL51: =AB51 -> 18.1 | BN51: =(BL51/BJ51)-1 -> 0.19471947 | BQ51: =H51/AZ51 -> 7.5087294 | BR51: 6.76 | BS51: 6.5 | BU51: =BR51/AW51 -> 0.003748683 | BV51: =AN51 -> - | BW51: =1/AO51 -> #VALUE! | BX51: =H51/AV51 -> 0.93836364 | BY51: =H51/BD51 -> 31.028056 | CA51: 15.18 | CB51: 14.7 | CC51: 13.77 | CE51: =BN51 -> 0.19471947 | CG51: =CC51/19.472 -> 0.70716927 | CH51: 0.0579 | CJ51: 8.09 | CQ51: FY | CR51: Metric | CS51: Range | CU51: Implied EV | DA51: FY | DB51: EPS | DC51: Range | DE51: Implied Price
CU52: 25th | CV52: Median | CW52: 75th | DE52: 25th | DF52: Median | DG52: 75th
B53: Samyang | E53: 003230 KS | F53: KRW to JPY | G53: 839.4 | H53: 866.3 | J53: 232.3 | K53: 99.3 | L53: 56.2 | M53: 39.1 | O53: =K53/J53 -> 0.42746449 | P53: =L53/J53 -> 0.24192854 | Q53: =BD53/J53 -> 0 | R53: =M53/J53 -> 0.16831683 | T53: 191.9 | U53: 252.7 | V53: 43.4 | W53: 63.4 | Y53: 5249.21 | Z53: 4054.22 | AA53: 5641.88 | AB53: 7825.89 | AE53: -0.29 | AG53: 0.2476 | AH53: 0.4054 | AI53: 0.2055 | AL53: 0.2338 | AM53: 1.07 | AN53: 0.45 | AO53: 21.93 | AQ53: 23.5 | AV53: =J53 -> 232.3 | AW53: =U53 -> 252.7 | AZ53: =L53 -> 56.2 | BA53: =U53 -> 252.7 | BH53: =P53 -> 0.24192854 | BJ53: =Y53 -> 5249.21 | BK53: =AA53 -> 5641.88 | BL53: =AB53 -> 7825.89 | BN53: =(BL53/BJ53)-1 -> 0.49087005 | BQ53: =H53/AZ53 -> 15.414591 | BR53: 14.15 | BS53: 10.6 | BU53: =BR53/AW53 -> 0.055995251 | BV53: =AN53 -> 0.45 | BW53: =1/AO53 -> 0.045599635 | BX53: =H53/AV53 -> 3.7292294 | BY53: - | CA53: 21.65 | CB53: 20.45 | CE53: =BN53 -> 0.49087005 | CG53: =CC53/49 -> 0 | CH53: 0.0037 | CJ53: -2.33 | CQ53: LTM | CR53: =#REF! -> #REF! | CS53: 9.18x-13.61x | CU53: =CR53*#REF! -> #REF! | CV53: =CR53*#REF! -> #REF! | CW53: =CR53*#REF! -> #REF! | DA53: LTM | DB53: =#REF! -> #REF! | DC53: 23.46x-40.0x | DE53: =DB53*#REF! -> #REF! | DF53: =DB53*#REF! -> #REF! | DG53: =DB53*#REF! -> #REF!
CQ54: 2026E | CR54: =#REF! -> #REF! | CS54: 8.56x-13.15x | CU54: =#REF!*CR54 -> #REF! | CV54: =#REF!*CR54 -> #REF! | CW54: =#REF!*CR54 -> #REF! | DA54: 2026E | DB54: =#REF! -> #REF! | DC54: 21.51x-27.94x | DE54: =DB54*#REF! -> #REF! | DF54: =DB54*#REF! -> #REF! | DG54: =DB54*#REF! -> #REF!
B55: Uni-President China Holdings | E55: 220 HK | F55: HKD to JPY | G55: 668.9 | H55: 602 | J55: 663.2 | K55: 217.9 | L55: 76.7 | M55: 44.3 | O55: =K55/J55 -> 0.3285585 | P55: =L55/J55 -> 0.11565139 | Q55: =BD55/J55 -> 0.081272618 | R55: =M55/J55 -> 0.066797346 | T55: 638.8 | U55: 723.2 | V55: 69.5 | W55: 84.8 | Y55: 10.24 | Z55: 8.85 | AA55: 11.51 | AB55: 12.44 | AE55: 0.431 | AG55: 0.1283 | AH55: 0.1683 | AI55: 0.0953 | AL55: 0.0124 | AM55: - | AN55: - | AO55: - | AQ55: 98.66 | AV55: =J55 -> 663.2 | AW55: =U55 -> 723.2 | AX55: 764 | AZ55: =L55 -> 76.7 | BA55: =U55 -> 723.2 | BB55: 90.8 | BD55: 53.9 | BE55: 60.7 | BF55: 64.7 | BH55: =P55 -> 0.11565139 | BJ55: =Y55 -> 10.24 | BK55: =AA55 -> 11.51 | BL55: =AB55 -> 12.44 | BN55: =(BL55/BJ55)-1 -> 0.21484375 | BQ55: =H55/AZ55 -> 7.8487614 | BR55: 6.96 | BS55: 6.5 | BU55: =BR55/AW55 -> 0.0096238938 | BV55: =AN55 -> - | BW55: =1/AO55 -> #VALUE! | BX55: =H55/AV55 -> 0.90772014 | BY55: =H55/BD55 -> 11.168831 | CA55: 13.65 | CB55: 13.37 | CC55: 12.38 | CE55: =BN55 -> 0.21484375 | CG55: =CC55/21/48 -> 0.012281746 | CH55: 0.0605 | CJ55: 9.72 | CQ55: 2027E | CR55: =#REF! -> #REF! | CS55: 8.00x - 12.00x | CU55: =CR55*#REF! -> #REF! | CV55: =CR55*#REF! -> #REF! | CW55: =CR55*#REF! -> #REF! | DA55: 2027E | DB55: =#REF! -> #REF! | DC55: 19.42x-25.05x | DE55: =DB55*#REF! -> #REF! | DF55: =DB55*#REF! -> #REF! | DG55: =DB55*#REF! -> #REF!
CS56: ROIC, ROE, ROA
B57: PT Indofood Sukes Makmur | E57: INDF IJ | F57: IDR to JPY | G57: 564.4 | H57: 1150.6 | J57: 1099.8 | K57: 373.6 | L57: 245.5 | M57: 65.1 | O57: =K57/J57 -> 0.33969813 | P57: =L57/J57 -> 0.2232224 | Q57: =BD57/J57 -> 0.18939807 | R57: =M57/J57 -> 0.05919258 | T57: 1106 | U57: 1137.7 | V57: 250.2 | W57: 250.9 | Y57: 7.41 | Z57: 8.69 | AA57: 11.48 | AB57: 12.51 | AE57: 0.527 | AG57: 0.0819 | AH57: 0.1048 | AI57: 0.0346 | AL57: 0.3521 | AM57: 2.85 | AN57: 0.76 | AO57: 17.53 | AQ57: 6.84 | AV57: =J57 -> 1099.8 | AW57: =U57 -> 1137.7 | AX57: 1195.2 | AZ57: =L57 -> 245.5 | BA57: =U57 -> 1137.7 | BB57: 264.7 | BD57: 208.3 | BE57: 215.8 | BF57: 227.2 | BH57: =P57 -> 0.2232224 | BJ57: =Y57 -> 7.41 | BK57: =AA57 -> 11.48 | BL57: =AB57 -> 12.51 | BN57: =(BL57/BJ57)-1 -> 0.68825911 | BQ57: =H57/AZ57 -> 4.6867617 | BR57: 4.76 | BS57: 4.51 | BU57: =BR57/AW57 -> 0.0041838798 | BV57: =AN57 -> 0.76 | BW57: =1/AO57 -> 0.057045066 | BX57: =H57/AV57 -> 1.0461902 | BY57: =H57/BD57 -> 5.5237638 | CA57: 7.84 | CB57: 5.67 | CC57: 5.2 | CE57: =BN57 -> 0.68825911 | CG57: =CC57/68.8 -> 0.075581395 | CH57: 0.0404 | CJ57: 19.4 | CS57: ROIC
CS58: FY | CT58: 25th | CU58: 75th | CV58: Diff | CX58: FY | CY58: 25th | CZ58: 75th | DA58: Diff
B59: Nong Shim | E59: 004370 KS | F59: KRW to JPY | G59: 271.5 | H59: 168.4 | J59: 369.3 | K59: 104.4 | L59: 31.3 | M59: 16.8 | O59: =K59/J59 -> 0.28269699 | P59: =L59/J59 -> 0.084754942 | Q59: =BD59/J59 -> 0.048740861 | R59: =M59/J59 -> 0.04549147 | T59: 381.8 | U59: 379.3 | V59: 31.4 | W59: 34.3 | Y59: 2785.26 | Z59: 2874.6 | AA59: 3183.02 | AB59: 3592.25 | AE59: 0.084 | AG59: 0.0458 | AH59: 0.0595 | AI59: 0.044 | AL59: 0.0565 | AM59: 0.6 | AN59: -3.32 | AO59: -35.38 | AQ59: 46.47 | AV59: =J59 -> 369.3 | AW59: =U59 -> 379.3 | AX59: - | AZ59: =L59 -> 31.3 | BA59: =U59 -> 379.3 | BB59: - | BD59: 18 | BE59: 23.9 | BF59: - | BH59: =P59 -> 0.084754942 | BJ59: =Y59 -> 2785.26 | BK59: =AA59 -> 3183.02 | BL59: =AB59 -> 3592.25 | BN59: =(BL59/BJ59)-1 -> 0.28973597 | BQ59: =H59/AZ59 -> 5.3801917 | BR59: 4.49 | BS59: - | BU59: =BR59/AW59 -> 0.011837596 | BV59: =AN59 -> -3.32 | BW59: =1/AO59 -> -0.028264556 | BX59: =H59/AV59 -> 0.45599783 | BY59: =H59/BD59 -> 9.3555556 | CA59: 14.82 | CB59: 14.18 | CC59: - | CE59: =BN59 -> 0.28973597 | CG59: - | CH59: - | CJ59: 8.67 | CS59: LTM Tier 1 ROIC | CT59: =AG25 -> 0.03865 | CU59: =AG26 -> 0.0643 | CV59: =CU59-CT59 -> 0.02565 | CX59: LTM Tier 1 | CY59: =AH25 -> 0.04785 | CZ59: 0.099
CS60: LTM Tier 1 ROE | CT60: =AH25 -> 0.04785 | CU60: 0.099 | CV60: =CU60-CT60 -> 0.05115 | CX60: FY1 Tier 1
B61: General Mills | E61: GIS US | F61: USD to JPY | G61: 4043.3 | H61: 6088.3 | J61: 2804.6 | K61: 950.6 | L61: 550 | M61: 300.8 | O61: =K61/J61 -> 0.33894316 | P61: =L61/J61 -> 0.1961064 | Q61: =BD61/J61 -> 0.16729658 | R61: =M61/J61 -> 0.10725237 | T61: 2931 | U61: 2919.2 | V61: 632.4 | W61: 547.7 | Y61: 549.65 | Z61: 667.89 | AA61: 573.17 | AB61: 584.24 | AE61: -0.192 | AG61: 0.102 | AH61: 0.2175 | AI61: 0.0611 | AL61: 0.4625 | AM61: 3.73 | AN61: 3.54 | AO61: 139.9 | AQ61: 7.32 | AV61: =J61 -> 2804.6 | AW61: =U61 -> 2919.2 | AX61: 2897.5 | AZ61: =L61 -> 550 | BA61: =U61 -> 2919.2 | BB61: 550.4 | BD61: 469.2 | BE61: 458.7 | BF61: 460 | BH61: =P61 -> 0.1961064 | BJ61: =Y61 -> 549.65 | BK61: =AA61 -> 573.17 | BL61: =AB61 -> 584.24 | BN61: =(BL61/BJ61)-1 -> 0.062930956 | BQ61: =H61/AZ61 -> 11.069636 | BR61: 11.12 | BS61: 11.06 | BU61: =BR61/AW61 -> 0.0038092628 | BV61: =AN61 -> 3.54 | BW61: =1/AO61 -> 0.0071479628 | BX61: =H61/AV61 -> 2.1708265 | BY61: =H61/BD61 -> 12.975916 | CA61: 13.14 | CB61: 13.22 | CC61: 12.97 | CE61: =BN61 -> 0.062930956 | CG61: =CC61/6.2 -> 2.0919355 | CH61: 0.0502 | CJ61: 6.78 | CS61: LTM Tier ROA | CT61: =AI25 -> 0.0313 | CU61: 0.0502 | CV61: =CU61-CT61 -> 0.0189 | CX61: FY2 Tier 1
CS62: FY 1 Tier 2 ROIC | CT62: =AG65 -> 0.086925 | CU62: =AG66 -> 0.137075 | CV62: =CU62-CT62 -> 0.05015 | CX62: LTM Tier 2
B63: Mean | AV63: Mean | BP63: Mean | CS63: FYI Tier 2 ROE | CT63: =AH65 -> 0.120675 | CU63: =AH66 -> 0.29865 | CV63: =CU63-CT63 -> 0.177975 | CX63: FY1 Tier 2
B64: Median | G64: =MEDIAN(G51:G61) -> 754.15 | H64: =MEDIAN(H51:H61) -> 1008.45 | J64: =MEDIAN(J51:J61) -> 881.5 | K64: =MEDIAN(K51:K61) -> 295.75 | L64: =MEDIAN(L51:L61) -> 141.45 | M64: =MEDIAN(M51:M61) -> 54.7 | O64: =MEDIAN(O51:O61) -> 0.33932065 | P64: =MEDIAN(P51:P61) -> 0.16053805 | Q64: =MEDIAN(Q51:Q61) -> 0.065006739 | R64: =MEDIAN(R51:R61) -> 0.062994963 | T64: =MEDIAN(T51:T61) -> 872.4 | U64: =MEDIAN(U51:U61) -> 930.45 | V64: =MEDIAN(V51:V61) -> 134.8 | W64: =MEDIAN(W51:W61) -> 157.4 | Y64: =MEDIAN(Y51:Y61) -> 282.4 | Z64: =MEDIAN(Z51:Z61) -> 340.915 | AA64: =MEDIAN(AA51:AA61) -> 295.065 | AB64: =MEDIAN(AB51:AB61) -> 301.17 | AG64: =MEDIAN(AG51:AG61) -> 0.11515 | AH64: =MEDIAN(AH51:AH61) -> 0.1929 | AI64: =MEDIAN(AI51:AI61) -> 0.0673 | AL64: =MEDIAN(AL51:AL61) -> 0.2441 | AM64: =MEDIAN(AM51:AM61) -> 1.96 | AN64: =MEDIAN(AN51:AN61) -> 0.605 | AO64: =MEDIAN(AO51:AO61) -> 19.73 | AQ64: =MEDIAN(AQ51:AQ61) -> 22.97 | AX64: =MEDIAN(AX51:AX61) -> 979.6 | BB64: =MEDIAN(BB51:BB61) -> 177.75 | BD64: =MEDIAN(BD51:BD61) -> 53.9 | BE64: =MEDIAN(BE51:BE61) -> 60.7 | BF64: =MEDIAN(BF51:BF61) -> 151.7 | BP64: Median | BQ64: =MEDIAN(BQ51:BQ61) -> 7.6787454 | BR64: =MEDIAN(BR51:BR61) -> 6.86 | BS64: =MEDIAN(BS51:BS61) -> 6.5 | CA64: =MEDIAN(CA51:CA61) -> 14.235 | CB64: =MEDIAN(CB51:CB61) -> 13.775 | CC64: =MEDIAN(CC51:CC61) -> 12.675 | CH64: =MEDIAN(CH51:CH61) -> 0.0502 | CJ64: =MEDIAN(CJ51:CJ61) -> 8.38 | CQ64: EV/EBITDA - Tier 2 | CS64: FY1 Tier 2 ROA | CT64: =AI65 -> 0.048275 | CU64: =8.99% -> 0.0899 | CV64: =CU64-CT64 -> 0.041625 | CX64: FY2 Tier 2
B65: 25th | G65: =_xlfn.PERCENTILE.INC(G51:G61,0.25) -> 590.525 | H65: =_xlfn.PERCENTILE.INC(H51:H61,0.25) -> 668.075 | J65: =_xlfn.PERCENTILE.INC(J51:J61,0.25) -> 442.775 | K65: =_xlfn.PERCENTILE.INC(K51:K61,0.25) -> 132.775 | L65: =_xlfn.PERCENTILE.INC(L51:L61,0.25) -> 61.325 | M65: =_xlfn.PERCENTILE.INC(M51:M61,0.25) -> 40.4 | O65: =_xlfn.PERCENTILE.INC(O51:O61,0.25) -> 0.33115467 | P65: =_xlfn.PERCENTILE.INC(P51:P61,0.25) -> 0.11798096 | Q65: =_xlfn.PERCENTILE.INC(Q51:Q61,0.25) -> 0.034867033 | R65: =_xlfn.PERCENTILE.INC(R51:R61,0.25) -> 0.053616327 | T65: =_xlfn.PERCENTILE.INC(T51:T61,0.25) -> 446.05 | U65: =_xlfn.PERCENTILE.INC(U51:U61,0.25) -> 465.275 | V65: =_xlfn.PERCENTILE.INC(V51:V61,0.25) -> 49.925 | W65: =_xlfn.PERCENTILE.INC(W51:W61,0.25) -> 68.75 | Y65: =_xlfn.PERCENTILE.INC(Y51:Y61,0.25) -> 11.4675 | Z65: =_xlfn.PERCENTILE.INC(Z51:Z61,0.25) -> 10.1225 | AA65: =_xlfn.PERCENTILE.INC(AA51:AA61,0.25) -> 12.8725 | AB65: =_xlfn.PERCENTILE.INC(AB51:AB61,0.25) -> 13.9075 | AG65: =_xlfn.PERCENTILE.INC(AG51:AG61,0.25) -> 0.086925 | AH65: =_xlfn.PERCENTILE.INC(AH51:AH61,0.25) -> 0.120675 | AI65: =_xlfn.PERCENTILE.INC(AI51:AI61,0.25) -> 0.048275 | AL65: =_xlfn.PERCENTILE.INC(AL51:AL61,0.25) -> 0.100825 | AM65: =_xlfn.PERCENTILE.INC(AM51:AM61,0.25) -> 0.9525 | AN65: =_xlfn.PERCENTILE.INC(AN51:AN61,0.25) -> -0.4925 | AO65: =_xlfn.PERCENTILE.INC(AO51:AO61,0.25) -> 4.3025 | AQ65: =_xlfn.PERCENTILE.INC(AQ51:AQ61,0.25) -> 11.1 | AV65: =_xlfn.PERCENTILE.INC(AV51:AV61,0.25) -> 442.775 | AW65: =_xlfn.PERCENTILE.INC(AW51:AW61,0.25) -> 465.275 | AX65: =_xlfn.PERCENTILE.INC(AX51:AX61,0.25) -> 653.8 | AZ65: =_xlfn.PERCENTILE.INC(AZ51:AZ61,0.25) -> 61.325 | BA65: =_xlfn.PERCENTILE.INC(BA51:BA61,0.25) -> 465.275 | BB65: =_xlfn.PERCENTILE.INC(BB51:BB61,0.25) -> 89.25 | BD65: =_xlfn.PERCENTILE.INC(BD51:BD61,0.25) -> 49.9 | BE65: =_xlfn.PERCENTILE.INC(BE51:BE61,0.25) -> 56.5 | BF65: =_xlfn.PERCENTILE.INC(BF51:BF61,0.25) -> 73.325 | BH65: =_xlfn.PERCENTILE.INC(BH51:BH61,0.25) -> 0.11798096 | BJ65: =_xlfn.PERCENTILE.INC(BJ51:BJ61,0.25) -> 11.4675 | BK65: =_xlfn.PERCENTILE.INC(BK51:BK61,0.25) -> 12.8725 | BL65: =_xlfn.PERCENTILE.INC(BL51:BL61,0.25) -> 13.9075 | BN65: =_xlfn.PERCENTILE.INC(BN51:BN61,0.25) -> 0.19975054 | BP65: 25th | BQ65: =_xlfn.PERCENTILE.INC(BQ51:BQ61,0.25) -> 5.9123261 | BR65: =_xlfn.PERCENTILE.INC(BR51:BR61,0.25) -> 5.26 | BS65: =_xlfn.PERCENTILE.INC(BS51:BS61,0.25) -> 6.5 | BU65: =_xlfn.PERCENTILE.INC(BU51:BU61,0.25) -> 0.003902917 | BV65: =_xlfn.PERCENTILE.INC(BV51:BV61,0.25) -> -0.4925 | BX65: =_xlfn.PERCENTILE.INC(BX51:BX61,0.25) -> 0.91538102 | BY65: =_xlfn.PERCENTILE.INC(BY51:BY61,0.25) -> 9.3555556 | CA65: =_xlfn.PERCENTILE.INC(CA51:CA61,0.25) -> 13.2675 | CB65: =_xlfn.PERCENTILE.INC(CB51:CB61,0.25) -> 13.2575 | CC65: =_xlfn.PERCENTILE.INC(CC51:CC61,0.25) -> 10.585 | CE65: =_xlfn.PERCENTILE.INC(CE51:CE61,0.25) -> 0.19975054 | CG65: =_xlfn.PERCENTILE.INC(CG51:CG61,0.25) -> 0.012281746 | CH65: =_xlfn.PERCENTILE.INC(CH51:CH61,0.25) -> 0.0404 | CJ65: =_xlfn.PERCENTILE.INC(CJ51:CJ61,0.25) -> 7.1075 | CQ65: FY | CR65: Metric | CS65: FY2 Tier 3 ROIC | CT65: =AG65 -> 0.086925 | CU65: 0.1371 | CV65: =CU65-CT65 -> 0.050175 | CX65: LTM Tier 3
B66: 75th | G66: =_xlfn.PERCENTILE.INC(G51:G61,0.75) -> 1268.925 | H66: =_xlfn.PERCENTILE.INC(H51:H61,0.75) -> 1448.875 | J66: =_xlfn.PERCENTILE.INC(J51:J61,0.75) -> 1512.45 | K66: =_xlfn.PERCENTILE.INC(K51:K61,0.75) -> 514.6 | L66: =_xlfn.PERCENTILE.INC(L51:L61,0.75) -> 235.675 | M66: =_xlfn.PERCENTILE.INC(M51:M61,0.75) -> 80.325 | O66: =_xlfn.PERCENTILE.INC(O51:O61,0.75) -> 0.34019726 | P66: =_xlfn.PERCENTILE.INC(P51:P61,0.75) -> 0.2164434 | Q66: =_xlfn.PERCENTILE.INC(Q51:Q61,0.75) -> 0.14579059 | R66: =_xlfn.PERCENTILE.INC(R51:R61,0.75) -> 0.097138615 | T66: =_xlfn.PERCENTILE.INC(T51:T61,0.75) -> 1550.45 | U66: =_xlfn.PERCENTILE.INC(U51:U61,0.75) -> 1636.9 | V66: =_xlfn.PERCENTILE.INC(V51:V61,0.75) -> 237.675 | W66: =_xlfn.PERCENTILE.INC(W51:W61,0.75) -> 245.675 | Y66: =_xlfn.PERCENTILE.INC(Y51:Y61,0.75) -> 2226.3575 | Z66: =_xlfn.PERCENTILE.INC(Z51:Z61,0.75) -> 2322.9225 | AA66: =_xlfn.PERCENTILE.INC(AA51:AA61,0.75) -> 2530.5575 | AB66: =_xlfn.PERCENTILE.INC(AB51:AB61,0.75) -> 2840.2475 | AC66: =_xlfn.PERCENTILE.INC(AC51:AC61,0.75) -> #NUM! | AG66: =_xlfn.PERCENTILE.INC(AG51:AG61,0.75) -> 0.137075 | AH66: =_xlfn.PERCENTILE.INC(AH51:AH61,0.75) -> 0.29865 | AI66: =_xlfn.PERCENTILE.INC(AI51:AI61,0.75) -> 0.08985 | AL66: =_xlfn.PERCENTILE.INC(AL51:AL61,0.75) -> 0.327675 | AM66: =_xlfn.PERCENTILE.INC(AM51:AM61,0.75) -> 3.07 | AN66: =_xlfn.PERCENTILE.INC(AN51:AN61,0.75) -> 1.455 | AO66: =_xlfn.PERCENTILE.INC(AO51:AO61,0.75) -> 51.4225 | AQ66: =_xlfn.PERCENTILE.INC(AQ51:AQ61,0.75) -> 40.7275 | AV66: =_xlfn.PERCENTILE.INC(AV51:AV61,0.75) -> 1512.45 | AW66: =_xlfn.PERCENTILE.INC(AW51:AW61,0.75) -> 1636.9 | AX66: =_xlfn.PERCENTILE.INC(AX51:AX61,0.75) -> 1620.775 | AZ66: =_xlfn.PERCENTILE.INC(AZ51:AZ61,0.75) -> 235.675 | BA66: =_xlfn.PERCENTILE.INC(BA51:BA61,0.75) -> 1636.9 | BB66: =_xlfn.PERCENTILE.INC(BB51:BB61,0.75) -> 336.125 | BD66: =_xlfn.PERCENTILE.INC(BD51:BD61,0.75) -> 208.3 | BE66: =_xlfn.PERCENTILE.INC(BE51:BE61,0.75) -> 215.8 | BF66: =_xlfn.PERCENTILE.INC(BF51:BF61,0.75) -> 285.4 | BH66: =_xlfn.PERCENTILE.INC(BH51:BH61,0.75) -> 0.2164434 | BJ66: =_xlfn.PERCENTILE.INC(BJ51:BJ61,0.75) -> 2226.3575 | BK66: =_xlfn.PERCENTILE.INC(BK51:BK61,0.75) -> 2530.5575 | BL66: =_xlfn.PERCENTILE.INC(BL51:BL61,0.75) -> 2840.2475 | BN66: =_xlfn.PERCENTILE.INC(BN51:BN61,0.75) -> 0.44058653 | BP66: 75th | BQ66: =_xlfn.PERCENTILE.INC(BQ51:BQ61,0.75) -> 10.264418 | BR66: =_xlfn.PERCENTILE.INC(BR51:BR61,0.75) -> 10.08 | BS66: =_xlfn.PERCENTILE.INC(BS51:BS61,0.75) -> 10.6 | BU66: =_xlfn.PERCENTILE.INC(BU51:BU61,0.75) -> 0.01128417 | BV66: =_xlfn.PERCENTILE.INC(BV51:BV61,0.75) -> 1.455 | BX66: =_xlfn.PERCENTILE.INC(BX51:BX61,0.75) -> 1.8896674 | BY66: =_xlfn.PERCENTILE.INC(BY51:BY61,0.75) -> 12.975916 | CA66: =_xlfn.PERCENTILE.INC(CA51:CA61,0.75) -> 15.09 | CB66: =_xlfn.PERCENTILE.INC(CB51:CB61,0.75) -> 14.57 | CC66: =_xlfn.PERCENTILE.INC(CC51:CC61,0.75) -> 13.17 | CE66: =_xlfn.PERCENTILE.INC(CE51:CE61,0.75) -> 0.44058653 | CG66: =_xlfn.PERCENTILE.INC(CG51:CG61,0.75) -> 0.70716927 | CH66: =_xlfn.PERCENTILE.INC(CH51:CH61,0.75) -> 0.0579 | CJ66: =_xlfn.PERCENTILE.INC(CJ51:CJ61,0.75) -> 9.4575 | CS66: FY 2 Tier 3 ROE | CT66: =AH65 -> 0.120675 | CU66: 0.2987 | CV66: =CU66-CT66 -> 0.178025 | CX66: FY 1 Tier 3 | DF66: Median | DG66: 75th
CQ67: LTM 2 | CR67: =CR53 -> #REF! | CS67: FY2 Tier 3 ROA | CT67: =AI65 -> 0.048275 | CU67: =AI66 -> 0.08985 | CV67: =CU67-CT67 -> 0.041575 | CX67: FY3 Tier 3 | DF67: =DB67*FJ11 -> 0 | DG67: =DB67*FJ13 -> 0
CQ68: 2026E 2 | CR68: =CR54 -> #REF! | DF68: =DB68*FK11 -> 0 | DG68: =DB68*FK13 -> 0
B69: Overall | CQ69: 2027E 2 | CR69: =CR55 -> #REF! | DF69: =DB69*FL11 -> 0 | DG69: =DB69*FL13 -> 0
B71: Mean | G71: SKIP THIS NOT NEEDED TOO OVERKILL
B72: Median | BQ72: =MEDIAN(BQ64,BQ45,BQ24) -> 8.777439
B73: 25th
B74: 75th
B76: High
B77: Low
B78: 25th
B79: 75th
H84: EV/EBITDA | R84: PE
H85: FY | I85: Metric | J85: Range | L85: Implied EV | R85: FY | T85: EPS Range | V85: Implied Price | CS85: EV/EBIT
L86: 25th | M86: Median | N86: 75th | V86: 25th | W86: Median | X86: 75th | CS86: FY | CU86: 25th | CV86: Diff | CW86: 75th
H87: LTM | I87: =L5 -> 89.5 | J87: 9.18x-13.61x | L87: =I87*BQ25 -> 821.34832 | M87: =I87*BQ24 -> 1051.2793 | N87: =I87*BQ26 -> 1217.8195 | R87: LTM | S87: =Y5 -> 174.92 | T87: 23.46x-40.0x | V87: =S87*CA25 -> 4102.7486 | W87: =S87*CA24 -> 4165.7198 | X87: =S87*CA26 -> 6996.8 | Y87: =MEDIAN(V87:X87) -> 4165.7198 | Z87: =AVERAGE(V87:X87) -> 5088.4228 | CS87: LTM Tier 1 | CU87: =BY25 -> 16.33418 | CV87: =CW87-CU87 -> 7.7455849 | CW87: =BY26 -> 24.079765
H88: 2026E | I88: =W5 -> 100.5 | J88: 8.56x-13.15x | L88: =BQ25*I88 -> 922.29615 | M88: =BR24*I88 -> 1110.525 | N88: =BR26*I88 -> 1321.575 | R88: 2026E | S88: =AA5 -> 159.76 | T88: 21.51x-27.94x | V88: =S88*CB25 -> 3436.0382 | W88: =S88*CB24 -> 3613.7712 | X88: =S88*CB26 -> 4463.6944 | Y88: =MEDIAN(V88:X88) -> 3613.7712 | Z88: =AVERAGE(V88:X88) -> 3837.8346 | CS88: LTM Tier 2 | CU88: =BY46 -> 0.69941733 | CV88: =CW88-CU88 -> 0.69430678 | CW88: =BY47 -> 1.3937241
H89: 2027E | I89: =BB5 -> 110.3 | J89: 8.00x - 12.00x | L89: =I89*BS25 -> 882.12425 | M89: =I89*BS24 -> 1078.1825 | N89: =I89*BS26 -> 1323.8758 | R89: 2027E | S89: =AB5 -> 177.71 | T89: 19.42x-25.05x | V89: =S89*CC25 -> 3451.1282 | W89: =S89*CC24 -> 3826.9849 | X89: =S89*CC26 -> 4452.0798 | Y89: =MEDIAN(V89:X89) -> 3826.9849 | Z89: =AVERAGE(V89:X89) -> 3910.0643 | CS89: LTM Tier 3 | CU89: =BY65 -> 9.3555556 | CV89: =CW89-CU89 -> 3.6203609 | CW89: =BY66 -> 12.975916
CO90: EV/EBITDA | CY90: PE
CO91: FY | CP91: Metric | CQ91: Range | CY91: FY | CZ91: EPS | DA91: Range | DC91: Implied Price
CT92: Median | CU92: 75th | DC92: 25th | DD92: Median | DE92: 75th
CO93: LTM | CP93: =CS11 -> 0 | CQ93: 9.18x-13.61x | CT93: =CP93*EX30 -> 0 | CU93: =CP93*EX32 -> 0 | CY93: LTM | CZ93: =DF11 -> 0 | DA93: 23.46x-40.0x | DC93: =CZ93*FH31 -> 0 | DD93: =CZ93*FH30 -> 0 | DE93: =CZ93*FH32 -> 0
CO94: 2026E | CP94: =DD11 -> 0 | CQ94: 8.56x-13.15x | CT94: =EY30*CP94 -> 0 | CU94: =EY32*CP94 -> 0 | CY94: 2026E | CZ94: =DH11 -> 0 | DA94: 21.51x-27.94x | DC94: =CZ94*FI31 -> 0 | DD94: =CZ94*FI30 -> 0 | DE94: =CZ94*FI32 -> 0
CO95: 2027E | CP95: =EI11 -> 0 | CQ95: 8.00x - 12.00x | CT95: =CP95*EZ30 -> 0 | CU95: =CP95*EZ32 -> 0 | CY95: 2027E | CZ95: =DI11 -> 0 | DA95: 19.42x-25.05x | DC95: =CZ95*FJ31 -> 0 | DD95: =CZ95*FJ30 -> 0 | DE95: =CZ95*FJ32 -> 0
H98: EV/EBITDA - Tier 2 | R98: PE - Tier 2
H99: FY | I99: Metric | J99: Range | L99: Implied EV | R99: FY | S99: Metric | T99: Range | V99: Implied Price
L100: 25th | M100: Median | N100: 75th | V100: 25th | W100: Median | X100: 75th
H101: LTM 2 | I101: =I87 -> 89.5 | J101: 8.53x-11.13x | L101: =I101*BQ46 -> 724.02666 | M101: =I101*BQ45 -> 785.58079 | N101: =I101*BQ47 -> 967.87474 | R101: LTM 2 | S101: =S87 -> 174.92 | T101: 18.87x-22.29x | V101: =S101*CA46 -> 3182.6694 | W101: =S101*CA45 -> 3633.0884 | X101: =S101*CA47 -> 3841.2432 | Z101: =AVERAGE(V101:X101) -> 3552.3337
H102: 2026E 2 | I102: =I88 -> 100.5 | J102: 8.10x-12.01x | L102: =I102*BR46 -> 794.955 | M102: =I102*BR45 -> 877.365 | N102: =I102*BR47 -> 1037.6625 | R102: 2026E 2 | S102: =S88 -> 159.76 | T102: 17.46x-18.77x | V102: =S102*CB46 -> 2771.836 | W102: =S102*CB45 -> 2795.8 | X102: =S102*CB47 -> 2997.0976 | Z102: =AVERAGE(V102:X102) -> 2854.9112
H103: 2027E 2 | I103: =I89 -> 110.3 | J103: 7.78x-9.78x | L103: =I103*BS46 -> 830.0075 | M103: =I103*BS45 -> 935.344 | N103: =I103*BS47 -> 1067.1525 | R103: 2027E 2 | S103: =S89 -> 177.71 | T103: 16.24x-17.64x | V103: =S103*CC46 -> 2735.8455 | W103: =S103*CC45 -> 2887.7875 | X103: =S103*CC47 -> 3118.8105 | Z103: =AVERAGE(V103:X103) -> 2914.1478
CO104: EV/EBITDA - Tier 2 | CY104: PE - Tier 2
CO105: FY | CP105: Metric | CQ105: Range | CS105: Implied EV | CY105: FY | CZ105: Metric | DA105: Range | DC105: Implied Price
CS106: 25th | CT106: Median | CU106: 75th | DC106: 25th | DD106: Median | DE106: 75th
CO107: LTM 2 | CP107: =CP93 -> 0 | CQ107: 8.53x-11.13x | CS107: =CP107*EX52 -> 0 | CT107: =CP107*EX51 -> 0 | CU107: =CP107*EX53 -> 0 | CY107: LTM 2 | CZ107: =CZ93 -> 0 | DA107: 18.87x-22.29x | DC107: =CZ107*FH52 -> 0 | DD107: =CZ107*FH51 -> 0 | DE107: =CZ107*FH53 -> 0
CO108: 2026E 2 | CP108: =CP94 -> 0 | CQ108: 8.10x-12.01x | CS108: =CP108*EY52 -> 0 | CT108: =CP108*EY51 -> 0 | CU108: =CP108*EY53 -> 0 | CY108: 2026E 2 | CZ108: =CZ94 -> 0 | DA108: 17.46x-18.77x | DC108: =CZ108*FI52 -> 0 | DD108: =CZ108*FI51 -> 0 | DE108: =CZ108*FI53 -> 0
CO109: 2027E 2 | CP109: =CP95 -> 0 | CQ109: 7.78x-9.78x | CS109: =CP109*EZ52 -> 0 | CT109: =CP109*EZ51 -> 0 | CU109: =CP109*EZ53 -> 0 | CY109: 2027E 2 | CZ109: =CZ95 -> 0 | DA109: 16.24x-17.64x | DC109: =CZ109*FJ52 -> 0 | DD109: =CZ109*FJ51 -> 0 | DE109: =CZ109*FJ53 -> 0
H112: Football field chart
I113: 25th | J113: Diff | K113: 75th | R113: LTM | S113: 4102.7486 | T113: =U113-S113 -> 2894.0514 | U113: 6996.8
H114: LTM | I114: 821.34832 | J114: =K114-I114 -> 396.47121 | K114: 1217.8195 | R114: 2026E | S114: 3436.0382 | T114: =U114-S114 -> 1027.6562 | U114: 4463.6944
H115: 2026E | I115: 922.29615 | J115: =K115-I115 -> 399.27885 | K115: 1321.575 | R115: 2027E | S115: 3451.1282 | T115: =U115-S115 -> 1000.9516 | U115: 4452.0798
H116: 2027E | I116: 882.12425 | J116: =K116-I116 -> 441.7515 | K116: 1323.8758 | R116: LTM Tier 2 | S116: 3299.8658 | T116: =U116-S116 -> 599.101 | U116: 3898.9668
H117: LTM 2 | I117: 763.02517 | J117: =K117-I117 -> 232.78444 | K117: 995.80961 | R117: 2026E Tier2 | S117: 2788.6108 | T117: =U117-S117 -> 210.0844 | U117: 2998.6952
H118: 2026E 2 | I118: 814.05 | J118: =K118-I118 -> 240.94875 | K118: 1054.9987 | R118: 2027E Tier 2 | S118: 2885.1218 | T118: =U118-S118 -> 248.794 | U118: 3133.9158
H119: 2027E 2 | I119: 857.5825 | J119: =K119-I119 -> 221.42725 | K119: 1079.0097

Sheet RTAGlobal
AA8: 43082119275279
